Workbook

Sheet Reporte
A2: ProjectName | B2: UT - ENTERRITORIO 2027 | E2: ProjectName | F2: UT - ENTERRITORIO 2027
J3: CPI (Cost Performance Index) | K3: SPI (Schedule Performance Index)
A4: Etiquetas de fila | B4: Promedio de SPI (Schedule Performance Index) | C4: Suma de Meta SPI | E4: Etiquetas de fila | F4: Promedio de CPI (Cost Performance Index) | G4: Suma de Meta CPI | J4: CPI = EV / AC | K4: SPI = EV / PV
A5: 2024 | B5: 1.2421744 | C5: 8 | E5: 2025 | F5: 15.886921 | G5: 12 | J5: CPI = 1,00 → gasto exacto según lo presupuestado | K5: SPI = 1,00 → a tiempo
A6: Mayo | B6: 2.5 | C6: 1 | E6: Enero | F6: 9.662221 | G6: 1 | J6: CPI > 1,00 → eficiente (gastas menos de lo esperado) | K6: SPI > 1,00 → adelantado
A7: Proyecto adelantado respecto al cronograma | B7: 2.5 | C7: 1 | E7: Costo eficiente: se está gastando menos de lo presupuestado | F7: 9.662221 | G7: 1 | J7: CPI < 1,00 → ineficiente (gastas más de lo esperado) | K7: SPI < 1,00 → atrasado
A8: Junio | B8: 1.4 | C8: 1 | E8: Febrero | F8: 10.777093 | G8: 1
A9: Proyecto adelantado respecto al cronograma | B9: 1.4 | C9: 1 | E9: Costo eficiente: se está gastando menos de lo presupuestado | F9: 10.777093 | G9: 1
A10: Julio | B10: 1 | C10: 1 | E10: Marzo | F10: 11.891964 | G10: 1
A11: Proyecto a tiempo según lo planificado | B11: 1 | C11: 1 | E11: Costo eficiente: se está gastando menos de lo presupuestado | F11: 11.891964 | G11: 1
A12: Agosto | B12: 1 | C12: 1 | E12: Abril | F12: 13.006836 | G12: 1
A13: Proyecto a tiempo según lo planificado | B13: 1 | C13: 1 | E13: Costo eficiente: se está gastando menos de lo presupuestado | F13: 13.006836 | G13: 1
A14: Septiembre | B14: 0.92857143 | C14: 1 | E14: Mayo | F14: 14.121708 | G14: 1
A15: Proyecto atrasado con respecto al cronograma | B15: 0.92857143 | C15: 1 | E15: Costo eficiente: se está gastando menos de lo presupuestado | F15: 14.121708 | G15: 1
A16: Octubre | B16: 1.0588235 | C16: 1 | E16: Junio | F16: 15.608203 | G16: 1
A17: Proyecto adelantado respecto al cronograma | B17: 1.0588235 | C17: 1 | E17: Costo eficiente: se está gastando menos de lo presupuestado | F17: 15.608203 | G17: 1
A18: Noviembre | B18: 1.05 | C18: 1 | E18: Julio | F18: 16.723075 | G18: 1
A19: Proyecto adelantado respecto al cronograma | B19: 1.05 | C19: 1 | E19: Costo eficiente: se está gastando menos de lo presupuestado | F19: 16.723075 | G19: 1
... A21: Proyecto a tiempo según lo planificado | B21: 1 | C21: 1 | E21: Costo eficiente: se está gastando menos de lo presupuestado | F21: 17.837946 | G21: 1
A22: 2025 | B22: 1.0056995 | C22: 12 | E22: Septiembre | F22: 18.581194 | G22: 1
A23: Enero | B23: 1 | C23: 1 | E23: Costo eficiente: se está gastando menos de lo presupuestado | F23: 18.581194 | G23: 1
A24: Proyecto a tiempo según lo planificado | B24: 1 | C24: 1 | E24: Octubre | F24: 19.696066 | G24: 1
A25: Febrero | B25: 1 | C25: 1 | E25: Costo eficiente: se está gastando menos de lo presupuestado | F25: 19.696066 | G25: 1
A26: Proyecto a tiempo según lo planificado | B26: 1 | C26: 1 | E26: Noviembre | F26: 20.810938 | G26: 1
A27: Marzo | B27: 1 | C27: 1 | E27: Costo eficiente: se está gastando menos de lo presupuestado | F27: 20.810938 | G27: 1
A28: Proyecto a tiempo según lo planificado | B28: 1 | C28: 1 | E28: Diciembre | F28: 21.925809 | G28: 1
A29: Abril | B29: 1 | C29: 1 | E29: Costo eficiente: se está gastando menos de lo presupuestado | F29: 21.925809 | G29: 1
A30: Proyecto a tiempo según lo planificado | B30: 1 | C30: 1 | E30: Total general | F30: 15.886921 | G30: 12
A31: Mayo | B31: 1 | C31: 1
A32: Proyecto a tiempo según lo planificado | B32: 1 | C32: 1
A33: Junio | B33: 1.0243902 | C33: 1
A34: Proyecto adelantado respecto al cronograma | B34: 1.0243902 | C34: 1
A35: Julio | B35: 1.0227273 | C35: 1
A36: Proyecto adelantado respecto al cronograma | B36: 1.0227273 | C36: 1
A37: Agosto | B37: 1.0212766 | C37: 1
A38: Proyecto adelantado respecto al cronograma | B38: 1.0212766 | C38: 1
A39: Septiembre | B39: 1 | C39: 1
A40: Proyecto a tiempo según lo planificado | B40: 1 | C40: 1
A41: Octubre | B41: 1 | C41: 1
A42: Proyecto a tiempo según lo planificado | B42: 1 | C42: 1
... A46: Proyecto atrasado con respecto al cronograma | B46: 1 | C46: 1
A47: 2026 | B47: 0.16788668 | C47: 12
A48: Enero | B48: 0.98387097 | C48: 1
A49: Proyecto atrasado con respecto al cronograma | B49: 0.98387097 | C49: 1
A50: Febrero | B50: 1.0307692 | C50: 1
A51: Proyecto adelantado respecto al cronograma | B51: 1.0307692 | C51: 1
A52: Marzo | B52: 0 | C52: 1
A53: Sin Línea Base | B53: 0 | C53: 1
A54: Abril | B54: 0 | C54: 1
A55: Sin Línea Base | B55: 0 | C55: 1
A56: Mayo | B56: 0 | C56: 1
A57: Sin Línea Base | B57: 0 | C57: 1
A58: Junio | B58: 0 | C58: 1
A59: Sin Línea Base | B59: 0 | C59: 1
A60: Julio | B60: 0 | C60: 1 | F60: 80
A61: Sin Línea Base | B61: 0 | C61: 1 | F61: 64
A62: Agosto | B62: 0 | C62: 1 | F62: =F61/F60 -> 0.8
A63: Sin Línea Base | B63: 0 | C63: 1
A64: Septiembre | B64: 0 | C64: 1
A65: Sin Línea Base | B65: 0 | C65: 1
A66: Octubre | B66: 0 | C66: 1
A67: Sin Línea Base | B67: 0 | C67: 1
A68: Noviembre | B68: 0 | C68: 1
A69: Sin Línea Base | B69: 0 | C69: 1
A70: Diciembre | B70: 0 | C70: 1
A71: Sin Línea Base | B71: 0 | C71: 1
A72: 2027 | B72: 0 | C72: 5
A73: Enero | B73: 0 | C73: 1
A74: Sin Línea Base | B74: 0 | C74: 1
A75: Febrero | B75: 0 | C75: 1
A76: Sin Línea Base | B76: 0 | C76: 1
A77: Marzo | B77: 0 | C77: 1
A78: Sin Línea Base | B78: 0 | C78: 1
A79: Abril | B79: 0 | C79: 1
A80: Sin Línea Base | B80: 0 | C80: 1
A81: Mayo | B81: 0 | C81: 1
A82: Sin Línea Base | B82: 0 | C82: 1
A83: Total general | B83: 0.64920079 | C83: 37

Sheet Resumen
A3: Etiquetas de fila | B3: Promedio de SPI (Schedule Performance Index) | C3: Cuenta de CPI (Cost Performance Index)
A4: FONDO ACCION - MEJORAS APLICATIVO ASEC | B4: 1.1333333 | C4: 3
A5: UT CIBERSEGURIDAD MT | B5: 1.0951082 | C5: 15
A6: EMTEL - ICFES - FABRICA | B6: 1.0623689 | C6: 8
A7: ERT- MT– DISPOSITIVOS IOT Y ANALÍTICA | B7: 1.0359642 | C7: 8
A8: SNR- MIGRACION FOLIO A SIR | B8: 1.0357843 | C8: 7
A9: EXPERTIX - DEFENSORIA – RENOVACIÓN MEGA | B9: 1 | C9: 2
A10: TELEFONICA - RNEC-ELECCIONES 2026 | B10: 1 | C10: 11
A11: CCD-INM-AE-2025 | B11: 1 | C11: 4
A12: FNA -DATAFABRIC | B12: 1 | C12: 12
A13: COMREDES - URT - SOLUCIÓN HCI FASE II | B13: 1 | C13: 1
A14: SNR-MIGRACION FOLIO A SIR-BID | B14: 1 | C14: 2
A15: DIAN-BORRADO SEGURO BLANCCO | B15: 1 | C15: 2
... A85: Total general | B85: 0.41543848 | C85: 914

Sheet Indicador
A1: Año | B1: Mes | C1: ProjectId | D1: ProjectCreatedDate | E1: ProjectName | F1: ProjectOwnerName | G1: ProjectWorkspaceInternalUrl | H1: Objetocontractual | I1: Portafolio | J1: CentrodeCostosProyecto | K1: Estado | L1: Presupuesto | M1: Inicio | N1: Fin | O1: Meses | P1: Tiempo Diferencia | Q1: Tiempo Ejecución | R1: Tiempo Proyectado | S1: % Planeado | T1: Completado Real | U1: AC (Actual Cost) | V1: Costo Mensual | W1: EV (Earned Value) | X1: PV (Planned Value) | Y1: CV (Cost Variance) | Z1: SV (Schedule Variance) | AA1: CPI (Cost Performance Index) | AB1: Detalle de CPI | AC1: SPI (Schedule Performance Index) | AD1: Detalle SPI | AE1: EAC (Estimación al finalizar) | AF1: VAC (Exceso de presupuesto proyectado) | AG1: Ruta | AH1: Meta SPI | AI1: Meta CPI
A2: 2024 | B2: Enero | C2: 72cbf93a-8da6-ef11-bd95-00155d10dc02 | D2: 45615.656 | E2: ERT-URT-HIPERCORVENGENCIA | F2: Carlos Alberto Osorio Ortiz | G2: https://growdatasas.sharepoint.com/sites/pwa/ERT-URT-HIPERCORVENGENCIA | H2: ​Suministro de una solución de Hiperconvergencia para la unidad de restitución de tierras | I2: TI | J2: 0349 | K2: Activo.En Cierre | L2: =VLOOKUP(E2,Diccionario!C$2:AC$150,22,0) -> 314881564 | M2: =VLOOKUP(E2,Diccionario!C$2:AC$150,24,0) -> 45292 | N2: =VLOOKUP(E2,Diccionario!C$2:AC$150,25,0) -> 45321 | O2: =VLOOKUP(E2,Diccionario!C$2:AC$150,26,0) -> 0.97 | P2: =O2-Q2 -> -0.03 | Q2: 1 | R2: 1 | S2: 1 | T2: 1 | U2: 314881564 | V2: 314881564 | W2: =IFERROR(T2*L2,0) -> 314881564 | X2: =S2*L2 -> 314881564 | Y2: =IFERROR(W2-U2,0) -> 0 | Z2: =W2-X2 -> 0 | AA2: =IFERROR(W2/U2,"No se realizó gasto en este corte") -> 1 | AB2: =IFERROR( IF(OR(AA2="",AA2=0), "No calculado", IF(AA2>1,"Costo eficiente: se está gastando menos de lo presupuestado", IF(AA2=1,"Costo según lo presupuestado", "Costo ineficiente: se está gastando más de lo presupuestado"))), "No calculado") -> Costo según lo presupuestado | AC2: =IFERROR(W2/X2,0) -> 1 | AD2: =IF(OR(AC2="",AC2=0),"Sin Línea Base", IF(AC2>1,"Proyecto adelantado respecto al cronograma", IF(AC2=1,"Proyecto a tiempo según lo planificado", IF(AC2<1,"Proyecto atrasado con respecto al cronograma", "No calculado")))) -> Proyecto a tiempo según lo planificado | AE2: =IFERROR(L2/AA2,0) -> 314881564 | AF2: =IFERROR(AE2-L2,0) -> 0 | AG2: =VLOOKUP(Indicador!E2,Diccionario!C$1:AC$150,27,0) -> https://growdatasas.sharepoint.com/:x:/r/sites/Gestiondocumental/Administrativa/GD/Financiera/_layouts/15/Doc.aspx?sourcedoc=%7BEA2AC996-D46C-4123-8126-7F0BE9537AF4%7D&file=20241108%20MODELO%20FINANCIERO%20REFERENCIA%20V7.2%20APROBADO.xlsm&action=default&mobileredirect=true | AH2: 1 | AI2: 1
A3: 2024 | B3: Enero | C3: a514ea09-ced4-ee11-bd00-00155d682338 | D3: 45348.736 | E3: TELEFONICA - SENA MDA | F3: Carlos Fernando Gomez Rodriguez | G3: https://growdatasas.sharepoint.com/sites/pwa/TELEFONICA - SENA MDA | H3: ​Mesa de servicio para el SENA | I3: TI | J3: 0319 | K3: Cerrado | L3: =VLOOKUP(E3,Diccionario!C$2:AC$150,22,0) -> 13344287960 | M3: =VLOOKUP(E3,Diccionario!C$2:AC$150,24,0) -> 45292 | N3: =VLOOKUP(E3,Diccionario!C$2:AC$150,25,0) -> 45381 | O3: =VLOOKUP(E3,Diccionario!C$2:AC$150,26,0) -> 2.97 | P3: =Q3-O3 -> -1.97 | Q3: 1 | R3: 3 | S3: 0.3 | T3: 0.25 | U3: 1589891803 | V3: 1589891803 | W3: =IFERROR(T3*L3,0) -> 3336071990 | X3: =S3*L3 -> 4003286388 | Y3: =IFERROR(W3-U3,0) -> 1746180187 | Z3: =W3-X3 -> -667214398 | AA3: =IFERROR(W3/U3,"No se realizó gasto en este corte") -> 2.0983013 | AB3: =IFERROR( IF(OR(AA3="",AA3=0), "No calculado", IF(AA3>1,"Costo eficiente: se está gastando menos de lo presupuestado", IF(AA3=1,"Costo según lo presupuestado", "Costo ineficiente: se está gastando más de lo presupuestado"))), "No calculado") -> Costo eficiente: se está gastando menos de lo presupuestado | AC3: =IFERROR(W3/X3,0) -> 0.83333333 | AD3: =IF(OR(AC3="",AC3=0),"Sin Línea Base", IF(AC3>1,"Proyecto adelantado respecto al cronograma", IF(AC3=1,"Proyecto a tiempo según lo planificado", IF(AC3<1,"Proyecto atrasado con respecto al cronograma", "No calculado")))) -> Proyecto atrasado con respecto al cronograma | AE3: =IFERROR(L3/AA3,0) -> 6359567212 | AF3: =IFERROR(AE3-L3,0) -> -6984720748 | AG3: =VLOOKUP(Indicador!E3,Diccionario!C$1:AC$150,27,0) -> https://growdatasas.sharepoint.com/:x:/r/sites/Gestiondocumental/Administrativa/GD/Financiera/_layouts/15/Doc.aspx?sourcedoc=%7B06FB1484-E2DE-40DA-83E0-D97F6AF0AE9B%7D&file=MODELO%20FINANCIERO%20REFERENCIA%20V7%20MS%2020240130.xlsx&action=default&mobileredirect=true | AH3: 1 | AI3: 1
A4: 2024 | B4: Febrero | C4: a514ea09-ced4-ee11-bd00-00155d682338 | D4: 45348.736 | E4: TELEFONICA - SENA MDA | F4: Carlos Fernando Gomez Rodriguez | G4: https://growdatasas.sharepoint.com/sites/pwa/TELEFONICA - SENA MDA | H4: ​Mesa de servicio para el SENA | I4: TI | J4: 0319 | K4: Cerrado | L4: =VLOOKUP(E4,Diccionario!C$2:AC$150,22,0) -> 13344287960 | M4: =VLOOKUP(E4,Diccionario!C$2:AC$150,24,0) -> 45292 | N4: =VLOOKUP(E4,Diccionario!C$2:AC$150,25,0) -> 45381 | O4: =VLOOKUP(E4,Diccionario!C$2:AC$150,26,0) -> 2.97 | P4: =Q4-O4 -> -0.97 | Q4: 2 | R4: 3 | S4: 0.7 | T4: 0.65 | U4: =U3+TablaIndicador[[#This Row],[Costo Mensual]] -> 3913702428 | V4: 2323810625 | W4: =IFERROR(T4*L4,0) -> 8673787174 | X4: =S4*L4 -> 9341001572 | Y4: =IFERROR(W4-U4,0) -> 4760084746 | Z4: =W4-X4 -> -667214398 | AA4: =IFERROR(W4/U4,"No se realizó gasto en este corte") -> 2.2162613 | AB4: =IFERROR( IF(OR(AA4="",AA4=0), "No calculado", IF(AA4>1,"Costo eficiente: se está gastando menos de lo presupuestado", IF(AA4=1,"Costo según lo presupuestado", "Costo ineficiente: se está gastando más de lo presupuestado"))), "No calculado") -> Costo eficiente: se está gastando menos de lo presupuestado | AC4: =IFERROR(W4/X4,0) -> 0.92857143 | AD4: =IF(OR(AC4="",AC4=0),"Sin Línea Base", IF(AC4>1,"Proyecto adelantado respecto al cronograma", IF(AC4=1,"Proyecto a tiempo según lo planificado", IF(AC4<1,"Proyecto atrasado con respecto al cronograma", "No calculado")))) -> Proyecto atrasado con respecto al cronograma | AE4: =IFERROR(L4/AA4,0) -> 6.0210807e+09 | AF4: =IFERROR(AE4-L4,0) -> -7.3232073e+09 | AG4: =VLOOKUP(Indicador!E4,Diccionario!C$1:AC$150,27,0) -> https://growdatasas.sharepoint.com/:x:/r/sites/Gestiondocumental/Administrativa/GD/Financiera/_layouts/15/Doc.aspx?sourcedoc=%7B06FB1484-E2DE-40DA-83E0-D97F6AF0AE9B%7D&file=MODELO%20FINANCIERO%20REFERENCIA%20V7%20MS%2020240130.xlsx&action=default&mobileredirect=true | AH4: 1 | AI4: 1
A5: 2024 | B5: Marzo | C5: a514ea09-ced4-ee11-bd00-00155d682338 | D5: 45348.736 | E5: TELEFONICA - SENA MDA | F5: Carlos Fernando Gomez Rodriguez | G5: https://growdatasas.sharepoint.com/sites/pwa/TELEFONICA - SENA MDA | H5: ​Mesa de servicio para el SENA | I5: TI | J5: 0319 | K5: Cerrado | L5: =VLOOKUP(E5,Diccionario!C$2:AC$150,22,0) -> 13344287960 | M5: =VLOOKUP(E5,Diccionario!C$2:AC$150,24,0) -> 45292 | N5: =VLOOKUP(E5,Diccionario!C$2:AC$150,25,0) -> 45381 | O5: =VLOOKUP(E5,Diccionario!C$2:AC$150,26,0) -> 2.97 | P5: =Q5-O5 -> 0.03 | Q5: 3 | R5: 3 | S5: 1 | T5: 1 | U5: =U4+TablaIndicador[[#This Row],[Costo Mensual]] -> 6237513053 | V5: 2323810625 | W5: =IFERROR(T5*L5,0) -> 13344287960 | X5: =S5*L5 -> 13344287960 | Y5: =IFERROR(W5-U5,0) -> 7106774907 | Z5: =W5-X5 -> 0 | AA5: =IFERROR(W5/U5,"No se realizó gasto en este corte") -> 2.1393603 | AB5: =IFERROR( IF(OR(AA5="",AA5=0), "No calculado", IF(AA5>1,"Costo eficiente: se está gastando menos de lo presupuestado", IF(AA5=1,"Costo según lo presupuestado", "Costo ineficiente: se está gastando más de lo presupuestado"))), "No calculado") -> Costo eficiente: se está gastando menos de lo presupuestado | AC5: =IFERROR(W5/X5,0) -> 1 | AD5: =IF(OR(AC5="",AC5=0),"Sin Línea Base", IF(AC5>1,"Proyecto adelantado respecto al cronograma", IF(AC5=1,"Proyecto a tiempo según lo planificado", IF(AC5<1,"Proyecto atrasado con respecto al cronograma", "No calculado")))) -> Proyecto a tiempo según lo planificado | AE5: =IFERROR(L5/AA5,0) -> 6237513053 | AF5: =IFERROR(AE5-L5,0) -> -7106774907 | AG5: =VLOOKUP(Indicador!E5,Diccionario!C$1:AC$150,27,0) -> https://growdatasas.sharepoint.com/:x:/r/sites/Gestiondocumental/Administrativa/GD/Financiera/_layouts/15/Doc.aspx?sourcedoc=%7B06FB1484-E2DE-40DA-83E0-D97F6AF0AE9B%7D&file=MODELO%20FINANCIERO%20REFERENCIA%20V7%20MS%2020240130.xlsx&action=default&mobileredirect=true | AH5: 1 | AI5: 1
A6: 2024 | B6: Enero | C6: b3dee2f4-49c1-ee11-add8-00155d10211a | D6: 45323.9 | E6: CORP COLOMBIA DIGITAL-FNA-AE | F6: Johan Sebastian Rodriguez Niño | G6: https://growdatasas.sharepoint.com/sites/pwa/CORP COLOMBIA DIGITAL-FNA-AE | H6: Consultoría para el diseño de la Transformación Digital de la entidad que designe la Corporación Colombia Digital, basado en desarrollar la arquitectura empresarial - AR, la definición e implementación del Gobierno y la gestión de datos, la definición de la hoja de ruta de la AR para el plan estratégico de TI PETI, la formación de personal y la planeación del proyecto de la entidad designada. | I6: CONSULTORÍA | J6: 0315 | K6: Activo.En Cierre | L6: =VLOOKUP(E6,Diccionario!C$2:AC$150,22,0) -> 1422409157 | M6: =VLOOKUP(E6,Diccionario!C$2:AC$150,24,0) -> 45292 | N6: =VLOOKUP(E6,Diccionario!C$2:AC$150,25,0) -> 45534 | O6: =VLOOKUP(E6,Diccionario!C$2:AC$150,26,0) -> 7.97 | P6: =Q6-O6 -> -6.97 | Q6: 1 | R6: 8 | S6: 0.1 | T6: 0.08 | U6: =TablaIndicador[[#This Row],[Costo Mensual]] -> 1.531156e+08 | V6: 1.531156e+08 | W6: =IFERROR(T6*L6,0) -> 1.1379273e+08 | X6: =S6*L6 -> 1.4224092e+08 | Y6: =IFERROR(W6-U6,0) -> -39322867 | Z6: =W6-X6 -> -28448183 | AA6: =IFERROR(W6/U6,"No se realizó gasto en este corte") -> 0.74318184 | AB6: =IFERROR( IF(OR(AA6="",AA6=0), "No calculado", IF(AA6>1,"Costo eficiente: se está gastando menos de lo presupuestado", IF(AA6=1,"Costo según lo presupuestado", "Costo ineficiente: se está gastando más de lo presupuestado"))), "No calculado") -> Costo ineficiente: se está gastando más de lo presupuestado | AC6: =IFERROR(W6/X6,0) -> 0.8 | AD6: =IF(OR(AC6="",AC6=0),"Sin Línea Base", IF(AC6>1,"Proyecto adelantado respecto al cronograma", IF(AC6=1,"Proyecto a tiempo según lo planificado", IF(AC6<1,"Proyecto atrasado con respecto al cronograma", "No calculado")))) -> Proyecto atrasado con respecto al cronograma | AE6: =IFERROR(L6/AA6,0) -> 1.913945e+09 | AF6: =IFERROR(AE6-L6,0) -> 4.9153584e+08 | AG6: =VLOOKUP(Indicador!E6,Diccionario!C$1:AC$150,27,0) -> https://growdatasas.sharepoint.com/:x:/r/sites/Gestiondocumental/Administrativa/GD/Financiera/_layouts/15/Doc.aspx?sourcedoc=%7B453B6AA8-B631-4722-B916-8323F8C43E87%7D&file=315%20CORP%20COLOMBIA%20DIGITAL%20FNA%20AE.xlsm&action=default&mobileredirect=true | AH6: 1 | AI6: 1
A7: 2024 | B7: Febrero | C7: b3dee2f4-49c1-ee11-add8-00155d10211a | D7: 45323.9 | E7: CORP COLOMBIA DIGITAL-FNA-AE | F7: Johan Sebastian Rodriguez Niño | G7: https://growdatasas.sharepoint.com/sites/pwa/CORP COLOMBIA DIGITAL-FNA-AE | H7: Consultoría para el diseño de la Transformación Digital de la entidad que designe la Corporación Colombia Digital, basado en desarrollar la arquitectura empresarial - AR, la definición e implementación del Gobierno y la gestión de datos, la definición de la hoja de ruta de la AR para el plan estratégico de TI PETI, la formación de personal y la planeación del proyecto de la entidad designada. | I7: CONSULTORÍA | J7: 0315 | K7: Activo.En Cierre | L7: =VLOOKUP(E7,Diccionario!C$2:AC$150,22,0) -> 1422409157 | M7: =VLOOKUP(E7,Diccionario!C$2:AC$150,24,0) -> 45292 | N7: =VLOOKUP(E7,Diccionario!C$2:AC$150,25,0) -> 45534 | O7: =VLOOKUP(E7,Diccionario!C$2:AC$150,26,0) -> 7.97 | P7: =Q7-O7 -> -5.97 | Q7: 2 | R7: 8 | S7: 0.2 | T7: 0.18 | U7: =U6+TablaIndicador[[#This Row],[Costo Mensual]] -> 4.0497338e+08 | V7: 2.5185778e+08 | W7: =IFERROR(T7*L7,0) -> 2.5603365e+08 | X7: =S7*L7 -> 2.8448183e+08 | Y7: =IFERROR(W7-U7,0) -> -1.4893973e+08 | Z7: =W7-X7 -> -28448183 | AA7: =IFERROR(W7/U7,"No se realizó gasto en este corte") -> 0.6322234 | AB7: =IFERROR( IF(OR(AA7="",AA7=0), "No calculado", IF(AA7>1,"Costo eficiente: se está gastando menos de lo presupuestado", IF(AA7=1,"Costo según lo presupuestado", "Costo ineficiente: se está gastando más de lo presupuestado"))), "No calculado") -> Costo ineficiente: se está gastando más de lo presupuestado | AC7: =IFERROR(W7/X7,0) -> 0.9 | AD7: =IF(OR(AC7="",AC7=0),"Sin Línea Base", IF(AC7>1,"Proyecto adelantado respecto al cronograma", IF(AC7=1,"Proyecto a tiempo según lo planificado", IF(AC7<1,"Proyecto atrasado con respecto al cronograma", "No calculado")))) -> Proyecto atrasado con respecto al cronograma | AE7: =IFERROR(L7/AA7,0) -> 2.2498521e+09 | AF7: =IFERROR(AE7-L7,0) -> 8.2744295e+08 | AG7: =VLOOKUP(Indicador!E7,Diccionario!C$1:AC$150,27,0) -> https://growdatasas.sharepoint.com/:x:/r/sites/Gestiondocumental/Administrativa/GD/Financiera/_layouts/15/Doc.aspx?sourcedoc=%7B453B6AA8-B631-4722-B916-8323F8C43E87%7D&file=315%20CORP%20COLOMBIA%20DIGITAL%20FNA%20AE.xlsm&action=default&mobileredirect=true | AH7: 1 | AI7: 1
A8: 2024 | B8: Marzo | C8: b3dee2f4-49c1-ee11-add8-00155d10211a | D8: 45323.9 | E8: CORP COLOMBIA DIGITAL-FNA-AE | F8: Johan Sebastian Rodriguez Niño | G8: https://growdatasas.sharepoint.com/sites/pwa/CORP COLOMBIA DIGITAL-FNA-AE | H8: Consultoría para el diseño de la Transformación Digital de la entidad que designe la Corporación Colombia Digital, basado en desarrollar la arquitectura empresarial - AR, la definición e implementación del Gobierno y la gestión de datos, la definición de la hoja de ruta de la AR para el plan estratégico de TI PETI, la formación de personal y la planeación del proyecto de la entidad designada. | I8: CONSULTORÍA | J8: 0315 | K8: Activo.En Cierre | L8: =VLOOKUP(E8,Diccionario!C$2:AC$150,22,0) -> 1422409157 | M8: =VLOOKUP(E8,Diccionario!C$2:AC$150,24,0) -> 45292 | N8: =VLOOKUP(E8,Diccionario!C$2:AC$150,25,0) -> 45534 | O8: =VLOOKUP(E8,Diccionario!C$2:AC$150,26,0) -> 7.97 | P8: =Q8-O8 -> -4.97 | Q8: 3 | R8: 8 | S8: 0.3 | T8: 0.32 | U8: =U7+TablaIndicador[[#This Row],[Costo Mensual]] -> 5.5808898e+08 | V8: 1.531156e+08 | W8: =IFERROR(T8*L8,0) -> 4.5517093e+08 | X8: =S8*L8 -> 4.2672275e+08 | Y8: =IFERROR(W8-U8,0) -> -1.0291805e+08 | Z8: =W8-X8 -> 28448183 | AA8: =IFERROR(W8/U8,"No se realizó gasto en este corte") -> 0.81558846 | AB8: =IFERROR( IF(OR(AA8="",AA8=0), "No calculado", IF(AA8>1,"Costo eficiente: se está gastando menos de lo presupuestado", IF(AA8=1,"Costo según lo presupuestado", "Costo ineficiente: se está gastando más de lo presupuestado"))), "No calculado") -> Costo ineficiente: se está gastando más de lo presupuestado | AC8: =IFERROR(W8/X8,0) -> 1.0666667 | AD8: =IF(OR(AC8="",AC8=0),"Sin Línea Base", IF(AC8>1,"Proyecto adelantado respecto al cronograma", IF(AC8=1,"Proyecto a tiempo según lo planificado", IF(AC8<1,"Proyecto atrasado con respecto al cronograma", "No calculado")))) -> Proyecto adelantado respecto al cronograma | AE8: =IFERROR(L8/AA8,0) -> 1.7440281e+09 | AF8: =IFERROR(AE8-L8,0) -> 3.216189e+08 | AG8: =VLOOKUP(Indicador!E8,Diccionario!C$1:AC$150,27,0) -> https://growdatasas.sharepoint.com/:x:/r/sites/Gestiondocumental/Administrativa/GD/Financiera/_layouts/15/Doc.aspx?sourcedoc=%7B453B6AA8-B631-4722-B916-8323F8C43E87%7D&file=315%20CORP%20COLOMBIA%20DIGITAL%20FNA%20AE.xlsm&action=default&mobileredirect=true | AH8: 1 | AI8: 1
A9: 2024 | B9: Abril | C9: b3dee2f4-49c1-ee11-add8-00155d10211a | D9: 45323.9 | E9: CORP COLOMBIA DIGITAL-FNA-AE | F9: Johan Sebastian Rodriguez Niño | G9: https://growdatasas.sharepoint.com/sites/pwa/CORP COLOMBIA DIGITAL-FNA-AE | H9: Consultoría para el diseño de la Transformación Digital de la entidad que designe la Corporación Colombia Digital, basado en desarrollar la arquitectura empresarial - AR, la definición e implementación del Gobierno y la gestión de datos, la definición de la hoja de ruta de la AR para el plan estratégico de TI PETI, la formación de personal y la planeación del proyecto de la entidad designada. | I9: CONSULTORÍA | J9: 0315 | K9: Activo.En Cierre | L9: =VLOOKUP(E9,Diccionario!C$2:AC$150,22,0) -> 1422409157 | M9: =VLOOKUP(E9,Diccionario!C$2:AC$150,24,0) -> 45292 | N9: =VLOOKUP(E9,Diccionario!C$2:AC$150,25,0) -> 45534 | O9: =VLOOKUP(E9,Diccionario!C$2:AC$150,26,0) -> 7.97 | P9: =Q9-O9 -> -3.97 | Q9: 4 | R9: 8 | S9: 0.5 | T9: 0.51 | U9: =U8+TablaIndicador[[#This Row],[Costo Mensual]] -> 7.1120458e+08 | V9: 1.531156e+08 | W9: =IFERROR(T9*L9,0) -> 7.2542867e+08 | X9: =S9*L9 -> 7.1120458e+08 | Y9: =IFERROR(W9-U9,0) -> 14224092 | Z9: =W9-X9 -> 14224092 | AA9: =IFERROR(W9/U9,"No se realizó gasto en este corte") -> 1.02 | AB9: =IFERROR( IF(OR(AA9="",AA9=0), "No calculado", IF(AA9>1,"Costo eficiente: se está gastando menos de lo presupuestado", IF(AA9=1,"Costo según lo presupuestado", "Costo ineficiente: se está gastando más de lo presupuestado"))), "No calculado") -> Costo eficiente: se está gastando menos de lo presupuestado | AC9: =IFERROR(W9/X9,0) -> 1.02 | AD9: =IF(OR(AC9="",AC9=0),"Sin Línea Base", IF(AC9>1,"Proyecto adelantado respecto al cronograma", IF(AC9=1,"Proyecto a tiempo según lo planificado", IF(AC9<1,"Proyecto atrasado con respecto al cronograma", "No calculado")))) -> Proyecto adelantado respecto al cronograma | AE9: =IFERROR(L9/AA9,0) -> 1.3945188e+09 | AF9: =IFERROR(AE9-L9,0) -> -27890376 | AG9: =VLOOKUP(Indicador!E9,Diccionario!C$1:AC$150,27,0) -> https://growdatasas.sharepoint.com/:x:/r/sites/Gestiondocumental/Administrativa/GD/Financiera/_layouts/15/Doc.aspx?sourcedoc=%7B453B6AA8-B631-4722-B916-8323F8C43E87%7D&file=315%20CORP%20COLOMBIA%20DIGITAL%20FNA%20AE.xlsm&action=default&mobileredirect=true | AH9: 1 | AI9: 1
A10: 2024 | B10: Mayo | C10: b3dee2f4-49c1-ee11-add8-00155d10211a | D10: 45323.9 | E10: CORP COLOMBIA DIGITAL-FNA-AE | F10: Johan Sebastian Rodriguez Niño | G10: https://growdatasas.sharepoint.com/sites/pwa/CORP COLOMBIA DIGITAL-FNA-AE | H10: Consultoría para el diseño de la Transformación Digital de la entidad que designe la Corporación Colombia Digital, basado en desarrollar la arquitectura empresarial - AR, la definición e implementación del Gobierno y la gestión de datos, la definición de la hoja de ruta de la AR para el plan estratégico de TI PETI, la formación de personal y la planeación del proyecto de la entidad designada. | I10: CONSULTORÍA | J10: 0315 | K10: Activo.En Cierre | L10: =VLOOKUP(E10,Diccionario!C$2:AC$150,22,0) -> 1422409157 | M10: =VLOOKUP(E10,Diccionario!C$2:AC$150,24,0) -> 45292 | N10: =VLOOKUP(E10,Diccionario!C$2:AC$150,25,0) -> 45534 | O10: =VLOOKUP(E10,Diccionario!C$2:AC$150,26,0) -> 7.97 | P10: =Q10-O10 -> -2.97 | Q10: 5 | R10: 8 | S10: 0.6 | T10: 0.6 | U10: =U9+TablaIndicador[[#This Row],[Costo Mensual]] -> 8.6432018e+08 | V10: 1.531156e+08 | W10: =IFERROR(T10*L10,0) -> 8.5344549e+08 | X10: =S10*L10 -> 8.5344549e+08 | Y10: =IFERROR(W10-U10,0) -> -10874684 | Z10: =W10-X10 -> 0 | AA10: =IFERROR(W10/U10,"No se realizó gasto en este corte") -> 0.98741822 | AB10: =IFERROR( IF(OR(AA10="",AA10=0), "No calculado", IF(AA10>1,"Costo eficiente: se está gastando menos de lo presupuestado", IF(AA10=1,"Costo según lo presupuestado", "Costo ineficiente: se está gastando más de lo presupuestado"))), "No calculado") -> Costo ineficiente: se está gastando más de lo presupuestado | AC10: =IFERROR(W10/X10,0) -> 1 | AD10: =IF(OR(AC10="",AC10=0),"Sin Línea Base", IF(AC10>1,"Proyecto adelantado respecto al cronograma", IF(AC10=1,"Proyecto a tiempo según lo planificado", IF(AC10<1,"Proyecto atrasado con respecto al cronograma", "No calculado")))) -> Proyecto a tiempo según lo planificado | AE10: =IFERROR(L10/AA10,0) -> 1.4405336e+09 | AF10: =IFERROR(AE10-L10,0) -> 18124473 | AG10: =VLOOKUP(Indicador!E10,Diccionario!C$1:AC$150,27,0) -> https://growdatasas.sharepoint.com/:x:/r/sites/Gestiondocumental/Administrativa/GD/Financiera/_layouts/15/Doc.aspx?sourcedoc=%7B453B6AA8-B631-4722-B916-8323F8C43E87%7D&file=315%20CORP%20COLOMBIA%20DIGITAL%20FNA%20AE.xlsm&action=default&mobileredirect=true | AH10: 1 | AI10: 1
A11: 2024 | B11: Junio | C11: b3dee2f4-49c1-ee11-add8-00155d10211a | D11: 45323.9 | E11: CORP COLOMBIA DIGITAL-FNA-AE | F11: Johan Sebastian Rodriguez Niño | G11: https://growdatasas.sharepoint.com/sites/pwa/CORP COLOMBIA DIGITAL-FNA-AE | H11: Consultoría para el diseño de la Transformación Digital de la entidad que designe la Corporación Colombia Digital, basado en desarrollar la arquitectura empresarial - AR, la definición e implementación del Gobierno y la gestión de datos, la definición de la hoja de ruta de la AR para el plan estratégico de TI PETI, la formación de personal y la planeación del proyecto de la entidad designada. | I11: CONSULTORÍA | J11: 0315 | K11: Activo.En Cierre | L11: =VLOOKUP(E11,Diccionario!C$2:AC$150,22,0) -> 1422409157 | M11: =VLOOKUP(E11,Diccionario!C$2:AC$150,24,0) -> 45292 | N11: =VLOOKUP(E11,Diccionario!C$2:AC$150,25,0) -> 45534 | O11: =VLOOKUP(E11,Diccionario!C$2:AC$150,26,0) -> 7.97 | P11: =Q11-O11 -> -1.97 | Q11: 6 | R11: 8 | S11: 0.75 | T11: 0.73 | U11: =U10+TablaIndicador[[#This Row],[Costo Mensual]] -> 1.116178e+09 | V11: 2.5185778e+08 | W11: =IFERROR(T11*L11,0) -> 1.0383587e+09 | X11: =S11*L11 -> 1.0668069e+09 | Y11: =IFERROR(W11-U11,0) -> -77819273 | Z11: =W11-X11 -> -28448183 | AA11: =IFERROR(W11/U11,"No se realizó gasto en este corte") -> 0.93028059 | AB11: =IFERROR( IF(OR(AA11="",AA11=0), "No calculado", IF(AA11>1,"Costo eficiente: se está gastando menos de lo presupuestado", IF(AA11=1,"Costo según lo presupuestado", "Costo ineficiente: se está gastando más de lo presupuestado"))), "No calculado") -> Costo ineficiente: se está gastando más de lo presupuestado | AC11: =IFERROR(W11/X11,0) -> 0.97333333 | AD11: =IF(OR(AC11="",AC11=0),"Sin Línea Base", IF(AC11>1,"Proyecto adelantado respecto al cronograma", IF(AC11=1,"Proyecto a tiempo según lo planificado", IF(AC11<1,"Proyecto atrasado con respecto al cronograma", "No calculado")))) -> Proyecto atrasado con respecto al cronograma | AE11: =IFERROR(L11/AA11,0) -> 1.5290109e+09 | AF11: =IFERROR(AE11-L11,0) -> 1.0660174e+08 | AG11: =VLOOKUP(Indicador!E11,Diccionario!C$1:AC$150,27,0) -> https://growdatasas.sharepoint.com/:x:/r/sites/Gestiondocumental/Administrativa/GD/Financiera/_layouts/15/Doc.aspx?sourcedoc=%7B453B6AA8-B631-4722-B916-8323F8C43E87%7D&file=315%20CORP%20COLOMBIA%20DIGITAL%20FNA%20AE.xlsm&action=default&mobileredirect=true | AH11: 1 | AI11: 1
A12: 2024 | B12: Julio | C12: b3dee2f4-49c1-ee11-add8-00155d10211a | D12: 45323.9 | E12: CORP COLOMBIA DIGITAL-FNA-AE | F12: Johan Sebastian Rodriguez Niño | G12: https://growdatasas.sharepoint.com/sites/pwa/CORP COLOMBIA DIGITAL-FNA-AE | H12: Consultoría para el diseño de la Transformación Digital de la entidad que designe la Corporación Colombia Digital, basado en desarrollar la arquitectura empresarial - AR, la definición e implementación del Gobierno y la gestión de datos, la definición de la hoja de ruta de la AR para el plan estratégico de TI PETI, la formación de personal y la planeación del proyecto de la entidad designada. | I12: CONSULTORÍA | J12: 0315 | K12: Activo.En Cierre | L12: =VLOOKUP(E12,Diccionario!C$2:AC$150,22,0) -> 1422409157 | M12: =VLOOKUP(E12,Diccionario!C$2:AC$150,24,0) -> 45292 | N12: =VLOOKUP(E12,Diccionario!C$2:AC$150,25,0) -> 45534 | O12: =VLOOKUP(E12,Diccionario!C$2:AC$150,26,0) -> 7.97 | P12: =Q12-O12 -> -0.97 | Q12: 7 | R12: 8 | S12: 0.8 | T12: 0.82 | U12: =U11+TablaIndicador[[#This Row],[Costo Mensual]] -> 1.2692936e+09 | V12: 1.531156e+08 | W12: =IFERROR(T12*L12,0) -> 1.1663755e+09 | X12: =S12*L12 -> 1.1379273e+09 | Y12: =IFERROR(W12-U12,0) -> -1.0291805e+08 | Z12: =W12-X12 -> 28448183 | AA12: =IFERROR(W12/U12,"No se realizó gasto en este corte") -> 0.91891706 | AB12: =IFERROR( IF(OR(AA12="",AA12=0), "No calculado", IF(AA12>1,"Costo eficiente: se está gastando menos de lo presupuestado", IF(AA12=1,"Costo según lo presupuestado", "Costo ineficiente: se está gastando más de lo presupuestado"))), "No calculado") -> Costo ineficiente: se está gastando más de lo presupuestado | AC12: =IFERROR(W12/X12,0) -> 1.025 | AD12: =IF(OR(AC12="",AC12=0),"Sin Línea Base", IF(AC12>1,"Proyecto adelantado respecto al cronograma", IF(AC12=1,"Proyecto a tiempo según lo planificado", IF(AC12<1,"Proyecto atrasado con respecto al cronograma", "No calculado")))) -> Proyecto adelantado respecto al cronograma | AE12: =IFERROR(L12/AA12,0) -> 1.547919e+09 | AF12: =IFERROR(AE12-L12,0) -> 1.2550982e+08 | AG12: =VLOOKUP(Indicador!E12,Diccionario!C$1:AC$150,27,0) -> https://growdatasas.sharepoint.com/:x:/r/sites/Gestiondocumental/Administrativa/GD/Financiera/_layouts/15/Doc.aspx?sourcedoc=%7B453B6AA8-B631-4722-B916-8323F8C43E87%7D&file=315%20CORP%20COLOMBIA%20DIGITAL%20FNA%20AE.xlsm&action=default&mobileredirect=true | AH12: 1 | AI12: 1
A13: 2024 | B13: Agosto | C13: b3dee2f4-49c1-ee11-add8-00155d10211a | D13: 45323.9 | E13: CORP COLOMBIA DIGITAL-FNA-AE | F13: Johan Sebastian Rodriguez Niño | G13: https://growdatasas.sharepoint.com/sites/pwa/CORP COLOMBIA DIGITAL-FNA-AE | H13: Consultoría para el diseño de la Transformación Digital de la entidad que designe la Corporación Colombia Digital, basado en desarrollar la arquitectura empresarial - AR, la definición e implementación del Gobierno y la gestión de datos, la definición de la hoja de ruta de la AR para el plan estratégico de TI PETI, la formación de personal y la planeación del proyecto de la entidad designada. | I13: CONSULTORÍA | J13: 0315 | K13: Activo.En Cierre | L13: =VLOOKUP(E13,Diccionario!C$2:AC$150,22,0) -> 1422409157 | M13: =VLOOKUP(E13,Diccionario!C$2:AC$150,24,0) -> 45292 | N13: =VLOOKUP(E13,Diccionario!C$2:AC$150,25,0) -> 45534 | O13: =VLOOKUP(E13,Diccionario!C$2:AC$150,26,0) -> 7.97 | P13: =Q13-O13 -> 0.03 | Q13: 8 | R13: 8 | S13: 1 | T13: 1 | U13: =U12+TablaIndicador[[#This Row],[Costo Mensual]] -> 1.4224092e+09 | V13: 1.531156e+08 | W13: =IFERROR(T13*L13,0) -> 1422409157 | X13: =S13*L13 -> 1422409157 | Y13: =IFERROR(W13-U13,0) -> -0.042016029 | Z13: =W13-X13 -> 0 | AA13: =IFERROR(W13/U13,"No se realizó gasto en este corte") -> 1 | AB13: =IFERROR( IF(OR(AA13="",AA13=0), "No calculado", IF(AA13>1,"Costo eficiente: se está gastando menos de lo presupuestado", IF(AA13=1,"Costo según lo presupuestado", "Costo ineficiente: se está gastando más de lo presupuestado"))), "No calculado") -> Costo ineficiente: se está gastando más de lo presupuestado | AC13: =IFERROR(W13/X13,0) -> 1 | AD13: =IF(OR(AC13="",AC13=0),"Sin Línea Base", IF(AC13>1,"Proyecto adelantado respecto al cronograma", IF(AC13=1,"Proyecto a tiempo según lo planificado", IF(AC13<1,"Proyecto atrasado con respecto al cronograma", "No calculado")))) -> Proyecto a tiempo según lo planificado | AE13: =IFERROR(L13/AA13,0) -> 1.4224092e+09 | AF13: =IFERROR(AE13-L13,0) -> 0.042016029 | AG13: =VLOOKUP(Indicador!E13,Diccionario!C$1:AC$150,27,0) -> https://growdatasas.sharepoint.com/:x:/r/sites/Gestiondocumental/Administrativa/GD/Financiera/_layouts/15/Doc.aspx?sourcedoc=%7B453B6AA8-B631-4722-B916-8323F8C43E87%7D&file=315%20CORP%20COLOMBIA%20DIGITAL%20FNA%20AE.xlsm&action=default&mobileredirect=true | AH13: 1 | AI13: 1
A14: 2024 | B14: Enero | C14: 93afa0f2-87b4-ee11-b12b-00155d10d37b | D14: 45307.665 | E14: INFOTIC-DPC-SOC | F14: Janeth Annelise Araujo Ramos | G14: https://growdatasas.sharepoint.com/sites/pwa/INFOTIC-DPC-SOC | H14: ​Implementación y puesta en operación del Centro de Operaciones de Seguridad (SOC). | I14: TI | J14: 0320 | K14: Cerrado | L14: =VLOOKUP(E14,Diccionario!C$2:AC$150,22,0) -> 5280083724 | M14: =VLOOKUP(E14,Diccionario!C$2:AC$150,24,0) -> 45300 | N14: =VLOOKUP(E14,Diccionario!C$2:AC$150,25,0) -> 45473 | O14: =VLOOKUP(E14,Diccionario!C$2:AC$150,26,0) -> 5.7 | P14: =Q14-O14 -> -4.7 | Q14: 1 | R14: 6 | S14: 0.2 | T14: 0.25 | U14: 35266820 | V14: 35266820 | W14: =IFERROR(T14*L14,0) -> 1320020931 | X14: =S14*L14 -> 1.0560167e+09 | Y14: =IFERROR(W14-U14,0) -> 1284754111 | Z14: =W14-X14 -> 2.6400419e+08 | AA14: =IFERROR(W14/U14,"No se realizó gasto en este corte") -> 37.429542 | AB14: =IFERROR( IF(OR(AA14="",AA14=0), "No calculado", IF(AA14>1,"Costo eficiente: se está gastando menos de lo presupuestado", IF(AA14=1,"Costo según lo presupuestado", "Costo ineficiente: se está gastando más de lo presupuestado"))), "No calculado") -> Costo eficiente: se está gastando menos de lo presupuestado | AC14: =IFERROR(W14/X14,0) -> 1.25 | AD14: =IF(OR(AC14="",AC14=0),"Sin Línea Base", IF(AC14>1,"Proyecto adelantado respecto al cronograma", IF(AC14=1,"Proyecto a tiempo según lo planificado", IF(AC14<1,"Proyecto atrasado con respecto al cronograma", "No calculado")))) -> Proyecto adelantado respecto al cronograma | AE14: =IFERROR(L14/AA14,0) -> 141067280 | AF14: =IFERROR(AE14-L14,0) -> -5139016444 | AG14: =VLOOKUP(Indicador!E14,Diccionario!C$1:AC$150,27,0) -> https://growdatasas.sharepoint.com/:x:/r/sites/Gestiondocumental/Administrativa/GD/Financiera/_layouts/15/Doc.aspx?sourcedoc=%7BB4DE39AF-1EC1-466C-A807-3FE95776A982%7D&file=17012024%20INFOTIC%20DPC%20SOC%20V2.xlsm&action=default&mobileredirect=true | AH14: 1 | AI14: 1
A15: 2024 | B15: Febrero | C15: 93afa0f2-87b4-ee11-b12b-00155d10d37b | D15: 45307.665 | E15: INFOTIC-DPC-SOC | F15: Janeth Annelise Araujo Ramos | G15: https://growdatasas.sharepoint.com/sites/pwa/INFOTIC-DPC-SOC | H15: ​Implementación y puesta en operación del Centro de Operaciones de Seguridad (SOC). | I15: TI | J15: 0320 | K15: Cerrado | L15: =VLOOKUP(E15,Diccionario!C$2:AC$150,22,0) -> 5280083724 | M15: =VLOOKUP(E15,Diccionario!C$2:AC$150,24,0) -> 45300 | N15: =VLOOKUP(E15,Diccionario!C$2:AC$150,25,0) -> 45473 | O15: =VLOOKUP(E15,Diccionario!C$2:AC$150,26,0) -> 5.7 | P15: =Q15-O15 -> -3.7 | Q15: 2 | R15: 6 | S15: 0.45 | T15: 0.35 | U15: 4039374977 | V15: 4039374977 | W15: =IFERROR(T15*L15,0) -> 1.8480293e+09 | X15: =S15*L15 -> 2.3760377e+09 | Y15: =IFERROR(W15-U15,0) -> -2.1913457e+09 | Z15: =W15-X15 -> -5.2800837e+08 | AA15: =IFERROR(W15/U15,"No se realizó gasto en este corte") -> 0.45750378 | AB15: =IFERROR( IF(OR(AA15="",AA15=0), "No calculado", IF(AA15>1,"Costo eficiente: se está gastando menos de lo presupuestado", IF(AA15=1,"Costo según lo presupuestado", "Costo ineficiente: se está gastando más de lo presupuestado"))), "No calculado") -> Costo ineficiente: se está gastando más de lo presupuestado | AC15: =IFERROR(W15/X15,0) -> 0.77777778 | AD15: =IF(OR(AC15="",AC15=0),"Sin Línea Base", IF(AC15>1,"Proyecto adelantado respecto al cronograma", IF(AC15=1,"Proyecto a tiempo según lo planificado", IF(AC15<1,"Proyecto atrasado con respecto al cronograma", "No calculado")))) -> Proyecto atrasado con respecto al cronograma | AE15: =IFERROR(L15/AA15,0) -> 1.1541071e+10 | AF15: =IFERROR(AE15-L15,0) -> 6.2609876e+09 | AG15: =VLOOKUP(Indicador!E15,Diccionario!C$1:AC$150,27,0) -> https://growdatasas.sharepoint.com/:x:/r/sites/Gestiondocumental/Administrativa/GD/Financiera/_layouts/15/Doc.aspx?sourcedoc=%7BB4DE39AF-1EC1-466C-A807-3FE95776A982%7D&file=17012024%20INFOTIC%20DPC%20SOC%20V2.xlsm&action=default&mobileredirect=true | AH15: 1 | AI15: 1
A16: 2024 | B16: Marzo | C16: 93afa0f2-87b4-ee11-b12b-00155d10d37b | D16: 45307.665 | E16: INFOTIC-DPC-SOC | F16: Janeth Annelise Araujo Ramos | G16: https://growdatasas.sharepoint.com/sites/pwa/INFOTIC-DPC-SOC | H16: ​Implementación y puesta en operación del Centro de Operaciones de Seguridad (SOC). | I16: TI | J16: 0320 | K16: Cerrado | L16: =VLOOKUP(E16,Diccionario!C$2:AC$150,22,0) -> 5280083724 | M16: =VLOOKUP(E16,Diccionario!C$2:AC$150,24,0) -> 45300 | N16: =VLOOKUP(E16,Diccionario!C$2:AC$150,25,0) -> 45473 | O16: =VLOOKUP(E16,Diccionario!C$2:AC$150,26,0) -> 5.7 | P16: =Q16-O16 -> -2.7 | Q16: 3 | R16: 6 | S16: 0.6 | T16: 0.38 | U16: 1072838872 | V16: 1072838872 | W16: =IFERROR(T16*L16,0) -> 2.0064318e+09 | X16: =S16*L16 -> 3.1680502e+09 | Y16: =IFERROR(W16-U16,0) -> 9.3359294e+08 | Z16: =W16-X16 -> -1.1616184e+09 | AA16: =IFERROR(W16/U16,"No se realizó gasto en este corte") -> 1.870208 | AB16: =IFERROR( IF(OR(AA16="",AA16=0), "No calculado", IF(AA16>1,"Costo eficiente: se está gastando menos de lo presupuestado", IF(AA16=1,"Costo según lo presupuestado", "Costo ineficiente: se está gastando más de lo presupuestado"))), "No calculado") -> Costo eficiente: se está gastando menos de lo presupuestado | AC16: =IFERROR(W16/X16,0) -> 0.63333333 | AD16: =IF(OR(AC16="",AC16=0),"Sin Línea Base", IF(AC16>1,"Proyecto adelantado respecto al cronograma", IF(AC16=1,"Proyecto a tiempo según lo planificado", IF(AC16<1,"Proyecto atrasado con respecto al cronograma", "No calculado")))) -> Proyecto atrasado con respecto al cronograma | AE16: =IFERROR(L16/AA16,0) -> 2.8232602e+09 | AF16: =IFERROR(AE16-L16,0) -> -2.4568235e+09 | AG16: =VLOOKUP(Indicador!E16,Diccionario!C$1:AC$150,27,0) -> https://growdatasas.sharepoint.com/:x:/r/sites/Gestiondocumental/Administrativa/GD/Financiera/_layouts/15/Doc.aspx?sourcedoc=%7BB4DE39AF-1EC1-466C-A807-3FE95776A982%7D&file=17012024%20INFOTIC%20DPC%20SOC%20V2.xlsm&action=default&mobileredirect=true | AH16: 1 | AI16: 1
A17: 2024 | B17: Abril | C17: 93afa0f2-87b4-ee11-b12b-00155d10d37b | D17: 45307.665 | E17: INFOTIC-DPC-SOC | F17: Janeth Annelise Araujo Ramos | G17: https://growdatasas.sharepoint.com/sites/pwa/INFOTIC-DPC-SOC | H17: ​Implementación y puesta en operación del Centro de Operaciones de Seguridad (SOC). | I17: TI | J17: 0320 | K17: Cerrado | L17: =VLOOKUP(E17,Diccionario!C$2:AC$150,22,0) -> 5280083724 | M17: =VLOOKUP(E17,Diccionario!C$2:AC$150,24,0) -> 45300 | N17: =VLOOKUP(E17,Diccionario!C$2:AC$150,25,0) -> 45473 | O17: =VLOOKUP(E17,Diccionario!C$2:AC$150,26,0) -> 5.7 | P17: =Q17-O17 -> -1.7 | Q17: 4 | R17: 6 | S17: 0.75 | T17: 0.49 | U17: 35266820 | V17: 35266820 | W17: =IFERROR(T17*L17,0) -> 2.587241e+09 | X17: =S17*L17 -> 3960062793 | Y17: =IFERROR(W17-U17,0) -> 2.5519742e+09 | Z17: =W17-X17 -> -1.3728218e+09 | AA17: =IFERROR(W17/U17,"No se realizó gasto en este corte") -> 73.361903 | AB17: =IFERROR( IF(OR(AA17="",AA17=0), "No calculado", IF(AA17>1,"Costo eficiente: se está gastando menos de lo presupuestado", IF(AA17=1,"Costo según lo presupuestado", "Costo ineficiente: se está gastando más de lo presupuestado"))), "No calculado") -> Costo eficiente: se está gastando menos de lo presupuestado | AC17: =IFERROR(W17/X17,0) -> 0.65333333 | AD17: =IF(OR(AC17="",AC17=0),"Sin Línea Base", IF(AC17>1,"Proyecto adelantado respecto al cronograma", IF(AC17=1,"Proyecto a tiempo según lo planificado", IF(AC17<1,"Proyecto atrasado con respecto al cronograma", "No calculado")))) -> Proyecto atrasado con respecto al cronograma | AE17: =IFERROR(L17/AA17,0) -> 71973102 | AF17: =IFERROR(AE17-L17,0) -> -5.2081106e+09 | AG17: =VLOOKUP(Indicador!E17,Diccionario!C$1:AC$150,27,0) -> https://growdatasas.sharepoint.com/:x:/r/sites/Gestiondocumental/Administrativa/GD/Financiera/_layouts/15/Doc.aspx?sourcedoc=%7BB4DE39AF-1EC1-466C-A807-3FE95776A982%7D&file=17012024%20INFOTIC%20DPC%20SOC%20V2.xlsm&action=default&mobileredirect=true | AH17: 1 | AI17: 1
A18: 2024 | B18: Mayo | C18: 93afa0f2-87b4-ee11-b12b-00155d10d37b | D18: 45307.665 | E18: INFOTIC-DPC-SOC | F18: Janeth Annelise Araujo Ramos | G18: https://growdatasas.sharepoint.com/sites/pwa/INFOTIC-DPC-SOC | H18: ​Implementación y puesta en operación del Centro de Operaciones de Seguridad (SOC). | I18: TI | J18: 0320 | K18: Cerrado | L18: =VLOOKUP(E18,Diccionario!C$2:AC$150,22,0) -> 5280083724 | M18: =VLOOKUP(E18,Diccionario!C$2:AC$150,24,0) -> 45300 | N18: =VLOOKUP(E18,Diccionario!C$2:AC$150,25,0) -> 45473 | O18: =VLOOKUP(E18,Diccionario!C$2:AC$150,26,0) -> 5.7 | P18: =Q18-O18 -> -0.7 | Q18: 5 | R18: 6 | S18: 0.8 | T18: 0.6 | U18: 35266820 | V18: 35266820 | W18: =IFERROR(T18*L18,0) -> 3.1680502e+09 | X18: =S18*L18 -> 4.224067e+09 | Y18: =IFERROR(W18-U18,0) -> 3.1327834e+09 | Z18: =W18-X18 -> -1.0560167e+09 | AA18: =IFERROR(W18/U18,"No se realizó gasto en este corte") -> 89.830902 | AB18: =IFERROR( IF(OR(AA18="",AA18=0), "No calculado", IF(AA18>1,"Costo eficiente: se está gastando menos de lo presupuestado", IF(AA18=1,"Costo según lo presupuestado", "Costo ineficiente: se está gastando más de lo presupuestado"))), "No calculado") -> Costo eficiente: se está gastando menos de lo presupuestado | AC18: =IFERROR(W18/X18,0) -> 0.75 | AD18: =IF(OR(AC18="",AC18=0),"Sin Línea Base", IF(AC18>1,"Proyecto adelantado respecto al cronograma", IF(AC18=1,"Proyecto a tiempo según lo planificado", IF(AC18<1,"Proyecto atrasado con respecto al cronograma", "No calculado")))) -> Proyecto atrasado con respecto al cronograma | AE18: =IFERROR(L18/AA18,0) -> 58778033 | AF18: =IFERROR(AE18-L18,0) -> -5.2213057e+09 | AG18: =VLOOKUP(Indicador!E18,Diccionario!C$1:AC$150,27,0) -> https://growdatasas.sharepoint.com/:x:/r/sites/Gestiondocumental/Administrativa/GD/Financiera/_layouts/15/Doc.aspx?sourcedoc=%7BB4DE39AF-1EC1-466C-A807-3FE95776A982%7D&file=17012024%20INFOTIC%20DPC%20SOC%20V2.xlsm&action=default&mobileredirect=true | AH18: 1 | AI18: 1
A19: 2024 | B19: Junio | C19: 93afa0f2-87b4-ee11-b12b-00155d10d37b | D19: 45307.665 | E19: INFOTIC-DPC-SOC | F19: Janeth Annelise Araujo Ramos | G19: https://growdatasas.sharepoint.com/sites/pwa/INFOTIC-DPC-SOC | H19: ​Implementación y puesta en operación del Centro de Operaciones de Seguridad (SOC). | I19: TI | J19: 0320 | K19: Cerrado | L19: =VLOOKUP(E19,Diccionario!C$2:AC$150,22,0) -> 5280083724 | M19: =VLOOKUP(E19,Diccionario!C$2:AC$150,24,0) -> 45300 | N19: =VLOOKUP(E19,Diccionario!C$2:AC$150,25,0) -> 45473 | O19: =VLOOKUP(E19,Diccionario!C$2:AC$150,26,0) -> 5.7 | P19: =Q19-O19 -> 0.3 | Q19: 6 | R19: 6 | S19: 1 | T19: 0.78 | U19: 35266820 | V19: 35266820 | W19: =IFERROR(T19*L19,0) -> 4.1184653e+09 | X19: =S19*L19 -> 5280083724 | Y19: =IFERROR(W19-U19,0) -> 4.0831985e+09 | Z19: =W19-X19 -> -1.1616184e+09 | AA19: =IFERROR(W19/U19,"No se realizó gasto en este corte") -> 116.78017 | AB19: =IFERROR( IF(OR(AA19="",AA19=0), "No calculado", IF(AA19>1,"Costo eficiente: se está gastando menos de lo presupuestado", IF(AA19=1,"Costo según lo presupuestado", "Costo ineficiente: se está gastando más de lo presupuestado"))), "No calculado") -> Costo eficiente: se está gastando menos de lo presupuestado | AC19: =IFERROR(W19/X19,0) -> 0.78 | AD19: =IF(OR(AC19="",AC19=0),"Sin Línea Base", IF(AC19>1,"Proyecto adelantado respecto al cronograma", IF(AC19=1,"Proyecto a tiempo según lo planificado", IF(AC19<1,"Proyecto atrasado con respecto al cronograma", "No calculado")))) -> Proyecto atrasado con respecto al cronograma | AE19: =IFERROR(L19/AA19,0) -> 45213872 | AF19: =IFERROR(AE19-L19,0) -> -5.2348699e+09 | AG19: =VLOOKUP(Indicador!E19,Diccionario!C$1:AC$150,27,0) -> https://growdatasas.sharepoint.com/:x:/r/sites/Gestiondocumental/Administrativa/GD/Financiera/_layouts/15/Doc.aspx?sourcedoc=%7BB4DE39AF-1EC1-466C-A807-3FE95776A982%7D&file=17012024%20INFOTIC%20DPC%20SOC%20V2.xlsm&action=default&mobileredirect=true | AH19: 1 | AI19: 1
A20: 2024 | B20: Julio | C20: 93afa0f2-87b4-ee11-b12b-00155d10d37b | D20: 45307.665 | E20: INFOTIC-DPC-SOC | F20: Janeth Annelise Araujo Ramos | G20: https://growdatasas.sharepoint.com/sites/pwa/INFOTIC-DPC-SOC | H20: ​Implementación y puesta en operación del Centro de Operaciones de Seguridad (SOC). | I20: TI | J20: 0320 | K20: Cerrado | L20: =VLOOKUP(E20,Diccionario!C$2:AC$150,22,0) -> 5280083724 | M20: =VLOOKUP(E20,Diccionario!C$2:AC$150,24,0) -> 45300 | N20: =VLOOKUP(E20,Diccionario!C$2:AC$150,25,0) -> 45473 | O20: =VLOOKUP(E20,Diccionario!C$2:AC$150,26,0) -> 5.7 | P20: =Q20-O20 -> 1.3 | Q20: 7 | R20: 6 | S20: 1 | T20: 0.9 | U20: 13401297 | V20: 13401297 | W20: =IFERROR(T20*L20,0) -> 4.7520754e+09 | X20: =S20*L20 -> 5280083724 | Y20: =IFERROR(W20-U20,0) -> 4.7386741e+09 | Z20: =W20-X20 -> -5.2800837e+08 | AA20: =IFERROR(W20/U20,"No se realizó gasto en este corte") -> 354.59817 | AB20: =IFERROR( IF(OR(AA20="",AA20=0), "No calculado", IF(AA20>1,"Costo eficiente: se está gastando menos de lo presupuestado", IF(AA20=1,"Costo según lo presupuestado", "Costo ineficiente: se está gastando más de lo presupuestado"))), "No calculado") -> Costo eficiente: se está gastando menos de lo presupuestado | AC20: =IFERROR(W20/X20,0) -> 0.9 | AD20: =IF(OR(AC20="",AC20=0),"Sin Línea Base", IF(AC20>1,"Proyecto adelantado respecto al cronograma", IF(AC20=1,"Proyecto a tiempo según lo planificado", IF(AC20<1,"Proyecto atrasado con respecto al cronograma", "No calculado")))) -> Proyecto atrasado con respecto al cronograma | AE20: =IFERROR(L20/AA20,0) -> 14890330 | AF20: =IFERROR(AE20-L20,0) -> -5265193394 | AG20: =VLOOKUP(Indicador!E20,Diccionario!C$1:AC$150,27,0) -> https://growdatasas.sharepoint.com/:x:/r/sites/Gestiondocumental/Administrativa/GD/Financiera/_layouts/15/Doc.aspx?sourcedoc=%7BB4DE39AF-1EC1-466C-A807-3FE95776A982%7D&file=17012024%20INFOTIC%20DPC%20SOC%20V2.xlsm&action=default&mobileredirect=true | AH20: 1 | AI20: 1
A21: 2024 | B21: Agosto | C21: 93afa0f2-87b4-ee11-b12b-00155d10d37b | D21: 45307.665 | E21: INFOTIC-DPC-SOC | F21: Janeth Annelise Araujo Ramos | G21: https://growdatasas.sharepoint.com/sites/pwa/INFOTIC-DPC-SOC | H21: ​Implementación y puesta en operación del Centro de Operaciones de Seguridad (SOC). | I21: TI | J21: 0320 | K21: Cerrado | L21: =VLOOKUP(E21,Diccionario!C$2:AC$150,22,0) -> 5280083724 | M21: =VLOOKUP(E21,Diccionario!C$2:AC$150,24,0) -> 45300 | N21: =VLOOKUP(E21,Diccionario!C$2:AC$150,25,0) -> 45473 | O21: =VLOOKUP(E21,Diccionario!C$2:AC$150,26,0) -> 5.7 | P21: =Q21-O21 -> 2.3 | Q21: 8 | R21: 6 | S21: 1 | T21: 1 | U21: 13401297 | V21: 13401297 | W21: =IFERROR(T21*L21,0) -> 5280083724 | X21: =S21*L21 -> 5280083724 | Y21: =IFERROR(W21-U21,0) -> 5266682427 | Z21: =W21-X21 -> 0 | AA21: =IFERROR(W21/U21,"No se realizó gasto en este corte") -> 393.99796 | AB21: =IFERROR( IF(OR(AA21="",AA21=0), "No calculado", IF(AA21>1,"Costo eficiente: se está gastando menos de lo presupuestado", IF(AA21=1,"Costo según lo presupuestado", "Costo ineficiente: se está gastando más de lo presupuestado"))), "No calculado") -> Costo eficiente: se está gastando menos de lo presupuestado | AC21: =IFERROR(W21/X21,0) -> 1 | AD21: =IF(OR(AC21="",AC21=0),"Sin Línea Base", IF(AC21>1,"Proyecto adelantado respecto al cronograma", IF(AC21=1,"Proyecto a tiempo según lo planificado", IF(AC21<1,"Proyecto atrasado con respecto al cronograma", "No calculado")))) -> Proyecto a tiempo según lo planificado | AE21: =IFERROR(L21/AA21,0) -> 13401297 | AF21: =IFERROR(AE21-L21,0) -> -5266682427 | AG21: =VLOOKUP(Indicador!E21,Diccionario!C$1:AC$150,27,0) -> https://growdatasas.sharepoint.com/:x:/r/sites/Gestiondocumental/Administrativa/GD/Financiera/_layouts/15/Doc.aspx?sourcedoc=%7BB4DE39AF-1EC1-466C-A807-3FE95776A982%7D&file=17012024%20INFOTIC%20DPC%20SOC%20V2.xlsm&action=default&mobileredirect=true | AH21: 1 | AI21: 1
A22: 2024 | B22: Enero | C22: 227b8bc1-c7ab-ee11-ba7f-00155d104f2c | D22: 45296.529 | E22: CCD - DPC - IMPLEMENTACIÓN ERP | F22: Johan Sebastian Rodriguez Niño | G22: https://growdatasas.sharepoint.com/sites/pwa/CCD - DPC - IMPLEMENTACIÓN ERP | H22: Suministro e implementación del sistema de información ADMINISTRATIVO ERP NOVASOFT – versión ENTERPRISE WEB y el GESTOR DE RIESGOS para la entidad Defensoría del Pueblo.Incluye: 14 módulos específicos + 5 módulos financieros con licencia para 5000 usuarios finales, Licenciamiento de la Base de Datos SQL Server (Estándar para 8 Cores), Consultoría estándar de implementación de cada uno de los sistemas ofrecidos, soporte y actualización por 2 años y una bolsa de horas (según acuerdo por 2 años) | I22: DATOS Y SISTEMAS DE INFORMACIÓN | J22: 0318 | K22: Activo.En Ejecución | L22: =VLOOKUP(E22,Diccionario!C$2:AC$150,22,0) -> 3323223361 | M22: =VLOOKUP(E22,Diccionario!C$2:AC$150,24,0) -> 45300 | N22: =VLOOKUP(E22,Diccionario!C$2:AC$150,25,0) -> 45473 | O22: =VLOOKUP(E22,Diccionario!C$2:AC$150,26,0) -> 5.7 | P22: =Q22-O22 -> -4.7 | Q22: 1 | R22: 6 | S22: 0.2 | T22: 0.2 | W22: =IFERROR(T22*L22,0) -> 6.6464467e+08 | X22: =S22*L22 -> 6.6464467e+08 | Y22: =IFERROR(W22-U22,0) -> 6.6464467e+08 | Z22: =W22-X22 -> 0 | AA22: =IFERROR(W22/U22,"No se realizó gasto en este corte") -> No se realizó gasto en este corte | AB22: =IFERROR( IF(OR(AA22="",AA22=0), "No calculado", IF(AA22>1,"Costo eficiente: se está gastando menos de lo presupuestado", IF(AA22=1,"Costo según lo presupuestado", "Costo ineficiente: se está gastando más de lo presupuestado"))), "No calculado") -> Costo eficiente: se está gastando menos de lo presupuestado | AC22: =IFERROR(W22/X22,0) -> 1 | AD22: =IF(OR(AC22="",AC22=0),"Sin Línea Base", IF(AC22>1,"Proyecto adelantado respecto al cronograma", IF(AC22=1,"Proyecto a tiempo según lo planificado", IF(AC22<1,"Proyecto atrasado con respecto al cronograma", "No calculado")))) -> Proyecto a tiempo según lo planificado | AE22: =IFERROR(L22/AA22,0) -> 0 | AF22: =IFERROR(AE22-L22,0) -> -3323223361 | AG22: =VLOOKUP(Indicador!E22,Diccionario!C$1:AC$150,27,0) -> https://growdatasas.sharepoint.com/:x:/r/sites/Gestiondocumental/Administrativa/GD/Financiera/_layouts/15/Doc.aspx?sourcedoc=%7BC3EFE0E2-C211-45B0-905D-ECEF11221767%7D&file=299.%20DEFENSORIA_ERP.xlsm&action=default&mobileredirect=true | AH22: 1 | AI22: 1
A23: 2024 | B23: Febrero | C23: 227b8bc1-c7ab-ee11-ba7f-00155d104f2c | D23: 45296.529 | E23: CCD - DPC - IMPLEMENTACIÓN ERP | F23: Johan Sebastian Rodriguez Niño | G23: https://growdatasas.sharepoint.com/sites/pwa/CCD - DPC - IMPLEMENTACIÓN ERP | H23: Suministro e implementación del sistema de información ADMINISTRATIVO ERP NOVASOFT – versión ENTERPRISE WEB y el GESTOR DE RIESGOS para la entidad Defensoría del Pueblo.Incluye: 14 módulos específicos + 5 módulos financieros con licencia para 5000 usuarios finales, Licenciamiento de la Base de Datos SQL Server (Estándar para 8 Cores), Consultoría estándar de implementación de cada uno de los sistemas ofrecidos, soporte y actualización por 2 años y una bolsa de horas (según acuerdo por 2 años) | I23: DATOS Y SISTEMAS DE INFORMACIÓN | J23: 0318 | K23: Activo.En Ejecución | L23: =VLOOKUP(E23,Diccionario!C$2:AC$150,22,0) -> 3323223361 | M23: =VLOOKUP(E23,Diccionario!C$2:AC$150,24,0) -> 45300 | N23: =VLOOKUP(E23,Diccionario!C$2:AC$150,25,0) -> 45473 | O23: =VLOOKUP(E23,Diccionario!C$2:AC$150,26,0) -> 5.7 | P23: =Q23-O23 -> -3.7 | Q23: 2 | R23: 6 | S23: 0.3 | T23: 0.3 | W23: =IFERROR(T23*L23,0) -> 9.9696701e+08 | X23: =S23*L23 -> 9.9696701e+08 | Y23: =IFERROR(W23-U23,0) -> 9.9696701e+08 | Z23: =W23-X23 -> 0 | AA23: =IFERROR(W23/U23,"No se realizó gasto en este corte") -> No se realizó gasto en este corte | AB23: =IFERROR( IF(OR(AA23="",AA23=0), "No calculado", IF(AA23>1,"Costo eficiente: se está gastando menos de lo presupuestado", IF(AA23=1,"Costo según lo presupuestado", "Costo ineficiente: se está gastando más de lo presupuestado"))), "No calculado") -> Costo eficiente: se está gastando menos de lo presupuestado | AC23: =IFERROR(W23/X23,0) -> 1 | AD23: =IF(OR(AC23="",AC23=0),"Sin Línea Base", IF(AC23>1,"Proyecto adelantado respecto al cronograma", IF(AC23=1,"Proyecto a tiempo según lo planificado", IF(AC23<1,"Proyecto atrasado con respecto al cronograma", "No calculado")))) -> Proyecto a tiempo según lo planificado | AE23: =IFERROR(L23/AA23,0) -> 0 | AF23: =IFERROR(AE23-L23,0) -> -3323223361 | AG23: =VLOOKUP(Indicador!E23,Diccionario!C$1:AC$150,27,0) -> https://growdatasas.sharepoint.com/:x:/r/sites/Gestiondocumental/Administrativa/GD/Financiera/_layouts/15/Doc.aspx?sourcedoc=%7BC3EFE0E2-C211-45B0-905D-ECEF11221767%7D&file=299.%20DEFENSORIA_ERP.xlsm&action=default&mobileredirect=true | AH23: 1 | AI23: 1
A24: 2024 | B24: Marzo | C24: 227b8bc1-c7ab-ee11-ba7f-00155d104f2c | D24: 45296.529 | E24: CCD - DPC - IMPLEMENTACIÓN ERP | F24: Johan Sebastian Rodriguez Niño | G24: https://growdatasas.sharepoint.com/sites/pwa/CCD - DPC - IMPLEMENTACIÓN ERP | H24: Suministro e implementación del sistema de información ADMINISTRATIVO ERP NOVASOFT – versión ENTERPRISE WEB y el GESTOR DE RIESGOS para la entidad Defensoría del Pueblo.Incluye: 14 módulos específicos + 5 módulos financieros con licencia para 5000 usuarios finales, Licenciamiento de la Base de Datos SQL Server (Estándar para 8 Cores), Consultoría estándar de implementación de cada uno de los sistemas ofrecidos, soporte y actualización por 2 años y una bolsa de horas (según acuerdo por 2 años) | I24: DATOS Y SISTEMAS DE INFORMACIÓN | J24: 0318 | K24: Activo.En Ejecución | L24: =VLOOKUP(E24,Diccionario!C$2:AC$150,22,0) -> 3323223361 | M24: =VLOOKUP(E24,Diccionario!C$2:AC$150,24,0) -> 45300 | N24: =VLOOKUP(E24,Diccionario!C$2:AC$150,25,0) -> 45473 | O24: =VLOOKUP(E24,Diccionario!C$2:AC$150,26,0) -> 5.7 | P24: =Q24-O24 -> 24.3 | Q24: =DATEDIF(M24,TODAY(),"m") -> 30 | R24: 6 | S24: 0.5 | T24: 0.4 | W24: =IFERROR(T24*L24,0) -> 1.3292893e+09 | X24: =S24*L24 -> 1.6616117e+09 | Y24: =IFERROR(W24-U24,0) -> 1.3292893e+09 | Z24: =W24-X24 -> -3.3232234e+08 | AA24: =IFERROR(W24/U24,"No se realizó gasto en este corte") -> No se realizó gasto en este corte | AB24: =IFERROR( IF(OR(AA24="",AA24=0), "No calculado", IF(AA24>1,"Costo eficiente: se está gastando menos de lo presupuestado", IF(AA24=1,"Costo según lo presupuestado", "Costo ineficiente: se está gastando más de lo presupuestado"))), "No calculado") -> Costo eficiente: se está gastando menos de lo presupuestado | AC24: =IFERROR(W24/X24,0) -> 0.8 | AD24: =IF(OR(AC24="",AC24=0),"Sin Línea Base", IF(AC24>1,"Proyecto adelantado respecto al cronograma", IF(AC24=1,"Proyecto a tiempo según lo planificado", IF(AC24<1,"Proyecto atrasado con respecto al cronograma", "No calculado")))) -> Proyecto atrasado con respecto al cronograma | AE24: =IFERROR(L24/AA24,0) -> 0 | AF24: =IFERROR(AE24-L24,0) -> -3323223361 | AG24: =VLOOKUP(Indicador!E24,Diccionario!C$1:AC$150,27,0) -> https://growdatasas.sharepoint.com/:x:/r/sites/Gestiondocumental/Administrativa/GD/Financiera/_layouts/15/Doc.aspx?sourcedoc=%7BC3EFE0E2-C211-45B0-905D-ECEF11221767%7D&file=299.%20DEFENSORIA_ERP.xlsm&action=default&mobileredirect=true | AH24: 1 | AI24: 1
A25: 2024 | B25: Abril | C25: 227b8bc1-c7ab-ee11-ba7f-00155d104f2c | D25: 45296.529 | E25: CCD - DPC - IMPLEMENTACIÓN ERP | F25: Johan Sebastian Rodriguez Niño | G25: https://growdatasas.sharepoint.com/sites/pwa/CCD - DPC - IMPLEMENTACIÓN ERP | H25: Suministro e implementación del sistema de información ADMINISTRATIVO ERP NOVASOFT – versión ENTERPRISE WEB y el GESTOR DE RIESGOS para la entidad Defensoría del Pueblo.Incluye: 14 módulos específicos + 5 módulos financieros con licencia para 5000 usuarios finales, Licenciamiento de la Base de Datos SQL Server (Estándar para 8 Cores), Consultoría estándar de implementación de cada uno de los sistemas ofrecidos, soporte y actualización por 2 años y una bolsa de horas (según acuerdo por 2 años) | I25: DATOS Y SISTEMAS DE INFORMACIÓN | J25: 0318 | K25: Activo.En Ejecución | L25: =VLOOKUP(E25,Diccionario!C$2:AC$150,22,0) -> 3323223361 | M25: =VLOOKUP(E25,Diccionario!C$2:AC$150,24,0) -> 45300 | N25: =VLOOKUP(E25,Diccionario!C$2:AC$150,25,0) -> 45473 | O25: =VLOOKUP(E25,Diccionario!C$2:AC$150,26,0) -> 5.7 | P25: =Q25-O25 -> 24.3 | Q25: =DATEDIF(M25,TODAY(),"m") -> 30 | R25: 6 | S25: 0.75 | T25: =T24+0.02 -> 0.42 | W25: =IFERROR(T25*L25,0) -> 1.3957538e+09 | X25: =S25*L25 -> 2.4924175e+09 | Y25: =IFERROR(W25-U25,0) -> 1.3957538e+09 | Z25: =W25-X25 -> -1.0966637e+09 | AA25: =IFERROR(W25/U25,"No se realizó gasto en este corte") -> No se realizó gasto en este corte | AB25: =IFERROR( IF(OR(AA25="",AA25=0), "No calculado", IF(AA25>1,"Costo eficiente: se está gastando menos de lo presupuestado", IF(AA25=1,"Costo según lo presupuestado", "Costo ineficiente: se está gastando más de lo presupuestado"))), "No calculado") -> Costo eficiente: se está gastando menos de lo presupuestado | AC25: =IFERROR(W25/X25,0) -> 0.56 | AD25: =IF(OR(AC25="",AC25=0),"Sin Línea Base", IF(AC25>1,"Proyecto adelantado respecto al cronograma", IF(AC25=1,"Proyecto a tiempo según lo planificado", IF(AC25<1,"Proyecto atrasado con respecto al cronograma", "No calculado")))) -> Proyecto atrasado con respecto al cronograma | AE25: =IFERROR(L25/AA25,0) -> 0 | AF25: =IFERROR(AE25-L25,0) -> -3323223361 | AG25: =VLOOKUP(Indicador!E25,Diccionario!C$1:AC$150,27,0) -> https://growdatasas.sharepoint.com/:x:/r/sites/Gestiondocumental/Administrativa/GD/Financiera/_layouts/15/Doc.aspx?sourcedoc=%7BC3EFE0E2-C211-45B0-905D-ECEF11221767%7D&file=299.%20DEFENSORIA_ERP.xlsm&action=default&mobileredirect=true | AH25: 1 | AI25: 1
A26: 2024 | B26: Mayo | C26: 227b8bc1-c7ab-ee11-ba7f-00155d104f2c | D26: 45296.529 | E26: CCD - DPC - IMPLEMENTACIÓN ERP | F26: Johan Sebastian Rodriguez Niño | G26: https://growdatasas.sharepoint.com/sites/pwa/CCD - DPC - IMPLEMENTACIÓN ERP | H26: Suministro e implementación del sistema de información ADMINISTRATIVO ERP NOVASOFT – versión ENTERPRISE WEB y el GESTOR DE RIESGOS para la entidad Defensoría del Pueblo.Incluye: 14 módulos específicos + 5 módulos financieros con licencia para 5000 usuarios finales, Licenciamiento de la Base de Datos SQL Server (Estándar para 8 Cores), Consultoría estándar de implementación de cada uno de los sistemas ofrecidos, soporte y actualización por 2 años y una bolsa de horas (según acuerdo por 2 años) | I26: DATOS Y SISTEMAS DE INFORMACIÓN | J26: 0318 | K26: Activo.En Ejecución | L26: =VLOOKUP(E26,Diccionario!C$2:AC$150,22,0) -> 3323223361 | M26: =VLOOKUP(E26,Diccionario!C$2:AC$150,24,0) -> 45300 | N26: =VLOOKUP(E26,Diccionario!C$2:AC$150,25,0) -> 45473 | O26: =VLOOKUP(E26,Diccionario!C$2:AC$150,26,0) -> 5.7 | P26: =Q26-O26 -> 24.3 | Q26: =DATEDIF(M26,TODAY(),"m") -> 30 | R26: 6 | S26: 0.8 | T26: =T25+0.02 -> 0.44 | W26: =IFERROR(T26*L26,0) -> 1.4622183e+09 | X26: =S26*L26 -> 2.6585787e+09 | Y26: =IFERROR(W26-U26,0) -> 1.4622183e+09 | Z26: =W26-X26 -> -1.1963604e+09 | AA26: =IFERROR(W26/U26,"No se realizó gasto en este corte") -> No se realizó gasto en este corte | AB26: =IFERROR( IF(OR(AA26="",AA26=0), "No calculado", IF(AA26>1,"Costo eficiente: se está gastando menos de lo presupuestado", IF(AA26=1,"Costo según lo presupuestado", "Costo ineficiente: se está gastando más de lo presupuestado"))), "No calculado") -> Costo eficiente: se está gastando menos de lo presupuestado | AC26: =IFERROR(W26/X26,0) -> 0.55 | AD26: =IF(OR(AC26="",AC26=0),"Sin Línea Base", IF(AC26>1,"Proyecto adelantado respecto al cronograma", IF(AC26=1,"Proyecto a tiempo según lo planificado", IF(AC26<1,"Proyecto atrasado con respecto al cronograma", "No calculado")))) -> Proyecto atrasado con respecto al cronograma | AE26: =IFERROR(L26/AA26,0) -> 0 | AF26: =IFERROR(AE26-L26,0) -> -3323223361 | AG26: =VLOOKUP(Indicador!E26,Diccionario!C$1:AC$150,27,0) -> https://growdatasas.sharepoint.com/:x:/r/sites/Gestiondocumental/Administrativa/GD/Financiera/_layouts/15/Doc.aspx?sourcedoc=%7BC3EFE0E2-C211-45B0-905D-ECEF11221767%7D&file=299.%20DEFENSORIA_ERP.xlsm&action=default&mobileredirect=true | AH26: 1 | AI26: 1
A27: 2024 | B27: Junio | C27: 227b8bc1-c7ab-ee11-ba7f-00155d104f2c | D27: 45296.529 | E27: CCD - DPC - IMPLEMENTACIÓN ERP | F27: Johan Sebastian Rodriguez Niño | G27: https://growdatasas.sharepoint.com/sites/pwa/CCD - DPC - IMPLEMENTACIÓN ERP | H27: Suministro e implementación del sistema de información ADMINISTRATIVO ERP NOVASOFT – versión ENTERPRISE WEB y el GESTOR DE RIESGOS para la entidad Defensoría del Pueblo.Incluye: 14 módulos específicos + 5 módulos financieros con licencia para 5000 usuarios finales, Licenciamiento de la Base de Datos SQL Server (Estándar para 8 Cores), Consultoría estándar de implementación de cada uno de los sistemas ofrecidos, soporte y actualización por 2 años y una bolsa de horas (según acuerdo por 2 años) | I27: DATOS Y SISTEMAS DE INFORMACIÓN | J27: 0318 | K27: Activo.En Ejecución | L27: =VLOOKUP(E27,Diccionario!C$2:AC$150,22,0) -> 3323223361 | M27: =VLOOKUP(E27,Diccionario!C$2:AC$150,24,0) -> 45300 | N27: =VLOOKUP(E27,Diccionario!C$2:AC$150,25,0) -> 45473 | O27: =VLOOKUP(E27,Diccionario!C$2:AC$150,26,0) -> 5.7 | P27: =Q27-O27 -> 24.3 | Q27: =DATEDIF(M27,TODAY(),"m") -> 30 | R27: 6 | S27: 1 | T27: =T26+0.02 -> 0.46 | W27: =IFERROR(T27*L27,0) -> 1.5286827e+09 | X27: =S27*L27 -> 3323223361 | Y27: =IFERROR(W27-U27,0) -> 1.5286827e+09 | Z27: =W27-X27 -> -1.7945406e+09 | AA27: =IFERROR(W27/U27,"No se realizó gasto en este corte") -> No se realizó gasto en este corte | AB27: =IFERROR( IF(OR(AA27="",AA27=0), "No calculado", IF(AA27>1,"Costo eficiente: se está gastando menos de lo presupuestado", IF(AA27=1,"Costo según lo presupuestado", "Costo ineficiente: se está gastando más de lo presupuestado"))), "No calculado") -> Costo eficiente: se está gastando menos de lo presupuestado | AC27: =IFERROR(W27/X27,0) -> 0.46 | AD27: =IF(OR(AC27="",AC27=0),"Sin Línea Base", IF(AC27>1,"Proyecto adelantado respecto al cronograma", IF(AC27=1,"Proyecto a tiempo según lo planificado", IF(AC27<1,"Proyecto atrasado con respecto al cronograma", "No calculado")))) -> Proyecto atrasado con respecto al cronograma | AE27: =IFERROR(L27/AA27,0) -> 0 | AF27: =IFERROR(AE27-L27,0) -> -3323223361 | AG27: =VLOOKUP(Indicador!E27,Diccionario!C$1:AC$150,27,0) -> https://growdatasas.sharepoint.com/:x:/r/sites/Gestiondocumental/Administrativa/GD/Financiera/_layouts/15/Doc.aspx?sourcedoc=%7BC3EFE0E2-C211-45B0-905D-ECEF11221767%7D&file=299.%20DEFENSORIA_ERP.xlsm&action=default&mobileredirect=true | AH27: 1 | AI27: 1
A28: 2024 | B28: Julio | C28: 227b8bc1-c7ab-ee11-ba7f-00155d104f2c | D28: 45296.529 | E28: CCD - DPC - IMPLEMENTACIÓN ERP | F28: Johan Sebastian Rodriguez Niño | G28: https://growdatasas.sharepoint.com/sites/pwa/CCD - DPC - IMPLEMENTACIÓN ERP | H28: Suministro e implementación del sistema de información ADMINISTRATIVO ERP NOVASOFT – versión ENTERPRISE WEB y el GESTOR DE RIESGOS para la entidad Defensoría del Pueblo.Incluye: 14 módulos específicos + 5 módulos financieros con licencia para 5000 usuarios finales, Licenciamiento de la Base de Datos SQL Server (Estándar para 8 Cores), Consultoría estándar de implementación de cada uno de los sistemas ofrecidos, soporte y actualización por 2 años y una bolsa de horas (según acuerdo por 2 años) | I28: DATOS Y SISTEMAS DE INFORMACIÓN | J28: 0318 | K28: Activo.En Ejecución | L28: =VLOOKUP(E28,Diccionario!C$2:AC$150,22,0) -> 3323223361 | M28: =VLOOKUP(E28,Diccionario!C$2:AC$150,24,0) -> 45300 | N28: =VLOOKUP(E28,Diccionario!C$2:AC$150,25,0) -> 45473 | O28: =VLOOKUP(E28,Diccionario!C$2:AC$150,26,0) -> 5.7 | P28: =Q28-O28 -> 24.3 | Q28: =DATEDIF(M28,TODAY(),"m") -> 30 | R28: 6 | S28: 1 | T28: =T27+0.02 -> 0.48 | W28: =IFERROR(T28*L28,0) -> 1.5951472e+09 | X28: =S28*L28 -> 3323223361 | Y28: =IFERROR(W28-U28,0) -> 1.5951472e+09 | Z28: =W28-X28 -> -1.7280761e+09 | AA28: =IFERROR(W28/U28,"No se realizó gasto en este corte") -> No se realizó gasto en este corte | AB28: =IFERROR( IF(OR(AA28="",AA28=0), "No calculado", IF(AA28>1,"Costo eficiente: se está gastando menos de lo presupuestado", IF(AA28=1,"Costo según lo presupuestado", "Costo ineficiente: se está gastando más de lo presupuestado"))), "No calculado") -> Costo eficiente: se está gastando menos de lo presupuestado | AC28: =IFERROR(W28/X28,0) -> 0.48 | AD28: =IF(OR(AC28="",AC28=0),"Sin Línea Base", IF(AC28>1,"Proyecto adelantado respecto al cronograma", IF(AC28=1,"Proyecto a tiempo según lo planificado", IF(AC28<1,"Proyecto atrasado con respecto al cronograma", "No calculado")))) -> Proyecto atrasado con respecto al cronograma | AE28: =IFERROR(L28/AA28,0) -> 0 | AF28: =IFERROR(AE28-L28,0) -> -3323223361 | AG28: =VLOOKUP(Indicador!E28,Diccionario!C$1:AC$150,27,0) -> https://growdatasas.sharepoint.com/:x:/r/sites/Gestiondocumental/Administrativa/GD/Financiera/_layouts/15/Doc.aspx?sourcedoc=%7BC3EFE0E2-C211-45B0-905D-ECEF11221767%7D&file=299.%20DEFENSORIA_ERP.xlsm&action=default&mobileredirect=true | AH28: 1 | AI28: 1
A29: 2024 | B29: Agosto | C29: 227b8bc1-c7ab-ee11-ba7f-00155d104f2c | D29: 45296.529 | E29: CCD - DPC - IMPLEMENTACIÓN ERP | F29: Johan Sebastian Rodriguez Niño | G29: https://growdatasas.sharepoint.com/sites/pwa/CCD - DPC - IMPLEMENTACIÓN ERP | H29: Suministro e implementación del sistema de información ADMINISTRATIVO ERP NOVASOFT – versión ENTERPRISE WEB y el GESTOR DE RIESGOS para la entidad Defensoría del Pueblo.Incluye: 14 módulos específicos + 5 módulos financieros con licencia para 5000 usuarios finales, Licenciamiento de la Base de Datos SQL Server (Estándar para 8 Cores), Consultoría estándar de implementación de cada uno de los sistemas ofrecidos, soporte y actualización por 2 años y una bolsa de horas (según acuerdo por 2 años) | I29: DATOS Y SISTEMAS DE INFORMACIÓN | J29: 0318 | K29: Activo.En Ejecución | L29: =VLOOKUP(E29,Diccionario!C$2:AC$150,22,0) -> 3323223361 | M29: =VLOOKUP(E29,Diccionario!C$2:AC$150,24,0) -> 45300 | N29: =VLOOKUP(E29,Diccionario!C$2:AC$150,25,0) -> 45473 | O29: =VLOOKUP(E29,Diccionario!C$2:AC$150,26,0) -> 5.7 | P29: =Q29-O29 -> 24.3 | Q29: =DATEDIF(M29,TODAY(),"m") -> 30 | R29: 6 | S29: 1 | T29: =T28+0.02 -> 0.5 | W29: =IFERROR(T29*L29,0) -> 1.6616117e+09 | X29: =S29*L29 -> 3323223361 | Y29: =IFERROR(W29-U29,0) -> 1.6616117e+09 | Z29: =W29-X29 -> -1.6616117e+09 | AA29: =IFERROR(W29/U29,"No se realizó gasto en este corte") -> No se realizó gasto en este corte | AB29: =IFERROR( IF(OR(AA29="",AA29=0), "No calculado", IF(AA29>1,"Costo eficiente: se está gastando menos de lo presupuestado", IF(AA29=1,"Costo según lo presupuestado", "Costo ineficiente: se está gastando más de lo presupuestado"))), "No calculado") -> Costo eficiente: se está gastando menos de lo presupuestado | AC29: =IFERROR(W29/X29,0) -> 0.5 | AD29: =IF(OR(AC29="",AC29=0),"Sin Línea Base", IF(AC29>1,"Proyecto adelantado respecto al cronograma", IF(AC29=1,"Proyecto a tiempo según lo planificado", IF(AC29<1,"Proyecto atrasado con respecto al cronograma", "No calculado")))) -> Proyecto atrasado con respecto al cronograma | AE29: =IFERROR(L29/AA29,0) -> 0 | AF29: =IFERROR(AE29-L29,0) -> -3323223361 | AG29: =VLOOKUP(Indicador!E29,Diccionario!C$1:AC$150,27,0) -> https://growdatasas.sharepoint.com/:x:/r/sites/Gestiondocumental/Administrativa/GD/Financiera/_layouts/15/Doc.aspx?sourcedoc=%7BC3EFE0E2-C211-45B0-905D-ECEF11221767%7D&file=299.%20DEFENSORIA_ERP.xlsm&action=default&mobileredirect=true | AH29: 1 | AI29: 1
A30: 2024 | B30: Septiembre | C30: 227b8bc1-c7ab-ee11-ba7f-00155d104f2c | D30: 45296.529 | E30: CCD - DPC - IMPLEMENTACIÓN ERP | F30: Johan Sebastian Rodriguez Niño | G30: https://growdatasas.sharepoint.com/sites/pwa/CCD - DPC - IMPLEMENTACIÓN ERP | H30: Suministro e implementación del sistema de información ADMINISTRATIVO ERP NOVASOFT – versión ENTERPRISE WEB y el GESTOR DE RIESGOS para la entidad Defensoría del Pueblo.Incluye: 14 módulos específicos + 5 módulos financieros con licencia para 5000 usuarios finales, Licenciamiento de la Base de Datos SQL Server (Estándar para 8 Cores), Consultoría estándar de implementación de cada uno de los sistemas ofrecidos, soporte y actualización por 2 años y una bolsa de horas (según acuerdo por 2 años) | I30: DATOS Y SISTEMAS DE INFORMACIÓN | J30: 0318 | K30: Activo.En Ejecución | L30: =VLOOKUP(E30,Diccionario!C$2:AC$150,22,0) -> 3323223361 | M30: =VLOOKUP(E30,Diccionario!C$2:AC$150,24,0) -> 45300 | N30: =VLOOKUP(E30,Diccionario!C$2:AC$150,25,0) -> 45473 | O30: =VLOOKUP(E30,Diccionario!C$2:AC$150,26,0) -> 5.7 | P30: =Q30-O30 -> 24.3 | Q30: =DATEDIF(M30,TODAY(),"m") -> 30 | R30: 6 | S30: 1 | T30: =T29+0.02 -> 0.52 | W30: =IFERROR(T30*L30,0) -> 1.7280761e+09 | X30: =S30*L30 -> 3323223361 | Y30: =IFERROR(W30-U30,0) -> 1.7280761e+09 | Z30: =W30-X30 -> -1.5951472e+09 | AA30: =IFERROR(W30/U30,"No se realizó gasto en este corte") -> No se realizó gasto en este corte | AB30: =IFERROR( IF(OR(AA30="",AA30=0), "No calculado", IF(AA30>1,"Costo eficiente: se está gastando menos de lo presupuestado", IF(AA30=1,"Costo según lo presupuestado", "Costo ineficiente: se está gastando más de lo presupuestado"))), "No calculado") -> Costo eficiente: se está gastando menos de lo presupuestado | AC30: =IFERROR(W30/X30,0) -> 0.52 | AD30: =IF(OR(AC30="",AC30=0),"Sin Línea Base", IF(AC30>1,"Proyecto adelantado respecto al cronograma", IF(AC30=1,"Proyecto a tiempo según lo planificado", IF(AC30<1,"Proyecto atrasado con respecto al cronograma", "No calculado")))) -> Proyecto atrasado con respecto al cronograma | AE30: =IFERROR(L30/AA30,0) -> 0 | AF30: =IFERROR(AE30-L30,0) -> -3323223361 | AG30: =VLOOKUP(Indicador!E30,Diccionario!C$1:AC$150,27,0) -> https://growdatasas.sharepoint.com/:x:/r/sites/Gestiondocumental/Administrativa/GD/Financiera/_layouts/15/Doc.aspx?sourcedoc=%7BC3EFE0E2-C211-45B0-905D-ECEF11221767%7D&file=299.%20DEFENSORIA_ERP.xlsm&action=default&mobileredirect=true | AH30: 1 | AI30: 1
A31: 2024 | B31: Octubre | C31: 227b8bc1-c7ab-ee11-ba7f-00155d104f2c | D31: 45296.529 | E31: CCD - DPC - IMPLEMENTACIÓN ERP | F31: Johan Sebastian Rodriguez Niño | G31: https://growdatasas.sharepoint.com/sites/pwa/CCD - DPC - IMPLEMENTACIÓN ERP | H31: Suministro e implementación del sistema de información ADMINISTRATIVO ERP NOVASOFT – versión ENTERPRISE WEB y el GESTOR DE RIESGOS para la entidad Defensoría del Pueblo.Incluye: 14 módulos específicos + 5 módulos financieros con licencia para 5000 usuarios finales, Licenciamiento de la Base de Datos SQL Server (Estándar para 8 Cores), Consultoría estándar de implementación de cada uno de los sistemas ofrecidos, soporte y actualización por 2 años y una bolsa de horas (según acuerdo por 2 años) | I31: DATOS Y SISTEMAS DE INFORMACIÓN | J31: 0318 | K31: Activo.En Ejecución | L31: =VLOOKUP(E31,Diccionario!C$2:AC$150,22,0) -> 3323223361 | M31: =VLOOKUP(E31,Diccionario!C$2:AC$150,24,0) -> 45300 | N31: =VLOOKUP(E31,Diccionario!C$2:AC$150,25,0) -> 45473 | O31: =VLOOKUP(E31,Diccionario!C$2:AC$150,26,0) -> 5.7 | P31: =Q31-O31 -> 24.3 | Q31: =DATEDIF(M31,TODAY(),"m") -> 30 | R31: 6 | S31: 1 | T31: =T30+0.02 -> 0.54 | W31: =IFERROR(T31*L31,0) -> 1.7945406e+09 | X31: =S31*L31 -> 3323223361 | Y31: =IFERROR(W31-U31,0) -> 1.7945406e+09 | Z31: =W31-X31 -> -1.5286827e+09 | AA31: =IFERROR(W31/U31,"No se realizó gasto en este corte") -> No se realizó gasto en este corte | AB31: =IFERROR( IF(OR(AA31="",AA31=0), "No calculado", IF(AA31>1,"Costo eficiente: se está gastando menos de lo presupuestado", IF(AA31=1,"Costo según lo presupuestado", "Costo ineficiente: se está gastando más de lo presupuestado"))), "No calculado") -> Costo eficiente: se está gastando menos de lo presupuestado | AC31: =IFERROR(W31/X31,0) -> 0.54 | AD31: =IF(OR(AC31="",AC31=0),"Sin Línea Base", IF(AC31>1,"Proyecto adelantado respecto al cronograma", IF(AC31=1,"Proyecto a tiempo según lo planificado", IF(AC31<1,"Proyecto atrasado con respecto al cronograma", "No calculado")))) -> Proyecto atrasado con respecto al cronograma | AE31: =IFERROR(L31/AA31,0) -> 0 | AF31: =IFERROR(AE31-L31,0) -> -3323223361 | AG31: =VLOOKUP(Indicador!E31,Diccionario!C$1:AC$150,27,0) -> https://growdatasas.sharepoint.com/:x:/r/sites/Gestiondocumental/Administrativa/GD/Financiera/_layouts/15/Doc.aspx?sourcedoc=%7BC3EFE0E2-C211-45B0-905D-ECEF11221767%7D&file=299.%20DEFENSORIA_ERP.xlsm&action=default&mobileredirect=true | AH31: 1 | AI31: 1
A32: 2024 | B32: Noviembre | C32: 227b8bc1-c7ab-ee11-ba7f-00155d104f2c | D32: 45296.529 | E32: CCD - DPC - IMPLEMENTACIÓN ERP | F32: Johan Sebastian Rodriguez Niño | G32: https://growdatasas.sharepoint.com/sites/pwa/CCD - DPC - IMPLEMENTACIÓN ERP | H32: Suministro e implementación del sistema de información ADMINISTRATIVO ERP NOVASOFT – versión ENTERPRISE WEB y el GESTOR DE RIESGOS para la entidad Defensoría del Pueblo.Incluye: 14 módulos específicos + 5 módulos financieros con licencia para 5000 usuarios finales, Licenciamiento de la Base de Datos SQL Server (Estándar para 8 Cores), Consultoría estándar de implementación de cada uno de los sistemas ofrecidos, soporte y actualización por 2 años y una bolsa de horas (según acuerdo por 2 años) | I32: DATOS Y SISTEMAS DE INFORMACIÓN | J32: 0318 | K32: Activo.En Ejecución | L32: =VLOOKUP(E32,Diccionario!C$2:AC$150,22,0) -> 3323223361 | M32: =VLOOKUP(E32,Diccionario!C$2:AC$150,24,0) -> 45300 | N32: =VLOOKUP(E32,Diccionario!C$2:AC$150,25,0) -> 45473 | O32: =VLOOKUP(E32,Diccionario!C$2:AC$150,26,0) -> 5.7 | P32: =Q32-O32 -> 24.3 | Q32: =DATEDIF(M32,TODAY(),"m") -> 30 | R32: 6 | S32: 1 | T32: =T31+0.02 -> 0.56 | W32: =IFERROR(T32*L32,0) -> 1.8610051e+09 | X32: =S32*L32 -> 3323223361 | Y32: =IFERROR(W32-U32,0) -> 1.8610051e+09 | Z32: =W32-X32 -> -1.4622183e+09 | AA32: =IFERROR(W32/U32,"No se realizó gasto en este corte") -> No se realizó gasto en este corte | AB32: =IFERROR( IF(OR(AA32="",AA32=0), "No calculado", IF(AA32>1,"Costo eficiente: se está gastando menos de lo presupuestado", IF(AA32=1,"Costo según lo presupuestado", "Costo ineficiente: se está gastando más de lo presupuestado"))), "No calculado") -> Costo eficiente: se está gastando menos de lo presupuestado | AC32: =IFERROR(W32/X32,0) -> 0.56 | AD32: =IF(OR(AC32="",AC32=0),"Sin Línea Base", IF(AC32>1,"Proyecto adelantado respecto al cronograma", IF(AC32=1,"Proyecto a tiempo según lo planificado", IF(AC32<1,"Proyecto atrasado con respecto al cronograma", "No calculado")))) -> Proyecto atrasado con respecto al cronograma | AE32: =IFERROR(L32/AA32,0) -> 0 | AF32: =IFERROR(AE32-L32,0) -> -3323223361 | AG32: =VLOOKUP(Indicador!E32,Diccionario!C$1:AC$150,27,0) -> https://growdatasas.sharepoint.com/:x:/r/sites/Gestiondocumental/Administrativa/GD/Financiera/_layouts/15/Doc.aspx?sourcedoc=%7BC3EFE0E2-C211-45B0-905D-ECEF11221767%7D&file=299.%20DEFENSORIA_ERP.xlsm&action=default&mobileredirect=true | AH32: 1 | AI32: 1
A33: 2024 | B33: Diciembre | C33: 227b8bc1-c7ab-ee11-ba7f-00155d104f2c | D33: 45296.529 | E33: CCD - DPC - IMPLEMENTACIÓN ERP | F33: Johan Sebastian Rodriguez Niño | G33: https://growdatasas.sharepoint.com/sites/pwa/CCD - DPC - IMPLEMENTACIÓN ERP | H33: Suministro e implementación del sistema de información ADMINISTRATIVO ERP NOVASOFT – versión ENTERPRISE WEB y el GESTOR DE RIESGOS para la entidad Defensoría del Pueblo.Incluye: 14 módulos específicos + 5 módulos financieros con licencia para 5000 usuarios finales, Licenciamiento de la Base de Datos SQL Server (Estándar para 8 Cores), Consultoría estándar de implementación de cada uno de los sistemas ofrecidos, soporte y actualización por 2 años y una bolsa de horas (según acuerdo por 2 años) | I33: DATOS Y SISTEMAS DE INFORMACIÓN | J33: 0318 | K33: Activo.En Ejecución | L33: =VLOOKUP(E33,Diccionario!C$2:AC$150,22,0) -> 3323223361 | M33: =VLOOKUP(E33,Diccionario!C$2:AC$150,24,0) -> 45300 | N33: =VLOOKUP(E33,Diccionario!C$2:AC$150,25,0) -> 45473 | O33: =VLOOKUP(E33,Diccionario!C$2:AC$150,26,0) -> 5.7 | P33: =Q33-O33 -> 24.3 | Q33: =DATEDIF(M33,TODAY(),"m") -> 30 | R33: 6 | S33: 1 | T33: =T32+0.02 -> 0.58 | W33: =IFERROR(T33*L33,0) -> 1.9274695e+09 | X33: =S33*L33 -> 3323223361 | Y33: =IFERROR(W33-U33,0) -> 1.9274695e+09 | Z33: =W33-X33 -> -1.3957538e+09 | AA33: =IFERROR(W33/U33,"No se realizó gasto en este corte") -> No se realizó gasto en este corte | AB33: =IFERROR( IF(OR(AA33="",AA33=0), "No calculado", IF(AA33>1,"Costo eficiente: se está gastando menos de lo presupuestado", IF(AA33=1,"Costo según lo presupuestado", "Costo ineficiente: se está gastando más de lo presupuestado"))), "No calculado") -> Costo eficiente: se está gastando menos de lo presupuestado | AC33: =IFERROR(W33/X33,0) -> 0.58 | AD33: =IF(OR(AC33="",AC33=0),"Sin Línea Base", IF(AC33>1,"Proyecto adelantado respecto al cronograma", IF(AC33=1,"Proyecto a tiempo según lo planificado", IF(AC33<1,"Proyecto atrasado con respecto al cronograma", "No calculado")))) -> Proyecto atrasado con respecto al cronograma | AE33: =IFERROR(L33/AA33,0) -> 0 | AF33: =IFERROR(AE33-L33,0) -> -3323223361 | AG33: =VLOOKUP(Indicador!E33,Diccionario!C$1:AC$150,27,0) -> https://growdatasas.sharepoint.com/:x:/r/sites/Gestiondocumental/Administrativa/GD/Financiera/_layouts/15/Doc.aspx?sourcedoc=%7BC3EFE0E2-C211-45B0-905D-ECEF11221767%7D&file=299.%20DEFENSORIA_ERP.xlsm&action=default&mobileredirect=true | AH33: 1 | AI33: 1
A34: 2025 | B34: Enero | C34: 227b8bc1-c7ab-ee11-ba7f-00155d104f2c | D34: 45296.529 | E34: CCD - DPC - IMPLEMENTACIÓN ERP | F34: Johan Sebastian Rodriguez Niño | G34: https://growdatasas.sharepoint.com/sites/pwa/CCD - DPC - IMPLEMENTACIÓN ERP | H34: Suministro e implementación del sistema de información ADMINISTRATIVO ERP NOVASOFT – versión ENTERPRISE WEB y el GESTOR DE RIESGOS para la entidad Defensoría del Pueblo.Incluye: 14 módulos específicos + 5 módulos financieros con licencia para 5000 usuarios finales, Licenciamiento de la Base de Datos SQL Server (Estándar para 8 Cores), Consultoría estándar de implementación de cada uno de los sistemas ofrecidos, soporte y actualización por 2 años y una bolsa de horas (según acuerdo por 2 años) | I34: DATOS Y SISTEMAS DE INFORMACIÓN | J34: 0318 | K34: Activo.En Ejecución | L34: =VLOOKUP(E34,Diccionario!C$2:AC$150,22,0) -> 3323223361 | M34: =VLOOKUP(E34,Diccionario!C$2:AC$150,24,0) -> 45300 | N34: =VLOOKUP(E34,Diccionario!C$2:AC$150,25,0) -> 45473 | O34: =VLOOKUP(E34,Diccionario!C$2:AC$150,26,0) -> 5.7 | P34: =Q34-O34 -> 24.3 | Q34: =DATEDIF(M34,TODAY(),"m") -> 30 | R34: 6 | S34: 1 | T34: =T33+0.02 -> 0.6 | W34: =IFERROR(T34*L34,0) -> 1.993934e+09 | X34: =S34*L34 -> 3323223361 | Y34: =IFERROR(W34-U34,0) -> 1.993934e+09 | Z34: =W34-X34 -> -1.3292893e+09 | AA34: =IFERROR(W34/U34,"No se realizó gasto en este corte") -> No se realizó gasto en este corte | AB34: =IFERROR( IF(OR(AA34="",AA34=0), "No calculado", IF(AA34>1,"Costo eficiente: se está gastando menos de lo presupuestado", IF(AA34=1,"Costo según lo presupuestado", "Costo ineficiente: se está gastando más de lo presupuestado"))), "No calculado") -> Costo eficiente: se está gastando menos de lo presupuestado | AC34: =IFERROR(W34/X34,0) -> 0.6 | AD34: =IF(OR(AC34="",AC34=0),"Sin Línea Base", IF(AC34>1,"Proyecto adelantado respecto al cronograma", IF(AC34=1,"Proyecto a tiempo según lo planificado", IF(AC34<1,"Proyecto atrasado con respecto al cronograma", "No calculado")))) -> Proyecto atrasado con respecto al cronograma | AE34: =IFERROR(L34/AA34,0) -> 0 | AF34: =IFERROR(AE34-L34,0) -> -3323223361 | AG34: =VLOOKUP(Indicador!E34,Diccionario!C$1:AC$150,27,0) -> https://growdatasas.sharepoint.com/:x:/r/sites/Gestiondocumental/Administrativa/GD/Financiera/_layouts/15/Doc.aspx?sourcedoc=%7BC3EFE0E2-C211-45B0-905D-ECEF11221767%7D&file=299.%20DEFENSORIA_ERP.xlsm&action=default&mobileredirect=true | AH34: 1 | AI34: 1
A35: 2025 | B35: Febrero | C35: 227b8bc1-c7ab-ee11-ba7f-00155d104f2c | D35: 45296.529 | E35: CCD - DPC - IMPLEMENTACIÓN ERP | F35: Johan Sebastian Rodriguez Niño | G35: https://growdatasas.sharepoint.com/sites/pwa/CCD - DPC - IMPLEMENTACIÓN ERP | H35: Suministro e implementación del sistema de información ADMINISTRATIVO ERP NOVASOFT – versión ENTERPRISE WEB y el GESTOR DE RIESGOS para la entidad Defensoría del Pueblo.Incluye: 14 módulos específicos + 5 módulos financieros con licencia para 5000 usuarios finales, Licenciamiento de la Base de Datos SQL Server (Estándar para 8 Cores), Consultoría estándar de implementación de cada uno de los sistemas ofrecidos, soporte y actualización por 2 años y una bolsa de horas (según acuerdo por 2 años) | I35: DATOS Y SISTEMAS DE INFORMACIÓN | J35: 0318 | K35: Activo.En Ejecución | L35: =VLOOKUP(E35,Diccionario!C$2:AC$150,22,0) -> 3323223361 | M35: =VLOOKUP(E35,Diccionario!C$2:AC$150,24,0) -> 45300 | N35: =VLOOKUP(E35,Diccionario!C$2:AC$150,25,0) -> 45473 | O35: =VLOOKUP(E35,Diccionario!C$2:AC$150,26,0) -> 5.7 | P35: =Q35-O35 -> 24.3 | Q35: =DATEDIF(M35,TODAY(),"m") -> 30 | R35: 6 | S35: 1 | T35: =T34+0.02 -> 0.62 | W35: =IFERROR(T35*L35,0) -> 2.0603985e+09 | X35: =S35*L35 -> 3323223361 | Y35: =IFERROR(W35-U35,0) -> 2.0603985e+09 | Z35: =W35-X35 -> -1.2628249e+09 | AA35: =IFERROR(W35/U35,"No se realizó gasto en este corte") -> No se realizó gasto en este corte | AB35: =IFERROR( IF(OR(AA35="",AA35=0), "No calculado", IF(AA35>1,"Costo eficiente: se está gastando menos de lo presupuestado", IF(AA35=1,"Costo según lo presupuestado", "Costo ineficiente: se está gastando más de lo presupuestado"))), "No calculado") -> Costo eficiente: se está gastando menos de lo presupuestado | AC35: =IFERROR(W35/X35,0) -> 0.62 | AD35: =IF(OR(AC35="",AC35=0),"Sin Línea Base", IF(AC35>1,"Proyecto adelantado respecto al cronograma", IF(AC35=1,"Proyecto a tiempo según lo planificado", IF(AC35<1,"Proyecto atrasado con respecto al cronograma", "No calculado")))) -> Proyecto atrasado con respecto al cronograma | AE35: =IFERROR(L35/AA35,0) -> 0 | AF35: =IFERROR(AE35-L35,0) -> -3323223361 | AG35: =VLOOKUP(Indicador!E35,Diccionario!C$1:AC$150,27,0) -> https://growdatasas.sharepoint.com/:x:/r/sites/Gestiondocumental/Administrativa/GD/Financiera/_layouts/15/Doc.aspx?sourcedoc=%7BC3EFE0E2-C211-45B0-905D-ECEF11221767%7D&file=299.%20DEFENSORIA_ERP.xlsm&action=default&mobileredirect=true | AH35: 1 | AI35: 1
A36: 2025 | B36: Marzo | C36: 227b8bc1-c7ab-ee11-ba7f-00155d104f2c | D36: 45296.529 | E36: CCD - DPC - IMPLEMENTACIÓN ERP | F36: Johan Sebastian Rodriguez Niño | G36: https://growdatasas.sharepoint.com/sites/pwa/CCD - DPC - IMPLEMENTACIÓN ERP | H36: Suministro e implementación del sistema de información ADMINISTRATIVO ERP NOVASOFT – versión ENTERPRISE WEB y el GESTOR DE RIESGOS para la entidad Defensoría del Pueblo.Incluye: 14 módulos específicos + 5 módulos financieros con licencia para 5000 usuarios finales, Licenciamiento de la Base de Datos SQL Server (Estándar para 8 Cores), Consultoría estándar de implementación de cada uno de los sistemas ofrecidos, soporte y actualización por 2 años y una bolsa de horas (según acuerdo por 2 años) | I36: DATOS Y SISTEMAS DE INFORMACIÓN | J36: 0318 | K36: Activo.En Ejecución | L36: =VLOOKUP(E36,Diccionario!C$2:AC$150,22,0) -> 3323223361 | M36: =VLOOKUP(E36,Diccionario!C$2:AC$150,24,0) -> 45300 | N36: =VLOOKUP(E36,Diccionario!C$2:AC$150,25,0) -> 45473 | O36: =VLOOKUP(E36,Diccionario!C$2:AC$150,26,0) -> 5.7 | P36: =Q36-O36 -> 24.3 | Q36: =DATEDIF(M36,TODAY(),"m") -> 30 | R36: 6 | S36: 1 | T36: =T35+0.02 -> 0.64 | W36: =IFERROR(T36*L36,0) -> 2.126863e+09 | X36: =S36*L36 -> 3323223361 | Y36: =IFERROR(W36-U36,0) -> 2.126863e+09 | Z36: =W36-X36 -> -1.1963604e+09 | AA36: =IFERROR(W36/U36,"No se realizó gasto en este corte") -> No se realizó gasto en este corte | AB36: =IFERROR( IF(OR(AA36="",AA36=0), "No calculado", IF(AA36>1,"Costo eficiente: se está gastando menos de lo presupuestado", IF(AA36=1,"Costo según lo presupuestado", "Costo ineficiente: se está gastando más de lo presupuestado"))), "No calculado") -> Costo eficiente: se está gastando menos de lo presupuestado | AC36: =IFERROR(W36/X36,0) -> 0.64 | AD36: =IF(OR(AC36="",AC36=0),"Sin Línea Base", IF(AC36>1,"Proyecto adelantado respecto al cronograma", IF(AC36=1,"Proyecto a tiempo según lo planificado", IF(AC36<1,"Proyecto atrasado con respecto al cronograma", "No calculado")))) -> Proyecto atrasado con respecto al cronograma | AE36: =IFERROR(L36/AA36,0) -> 0 | AF36: =IFERROR(AE36-L36,0) -> -3323223361 | AG36: =VLOOKUP(Indicador!E36,Diccionario!C$1:AC$150,27,0) -> https://growdatasas.sharepoint.com/:x:/r/sites/Gestiondocumental/Administrativa/GD/Financiera/_layouts/15/Doc.aspx?sourcedoc=%7BC3EFE0E2-C211-45B0-905D-ECEF11221767%7D&file=299.%20DEFENSORIA_ERP.xlsm&action=default&mobileredirect=true | AH36: 1 | AI36: 1
... A47: 2026 | B47: Febrero | C47: 227b8bc1-c7ab-ee11-ba7f-00155d104f2c | D47: 45296.529 | E47: CCD - DPC - IMPLEMENTACIÓN ERP | F47: Johan Sebastian Rodriguez Niño | G47: https://growdatasas.sharepoint.com/sites/pwa/CCD - DPC - IMPLEMENTACIÓN ERP | H47: Suministro e implementación del sistema de información ADMINISTRATIVO ERP NOVASOFT – versión ENTERPRISE WEB y el GESTOR DE RIESGOS para la entidad Defensoría del Pueblo.Incluye: 14 módulos específicos + 5 módulos financieros con licencia para 5000 usuarios finales, Licenciamiento de la Base de Datos SQL Server (Estándar para 8 Cores), Consultoría estándar de implementación de cada uno de los sistemas ofrecidos, soporte y actualización por 2 años y una bolsa de horas (según acuerdo por 2 años) | I47: DATOS Y SISTEMAS DE INFORMACIÓN | J47: 0318 | K47: Activo.En Ejecución | L47: =VLOOKUP(E47,Diccionario!C$2:AC$150,22,0) -> 3323223361 | M47: =VLOOKUP(E47,Diccionario!C$2:AC$150,24,0) -> 45300 | N47: =VLOOKUP(E47,Diccionario!C$2:AC$150,25,0) -> 45473 | O47: =VLOOKUP(E47,Diccionario!C$2:AC$150,26,0) -> 5.7 | P47: =Q47-O47 -> 24.3 | Q47: =DATEDIF(M47,TODAY(),"m") -> 30 | R47: 6 | S47: 1 | T47: =T46+0.02 -> 0.86 | W47: =IFERROR(T47*L47,0) -> 2.8579721e+09 | X47: =S47*L47 -> 3323223361 | Y47: =IFERROR(W47-U47,0) -> 2.8579721e+09 | Z47: =W47-X47 -> -4.6525127e+08 | AA47: =IFERROR(W47/U47,"No se realizó gasto en este corte") -> No se realizó gasto en este corte | AB47: =IFERROR( IF(OR(AA47="",AA47=0), "No calculado", IF(AA47>1,"Costo eficiente: se está gastando menos de lo presupuestado", IF(AA47=1,"Costo según lo presupuestado", "Costo ineficiente: se está gastando más de lo presupuestado"))), "No calculado") -> Costo eficiente: se está gastando menos de lo presupuestado | AC47: =IFERROR(W47/X47,0) -> 0.86 | AD47: =IF(OR(AC47="",AC47=0),"Sin Línea Base", IF(AC47>1,"Proyecto adelantado respecto al cronograma", IF(AC47=1,"Proyecto a tiempo según lo planificado", IF(AC47<1,"Proyecto atrasado con respecto al cronograma", "No calculado")))) -> Proyecto atrasado con respecto al cronograma | AE47: =IFERROR(L47/AA47,0) -> 0 | AF47: =IFERROR(AE47-L47,0) -> -3323223361 | AG47: =VLOOKUP(Indicador!E47,Diccionario!C$1:AC$150,27,0) -> https://growdatasas.sharepoint.com/:x:/r/sites/Gestiondocumental/Administrativa/GD/Financiera/_layouts/15/Doc.aspx?sourcedoc=%7BC3EFE0E2-C211-45B0-905D-ECEF11221767%7D&file=299.%20DEFENSORIA_ERP.xlsm&action=default&mobileredirect=true | AH47: 1 | AI47: 1
A48: 2024 | B48: Enero | C48: becfcaa1-85b4-ee11-871a-00155d105d1e | D48: 45307.653 | E48: TELEFONICA – DPC SALA DE ANALITICA | F48: Guiovanni Andres Serrano Serna | G48: https://growdatasas.sharepoint.com/sites/pwa/TELEFONICA – DPC SALA DE ANALITICA | H48: ​Adecuación de la sala de analítica en dos fases, fase 1 obra civil y remodelación. | I48: TI | J48: 0314 | K48: Postventa | L48: =VLOOKUP(E48,Diccionario!C$2:AC$150,22,0) -> 970233948 | M48: =VLOOKUP(E48,Diccionario!C$2:AC$150,24,0) -> 45306 | N48: =VLOOKUP(E48,Diccionario!C$2:AC$150,25,0) -> 45412 | O48: =VLOOKUP(E48,Diccionario!C$2:AC$150,26,0) -> 3.5 | P48: =Q48-O48 -> -2.5 | Q48: 1 | R48: 4 | S48: 0.2 | T48: 0.2 | U48: 13092805 | V48: 13092805 | W48: =IFERROR(T48*L48,0) -> 1.9404679e+08 | X48: =S48*L48 -> 1.9404679e+08 | Y48: =IFERROR(W48-U48,0) -> 1.8095398e+08 | Z48: =W48-X48 -> 0 | AA48: =IFERROR(W48/U48,"No se realizó gasto en este corte") -> 14.820872 | AB48: =IFERROR( IF(OR(AA48="",AA48=0), "No calculado", IF(AA48>1,"Costo eficiente: se está gastando menos de lo presupuestado", IF(AA48=1,"Costo según lo presupuestado", "Costo ineficiente: se está gastando más de lo presupuestado"))), "No calculado") -> Costo eficiente: se está gastando menos de lo presupuestado | AC48: =IFERROR(W48/X48,0) -> 1 | AD48: =IF(OR(AC48="",AC48=0),"Sin Línea Base", IF(AC48>1,"Proyecto adelantado respecto al cronograma", IF(AC48=1,"Proyecto a tiempo según lo planificado", IF(AC48<1,"Proyecto atrasado con respecto al cronograma", "No calculado")))) -> Proyecto a tiempo según lo planificado | AE48: =IFERROR(L48/AA48,0) -> 65464025 | AF48: =IFERROR(AE48-L48,0) -> -904769923 | AG48: =VLOOKUP(Indicador!E48,Diccionario!C$1:AC$150,27,0) -> https://growdatasas.sharepoint.com/:x:/r/sites/Gestiondocumental/Administrativa/GD/Financiera/_layouts/15/Doc.aspx?sourcedoc=%7B4F9BD6BF-F6F0-4033-84A5-4B5D6077FC32%7D&file=314.%20TELEFONICA%20%E2%80%93%20DPC%20%20SALA%20DE%20ANALITICA.xlsx&action=default&mobileredirect=true | AH48: 1 | AI48: 1
A49: 2024 | B49: Febrero | C49: becfcaa1-85b4-ee11-871a-00155d105d1e | D49: 45307.653 | E49: TELEFONICA – DPC SALA DE ANALITICA | F49: Guiovanni Andres Serrano Serna | G49: https://growdatasas.sharepoint.com/sites/pwa/TELEFONICA – DPC SALA DE ANALITICA | H49: ​Adecuación de la sala de analítica en dos fases, fase 1 obra civil y remodelación. | I49: TI | J49: 0314 | K49: Postventa | L49: =VLOOKUP(E49,Diccionario!C$2:AC$150,22,0) -> 970233948 | M49: =VLOOKUP(E49,Diccionario!C$2:AC$150,24,0) -> 45306 | N49: =VLOOKUP(E49,Diccionario!C$2:AC$150,25,0) -> 45412 | O49: =VLOOKUP(E49,Diccionario!C$2:AC$150,26,0) -> 3.5 | P49: =Q49-O49 -> -1.5 | Q49: 2 | R49: 4 | S49: 0.6 | T49: 0.4 | U49: 28162559 | V49: 28162559 | W49: =IFERROR(T49*L49,0) -> 3.8809358e+08 | X49: =S49*L49 -> 5.8214037e+08 | Y49: =IFERROR(W49-U49,0) -> 3.5993102e+08 | Z49: =W49-X49 -> -1.9404679e+08 | AA49: =IFERROR(W49/U49,"No se realizó gasto en este corte") -> 13.78048 | AB49: =IFERROR( IF(OR(AA49="",AA49=0), "No calculado", IF(AA49>1,"Costo eficiente: se está gastando menos de lo presupuestado", IF(AA49=1,"Costo según lo presupuestado", "Costo ineficiente: se está gastando más de lo presupuestado"))), "No calculado") -> Costo eficiente: se está gastando menos de lo presupuestado | AC49: =IFERROR(W49/X49,0) -> 0.66666667 | AD49: =IF(OR(AC49="",AC49=0),"Sin Línea Base", IF(AC49>1,"Proyecto adelantado respecto al cronograma", IF(AC49=1,"Proyecto a tiempo según lo planificado", IF(AC49<1,"Proyecto atrasado con respecto al cronograma", "No calculado")))) -> Proyecto atrasado con respecto al cronograma | AE49: =IFERROR(L49/AA49,0) -> 70406398 | AF49: =IFERROR(AE49-L49,0) -> -8.9982755e+08 | AG49: =VLOOKUP(Indicador!E49,Diccionario!C$1:AC$150,27,0) -> https://growdatasas.sharepoint.com/:x:/r/sites/Gestiondocumental/Administrativa/GD/Financiera/_layouts/15/Doc.aspx?sourcedoc=%7B4F9BD6BF-F6F0-4033-84A5-4B5D6077FC32%7D&file=314.%20TELEFONICA%20%E2%80%93%20DPC%20%20SALA%20DE%20ANALITICA.xlsx&action=default&mobileredirect=true | AH49: 1 | AI49: 1
A50: 2024 | B50: Marzo | C50: becfcaa1-85b4-ee11-871a-00155d105d1e | D50: 45307.653 | E50: TELEFONICA – DPC SALA DE ANALITICA | F50: Guiovanni Andres Serrano Serna | G50: https://growdatasas.sharepoint.com/sites/pwa/TELEFONICA – DPC SALA DE ANALITICA | H50: ​Adecuación de la sala de analítica en dos fases, fase 1 obra civil y remodelación. | I50: TI | J50: 0314 | K50: Postventa | L50: =VLOOKUP(E50,Diccionario!C$2:AC$150,22,0) -> 970233948 | M50: =VLOOKUP(E50,Diccionario!C$2:AC$150,24,0) -> 45306 | N50: =VLOOKUP(E50,Diccionario!C$2:AC$150,25,0) -> 45412 | O50: =VLOOKUP(E50,Diccionario!C$2:AC$150,26,0) -> 3.5 | P50: =Q50-O50 -> -0.5 | Q50: 3 | R50: 4 | S50: 0.8 | T50: 0.5 | U50: 28162559 | V50: 28162559 | W50: =IFERROR(T50*L50,0) -> 485116974 | X50: =S50*L50 -> 7.7618716e+08 | Y50: =IFERROR(W50-U50,0) -> 456954415 | Z50: =W50-X50 -> -2.9107018e+08 | AA50: =IFERROR(W50/U50,"No se realizó gasto en este corte") -> 17.2256 | AB50: =IFERROR( IF(OR(AA50="",AA50=0), "No calculado", IF(AA50>1,"Costo eficiente: se está gastando menos de lo presupuestado", IF(AA50=1,"Costo según lo presupuestado", "Costo ineficiente: se está gastando más de lo presupuestado"))), "No calculado") -> Costo eficiente: se está gastando menos de lo presupuestado | AC50: =IFERROR(W50/X50,0) -> 0.625 | AD50: =IF(OR(AC50="",AC50=0),"Sin Línea Base", IF(AC50>1,"Proyecto adelantado respecto al cronograma", IF(AC50=1,"Proyecto a tiempo según lo planificado", IF(AC50<1,"Proyecto atrasado con respecto al cronograma", "No calculado")))) -> Proyecto atrasado con respecto al cronograma | AE50: =IFERROR(L50/AA50,0) -> 56325118 | AF50: =IFERROR(AE50-L50,0) -> -913908830 | AG50: =VLOOKUP(Indicador!E50,Diccionario!C$1:AC$150,27,0) -> https://growdatasas.sharepoint.com/:x:/r/sites/Gestiondocumental/Administrativa/GD/Financiera/_layouts/15/Doc.aspx?sourcedoc=%7B4F9BD6BF-F6F0-4033-84A5-4B5D6077FC32%7D&file=314.%20TELEFONICA%20%E2%80%93%20DPC%20%20SALA%20DE%20ANALITICA.xlsx&action=default&mobileredirect=true | AH50: 1 | AI50: 1
A51: 2024 | B51: Abril | C51: becfcaa1-85b4-ee11-871a-00155d105d1e | D51: 45307.653 | E51: TELEFONICA – DPC SALA DE ANALITICA | F51: Guiovanni Andres Serrano Serna | G51: https://growdatasas.sharepoint.com/sites/pwa/TELEFONICA – DPC SALA DE ANALITICA | H51: ​Adecuación de la sala de analítica en dos fases, fase 1 obra civil y remodelación. | I51: TI | J51: 0314 | K51: Postventa | L51: =VLOOKUP(E51,Diccionario!C$2:AC$150,22,0) -> 970233948 | M51: =VLOOKUP(E51,Diccionario!C$2:AC$150,24,0) -> 45306 | N51: =VLOOKUP(E51,Diccionario!C$2:AC$150,25,0) -> 45412 | O51: =VLOOKUP(E51,Diccionario!C$2:AC$150,26,0) -> 3.5 | P51: =Q51-O51 -> 0.5 | Q51: 4 | R51: 4 | S51: 1 | T51: 0.6 | U51: 574605868 | V51: 574605868 | W51: =IFERROR(T51*L51,0) -> 5.8214037e+08 | X51: =S51*L51 -> 970233948 | Y51: =IFERROR(W51-U51,0) -> 7534500.8 | Z51: =W51-X51 -> -3.8809358e+08 | AA51: =IFERROR(W51/U51,"No se realizó gasto en este corte") -> 1.0131125 | AB51: =IFERROR( IF(OR(AA51="",AA51=0), "No calculado", IF(AA51>1,"Costo eficiente: se está gastando menos de lo presupuestado", IF(AA51=1,"Costo según lo presupuestado", "Costo ineficiente: se está gastando más de lo presupuestado"))), "No calculado") -> Costo eficiente: se está gastando menos de lo presupuestado | AC51: =IFERROR(W51/X51,0) -> 0.6 | AD51: =IF(OR(AC51="",AC51=0),"Sin Línea Base", IF(AC51>1,"Proyecto adelantado respecto al cronograma", IF(AC51=1,"Proyecto a tiempo según lo planificado", IF(AC51<1,"Proyecto atrasado con respecto al cronograma", "No calculado")))) -> Proyecto atrasado con respecto al cronograma | AE51: =IFERROR(L51/AA51,0) -> 9.5767645e+08 | AF51: =IFERROR(AE51-L51,0) -> -12557501 | AG51: =VLOOKUP(Indicador!E51,Diccionario!C$1:AC$150,27,0) -> https://growdatasas.sharepoint.com/:x:/r/sites/Gestiondocumental/Administrativa/GD/Financiera/_layouts/15/Doc.aspx?sourcedoc=%7B4F9BD6BF-F6F0-4033-84A5-4B5D6077FC32%7D&file=314.%20TELEFONICA%20%E2%80%93%20DPC%20%20SALA%20DE%20ANALITICA.xlsx&action=default&mobileredirect=true | AH51: 1 | AI51: 1
A52: 2024 | B52: Mayo | C52: becfcaa1-85b4-ee11-871a-00155d105d1e | D52: 45307.653 | E52: TELEFONICA – DPC SALA DE ANALITICA | F52: Guiovanni Andres Serrano Serna | G52: https://growdatasas.sharepoint.com/sites/pwa/TELEFONICA – DPC SALA DE ANALITICA | H52: ​Adecuación de la sala de analítica en dos fases, fase 1 obra civil y remodelación. | I52: TI | J52: 0314 | K52: Postventa | L52: =VLOOKUP(E52,Diccionario!C$2:AC$150,22,0) -> 970233948 | M52: =VLOOKUP(E52,Diccionario!C$2:AC$150,24,0) -> 45306 | N52: =VLOOKUP(E52,Diccionario!C$2:AC$150,25,0) -> 45412 | O52: =VLOOKUP(E52,Diccionario!C$2:AC$150,26,0) -> 3.5 | P52: =Q52-O52 -> 1.5 | Q52: 5 | R52: 4 | S52: 1 | T52: 0.8 | U52: 258032419 | V52: 258032419 | W52: =IFERROR(T52*L52,0) -> 7.7618716e+08 | X52: =S52*L52 -> 970233948 | Y52: =IFERROR(W52-U52,0) -> 5.1815474e+08 | Z52: =W52-X52 -> -1.9404679e+08 | AA52: =IFERROR(W52/U52,"No se realizó gasto en este corte") -> 3.0080994 | AB52: =IFERROR( IF(OR(AA52="",AA52=0), "No calculado", IF(AA52>1,"Costo eficiente: se está gastando menos de lo presupuestado", IF(AA52=1,"Costo según lo presupuestado", "Costo ineficiente: se está gastando más de lo presupuestado"))), "No calculado") -> Costo eficiente: se está gastando menos de lo presupuestado | AC52: =IFERROR(W52/X52,0) -> 0.8 | AD52: =IF(OR(AC52="",AC52=0),"Sin Línea Base", IF(AC52>1,"Proyecto adelantado respecto al cronograma", IF(AC52=1,"Proyecto a tiempo según lo planificado", IF(AC52<1,"Proyecto atrasado con respecto al cronograma", "No calculado")))) -> Proyecto atrasado con respecto al cronograma | AE52: =IFERROR(L52/AA52,0) -> 3.2254052e+08 | AF52: =IFERROR(AE52-L52,0) -> -6.4769342e+08 | AG52: =VLOOKUP(Indicador!E52,Diccionario!C$1:AC$150,27,0) -> https://growdatasas.sharepoint.com/:x:/r/sites/Gestiondocumental/Administrativa/GD/Financiera/_layouts/15/Doc.aspx?sourcedoc=%7B4F9BD6BF-F6F0-4033-84A5-4B5D6077FC32%7D&file=314.%20TELEFONICA%20%E2%80%93%20DPC%20%20SALA%20DE%20ANALITICA.xlsx&action=default&mobileredirect=true | AH52: 1 | AI52: 1
A53: 2024 | B53: Junio | C53: becfcaa1-85b4-ee11-871a-00155d105d1e | D53: 45307.653 | E53: TELEFONICA – DPC SALA DE ANALITICA | F53: Guiovanni Andres Serrano Serna | G53: https://growdatasas.sharepoint.com/sites/pwa/TELEFONICA – DPC SALA DE ANALITICA | H53: ​Adecuación de la sala de analítica en dos fases, fase 1 obra civil y remodelación. | I53: TI | J53: 0314 | K53: Postventa | L53: =VLOOKUP(E53,Diccionario!C$2:AC$150,22,0) -> 970233948 | M53: =VLOOKUP(E53,Diccionario!C$2:AC$150,24,0) -> 45306 | N53: =VLOOKUP(E53,Diccionario!C$2:AC$150,25,0) -> 45412 | O53: =VLOOKUP(E53,Diccionario!C$2:AC$150,26,0) -> 3.5 | P53: =Q53-O53 -> 2.5 | Q53: 6 | R53: 4 | S53: 1 | T53: 1 | U53: 62526580 | V53: 62526580 | W53: =IFERROR(T53*L53,0) -> 970233948 | X53: =S53*L53 -> 970233948 | Y53: =IFERROR(W53-U53,0) -> 907707368 | Z53: =W53-X53 -> 0 | AA53: =IFERROR(W53/U53,"No se realizó gasto en este corte") -> 15.517144 | AB53: =IFERROR( IF(OR(AA53="",AA53=0), "No calculado", IF(AA53>1,"Costo eficiente: se está gastando menos de lo presupuestado", IF(AA53=1,"Costo según lo presupuestado", "Costo ineficiente: se está gastando más de lo presupuestado"))), "No calculado") -> Costo eficiente: se está gastando menos de lo presupuestado | AC53: =IFERROR(W53/X53,0) -> 1 | AD53: =IF(OR(AC53="",AC53=0),"Sin Línea Base", IF(AC53>1,"Proyecto adelantado respecto al cronograma", IF(AC53=1,"Proyecto a tiempo según lo planificado", IF(AC53<1,"Proyecto atrasado con respecto al cronograma", "No calculado")))) -> Proyecto a tiempo según lo planificado | AE53: =IFERROR(L53/AA53,0) -> 62526580 | AF53: =IFERROR(AE53-L53,0) -> -907707368 | AG53: =VLOOKUP(Indicador!E53,Diccionario!C$1:AC$150,27,0) -> https://growdatasas.sharepoint.com/:x:/r/sites/Gestiondocumental/Administrativa/GD/Financiera/_layouts/15/Doc.aspx?sourcedoc=%7B4F9BD6BF-F6F0-4033-84A5-4B5D6077FC32%7D&file=314.%20TELEFONICA%20%E2%80%93%20DPC%20%20SALA%20DE%20ANALITICA.xlsx&action=default&mobileredirect=true | AH53: 1 | AI53: 1
A54: 2024 | B54: Febrero | C54: 3f6c4573-29db-ee11-8860-00155d681010 | D54: 45356.826 | E54: ERT- MT– DISPOSITIVOS IOT Y ANALÍTICA | F54: Mario Andres Pirachican Gil | G54: https://growdatasas.sharepoint.com/sites/pwa/ERT- MT– DISPOSITIVOS IOT Y ANALÍTICA | H54: ​Se propone prestar el servicio de asistencia técnica mediante la recolección, procesamiento y correlación de datos con capacidad de análisis, a través de una plataforma de soluciones basadas en IoT (internet de las cosas), que permita la visualización de indicadores específicos con el objetivo de mejorar la seguridad vial y trazabilidad de recorrido a través de la integración de dispositivos de georreferenciación en vehículos de transporte de carga. | I54: DATOS Y SISTEMAS DE INFORMACIÓN | J54: 0322 | K54: Postventa | L54: =VLOOKUP(E54,Diccionario!C$2:AC$150,22,0) -> 4004446789 | M54: =VLOOKUP(E54,Diccionario!C$2:AC$150,24,0) -> 45345 | N54: =VLOOKUP(E54,Diccionario!C$2:AC$150,25,0) -> 45587 | O54: =VLOOKUP(E54,Diccionario!C$2:AC$150,26,0) -> 7.97 | P54: =Q54-O54 -> -6.97 | Q54: 1 | R54: 8 | S54: 0.1 | T54: 0.09 | U54: 1261863958 | V54: 1261863958 | W54: =IFERROR(T54*L54,0) -> 3.6040021e+08 | X54: =S54*L54 -> 4.0044468e+08 | Y54: =IFERROR(W54-U54,0) -> -9.0146375e+08 | Z54: =W54-X54 -> -40044468 | AA54: =IFERROR(W54/U54,"No se realizó gasto en este corte") -> 0.2856094 | AB54: =IFERROR( IF(OR(AA54="",AA54=0), "No calculado", IF(AA54>1,"Costo eficiente: se está gastando menos de lo presupuestado", IF(AA54=1,"Costo según lo presupuestado", "Costo ineficiente: se está gastando más de lo presupuestado"))), "No calculado") -> Costo ineficiente: se está gastando más de lo presupuestado | AC54: =IFERROR(W54/X54,0) -> 0.9 | AD54: =IF(OR(AC54="",AC54=0),"Sin Línea Base", IF(AC54>1,"Proyecto adelantado respecto al cronograma", IF(AC54=1,"Proyecto a tiempo según lo planificado", IF(AC54<1,"Proyecto atrasado con respecto al cronograma", "No calculado")))) -> Proyecto atrasado con respecto al cronograma | AE54: =IFERROR(L54/AA54,0) -> 1.4020711e+10 | AF54: =IFERROR(AE54-L54,0) -> 1.0016264e+10 | AG54: =VLOOKUP(Indicador!E54,Diccionario!C$1:AC$150,27,0) -> https://growdatasas.sharepoint.com/:x:/r/sites/Gestiondocumental/Administrativa/GD/Financiera/_layouts/15/Doc.aspx?sourcedoc=%7B29DCF375-0847-4DAD-9B9A-9F9E84ABD4DE%7D&file=322.%20MINTRANSPORTE.xlsx&action=default&mobileredirect=true | AH54: 1 | AI54: 1
A55: 2024 | B55: Marzo | C55: 3f6c4573-29db-ee11-8860-00155d681010 | D55: 45356.826 | E55: ERT- MT– DISPOSITIVOS IOT Y ANALÍTICA | F55: Mario Andres Pirachican Gil | G55: https://growdatasas.sharepoint.com/sites/pwa/ERT- MT– DISPOSITIVOS IOT Y ANALÍTICA | H55: ​Se propone prestar el servicio de asistencia técnica mediante la recolección, procesamiento y correlación de datos con capacidad de análisis, a través de una plataforma de soluciones basadas en IoT (internet de las cosas), que permita la visualización de indicadores específicos con el objetivo de mejorar la seguridad vial y trazabilidad de recorrido a través de la integración de dispositivos de georreferenciación en vehículos de transporte de carga. | I55: DATOS Y SISTEMAS DE INFORMACIÓN | J55: 0322 | K55: Postventa | L55: =VLOOKUP(E55,Diccionario!C$2:AC$150,22,0) -> 4004446789 | M55: =VLOOKUP(E55,Diccionario!C$2:AC$150,24,0) -> 45345 | N55: =VLOOKUP(E55,Diccionario!C$2:AC$150,25,0) -> 45587 | O55: =VLOOKUP(E55,Diccionario!C$2:AC$150,26,0) -> 7.97 | P55: =Q55-O55 -> -5.97 | Q55: =Q54+1 -> 2 | R55: 8 | S55: 0.2 | T55: 0.25 | U55: 790679659 | V55: 790679659 | W55: =IFERROR(T55*L55,0) -> 1.0011117e+09 | X55: =S55*L55 -> 8.0088936e+08 | Y55: =IFERROR(W55-U55,0) -> 2.1043204e+08 | Z55: =W55-X55 -> 2.0022234e+08 | AA55: =IFERROR(W55/U55,"No se realizó gasto en este corte") -> 1.2661407 | AB55: =IFERROR( IF(OR(AA55="",AA55=0), "No calculado", IF(AA55>1,"Costo eficiente: se está gastando menos de lo presupuestado", IF(AA55=1,"Costo según lo presupuestado", "Costo ineficiente: se está gastando más de lo presupuestado"))), "No calculado") -> Costo eficiente: se está gastando menos de lo presupuestado | AC55: =IFERROR(W55/X55,0) -> 1.25 | AD55: =IF(OR(AC55="",AC55=0),"Sin Línea Base", IF(AC55>1,"Proyecto adelantado respecto al cronograma", IF(AC55=1,"Proyecto a tiempo según lo planificado", IF(AC55<1,"Proyecto atrasado con respecto al cronograma", "No calculado")))) -> Proyecto adelantado respecto al cronograma | AE55: =IFERROR(L55/AA55,0) -> 3162718636 | AF55: =IFERROR(AE55-L55,0) -> -841728153 | AG55: =VLOOKUP(Indicador!E55,Diccionario!C$1:AC$150,27,0) -> https://growdatasas.sharepoint.com/:x:/r/sites/Gestiondocumental/Administrativa/GD/Financiera/_layouts/15/Doc.aspx?sourcedoc=%7B29DCF375-0847-4DAD-9B9A-9F9E84ABD4DE%7D&file=322.%20MINTRANSPORTE.xlsx&action=default&mobileredirect=true | AH55: 1 | AI55: 1
A56: 2024 | B56: Abril | C56: 3f6c4573-29db-ee11-8860-00155d681010 | D56: 45356.826 | E56: ERT- MT– DISPOSITIVOS IOT Y ANALÍTICA | F56: Mario Andres Pirachican Gil | G56: https://growdatasas.sharepoint.com/sites/pwa/ERT- MT– DISPOSITIVOS IOT Y ANALÍTICA | H56: ​Se propone prestar el servicio de asistencia técnica mediante la recolección, procesamiento y correlación de datos con capacidad de análisis, a través de una plataforma de soluciones basadas en IoT (internet de las cosas), que permita la visualización de indicadores específicos con el objetivo de mejorar la seguridad vial y trazabilidad de recorrido a través de la integración de dispositivos de georreferenciación en vehículos de transporte de carga. | I56: DATOS Y SISTEMAS DE INFORMACIÓN | J56: 0322 | K56: Postventa | L56: =VLOOKUP(E56,Diccionario!C$2:AC$150,22,0) -> 4004446789 | M56: =VLOOKUP(E56,Diccionario!C$2:AC$150,24,0) -> 45345 | N56: =VLOOKUP(E56,Diccionario!C$2:AC$150,25,0) -> 45587 | O56: =VLOOKUP(E56,Diccionario!C$2:AC$150,26,0) -> 7.97 | P56: =Q56-O56 -> -4.97 | Q56: =Q55+1 -> 3 | R56: 8 | S56: 0.3 | T56: 0.3 | U56: 674339043 | V56: 674339043 | W56: =IFERROR(T56*L56,0) -> 1.201334e+09 | X56: =S56*L56 -> 1.201334e+09 | Y56: =IFERROR(W56-U56,0) -> 5.2699499e+08 | Z56: =W56-X56 -> 0 | AA56: =IFERROR(W56/U56,"No se realizó gasto en este corte") -> 1.7814986 | AB56: =IFERROR( IF(OR(AA56="",AA56=0), "No calculado", IF(AA56>1,"Costo eficiente: se está gastando menos de lo presupuestado", IF(AA56=1,"Costo según lo presupuestado", "Costo ineficiente: se está gastando más de lo presupuestado"))), "No calculado") -> Costo eficiente: se está gastando menos de lo presupuestado | AC56: =IFERROR(W56/X56,0) -> 1 | AD56: =IF(OR(AC56="",AC56=0),"Sin Línea Base", IF(AC56>1,"Proyecto adelantado respecto al cronograma", IF(AC56=1,"Proyecto a tiempo según lo planificado", IF(AC56<1,"Proyecto atrasado con respecto al cronograma", "No calculado")))) -> Proyecto a tiempo según lo planificado | AE56: =IFERROR(L56/AA56,0) -> 2247796810 | AF56: =IFERROR(AE56-L56,0) -> -1756649979 | AG56: =VLOOKUP(Indicador!E56,Diccionario!C$1:AC$150,27,0) -> https://growdatasas.sharepoint.com/:x:/r/sites/Gestiondocumental/Administrativa/GD/Financiera/_layouts/15/Doc.aspx?sourcedoc=%7B29DCF375-0847-4DAD-9B9A-9F9E84ABD4DE%7D&file=322.%20MINTRANSPORTE.xlsx&action=default&mobileredirect=true | AH56: 1 | AI56: 1
A57: 2024 | B57: Mayo | C57: 3f6c4573-29db-ee11-8860-00155d681010 | D57: 45356.826 | E57: ERT- MT– DISPOSITIVOS IOT Y ANALÍTICA | F57: Mario Andres Pirachican Gil | G57: https://growdatasas.sharepoint.com/sites/pwa/ERT- MT– DISPOSITIVOS IOT Y ANALÍTICA | H57: ​Se propone prestar el servicio de asistencia técnica mediante la recolección, procesamiento y correlación de datos con capacidad de análisis, a través de una plataforma de soluciones basadas en IoT (internet de las cosas), que permita la visualización de indicadores específicos con el objetivo de mejorar la seguridad vial y trazabilidad de recorrido a través de la integración de dispositivos de georreferenciación en vehículos de transporte de carga. | I57: DATOS Y SISTEMAS DE INFORMACIÓN | J57: 0322 | K57: Postventa | L57: =VLOOKUP(E57,Diccionario!C$2:AC$150,22,0) -> 4004446789 | M57: =VLOOKUP(E57,Diccionario!C$2:AC$150,24,0) -> 45345 | N57: =VLOOKUP(E57,Diccionario!C$2:AC$150,25,0) -> 45587 | O57: =VLOOKUP(E57,Diccionario!C$2:AC$150,26,0) -> 7.97 | P57: =Q57-O57 -> -3.97 | Q57: =Q56+1 -> 4 | R57: 8 | S57: 0.45 | T57: 0.42 | U57: 441657811 | V57: 441657811 | W57: =IFERROR(T57*L57,0) -> 1.6818677e+09 | X57: =S57*L57 -> 1.8020011e+09 | Y57: =IFERROR(W57-U57,0) -> 1.2402098e+09 | Z57: =W57-X57 -> -1.201334e+08 | AA57: =IFERROR(W57/U57,"No se realizó gasto en este corte") -> 3.8080786 | AB57: =IFERROR( IF(OR(AA57="",AA57=0), "No calculado", IF(AA57>1,"Costo eficiente: se está gastando menos de lo presupuestado", IF(AA57=1,"Costo según lo presupuestado", "Costo ineficiente: se está gastando más de lo presupuestado"))), "No calculado") -> Costo eficiente: se está gastando menos de lo presupuestado | AC57: =IFERROR(W57/X57,0) -> 0.93333333 | AD57: =IF(OR(AC57="",AC57=0),"Sin Línea Base", IF(AC57>1,"Proyecto adelantado respecto al cronograma", IF(AC57=1,"Proyecto a tiempo según lo planificado", IF(AC57<1,"Proyecto atrasado con respecto al cronograma", "No calculado")))) -> Proyecto atrasado con respecto al cronograma | AE57: =IFERROR(L57/AA57,0) -> 1.0515662e+09 | AF57: =IFERROR(AE57-L57,0) -> -2.9528806e+09 | AG57: =VLOOKUP(Indicador!E57,Diccionario!C$1:AC$150,27,0) -> https://growdatasas.sharepoint.com/:x:/r/sites/Gestiondocumental/Administrativa/GD/Financiera/_layouts/15/Doc.aspx?sourcedoc=%7B29DCF375-0847-4DAD-9B9A-9F9E84ABD4DE%7D&file=322.%20MINTRANSPORTE.xlsx&action=default&mobileredirect=true | AH57: 1 | AI57: 1
A58: 2024 | B58: Junio | C58: 3f6c4573-29db-ee11-8860-00155d681010 | D58: 45356.826 | E58: ERT- MT– DISPOSITIVOS IOT Y ANALÍTICA | F58: Mario Andres Pirachican Gil | G58: https://growdatasas.sharepoint.com/sites/pwa/ERT- MT– DISPOSITIVOS IOT Y ANALÍTICA | H58: ​Se propone prestar el servicio de asistencia técnica mediante la recolección, procesamiento y correlación de datos con capacidad de análisis, a través de una plataforma de soluciones basadas en IoT (internet de las cosas), que permita la visualización de indicadores específicos con el objetivo de mejorar la seguridad vial y trazabilidad de recorrido a través de la integración de dispositivos de georreferenciación en vehículos de transporte de carga. | I58: DATOS Y SISTEMAS DE INFORMACIÓN | J58: 0322 | K58: Postventa | L58: =VLOOKUP(E58,Diccionario!C$2:AC$150,22,0) -> 4004446789 | M58: =VLOOKUP(E58,Diccionario!C$2:AC$150,24,0) -> 45345 | N58: =VLOOKUP(E58,Diccionario!C$2:AC$150,25,0) -> 45587 | O58: =VLOOKUP(E58,Diccionario!C$2:AC$150,26,0) -> 7.97 | P58: =Q58-O58 -> -2.97 | Q58: =Q57+1 -> 5 | R58: 8 | S58: 0.55 | T58: 0.55 | U58: 208976579 | V58: 208976579 | W58: =IFERROR(T58*L58,0) -> 2.2024457e+09 | X58: =S58*L58 -> 2.2024457e+09 | Y58: =IFERROR(W58-U58,0) -> 1.9934692e+09 | Z58: =W58-X58 -> 0 | AA58: =IFERROR(W58/U58,"No se realizó gasto en este corte") -> 10.539199 | AB58: =IFERROR( IF(OR(AA58="",AA58=0), "No calculado", IF(AA58>1,"Costo eficiente: se está gastando menos de lo presupuestado", IF(AA58=1,"Costo según lo presupuestado", "Costo ineficiente: se está gastando más de lo presupuestado"))), "No calculado") -> Costo eficiente: se está gastando menos de lo presupuestado | AC58: =IFERROR(W58/X58,0) -> 1 | AD58: =IF(OR(AC58="",AC58=0),"Sin Línea Base", IF(AC58>1,"Proyecto adelantado respecto al cronograma", IF(AC58=1,"Proyecto a tiempo según lo planificado", IF(AC58<1,"Proyecto atrasado con respecto al cronograma", "No calculado")))) -> Proyecto a tiempo según lo planificado | AE58: =IFERROR(L58/AA58,0) -> 3.7995742e+08 | AF58: =IFERROR(AE58-L58,0) -> -3.6244894e+09 | AG58: =VLOOKUP(Indicador!E58,Diccionario!C$1:AC$150,27,0) -> https://growdatasas.sharepoint.com/:x:/r/sites/Gestiondocumental/Administrativa/GD/Financiera/_layouts/15/Doc.aspx?sourcedoc=%7B29DCF375-0847-4DAD-9B9A-9F9E84ABD4DE%7D&file=322.%20MINTRANSPORTE.xlsx&action=default&mobileredirect=true | AH58: 1 | AI58: 1
A59: 2024 | B59: Julio | C59: 3f6c4573-29db-ee11-8860-00155d681010 | D59: 45356.826 | E59: ERT- MT– DISPOSITIVOS IOT Y ANALÍTICA | F59: Mario Andres Pirachican Gil | G59: https://growdatasas.sharepoint.com/sites/pwa/ERT- MT– DISPOSITIVOS IOT Y ANALÍTICA | H59: ​Se propone prestar el servicio de asistencia técnica mediante la recolección, procesamiento y correlación de datos con capacidad de análisis, a través de una plataforma de soluciones basadas en IoT (internet de las cosas), que permita la visualización de indicadores específicos con el objetivo de mejorar la seguridad vial y trazabilidad de recorrido a través de la integración de dispositivos de georreferenciación en vehículos de transporte de carga. | I59: DATOS Y SISTEMAS DE INFORMACIÓN | J59: 0322 | K59: Postventa | L59: =VLOOKUP(E59,Diccionario!C$2:AC$150,22,0) -> 4004446789 | M59: =VLOOKUP(E59,Diccionario!C$2:AC$150,24,0) -> 45345 | N59: =VLOOKUP(E59,Diccionario!C$2:AC$150,25,0) -> 45587 | O59: =VLOOKUP(E59,Diccionario!C$2:AC$150,26,0) -> 7.97 | P59: =Q59-O59 -> -1.97 | Q59: =Q58+1 -> 6 | R59: 8 | S59: 0.65 | T59: 0.67 | U59: 208976579 | V59: 208976579 | W59: =IFERROR(T59*L59,0) -> 2.6829793e+09 | X59: =S59*L59 -> 2.6028904e+09 | Y59: =IFERROR(W59-U59,0) -> 2.4740028e+09 | Z59: =W59-X59 -> 80088936 | AA59: =IFERROR(W59/U59,"No se realizó gasto en este corte") -> 12.83866 | AB59: =IFERROR( IF(OR(AA59="",AA59=0), "No calculado", IF(AA59>1,"Costo eficiente: se está gastando menos de lo presupuestado", IF(AA59=1,"Costo según lo presupuestado", "Costo ineficiente: se está gastando más de lo presupuestado"))), "No calculado") -> Costo eficiente: se está gastando menos de lo presupuestado | AC59: =IFERROR(W59/X59,0) -> 1.0307692 | AD59: =IF(OR(AC59="",AC59=0),"Sin Línea Base", IF(AC59>1,"Proyecto adelantado respecto al cronograma", IF(AC59=1,"Proyecto a tiempo según lo planificado", IF(AC59<1,"Proyecto atrasado con respecto al cronograma", "No calculado")))) -> Proyecto adelantado respecto al cronograma | AE59: =IFERROR(L59/AA59,0) -> 3.1190534e+08 | AF59: =IFERROR(AE59-L59,0) -> -3.6925414e+09 | AG59: =VLOOKUP(Indicador!E59,Diccionario!C$1:AC$150,27,0) -> https://growdatasas.sharepoint.com/:x:/r/sites/Gestiondocumental/Administrativa/GD/Financiera/_layouts/15/Doc.aspx?sourcedoc=%7B29DCF375-0847-4DAD-9B9A-9F9E84ABD4DE%7D&file=322.%20MINTRANSPORTE.xlsx&action=default&mobileredirect=true | AH59: 1 | AI59: 1
A60: 2024 | B60: Agosto | C60: 3f6c4573-29db-ee11-8860-00155d681010 | D60: 45356.826 | E60: ERT- MT– DISPOSITIVOS IOT Y ANALÍTICA | F60: Mario Andres Pirachican Gil | G60: https://growdatasas.sharepoint.com/sites/pwa/ERT- MT– DISPOSITIVOS IOT Y ANALÍTICA | H60: ​Se propone prestar el servicio de asistencia técnica mediante la recolección, procesamiento y correlación de datos con capacidad de análisis, a través de una plataforma de soluciones basadas en IoT (internet de las cosas), que permita la visualización de indicadores específicos con el objetivo de mejorar la seguridad vial y trazabilidad de recorrido a través de la integración de dispositivos de georreferenciación en vehículos de transporte de carga. | I60: DATOS Y SISTEMAS DE INFORMACIÓN | J60: 0322 | K60: Postventa | L60: =VLOOKUP(E60,Diccionario!C$2:AC$150,22,0) -> 4004446789 | M60: =VLOOKUP(E60,Diccionario!C$2:AC$150,24,0) -> 45345 | N60: =VLOOKUP(E60,Diccionario!C$2:AC$150,25,0) -> 45587 | O60: =VLOOKUP(E60,Diccionario!C$2:AC$150,26,0) -> 7.97 | P60: =Q60-O60 -> -0.97 | Q60: =Q59+1 -> 7 | R60: 8 | S60: 0.8 | T60: 0.85 | U60: 208976579 | V60: 208976579 | W60: =IFERROR(T60*L60,0) -> 3.4037798e+09 | X60: =S60*L60 -> 3.2035574e+09 | Y60: =IFERROR(W60-U60,0) -> 3.1948032e+09 | Z60: =W60-X60 -> 2.0022234e+08 | AA60: =IFERROR(W60/U60,"No se realizó gasto en este corte") -> 16.287853 | AB60: =IFERROR( IF(OR(AA60="",AA60=0), "No calculado", IF(AA60>1,"Costo eficiente: se está gastando menos de lo presupuestado", IF(AA60=1,"Costo según lo presupuestado", "Costo ineficiente: se está gastando más de lo presupuestado"))), "No calculado") -> Costo eficiente: se está gastando menos de lo presupuestado | AC60: =IFERROR(W60/X60,0) -> 1.0625 | AD60: =IF(OR(AC60="",AC60=0),"Sin Línea Base", IF(AC60>1,"Proyecto adelantado respecto al cronograma", IF(AC60=1,"Proyecto a tiempo según lo planificado", IF(AC60<1,"Proyecto atrasado con respecto al cronograma", "No calculado")))) -> Proyecto adelantado respecto al cronograma | AE60: =IFERROR(L60/AA60,0) -> 2.458548e+08 | AF60: =IFERROR(AE60-L60,0) -> -3.758592e+09 | AG60: =VLOOKUP(Indicador!E60,Diccionario!C$1:AC$150,27,0) -> https://growdatasas.sharepoint.com/:x:/r/sites/Gestiondocumental/Administrativa/GD/Financiera/_layouts/15/Doc.aspx?sourcedoc=%7B29DCF375-0847-4DAD-9B9A-9F9E84ABD4DE%7D&file=322.%20MINTRANSPORTE.xlsx&action=default&mobileredirect=true | AH60: 1 | AI60: 1
A61: 2024 | B61: Septiembre | C61: 3f6c4573-29db-ee11-8860-00155d681010 | D61: 45356.826 | E61: ERT- MT– DISPOSITIVOS IOT Y ANALÍTICA | F61: Mario Andres Pirachican Gil | G61: https://growdatasas.sharepoint.com/sites/pwa/ERT- MT– DISPOSITIVOS IOT Y ANALÍTICA | H61: ​Se propone prestar el servicio de asistencia técnica mediante la recolección, procesamiento y correlación de datos con capacidad de análisis, a través de una plataforma de soluciones basadas en IoT (internet de las cosas), que permita la visualización de indicadores específicos con el objetivo de mejorar la seguridad vial y trazabilidad de recorrido a través de la integración de dispositivos de georreferenciación en vehículos de transporte de carga. | I61: DATOS Y SISTEMAS DE INFORMACIÓN | J61: 0322 | K61: Postventa | L61: =VLOOKUP(E61,Diccionario!C$2:AC$150,22,0) -> 4004446789 | M61: =VLOOKUP(E61,Diccionario!C$2:AC$150,24,0) -> 45345 | N61: =VLOOKUP(E61,Diccionario!C$2:AC$150,25,0) -> 45587 | O61: =VLOOKUP(E61,Diccionario!C$2:AC$150,26,0) -> 7.97 | P61: =Q61-O61 -> 0.03 | Q61: =Q60+1 -> 8 | R61: 8 | S61: 0.9 | T61: 1 | U61: 208976579 | V61: 208976579 | W61: =IFERROR(T61*L61,0) -> 4004446789 | X61: =S61*L61 -> 3.6040021e+09 | Y61: =IFERROR(W61-U61,0) -> 3795470210 | Z61: =W61-X61 -> 4.0044468e+08 | AA61: =IFERROR(W61/U61,"No se realizó gasto en este corte") -> 19.16218 | AB61: =IFERROR( IF(OR(AA61="",AA61=0), "No calculado", IF(AA61>1,"Costo eficiente: se está gastando menos de lo presupuestado", IF(AA61=1,"Costo según lo presupuestado", "Costo ineficiente: se está gastando más de lo presupuestado"))), "No calculado") -> Costo eficiente: se está gastando menos de lo presupuestado | AC61: =IFERROR(W61/X61,0) -> 1.1111111 | AD61: =IF(OR(AC61="",AC61=0),"Sin Línea Base", IF(AC61>1,"Proyecto adelantado respecto al cronograma", IF(AC61=1,"Proyecto a tiempo según lo planificado", IF(AC61<1,"Proyecto atrasado con respecto al cronograma", "No calculado")))) -> Proyecto adelantado respecto al cronograma | AE61: =IFERROR(L61/AA61,0) -> 2.0897658e+08 | AF61: =IFERROR(AE61-L61,0) -> -3795470210 | AG61: =VLOOKUP(Indicador!E61,Diccionario!C$1:AC$150,27,0) -> https://growdatasas.sharepoint.com/:x:/r/sites/Gestiondocumental/Administrativa/GD/Financiera/_layouts/15/Doc.aspx?sourcedoc=%7B29DCF375-0847-4DAD-9B9A-9F9E84ABD4DE%7D&file=322.%20MINTRANSPORTE.xlsx&action=default&mobileredirect=true | AH61: 1 | AI61: 1
A62: 2024 | B62: Marzo | C62: b325f473-91e8-ee11-b9dc-00155d68784b | D62: 45373.887 | E62: RUNT – DISEÑO,IMPLEMENTACION MDM | F62: Leidy Susana Ramirez Herrera | G62: https://growdatasas.sharepoint.com/sites/pwa/RUNT – DISEÑO,IMPLEMENTACION MDM | H62: ​Implementar el modelo de gestión de datos maestros y de referencia a partir del diseño y definición de la estrategia de las capacidades para que permita a la entidad estandarizar y tener una única visión de los datos transversales que se manejan en los diferentes procesos del RUNT. Con el objetivo de asegurar una correcta implementación de la solución de IBM Cloud Pak for Data proponemos la incorporación de una capa de servicios profesionales especializados en la plataforma. Con un alcance de tres registros maestros a saber: Registro Nacional Automotor RNA y el Registro de Personas Jurídicas RNPJ, Registro Nacional de Conductores. | I62: DATOS Y SISTEMAS DE INFORMACIÓN | J62: 0324 | K62: Activo.En Ejecución | L62: =VLOOKUP(E62,Diccionario!C$2:AC$150,22,0) -> 372376516 | M62: =VLOOKUP(E62,Diccionario!C$2:AC$150,24,0) -> 45352 | N62: =VLOOKUP(E62,Diccionario!C$2:AC$150,25,0) -> 45534 | O62: =VLOOKUP(E62,Diccionario!C$2:AC$150,26,0) -> 5.97 | P62: =Q62-O62 -> -4.97 | Q62: 1 | R62: 6 | S62: 0.2 | T62: 0.15 | U62: 110202191 | V62: 110202191 | W62: =IFERROR(T62*L62,0) -> 55856477 | X62: =S62*L62 -> 74475303 | Y62: =IFERROR(W62-U62,0) -> -54345714 | Z62: =W62-X62 -> -18618826 | AA62: =IFERROR(W62/U62,"No se realizó gasto en este corte") -> 0.50685451 | AB62: =IFERROR( IF(OR(AA62="",AA62=0), "No calculado", IF(AA62>1,"Costo eficiente: se está gastando menos de lo presupuestado", IF(AA62=1,"Costo según lo presupuestado", "Costo ineficiente: se está gastando más de lo presupuestado"))), "No calculado") -> Costo ineficiente: se está gastando más de lo presupuestado | AC62: =IFERROR(W62/X62,0) -> 0.75 | AD62: =IF(OR(AC62="",AC62=0),"Sin Línea Base", IF(AC62>1,"Proyecto adelantado respecto al cronograma", IF(AC62=1,"Proyecto a tiempo según lo planificado", IF(AC62<1,"Proyecto atrasado con respecto al cronograma", "No calculado")))) -> Proyecto atrasado con respecto al cronograma | AE62: =IFERROR(L62/AA62,0) -> 7.3468127e+08 | AF62: =IFERROR(AE62-L62,0) -> 3.6230476e+08 | AG62: =VLOOKUP(Indicador!E62,Diccionario!C$1:AC$150,27,0) -> https://growdatasas.sharepoint.com/:x:/r/sites/Gestiondocumental/Administrativa/GD/Financiera/_layouts/15/Doc.aspx?sourcedoc=%7B465AB503-754C-43E2-86C3-8E24183E3BBF%7D&file=090424%20324.%20RUNT%202.0%20-%20RUNT%20MDM.xlsx&action=default&mobileredirect=true | AH62: 1 | AI62: 1
A63: 2024 | B63: Abril | C63: b325f473-91e8-ee11-b9dc-00155d68784b | D63: 45373.887 | E63: RUNT – DISEÑO,IMPLEMENTACION MDM | F63: Leidy Susana Ramirez Herrera | G63: https://growdatasas.sharepoint.com/sites/pwa/RUNT – DISEÑO,IMPLEMENTACION MDM | H63: ​Implementar el modelo de gestión de datos maestros y de referencia a partir del diseño y definición de la estrategia de las capacidades para que permita a la entidad estandarizar y tener una única visión de los datos transversales que se manejan en los diferentes procesos del RUNT. Con el objetivo de asegurar una correcta implementación de la solución de IBM Cloud Pak for Data proponemos la incorporación de una capa de servicios profesionales especializados en la plataforma. Con un alcance de tres registros maestros a saber: Registro Nacional Automotor RNA y el Registro de Personas Jurídicas RNPJ, Registro Nacional de Conductores. | I63: DATOS Y SISTEMAS DE INFORMACIÓN | J63: 0324 | K63: Activo.En Ejecución | L63: =VLOOKUP(E63,Diccionario!C$2:AC$150,22,0) -> 372376516 | M63: =VLOOKUP(E63,Diccionario!C$2:AC$150,24,0) -> 45352 | N63: =VLOOKUP(E63,Diccionario!C$2:AC$150,25,0) -> 45534 | O63: =VLOOKUP(E63,Diccionario!C$2:AC$150,26,0) -> 5.97 | P63: =Q63-O63 -> -3.97 | Q63: 2 | R63: 6 | S63: 0.3 | T63: 0.2 | U63: 13923314 | V63: 13923314 | W63: =IFERROR(T63*L63,0) -> 74475303 | X63: =S63*L63 -> 1.1171295e+08 | Y63: =IFERROR(W63-U63,0) -> 60551989 | Z63: =W63-X63 -> -37237652 | AA63: =IFERROR(W63/U63,"No se realizó gasto en este corte") -> 5.3489638 | AB63: =IFERROR( IF(OR(AA63="",AA63=0), "No calculado", IF(AA63>1,"Costo eficiente: se está gastando menos de lo presupuestado", IF(AA63=1,"Costo según lo presupuestado", "Costo ineficiente: se está gastando más de lo presupuestado"))), "No calculado") -> Costo eficiente: se está gastando menos de lo presupuestado | AC63: =IFERROR(W63/X63,0) -> 0.66666667 | AD63: =IF(OR(AC63="",AC63=0),"Sin Línea Base", IF(AC63>1,"Proyecto adelantado respecto al cronograma", IF(AC63=1,"Proyecto a tiempo según lo planificado", IF(AC63<1,"Proyecto atrasado con respecto al cronograma", "No calculado")))) -> Proyecto atrasado con respecto al cronograma | AE63: =IFERROR(L63/AA63,0) -> 69616570 | AF63: =IFERROR(AE63-L63,0) -> -302759946 | AG63: =VLOOKUP(Indicador!E63,Diccionario!C$1:AC$150,27,0) -> https://growdatasas.sharepoint.com/:x:/r/sites/Gestiondocumental/Administrativa/GD/Financiera/_layouts/15/Doc.aspx?sourcedoc=%7B465AB503-754C-43E2-86C3-8E24183E3BBF%7D&file=090424%20324.%20RUNT%202.0%20-%20RUNT%20MDM.xlsx&action=default&mobileredirect=true | AH63: 1 | AI63: 1
A64: 2024 | B64: Mayo | C64: b325f473-91e8-ee11-b9dc-00155d68784b | D64: 45373.887 | E64: RUNT – DISEÑO,IMPLEMENTACION MDM | F64: Leidy Susana Ramirez Herrera | G64: https://growdatasas.sharepoint.com/sites/pwa/RUNT – DISEÑO,IMPLEMENTACION MDM | H64: ​Implementar el modelo de gestión de datos maestros y de referencia a partir del diseño y definición de la estrategia de las capacidades para que permita a la entidad estandarizar y tener una única visión de los datos transversales que se manejan en los diferentes procesos del RUNT. Con el objetivo de asegurar una correcta implementación de la solución de IBM Cloud Pak for Data proponemos la incorporación de una capa de servicios profesionales especializados en la plataforma. Con un alcance de tres registros maestros a saber: Registro Nacional Automotor RNA y el Registro de Personas Jurídicas RNPJ, Registro Nacional de Conductores. | I64: DATOS Y SISTEMAS DE INFORMACIÓN | J64: 0324 | K64: Activo.En Ejecución | L64: =VLOOKUP(E64,Diccionario!C$2:AC$150,22,0) -> 372376516 | M64: =VLOOKUP(E64,Diccionario!C$2:AC$150,24,0) -> 45352 | N64: =VLOOKUP(E64,Diccionario!C$2:AC$150,25,0) -> 45534 | O64: =VLOOKUP(E64,Diccionario!C$2:AC$150,26,0) -> 5.97 | P64: =Q64-O64 -> -2.97 | Q64: 3 | R64: 6 | S64: 0.5 | T64: 0.4 | U64: 110202191 | V64: 110202191 | W64: =IFERROR(T64*L64,0) -> 1.4895061e+08 | X64: =S64*L64 -> 186188258 | Y64: =IFERROR(W64-U64,0) -> 38748415 | Z64: =W64-X64 -> -37237652 | AA64: =IFERROR(W64/U64,"No se realizó gasto en este corte") -> 1.351612 | AB64: =IFERROR( IF(OR(AA64="",AA64=0), "No calculado", IF(AA64>1,"Costo eficiente: se está gastando menos de lo presupuestado", IF(AA64=1,"Costo según lo presupuestado", "Costo ineficiente: se está gastando más de lo presupuestado"))), "No calculado") -> Costo eficiente: se está gastando menos de lo presupuestado | AC64: =IFERROR(W64/X64,0) -> 0.8 | AD64: =IF(OR(AC64="",AC64=0),"Sin Línea Base", IF(AC64>1,"Proyecto adelantado respecto al cronograma", IF(AC64=1,"Proyecto a tiempo según lo planificado", IF(AC64<1,"Proyecto atrasado con respecto al cronograma", "No calculado")))) -> Proyecto atrasado con respecto al cronograma | AE64: =IFERROR(L64/AA64,0) -> 2.7550548e+08 | AF64: =IFERROR(AE64-L64,0) -> -96871038 | AG64: =VLOOKUP(Indicador!E64,Diccionario!C$1:AC$150,27,0) -> https://growdatasas.sharepoint.com/:x:/r/sites/Gestiondocumental/Administrativa/GD/Financiera/_layouts/15/Doc.aspx?sourcedoc=%7B465AB503-754C-43E2-86C3-8E24183E3BBF%7D&file=090424%20324.%20RUNT%202.0%20-%20RUNT%20MDM.xlsx&action=default&mobileredirect=true | AH64: 1 | AI64: 1
A65: 2024 | B65: Junio | C65: b325f473-91e8-ee11-b9dc-00155d68784b | D65: 45373.887 | E65: RUNT – DISEÑO,IMPLEMENTACION MDM | F65: Leidy Susana Ramirez Herrera | G65: https://growdatasas.sharepoint.com/sites/pwa/RUNT – DISEÑO,IMPLEMENTACION MDM | H65: ​Implementar el modelo de gestión de datos maestros y de referencia a partir del diseño y definición de la estrategia de las capacidades para que permita a la entidad estandarizar y tener una única visión de los datos transversales que se manejan en los diferentes procesos del RUNT. Con el objetivo de asegurar una correcta implementación de la solución de IBM Cloud Pak for Data proponemos la incorporación de una capa de servicios profesionales especializados en la plataforma. Con un alcance de tres registros maestros a saber: Registro Nacional Automotor RNA y el Registro de Personas Jurídicas RNPJ, Registro Nacional de Conductores. | I65: DATOS Y SISTEMAS DE INFORMACIÓN | J65: 0324 | K65: Activo.En Ejecución | L65: =VLOOKUP(E65,Diccionario!C$2:AC$150,22,0) -> 372376516 | M65: =VLOOKUP(E65,Diccionario!C$2:AC$150,24,0) -> 45352 | N65: =VLOOKUP(E65,Diccionario!C$2:AC$150,25,0) -> 45534 | O65: =VLOOKUP(E65,Diccionario!C$2:AC$150,26,0) -> 5.97 | P65: =Q65-O65 -> -1.97 | Q65: 4 | R65: 6 | S65: 0.75 | T65: 0.7 | U65: 13923314 | V65: 13923314 | W65: =IFERROR(T65*L65,0) -> 2.6066356e+08 | X65: =S65*L65 -> 279282387 | Y65: =IFERROR(W65-U65,0) -> 2.4674025e+08 | Z65: =W65-X65 -> -18618826 | AA65: =IFERROR(W65/U65,"No se realizó gasto en este corte") -> 18.721373 | AB65: =IFERROR( IF(OR(AA65="",AA65=0), "No calculado", IF(AA65>1,"Costo eficiente: se está gastando menos de lo presupuestado", IF(AA65=1,"Costo según lo presupuestado", "Costo ineficiente: se está gastando más de lo presupuestado"))), "No calculado") -> Costo eficiente: se está gastando menos de lo presupuestado | AC65: =IFERROR(W65/X65,0) -> 0.93333333 | AD65: =IF(OR(AC65="",AC65=0),"Sin Línea Base", IF(AC65>1,"Proyecto adelantado respecto al cronograma", IF(AC65=1,"Proyecto a tiempo según lo planificado", IF(AC65<1,"Proyecto atrasado con respecto al cronograma", "No calculado")))) -> Proyecto atrasado con respecto al cronograma | AE65: =IFERROR(L65/AA65,0) -> 19890449 | AF65: =IFERROR(AE65-L65,0) -> -3.5248607e+08 | AG65: =VLOOKUP(Indicador!E65,Diccionario!C$1:AC$150,27,0) -> https://growdatasas.sharepoint.com/:x:/r/sites/Gestiondocumental/Administrativa/GD/Financiera/_layouts/15/Doc.aspx?sourcedoc=%7B465AB503-754C-43E2-86C3-8E24183E3BBF%7D&file=090424%20324.%20RUNT%202.0%20-%20RUNT%20MDM.xlsx&action=default&mobileredirect=true | AH65: 1 | AI65: 1
A66: 2024 | B66: Julio | C66: b325f473-91e8-ee11-b9dc-00155d68784b | D66: 45373.887 | E66: RUNT – DISEÑO,IMPLEMENTACION MDM | F66: Leidy Susana Ramirez Herrera | G66: https://growdatasas.sharepoint.com/sites/pwa/RUNT – DISEÑO,IMPLEMENTACION MDM | H66: ​Implementar el modelo de gestión de datos maestros y de referencia a partir del diseño y definición de la estrategia de las capacidades para que permita a la entidad estandarizar y tener una única visión de los datos transversales que se manejan en los diferentes procesos del RUNT. Con el objetivo de asegurar una correcta implementación de la solución de IBM Cloud Pak for Data proponemos la incorporación de una capa de servicios profesionales especializados en la plataforma. Con un alcance de tres registros maestros a saber: Registro Nacional Automotor RNA y el Registro de Personas Jurídicas RNPJ, Registro Nacional de Conductores. | I66: DATOS Y SISTEMAS DE INFORMACIÓN | J66: 0324 | K66: Activo.En Ejecución | L66: =VLOOKUP(E66,Diccionario!C$2:AC$150,22,0) -> 372376516 | M66: =VLOOKUP(E66,Diccionario!C$2:AC$150,24,0) -> 45352 | N66: =VLOOKUP(E66,Diccionario!C$2:AC$150,25,0) -> 45534 | O66: =VLOOKUP(E66,Diccionario!C$2:AC$150,26,0) -> 5.97 | P66: =Q66-O66 -> -0.97 | Q66: 5 | R66: 6 | S66: 0.8 | T66: 0.79 | U66: 110202191 | V66: 110202191 | W66: =IFERROR(T66*L66,0) -> 2.9417745e+08 | X66: =S66*L66 -> 2.9790121e+08 | Y66: =IFERROR(W66-U66,0) -> 1.8397526e+08 | Z66: =W66-X66 -> -3723765.2 | AA66: =IFERROR(W66/U66,"No se realizó gasto en este corte") -> 2.6694337 | AB66: =IFERROR( IF(OR(AA66="",AA66=0), "No calculado", IF(AA66>1,"Costo eficiente: se está gastando menos de lo presupuestado", IF(AA66=1,"Costo según lo presupuestado", "Costo ineficiente: se está gastando más de lo presupuestado"))), "No calculado") -> Costo eficiente: se está gastando menos de lo presupuestado | AC66: =IFERROR(W66/X66,0) -> 0.9875 | AD66: =IF(OR(AC66="",AC66=0),"Sin Línea Base", IF(AC66>1,"Proyecto adelantado respecto al cronograma", IF(AC66=1,"Proyecto a tiempo según lo planificado", IF(AC66<1,"Proyecto atrasado con respecto al cronograma", "No calculado")))) -> Proyecto atrasado con respecto al cronograma | AE66: =IFERROR(L66/AA66,0) -> 1.3949644e+08 | AF66: =IFERROR(AE66-L66,0) -> -2.3288007e+08 | AG66: =VLOOKUP(Indicador!E66,Diccionario!C$1:AC$150,27,0) -> https://growdatasas.sharepoint.com/:x:/r/sites/Gestiondocumental/Administrativa/GD/Financiera/_layouts/15/Doc.aspx?sourcedoc=%7B465AB503-754C-43E2-86C3-8E24183E3BBF%7D&file=090424%20324.%20RUNT%202.0%20-%20RUNT%20MDM.xlsx&action=default&mobileredirect=true | AH66: 1 | AI66: 1
A67: 2024 | B67: Agosto | C67: b325f473-91e8-ee11-b9dc-00155d68784b | D67: 45373.887 | E67: RUNT – DISEÑO,IMPLEMENTACION MDM | F67: Leidy Susana Ramirez Herrera | G67: https://growdatasas.sharepoint.com/sites/pwa/RUNT – DISEÑO,IMPLEMENTACION MDM | H67: ​Implementar el modelo de gestión de datos maestros y de referencia a partir del diseño y definición de la estrategia de las capacidades para que permita a la entidad estandarizar y tener una única visión de los datos transversales que se manejan en los diferentes procesos del RUNT. Con el objetivo de asegurar una correcta implementación de la solución de IBM Cloud Pak for Data proponemos la incorporación de una capa de servicios profesionales especializados en la plataforma. Con un alcance de tres registros maestros a saber: Registro Nacional Automotor RNA y el Registro de Personas Jurídicas RNPJ, Registro Nacional de Conductores. | I67: DATOS Y SISTEMAS DE INFORMACIÓN | J67: 0324 | K67: Activo.En Ejecución | L67: =VLOOKUP(E67,Diccionario!C$2:AC$150,22,0) -> 372376516 | M67: =VLOOKUP(E67,Diccionario!C$2:AC$150,24,0) -> 45352 | N67: =VLOOKUP(E67,Diccionario!C$2:AC$150,25,0) -> 45534 | O67: =VLOOKUP(E67,Diccionario!C$2:AC$150,26,0) -> 5.97 | P67: =Q67-O67 -> 0.03 | Q67: 6 | R67: 6 | S67: 1 | T67: 1 | U67: 13923314 | V67: 13923314 | W67: =IFERROR(T67*L67,0) -> 372376516 | X67: =S67*L67 -> 372376516 | Y67: =IFERROR(W67-U67,0) -> 358453202 | Z67: =W67-X67 -> 0 | AA67: =IFERROR(W67/U67,"No se realizó gasto en este corte") -> 26.744819 | AB67: =IFERROR( IF(OR(AA67="",AA67=0), "No calculado", IF(AA67>1,"Costo eficiente: se está gastando menos de lo presupuestado", IF(AA67=1,"Costo según lo presupuestado", "Costo ineficiente: se está gastando más de lo presupuestado"))), "No calculado") -> Costo eficiente: se está gastando menos de lo presupuestado | AC67: =IFERROR(W67/X67,0) -> 1 | AD67: =IF(OR(AC67="",AC67=0),"Sin Línea Base", IF(AC67>1,"Proyecto adelantado respecto al cronograma", IF(AC67=1,"Proyecto a tiempo según lo planificado", IF(AC67<1,"Proyecto atrasado con respecto al cronograma", "No calculado")))) -> Proyecto a tiempo según lo planificado | AE67: =IFERROR(L67/AA67,0) -> 13923314 | AF67: =IFERROR(AE67-L67,0) -> -358453202 | AG67: =VLOOKUP(Indicador!E67,Diccionario!C$1:AC$150,27,0) -> https://growdatasas.sharepoint.com/:x:/r/sites/Gestiondocumental/Administrativa/GD/Financiera/_layouts/15/Doc.aspx?sourcedoc=%7B465AB503-754C-43E2-86C3-8E24183E3BBF%7D&file=090424%20324.%20RUNT%202.0%20-%20RUNT%20MDM.xlsx&action=default&mobileredirect=true | AH67: 1 | AI67: 1
A68: 2024 | B68: Marzo | C68: 7bad0cc0-6d01-ef11-b0c0-00155d68bf05 | D68: 45405.524 | E68: ALDESARROLLO - ICFES - SOSTENIBILIDAD | F68: Laura Johanna Jaramillo Soto | G68: https://growdatasas.sharepoint.com/sites/pwa/ALDESARROLLO - ICFES - SOSTENIBILIDAD | H68: CONTRATAR LA REALIZACIÓN DEL DISEÑO DE ESTRATEGIA Y POLÍTICADE SOSTENIBILIDAD-RESPONSABILIDAD SOCIAL E INFORME DE SOSTENIBILIDAD 2023 CON EL ESTÁNDAR GRI, CON MIRAS AL FORTALECIMIENTO INSTITUCIONAL, SU PROYECCIÓN A GRUPOS DE INTERÉS Y LA DISPOSICIÓN A LOS RETOS DE INTERNACIONALIZACIÓN, COMPROMISO SOCIAL Y AMBIENTAL DE LA ENTIDAD. SE REALIZA UN OTRO SI ACLARATORIO DONDE SE AJUSTE LA NOMENCLATURA ASIGNADA AL CONTRATO DE CP-PR-2024-161 A CP-PR-2024-161A | I68: CONSULTORÍA | J68: 0327 | K68: Activo.En Ejecución | L68: =VLOOKUP(E68,Diccionario!C$2:AC$150,22,0) -> 1087776079 | M68: =VLOOKUP(E68,Diccionario!C$2:AC$150,24,0) -> 45369 | N68: =VLOOKUP(E68,Diccionario!C$2:AC$150,25,0) -> 45552 | O68: =VLOOKUP(E68,Diccionario!C$2:AC$150,26,0) -> 5.97 | P68: =Q68-O68 -> -4.97 | Q68: 1 | R68: 6 | S68: 0.3 | T68: 0.25 | U68: 156296013 | V68: 156296013 | W68: =IFERROR(T68*L68,0) -> 2.7194402e+08 | X68: =S68*L68 -> 3.2633282e+08 | Y68: =IFERROR(W68-U68,0) -> 1.1564801e+08 | Z68: =W68-X68 -> -54388804 | AA68: =IFERROR(W68/U68,"No se realizó gasto en este corte") -> 1.7399293 | AB68: =IFERROR( IF(OR(AA68="",AA68=0), "No calculado", IF(AA68>1,"Costo eficiente: se está gastando menos de lo presupuestado", IF(AA68=1,"Costo según lo presupuestado", "Costo ineficiente: se está gastando más de lo presupuestado"))), "No calculado") -> Costo eficiente: se está gastando menos de lo presupuestado | AC68: =IFERROR(W68/X68,0) -> 0.83333333 | AD68: =IF(OR(AC68="",AC68=0),"Sin Línea Base", IF(AC68>1,"Proyecto adelantado respecto al cronograma", IF(AC68=1,"Proyecto a tiempo según lo planificado", IF(AC68<1,"Proyecto atrasado con respecto al cronograma", "No calculado")))) -> Proyecto atrasado con respecto al cronograma | AE68: =IFERROR(L68/AA68,0) -> 625184052 | AF68: =IFERROR(AE68-L68,0) -> -462592027 | AG68: =VLOOKUP(Indicador!E68,Diccionario!C$1:AC$150,27,0) -> https://growdatasas.sharepoint.com/:x:/r/sites/Gestiondocumental/Administrativa/GD/Financiera/_layouts/15/Doc.aspx?sourcedoc=%7B293F42A2-5CA4-4376-950C-5CBFEA13F436%7D&file=327.%20ALDESARROLLO%20-%20ICFES%20-%20SOSTENIBILIDAD.xlsx&action=default&mobileredirect=true | AH68: 1 | AI68: 1
A69: 2024 | B69: Abril | C69: 7bad0cc0-6d01-ef11-b0c0-00155d68bf05 | D69: 45405.524 | E69: ALDESARROLLO - ICFES - SOSTENIBILIDAD | F69: Laura Johanna Jaramillo Soto | G69: https://growdatasas.sharepoint.com/sites/pwa/ALDESARROLLO - ICFES - SOSTENIBILIDAD | H69: CONTRATAR LA REALIZACIÓN DEL DISEÑO DE ESTRATEGIA Y POLÍTICADE SOSTENIBILIDAD-RESPONSABILIDAD SOCIAL E INFORME DE SOSTENIBILIDAD 2023 CON EL ESTÁNDAR GRI, CON MIRAS AL FORTALECIMIENTO INSTITUCIONAL, SU PROYECCIÓN A GRUPOS DE INTERÉS Y LA DISPOSICIÓN A LOS RETOS DE INTERNACIONALIZACIÓN, COMPROMISO SOCIAL Y AMBIENTAL DE LA ENTIDAD. SE REALIZA UN OTRO SI ACLARATORIO DONDE SE AJUSTE LA NOMENCLATURA ASIGNADA AL CONTRATO DE CP-PR-2024-161 A CP-PR-2024-161A | I69: CONSULTORÍA | J69: 0327 | K69: Activo.En Ejecución | L69: =VLOOKUP(E69,Diccionario!C$2:AC$150,22,0) -> 1087776079 | M69: =VLOOKUP(E69,Diccionario!C$2:AC$150,24,0) -> 45369 | N69: =VLOOKUP(E69,Diccionario!C$2:AC$150,25,0) -> 45552 | O69: =VLOOKUP(E69,Diccionario!C$2:AC$150,26,0) -> 5.97 | P69: =Q69-O69 -> -3.97 | Q69: 2 | R69: 6 | S69: 0.45 | T69: 0.45 | U69: 231296013 | V69: 231296013 | W69: =IFERROR(T69*L69,0) -> 4.8949924e+08 | X69: =S69*L69 -> 4.8949924e+08 | Y69: =IFERROR(W69-U69,0) -> 2.5820322e+08 | Z69: =W69-X69 -> 0 | AA69: =IFERROR(W69/U69,"No se realizó gasto en este corte") -> 2.1163324 | AB69: =IFERROR( IF(OR(AA69="",AA69=0), "No calculado", IF(AA69>1,"Costo eficiente: se está gastando menos de lo presupuestado", IF(AA69=1,"Costo según lo presupuestado", "Costo ineficiente: se está gastando más de lo presupuestado"))), "No calculado") -> Costo eficiente: se está gastando menos de lo presupuestado | AC69: =IFERROR(W69/X69,0) -> 1 | AD69: =IF(OR(AC69="",AC69=0),"Sin Línea Base", IF(AC69>1,"Proyecto adelantado respecto al cronograma", IF(AC69=1,"Proyecto a tiempo según lo planificado", IF(AC69<1,"Proyecto atrasado con respecto al cronograma", "No calculado")))) -> Proyecto a tiempo según lo planificado | AE69: =IFERROR(L69/AA69,0) -> 513991140 | AF69: =IFERROR(AE69-L69,0) -> -573784939 | AG69: =VLOOKUP(Indicador!E69,Diccionario!C$1:AC$150,27,0) -> https://growdatasas.sharepoint.com/:x:/r/sites/Gestiondocumental/Administrativa/GD/Financiera/_layouts/15/Doc.aspx?sourcedoc=%7B293F42A2-5CA4-4376-950C-5CBFEA13F436%7D&file=327.%20ALDESARROLLO%20-%20ICFES%20-%20SOSTENIBILIDAD.xlsx&action=default&mobileredirect=true | AH69: 1 | AI69: 1
A70: 2024 | B70: Mayo | C70: 7bad0cc0-6d01-ef11-b0c0-00155d68bf05 | D70: 45405.524 | E70: ALDESARROLLO - ICFES - SOSTENIBILIDAD | F70: Laura Johanna Jaramillo Soto | G70: https://growdatasas.sharepoint.com/sites/pwa/ALDESARROLLO - ICFES - SOSTENIBILIDAD | H70: CONTRATAR LA REALIZACIÓN DEL DISEÑO DE ESTRATEGIA Y POLÍTICADE SOSTENIBILIDAD-RESPONSABILIDAD SOCIAL E INFORME DE SOSTENIBILIDAD 2023 CON EL ESTÁNDAR GRI, CON MIRAS AL FORTALECIMIENTO INSTITUCIONAL, SU PROYECCIÓN A GRUPOS DE INTERÉS Y LA DISPOSICIÓN A LOS RETOS DE INTERNACIONALIZACIÓN, COMPROMISO SOCIAL Y AMBIENTAL DE LA ENTIDAD. SE REALIZA UN OTRO SI ACLARATORIO DONDE SE AJUSTE LA NOMENCLATURA ASIGNADA AL CONTRATO DE CP-PR-2024-161 A CP-PR-2024-161A | I70: CONSULTORÍA | J70: 0327 | K70: Activo.En Ejecución | L70: =VLOOKUP(E70,Diccionario!C$2:AC$150,22,0) -> 1087776079 | M70: =VLOOKUP(E70,Diccionario!C$2:AC$150,24,0) -> 45369 | N70: =VLOOKUP(E70,Diccionario!C$2:AC$150,25,0) -> 45552 | O70: =VLOOKUP(E70,Diccionario!C$2:AC$150,26,0) -> 5.97 | P70: =Q70-O70 -> -2.97 | Q70: 3 | R70: 6 | S70: 0.5 | T70: 0.55 | U70: 156296013 | V70: 156296013 | W70: =IFERROR(T70*L70,0) -> 5.9827684e+08 | X70: =S70*L70 -> 5.4388804e+08 | Y70: =IFERROR(W70-U70,0) -> 4.4198083e+08 | Z70: =W70-X70 -> 54388804 | AA70: =IFERROR(W70/U70,"No se realizó gasto en este corte") -> 3.8278446 | AB70: =IFERROR( IF(OR(AA70="",AA70=0), "No calculado", IF(AA70>1,"Costo eficiente: se está gastando menos de lo presupuestado", IF(AA70=1,"Costo según lo presupuestado", "Costo ineficiente: se está gastando más de lo presupuestado"))), "No calculado") -> Costo eficiente: se está gastando menos de lo presupuestado | AC70: =IFERROR(W70/X70,0) -> 1.1 | AD70: =IF(OR(AC70="",AC70=0),"Sin Línea Base", IF(AC70>1,"Proyecto adelantado respecto al cronograma", IF(AC70=1,"Proyecto a tiempo según lo planificado", IF(AC70<1,"Proyecto atrasado con respecto al cronograma", "No calculado")))) -> Proyecto adelantado respecto al cronograma | AE70: =IFERROR(L70/AA70,0) -> 2.8417457e+08 | AF70: =IFERROR(AE70-L70,0) -> -8.0360151e+08 | AG70: =VLOOKUP(Indicador!E70,Diccionario!C$1:AC$150,27,0) -> https://growdatasas.sharepoint.com/:x:/r/sites/Gestiondocumental/Administrativa/GD/Financiera/_layouts/15/Doc.aspx?sourcedoc=%7B293F42A2-5CA4-4376-950C-5CBFEA13F436%7D&file=327.%20ALDESARROLLO%20-%20ICFES%20-%20SOSTENIBILIDAD.xlsx&action=default&mobileredirect=true | AH70: 1 | AI70: 1
A71: 2024 | B71: Junio | C71: 7bad0cc0-6d01-ef11-b0c0-00155d68bf05 | D71: 45405.524 | E71: ALDESARROLLO - ICFES - SOSTENIBILIDAD | F71: Laura Johanna Jaramillo Soto | G71: https://growdatasas.sharepoint.com/sites/pwa/ALDESARROLLO - ICFES - SOSTENIBILIDAD | H71: CONTRATAR LA REALIZACIÓN DEL DISEÑO DE ESTRATEGIA Y POLÍTICADE SOSTENIBILIDAD-RESPONSABILIDAD SOCIAL E INFORME DE SOSTENIBILIDAD 2023 CON EL ESTÁNDAR GRI, CON MIRAS AL FORTALECIMIENTO INSTITUCIONAL, SU PROYECCIÓN A GRUPOS DE INTERÉS Y LA DISPOSICIÓN A LOS RETOS DE INTERNACIONALIZACIÓN, COMPROMISO SOCIAL Y AMBIENTAL DE LA ENTIDAD. SE REALIZA UN OTRO SI ACLARATORIO DONDE SE AJUSTE LA NOMENCLATURA ASIGNADA AL CONTRATO DE CP-PR-2024-161 A CP-PR-2024-161A | I71: CONSULTORÍA | J71: 0327 | K71: Activo.En Ejecución | L71: =VLOOKUP(E71,Diccionario!C$2:AC$150,22,0) -> 1087776079 | M71: =VLOOKUP(E71,Diccionario!C$2:AC$150,24,0) -> 45369 | N71: =VLOOKUP(E71,Diccionario!C$2:AC$150,25,0) -> 45552 | O71: =VLOOKUP(E71,Diccionario!C$2:AC$150,26,0) -> 5.97 | P71: =Q71-O71 -> -1.97 | Q71: 4 | R71: 6 | S71: 0.75 | T71: 0.77 | U71: 156296013 | V71: 156296013 | W71: =IFERROR(T71*L71,0) -> 8.3758758e+08 | X71: =S71*L71 -> 8.1583206e+08 | Y71: =IFERROR(W71-U71,0) -> 6.8129157e+08 | Z71: =W71-X71 -> 21755522 | AA71: =IFERROR(W71/U71,"No se realizó gasto en este corte") -> 5.3589824 | AB71: =IFERROR( IF(OR(AA71="",AA71=0), "No calculado", IF(AA71>1,"Costo eficiente: se está gastando menos de lo presupuestado", IF(AA71=1,"Costo según lo presupuestado", "Costo ineficiente: se está gastando más de lo presupuestado"))), "No calculado") -> Costo eficiente: se está gastando menos de lo presupuestado | AC71: =IFERROR(W71/X71,0) -> 1.0266667 | AD71: =IF(OR(AC71="",AC71=0),"Sin Línea Base", IF(AC71>1,"Proyecto adelantado respecto al cronograma", IF(AC71=1,"Proyecto a tiempo según lo planificado", IF(AC71<1,"Proyecto atrasado con respecto al cronograma", "No calculado")))) -> Proyecto adelantado respecto al cronograma | AE71: =IFERROR(L71/AA71,0) -> 2.0298184e+08 | AF71: =IFERROR(AE71-L71,0) -> -8.8479424e+08 | AG71: =VLOOKUP(Indicador!E71,Diccionario!C$1:AC$150,27,0) -> https://growdatasas.sharepoint.com/:x:/r/sites/Gestiondocumental/Administrativa/GD/Financiera/_layouts/15/Doc.aspx?sourcedoc=%7B293F42A2-5CA4-4376-950C-5CBFEA13F436%7D&file=327.%20ALDESARROLLO%20-%20ICFES%20-%20SOSTENIBILIDAD.xlsx&action=default&mobileredirect=true | AH71: 1 | AI71: 1
A72: 2024 | B72: Julio | C72: 7bad0cc0-6d01-ef11-b0c0-00155d68bf05 | D72: 45405.524 | E72: ALDESARROLLO - ICFES - SOSTENIBILIDAD | F72: Laura Johanna Jaramillo Soto | G72: https://growdatasas.sharepoint.com/sites/pwa/ALDESARROLLO - ICFES - SOSTENIBILIDAD | H72: CONTRATAR LA REALIZACIÓN DEL DISEÑO DE ESTRATEGIA Y POLÍTICADE SOSTENIBILIDAD-RESPONSABILIDAD SOCIAL E INFORME DE SOSTENIBILIDAD 2023 CON EL ESTÁNDAR GRI, CON MIRAS AL FORTALECIMIENTO INSTITUCIONAL, SU PROYECCIÓN A GRUPOS DE INTERÉS Y LA DISPOSICIÓN A LOS RETOS DE INTERNACIONALIZACIÓN, COMPROMISO SOCIAL Y AMBIENTAL DE LA ENTIDAD. SE REALIZA UN OTRO SI ACLARATORIO DONDE SE AJUSTE LA NOMENCLATURA ASIGNADA AL CONTRATO DE CP-PR-2024-161 A CP-PR-2024-161A | I72: CONSULTORÍA | J72: 0327 | K72: Activo.En Ejecución | L72: =VLOOKUP(E72,Diccionario!C$2:AC$150,22,0) -> 1087776079 | M72: =VLOOKUP(E72,Diccionario!C$2:AC$150,24,0) -> 45369 | N72: =VLOOKUP(E72,Diccionario!C$2:AC$150,25,0) -> 45552 | O72: =VLOOKUP(E72,Diccionario!C$2:AC$150,26,0) -> 5.97 | P72: =Q72-O72 -> -0.97 | Q72: 5 | R72: 6 | S72: 0.8 | T72: 0.81 | U72: 231296013 | V72: 231296013 | W72: =IFERROR(T72*L72,0) -> 8.8109862e+08 | X72: =S72*L72 -> 8.7022086e+08 | Y72: =IFERROR(W72-U72,0) -> 6.4980261e+08 | Z72: =W72-X72 -> 10877761 | AA72: =IFERROR(W72/U72,"No se realizó gasto en este corte") -> 3.8093982 | AB72: =IFERROR( IF(OR(AA72="",AA72=0), "No calculado", IF(AA72>1,"Costo eficiente: se está gastando menos de lo presupuestado", IF(AA72=1,"Costo según lo presupuestado", "Costo ineficiente: se está gastando más de lo presupuestado"))), "No calculado") -> Costo eficiente: se está gastando menos de lo presupuestado | AC72: =IFERROR(W72/X72,0) -> 1.0125 | AD72: =IF(OR(AC72="",AC72=0),"Sin Línea Base", IF(AC72>1,"Proyecto adelantado respecto al cronograma", IF(AC72=1,"Proyecto a tiempo según lo planificado", IF(AC72<1,"Proyecto atrasado con respecto al cronograma", "No calculado")))) -> Proyecto adelantado respecto al cronograma | AE72: =IFERROR(L72/AA72,0) -> 2.8555063e+08 | AF72: =IFERROR(AE72-L72,0) -> -8.0222545e+08 | AG72: =VLOOKUP(Indicador!E72,Diccionario!C$1:AC$150,27,0) -> https://growdatasas.sharepoint.com/:x:/r/sites/Gestiondocumental/Administrativa/GD/Financiera/_layouts/15/Doc.aspx?sourcedoc=%7B293F42A2-5CA4-4376-950C-5CBFEA13F436%7D&file=327.%20ALDESARROLLO%20-%20ICFES%20-%20SOSTENIBILIDAD.xlsx&action=default&mobileredirect=true | AH72: 1 | AI72: 1
A73: 2024 | B73: Agosto | C73: 7bad0cc0-6d01-ef11-b0c0-00155d68bf05 | D73: 45405.524 | E73: ALDESARROLLO - ICFES - SOSTENIBILIDAD | F73: Laura Johanna Jaramillo Soto | G73: https://growdatasas.sharepoint.com/sites/pwa/ALDESARROLLO - ICFES - SOSTENIBILIDAD | H73: CONTRATAR LA REALIZACIÓN DEL DISEÑO DE ESTRATEGIA Y POLÍTICADE SOSTENIBILIDAD-RESPONSABILIDAD SOCIAL E INFORME DE SOSTENIBILIDAD 2023 CON EL ESTÁNDAR GRI, CON MIRAS AL FORTALECIMIENTO INSTITUCIONAL, SU PROYECCIÓN A GRUPOS DE INTERÉS Y LA DISPOSICIÓN A LOS RETOS DE INTERNACIONALIZACIÓN, COMPROMISO SOCIAL Y AMBIENTAL DE LA ENTIDAD. SE REALIZA UN OTRO SI ACLARATORIO DONDE SE AJUSTE LA NOMENCLATURA ASIGNADA AL CONTRATO DE CP-PR-2024-161 A CP-PR-2024-161A | I73: CONSULTORÍA | J73: 0327 | K73: Activo.En Ejecución | L73: =VLOOKUP(E73,Diccionario!C$2:AC$150,22,0) -> 1087776079 | M73: =VLOOKUP(E73,Diccionario!C$2:AC$150,24,0) -> 45369 | N73: =VLOOKUP(E73,Diccionario!C$2:AC$150,25,0) -> 45552 | O73: =VLOOKUP(E73,Diccionario!C$2:AC$150,26,0) -> 5.97 | P73: =Q73-O73 -> 0.03 | Q73: 6 | R73: 6 | S73: 1 | T73: 1 | U73: 156296013 | V73: 156296013 | W73: =IFERROR(T73*L73,0) -> 1087776079 | X73: =S73*L73 -> 1087776079 | Y73: =IFERROR(W73-U73,0) -> 931480066 | Z73: =W73-X73 -> 0 | AA73: =IFERROR(W73/U73,"No se realizó gasto en este corte") -> 6.9597174 | AB73: =IFERROR( IF(OR(AA73="",AA73=0), "No calculado", IF(AA73>1,"Costo eficiente: se está gastando menos de lo presupuestado", IF(AA73=1,"Costo según lo presupuestado", "Costo ineficiente: se está gastando más de lo presupuestado"))), "No calculado") -> Costo eficiente: se está gastando menos de lo presupuestado | AC73: =IFERROR(W73/X73,0) -> 1 | AD73: =IF(OR(AC73="",AC73=0),"Sin Línea Base", IF(AC73>1,"Proyecto adelantado respecto al cronograma", IF(AC73=1,"Proyecto a tiempo según lo planificado", IF(AC73<1,"Proyecto atrasado con respecto al cronograma", "No calculado")))) -> Proyecto a tiempo según lo planificado | AE73: =IFERROR(L73/AA73,0) -> 156296013 | AF73: =IFERROR(AE73-L73,0) -> -931480066 | AG73: =VLOOKUP(Indicador!E73,Diccionario!C$1:AC$150,27,0) -> https://growdatasas.sharepoint.com/:x:/r/sites/Gestiondocumental/Administrativa/GD/Financiera/_layouts/15/Doc.aspx?sourcedoc=%7B293F42A2-5CA4-4376-950C-5CBFEA13F436%7D&file=327.%20ALDESARROLLO%20-%20ICFES%20-%20SOSTENIBILIDAD.xlsx&action=default&mobileredirect=true | AH73: 1 | AI73: 1
... A82: 2024 | B82: Noviembre | C82: 378e9b3a-aa01-ef11-88ac-00155d682343 | D82: 45405.824 | E82: EMTEL - ICFES - FABRICA | F82: Leidy Susana Ramirez Herrera | G82: https://growdatasas.sharepoint.com/sites/pwa/EMTEL - ICFES - FABRICA | H82: Prestación de servicios de Fábrica de Software para los proyectos de transformación digital del ICFES.Prestación de servicios de pruebas funcionales, no funcionales por demanda y aseguramiento de calidad asociado a las soluciones tecnológicas definidas para el Instituto Colombiano para la Evaluación de la Educación – ICFES. | I82: DATOS Y SISTEMAS DE INFORMACIÓN | J82: 0326 | K82: Activo.En Cierre | L82: =VLOOKUP(E82,Diccionario!C$2:AC$150,22,0) -> 1566562163 | M82: =VLOOKUP(E82,Diccionario!C$2:AC$150,24,0) -> 45402 | N82: =VLOOKUP(E82,Diccionario!C$2:AC$150,25,0) -> 45656 | O82: =VLOOKUP(E82,Diccionario!C$2:AC$150,26,0) -> 8.33 | P82: =Q82-O82 -> -0.33 | Q82: 8 | R82: 8 | S82: 1 | T82: 1 | U82: 195820270 | V82: 195820270 | W82: =IFERROR(T82*L82,0) -> 1566562163 | X82: =S82*L82 -> 1566562163 | Y82: =IFERROR(W82-U82,0) -> 1370741893 | Z82: =W82-X82 -> 0 | AA82: =IFERROR(W82/U82,"No se realizó gasto en este corte") -> 8 | AB82: =IFERROR( IF(OR(AA82="",AA82=0), "No calculado", IF(AA82>1,"Costo eficiente: se está gastando menos de lo presupuestado", IF(AA82=1,"Costo según lo presupuestado", "Costo ineficiente: se está gastando más de lo presupuestado"))), "No calculado") -> Costo eficiente: se está gastando menos de lo presupuestado | AC82: =IFERROR(W82/X82,0) -> 1 | AD82: =IF(OR(AC82="",AC82=0),"Sin Línea Base", IF(AC82>1,"Proyecto adelantado respecto al cronograma", IF(AC82=1,"Proyecto a tiempo según lo planificado", IF(AC82<1,"Proyecto atrasado con respecto al cronograma", "No calculado")))) -> Proyecto a tiempo según lo planificado | AE82: =IFERROR(L82/AA82,0) -> 1.9582027e+08 | AF82: =IFERROR(AE82-L82,0) -> -1370741893 | AG82: =VLOOKUP(Indicador!E82,Diccionario!C$1:AC$150,27,0) -> https://growdatasas.sharepoint.com/:x:/r/sites/Gestiondocumental/Administrativa/GD/Financiera/_layouts/15/Doc.aspx?sourcedoc=%7BB89BD188-BEAD-4E84-BC3B-FF43B34DCCB0%7D&file=326.%20ICFES%20-%20FABRICA%20DE%20SOFTWARE%20PRUEBAS.xlsx&action=default&mobileredirect=true | AH82: 1 | AI82: 1
A83: 2024 | B83: Mayo | C83: fb6b6bf8-513d-ef11-964f-00155d687105 | D83: 45481.74 | E83: ALDESARROLLO - INM - DATOS Y PROCESOS | F83: Leidy Susana Ramirez Herrera | G83: https://growdatasas.sharepoint.com/sites/pwa/INM-ALDESARROLLO-DATOS Y PROCESOS | H83: ​CONTRATAR LOS SERVICIOS PARA CONTINUAR IMPLEMENTANDO LA POLÍTICA DE GOBIERNO DIGITAL A TRAVÉS DEL DESARROLLO DE EJERCICIOS DE ARQUITECTURA EMPRESARIAL EN LOS DOMINIOS INSTITUCIONAL, DE INFORMACIÓN Y DE TECNOLOGÍA. | I83: CONSULTORÍA | J83: 0331 | K83: Activo.En Ejecución | L83: =VLOOKUP(E83,Diccionario!C$2:AC$150,22,0) -> 218649688 | M83: =VLOOKUP(E83,Diccionario!C$2:AC$150,24,0) -> 45413 | N83: =VLOOKUP(E83,Diccionario!C$2:AC$150,25,0) -> 45534 | O83: =VLOOKUP(E83,Diccionario!C$2:AC$150,26,0) -> 3.97 | P83: =Q83-O83 -> 22.03 | Q83: =DATEDIF(M83,TODAY(),"m") -> 26 | R83: 4 | S83: 0.2 | T83: 0.15 | U83: 43729938 | V83: 43729938 | W83: =IFERROR(T83*L83,0) -> 32797453 | X83: =S83*L83 -> 43729938 | Y83: =IFERROR(W83-U83,0) -> -10932485 | Z83: =W83-X83 -> -10932484 | AA83: =IFERROR(W83/U83,"No se realizó gasto en este corte") -> 0.74999999 | AB83: =IFERROR( IF(OR(AA83="",AA83=0), "No calculado", IF(AA83>1,"Costo eficiente: se está gastando menos de lo presupuestado", IF(AA83=1,"Costo según lo presupuestado", "Costo ineficiente: se está gastando más de lo presupuestado"))), "No calculado") -> Costo ineficiente: se está gastando más de lo presupuestado | AC83: =IFERROR(W83/X83,0) -> 0.75 | AD83: =IF(OR(AC83="",AC83=0),"Sin Línea Base", IF(AC83>1,"Proyecto adelantado respecto al cronograma", IF(AC83=1,"Proyecto a tiempo según lo planificado", IF(AC83<1,"Proyecto atrasado con respecto al cronograma", "No calculado")))) -> Proyecto atrasado con respecto al cronograma | AE83: =IFERROR(L83/AA83,0) -> 291532920 | AF83: =IFERROR(AE83-L83,0) -> 72883232 | AG83: =VLOOKUP(Indicador!E83,Diccionario!C$1:AC$150,27,0) -> https://growdatasas.sharepoint.com/:x:/r/sites/Gestiondocumental/Administrativa/GD/Financiera/_layouts/15/Doc.aspx?sourcedoc=%7B90300F8C-6F13-418B-97E4-626034BE9C0E%7D&file=MODELO%20FINANCIERO%20REFERENCIA%20V7-INM_V1.0%20-%20500M.xlsm&action=default&mobileredirect=true | AH83: 1 | AI83: 1
A84: 2024 | B84: Junio | C84: fb6b6bf8-513d-ef11-964f-00155d687105 | D84: 45481.74 | E84: ALDESARROLLO - INM - DATOS Y PROCESOS | F84: Leidy Susana Ramirez Herrera | G84: https://growdatasas.sharepoint.com/sites/pwa/INM-ALDESARROLLO-DATOS Y PROCESOS | H84: ​CONTRATAR LOS SERVICIOS PARA CONTINUAR IMPLEMENTANDO LA POLÍTICA DE GOBIERNO DIGITAL A TRAVÉS DEL DESARROLLO DE EJERCICIOS DE ARQUITECTURA EMPRESARIAL EN LOS DOMINIOS INSTITUCIONAL, DE INFORMACIÓN Y DE TECNOLOGÍA. | I84: CONSULTORÍA | J84: 0331 | K84: Activo.En Ejecución | L84: =VLOOKUP(E84,Diccionario!C$2:AC$150,22,0) -> 218649688 | M84: =VLOOKUP(E84,Diccionario!C$2:AC$150,24,0) -> 45413 | N84: =VLOOKUP(E84,Diccionario!C$2:AC$150,25,0) -> 45534 | O84: =VLOOKUP(E84,Diccionario!C$2:AC$150,26,0) -> 3.97 | P84: =Q84-O84 -> 22.03 | Q84: =DATEDIF(M84,TODAY(),"m") -> 26 | R84: 4 | S84: 0.5 | T84: 0.56 | U84: 43729938 | V84: 43729938 | W84: =IFERROR(T84*L84,0) -> 1.2244383e+08 | X84: =S84*L84 -> 109324844 | Y84: =IFERROR(W84-U84,0) -> 78713887 | Z84: =W84-X84 -> 13118981 | AA84: =IFERROR(W84/U84,"No se realizó gasto en este corte") -> 2.8 | AB84: =IFERROR( IF(OR(AA84="",AA84=0), "No calculado", IF(AA84>1,"Costo eficiente: se está gastando menos de lo presupuestado", IF(AA84=1,"Costo según lo presupuestado", "Costo ineficiente: se está gastando más de lo presupuestado"))), "No calculado") -> Costo eficiente: se está gastando menos de lo presupuestado | AC84: =IFERROR(W84/X84,0) -> 1.12 | AD84: =IF(OR(AC84="",AC84=0),"Sin Línea Base", IF(AC84>1,"Proyecto adelantado respecto al cronograma", IF(AC84=1,"Proyecto a tiempo según lo planificado", IF(AC84<1,"Proyecto atrasado con respecto al cronograma", "No calculado")))) -> Proyecto adelantado respecto al cronograma | AE84: =IFERROR(L84/AA84,0) -> 78089175 | AF84: =IFERROR(AE84-L84,0) -> -140560513 | AG84: =VLOOKUP(Indicador!E84,Diccionario!C$1:AC$150,27,0) -> https://growdatasas.sharepoint.com/:x:/r/sites/Gestiondocumental/Administrativa/GD/Financiera/_layouts/15/Doc.aspx?sourcedoc=%7B90300F8C-6F13-418B-97E4-626034BE9C0E%7D&file=MODELO%20FINANCIERO%20REFERENCIA%20V7-INM_V1.0%20-%20500M.xlsm&action=default&mobileredirect=true | AH84: 1 | AI84: 1
A85: 2024 | B85: Julio | C85: fb6b6bf8-513d-ef11-964f-00155d687105 | D85: 45481.74 | E85: ALDESARROLLO - INM - DATOS Y PROCESOS | F85: Leidy Susana Ramirez Herrera | G85: https://growdatasas.sharepoint.com/sites/pwa/INM-ALDESARROLLO-DATOS Y PROCESOS | H85: ​CONTRATAR LOS SERVICIOS PARA CONTINUAR IMPLEMENTANDO LA POLÍTICA DE GOBIERNO DIGITAL A TRAVÉS DEL DESARROLLO DE EJERCICIOS DE ARQUITECTURA EMPRESARIAL EN LOS DOMINIOS INSTITUCIONAL, DE INFORMACIÓN Y DE TECNOLOGÍA. | I85: CONSULTORÍA | J85: 0331 | K85: Activo.En Ejecución | L85: =VLOOKUP(E85,Diccionario!C$2:AC$150,22,0) -> 218649688 | M85: =VLOOKUP(E85,Diccionario!C$2:AC$150,24,0) -> 45413 | N85: =VLOOKUP(E85,Diccionario!C$2:AC$150,25,0) -> 45534 | O85: =VLOOKUP(E85,Diccionario!C$2:AC$150,26,0) -> 3.97 | P85: =Q85-O85 -> 22.03 | Q85: =DATEDIF(M85,TODAY(),"m") -> 26 | R85: 4 | S85: 0.85 | T85: 0.67 | U85: 43729938 | V85: 43729938 | W85: =IFERROR(T85*L85,0) -> 1.4649529e+08 | X85: =S85*L85 -> 1.8585223e+08 | Y85: =IFERROR(W85-U85,0) -> 1.0276535e+08 | Z85: =W85-X85 -> -39356944 | AA85: =IFERROR(W85/U85,"No se realizó gasto en este corte") -> 3.35 | AB85: =IFERROR( IF(OR(AA85="",AA85=0), "No calculado", IF(AA85>1,"Costo eficiente: se está gastando menos de lo presupuestado", IF(AA85=1,"Costo según lo presupuestado", "Costo ineficiente: se está gastando más de lo presupuestado"))), "No calculado") -> Costo eficiente: se está gastando menos de lo presupuestado | AC85: =IFERROR(W85/X85,0) -> 0.78823529 | AD85: =IF(OR(AC85="",AC85=0),"Sin Línea Base", IF(AC85>1,"Proyecto adelantado respecto al cronograma", IF(AC85=1,"Proyecto a tiempo según lo planificado", IF(AC85<1,"Proyecto atrasado con respecto al cronograma", "No calculado")))) -> Proyecto atrasado con respecto al cronograma | AE85: =IFERROR(L85/AA85,0) -> 65268564 | AF85: =IFERROR(AE85-L85,0) -> -1.5338112e+08 | AG85: =VLOOKUP(Indicador!E85,Diccionario!C$1:AC$150,27,0) -> https://growdatasas.sharepoint.com/:x:/r/sites/Gestiondocumental/Administrativa/GD/Financiera/_layouts/15/Doc.aspx?sourcedoc=%7B90300F8C-6F13-418B-97E4-626034BE9C0E%7D&file=MODELO%20FINANCIERO%20REFERENCIA%20V7-INM_V1.0%20-%20500M.xlsm&action=default&mobileredirect=true | AH85: 1 | AI85: 1
A86: 2024 | B86: Agosto | C86: fb6b6bf8-513d-ef11-964f-00155d687105 | D86: 45481.74 | E86: ALDESARROLLO - INM - DATOS Y PROCESOS | F86: Leidy Susana Ramirez Herrera | G86: https://growdatasas.sharepoint.com/sites/pwa/INM-ALDESARROLLO-DATOS Y PROCESOS | H86: ​CONTRATAR LOS SERVICIOS PARA CONTINUAR IMPLEMENTANDO LA POLÍTICA DE GOBIERNO DIGITAL A TRAVÉS DEL DESARROLLO DE EJERCICIOS DE ARQUITECTURA EMPRESARIAL EN LOS DOMINIOS INSTITUCIONAL, DE INFORMACIÓN Y DE TECNOLOGÍA. | I86: CONSULTORÍA | J86: 0331 | K86: Activo.En Ejecución | L86: =VLOOKUP(E86,Diccionario!C$2:AC$150,22,0) -> 218649688 | M86: =VLOOKUP(E86,Diccionario!C$2:AC$150,24,0) -> 45413 | N86: =VLOOKUP(E86,Diccionario!C$2:AC$150,25,0) -> 45534 | O86: =VLOOKUP(E86,Diccionario!C$2:AC$150,26,0) -> 3.97 | P86: =Q86-O86 -> 22.03 | Q86: =DATEDIF(M86,TODAY(),"m") -> 26 | R86: 4 | S86: 1 | T86: 0.85 | U86: 43729938 | V86: 43729938 | W86: =IFERROR(T86*L86,0) -> 1.8585223e+08 | X86: =S86*L86 -> 218649688 | Y86: =IFERROR(W86-U86,0) -> 1.421223e+08 | Z86: =W86-X86 -> -32797453 | AA86: =IFERROR(W86/U86,"No se realizó gasto en este corte") -> 4.25 | AB86: =IFERROR( IF(OR(AA86="",AA86=0), "No calculado", IF(AA86>1,"Costo eficiente: se está gastando menos de lo presupuestado", IF(AA86=1,"Costo según lo presupuestado", "Costo ineficiente: se está gastando más de lo presupuestado"))), "No calculado") -> Costo eficiente: se está gastando menos de lo presupuestado | AC86: =IFERROR(W86/X86,0) -> 0.85 | AD86: =IF(OR(AC86="",AC86=0),"Sin Línea Base", IF(AC86>1,"Proyecto adelantado respecto al cronograma", IF(AC86=1,"Proyecto a tiempo según lo planificado", IF(AC86<1,"Proyecto atrasado con respecto al cronograma", "No calculado")))) -> Proyecto atrasado con respecto al cronograma | AE86: =IFERROR(L86/AA86,0) -> 51446986 | AF86: =IFERROR(AE86-L86,0) -> -1.672027e+08 | AG86: =VLOOKUP(Indicador!E86,Diccionario!C$1:AC$150,27,0) -> https://growdatasas.sharepoint.com/:x:/r/sites/Gestiondocumental/Administrativa/GD/Financiera/_layouts/15/Doc.aspx?sourcedoc=%7B90300F8C-6F13-418B-97E4-626034BE9C0E%7D&file=MODELO%20FINANCIERO%20REFERENCIA%20V7-INM_V1.0%20-%20500M.xlsm&action=default&mobileredirect=true | AH86: 1 | AI86: 1
A87: 2024 | B87: Agosto | C87: fb6b6bf8-513d-ef11-964f-00155d687105 | D87: 45481.74 | E87: ALDESARROLLO - INM - DATOS Y PROCESOS | F87: Leidy Susana Ramirez Herrera | G87: https://growdatasas.sharepoint.com/sites/pwa/INM-ALDESARROLLO-DATOS Y PROCESOS | H87: ​CONTRATAR LOS SERVICIOS PARA CONTINUAR IMPLEMENTANDO LA POLÍTICA DE GOBIERNO DIGITAL A TRAVÉS DEL DESARROLLO DE EJERCICIOS DE ARQUITECTURA EMPRESARIAL EN LOS DOMINIOS INSTITUCIONAL, DE INFORMACIÓN Y DE TECNOLOGÍA. | I87: CONSULTORÍA | J87: 0331 | K87: Activo.En Ejecución | L87: =VLOOKUP(E87,Diccionario!C$2:AC$150,22,0) -> 218649688 | M87: =VLOOKUP(E87,Diccionario!C$2:AC$150,24,0) -> 45413 | N87: =VLOOKUP(E87,Diccionario!C$2:AC$150,25,0) -> 45534 | O87: =VLOOKUP(E87,Diccionario!C$2:AC$150,26,0) -> 3.97 | P87: =Q87-O87 -> 22.03 | Q87: =DATEDIF(M87,TODAY(),"m") -> 26 | R87: 4 | S87: 1 | T87: 1 | U87: 43729938 | V87: 43729938 | W87: =IFERROR(T87*L87,0) -> 218649688 | X87: =S87*L87 -> 218649688 | Y87: =IFERROR(W87-U87,0) -> 174919750 | Z87: =W87-X87 -> 0 | AA87: =IFERROR(W87/U87,"No se realizó gasto en este corte") -> 5 | AB87: =IFERROR( IF(OR(AA87="",AA87=0), "No calculado", IF(AA87>1,"Costo eficiente: se está gastando menos de lo presupuestado", IF(AA87=1,"Costo según lo presupuestado", "Costo ineficiente: se está gastando más de lo presupuestado"))), "No calculado") -> Costo eficiente: se está gastando menos de lo presupuestado | AC87: =IFERROR(W87/X87,0) -> 1 | AD87: =IF(OR(AC87="",AC87=0),"Sin Línea Base", IF(AC87>1,"Proyecto adelantado respecto al cronograma", IF(AC87=1,"Proyecto a tiempo según lo planificado", IF(AC87<1,"Proyecto atrasado con respecto al cronograma", "No calculado")))) -> Proyecto a tiempo según lo planificado | AE87: =IFERROR(L87/AA87,0) -> 43729938 | AF87: =IFERROR(AE87-L87,0) -> -174919750 | AG87: =VLOOKUP(Indicador!E87,Diccionario!C$1:AC$150,27,0) -> https://growdatasas.sharepoint.com/:x:/r/sites/Gestiondocumental/Administrativa/GD/Financiera/_layouts/15/Doc.aspx?sourcedoc=%7B90300F8C-6F13-418B-97E4-626034BE9C0E%7D&file=MODELO%20FINANCIERO%20REFERENCIA%20V7-INM_V1.0%20-%20500M.xlsm&action=default&mobileredirect=true | AH87: 1 | AI87: 1
A88: 2024 | B88: Mayo | C88: 2f048f31-0b0f-ef11-9ac8-00155d68220c | D88: 45422.85 | E88: INFOTIC - ICFES - PRUEBAS CSJ | F88: Janeth Annelise Araujo Ramos | G88: https://growdatasas.sharepoint.com/sites/pwa/INFOTIC - ICFES - PRUEBAS CSJ | H88: APLICACIÓN ELECTRÓNICA DEL EXAMEN PARA EJERCER LA PROFESIÓN DE ABOGADO A REALIZARSE EN LA VIGENCIA 2024SUMINISTRO DE MESA DE SERVICIO CON COBERTURA NACIONAL | I88: TI | J88: 0328 | K88: Activo.En Cierre | L88: =VLOOKUP(E88,Diccionario!C$2:AC$150,22,0) -> 830180856 | M88: =VLOOKUP(E88,Diccionario!C$2:AC$150,24,0) -> 45414 | N88: =VLOOKUP(E88,Diccionario!C$2:AC$150,25,0) -> 45596 | O88: =VLOOKUP(E88,Diccionario!C$2:AC$150,26,0) -> 5.97 | P88: =Q88-O88 -> 20.03 | Q88: =DATEDIF(M88,TODAY(),"m") -> 26 | R88: 6 | S88: 0.2 | T88: 0.15 | U88: 311082365 | V88: 311082365 | W88: =IFERROR(T88*L88,0) -> 1.2452713e+08 | X88: =S88*L88 -> 1.6603617e+08 | Y88: =IFERROR(W88-U88,0) -> -1.8655524e+08 | Z88: =W88-X88 -> -41509043 | AA88: =IFERROR(W88/U88,"No se realizó gasto en este corte") -> 0.40030276 | AB88: =IFERROR( IF(OR(AA88="",AA88=0), "No calculado", IF(AA88>1,"Costo eficiente: se está gastando menos de lo presupuestado", IF(AA88=1,"Costo según lo presupuestado", "Costo ineficiente: se está gastando más de lo presupuestado"))), "No calculado") -> Costo ineficiente: se está gastando más de lo presupuestado | AC88: =IFERROR(W88/X88,0) -> 0.75 | AD88: =IF(OR(AC88="",AC88=0),"Sin Línea Base", IF(AC88>1,"Proyecto adelantado respecto al cronograma", IF(AC88=1,"Proyecto a tiempo según lo planificado", IF(AC88<1,"Proyecto atrasado con respecto al cronograma", "No calculado")))) -> Proyecto atrasado con respecto al cronograma | AE88: =IFERROR(L88/AA88,0) -> 2.0738824e+09 | AF88: =IFERROR(AE88-L88,0) -> 1.2437016e+09 | AG88: =VLOOKUP(Indicador!E88,Diccionario!C$1:AC$150,27,0) -> https://growdatasas.sharepoint.com/sites/Gestiondocumental/Administrativa/GD/Financiera/Documentos%20compartidos/Forms/AllItems.aspx?id=%2Fsites%2FGestiondocumental%2FAdministrativa%2FGD%2FFinanciera%2FDocumentos%20compartidos%2FAN%C3%81LISIS%20FINANCIERO%2FPMO%20SEGUIMIENTO%20A%20PROYECTOS%2F328%2E%20INFOTIC%20%2D%20ICFES%20%2D%20PRUEBAS%20CSJ&viewid=8ba7db0b%2Dbb48%2D40cc%2Da532%2D9b5bc18760d5 | AH88: 1 | AI88: 1
A89: 2024 | B89: Junio | C89: 2f048f31-0b0f-ef11-9ac8-00155d68220c | D89: 45422.85 | E89: INFOTIC - ICFES - PRUEBAS CSJ | F89: Janeth Annelise Araujo Ramos | G89: https://growdatasas.sharepoint.com/sites/pwa/INFOTIC - ICFES - PRUEBAS CSJ | H89: APLICACIÓN ELECTRÓNICA DEL EXAMEN PARA EJERCER LA PROFESIÓN DE ABOGADO A REALIZARSE EN LA VIGENCIA 2024SUMINISTRO DE MESA DE SERVICIO CON COBERTURA NACIONAL | I89: TI | J89: 0328 | K89: Activo.En Cierre | L89: =VLOOKUP(E89,Diccionario!C$2:AC$150,22,0) -> 830180856 | M89: =VLOOKUP(E89,Diccionario!C$2:AC$150,24,0) -> 45414 | N89: =VLOOKUP(E89,Diccionario!C$2:AC$150,25,0) -> 45596 | O89: =VLOOKUP(E89,Diccionario!C$2:AC$150,26,0) -> 5.97 | P89: =Q89-O89 -> 20.03 | Q89: =DATEDIF(M89,TODAY(),"m") -> 26 | R89: 6 | S89: 0.4 | T89: 0.35 | U89: 0 | V89: 0 | W89: =IFERROR(T89*L89,0) -> 2.905633e+08 | X89: =S89*L89 -> 3.3207234e+08 | Y89: =IFERROR(W89-U89,0) -> 2.905633e+08 | Z89: =W89-X89 -> -41509043 | AA89: =IFERROR(W89/U89,"No se realizó gasto en este corte") -> No se realizó gasto en este corte | AB89: =IFERROR( IF(OR(AA89="",AA89=0), "No calculado", IF(AA89>1,"Costo eficiente: se está gastando menos de lo presupuestado", IF(AA89=1,"Costo según lo presupuestado", "Costo ineficiente: se está gastando más de lo presupuestado"))), "No calculado") -> Costo eficiente: se está gastando menos de lo presupuestado | AC89: =IFERROR(W89/X89,0) -> 0.875 | AD89: =IF(OR(AC89="",AC89=0),"Sin Línea Base", IF(AC89>1,"Proyecto adelantado respecto al cronograma", IF(AC89=1,"Proyecto a tiempo según lo planificado", IF(AC89<1,"Proyecto atrasado con respecto al cronograma", "No calculado")))) -> Proyecto atrasado con respecto al cronograma | AE89: =IFERROR(L89/AA89,0) -> 0 | AF89: =IFERROR(AE89-L89,0) -> -830180856 | AG89: =VLOOKUP(Indicador!E89,Diccionario!C$1:AC$150,27,0) -> https://growdatasas.sharepoint.com/sites/Gestiondocumental/Administrativa/GD/Financiera/Documentos%20compartidos/Forms/AllItems.aspx?id=%2Fsites%2FGestiondocumental%2FAdministrativa%2FGD%2FFinanciera%2FDocumentos%20compartidos%2FAN%C3%81LISIS%20FINANCIERO%2FPMO%20SEGUIMIENTO%20A%20PROYECTOS%2F328%2E%20INFOTIC%20%2D%20ICFES%20%2D%20PRUEBAS%20CSJ&viewid=8ba7db0b%2Dbb48%2D40cc%2Da532%2D9b5bc18760d5 | AH89: 1 | AI89: 1
A90: 2024 | B90: Julio | C90: 2f048f31-0b0f-ef11-9ac8-00155d68220c | D90: 45422.85 | E90: INFOTIC - ICFES - PRUEBAS CSJ | F90: Janeth Annelise Araujo Ramos | G90: https://growdatasas.sharepoint.com/sites/pwa/INFOTIC - ICFES - PRUEBAS CSJ | H90: APLICACIÓN ELECTRÓNICA DEL EXAMEN PARA EJERCER LA PROFESIÓN DE ABOGADO A REALIZARSE EN LA VIGENCIA 2024SUMINISTRO DE MESA DE SERVICIO CON COBERTURA NACIONAL | I90: TI | J90: 0328 | K90: Activo.En Cierre | L90: =VLOOKUP(E90,Diccionario!C$2:AC$150,22,0) -> 830180856 | M90: =VLOOKUP(E90,Diccionario!C$2:AC$150,24,0) -> 45414 | N90: =VLOOKUP(E90,Diccionario!C$2:AC$150,25,0) -> 45596 | O90: =VLOOKUP(E90,Diccionario!C$2:AC$150,26,0) -> 5.97 | P90: =Q90-O90 -> 20.03 | Q90: =DATEDIF(M90,TODAY(),"m") -> 26 | R90: 6 | S90: 0.6 | T90: 0.56 | U90: 0 | V90: 0 | W90: =IFERROR(T90*L90,0) -> 4.6490128e+08 | X90: =S90*L90 -> 4.9810851e+08 | Y90: =IFERROR(W90-U90,0) -> 4.6490128e+08 | Z90: =W90-X90 -> -33207234 | AA90: =IFERROR(W90/U90,"No se realizó gasto en este corte") -> No se realizó gasto en este corte | AB90: =IFERROR( IF(OR(AA90="",AA90=0), "No calculado", IF(AA90>1,"Costo eficiente: se está gastando menos de lo presupuestado", IF(AA90=1,"Costo según lo presupuestado", "Costo ineficiente: se está gastando más de lo presupuestado"))), "No calculado") -> Costo eficiente: se está gastando menos de lo presupuestado | AC90: =IFERROR(W90/X90,0) -> 0.93333333 | AD90: =IF(OR(AC90="",AC90=0),"Sin Línea Base", IF(AC90>1,"Proyecto adelantado respecto al cronograma", IF(AC90=1,"Proyecto a tiempo según lo planificado", IF(AC90<1,"Proyecto atrasado con respecto al cronograma", "No calculado")))) -> Proyecto atrasado con respecto al cronograma | AE90: =IFERROR(L90/AA90,0) -> 0 | AF90: =IFERROR(AE90-L90,0) -> -830180856 | AG90: =VLOOKUP(Indicador!E90,Diccionario!C$1:AC$150,27,0) -> https://growdatasas.sharepoint.com/sites/Gestiondocumental/Administrativa/GD/Financiera/Documentos%20compartidos/Forms/AllItems.aspx?id=%2Fsites%2FGestiondocumental%2FAdministrativa%2FGD%2FFinanciera%2FDocumentos%20compartidos%2FAN%C3%81LISIS%20FINANCIERO%2FPMO%20SEGUIMIENTO%20A%20PROYECTOS%2F328%2E%20INFOTIC%20%2D%20ICFES%20%2D%20PRUEBAS%20CSJ&viewid=8ba7db0b%2Dbb48%2D40cc%2Da532%2D9b5bc18760d5 | AH90: 1 | AI90: 1
A91: 2024 | B91: Agosto | C91: 2f048f31-0b0f-ef11-9ac8-00155d68220c | D91: 45422.85 | E91: INFOTIC - ICFES - PRUEBAS CSJ | F91: Janeth Annelise Araujo Ramos | G91: https://growdatasas.sharepoint.com/sites/pwa/INFOTIC - ICFES - PRUEBAS CSJ | H91: APLICACIÓN ELECTRÓNICA DEL EXAMEN PARA EJERCER LA PROFESIÓN DE ABOGADO A REALIZARSE EN LA VIGENCIA 2024SUMINISTRO DE MESA DE SERVICIO CON COBERTURA NACIONAL | I91: TI | J91: 0328 | K91: Activo.En Cierre | L91: =VLOOKUP(E91,Diccionario!C$2:AC$150,22,0) -> 830180856 | M91: =VLOOKUP(E91,Diccionario!C$2:AC$150,24,0) -> 45414 | N91: =VLOOKUP(E91,Diccionario!C$2:AC$150,25,0) -> 45596 | O91: =VLOOKUP(E91,Diccionario!C$2:AC$150,26,0) -> 5.97 | P91: =Q91-O91 -> 20.03 | Q91: =DATEDIF(M91,TODAY(),"m") -> 26 | R91: 6 | S91: 0.8 | T91: 0.67 | U91: 0 | V91: 0 | W91: =IFERROR(T91*L91,0) -> 5.5622117e+08 | X91: =S91*L91 -> 6.6414468e+08 | Y91: =IFERROR(W91-U91,0) -> 5.5622117e+08 | Z91: =W91-X91 -> -1.0792351e+08 | AA91: =IFERROR(W91/U91,"No se realizó gasto en este corte") -> No se realizó gasto en este corte | AB91: =IFERROR( IF(OR(AA91="",AA91=0), "No calculado", IF(AA91>1,"Costo eficiente: se está gastando menos de lo presupuestado", IF(AA91=1,"Costo según lo presupuestado", "Costo ineficiente: se está gastando más de lo presupuestado"))), "No calculado") -> Costo eficiente: se está gastando menos de lo presupuestado | AC91: =IFERROR(W91/X91,0) -> 0.8375 | AD91: =IF(OR(AC91="",AC91=0),"Sin Línea Base", IF(AC91>1,"Proyecto adelantado respecto al cronograma", IF(AC91=1,"Proyecto a tiempo según lo planificado", IF(AC91<1,"Proyecto atrasado con respecto al cronograma", "No calculado")))) -> Proyecto atrasado con respecto al cronograma | AE91: =IFERROR(L91/AA91,0) -> 0 | AF91: =IFERROR(AE91-L91,0) -> -830180856 | AG91: =VLOOKUP(Indicador!E91,Diccionario!C$1:AC$150,27,0) -> https://growdatasas.sharepoint.com/sites/Gestiondocumental/Administrativa/GD/Financiera/Documentos%20compartidos/Forms/AllItems.aspx?id=%2Fsites%2FGestiondocumental%2FAdministrativa%2FGD%2FFinanciera%2FDocumentos%20compartidos%2FAN%C3%81LISIS%20FINANCIERO%2FPMO%20SEGUIMIENTO%20A%20PROYECTOS%2F328%2E%20INFOTIC%20%2D%20ICFES%20%2D%20PRUEBAS%20CSJ&viewid=8ba7db0b%2Dbb48%2D40cc%2Da532%2D9b5bc18760d5 | AH91: 1 | AI91: 1
A92: 2024 | B92: Septiembre | C92: 2f048f31-0b0f-ef11-9ac8-00155d68220c | D92: 45422.85 | E92: INFOTIC - ICFES - PRUEBAS CSJ | F92: Janeth Annelise Araujo Ramos | G92: https://growdatasas.sharepoint.com/sites/pwa/INFOTIC - ICFES - PRUEBAS CSJ | H92: APLICACIÓN ELECTRÓNICA DEL EXAMEN PARA EJERCER LA PROFESIÓN DE ABOGADO A REALIZARSE EN LA VIGENCIA 2024SUMINISTRO DE MESA DE SERVICIO CON COBERTURA NACIONAL | I92: TI | J92: 0328 | K92: Activo.En Cierre | L92: =VLOOKUP(E92,Diccionario!C$2:AC$150,22,0) -> 830180856 | M92: =VLOOKUP(E92,Diccionario!C$2:AC$150,24,0) -> 45414 | N92: =VLOOKUP(E92,Diccionario!C$2:AC$150,25,0) -> 45596 | O92: =VLOOKUP(E92,Diccionario!C$2:AC$150,26,0) -> 5.97 | P92: =Q92-O92 -> 20.03 | Q92: =DATEDIF(M92,TODAY(),"m") -> 26 | R92: 6 | S92: 0.9 | T92: 0.85 | U92: 0 | V92: 0 | W92: =IFERROR(T92*L92,0) -> 7.0565373e+08 | X92: =S92*L92 -> 7.4716277e+08 | Y92: =IFERROR(W92-U92,0) -> 7.0565373e+08 | Z92: =W92-X92 -> -41509043 | AA92: =IFERROR(W92/U92,"No se realizó gasto en este corte") -> No se realizó gasto en este corte | AB92: =IFERROR( IF(OR(AA92="",AA92=0), "No calculado", IF(AA92>1,"Costo eficiente: se está gastando menos de lo presupuestado", IF(AA92=1,"Costo según lo presupuestado", "Costo ineficiente: se está gastando más de lo presupuestado"))), "No calculado") -> Costo eficiente: se está gastando menos de lo presupuestado | AC92: =IFERROR(W92/X92,0) -> 0.94444444 | AD92: =IF(OR(AC92="",AC92=0),"Sin Línea Base", IF(AC92>1,"Proyecto adelantado respecto al cronograma", IF(AC92=1,"Proyecto a tiempo según lo planificado", IF(AC92<1,"Proyecto atrasado con respecto al cronograma", "No calculado")))) -> Proyecto atrasado con respecto al cronograma | AE92: =IFERROR(L92/AA92,0) -> 0 | AF92: =IFERROR(AE92-L92,0) -> -830180856 | AG92: =VLOOKUP(Indicador!E92,Diccionario!C$1:AC$150,27,0) -> https://growdatasas.sharepoint.com/sites/Gestiondocumental/Administrativa/GD/Financiera/Documentos%20compartidos/Forms/AllItems.aspx?id=%2Fsites%2FGestiondocumental%2FAdministrativa%2FGD%2FFinanciera%2FDocumentos%20compartidos%2FAN%C3%81LISIS%20FINANCIERO%2FPMO%20SEGUIMIENTO%20A%20PROYECTOS%2F328%2E%20INFOTIC%20%2D%20ICFES%20%2D%20PRUEBAS%20CSJ&viewid=8ba7db0b%2Dbb48%2D40cc%2Da532%2D9b5bc18760d5 | AH92: 1 | AI92: 1
A93: 2024 | B93: Octubre | C93: 2f048f31-0b0f-ef11-9ac8-00155d68220c | D93: 45422.85 | E93: INFOTIC - ICFES - PRUEBAS CSJ | F93: Janeth Annelise Araujo Ramos | G93: https://growdatasas.sharepoint.com/sites/pwa/INFOTIC - ICFES - PRUEBAS CSJ | H93: APLICACIÓN ELECTRÓNICA DEL EXAMEN PARA EJERCER LA PROFESIÓN DE ABOGADO A REALIZARSE EN LA VIGENCIA 2024SUMINISTRO DE MESA DE SERVICIO CON COBERTURA NACIONAL | I93: TI | J93: 0328 | K93: Activo.En Cierre | L93: =VLOOKUP(E93,Diccionario!C$2:AC$150,22,0) -> 830180856 | M93: =VLOOKUP(E93,Diccionario!C$2:AC$150,24,0) -> 45414 | N93: =VLOOKUP(E93,Diccionario!C$2:AC$150,25,0) -> 45596 | O93: =VLOOKUP(E93,Diccionario!C$2:AC$150,26,0) -> 5.97 | P93: =Q93-O93 -> 20.03 | Q93: =DATEDIF(M93,TODAY(),"m") -> 26 | R93: 6 | S93: 1 | T93: 1 | U93: 519098491 | V93: 519098491 | W93: =IFERROR(T93*L93,0) -> 830180856 | X93: =S93*L93 -> 830180856 | Y93: =IFERROR(W93-U93,0) -> 311082365 | Z93: =W93-X93 -> 0 | AA93: =IFERROR(W93/U93,"No se realizó gasto en este corte") -> 1.5992743 | AB93: =IFERROR( IF(OR(AA93="",AA93=0), "No calculado", IF(AA93>1,"Costo eficiente: se está gastando menos de lo presupuestado", IF(AA93=1,"Costo según lo presupuestado", "Costo ineficiente: se está gastando más de lo presupuestado"))), "No calculado") -> Costo eficiente: se está gastando menos de lo presupuestado | AC93: =IFERROR(W93/X93,0) -> 1 | AD93: =IF(OR(AC93="",AC93=0),"Sin Línea Base", IF(AC93>1,"Proyecto adelantado respecto al cronograma", IF(AC93=1,"Proyecto a tiempo según lo planificado", IF(AC93<1,"Proyecto atrasado con respecto al cronograma", "No calculado")))) -> Proyecto a tiempo según lo planificado | AE93: =IFERROR(L93/AA93,0) -> 519098491 | AF93: =IFERROR(AE93-L93,0) -> -311082365 | AG93: =VLOOKUP(Indicador!E93,Diccionario!C$1:AC$150,27,0) -> https://growdatasas.sharepoint.com/sites/Gestiondocumental/Administrativa/GD/Financiera/Documentos%20compartidos/Forms/AllItems.aspx?id=%2Fsites%2FGestiondocumental%2FAdministrativa%2FGD%2FFinanciera%2FDocumentos%20compartidos%2FAN%C3%81LISIS%20FINANCIERO%2FPMO%20SEGUIMIENTO%20A%20PROYECTOS%2F328%2E%20INFOTIC%20%2D%20ICFES%20%2D%20PRUEBAS%20CSJ&viewid=8ba7db0b%2Dbb48%2D40cc%2Da532%2D9b5bc18760d5 | AH93: 1 | AI93: 1
A94: 2024 | B94: Mayo | C94: 4387201d-861f-ef11-963a-00155d690311 | D94: 45443.822 | E94: UT - ENTERRITORIO 2027 | F94: Carlos Fernando Gomez Rodriguez | G94: https://growdatasas.sharepoint.com/sites/pwa/UT - ENTERRITORIO 2027 | H94: ​PRESTACIÓN DE SERVICIOS INTEGRALES EN TECNOLOGÍAS DE INFORMACIÓN Y COMUNICACIONES -TIC, PARA LLEVAR A CABO LA ADMINISTRACIÓN, OPERACIÓN, MANTENIMIENTO Y LA GESTIÓN DE LA PLATAFORMA TECNOLÓGICA DE ENTERRITORIO. | I94: TI | J94: 10025 | K94: Activo.En Ejecución | L94: =VLOOKUP(E94,Diccionario!C$2:AC$150,22,0) -> 4504425757 | M94: =VLOOKUP(E94,Diccionario!C$2:AC$150,24,0) -> 45439 | N94: =VLOOKUP(E94,Diccionario!C$2:AC$150,25,0) -> 46533 | O94: =VLOOKUP(E94,Diccionario!C$2:AC$150,26,0) -> 35.97 | P94: =Q94-O94 -> -34.97 | Q94: 1 | R94: 36 | S94: 0.02 | T94: 0.05 | U94: 14689 | V94: 14689 | W94: =IFERROR(T94*L94,0) -> 2.2522129e+08 | X94: =S94*L94 -> 90088515 | Y94: =IFERROR(W94-U94,0) -> 2.252066e+08 | Z94: =W94-X94 -> 1.3513277e+08 | AA94: =IFERROR(W94/U94,"No se realizó gasto en este corte") -> 15332.649 | AB94: =IFERROR( IF(OR(AA94="",AA94=0), "No calculado", IF(AA94>1,"Costo eficiente: se está gastando menos de lo presupuestado", IF(AA94=1,"Costo según lo presupuestado", "Costo ineficiente: se está gastando más de lo presupuestado"))), "No calculado") -> Costo eficiente: se está gastando menos de lo presupuestado | AC94: =IFERROR(W94/X94,0) -> 2.5 | AD94: =IF(OR(AC94="",AC94=0),"Sin Línea Base", IF(AC94>1,"Proyecto adelantado respecto al cronograma", IF(AC94=1,"Proyecto a tiempo según lo planificado", IF(AC94<1,"Proyecto atrasado con respecto al cronograma", "No calculado")))) -> Proyecto adelantado respecto al cronograma | AE94: =IFERROR(L94/AA94,0) -> 293780 | AF94: =IFERROR(AE94-L94,0) -> -4504131977 | AG94: =VLOOKUP(Indicador!E94,Diccionario!C$1:AC$150,27,0) -> https://growdatasas.sharepoint.com/:x:/r/sites/Gestiondocumental/Administrativa/GD/Financiera/_layouts/15/Doc.aspx?sourcedoc=%7B0974E3E6-B78B-4C29-8F8A-9CF11A235CF4%7D&file=20240530%20UT%20ENTERRITORIO%202027%20(SERVICIO).xlsm&action=default&mobileredirect=true | AH94: 1 | AI94: 1
A95: 2024 | B95: Junio | C95: 4387201d-861f-ef11-963a-00155d690311 | D95: 45443.822 | E95: UT - ENTERRITORIO 2027 | F95: Carlos Fernando Gomez Rodriguez | G95: https://growdatasas.sharepoint.com/sites/pwa/UT - ENTERRITORIO 2027 | H95: ​PRESTACIÓN DE SERVICIOS INTEGRALES EN TECNOLOGÍAS DE INFORMACIÓN Y COMUNICACIONES -TIC, PARA LLEVAR A CABO LA ADMINISTRACIÓN, OPERACIÓN, MANTENIMIENTO Y LA GESTIÓN DE LA PLATAFORMA TECNOLÓGICA DE ENTERRITORIO. | I95: TI | J95: 10025 | K95: Activo.En Ejecución | L95: =VLOOKUP(E95,Diccionario!C$2:AC$150,22,0) -> 4504425757 | M95: =VLOOKUP(E95,Diccionario!C$2:AC$150,24,0) -> 45439 | N95: =VLOOKUP(E95,Diccionario!C$2:AC$150,25,0) -> 46533 | O95: =VLOOKUP(E95,Diccionario!C$2:AC$150,26,0) -> 35.97 | P95: =Q95-O95 -> -33.97 | Q95: =Q94+1 -> 2 | R95: 36 | S95: =S94+0.03 -> 0.05 | T95: 0.07 | U95: 276012204 | V95: 276012204 | W95: =IFERROR(T95*L95,0) -> 3.153098e+08 | X95: =S95*L95 -> 2.2522129e+08 | Y95: =IFERROR(W95-U95,0) -> 39297599 | Z95: =W95-X95 -> 90088515 | AA95: =IFERROR(W95/U95,"No se realizó gasto en este corte") -> 1.1423763 | AB95: =IFERROR( IF(OR(AA95="",AA95=0), "No calculado", IF(AA95>1,"Costo eficiente: se está gastando menos de lo presupuestado", IF(AA95=1,"Costo según lo presupuestado", "Costo ineficiente: se está gastando más de lo presupuestado"))), "No calculado") -> Costo eficiente: se está gastando menos de lo presupuestado | AC95: =IFERROR(W95/X95,0) -> 1.4 | AD95: =IF(OR(AC95="",AC95=0),"Sin Línea Base", IF(AC95>1,"Proyecto adelantado respecto al cronograma", IF(AC95=1,"Proyecto a tiempo según lo planificado", IF(AC95<1,"Proyecto atrasado con respecto al cronograma", "No calculado")))) -> Proyecto adelantado respecto al cronograma | AE95: =IFERROR(L95/AA95,0) -> 3.9430315e+09 | AF95: =IFERROR(AE95-L95,0) -> -5.6139427e+08 | AG95: =VLOOKUP(Indicador!E95,Diccionario!C$1:AC$150,27,0) -> https://growdatasas.sharepoint.com/:x:/r/sites/Gestiondocumental/Administrativa/GD/Financiera/_layouts/15/Doc.aspx?sourcedoc=%7B0974E3E6-B78B-4C29-8F8A-9CF11A235CF4%7D&file=20240530%20UT%20ENTERRITORIO%202027%20(SERVICIO).xlsm&action=default&mobileredirect=true | AH95: 1 | AI95: 1
A96: 2024 | B96: Julio | C96: 4387201d-861f-ef11-963a-00155d690311 | D96: 45443.822 | E96: UT - ENTERRITORIO 2027 | F96: Carlos Fernando Gomez Rodriguez | G96: https://growdatasas.sharepoint.com/sites/pwa/UT - ENTERRITORIO 2027 | H96: ​PRESTACIÓN DE SERVICIOS INTEGRALES EN TECNOLOGÍAS DE INFORMACIÓN Y COMUNICACIONES -TIC, PARA LLEVAR A CABO LA ADMINISTRACIÓN, OPERACIÓN, MANTENIMIENTO Y LA GESTIÓN DE LA PLATAFORMA TECNOLÓGICA DE ENTERRITORIO. | I96: TI | J96: 10025 | K96: Activo.En Ejecución | L96: =VLOOKUP(E96,Diccionario!C$2:AC$150,22,0) -> 4504425757 | M96: =VLOOKUP(E96,Diccionario!C$2:AC$150,24,0) -> 45439 | N96: =VLOOKUP(E96,Diccionario!C$2:AC$150,25,0) -> 46533 | O96: =VLOOKUP(E96,Diccionario!C$2:AC$150,26,0) -> 35.97 | P96: =Q96-O96 -> -32.97 | Q96: =Q95+1 -> 3 | R96: 36 | S96: =S95+0.03 -> 0.08 | T96: 0.08 | U96: 120457490 | V96: 120457490 | W96: =IFERROR(T96*L96,0) -> 3.6035406e+08 | X96: =S96*L96 -> 3.6035406e+08 | Y96: =IFERROR(W96-U96,0) -> 2.3989657e+08 | Z96: =W96-X96 -> 0 | AA96: =IFERROR(W96/U96,"No se realizó gasto en este corte") -> 2.9915455 | AB96: =IFERROR( IF(OR(AA96="",AA96=0), "No calculado", IF(AA96>1,"Costo eficiente: se está gastando menos de lo presupuestado", IF(AA96=1,"Costo según lo presupuestado", "Costo ineficiente: se está gastando más de lo presupuestado"))), "No calculado") -> Costo eficiente: se está gastando menos de lo presupuestado | AC96: =IFERROR(W96/X96,0) -> 1 | AD96: =IF(OR(AC96="",AC96=0),"Sin Línea Base", IF(AC96>1,"Proyecto adelantado respecto al cronograma", IF(AC96=1,"Proyecto a tiempo según lo planificado", IF(AC96<1,"Proyecto atrasado con respecto al cronograma", "No calculado")))) -> Proyecto a tiempo según lo planificado | AE96: =IFERROR(L96/AA96,0) -> 1505718625 | AF96: =IFERROR(AE96-L96,0) -> -2998707132 | AG96: =VLOOKUP(Indicador!E96,Diccionario!C$1:AC$150,27,0) -> https://growdatasas.sharepoint.com/:x:/r/sites/Gestiondocumental/Administrativa/GD/Financiera/_layouts/15/Doc.aspx?sourcedoc=%7B0974E3E6-B78B-4C29-8F8A-9CF11A235CF4%7D&file=20240530%20UT%20ENTERRITORIO%202027%20(SERVICIO).xlsm&action=default&mobileredirect=true | AH96: 1 | AI96: 1
A97: 2024 | B97: Agosto | C97: 4387201d-861f-ef11-963a-00155d690311 | D97: 45443.822 | E97: UT - ENTERRITORIO 2027 | F97: Carlos Fernando Gomez Rodriguez | G97: https://growdatasas.sharepoint.com/sites/pwa/UT - ENTERRITORIO 2027 | H97: ​PRESTACIÓN DE SERVICIOS INTEGRALES EN TECNOLOGÍAS DE INFORMACIÓN Y COMUNICACIONES -TIC, PARA LLEVAR A CABO LA ADMINISTRACIÓN, OPERACIÓN, MANTENIMIENTO Y LA GESTIÓN DE LA PLATAFORMA TECNOLÓGICA DE ENTERRITORIO. | I97: TI | J97: 10025 | K97: Activo.En Ejecución | L97: =VLOOKUP(E97,Diccionario!C$2:AC$150,22,0) -> 4504425757 | M97: =VLOOKUP(E97,Diccionario!C$2:AC$150,24,0) -> 45439 | N97: =VLOOKUP(E97,Diccionario!C$2:AC$150,25,0) -> 46533 | O97: =VLOOKUP(E97,Diccionario!C$2:AC$150,26,0) -> 35.97 | P97: =Q97-O97 -> -31.97 | Q97: =Q96+1 -> 4 | R97: 36 | S97: =S96+0.03 -> 0.11 | T97: 0.11 | U97: 110451020 | V97: 110451020 | W97: =IFERROR(T97*L97,0) -> 4.9548683e+08 | X97: =S97*L97 -> 4.9548683e+08 | Y97: =IFERROR(W97-U97,0) -> 3.8503581e+08 | Z97: =W97-X97 -> 0 | AA97: =IFERROR(W97/U97,"No se realizó gasto en este corte") -> 4.4860322 | AB97: =IFERROR( IF(OR(AA97="",AA97=0), "No calculado", IF(AA97>1,"Costo eficiente: se está gastando menos de lo presupuestado", IF(AA97=1,"Costo según lo presupuestado", "Costo ineficiente: se está gastando más de lo presupuestado"))), "No calculado") -> Costo eficiente: se está gastando menos de lo presupuestado | AC97: =IFERROR(W97/X97,0) -> 1 | AD97: =IF(OR(AC97="",AC97=0),"Sin Línea Base", IF(AC97>1,"Proyecto adelantado respecto al cronograma", IF(AC97=1,"Proyecto a tiempo según lo planificado", IF(AC97<1,"Proyecto atrasado con respecto al cronograma", "No calculado")))) -> Proyecto a tiempo según lo planificado | AE97: =IFERROR(L97/AA97,0) -> 1.0041002e+09 | AF97: =IFERROR(AE97-L97,0) -> -3.5003256e+09 | AG97: =VLOOKUP(Indicador!E97,Diccionario!C$1:AC$150,27,0) -> https://growdatasas.sharepoint.com/:x:/r/sites/Gestiondocumental/Administrativa/GD/Financiera/_layouts/15/Doc.aspx?sourcedoc=%7B0974E3E6-B78B-4C29-8F8A-9CF11A235CF4%7D&file=20240530%20UT%20ENTERRITORIO%202027%20(SERVICIO).xlsm&action=default&mobileredirect=true | AH97: 1 | AI97: 1
A98: 2024 | B98: Septiembre | C98: 4387201d-861f-ef11-963a-00155d690311 | D98: 45443.822 | E98: UT - ENTERRITORIO 2027 | F98: Carlos Fernando Gomez Rodriguez | G98: https://growdatasas.sharepoint.com/sites/pwa/UT - ENTERRITORIO 2027 | H98: ​PRESTACIÓN DE SERVICIOS INTEGRALES EN TECNOLOGÍAS DE INFORMACIÓN Y COMUNICACIONES -TIC, PARA LLEVAR A CABO LA ADMINISTRACIÓN, OPERACIÓN, MANTENIMIENTO Y LA GESTIÓN DE LA PLATAFORMA TECNOLÓGICA DE ENTERRITORIO. | I98: TI | J98: 10025 | K98: Activo.En Ejecución | L98: =VLOOKUP(E98,Diccionario!C$2:AC$150,22,0) -> 4504425757 | M98: =VLOOKUP(E98,Diccionario!C$2:AC$150,24,0) -> 45439 | N98: =VLOOKUP(E98,Diccionario!C$2:AC$150,25,0) -> 46533 | O98: =VLOOKUP(E98,Diccionario!C$2:AC$150,26,0) -> 35.97 | P98: =Q98-O98 -> -30.97 | Q98: =Q97+1 -> 5 | R98: 36 | S98: =S97+0.03 -> 0.14 | T98: 0.13 | U98: 121118864 | V98: 121118864 | W98: =IFERROR(T98*L98,0) -> 5.8557535e+08 | X98: =S98*L98 -> 6.3061961e+08 | Y98: =IFERROR(W98-U98,0) -> 4.6445648e+08 | Z98: =W98-X98 -> -45044258 | AA98: =IFERROR(W98/U98,"No se realizó gasto en este corte") -> 4.8347163 | AB98: =IFERROR( IF(OR(AA98="",AA98=0), "No calculado", IF(AA98>1,"Costo eficiente: se está gastando menos de lo presupuestado", IF(AA98=1,"Costo según lo presupuestado", "Costo ineficiente: se está gastando más de lo presupuestado"))), "No calculado") -> Costo eficiente: se está gastando menos de lo presupuestado | AC98: =IFERROR(W98/X98,0) -> 0.92857143 | AD98: =IF(OR(AC98="",AC98=0),"Sin Línea Base", IF(AC98>1,"Proyecto adelantado respecto al cronograma", IF(AC98=1,"Proyecto a tiempo según lo planificado", IF(AC98<1,"Proyecto atrasado con respecto al cronograma", "No calculado")))) -> Proyecto atrasado con respecto al cronograma | AE98: =IFERROR(L98/AA98,0) -> 9.3168357e+08 | AF98: =IFERROR(AE98-L98,0) -> -3.5727422e+09 | AG98: =VLOOKUP(Indicador!E98,Diccionario!C$1:AC$150,27,0) -> https://growdatasas.sharepoint.com/:x:/r/sites/Gestiondocumental/Administrativa/GD/Financiera/_layouts/15/Doc.aspx?sourcedoc=%7B0974E3E6-B78B-4C29-8F8A-9CF11A235CF4%7D&file=20240530%20UT%20ENTERRITORIO%202027%20(SERVICIO).xlsm&action=default&mobileredirect=true | AH98: 1 | AI98: 1
A99: 2024 | B99: Octubre | C99: 4387201d-861f-ef11-963a-00155d690311 | D99: 45443.822 | E99: UT - ENTERRITORIO 2027 | F99: Carlos Fernando Gomez Rodriguez | G99: https://growdatasas.sharepoint.com/sites/pwa/UT - ENTERRITORIO 2027 | H99: ​PRESTACIÓN DE SERVICIOS INTEGRALES EN TECNOLOGÍAS DE INFORMACIÓN Y COMUNICACIONES -TIC, PARA LLEVAR A CABO LA ADMINISTRACIÓN, OPERACIÓN, MANTENIMIENTO Y LA GESTIÓN DE LA PLATAFORMA TECNOLÓGICA DE ENTERRITORIO. | I99: TI | J99: 10025 | K99: Activo.En Ejecución | L99: =VLOOKUP(E99,Diccionario!C$2:AC$150,22,0) -> 4504425757 | M99: =VLOOKUP(E99,Diccionario!C$2:AC$150,24,0) -> 45439 | N99: =VLOOKUP(E99,Diccionario!C$2:AC$150,25,0) -> 46533 | O99: =VLOOKUP(E99,Diccionario!C$2:AC$150,26,0) -> 35.97 | P99: =Q99-O99 -> -29.97 | Q99: =Q98+1 -> 6 | R99: 36 | S99: =S98+0.03 -> 0.17 | T99: 0.18 | U99: 121118864 | V99: 121118864 | W99: =IFERROR(T99*L99,0) -> 8.1079664e+08 | X99: =S99*L99 -> 7.6575238e+08 | Y99: =IFERROR(W99-U99,0) -> 6.8967777e+08 | Z99: =W99-X99 -> 45044258 | AA99: =IFERROR(W99/U99,"No se realizó gasto en este corte") -> 6.6942226 | AB99: =IFERROR( IF(OR(AA99="",AA99=0), "No calculado", IF(AA99>1,"Costo eficiente: se está gastando menos de lo presupuestado", IF(AA99=1,"Costo según lo presupuestado", "Costo ineficiente: se está gastando más de lo presupuestado"))), "No calculado") -> Costo eficiente: se está gastando menos de lo presupuestado | AC99: =IFERROR(W99/X99,0) -> 1.0588235 | AD99: =IF(OR(AC99="",AC99=0),"Sin Línea Base", IF(AC99>1,"Proyecto adelantado respecto al cronograma", IF(AC99=1,"Proyecto a tiempo según lo planificado", IF(AC99<1,"Proyecto atrasado con respecto al cronograma", "No calculado")))) -> Proyecto adelantado respecto al cronograma | AE99: =IFERROR(L99/AA99,0) -> 6.7288258e+08 | AF99: =IFERROR(AE99-L99,0) -> -3.8315432e+09 | AG99: =VLOOKUP(Indicador!E99,Diccionario!C$1:AC$150,27,0) -> https://growdatasas.sharepoint.com/:x:/r/sites/Gestiondocumental/Administrativa/GD/Financiera/_layouts/15/Doc.aspx?sourcedoc=%7B0974E3E6-B78B-4C29-8F8A-9CF11A235CF4%7D&file=20240530%20UT%20ENTERRITORIO%202027%20(SERVICIO).xlsm&action=default&mobileredirect=true | AH99: 1 | AI99: 1
A100: 2024 | B100: Noviembre | C100: 4387201d-861f-ef11-963a-00155d690311 | D100: 45443.822 | E100: UT - ENTERRITORIO 2027 | F100: Carlos Fernando Gomez Rodriguez | G100: https://growdatasas.sharepoint.com/sites/pwa/UT - ENTERRITORIO 2027 | H100: ​PRESTACIÓN DE SERVICIOS INTEGRALES EN TECNOLOGÍAS DE INFORMACIÓN Y COMUNICACIONES -TIC, PARA LLEVAR A CABO LA ADMINISTRACIÓN, OPERACIÓN, MANTENIMIENTO Y LA GESTIÓN DE LA PLATAFORMA TECNOLÓGICA DE ENTERRITORIO. | I100: TI | J100: 10025 | K100: Activo.En Ejecución | L100: =VLOOKUP(E100,Diccionario!C$2:AC$150,22,0) -> 4504425757 | M100: =VLOOKUP(E100,Diccionario!C$2:AC$150,24,0) -> 45439 | N100: =VLOOKUP(E100,Diccionario!C$2:AC$150,25,0) -> 46533 | O100: =VLOOKUP(E100,Diccionario!C$2:AC$150,26,0) -> 35.97 | P100: =Q100-O100 -> -28.97 | Q100: =Q99+1 -> 7 | R100: 36 | S100: =S99+0.03 -> 0.2 | T100: 0.21 | U100: 121118864 | V100: 121118864 | W100: =IFERROR(T100*L100,0) -> 9.4592941e+08 | X100: =S100*L100 -> 9.0088515e+08 | Y100: =IFERROR(W100-U100,0) -> 8.2481054e+08 | Z100: =W100-X100 -> 45044258 | AA100: =IFERROR(W100/U100,"No se realizó gasto en este corte") -> 7.8099264 | AB100: =IFERROR( IF(OR(AA100="",AA100=0), "No calculado", IF(AA100>1,"Costo eficiente: se está gastando menos de lo presupuestado", IF(AA100=1,"Costo según lo presupuestado", "Costo ineficiente: se está gastando más de lo presupuestado"))), "No calculado") -> Costo eficiente: se está gastando menos de lo presupuestado | AC100: =IFERROR(W100/X100,0) -> 1.05 | AD100: =IF(OR(AC100="",AC100=0),"Sin Línea Base", IF(AC100>1,"Proyecto adelantado respecto al cronograma", IF(AC100=1,"Proyecto a tiempo según lo planificado", IF(AC100<1,"Proyecto atrasado con respecto al cronograma", "No calculado")))) -> Proyecto adelantado respecto al cronograma | AE100: =IFERROR(L100/AA100,0) -> 5.767565e+08 | AF100: =IFERROR(AE100-L100,0) -> -3.9276693e+09 | AG100: =VLOOKUP(Indicador!E100,Diccionario!C$1:AC$150,27,0) -> https://growdatasas.sharepoint.com/:x:/r/sites/Gestiondocumental/Administrativa/GD/Financiera/_layouts/15/Doc.aspx?sourcedoc=%7B0974E3E6-B78B-4C29-8F8A-9CF11A235CF4%7D&file=20240530%20UT%20ENTERRITORIO%202027%20(SERVICIO).xlsm&action=default&mobileredirect=true | AH100: 1 | AI100: 1
A101: 2024 | B101: Diciembre | C101: 4387201d-861f-ef11-963a-00155d690311 | D101: 45443.822 | E101: UT - ENTERRITORIO 2027 | F101: Carlos Fernando Gomez Rodriguez | G101: https://growdatasas.sharepoint.com/sites/pwa/UT - ENTERRITORIO 2027 | H101: ​PRESTACIÓN DE SERVICIOS INTEGRALES EN TECNOLOGÍAS DE INFORMACIÓN Y COMUNICACIONES -TIC, PARA LLEVAR A CABO LA ADMINISTRACIÓN, OPERACIÓN, MANTENIMIENTO Y LA GESTIÓN DE LA PLATAFORMA TECNOLÓGICA DE ENTERRITORIO. | I101: TI | J101: 10025 | K101: Activo.En Ejecución | L101: =VLOOKUP(E101,Diccionario!C$2:AC$150,22,0) -> 4504425757 | M101: =VLOOKUP(E101,Diccionario!C$2:AC$150,24,0) -> 45439 | N101: =VLOOKUP(E101,Diccionario!C$2:AC$150,25,0) -> 46533 | O101: =VLOOKUP(E101,Diccionario!C$2:AC$150,26,0) -> 35.97 | P101: =Q101-O101 -> -27.97 | Q101: =Q100+1 -> 8 | R101: 36 | S101: =S100+0.03 -> 0.23 | T101: 0.23 | U101: 121118864 | V101: 121118864 | W101: =IFERROR(T101*L101,0) -> 1.0360179e+09 | X101: =S101*L101 -> 1.0360179e+09 | Y101: =IFERROR(W101-U101,0) -> 9.1489906e+08 | Z101: =W101-X101 -> 0 | AA101: =IFERROR(W101/U101,"No se realizó gasto en este corte") -> 8.5537289 | AB101: =IFERROR( IF(OR(AA101="",AA101=0), "No calculado", IF(AA101>1,"Costo eficiente: se está gastando menos de lo presupuestado", IF(AA101=1,"Costo según lo presupuestado", "Costo ineficiente: se está gastando más de lo presupuestado"))), "No calculado") -> Costo eficiente: se está gastando menos de lo presupuestado | AC101: =IFERROR(W101/X101,0) -> 1 | AD101: =IF(OR(AC101="",AC101=0),"Sin Línea Base", IF(AC101>1,"Proyecto adelantado respecto al cronograma", IF(AC101=1,"Proyecto a tiempo según lo planificado", IF(AC101<1,"Proyecto atrasado con respecto al cronograma", "No calculado")))) -> Proyecto a tiempo según lo planificado | AE101: =IFERROR(L101/AA101,0) -> 5.2660376e+08 | AF101: =IFERROR(AE101-L101,0) -> -3.977822e+09 | AG101: =VLOOKUP(Indicador!E101,Diccionario!C$1:AC$150,27,0) -> https://growdatasas.sharepoint.com/:x:/r/sites/Gestiondocumental/Administrativa/GD/Financiera/_layouts/15/Doc.aspx?sourcedoc=%7B0974E3E6-B78B-4C29-8F8A-9CF11A235CF4%7D&file=20240530%20UT%20ENTERRITORIO%202027%20(SERVICIO).xlsm&action=default&mobileredirect=true | AH101: 1 | AI101: 1
A102: 2025 | B102: Enero | C102: 4387201d-861f-ef11-963a-00155d690311 | D102: 45443.822 | E102: UT - ENTERRITORIO 2027 | F102: Carlos Fernando Gomez Rodriguez | G102: https://growdatasas.sharepoint.com/sites/pwa/UT - ENTERRITORIO 2027 | H102: ​PRESTACIÓN DE SERVICIOS INTEGRALES EN TECNOLOGÍAS DE INFORMACIÓN Y COMUNICACIONES -TIC, PARA LLEVAR A CABO LA ADMINISTRACIÓN, OPERACIÓN, MANTENIMIENTO Y LA GESTIÓN DE LA PLATAFORMA TECNOLÓGICA DE ENTERRITORIO. | I102: TI | J102: 10025 | K102: Activo.En Ejecución | L102: =VLOOKUP(E102,Diccionario!C$2:AC$150,22,0) -> 4504425757 | M102: =VLOOKUP(E102,Diccionario!C$2:AC$150,24,0) -> 45439 | N102: =VLOOKUP(E102,Diccionario!C$2:AC$150,25,0) -> 46533 | O102: =VLOOKUP(E102,Diccionario!C$2:AC$150,26,0) -> 35.97 | P102: =Q102-O102 -> -26.97 | Q102: =Q101+1 -> 9 | R102: 36 | S102: =S101+0.03 -> 0.26 | T102: 0.26 | U102: 121209264 | V102: 121209264 | W102: =IFERROR(T102*L102,0) -> 1.1711507e+09 | X102: =S102*L102 -> 1.1711507e+09 | Y102: =IFERROR(W102-U102,0) -> 1.0499414e+09 | Z102: =W102-X102 -> 0 | AA102: =IFERROR(W102/U102,"No se realizó gasto en este corte") -> 9.662221 | AB102: =IFERROR( IF(OR(AA102="",AA102=0), "No calculado", IF(AA102>1,"Costo eficiente: se está gastando menos de lo presupuestado", IF(AA102=1,"Costo según lo presupuestado", "Costo ineficiente: se está gastando más de lo presupuestado"))), "No calculado") -> Costo eficiente: se está gastando menos de lo presupuestado | AC102: =IFERROR(W102/X102,0) -> 1 | AD102: =IF(OR(AC102="",AC102=0),"Sin Línea Base", IF(AC102>1,"Proyecto adelantado respecto al cronograma", IF(AC102=1,"Proyecto a tiempo según lo planificado", IF(AC102<1,"Proyecto atrasado con respecto al cronograma", "No calculado")))) -> Proyecto a tiempo según lo planificado | AE102: =IFERROR(L102/AA102,0) -> 4.6618948e+08 | AF102: =IFERROR(AE102-L102,0) -> -4.0382363e+09 | AG102: =VLOOKUP(Indicador!E102,Diccionario!C$1:AC$150,27,0) -> https://growdatasas.sharepoint.com/:x:/r/sites/Gestiondocumental/Administrativa/GD/Financiera/_layouts/15/Doc.aspx?sourcedoc=%7B0974E3E6-B78B-4C29-8F8A-9CF11A235CF4%7D&file=20240530%20UT%20ENTERRITORIO%202027%20(SERVICIO).xlsm&action=default&mobileredirect=true | AH102: 1 | AI102: 1
A103: 2025 | B103: Febrero | C103: 4387201d-861f-ef11-963a-00155d690311 | D103: 45443.822 | E103: UT - ENTERRITORIO 2027 | F103: Carlos Fernando Gomez Rodriguez | G103: https://growdatasas.sharepoint.com/sites/pwa/UT - ENTERRITORIO 2027 | H103: ​PRESTACIÓN DE SERVICIOS INTEGRALES EN TECNOLOGÍAS DE INFORMACIÓN Y COMUNICACIONES -TIC, PARA LLEVAR A CABO LA ADMINISTRACIÓN, OPERACIÓN, MANTENIMIENTO Y LA GESTIÓN DE LA PLATAFORMA TECNOLÓGICA DE ENTERRITORIO. | I103: TI | J103: 10025 | K103: Activo.En Ejecución | L103: =VLOOKUP(E103,Diccionario!C$2:AC$150,22,0) -> 4504425757 | M103: =VLOOKUP(E103,Diccionario!C$2:AC$150,24,0) -> 45439 | N103: =VLOOKUP(E103,Diccionario!C$2:AC$150,25,0) -> 46533 | O103: =VLOOKUP(E103,Diccionario!C$2:AC$150,26,0) -> 35.97 | P103: =Q103-O103 -> -25.97 | Q103: =Q102+1 -> 10 | R103: 36 | S103: =S102+0.03 -> 0.29 | T103: 0.29 | U103: 121209264 | V103: 121209264 | W103: =IFERROR(T103*L103,0) -> 1.3062835e+09 | X103: =S103*L103 -> 1.3062835e+09 | Y103: =IFERROR(W103-U103,0) -> 1.1850742e+09 | Z103: =W103-X103 -> 0 | AA103: =IFERROR(W103/U103,"No se realizó gasto en este corte") -> 10.777093 | AB103: =IFERROR( IF(OR(AA103="",AA103=0), "No calculado", IF(AA103>1,"Costo eficiente: se está gastando menos de lo presupuestado", IF(AA103=1,"Costo según lo presupuestado", "Costo ineficiente: se está gastando más de lo presupuestado"))), "No calculado") -> Costo eficiente: se está gastando menos de lo presupuestado | AC103: =IFERROR(W103/X103,0) -> 1 | AD103: =IF(OR(AC103="",AC103=0),"Sin Línea Base", IF(AC103>1,"Proyecto adelantado respecto al cronograma", IF(AC103=1,"Proyecto a tiempo según lo planificado", IF(AC103<1,"Proyecto atrasado con respecto al cronograma", "No calculado")))) -> Proyecto a tiempo según lo planificado | AE103: =IFERROR(L103/AA103,0) -> 4.1796298e+08 | AF103: =IFERROR(AE103-L103,0) -> -4.0864628e+09 | AG103: =VLOOKUP(Indicador!E103,Diccionario!C$1:AC$150,27,0) -> https://growdatasas.sharepoint.com/:x:/r/sites/Gestiondocumental/Administrativa/GD/Financiera/_layouts/15/Doc.aspx?sourcedoc=%7B0974E3E6-B78B-4C29-8F8A-9CF11A235CF4%7D&file=20240530%20UT%20ENTERRITORIO%202027%20(SERVICIO).xlsm&action=default&mobileredirect=true | AH103: 1 | AI103: 1
A104: 2025 | B104: Marzo | C104: 4387201d-861f-ef11-963a-00155d690311 | D104: 45443.822 | E104: UT - ENTERRITORIO 2027 | F104: Carlos Fernando Gomez Rodriguez | G104: https://growdatasas.sharepoint.com/sites/pwa/UT - ENTERRITORIO 2027 | H104: ​PRESTACIÓN DE SERVICIOS INTEGRALES EN TECNOLOGÍAS DE INFORMACIÓN Y COMUNICACIONES -TIC, PARA LLEVAR A CABO LA ADMINISTRACIÓN, OPERACIÓN, MANTENIMIENTO Y LA GESTIÓN DE LA PLATAFORMA TECNOLÓGICA DE ENTERRITORIO. | I104: TI | J104: 10025 | K104: Activo.En Ejecución | L104: =VLOOKUP(E104,Diccionario!C$2:AC$150,22,0) -> 4504425757 | M104: =VLOOKUP(E104,Diccionario!C$2:AC$150,24,0) -> 45439 | N104: =VLOOKUP(E104,Diccionario!C$2:AC$150,25,0) -> 46533 | O104: =VLOOKUP(E104,Diccionario!C$2:AC$150,26,0) -> 35.97 | P104: =Q104-O104 -> -24.97 | Q104: =Q103+1 -> 11 | R104: 36 | S104: =S103+0.03 -> 0.32 | T104: 0.32 | U104: 121209264 | V104: 121209264 | W104: =IFERROR(T104*L104,0) -> 1.4414162e+09 | X104: =S104*L104 -> 1.4414162e+09 | Y104: =IFERROR(W104-U104,0) -> 1.320207e+09 | Z104: =W104-X104 -> 0 | AA104: =IFERROR(W104/U104,"No se realizó gasto en este corte") -> 11.891964 | AB104: =IFERROR( IF(OR(AA104="",AA104=0), "No calculado", IF(AA104>1,"Costo eficiente: se está gastando menos de lo presupuestado", IF(AA104=1,"Costo según lo presupuestado", "Costo ineficiente: se está gastando más de lo presupuestado"))), "No calculado") -> Costo eficiente: se está gastando menos de lo presupuestado | AC104: =IFERROR(W104/X104,0) -> 1 | AD104: =IF(OR(AC104="",AC104=0),"Sin Línea Base", IF(AC104>1,"Proyecto adelantado respecto al cronograma", IF(AC104=1,"Proyecto a tiempo según lo planificado", IF(AC104<1,"Proyecto atrasado con respecto al cronograma", "No calculado")))) -> Proyecto a tiempo según lo planificado | AE104: =IFERROR(L104/AA104,0) -> 378778950 | AF104: =IFERROR(AE104-L104,0) -> -4125646807 | AG104: =VLOOKUP(Indicador!E104,Diccionario!C$1:AC$150,27,0) -> https://growdatasas.sharepoint.com/:x:/r/sites/Gestiondocumental/Administrativa/GD/Financiera/_layouts/15/Doc.aspx?sourcedoc=%7B0974E3E6-B78B-4C29-8F8A-9CF11A235CF4%7D&file=20240530%20UT%20ENTERRITORIO%202027%20(SERVICIO).xlsm&action=default&mobileredirect=true | AH104: 1 | AI104: 1
