Workbook

Sheet Indicador
A1: Año | B1: Mes | C1: ProjectId | D1: ProjectCreatedDate | E1: ProjectName | F1: ProjectOwnerName | G1: ProjectWorkspaceInternalUrl | H1: Objetocontractual | I1: Portafolio | J1: CentrodeCostosProyecto | K1: Estado | L1: Presupuesto | M1: Inicio | N1: Fin | O1: Meses | P1: Tiempo Diferencia | Q1: Tiempo Ejecución | R1: Tiempo Proyectado | S1: % Planeado | T1: Completado Real | U1: AC (Actual Cost) | V1: Costo Mensual | W1: EV (Earned Value) | X1: PV (Planned Value) | Y1: CV (Cost Variance) | Z1: SV (Schedule Variance) | AA1: CPI (Cost Performance Index) | AB1: Detalle de CPI | AC1: SPI (Schedule Performance Index) | AD1: Detalle SPI | AE1: EAC (Estimación al finalizar) | AF1: VAC (Exceso de presupuesto proyectado) | AG1: Ruta | AH1: Meta SPI | AI1: Meta CPI | AJ1: Estado CMMI | AK1: Columna1
A2: 2024 | B2: Enero | C2: 227b8bc1-c7ab-ee11-ba7f-00155d104f2c | D2: 45296.529 | E2: CCD - DPC - IMPLEMENTACIÓN ERP | F2: Johan Sebastian Rodriguez Niño | G2: https://growdatasas.sharepoint.com/sites/pwa/CCD - DPC - IMPLEMENTACIÓN ERP | H2: Suministro e implementación del sistema de información ADMINISTRATIVO ERP NOVASOFT – versión ENTERPRISE WEB y el GESTOR DE RIESGOS para la entidad Defensoría del Pueblo.Incluye: 14 módulos específicos + 5 módulos financieros con licencia para 5000 usuarios finales, Licenciamiento de la Base de Datos SQL Server (Estándar para 8 Cores), Consultoría estándar de implementación de cada uno de los sistemas ofrecidos, soporte y actualización por 2 años y una bolsa de horas (según acuerdo por 2 años) | I2: DATOS Y SISTEMAS DE INFORMACIÓN | J2: 0318 | K2: Activo.En Ejecución | L2: =VLOOKUP(E2,[1]Diccionario!C$2:AC$150,22,0) -> 3323223361 | M2: =VLOOKUP(E2,[1]Diccionario!C$2:AC$150,24,0) -> 45300 | N2: =VLOOKUP(E2,[1]Diccionario!C$2:AC$150,25,0) -> 45473 | O2: =VLOOKUP(E2,[1]Diccionario!C$2:AC$150,26,0) -> 5.7 | P2: =Q2-O2 -> -4.7 | Q2: 1 | R2: 6 | S2: 0.2 | T2: 0.2 | U2: =TablaIndicador[[#This Row],[Costo Mensual]] -> 0 | W2: =IFERROR(T2*L2,0) -> 6.6464467e+08 | X2: =S2*L2 -> 6.6464467e+08 | Y2: =IFERROR(W2-U2,0) -> 6.6464467e+08 | Z2: =W2-X2 -> 0 | AA2: =IFERROR(W2/U2,"No se realizó gasto en este corte") -> No se realizó gasto en este corte | AB2: =IFERROR( IF(OR(AA2="",AA2=0), "No calculado", IF(AA2>1,"Costo eficiente: se está gastando menos de lo presupuestado", IF(AA2=1,"Costo según lo presupuestado", "Costo ineficiente: se está gastando más de lo presupuestado"))), "No calculado") -> Costo eficiente: se está gastando menos de lo presupuestado | AC2: =IFERROR(W2/X2,0) -> 1 | AD2: =IF(OR(AC2="",AC2=0),"Sin Línea Base", IF(AC2>1,"Proyecto adelantado respecto al cronograma", IF(AC2=1,"Proyecto a tiempo según lo planificado", IF(AC2<1,"Proyecto atrasado con respecto al cronograma", "No calculado")))) -> Proyecto a tiempo según lo planificado | AE2: =IFERROR(L2/AA2,0) -> 0 | AF2: =IFERROR(AE2-L2,0) -> -3323223361 | AG2: =VLOOKUP(Indicador!E25,[1]Diccionario!C$1:AC$150,27,0) -> https://growdatasas.sharepoint.com/:x:/r/sites/Gestiondocumental/Administrativa/GD/Financiera/_layouts/15/Doc.aspx?sourcedoc=%7BC3EFE0E2-C211-45B0-905D-ECEF11221767%7D&file=299.%20DEFENSORIA_ERP.xlsm&action=default&mobileredirect=true | AH2: 1 | AI2: 1 | AJ2: ok
A3: 2024 | B3: Febrero | C3: 227b8bc1-c7ab-ee11-ba7f-00155d104f2c | D3: 45296.529 | E3: CCD - DPC - IMPLEMENTACIÓN ERP | F3: Johan Sebastian Rodriguez Niño | G3: https://growdatasas.sharepoint.com/sites/pwa/CCD - DPC - IMPLEMENTACIÓN ERP | H3: Suministro e implementación del sistema de información ADMINISTRATIVO ERP NOVASOFT – versión ENTERPRISE WEB y el GESTOR DE RIESGOS para la entidad Defensoría del Pueblo.Incluye: 14 módulos específicos + 5 módulos financieros con licencia para 5000 usuarios finales, Licenciamiento de la Base de Datos SQL Server (Estándar para 8 Cores), Consultoría estándar de implementación de cada uno de los sistemas ofrecidos, soporte y actualización por 2 años y una bolsa de horas (según acuerdo por 2 años) | I3: DATOS Y SISTEMAS DE INFORMACIÓN | J3: 0318 | K3: Activo.En Ejecución | L3: =VLOOKUP(E3,[1]Diccionario!C$2:AC$150,22,0) -> 3323223361 | M3: =VLOOKUP(E3,[1]Diccionario!C$2:AC$150,24,0) -> 45300 | N3: =VLOOKUP(E3,[1]Diccionario!C$2:AC$150,25,0) -> 45473 | O3: =VLOOKUP(E3,[1]Diccionario!C$2:AC$150,26,0) -> 5.7 | P3: =Q3-O3 -> -3.7 | Q3: 2 | R3: 6 | S3: 0.3 | T3: 0.3 | U3: =U2+TablaIndicador[[#This Row],[Costo Mensual]] -> 0 | W3: =IFERROR(T3*L3,0) -> 9.9696701e+08 | X3: =S3*L3 -> 9.9696701e+08 | Y3: =IFERROR(W3-U3,0) -> 9.9696701e+08 | Z3: =W3-X3 -> 0 | AA3: =IFERROR(W3/U3,"No se realizó gasto en este corte") -> No se realizó gasto en este corte | AB3: =IFERROR( IF(OR(AA3="",AA3=0), "No calculado", IF(AA3>1,"Costo eficiente: se está gastando menos de lo presupuestado", IF(AA3=1,"Costo según lo presupuestado", "Costo ineficiente: se está gastando más de lo presupuestado"))), "No calculado") -> Costo eficiente: se está gastando menos de lo presupuestado | AC3: =IFERROR(W3/X3,0) -> 1 | AD3: =IF(OR(AC3="",AC3=0),"Sin Línea Base", IF(AC3>1,"Proyecto adelantado respecto al cronograma", IF(AC3=1,"Proyecto a tiempo según lo planificado", IF(AC3<1,"Proyecto atrasado con respecto al cronograma", "No calculado")))) -> Proyecto a tiempo según lo planificado | AE3: =IFERROR(L3/AA3,0) -> 0 | AF3: =IFERROR(AE3-L3,0) -> -3323223361 | AG3: =VLOOKUP(Indicador!E26,[1]Diccionario!C$1:AC$150,27,0) -> https://growdatasas.sharepoint.com/:x:/r/sites/Gestiondocumental/Administrativa/GD/Financiera/_layouts/15/Doc.aspx?sourcedoc=%7BC3EFE0E2-C211-45B0-905D-ECEF11221767%7D&file=299.%20DEFENSORIA_ERP.xlsm&action=default&mobileredirect=true | AH3: 1 | AI3: 1 | AJ3: ok
A4: 2024 | B4: Marzo | C4: 227b8bc1-c7ab-ee11-ba7f-00155d104f2c | D4: 45296.529 | E4: CCD - DPC - IMPLEMENTACIÓN ERP | F4: Johan Sebastian Rodriguez Niño | G4: https://growdatasas.sharepoint.com/sites/pwa/CCD - DPC - IMPLEMENTACIÓN ERP | H4: Suministro e implementación del sistema de información ADMINISTRATIVO ERP NOVASOFT – versión ENTERPRISE WEB y el GESTOR DE RIESGOS para la entidad Defensoría del Pueblo.Incluye: 14 módulos específicos + 5 módulos financieros con licencia para 5000 usuarios finales, Licenciamiento de la Base de Datos SQL Server (Estándar para 8 Cores), Consultoría estándar de implementación de cada uno de los sistemas ofrecidos, soporte y actualización por 2 años y una bolsa de horas (según acuerdo por 2 años) | I4: DATOS Y SISTEMAS DE INFORMACIÓN | J4: 0318 | K4: Activo.En Ejecución | L4: =VLOOKUP(E4,[1]Diccionario!C$2:AC$150,22,0) -> 3323223361 | M4: =VLOOKUP(E4,[1]Diccionario!C$2:AC$150,24,0) -> 45300 | N4: =VLOOKUP(E4,[1]Diccionario!C$2:AC$150,25,0) -> 45473 | O4: =VLOOKUP(E4,[1]Diccionario!C$2:AC$150,26,0) -> 5.7 | P4: =Q4-O4 -> 20.3 | Q4: =DATEDIF(M4,TODAY(),"m") -> 26 | R4: 6 | S4: 0.5 | T4: 0.4 | U4: =U3+TablaIndicador[[#This Row],[Costo Mensual]] -> 0 | W4: =IFERROR(T4*L4,0) -> 1.3292893e+09 | X4: =S4*L4 -> 1.6616117e+09 | Y4: =IFERROR(W4-U4,0) -> 1.3292893e+09 | Z4: =W4-X4 -> -3.3232234e+08 | AA4: =IFERROR(W4/U4,"No se realizó gasto en este corte") -> No se realizó gasto en este corte | AB4: =IFERROR( IF(OR(AA4="",AA4=0), "No calculado", IF(AA4>1,"Costo eficiente: se está gastando menos de lo presupuestado", IF(AA4=1,"Costo según lo presupuestado", "Costo ineficiente: se está gastando más de lo presupuestado"))), "No calculado") -> Costo eficiente: se está gastando menos de lo presupuestado | AC4: =IFERROR(W4/X4,0) -> 0.8 | AD4: =IF(OR(AC4="",AC4=0),"Sin Línea Base", IF(AC4>1,"Proyecto adelantado respecto al cronograma", IF(AC4=1,"Proyecto a tiempo según lo planificado", IF(AC4<1,"Proyecto atrasado con respecto al cronograma", "No calculado")))) -> Proyecto atrasado con respecto al cronograma | AE4: =IFERROR(L4/AA4,0) -> 0 | AF4: =IFERROR(AE4-L4,0) -> -3323223361 | AG4: =VLOOKUP(Indicador!E27,[1]Diccionario!C$1:AC$150,27,0) -> https://growdatasas.sharepoint.com/:x:/r/sites/Gestiondocumental/Administrativa/GD/Financiera/_layouts/15/Doc.aspx?sourcedoc=%7BC3EFE0E2-C211-45B0-905D-ECEF11221767%7D&file=299.%20DEFENSORIA_ERP.xlsm&action=default&mobileredirect=true | AH4: 1 | AI4: 1 | AJ4: ok
A5: 2024 | B5: Abril | C5: 227b8bc1-c7ab-ee11-ba7f-00155d104f2c | D5: 45296.529 | E5: CCD - DPC - IMPLEMENTACIÓN ERP | F5: Johan Sebastian Rodriguez Niño | G5: https://growdatasas.sharepoint.com/sites/pwa/CCD - DPC - IMPLEMENTACIÓN ERP | H5: Suministro e implementación del sistema de información ADMINISTRATIVO ERP NOVASOFT – versión ENTERPRISE WEB y el GESTOR DE RIESGOS para la entidad Defensoría del Pueblo.Incluye: 14 módulos específicos + 5 módulos financieros con licencia para 5000 usuarios finales, Licenciamiento de la Base de Datos SQL Server (Estándar para 8 Cores), Consultoría estándar de implementación de cada uno de los sistemas ofrecidos, soporte y actualización por 2 años y una bolsa de horas (según acuerdo por 2 años) | I5: DATOS Y SISTEMAS DE INFORMACIÓN | J5: 0318 | K5: Activo.En Ejecución | L5: =VLOOKUP(E5,[1]Diccionario!C$2:AC$150,22,0) -> 3323223361 | M5: =VLOOKUP(E5,[1]Diccionario!C$2:AC$150,24,0) -> 45300 | N5: =VLOOKUP(E5,[1]Diccionario!C$2:AC$150,25,0) -> 45473 | O5: =VLOOKUP(E5,[1]Diccionario!C$2:AC$150,26,0) -> 5.7 | P5: =Q5-O5 -> 20.3 | Q5: =DATEDIF(M5,TODAY(),"m") -> 26 | R5: 6 | S5: 0.75 | T5: =T4+0.02 -> 0.42 | U5: =U4+TablaIndicador[[#This Row],[Costo Mensual]] -> 0 | W5: =IFERROR(T5*L5,0) -> 1.3957538e+09 | X5: =S5*L5 -> 2.4924175e+09 | Y5: =IFERROR(W5-U5,0) -> 1.3957538e+09 | Z5: =W5-X5 -> -1.0966637e+09 | AA5: =IFERROR(W5/U5,"No se realizó gasto en este corte") -> No se realizó gasto en este corte | AB5: =IFERROR( IF(OR(AA5="",AA5=0), "No calculado", IF(AA5>1,"Costo eficiente: se está gastando menos de lo presupuestado", IF(AA5=1,"Costo según lo presupuestado", "Costo ineficiente: se está gastando más de lo presupuestado"))), "No calculado") -> Costo eficiente: se está gastando menos de lo presupuestado | AC5: =IFERROR(W5/X5,0) -> 0.56 | AD5: =IF(OR(AC5="",AC5=0),"Sin Línea Base", IF(AC5>1,"Proyecto adelantado respecto al cronograma", IF(AC5=1,"Proyecto a tiempo según lo planificado", IF(AC5<1,"Proyecto atrasado con respecto al cronograma", "No calculado")))) -> Proyecto atrasado con respecto al cronograma | AE5: =IFERROR(L5/AA5,0) -> 0 | AF5: =IFERROR(AE5-L5,0) -> -3323223361 | AG5: =VLOOKUP(Indicador!E28,[1]Diccionario!C$1:AC$150,27,0) -> https://growdatasas.sharepoint.com/:x:/r/sites/Gestiondocumental/Administrativa/GD/Financiera/_layouts/15/Doc.aspx?sourcedoc=%7B4F9BD6BF-F6F0-4033-84A5-4B5D6077FC32%7D&file=314.%20TELEFONICA%20%E2%80%93%20DPC%20%20SALA%20DE%20ANALITICA.xlsx&action=default&mobileredirect=true | AH5: 1 | AI5: 1 | AJ5: ok
A6: 2024 | B6: Mayo | C6: 227b8bc1-c7ab-ee11-ba7f-00155d104f2c | D6: 45296.529 | E6: CCD - DPC - IMPLEMENTACIÓN ERP | F6: Johan Sebastian Rodriguez Niño | G6: https://growdatasas.sharepoint.com/sites/pwa/CCD - DPC - IMPLEMENTACIÓN ERP | H6: Suministro e implementación del sistema de información ADMINISTRATIVO ERP NOVASOFT – versión ENTERPRISE WEB y el GESTOR DE RIESGOS para la entidad Defensoría del Pueblo.Incluye: 14 módulos específicos + 5 módulos financieros con licencia para 5000 usuarios finales, Licenciamiento de la Base de Datos SQL Server (Estándar para 8 Cores), Consultoría estándar de implementación de cada uno de los sistemas ofrecidos, soporte y actualización por 2 años y una bolsa de horas (según acuerdo por 2 años) | I6: DATOS Y SISTEMAS DE INFORMACIÓN | J6: 0318 | K6: Activo.En Ejecución | L6: =VLOOKUP(E6,[1]Diccionario!C$2:AC$150,22,0) -> 3323223361 | M6: =VLOOKUP(E6,[1]Diccionario!C$2:AC$150,24,0) -> 45300 | N6: =VLOOKUP(E6,[1]Diccionario!C$2:AC$150,25,0) -> 45473 | O6: =VLOOKUP(E6,[1]Diccionario!C$2:AC$150,26,0) -> 5.7 | P6: =Q6-O6 -> 20.3 | Q6: =DATEDIF(M6,TODAY(),"m") -> 26 | R6: 6 | S6: 0.8 | T6: =T5+0.02 -> 0.44 | U6: =U5+TablaIndicador[[#This Row],[Costo Mensual]] -> 0 | W6: =IFERROR(T6*L6,0) -> 1.4622183e+09 | X6: =S6*L6 -> 2.6585787e+09 | Y6: =IFERROR(W6-U6,0) -> 1.4622183e+09 | Z6: =W6-X6 -> -1.1963604e+09 | AA6: =IFERROR(W6/U6,"No se realizó gasto en este corte") -> No se realizó gasto en este corte | AB6: =IFERROR( IF(OR(AA6="",AA6=0), "No calculado", IF(AA6>1,"Costo eficiente: se está gastando menos de lo presupuestado", IF(AA6=1,"Costo según lo presupuestado", "Costo ineficiente: se está gastando más de lo presupuestado"))), "No calculado") -> Costo eficiente: se está gastando menos de lo presupuestado | AC6: =IFERROR(W6/X6,0) -> 0.55 | AD6: =IF(OR(AC6="",AC6=0),"Sin Línea Base", IF(AC6>1,"Proyecto adelantado respecto al cronograma", IF(AC6=1,"Proyecto a tiempo según lo planificado", IF(AC6<1,"Proyecto atrasado con respecto al cronograma", "No calculado")))) -> Proyecto atrasado con respecto al cronograma | AE6: =IFERROR(L6/AA6,0) -> 0 | AF6: =IFERROR(AE6-L6,0) -> -3323223361 | AG6: =VLOOKUP(Indicador!E29,[1]Diccionario!C$1:AC$150,27,0) -> https://growdatasas.sharepoint.com/:x:/r/sites/Gestiondocumental/Administrativa/GD/Financiera/_layouts/15/Doc.aspx?sourcedoc=%7B4F9BD6BF-F6F0-4033-84A5-4B5D6077FC32%7D&file=314.%20TELEFONICA%20%E2%80%93%20DPC%20%20SALA%20DE%20ANALITICA.xlsx&action=default&mobileredirect=true | AH6: 1 | AI6: 1 | AJ6: ok
A7: 2024 | B7: Junio | C7: 227b8bc1-c7ab-ee11-ba7f-00155d104f2c | D7: 45296.529 | E7: CCD - DPC - IMPLEMENTACIÓN ERP | F7: Johan Sebastian Rodriguez Niño | G7: https://growdatasas.sharepoint.com/sites/pwa/CCD - DPC - IMPLEMENTACIÓN ERP | H7: Suministro e implementación del sistema de información ADMINISTRATIVO ERP NOVASOFT – versión ENTERPRISE WEB y el GESTOR DE RIESGOS para la entidad Defensoría del Pueblo.Incluye: 14 módulos específicos + 5 módulos financieros con licencia para 5000 usuarios finales, Licenciamiento de la Base de Datos SQL Server (Estándar para 8 Cores), Consultoría estándar de implementación de cada uno de los sistemas ofrecidos, soporte y actualización por 2 años y una bolsa de horas (según acuerdo por 2 años) | I7: DATOS Y SISTEMAS DE INFORMACIÓN | J7: 0318 | K7: Activo.En Ejecución | L7: =VLOOKUP(E7,[1]Diccionario!C$2:AC$150,22,0) -> 3323223361 | M7: =VLOOKUP(E7,[1]Diccionario!C$2:AC$150,24,0) -> 45300 | N7: =VLOOKUP(E7,[1]Diccionario!C$2:AC$150,25,0) -> 45473 | O7: =VLOOKUP(E7,[1]Diccionario!C$2:AC$150,26,0) -> 5.7 | P7: =Q7-O7 -> 20.3 | Q7: =DATEDIF(M7,TODAY(),"m") -> 26 | R7: 6 | S7: 1 | T7: =T6+0.02 -> 0.46 | U7: =U6+TablaIndicador[[#This Row],[Costo Mensual]] -> 0 | W7: =IFERROR(T7*L7,0) -> 1.5286827e+09 | X7: =S7*L7 -> 3323223361 | Y7: =IFERROR(W7-U7,0) -> 1.5286827e+09 | Z7: =W7-X7 -> -1.7945406e+09 | AA7: =IFERROR(W7/U7,"No se realizó gasto en este corte") -> No se realizó gasto en este corte | AB7: =IFERROR( IF(OR(AA7="",AA7=0), "No calculado", IF(AA7>1,"Costo eficiente: se está gastando menos de lo presupuestado", IF(AA7=1,"Costo según lo presupuestado", "Costo ineficiente: se está gastando más de lo presupuestado"))), "No calculado") -> Costo eficiente: se está gastando menos de lo presupuestado | AC7: =IFERROR(W7/X7,0) -> 0.46 | AD7: =IF(OR(AC7="",AC7=0),"Sin Línea Base", IF(AC7>1,"Proyecto adelantado respecto al cronograma", IF(AC7=1,"Proyecto a tiempo según lo planificado", IF(AC7<1,"Proyecto atrasado con respecto al cronograma", "No calculado")))) -> Proyecto atrasado con respecto al cronograma | AE7: =IFERROR(L7/AA7,0) -> 0 | AF7: =IFERROR(AE7-L7,0) -> -3323223361 | AG7: =VLOOKUP(Indicador!E30,[1]Diccionario!C$1:AC$150,27,0) -> https://growdatasas.sharepoint.com/:x:/r/sites/Gestiondocumental/Administrativa/GD/Financiera/_layouts/15/Doc.aspx?sourcedoc=%7B4F9BD6BF-F6F0-4033-84A5-4B5D6077FC32%7D&file=314.%20TELEFONICA%20%E2%80%93%20DPC%20%20SALA%20DE%20ANALITICA.xlsx&action=default&mobileredirect=true | AH7: 1 | AI7: 1 | AJ7: ok
A8: 2024 | B8: Julio | C8: 227b8bc1-c7ab-ee11-ba7f-00155d104f2c | D8: 45296.529 | E8: CCD - DPC - IMPLEMENTACIÓN ERP | F8: Johan Sebastian Rodriguez Niño | G8: https://growdatasas.sharepoint.com/sites/pwa/CCD - DPC - IMPLEMENTACIÓN ERP | H8: Suministro e implementación del sistema de información ADMINISTRATIVO ERP NOVASOFT – versión ENTERPRISE WEB y el GESTOR DE RIESGOS para la entidad Defensoría del Pueblo.Incluye: 14 módulos específicos + 5 módulos financieros con licencia para 5000 usuarios finales, Licenciamiento de la Base de Datos SQL Server (Estándar para 8 Cores), Consultoría estándar de implementación de cada uno de los sistemas ofrecidos, soporte y actualización por 2 años y una bolsa de horas (según acuerdo por 2 años) | I8: DATOS Y SISTEMAS DE INFORMACIÓN | J8: 0318 | K8: Activo.En Ejecución | L8: =VLOOKUP(E8,[1]Diccionario!C$2:AC$150,22,0) -> 3323223361 | M8: =VLOOKUP(E8,[1]Diccionario!C$2:AC$150,24,0) -> 45300 | N8: =VLOOKUP(E8,[1]Diccionario!C$2:AC$150,25,0) -> 45473 | O8: =VLOOKUP(E8,[1]Diccionario!C$2:AC$150,26,0) -> 5.7 | P8: =Q8-O8 -> 20.3 | Q8: =DATEDIF(M8,TODAY(),"m") -> 26 | R8: 6 | S8: 1 | T8: =T7+0.02 -> 0.48 | U8: =U7+TablaIndicador[[#This Row],[Costo Mensual]] -> 0 | W8: =IFERROR(T8*L8,0) -> 1.5951472e+09 | X8: =S8*L8 -> 3323223361 | Y8: =IFERROR(W8-U8,0) -> 1.5951472e+09 | Z8: =W8-X8 -> -1.7280761e+09 | AA8: =IFERROR(W8/U8,"No se realizó gasto en este corte") -> No se realizó gasto en este corte | AB8: =IFERROR( IF(OR(AA8="",AA8=0), "No calculado", IF(AA8>1,"Costo eficiente: se está gastando menos de lo presupuestado", IF(AA8=1,"Costo según lo presupuestado", "Costo ineficiente: se está gastando más de lo presupuestado"))), "No calculado") -> Costo eficiente: se está gastando menos de lo presupuestado | AC8: =IFERROR(W8/X8,0) -> 0.48 | AD8: =IF(OR(AC8="",AC8=0),"Sin Línea Base", IF(AC8>1,"Proyecto adelantado respecto al cronograma", IF(AC8=1,"Proyecto a tiempo según lo planificado", IF(AC8<1,"Proyecto atrasado con respecto al cronograma", "No calculado")))) -> Proyecto atrasado con respecto al cronograma | AE8: =IFERROR(L8/AA8,0) -> 0 | AF8: =IFERROR(AE8-L8,0) -> -3323223361 | AG8: =VLOOKUP(Indicador!E31,[1]Diccionario!C$1:AC$150,27,0) -> https://growdatasas.sharepoint.com/:x:/r/sites/Gestiondocumental/Administrativa/GD/Financiera/_layouts/15/Doc.aspx?sourcedoc=%7B4F9BD6BF-F6F0-4033-84A5-4B5D6077FC32%7D&file=314.%20TELEFONICA%20%E2%80%93%20DPC%20%20SALA%20DE%20ANALITICA.xlsx&action=default&mobileredirect=true | AH8: 1 | AI8: 1 | AJ8: ok
A9: 2024 | B9: Agosto | C9: 227b8bc1-c7ab-ee11-ba7f-00155d104f2c | D9: 45296.529 | E9: CCD - DPC - IMPLEMENTACIÓN ERP | F9: Johan Sebastian Rodriguez Niño | G9: https://growdatasas.sharepoint.com/sites/pwa/CCD - DPC - IMPLEMENTACIÓN ERP | H9: Suministro e implementación del sistema de información ADMINISTRATIVO ERP NOVASOFT – versión ENTERPRISE WEB y el GESTOR DE RIESGOS para la entidad Defensoría del Pueblo.Incluye: 14 módulos específicos + 5 módulos financieros con licencia para 5000 usuarios finales, Licenciamiento de la Base de Datos SQL Server (Estándar para 8 Cores), Consultoría estándar de implementación de cada uno de los sistemas ofrecidos, soporte y actualización por 2 años y una bolsa de horas (según acuerdo por 2 años) | I9: DATOS Y SISTEMAS DE INFORMACIÓN | J9: 0318 | K9: Activo.En Ejecución | L9: =VLOOKUP(E9,[1]Diccionario!C$2:AC$150,22,0) -> 3323223361 | M9: =VLOOKUP(E9,[1]Diccionario!C$2:AC$150,24,0) -> 45300 | N9: =VLOOKUP(E9,[1]Diccionario!C$2:AC$150,25,0) -> 45473 | O9: =VLOOKUP(E9,[1]Diccionario!C$2:AC$150,26,0) -> 5.7 | P9: =Q9-O9 -> 20.3 | Q9: =DATEDIF(M9,TODAY(),"m") -> 26 | R9: 6 | S9: 1 | T9: =T8+0.02 -> 0.5 | U9: =U8+TablaIndicador[[#This Row],[Costo Mensual]] -> 0 | W9: =IFERROR(T9*L9,0) -> 1.6616117e+09 | X9: =S9*L9 -> 3323223361 | Y9: =IFERROR(W9-U9,0) -> 1.6616117e+09 | Z9: =W9-X9 -> -1.6616117e+09 | AA9: =IFERROR(W9/U9,"No se realizó gasto en este corte") -> No se realizó gasto en este corte | AB9: =IFERROR( IF(OR(AA9="",AA9=0), "No calculado", IF(AA9>1,"Costo eficiente: se está gastando menos de lo presupuestado", IF(AA9=1,"Costo según lo presupuestado", "Costo ineficiente: se está gastando más de lo presupuestado"))), "No calculado") -> Costo eficiente: se está gastando menos de lo presupuestado | AC9: =IFERROR(W9/X9,0) -> 0.5 | AD9: =IF(OR(AC9="",AC9=0),"Sin Línea Base", IF(AC9>1,"Proyecto adelantado respecto al cronograma", IF(AC9=1,"Proyecto a tiempo según lo planificado", IF(AC9<1,"Proyecto atrasado con respecto al cronograma", "No calculado")))) -> Proyecto atrasado con respecto al cronograma | AE9: =IFERROR(L9/AA9,0) -> 0 | AF9: =IFERROR(AE9-L9,0) -> -3323223361 | AG9: =VLOOKUP(Indicador!E32,[1]Diccionario!C$1:AC$150,27,0) -> https://growdatasas.sharepoint.com/:x:/r/sites/Gestiondocumental/Administrativa/GD/Financiera/_layouts/15/Doc.aspx?sourcedoc=%7B4F9BD6BF-F6F0-4033-84A5-4B5D6077FC32%7D&file=314.%20TELEFONICA%20%E2%80%93%20DPC%20%20SALA%20DE%20ANALITICA.xlsx&action=default&mobileredirect=true | AH9: 1 | AI9: 1 | AJ9: ok
A10: 2024 | B10: Septiembre | C10: 227b8bc1-c7ab-ee11-ba7f-00155d104f2c | D10: 45296.529 | E10: CCD - DPC - IMPLEMENTACIÓN ERP | F10: Johan Sebastian Rodriguez Niño | G10: https://growdatasas.sharepoint.com/sites/pwa/CCD - DPC - IMPLEMENTACIÓN ERP | H10: Suministro e implementación del sistema de información ADMINISTRATIVO ERP NOVASOFT – versión ENTERPRISE WEB y el GESTOR DE RIESGOS para la entidad Defensoría del Pueblo.Incluye: 14 módulos específicos + 5 módulos financieros con licencia para 5000 usuarios finales, Licenciamiento de la Base de Datos SQL Server (Estándar para 8 Cores), Consultoría estándar de implementación de cada uno de los sistemas ofrecidos, soporte y actualización por 2 años y una bolsa de horas (según acuerdo por 2 años) | I10: DATOS Y SISTEMAS DE INFORMACIÓN | J10: 0318 | K10: Activo.En Ejecución | L10: =VLOOKUP(E10,[1]Diccionario!C$2:AC$150,22,0) -> 3323223361 | M10: =VLOOKUP(E10,[1]Diccionario!C$2:AC$150,24,0) -> 45300 | N10: =VLOOKUP(E10,[1]Diccionario!C$2:AC$150,25,0) -> 45473 | O10: =VLOOKUP(E10,[1]Diccionario!C$2:AC$150,26,0) -> 5.7 | P10: =Q10-O10 -> 20.3 | Q10: =DATEDIF(M10,TODAY(),"m") -> 26 | R10: 6 | S10: 1 | T10: =T9+0.02 -> 0.52 | U10: =U9+TablaIndicador[[#This Row],[Costo Mensual]] -> 0 | W10: =IFERROR(T10*L10,0) -> 1.7280761e+09 | X10: =S10*L10 -> 3323223361 | Y10: =IFERROR(W10-U10,0) -> 1.7280761e+09 | Z10: =W10-X10 -> -1.5951472e+09 | AA10: =IFERROR(W10/U10,"No se realizó gasto en este corte") -> No se realizó gasto en este corte | AB10: =IFERROR( IF(OR(AA10="",AA10=0), "No calculado", IF(AA10>1,"Costo eficiente: se está gastando menos de lo presupuestado", IF(AA10=1,"Costo según lo presupuestado", "Costo ineficiente: se está gastando más de lo presupuestado"))), "No calculado") -> Costo eficiente: se está gastando menos de lo presupuestado | AC10: =IFERROR(W10/X10,0) -> 0.52 | AD10: =IF(OR(AC10="",AC10=0),"Sin Línea Base", IF(AC10>1,"Proyecto adelantado respecto al cronograma", IF(AC10=1,"Proyecto a tiempo según lo planificado", IF(AC10<1,"Proyecto atrasado con respecto al cronograma", "No calculado")))) -> Proyecto atrasado con respecto al cronograma | AE10: =IFERROR(L10/AA10,0) -> 0 | AF10: =IFERROR(AE10-L10,0) -> -3323223361 | AG10: =VLOOKUP(Indicador!E33,[1]Diccionario!C$1:AC$150,27,0) -> https://growdatasas.sharepoint.com/:x:/r/sites/Gestiondocumental/Administrativa/GD/Financiera/_layouts/15/Doc.aspx?sourcedoc=%7B4F9BD6BF-F6F0-4033-84A5-4B5D6077FC32%7D&file=314.%20TELEFONICA%20%E2%80%93%20DPC%20%20SALA%20DE%20ANALITICA.xlsx&action=default&mobileredirect=true | AH10: 1 | AI10: 1 | AJ10: ok
A11: 2024 | B11: Octubre | C11: 227b8bc1-c7ab-ee11-ba7f-00155d104f2c | D11: 45296.529 | E11: CCD - DPC - IMPLEMENTACIÓN ERP | F11: Johan Sebastian Rodriguez Niño | G11: https://growdatasas.sharepoint.com/sites/pwa/CCD - DPC - IMPLEMENTACIÓN ERP | H11: Suministro e implementación del sistema de información ADMINISTRATIVO ERP NOVASOFT – versión ENTERPRISE WEB y el GESTOR DE RIESGOS para la entidad Defensoría del Pueblo.Incluye: 14 módulos específicos + 5 módulos financieros con licencia para 5000 usuarios finales, Licenciamiento de la Base de Datos SQL Server (Estándar para 8 Cores), Consultoría estándar de implementación de cada uno de los sistemas ofrecidos, soporte y actualización por 2 años y una bolsa de horas (según acuerdo por 2 años) | I11: DATOS Y SISTEMAS DE INFORMACIÓN | J11: 0318 | K11: Activo.En Ejecución | L11: =VLOOKUP(E11,[1]Diccionario!C$2:AC$150,22,0) -> 3323223361 | M11: =VLOOKUP(E11,[1]Diccionario!C$2:AC$150,24,0) -> 45300 | N11: =VLOOKUP(E11,[1]Diccionario!C$2:AC$150,25,0) -> 45473 | O11: =VLOOKUP(E11,[1]Diccionario!C$2:AC$150,26,0) -> 5.7 | P11: =Q11-O11 -> 20.3 | Q11: =DATEDIF(M11,TODAY(),"m") -> 26 | R11: 6 | S11: 1 | T11: =T10+0.02 -> 0.54 | U11: =U10+TablaIndicador[[#This Row],[Costo Mensual]] -> 0 | W11: =IFERROR(T11*L11,0) -> 1.7945406e+09 | X11: =S11*L11 -> 3323223361 | Y11: =IFERROR(W11-U11,0) -> 1.7945406e+09 | Z11: =W11-X11 -> -1.5286827e+09 | AA11: =IFERROR(W11/U11,"No se realizó gasto en este corte") -> No se realizó gasto en este corte | AB11: =IFERROR( IF(OR(AA11="",AA11=0), "No calculado", IF(AA11>1,"Costo eficiente: se está gastando menos de lo presupuestado", IF(AA11=1,"Costo según lo presupuestado", "Costo ineficiente: se está gastando más de lo presupuestado"))), "No calculado") -> Costo eficiente: se está gastando menos de lo presupuestado | AC11: =IFERROR(W11/X11,0) -> 0.54 | AD11: =IF(OR(AC11="",AC11=0),"Sin Línea Base", IF(AC11>1,"Proyecto adelantado respecto al cronograma", IF(AC11=1,"Proyecto a tiempo según lo planificado", IF(AC11<1,"Proyecto atrasado con respecto al cronograma", "No calculado")))) -> Proyecto atrasado con respecto al cronograma | AE11: =IFERROR(L11/AA11,0) -> 0 | AF11: =IFERROR(AE11-L11,0) -> -3323223361 | AG11: =VLOOKUP(Indicador!E34,[1]Diccionario!C$1:AC$150,27,0) -> https://growdatasas.sharepoint.com/:x:/r/sites/Gestiondocumental/Administrativa/GD/Financiera/_layouts/15/Doc.aspx?sourcedoc=%7BB4DE39AF-1EC1-466C-A807-3FE95776A982%7D&file=17012024%20INFOTIC%20DPC%20SOC%20V2.xlsm&action=default&mobileredirect=true | AH11: 1 | AI11: 1 | AJ11: ok
A12: 2024 | B12: Noviembre | C12: 227b8bc1-c7ab-ee11-ba7f-00155d104f2c | D12: 45296.529 | E12: CCD - DPC - IMPLEMENTACIÓN ERP | F12: Johan Sebastian Rodriguez Niño | G12: https://growdatasas.sharepoint.com/sites/pwa/CCD - DPC - IMPLEMENTACIÓN ERP | H12: Suministro e implementación del sistema de información ADMINISTRATIVO ERP NOVASOFT – versión ENTERPRISE WEB y el GESTOR DE RIESGOS para la entidad Defensoría del Pueblo.Incluye: 14 módulos específicos + 5 módulos financieros con licencia para 5000 usuarios finales, Licenciamiento de la Base de Datos SQL Server (Estándar para 8 Cores), Consultoría estándar de implementación de cada uno de los sistemas ofrecidos, soporte y actualización por 2 años y una bolsa de horas (según acuerdo por 2 años) | I12: DATOS Y SISTEMAS DE INFORMACIÓN | J12: 0318 | K12: Activo.En Ejecución | L12: =VLOOKUP(E12,[1]Diccionario!C$2:AC$150,22,0) -> 3323223361 | M12: =VLOOKUP(E12,[1]Diccionario!C$2:AC$150,24,0) -> 45300 | N12: =VLOOKUP(E12,[1]Diccionario!C$2:AC$150,25,0) -> 45473 | O12: =VLOOKUP(E12,[1]Diccionario!C$2:AC$150,26,0) -> 5.7 | P12: =Q12-O12 -> 20.3 | Q12: =DATEDIF(M12,TODAY(),"m") -> 26 | R12: 6 | S12: 1 | T12: =T11+0.02 -> 0.56 | U12: =U11+TablaIndicador[[#This Row],[Costo Mensual]] -> 0 | W12: =IFERROR(T12*L12,0) -> 1.8610051e+09 | X12: =S12*L12 -> 3323223361 | Y12: =IFERROR(W12-U12,0) -> 1.8610051e+09 | Z12: =W12-X12 -> -1.4622183e+09 | AA12: =IFERROR(W12/U12,"No se realizó gasto en este corte") -> No se realizó gasto en este corte | AB12: =IFERROR( IF(OR(AA12="",AA12=0), "No calculado", IF(AA12>1,"Costo eficiente: se está gastando menos de lo presupuestado", IF(AA12=1,"Costo según lo presupuestado", "Costo ineficiente: se está gastando más de lo presupuestado"))), "No calculado") -> Costo eficiente: se está gastando menos de lo presupuestado | AC12: =IFERROR(W12/X12,0) -> 0.56 | AD12: =IF(OR(AC12="",AC12=0),"Sin Línea Base", IF(AC12>1,"Proyecto adelantado respecto al cronograma", IF(AC12=1,"Proyecto a tiempo según lo planificado", IF(AC12<1,"Proyecto atrasado con respecto al cronograma", "No calculado")))) -> Proyecto atrasado con respecto al cronograma | AE12: =IFERROR(L12/AA12,0) -> 0 | AF12: =IFERROR(AE12-L12,0) -> -3323223361 | AG12: =VLOOKUP(Indicador!E35,[1]Diccionario!C$1:AC$150,27,0) -> https://growdatasas.sharepoint.com/:x:/r/sites/Gestiondocumental/Administrativa/GD/Financiera/_layouts/15/Doc.aspx?sourcedoc=%7BB4DE39AF-1EC1-466C-A807-3FE95776A982%7D&file=17012024%20INFOTIC%20DPC%20SOC%20V2.xlsm&action=default&mobileredirect=true | AH12: 1 | AI12: 1 | AJ12: ok
A13: 2024 | B13: Diciembre | C13: 227b8bc1-c7ab-ee11-ba7f-00155d104f2c | D13: 45296.529 | E13: CCD - DPC - IMPLEMENTACIÓN ERP | F13: Johan Sebastian Rodriguez Niño | G13: https://growdatasas.sharepoint.com/sites/pwa/CCD - DPC - IMPLEMENTACIÓN ERP | H13: Suministro e implementación del sistema de información ADMINISTRATIVO ERP NOVASOFT – versión ENTERPRISE WEB y el GESTOR DE RIESGOS para la entidad Defensoría del Pueblo.Incluye: 14 módulos específicos + 5 módulos financieros con licencia para 5000 usuarios finales, Licenciamiento de la Base de Datos SQL Server (Estándar para 8 Cores), Consultoría estándar de implementación de cada uno de los sistemas ofrecidos, soporte y actualización por 2 años y una bolsa de horas (según acuerdo por 2 años) | I13: DATOS Y SISTEMAS DE INFORMACIÓN | J13: 0318 | K13: Activo.En Ejecución | L13: =VLOOKUP(E13,[1]Diccionario!C$2:AC$150,22,0) -> 3323223361 | M13: =VLOOKUP(E13,[1]Diccionario!C$2:AC$150,24,0) -> 45300 | N13: =VLOOKUP(E13,[1]Diccionario!C$2:AC$150,25,0) -> 45473 | O13: =VLOOKUP(E13,[1]Diccionario!C$2:AC$150,26,0) -> 5.7 | P13: =Q13-O13 -> 20.3 | Q13: =DATEDIF(M13,TODAY(),"m") -> 26 | R13: 6 | S13: 1 | T13: =T12+0.02 -> 0.58 | U13: =U12+TablaIndicador[[#This Row],[Costo Mensual]] -> 0 | W13: =IFERROR(T13*L13,0) -> 1.9274695e+09 | X13: =S13*L13 -> 3323223361 | Y13: =IFERROR(W13-U13,0) -> 1.9274695e+09 | Z13: =W13-X13 -> -1.3957538e+09 | AA13: =IFERROR(W13/U13,"No se realizó gasto en este corte") -> No se realizó gasto en este corte | AB13: =IFERROR( IF(OR(AA13="",AA13=0), "No calculado", IF(AA13>1,"Costo eficiente: se está gastando menos de lo presupuestado", IF(AA13=1,"Costo según lo presupuestado", "Costo ineficiente: se está gastando más de lo presupuestado"))), "No calculado") -> Costo eficiente: se está gastando menos de lo presupuestado | AC13: =IFERROR(W13/X13,0) -> 0.58 | AD13: =IF(OR(AC13="",AC13=0),"Sin Línea Base", IF(AC13>1,"Proyecto adelantado respecto al cronograma", IF(AC13=1,"Proyecto a tiempo según lo planificado", IF(AC13<1,"Proyecto atrasado con respecto al cronograma", "No calculado")))) -> Proyecto atrasado con respecto al cronograma | AE13: =IFERROR(L13/AA13,0) -> 0 | AF13: =IFERROR(AE13-L13,0) -> -3323223361 | AG13: =VLOOKUP(Indicador!E36,[1]Diccionario!C$1:AC$150,27,0) -> https://growdatasas.sharepoint.com/:x:/r/sites/Gestiondocumental/Administrativa/GD/Financiera/_layouts/15/Doc.aspx?sourcedoc=%7BB4DE39AF-1EC1-466C-A807-3FE95776A982%7D&file=17012024%20INFOTIC%20DPC%20SOC%20V2.xlsm&action=default&mobileredirect=true | AH13: 1 | AI13: 1 | AJ13: ok
A14: 2025 | B14: Enero | C14: 227b8bc1-c7ab-ee11-ba7f-00155d104f2c | D14: 45296.529 | E14: CCD - DPC - IMPLEMENTACIÓN ERP | F14: Johan Sebastian Rodriguez Niño | G14: https://growdatasas.sharepoint.com/sites/pwa/CCD - DPC - IMPLEMENTACIÓN ERP | H14: Suministro e implementación del sistema de información ADMINISTRATIVO ERP NOVASOFT – versión ENTERPRISE WEB y el GESTOR DE RIESGOS para la entidad Defensoría del Pueblo.Incluye: 14 módulos específicos + 5 módulos financieros con licencia para 5000 usuarios finales, Licenciamiento de la Base de Datos SQL Server (Estándar para 8 Cores), Consultoría estándar de implementación de cada uno de los sistemas ofrecidos, soporte y actualización por 2 años y una bolsa de horas (según acuerdo por 2 años) | I14: DATOS Y SISTEMAS DE INFORMACIÓN | J14: 0318 | K14: Activo.En Ejecución | L14: =VLOOKUP(E14,[1]Diccionario!C$2:AC$150,22,0) -> 3323223361 | M14: =VLOOKUP(E14,[1]Diccionario!C$2:AC$150,24,0) -> 45300 | N14: =VLOOKUP(E14,[1]Diccionario!C$2:AC$150,25,0) -> 45473 | O14: =VLOOKUP(E14,[1]Diccionario!C$2:AC$150,26,0) -> 5.7 | P14: =Q14-O14 -> 20.3 | Q14: =DATEDIF(M14,TODAY(),"m") -> 26 | R14: 6 | S14: 1 | T14: =T13+0.02 -> 0.6 | U14: =U13+TablaIndicador[[#This Row],[Costo Mensual]] -> 0 | W14: =IFERROR(T14*L14,0) -> 1.993934e+09 | X14: =S14*L14 -> 3323223361 | Y14: =IFERROR(W14-U14,0) -> 1.993934e+09 | Z14: =W14-X14 -> -1.3292893e+09 | AA14: =IFERROR(W14/U14,"No se realizó gasto en este corte") -> No se realizó gasto en este corte | AB14: =IFERROR( IF(OR(AA14="",AA14=0), "No calculado", IF(AA14>1,"Costo eficiente: se está gastando menos de lo presupuestado", IF(AA14=1,"Costo según lo presupuestado", "Costo ineficiente: se está gastando más de lo presupuestado"))), "No calculado") -> Costo eficiente: se está gastando menos de lo presupuestado | AC14: =IFERROR(W14/X14,0) -> 0.6 | AD14: =IF(OR(AC14="",AC14=0),"Sin Línea Base", IF(AC14>1,"Proyecto adelantado respecto al cronograma", IF(AC14=1,"Proyecto a tiempo según lo planificado", IF(AC14<1,"Proyecto atrasado con respecto al cronograma", "No calculado")))) -> Proyecto atrasado con respecto al cronograma | AE14: =IFERROR(L14/AA14,0) -> 0 | AF14: =IFERROR(AE14-L14,0) -> -3323223361 | AG14: =VLOOKUP(Indicador!E37,[1]Diccionario!C$1:AC$150,27,0) -> https://growdatasas.sharepoint.com/:x:/r/sites/Gestiondocumental/Administrativa/GD/Financiera/_layouts/15/Doc.aspx?sourcedoc=%7BB4DE39AF-1EC1-466C-A807-3FE95776A982%7D&file=17012024%20INFOTIC%20DPC%20SOC%20V2.xlsm&action=default&mobileredirect=true | AH14: 1 | AI14: 1
A15: 2025 | B15: Febrero | C15: 227b8bc1-c7ab-ee11-ba7f-00155d104f2c | D15: 45296.529 | E15: CCD - DPC - IMPLEMENTACIÓN ERP | F15: Johan Sebastian Rodriguez Niño | G15: https://growdatasas.sharepoint.com/sites/pwa/CCD - DPC - IMPLEMENTACIÓN ERP | H15: Suministro e implementación del sistema de información ADMINISTRATIVO ERP NOVASOFT – versión ENTERPRISE WEB y el GESTOR DE RIESGOS para la entidad Defensoría del Pueblo.Incluye: 14 módulos específicos + 5 módulos financieros con licencia para 5000 usuarios finales, Licenciamiento de la Base de Datos SQL Server (Estándar para 8 Cores), Consultoría estándar de implementación de cada uno de los sistemas ofrecidos, soporte y actualización por 2 años y una bolsa de horas (según acuerdo por 2 años) | I15: DATOS Y SISTEMAS DE INFORMACIÓN | J15: 0318 | K15: Activo.En Ejecución | L15: =VLOOKUP(E15,[1]Diccionario!C$2:AC$150,22,0) -> 3323223361 | M15: =VLOOKUP(E15,[1]Diccionario!C$2:AC$150,24,0) -> 45300 | N15: =VLOOKUP(E15,[1]Diccionario!C$2:AC$150,25,0) -> 45473 | O15: =VLOOKUP(E15,[1]Diccionario!C$2:AC$150,26,0) -> 5.7 | P15: =Q15-O15 -> 20.3 | Q15: =DATEDIF(M15,TODAY(),"m") -> 26 | R15: 6 | S15: 1 | T15: =T14+0.02 -> 0.62 | U15: =U14+TablaIndicador[[#This Row],[Costo Mensual]] -> 0 | W15: =IFERROR(T15*L15,0) -> 2.0603985e+09 | X15: =S15*L15 -> 3323223361 | Y15: =IFERROR(W15-U15,0) -> 2.0603985e+09 | Z15: =W15-X15 -> -1.2628249e+09 | AA15: =IFERROR(W15/U15,"No se realizó gasto en este corte") -> No se realizó gasto en este corte | AB15: =IFERROR( IF(OR(AA15="",AA15=0), "No calculado", IF(AA15>1,"Costo eficiente: se está gastando menos de lo presupuestado", IF(AA15=1,"Costo según lo presupuestado", "Costo ineficiente: se está gastando más de lo presupuestado"))), "No calculado") -> Costo eficiente: se está gastando menos de lo presupuestado | AC15: =IFERROR(W15/X15,0) -> 0.62 | AD15: =IF(OR(AC15="",AC15=0),"Sin Línea Base", IF(AC15>1,"Proyecto adelantado respecto al cronograma", IF(AC15=1,"Proyecto a tiempo según lo planificado", IF(AC15<1,"Proyecto atrasado con respecto al cronograma", "No calculado")))) -> Proyecto atrasado con respecto al cronograma | AE15: =IFERROR(L15/AA15,0) -> 0 | AF15: =IFERROR(AE15-L15,0) -> -3323223361 | AG15: =VLOOKUP(Indicador!E38,[1]Diccionario!C$1:AC$150,27,0) -> https://growdatasas.sharepoint.com/:x:/r/sites/Gestiondocumental/Administrativa/GD/Financiera/_layouts/15/Doc.aspx?sourcedoc=%7BB4DE39AF-1EC1-466C-A807-3FE95776A982%7D&file=17012024%20INFOTIC%20DPC%20SOC%20V2.xlsm&action=default&mobileredirect=true | AH15: 1 | AI15: 1
A16: 2025 | B16: Marzo | C16: 227b8bc1-c7ab-ee11-ba7f-00155d104f2c | D16: 45296.529 | E16: CCD - DPC - IMPLEMENTACIÓN ERP | F16: Johan Sebastian Rodriguez Niño | G16: https://growdatasas.sharepoint.com/sites/pwa/CCD - DPC - IMPLEMENTACIÓN ERP | H16: Suministro e implementación del sistema de información ADMINISTRATIVO ERP NOVASOFT – versión ENTERPRISE WEB y el GESTOR DE RIESGOS para la entidad Defensoría del Pueblo.Incluye: 14 módulos específicos + 5 módulos financieros con licencia para 5000 usuarios finales, Licenciamiento de la Base de Datos SQL Server (Estándar para 8 Cores), Consultoría estándar de implementación de cada uno de los sistemas ofrecidos, soporte y actualización por 2 años y una bolsa de horas (según acuerdo por 2 años) | I16: DATOS Y SISTEMAS DE INFORMACIÓN | J16: 0318 | K16: Activo.En Ejecución | L16: =VLOOKUP(E16,[1]Diccionario!C$2:AC$150,22,0) -> 3323223361 | M16: =VLOOKUP(E16,[1]Diccionario!C$2:AC$150,24,0) -> 45300 | N16: =VLOOKUP(E16,[1]Diccionario!C$2:AC$150,25,0) -> 45473 | O16: =VLOOKUP(E16,[1]Diccionario!C$2:AC$150,26,0) -> 5.7 | P16: =Q16-O16 -> 20.3 | Q16: =DATEDIF(M16,TODAY(),"m") -> 26 | R16: 6 | S16: 1 | T16: =T15+0.02 -> 0.64 | U16: =U15+TablaIndicador[[#This Row],[Costo Mensual]] -> 0 | W16: =IFERROR(T16*L16,0) -> 2.126863e+09 | X16: =S16*L16 -> 3323223361 | Y16: =IFERROR(W16-U16,0) -> 2.126863e+09 | Z16: =W16-X16 -> -1.1963604e+09 | AA16: =IFERROR(W16/U16,"No se realizó gasto en este corte") -> No se realizó gasto en este corte | AB16: =IFERROR( IF(OR(AA16="",AA16=0), "No calculado", IF(AA16>1,"Costo eficiente: se está gastando menos de lo presupuestado", IF(AA16=1,"Costo según lo presupuestado", "Costo ineficiente: se está gastando más de lo presupuestado"))), "No calculado") -> Costo eficiente: se está gastando menos de lo presupuestado | AC16: =IFERROR(W16/X16,0) -> 0.64 | AD16: =IF(OR(AC16="",AC16=0),"Sin Línea Base", IF(AC16>1,"Proyecto adelantado respecto al cronograma", IF(AC16=1,"Proyecto a tiempo según lo planificado", IF(AC16<1,"Proyecto atrasado con respecto al cronograma", "No calculado")))) -> Proyecto atrasado con respecto al cronograma | AE16: =IFERROR(L16/AA16,0) -> 0 | AF16: =IFERROR(AE16-L16,0) -> -3323223361 | AG16: =VLOOKUP(Indicador!E39,[1]Diccionario!C$1:AC$150,27,0) -> https://growdatasas.sharepoint.com/:x:/r/sites/Gestiondocumental/Administrativa/GD/Financiera/_layouts/15/Doc.aspx?sourcedoc=%7BB4DE39AF-1EC1-466C-A807-3FE95776A982%7D&file=17012024%20INFOTIC%20DPC%20SOC%20V2.xlsm&action=default&mobileredirect=true | AH16: 1 | AI16: 1
A17: 2025 | B17: Abril | C17: 227b8bc1-c7ab-ee11-ba7f-00155d104f2c | D17: 45296.529 | E17: CCD - DPC - IMPLEMENTACIÓN ERP | F17: Johan Sebastian Rodriguez Niño | G17: https://growdatasas.sharepoint.com/sites/pwa/CCD - DPC - IMPLEMENTACIÓN ERP | H17: Suministro e implementación del sistema de información ADMINISTRATIVO ERP NOVASOFT – versión ENTERPRISE WEB y el GESTOR DE RIESGOS para la entidad Defensoría del Pueblo.Incluye: 14 módulos específicos + 5 módulos financieros con licencia para 5000 usuarios finales, Licenciamiento de la Base de Datos SQL Server (Estándar para 8 Cores), Consultoría estándar de implementación de cada uno de los sistemas ofrecidos, soporte y actualización por 2 años y una bolsa de horas (según acuerdo por 2 años) | I17: DATOS Y SISTEMAS DE INFORMACIÓN | J17: 0318 | K17: Activo.En Ejecución | L17: =VLOOKUP(E17,[1]Diccionario!C$2:AC$150,22,0) -> 3323223361 | M17: =VLOOKUP(E17,[1]Diccionario!C$2:AC$150,24,0) -> 45300 | N17: =VLOOKUP(E17,[1]Diccionario!C$2:AC$150,25,0) -> 45473 | O17: =VLOOKUP(E17,[1]Diccionario!C$2:AC$150,26,0) -> 5.7 | P17: =Q17-O17 -> 20.3 | Q17: =DATEDIF(M17,TODAY(),"m") -> 26 | R17: 6 | S17: 1 | T17: =T16+0.02 -> 0.66 | U17: =U16+TablaIndicador[[#This Row],[Costo Mensual]] -> 0 | W17: =IFERROR(T17*L17,0) -> 2.1933274e+09 | X17: =S17*L17 -> 3323223361 | Y17: =IFERROR(W17-U17,0) -> 2.1933274e+09 | Z17: =W17-X17 -> -1.1298959e+09 | AA17: =IFERROR(W17/U17,"No se realizó gasto en este corte") -> No se realizó gasto en este corte | AB17: =IFERROR( IF(OR(AA17="",AA17=0), "No calculado", IF(AA17>1,"Costo eficiente: se está gastando menos de lo presupuestado", IF(AA17=1,"Costo según lo presupuestado", "Costo ineficiente: se está gastando más de lo presupuestado"))), "No calculado") -> Costo eficiente: se está gastando menos de lo presupuestado | AC17: =IFERROR(W17/X17,0) -> 0.66 | AD17: =IF(OR(AC17="",AC17=0),"Sin Línea Base", IF(AC17>1,"Proyecto adelantado respecto al cronograma", IF(AC17=1,"Proyecto a tiempo según lo planificado", IF(AC17<1,"Proyecto atrasado con respecto al cronograma", "No calculado")))) -> Proyecto atrasado con respecto al cronograma | AE17: =IFERROR(L17/AA17,0) -> 0 | AF17: =IFERROR(AE17-L17,0) -> -3323223361 | AG17: =VLOOKUP(Indicador!E40,[1]Diccionario!C$1:AC$150,27,0) -> https://growdatasas.sharepoint.com/:x:/r/sites/Gestiondocumental/Administrativa/GD/Financiera/_layouts/15/Doc.aspx?sourcedoc=%7BB4DE39AF-1EC1-466C-A807-3FE95776A982%7D&file=17012024%20INFOTIC%20DPC%20SOC%20V2.xlsm&action=default&mobileredirect=true | AH17: 1 | AI17: 1
A18: 2025 | B18: Mayo | C18: 227b8bc1-c7ab-ee11-ba7f-00155d104f2c | D18: 45296.529 | E18: CCD - DPC - IMPLEMENTACIÓN ERP | F18: Johan Sebastian Rodriguez Niño | G18: https://growdatasas.sharepoint.com/sites/pwa/CCD - DPC - IMPLEMENTACIÓN ERP | H18: Suministro e implementación del sistema de información ADMINISTRATIVO ERP NOVASOFT – versión ENTERPRISE WEB y el GESTOR DE RIESGOS para la entidad Defensoría del Pueblo.Incluye: 14 módulos específicos + 5 módulos financieros con licencia para 5000 usuarios finales, Licenciamiento de la Base de Datos SQL Server (Estándar para 8 Cores), Consultoría estándar de implementación de cada uno de los sistemas ofrecidos, soporte y actualización por 2 años y una bolsa de horas (según acuerdo por 2 años) | I18: DATOS Y SISTEMAS DE INFORMACIÓN | J18: 0318 | K18: Activo.En Ejecución | L18: =VLOOKUP(E18,[1]Diccionario!C$2:AC$150,22,0) -> 3323223361 | M18: =VLOOKUP(E18,[1]Diccionario!C$2:AC$150,24,0) -> 45300 | N18: =VLOOKUP(E18,[1]Diccionario!C$2:AC$150,25,0) -> 45473 | O18: =VLOOKUP(E18,[1]Diccionario!C$2:AC$150,26,0) -> 5.7 | P18: =Q18-O18 -> 20.3 | Q18: =DATEDIF(M18,TODAY(),"m") -> 26 | R18: 6 | S18: 1 | T18: =T17+0.02 -> 0.68 | U18: =U17+TablaIndicador[[#This Row],[Costo Mensual]] -> 0 | W18: =IFERROR(T18*L18,0) -> 2.2597919e+09 | X18: =S18*L18 -> 3323223361 | Y18: =IFERROR(W18-U18,0) -> 2.2597919e+09 | Z18: =W18-X18 -> -1.0634315e+09 | AA18: =IFERROR(W18/U18,"No se realizó gasto en este corte") -> No se realizó gasto en este corte | AB18: =IFERROR( IF(OR(AA18="",AA18=0), "No calculado", IF(AA18>1,"Costo eficiente: se está gastando menos de lo presupuestado", IF(AA18=1,"Costo según lo presupuestado", "Costo ineficiente: se está gastando más de lo presupuestado"))), "No calculado") -> Costo eficiente: se está gastando menos de lo presupuestado | AC18: =IFERROR(W18/X18,0) -> 0.68 | AD18: =IF(OR(AC18="",AC18=0),"Sin Línea Base", IF(AC18>1,"Proyecto adelantado respecto al cronograma", IF(AC18=1,"Proyecto a tiempo según lo planificado", IF(AC18<1,"Proyecto atrasado con respecto al cronograma", "No calculado")))) -> Proyecto atrasado con respecto al cronograma | AE18: =IFERROR(L18/AA18,0) -> 0 | AF18: =IFERROR(AE18-L18,0) -> -3323223361 | AG18: =VLOOKUP(Indicador!E41,[1]Diccionario!C$1:AC$150,27,0) -> https://growdatasas.sharepoint.com/:x:/r/sites/Gestiondocumental/Administrativa/GD/Financiera/_layouts/15/Doc.aspx?sourcedoc=%7BB4DE39AF-1EC1-466C-A807-3FE95776A982%7D&file=17012024%20INFOTIC%20DPC%20SOC%20V2.xlsm&action=default&mobileredirect=true | AH18: 1 | AI18: 1
A19: 2025 | B19: Junio | C19: 227b8bc1-c7ab-ee11-ba7f-00155d104f2c | D19: 45296.529 | E19: CCD - DPC - IMPLEMENTACIÓN ERP | F19: Johan Sebastian Rodriguez Niño | G19: https://growdatasas.sharepoint.com/sites/pwa/CCD - DPC - IMPLEMENTACIÓN ERP | H19: Suministro e implementación del sistema de información ADMINISTRATIVO ERP NOVASOFT – versión ENTERPRISE WEB y el GESTOR DE RIESGOS para la entidad Defensoría del Pueblo.Incluye: 14 módulos específicos + 5 módulos financieros con licencia para 5000 usuarios finales, Licenciamiento de la Base de Datos SQL Server (Estándar para 8 Cores), Consultoría estándar de implementación de cada uno de los sistemas ofrecidos, soporte y actualización por 2 años y una bolsa de horas (según acuerdo por 2 años) | I19: DATOS Y SISTEMAS DE INFORMACIÓN | J19: 0318 | K19: Activo.En Ejecución | L19: =VLOOKUP(E19,[1]Diccionario!C$2:AC$150,22,0) -> 3323223361 | M19: =VLOOKUP(E19,[1]Diccionario!C$2:AC$150,24,0) -> 45300 | N19: =VLOOKUP(E19,[1]Diccionario!C$2:AC$150,25,0) -> 45473 | O19: =VLOOKUP(E19,[1]Diccionario!C$2:AC$150,26,0) -> 5.7 | P19: =Q19-O19 -> 20.3 | Q19: =DATEDIF(M19,TODAY(),"m") -> 26 | R19: 6 | S19: 1 | T19: =T18+0.02 -> 0.7 | U19: =U18+TablaIndicador[[#This Row],[Costo Mensual]] -> 0 | W19: =IFERROR(T19*L19,0) -> 2.3262564e+09 | X19: =S19*L19 -> 3323223361 | Y19: =IFERROR(W19-U19,0) -> 2.3262564e+09 | Z19: =W19-X19 -> -9.9696701e+08 | AA19: =IFERROR(W19/U19,"No se realizó gasto en este corte") -> No se realizó gasto en este corte | AB19: =IFERROR( IF(OR(AA19="",AA19=0), "No calculado", IF(AA19>1,"Costo eficiente: se está gastando menos de lo presupuestado", IF(AA19=1,"Costo según lo presupuestado", "Costo ineficiente: se está gastando más de lo presupuestado"))), "No calculado") -> Costo eficiente: se está gastando menos de lo presupuestado | AC19: =IFERROR(W19/X19,0) -> 0.7 | AD19: =IF(OR(AC19="",AC19=0),"Sin Línea Base", IF(AC19>1,"Proyecto adelantado respecto al cronograma", IF(AC19=1,"Proyecto a tiempo según lo planificado", IF(AC19<1,"Proyecto atrasado con respecto al cronograma", "No calculado")))) -> Proyecto atrasado con respecto al cronograma | AE19: =IFERROR(L19/AA19,0) -> 0 | AF19: =IFERROR(AE19-L19,0) -> -3323223361 | AG19: =VLOOKUP(Indicador!E42,[1]Diccionario!C$1:AC$150,27,0) -> https://growdatasas.sharepoint.com/:x:/r/sites/Gestiondocumental/Administrativa/GD/Financiera/_layouts/15/Doc.aspx?sourcedoc=%7B453B6AA8-B631-4722-B916-8323F8C43E87%7D&file=315%20CORP%20COLOMBIA%20DIGITAL%20FNA%20AE.xlsm&action=default&mobileredirect=true | AH19: 1 | AI19: 1
A20: 2025 | B20: Julio | C20: 227b8bc1-c7ab-ee11-ba7f-00155d104f2c | D20: 45296.529 | E20: CCD - DPC - IMPLEMENTACIÓN ERP | F20: Johan Sebastian Rodriguez Niño | G20: https://growdatasas.sharepoint.com/sites/pwa/CCD - DPC - IMPLEMENTACIÓN ERP | H20: Suministro e implementación del sistema de información ADMINISTRATIVO ERP NOVASOFT – versión ENTERPRISE WEB y el GESTOR DE RIESGOS para la entidad Defensoría del Pueblo.Incluye: 14 módulos específicos + 5 módulos financieros con licencia para 5000 usuarios finales, Licenciamiento de la Base de Datos SQL Server (Estándar para 8 Cores), Consultoría estándar de implementación de cada uno de los sistemas ofrecidos, soporte y actualización por 2 años y una bolsa de horas (según acuerdo por 2 años) | I20: DATOS Y SISTEMAS DE INFORMACIÓN | J20: 0318 | K20: Activo.En Ejecución | L20: =VLOOKUP(E20,[1]Diccionario!C$2:AC$150,22,0) -> 3323223361 | M20: =VLOOKUP(E20,[1]Diccionario!C$2:AC$150,24,0) -> 45300 | N20: =VLOOKUP(E20,[1]Diccionario!C$2:AC$150,25,0) -> 45473 | O20: =VLOOKUP(E20,[1]Diccionario!C$2:AC$150,26,0) -> 5.7 | P20: =Q20-O20 -> 20.3 | Q20: =DATEDIF(M20,TODAY(),"m") -> 26 | R20: 6 | S20: 1 | T20: =T19+0.02 -> 0.72 | U20: =U19+TablaIndicador[[#This Row],[Costo Mensual]] -> 0 | W20: =IFERROR(T20*L20,0) -> 2.3927208e+09 | X20: =S20*L20 -> 3323223361 | Y20: =IFERROR(W20-U20,0) -> 2.3927208e+09 | Z20: =W20-X20 -> -9.3050254e+08 | AA20: =IFERROR(W20/U20,"No se realizó gasto en este corte") -> No se realizó gasto en este corte | AB20: =IFERROR( IF(OR(AA20="",AA20=0), "No calculado", IF(AA20>1,"Costo eficiente: se está gastando menos de lo presupuestado", IF(AA20=1,"Costo según lo presupuestado", "Costo ineficiente: se está gastando más de lo presupuestado"))), "No calculado") -> Costo eficiente: se está gastando menos de lo presupuestado | AC20: =IFERROR(W20/X20,0) -> 0.72 | AD20: =IF(OR(AC20="",AC20=0),"Sin Línea Base", IF(AC20>1,"Proyecto adelantado respecto al cronograma", IF(AC20=1,"Proyecto a tiempo según lo planificado", IF(AC20<1,"Proyecto atrasado con respecto al cronograma", "No calculado")))) -> Proyecto atrasado con respecto al cronograma | AE20: =IFERROR(L20/AA20,0) -> 0 | AF20: =IFERROR(AE20-L20,0) -> -3323223361 | AG20: =VLOOKUP(Indicador!E43,[1]Diccionario!C$1:AC$150,27,0) -> https://growdatasas.sharepoint.com/:x:/r/sites/Gestiondocumental/Administrativa/GD/Financiera/_layouts/15/Doc.aspx?sourcedoc=%7B453B6AA8-B631-4722-B916-8323F8C43E87%7D&file=315%20CORP%20COLOMBIA%20DIGITAL%20FNA%20AE.xlsm&action=default&mobileredirect=true | AH20: 1 | AI20: 1
A21: 2025 | B21: Agosto | C21: 227b8bc1-c7ab-ee11-ba7f-00155d104f2c | D21: 45296.529 | E21: CCD - DPC - IMPLEMENTACIÓN ERP | F21: Johan Sebastian Rodriguez Niño | G21: https://growdatasas.sharepoint.com/sites/pwa/CCD - DPC - IMPLEMENTACIÓN ERP | H21: Suministro e implementación del sistema de información ADMINISTRATIVO ERP NOVASOFT – versión ENTERPRISE WEB y el GESTOR DE RIESGOS para la entidad Defensoría del Pueblo.Incluye: 14 módulos específicos + 5 módulos financieros con licencia para 5000 usuarios finales, Licenciamiento de la Base de Datos SQL Server (Estándar para 8 Cores), Consultoría estándar de implementación de cada uno de los sistemas ofrecidos, soporte y actualización por 2 años y una bolsa de horas (según acuerdo por 2 años) | I21: DATOS Y SISTEMAS DE INFORMACIÓN | J21: 0318 | K21: Activo.En Ejecución | L21: =VLOOKUP(E21,[1]Diccionario!C$2:AC$150,22,0) -> 3323223361 | M21: =VLOOKUP(E21,[1]Diccionario!C$2:AC$150,24,0) -> 45300 | N21: =VLOOKUP(E21,[1]Diccionario!C$2:AC$150,25,0) -> 45473 | O21: =VLOOKUP(E21,[1]Diccionario!C$2:AC$150,26,0) -> 5.7 | P21: =Q21-O21 -> 20.3 | Q21: =DATEDIF(M21,TODAY(),"m") -> 26 | R21: 6 | S21: 1 | T21: =T20+0.02 -> 0.74 | U21: =U20+TablaIndicador[[#This Row],[Costo Mensual]] -> 0 | W21: =IFERROR(T21*L21,0) -> 2.4591853e+09 | X21: =S21*L21 -> 3323223361 | Y21: =IFERROR(W21-U21,0) -> 2.4591853e+09 | Z21: =W21-X21 -> -8.6403807e+08 | AA21: =IFERROR(W21/U21,"No se realizó gasto en este corte") -> No se realizó gasto en este corte | AB21: =IFERROR( IF(OR(AA21="",AA21=0), "No calculado", IF(AA21>1,"Costo eficiente: se está gastando menos de lo presupuestado", IF(AA21=1,"Costo según lo presupuestado", "Costo ineficiente: se está gastando más de lo presupuestado"))), "No calculado") -> Costo eficiente: se está gastando menos de lo presupuestado | AC21: =IFERROR(W21/X21,0) -> 0.74 | AD21: =IF(OR(AC21="",AC21=0),"Sin Línea Base", IF(AC21>1,"Proyecto adelantado respecto al cronograma", IF(AC21=1,"Proyecto a tiempo según lo planificado", IF(AC21<1,"Proyecto atrasado con respecto al cronograma", "No calculado")))) -> Proyecto atrasado con respecto al cronograma | AE21: =IFERROR(L21/AA21,0) -> 0 | AF21: =IFERROR(AE21-L21,0) -> -3323223361 | AG21: =VLOOKUP(Indicador!E44,[1]Diccionario!C$1:AC$150,27,0) -> https://growdatasas.sharepoint.com/:x:/r/sites/Gestiondocumental/Administrativa/GD/Financiera/_layouts/15/Doc.aspx?sourcedoc=%7B453B6AA8-B631-4722-B916-8323F8C43E87%7D&file=315%20CORP%20COLOMBIA%20DIGITAL%20FNA%20AE.xlsm&action=default&mobileredirect=true | AH21: 1 | AI21: 1
A22: 2025 | B22: Septiembre | C22: 227b8bc1-c7ab-ee11-ba7f-00155d104f2c | D22: 45296.529 | E22: CCD - DPC - IMPLEMENTACIÓN ERP | F22: Johan Sebastian Rodriguez Niño | G22: https://growdatasas.sharepoint.com/sites/pwa/CCD - DPC - IMPLEMENTACIÓN ERP | H22: Suministro e implementación del sistema de información ADMINISTRATIVO ERP NOVASOFT – versión ENTERPRISE WEB y el GESTOR DE RIESGOS para la entidad Defensoría del Pueblo.Incluye: 14 módulos específicos + 5 módulos financieros con licencia para 5000 usuarios finales, Licenciamiento de la Base de Datos SQL Server (Estándar para 8 Cores), Consultoría estándar de implementación de cada uno de los sistemas ofrecidos, soporte y actualización por 2 años y una bolsa de horas (según acuerdo por 2 años) | I22: DATOS Y SISTEMAS DE INFORMACIÓN | J22: 0318 | K22: Activo.En Ejecución | L22: =VLOOKUP(E22,[1]Diccionario!C$2:AC$150,22,0) -> 3323223361 | M22: =VLOOKUP(E22,[1]Diccionario!C$2:AC$150,24,0) -> 45300 | N22: =VLOOKUP(E22,[1]Diccionario!C$2:AC$150,25,0) -> 45473 | O22: =VLOOKUP(E22,[1]Diccionario!C$2:AC$150,26,0) -> 5.7 | P22: =Q22-O22 -> 20.3 | Q22: =DATEDIF(M22,TODAY(),"m") -> 26 | R22: 6 | S22: 1 | T22: =T21+0.02 -> 0.76 | U22: =U21+TablaIndicador[[#This Row],[Costo Mensual]] -> 0 | W22: =IFERROR(T22*L22,0) -> 2.5256498e+09 | X22: =S22*L22 -> 3323223361 | Y22: =IFERROR(W22-U22,0) -> 2.5256498e+09 | Z22: =W22-X22 -> -7.9757361e+08 | AA22: =IFERROR(W22/U22,"No se realizó gasto en este corte") -> No se realizó gasto en este corte | AB22: =IFERROR( IF(OR(AA22="",AA22=0), "No calculado", IF(AA22>1,"Costo eficiente: se está gastando menos de lo presupuestado", IF(AA22=1,"Costo según lo presupuestado", "Costo ineficiente: se está gastando más de lo presupuestado"))), "No calculado") -> Costo eficiente: se está gastando menos de lo presupuestado | AC22: =IFERROR(W22/X22,0) -> 0.76 | AD22: =IF(OR(AC22="",AC22=0),"Sin Línea Base", IF(AC22>1,"Proyecto adelantado respecto al cronograma", IF(AC22=1,"Proyecto a tiempo según lo planificado", IF(AC22<1,"Proyecto atrasado con respecto al cronograma", "No calculado")))) -> Proyecto atrasado con respecto al cronograma | AE22: =IFERROR(L22/AA22,0) -> 0 | AF22: =IFERROR(AE22-L22,0) -> -3323223361 | AG22: =VLOOKUP(Indicador!E45,[1]Diccionario!C$1:AC$150,27,0) -> https://growdatasas.sharepoint.com/:x:/r/sites/Gestiondocumental/Administrativa/GD/Financiera/_layouts/15/Doc.aspx?sourcedoc=%7B453B6AA8-B631-4722-B916-8323F8C43E87%7D&file=315%20CORP%20COLOMBIA%20DIGITAL%20FNA%20AE.xlsm&action=default&mobileredirect=true | AH22: 1 | AI22: 1
A23: 2025 | B23: Octubre | C23: 227b8bc1-c7ab-ee11-ba7f-00155d104f2c | D23: 45296.529 | E23: CCD - DPC - IMPLEMENTACIÓN ERP | F23: Johan Sebastian Rodriguez Niño | G23: https://growdatasas.sharepoint.com/sites/pwa/CCD - DPC - IMPLEMENTACIÓN ERP | H23: Suministro e implementación del sistema de información ADMINISTRATIVO ERP NOVASOFT – versión ENTERPRISE WEB y el GESTOR DE RIESGOS para la entidad Defensoría del Pueblo.Incluye: 14 módulos específicos + 5 módulos financieros con licencia para 5000 usuarios finales, Licenciamiento de la Base de Datos SQL Server (Estándar para 8 Cores), Consultoría estándar de implementación de cada uno de los sistemas ofrecidos, soporte y actualización por 2 años y una bolsa de horas (según acuerdo por 2 años) | I23: DATOS Y SISTEMAS DE INFORMACIÓN | J23: 0318 | K23: Activo.En Ejecución | L23: =VLOOKUP(E23,[1]Diccionario!C$2:AC$150,22,0) -> 3323223361 | M23: =VLOOKUP(E23,[1]Diccionario!C$2:AC$150,24,0) -> 45300 | N23: =VLOOKUP(E23,[1]Diccionario!C$2:AC$150,25,0) -> 45473 | O23: =VLOOKUP(E23,[1]Diccionario!C$2:AC$150,26,0) -> 5.7 | P23: =Q23-O23 -> 20.3 | Q23: =DATEDIF(M23,TODAY(),"m") -> 26 | R23: 6 | S23: 1 | T23: =T22+0.02 -> 0.78 | U23: =U22+TablaIndicador[[#This Row],[Costo Mensual]] -> 0 | W23: =IFERROR(T23*L23,0) -> 2.5921142e+09 | X23: =S23*L23 -> 3323223361 | Y23: =IFERROR(W23-U23,0) -> 2.5921142e+09 | Z23: =W23-X23 -> -7.3110914e+08 | AA23: =IFERROR(W23/U23,"No se realizó gasto en este corte") -> No se realizó gasto en este corte | AB23: =IFERROR( IF(OR(AA23="",AA23=0), "No calculado", IF(AA23>1,"Costo eficiente: se está gastando menos de lo presupuestado", IF(AA23=1,"Costo según lo presupuestado", "Costo ineficiente: se está gastando más de lo presupuestado"))), "No calculado") -> Costo eficiente: se está gastando menos de lo presupuestado | AC23: =IFERROR(W23/X23,0) -> 0.78 | AD23: =IF(OR(AC23="",AC23=0),"Sin Línea Base", IF(AC23>1,"Proyecto adelantado respecto al cronograma", IF(AC23=1,"Proyecto a tiempo según lo planificado", IF(AC23<1,"Proyecto atrasado con respecto al cronograma", "No calculado")))) -> Proyecto atrasado con respecto al cronograma | AE23: =IFERROR(L23/AA23,0) -> 0 | AF23: =IFERROR(AE23-L23,0) -> -3323223361 | AG23: =VLOOKUP(Indicador!E46,[1]Diccionario!C$1:AC$150,27,0) -> https://growdatasas.sharepoint.com/:x:/r/sites/Gestiondocumental/Administrativa/GD/Financiera/_layouts/15/Doc.aspx?sourcedoc=%7B453B6AA8-B631-4722-B916-8323F8C43E87%7D&file=315%20CORP%20COLOMBIA%20DIGITAL%20FNA%20AE.xlsm&action=default&mobileredirect=true | AH23: 1 | AI23: 1
A24: 2025 | B24: Noviembre | C24: 227b8bc1-c7ab-ee11-ba7f-00155d104f2c | D24: 45296.529 | E24: CCD - DPC - IMPLEMENTACIÓN ERP | F24: Johan Sebastian Rodriguez Niño | G24: https://growdatasas.sharepoint.com/sites/pwa/CCD - DPC - IMPLEMENTACIÓN ERP | H24: Suministro e implementación del sistema de información ADMINISTRATIVO ERP NOVASOFT – versión ENTERPRISE WEB y el GESTOR DE RIESGOS para la entidad Defensoría del Pueblo.Incluye: 14 módulos específicos + 5 módulos financieros con licencia para 5000 usuarios finales, Licenciamiento de la Base de Datos SQL Server (Estándar para 8 Cores), Consultoría estándar de implementación de cada uno de los sistemas ofrecidos, soporte y actualización por 2 años y una bolsa de horas (según acuerdo por 2 años) | I24: DATOS Y SISTEMAS DE INFORMACIÓN | J24: 0318 | K24: Activo.En Ejecución | L24: =VLOOKUP(E24,[1]Diccionario!C$2:AC$150,22,0) -> 3323223361 | M24: =VLOOKUP(E24,[1]Diccionario!C$2:AC$150,24,0) -> 45300 | N24: =VLOOKUP(E24,[1]Diccionario!C$2:AC$150,25,0) -> 45473 | O24: =VLOOKUP(E24,[1]Diccionario!C$2:AC$150,26,0) -> 5.7 | P24: =Q24-O24 -> 20.3 | Q24: =DATEDIF(M24,TODAY(),"m") -> 26 | R24: 6 | S24: 1 | T24: =T23+0.02 -> 0.8 | U24: =U23+TablaIndicador[[#This Row],[Costo Mensual]] -> 0 | W24: =IFERROR(T24*L24,0) -> 2.6585787e+09 | X24: =S24*L24 -> 3323223361 | Y24: =IFERROR(W24-U24,0) -> 2.6585787e+09 | Z24: =W24-X24 -> -6.6464467e+08 | AA24: =IFERROR(W24/U24,"No se realizó gasto en este corte") -> No se realizó gasto en este corte | AB24: =IFERROR( IF(OR(AA24="",AA24=0), "No calculado", IF(AA24>1,"Costo eficiente: se está gastando menos de lo presupuestado", IF(AA24=1,"Costo según lo presupuestado", "Costo ineficiente: se está gastando más de lo presupuestado"))), "No calculado") -> Costo eficiente: se está gastando menos de lo presupuestado | AC24: =IFERROR(W24/X24,0) -> 0.8 | AD24: =IF(OR(AC24="",AC24=0),"Sin Línea Base", IF(AC24>1,"Proyecto adelantado respecto al cronograma", IF(AC24=1,"Proyecto a tiempo según lo planificado", IF(AC24<1,"Proyecto atrasado con respecto al cronograma", "No calculado")))) -> Proyecto atrasado con respecto al cronograma | AE24: =IFERROR(L24/AA24,0) -> 0 | AF24: =IFERROR(AE24-L24,0) -> -3323223361 | AG24: =VLOOKUP(Indicador!E47,[1]Diccionario!C$1:AC$150,27,0) -> https://growdatasas.sharepoint.com/:x:/r/sites/Gestiondocumental/Administrativa/GD/Financiera/_layouts/15/Doc.aspx?sourcedoc=%7B453B6AA8-B631-4722-B916-8323F8C43E87%7D&file=315%20CORP%20COLOMBIA%20DIGITAL%20FNA%20AE.xlsm&action=default&mobileredirect=true | AH24: 1 | AI24: 1
A25: 2025 | B25: Diciembre | C25: 227b8bc1-c7ab-ee11-ba7f-00155d104f2c | D25: 45296.529 | E25: CCD - DPC - IMPLEMENTACIÓN ERP | F25: Johan Sebastian Rodriguez Niño | G25: https://growdatasas.sharepoint.com/sites/pwa/CCD - DPC - IMPLEMENTACIÓN ERP | H25: Suministro e implementación del sistema de información ADMINISTRATIVO ERP NOVASOFT – versión ENTERPRISE WEB y el GESTOR DE RIESGOS para la entidad Defensoría del Pueblo.Incluye: 14 módulos específicos + 5 módulos financieros con licencia para 5000 usuarios finales, Licenciamiento de la Base de Datos SQL Server (Estándar para 8 Cores), Consultoría estándar de implementación de cada uno de los sistemas ofrecidos, soporte y actualización por 2 años y una bolsa de horas (según acuerdo por 2 años) | I25: DATOS Y SISTEMAS DE INFORMACIÓN | J25: 0318 | K25: Activo.En Ejecución | L25: =VLOOKUP(E25,[1]Diccionario!C$2:AC$150,22,0) -> 3323223361 | M25: =VLOOKUP(E25,[1]Diccionario!C$2:AC$150,24,0) -> 45300 | N25: =VLOOKUP(E25,[1]Diccionario!C$2:AC$150,25,0) -> 45473 | O25: =VLOOKUP(E25,[1]Diccionario!C$2:AC$150,26,0) -> 5.7 | P25: =Q25-O25 -> 20.3 | Q25: =DATEDIF(M25,TODAY(),"m") -> 26 | R25: 6 | S25: 1 | T25: =T24+0.02 -> 0.82 | U25: =U24+TablaIndicador[[#This Row],[Costo Mensual]] -> 0 | W25: =IFERROR(T25*L25,0) -> 2.7250432e+09 | X25: =S25*L25 -> 3323223361 | Y25: =IFERROR(W25-U25,0) -> 2.7250432e+09 | Z25: =W25-X25 -> -5.981802e+08 | AA25: =IFERROR(W25/U25,"No se realizó gasto en este corte") -> No se realizó gasto en este corte | AB25: =IFERROR( IF(OR(AA25="",AA25=0), "No calculado", IF(AA25>1,"Costo eficiente: se está gastando menos de lo presupuestado", IF(AA25=1,"Costo según lo presupuestado", "Costo ineficiente: se está gastando más de lo presupuestado"))), "No calculado") -> Costo eficiente: se está gastando menos de lo presupuestado | AC25: =IFERROR(W25/X25,0) -> 0.82 | AD25: =IF(OR(AC25="",AC25=0),"Sin Línea Base", IF(AC25>1,"Proyecto adelantado respecto al cronograma", IF(AC25=1,"Proyecto a tiempo según lo planificado", IF(AC25<1,"Proyecto atrasado con respecto al cronograma", "No calculado")))) -> Proyecto atrasado con respecto al cronograma | AE25: =IFERROR(L25/AA25,0) -> 0 | AF25: =IFERROR(AE25-L25,0) -> -3323223361 | AG25: =VLOOKUP(Indicador!E48,[1]Diccionario!C$1:AC$150,27,0) -> https://growdatasas.sharepoint.com/:x:/r/sites/Gestiondocumental/Administrativa/GD/Financiera/_layouts/15/Doc.aspx?sourcedoc=%7B453B6AA8-B631-4722-B916-8323F8C43E87%7D&file=315%20CORP%20COLOMBIA%20DIGITAL%20FNA%20AE.xlsm&action=default&mobileredirect=true | AH25: 1 | AI25: 1
... A27: 2026 | B27: Febrero | C27: 227b8bc1-c7ab-ee11-ba7f-00155d104f2c | D27: 45296.529 | E27: CCD - DPC - IMPLEMENTACIÓN ERP | F27: Johan Sebastian Rodriguez Niño | G27: https://growdatasas.sharepoint.com/sites/pwa/CCD - DPC - IMPLEMENTACIÓN ERP | H27: Suministro e implementación del sistema de información ADMINISTRATIVO ERP NOVASOFT – versión ENTERPRISE WEB y el GESTOR DE RIESGOS para la entidad Defensoría del Pueblo.Incluye: 14 módulos específicos + 5 módulos financieros con licencia para 5000 usuarios finales, Licenciamiento de la Base de Datos SQL Server (Estándar para 8 Cores), Consultoría estándar de implementación de cada uno de los sistemas ofrecidos, soporte y actualización por 2 años y una bolsa de horas (según acuerdo por 2 años) | I27: DATOS Y SISTEMAS DE INFORMACIÓN | J27: 0318 | K27: Activo.En Ejecución | L27: =VLOOKUP(E27,[1]Diccionario!C$2:AC$150,22,0) -> 3323223361 | M27: =VLOOKUP(E27,[1]Diccionario!C$2:AC$150,24,0) -> 45300 | N27: =VLOOKUP(E27,[1]Diccionario!C$2:AC$150,25,0) -> 45473 | O27: =VLOOKUP(E27,[1]Diccionario!C$2:AC$150,26,0) -> 5.7 | P27: =Q27-O27 -> 20.3 | Q27: =DATEDIF(M27,TODAY(),"m") -> 26 | R27: 6 | S27: 1 | T27: =T26+0.02 -> 0.86 | U27: =U26+TablaIndicador[[#This Row],[Costo Mensual]] -> 0 | W27: =IFERROR(T27*L27,0) -> 2.8579721e+09 | X27: =S27*L27 -> 3323223361 | Y27: =IFERROR(W27-U27,0) -> 2.8579721e+09 | Z27: =W27-X27 -> -4.6525127e+08 | AA27: =IFERROR(W27/U27,"No se realizó gasto en este corte") -> No se realizó gasto en este corte | AB27: =IFERROR( IF(OR(AA27="",AA27=0), "No calculado", IF(AA27>1,"Costo eficiente: se está gastando menos de lo presupuestado", IF(AA27=1,"Costo según lo presupuestado", "Costo ineficiente: se está gastando más de lo presupuestado"))), "No calculado") -> Costo eficiente: se está gastando menos de lo presupuestado | AC27: =IFERROR(W27/X27,0) -> 0.86 | AD27: =IF(OR(AC27="",AC27=0),"Sin Línea Base", IF(AC27>1,"Proyecto adelantado respecto al cronograma", IF(AC27=1,"Proyecto a tiempo según lo planificado", IF(AC27<1,"Proyecto atrasado con respecto al cronograma", "No calculado")))) -> Proyecto atrasado con respecto al cronograma | AE27: =IFERROR(L27/AA27,0) -> 0 | AF27: =IFERROR(AE27-L27,0) -> -3323223361 | AG27: =VLOOKUP(Indicador!E50,[1]Diccionario!C$1:AC$150,27,0) -> https://growdatasas.sharepoint.com/:x:/r/sites/Gestiondocumental/Administrativa/GD/Financiera/_layouts/15/Doc.aspx?sourcedoc=%7B453B6AA8-B631-4722-B916-8323F8C43E87%7D&file=315%20CORP%20COLOMBIA%20DIGITAL%20FNA%20AE.xlsm&action=default&mobileredirect=true | AH27: 1 | AI27: 1
A28: 2024 | B28: Enero | C28: becfcaa1-85b4-ee11-871a-00155d105d1e | D28: 45307.653 | E28: TELEFONICA – DPC SALA DE ANALITICA | F28: Guiovanni Andres Serrano Serna | G28: https://growdatasas.sharepoint.com/sites/pwa/TELEFONICA – DPC SALA DE ANALITICA | H28: ​Adecuación de la sala de analítica en dos fases, fase 1 obra civil y remodelación. | I28: TI | J28: 0314 | K28: Postventa | L28: =VLOOKUP(E28,[1]Diccionario!C$2:AC$150,22,0) -> 970233948 | M28: =VLOOKUP(E28,[1]Diccionario!C$2:AC$150,24,0) -> 45306 | N28: =VLOOKUP(E28,[1]Diccionario!C$2:AC$150,25,0) -> 45412 | O28: =VLOOKUP(E28,[1]Diccionario!C$2:AC$150,26,0) -> 3.5 | P28: =Q28-O28 -> -2.5 | Q28: 1 | R28: 4 | S28: 0.2 | T28: 0.2 | U28: =TablaIndicador[[#This Row],[Costo Mensual]] -> 0 | W28: =IFERROR(T28*L28,0) -> 1.9404679e+08 | X28: =S28*L28 -> 1.9404679e+08 | Y28: =IFERROR(W28-U28,0) -> 1.9404679e+08 | Z28: =W28-X28 -> 0 | AA28: =IFERROR(W28/U28,"No se realizó gasto en este corte") -> No se realizó gasto en este corte | AB28: =IFERROR( IF(OR(AA28="",AA28=0), "No calculado", IF(AA28>1,"Costo eficiente: se está gastando menos de lo presupuestado", IF(AA28=1,"Costo según lo presupuestado", "Costo ineficiente: se está gastando más de lo presupuestado"))), "No calculado") -> Costo eficiente: se está gastando menos de lo presupuestado | AC28: =IFERROR(W28/X28,0) -> 1 | AD28: =IF(OR(AC28="",AC28=0),"Sin Línea Base", IF(AC28>1,"Proyecto adelantado respecto al cronograma", IF(AC28=1,"Proyecto a tiempo según lo planificado", IF(AC28<1,"Proyecto atrasado con respecto al cronograma", "No calculado")))) -> Proyecto a tiempo según lo planificado | AE28: =IFERROR(L28/AA28,0) -> 0 | AF28: =IFERROR(AE28-L28,0) -> -970233948 | AG28: =VLOOKUP(Indicador!E51,[1]Diccionario!C$1:AC$150,27,0) -> https://growdatasas.sharepoint.com/:x:/r/sites/Gestiondocumental/Administrativa/GD/Financiera/_layouts/15/Doc.aspx?sourcedoc=%7B453B6AA8-B631-4722-B916-8323F8C43E87%7D&file=315%20CORP%20COLOMBIA%20DIGITAL%20FNA%20AE.xlsm&action=default&mobileredirect=true | AH28: 1 | AI28: 1 | AK28: Revisar este se ejecuto 2024
A29: 2024 | B29: Febrero | C29: becfcaa1-85b4-ee11-871a-00155d105d1e | D29: 45307.653 | E29: TELEFONICA – DPC SALA DE ANALITICA | F29: Guiovanni Andres Serrano Serna | G29: https://growdatasas.sharepoint.com/sites/pwa/TELEFONICA – DPC SALA DE ANALITICA | H29: ​Adecuación de la sala de analítica en dos fases, fase 1 obra civil y remodelación. | I29: TI | J29: 0314 | K29: Postventa | L29: =VLOOKUP(E29,[1]Diccionario!C$2:AC$150,22,0) -> 970233948 | M29: =VLOOKUP(E29,[1]Diccionario!C$2:AC$150,24,0) -> 45306 | N29: =VLOOKUP(E29,[1]Diccionario!C$2:AC$150,25,0) -> 45412 | O29: =VLOOKUP(E29,[1]Diccionario!C$2:AC$150,26,0) -> 3.5 | P29: =Q29-O29 -> -1.5 | Q29: 2 | R29: 4 | S29: 0.6 | T29: 0.4 | U29: =U28+TablaIndicador[[#This Row],[Costo Mensual]] -> 0 | W29: =IFERROR(T29*L29,0) -> 3.8809358e+08 | X29: =S29*L29 -> 5.8214037e+08 | Y29: =IFERROR(W29-U29,0) -> 3.8809358e+08 | Z29: =W29-X29 -> -1.9404679e+08 | AA29: =IFERROR(W29/U29,"No se realizó gasto en este corte") -> No se realizó gasto en este corte | AB29: =IFERROR( IF(OR(AA29="",AA29=0), "No calculado", IF(AA29>1,"Costo eficiente: se está gastando menos de lo presupuestado", IF(AA29=1,"Costo según lo presupuestado", "Costo ineficiente: se está gastando más de lo presupuestado"))), "No calculado") -> Costo eficiente: se está gastando menos de lo presupuestado | AC29: =IFERROR(W29/X29,0) -> 0.66666667 | AD29: =IF(OR(AC29="",AC29=0),"Sin Línea Base", IF(AC29>1,"Proyecto adelantado respecto al cronograma", IF(AC29=1,"Proyecto a tiempo según lo planificado", IF(AC29<1,"Proyecto atrasado con respecto al cronograma", "No calculado")))) -> Proyecto atrasado con respecto al cronograma | AE29: =IFERROR(L29/AA29,0) -> 0 | AF29: =IFERROR(AE29-L29,0) -> -970233948 | AG29: =VLOOKUP(Indicador!E52,[1]Diccionario!C$1:AC$150,27,0) -> https://growdatasas.sharepoint.com/:x:/r/sites/Gestiondocumental/Administrativa/GD/Financiera/_layouts/15/Doc.aspx?sourcedoc=%7B453B6AA8-B631-4722-B916-8323F8C43E87%7D&file=315%20CORP%20COLOMBIA%20DIGITAL%20FNA%20AE.xlsm&action=default&mobileredirect=true | AH29: 1 | AI29: 1 | AK29: Revisar este se ejecuto 2024
A30: 2024 | B30: Marzo | C30: becfcaa1-85b4-ee11-871a-00155d105d1e | D30: 45307.653 | E30: TELEFONICA – DPC SALA DE ANALITICA | F30: Guiovanni Andres Serrano Serna | G30: https://growdatasas.sharepoint.com/sites/pwa/TELEFONICA – DPC SALA DE ANALITICA | H30: ​Adecuación de la sala de analítica en dos fases, fase 1 obra civil y remodelación. | I30: TI | J30: 0314 | K30: Postventa | L30: =VLOOKUP(E30,[1]Diccionario!C$2:AC$150,22,0) -> 970233948 | M30: =VLOOKUP(E30,[1]Diccionario!C$2:AC$150,24,0) -> 45306 | N30: =VLOOKUP(E30,[1]Diccionario!C$2:AC$150,25,0) -> 45412 | O30: =VLOOKUP(E30,[1]Diccionario!C$2:AC$150,26,0) -> 3.5 | P30: =Q30-O30 -> -0.5 | Q30: 3 | R30: 4 | S30: 0.8 | T30: 0.5 | U30: =U29+TablaIndicador[[#This Row],[Costo Mensual]] -> 0 | W30: =IFERROR(T30*L30,0) -> 485116974 | X30: =S30*L30 -> 7.7618716e+08 | Y30: =IFERROR(W30-U30,0) -> 485116974 | Z30: =W30-X30 -> -2.9107018e+08 | AA30: =IFERROR(W30/U30,"No se realizó gasto en este corte") -> No se realizó gasto en este corte | AB30: =IFERROR( IF(OR(AA30="",AA30=0), "No calculado", IF(AA30>1,"Costo eficiente: se está gastando menos de lo presupuestado", IF(AA30=1,"Costo según lo presupuestado", "Costo ineficiente: se está gastando más de lo presupuestado"))), "No calculado") -> Costo eficiente: se está gastando menos de lo presupuestado | AC30: =IFERROR(W30/X30,0) -> 0.625 | AD30: =IF(OR(AC30="",AC30=0),"Sin Línea Base", IF(AC30>1,"Proyecto adelantado respecto al cronograma", IF(AC30=1,"Proyecto a tiempo según lo planificado", IF(AC30<1,"Proyecto atrasado con respecto al cronograma", "No calculado")))) -> Proyecto atrasado con respecto al cronograma | AE30: =IFERROR(L30/AA30,0) -> 0 | AF30: =IFERROR(AE30-L30,0) -> -970233948 | AG30: =VLOOKUP(Indicador!E53,[1]Diccionario!C$1:AC$150,27,0) -> https://growdatasas.sharepoint.com/:x:/r/sites/Gestiondocumental/Administrativa/GD/Financiera/_layouts/15/Doc.aspx?sourcedoc=%7B06FB1484-E2DE-40DA-83E0-D97F6AF0AE9B%7D&file=MODELO%20FINANCIERO%20REFERENCIA%20V7%20MS%2020240130.xlsx&action=default&mobileredirect=true | AH30: 1 | AI30: 1 | AK30: Revisar este se ejecuto 2024
A31: 2024 | B31: Abril | C31: becfcaa1-85b4-ee11-871a-00155d105d1e | D31: 45307.653 | E31: TELEFONICA – DPC SALA DE ANALITICA | F31: Guiovanni Andres Serrano Serna | G31: https://growdatasas.sharepoint.com/sites/pwa/TELEFONICA – DPC SALA DE ANALITICA | H31: ​Adecuación de la sala de analítica en dos fases, fase 1 obra civil y remodelación. | I31: TI | J31: 0314 | K31: Postventa | L31: =VLOOKUP(E31,[1]Diccionario!C$2:AC$150,22,0) -> 970233948 | M31: =VLOOKUP(E31,[1]Diccionario!C$2:AC$150,24,0) -> 45306 | N31: =VLOOKUP(E31,[1]Diccionario!C$2:AC$150,25,0) -> 45412 | O31: =VLOOKUP(E31,[1]Diccionario!C$2:AC$150,26,0) -> 3.5 | P31: =Q31-O31 -> 0.5 | Q31: 4 | R31: 4 | S31: 1 | T31: 0.6 | U31: =U30+TablaIndicador[[#This Row],[Costo Mensual]] -> 0 | W31: =IFERROR(T31*L31,0) -> 5.8214037e+08 | X31: =S31*L31 -> 970233948 | Y31: =IFERROR(W31-U31,0) -> 5.8214037e+08 | Z31: =W31-X31 -> -3.8809358e+08 | AA31: =IFERROR(W31/U31,"No se realizó gasto en este corte") -> No se realizó gasto en este corte | AB31: =IFERROR( IF(OR(AA31="",AA31=0), "No calculado", IF(AA31>1,"Costo eficiente: se está gastando menos de lo presupuestado", IF(AA31=1,"Costo según lo presupuestado", "Costo ineficiente: se está gastando más de lo presupuestado"))), "No calculado") -> Costo eficiente: se está gastando menos de lo presupuestado | AC31: =IFERROR(W31/X31,0) -> 0.6 | AD31: =IF(OR(AC31="",AC31=0),"Sin Línea Base", IF(AC31>1,"Proyecto adelantado respecto al cronograma", IF(AC31=1,"Proyecto a tiempo según lo planificado", IF(AC31<1,"Proyecto atrasado con respecto al cronograma", "No calculado")))) -> Proyecto atrasado con respecto al cronograma | AE31: =IFERROR(L31/AA31,0) -> 0 | AF31: =IFERROR(AE31-L31,0) -> -970233948 | AG31: =VLOOKUP(Indicador!E54,[1]Diccionario!C$1:AC$150,27,0) -> https://growdatasas.sharepoint.com/:x:/r/sites/Gestiondocumental/Administrativa/GD/Financiera/_layouts/15/Doc.aspx?sourcedoc=%7B06FB1484-E2DE-40DA-83E0-D97F6AF0AE9B%7D&file=MODELO%20FINANCIERO%20REFERENCIA%20V7%20MS%2020240130.xlsx&action=default&mobileredirect=true | AH31: 1 | AI31: 1 | AK31: Revisar este se ejecuto 2024
A32: 2024 | B32: Mayo | C32: becfcaa1-85b4-ee11-871a-00155d105d1e | D32: 45307.653 | E32: TELEFONICA – DPC SALA DE ANALITICA | F32: Guiovanni Andres Serrano Serna | G32: https://growdatasas.sharepoint.com/sites/pwa/TELEFONICA – DPC SALA DE ANALITICA | H32: ​Adecuación de la sala de analítica en dos fases, fase 1 obra civil y remodelación. | I32: TI | J32: 0314 | K32: Postventa | L32: =VLOOKUP(E32,[1]Diccionario!C$2:AC$150,22,0) -> 970233948 | M32: =VLOOKUP(E32,[1]Diccionario!C$2:AC$150,24,0) -> 45306 | N32: =VLOOKUP(E32,[1]Diccionario!C$2:AC$150,25,0) -> 45412 | O32: =VLOOKUP(E32,[1]Diccionario!C$2:AC$150,26,0) -> 3.5 | P32: =Q32-O32 -> 1.5 | Q32: 5 | R32: 4 | S32: 1 | T32: 0.8 | U32: =U31+TablaIndicador[[#This Row],[Costo Mensual]] -> 0 | W32: =IFERROR(T32*L32,0) -> 7.7618716e+08 | X32: =S32*L32 -> 970233948 | Y32: =IFERROR(W32-U32,0) -> 7.7618716e+08 | Z32: =W32-X32 -> -1.9404679e+08 | AA32: =IFERROR(W32/U32,"No se realizó gasto en este corte") -> No se realizó gasto en este corte | AB32: =IFERROR( IF(OR(AA32="",AA32=0), "No calculado", IF(AA32>1,"Costo eficiente: se está gastando menos de lo presupuestado", IF(AA32=1,"Costo según lo presupuestado", "Costo ineficiente: se está gastando más de lo presupuestado"))), "No calculado") -> Costo eficiente: se está gastando menos de lo presupuestado | AC32: =IFERROR(W32/X32,0) -> 0.8 | AD32: =IF(OR(AC32="",AC32=0),"Sin Línea Base", IF(AC32>1,"Proyecto adelantado respecto al cronograma", IF(AC32=1,"Proyecto a tiempo según lo planificado", IF(AC32<1,"Proyecto atrasado con respecto al cronograma", "No calculado")))) -> Proyecto atrasado con respecto al cronograma | AE32: =IFERROR(L32/AA32,0) -> 0 | AF32: =IFERROR(AE32-L32,0) -> -970233948 | AG32: =VLOOKUP(Indicador!E55,[1]Diccionario!C$1:AC$150,27,0) -> https://growdatasas.sharepoint.com/:x:/r/sites/Gestiondocumental/Administrativa/GD/Financiera/_layouts/15/Doc.aspx?sourcedoc=%7B06FB1484-E2DE-40DA-83E0-D97F6AF0AE9B%7D&file=MODELO%20FINANCIERO%20REFERENCIA%20V7%20MS%2020240130.xlsx&action=default&mobileredirect=true | AH32: 1 | AI32: 1 | AK32: Revisar este se ejecuto 2024
A33: 2024 | B33: Junio | C33: becfcaa1-85b4-ee11-871a-00155d105d1e | D33: 45307.653 | E33: TELEFONICA – DPC SALA DE ANALITICA | F33: Guiovanni Andres Serrano Serna | G33: https://growdatasas.sharepoint.com/sites/pwa/TELEFONICA – DPC SALA DE ANALITICA | H33: ​Adecuación de la sala de analítica en dos fases, fase 1 obra civil y remodelación. | I33: TI | J33: 0314 | K33: Postventa | L33: =VLOOKUP(E33,[1]Diccionario!C$2:AC$150,22,0) -> 970233948 | M33: =VLOOKUP(E33,[1]Diccionario!C$2:AC$150,24,0) -> 45306 | N33: =VLOOKUP(E33,[1]Diccionario!C$2:AC$150,25,0) -> 45412 | O33: =VLOOKUP(E33,[1]Diccionario!C$2:AC$150,26,0) -> 3.5 | P33: =Q33-O33 -> 2.5 | Q33: 6 | R33: 4 | S33: 1 | T33: 1 | U33: =U32+TablaIndicador[[#This Row],[Costo Mensual]] -> 0 | W33: =IFERROR(T33*L33,0) -> 970233948 | X33: =S33*L33 -> 970233948 | Y33: =IFERROR(W33-U33,0) -> 970233948 | Z33: =W33-X33 -> 0 | AA33: =IFERROR(W33/U33,"No se realizó gasto en este corte") -> No se realizó gasto en este corte | AB33: =IFERROR( IF(OR(AA33="",AA33=0), "No calculado", IF(AA33>1,"Costo eficiente: se está gastando menos de lo presupuestado", IF(AA33=1,"Costo según lo presupuestado", "Costo ineficiente: se está gastando más de lo presupuestado"))), "No calculado") -> Costo eficiente: se está gastando menos de lo presupuestado | AC33: =IFERROR(W33/X33,0) -> 1 | AD33: =IF(OR(AC33="",AC33=0),"Sin Línea Base", IF(AC33>1,"Proyecto adelantado respecto al cronograma", IF(AC33=1,"Proyecto a tiempo según lo planificado", IF(AC33<1,"Proyecto atrasado con respecto al cronograma", "No calculado")))) -> Proyecto a tiempo según lo planificado | AE33: =IFERROR(L33/AA33,0) -> 0 | AF33: =IFERROR(AE33-L33,0) -> -970233948 | AG33: =VLOOKUP(Indicador!E56,[1]Diccionario!C$1:AC$150,27,0) -> https://growdatasas.sharepoint.com/:x:/r/sites/Gestiondocumental/Administrativa/GD/Financiera/_layouts/15/Doc.aspx?sourcedoc=%7B29DCF375-0847-4DAD-9B9A-9F9E84ABD4DE%7D&file=322.%20MINTRANSPORTE.xlsx&action=default&mobileredirect=true | AH33: 1 | AI33: 1 | AK33: Revisar este se ejecuto 2024
A34: 2024 | B34: Enero | C34: 93afa0f2-87b4-ee11-b12b-00155d10d37b | D34: 45307.665 | E34: INFOTIC-DPC-SOC | F34: Janeth Annelise Araujo Ramos | G34: https://growdatasas.sharepoint.com/sites/pwa/INFOTIC-DPC-SOC | H34: ​Implementación y puesta en operación del Centro de Operaciones de Seguridad (SOC). | I34: TI | J34: 0320 | K34: Cerrado | L34: =VLOOKUP(E34,[1]Diccionario!C$2:AC$150,22,0) -> 5280083724 | M34: =VLOOKUP(E34,[1]Diccionario!C$2:AC$150,24,0) -> 45300 | N34: =VLOOKUP(E34,[1]Diccionario!C$2:AC$150,25,0) -> 45473 | O34: =VLOOKUP(E34,[1]Diccionario!C$2:AC$150,26,0) -> 5.7 | P34: =Q34-O34 -> -4.7 | Q34: 1 | R34: 6 | S34: 0.2 | T34: 0.25 | U34: =TablaIndicador[[#This Row],[Costo Mensual]] -> 0 | W34: =IFERROR(T34*L34,0) -> 1320020931 | X34: =S34*L34 -> 1.0560167e+09 | Y34: =IFERROR(W34-U34,0) -> 1320020931 | Z34: =W34-X34 -> 2.6400419e+08 | AA34: =IFERROR(W34/U34,"No se realizó gasto en este corte") -> No se realizó gasto en este corte | AB34: =IFERROR( IF(OR(AA34="",AA34=0), "No calculado", IF(AA34>1,"Costo eficiente: se está gastando menos de lo presupuestado", IF(AA34=1,"Costo según lo presupuestado", "Costo ineficiente: se está gastando más de lo presupuestado"))), "No calculado") -> Costo eficiente: se está gastando menos de lo presupuestado | AC34: =IFERROR(W34/X34,0) -> 1.25 | AD34: =IF(OR(AC34="",AC34=0),"Sin Línea Base", IF(AC34>1,"Proyecto adelantado respecto al cronograma", IF(AC34=1,"Proyecto a tiempo según lo planificado", IF(AC34<1,"Proyecto atrasado con respecto al cronograma", "No calculado")))) -> Proyecto adelantado respecto al cronograma | AE34: =IFERROR(L34/AA34,0) -> 0 | AF34: =IFERROR(AE34-L34,0) -> -5280083724 | AG34: =VLOOKUP(Indicador!E17,[1]Diccionario!C$1:AC$150,27,0) -> https://growdatasas.sharepoint.com/:x:/r/sites/Gestiondocumental/Administrativa/GD/Financiera/_layouts/15/Doc.aspx?sourcedoc=%7BC3EFE0E2-C211-45B0-905D-ECEF11221767%7D&file=299.%20DEFENSORIA_ERP.xlsm&action=default&mobileredirect=true | AH34: 1 | AI34: 1 | AJ34: ok
A35: 2024 | B35: Febrero | C35: 93afa0f2-87b4-ee11-b12b-00155d10d37b | D35: 45307.665 | E35: INFOTIC-DPC-SOC | F35: Janeth Annelise Araujo Ramos | G35: https://growdatasas.sharepoint.com/sites/pwa/INFOTIC-DPC-SOC | H35: ​Implementación y puesta en operación del Centro de Operaciones de Seguridad (SOC). | I35: TI | J35: 0320 | K35: Cerrado | L35: =VLOOKUP(E35,[1]Diccionario!C$2:AC$150,22,0) -> 5280083724 | M35: =VLOOKUP(E35,[1]Diccionario!C$2:AC$150,24,0) -> 45300 | N35: =VLOOKUP(E35,[1]Diccionario!C$2:AC$150,25,0) -> 45473 | O35: =VLOOKUP(E35,[1]Diccionario!C$2:AC$150,26,0) -> 5.7 | P35: =Q35-O35 -> -3.7 | Q35: 2 | R35: 6 | S35: 0.45 | T35: 0.35 | U35: =U34+TablaIndicador[[#This Row],[Costo Mensual]] -> 0 | W35: =IFERROR(T35*L35,0) -> 1.8480293e+09 | X35: =S35*L35 -> 2.3760377e+09 | Y35: =IFERROR(W35-U35,0) -> 1.8480293e+09 | Z35: =W35-X35 -> -5.2800837e+08 | AA35: =IFERROR(W35/U35,"No se realizó gasto en este corte") -> No se realizó gasto en este corte | AB35: =IFERROR( IF(OR(AA35="",AA35=0), "No calculado", IF(AA35>1,"Costo eficiente: se está gastando menos de lo presupuestado", IF(AA35=1,"Costo según lo presupuestado", "Costo ineficiente: se está gastando más de lo presupuestado"))), "No calculado") -> Costo eficiente: se está gastando menos de lo presupuestado | AC35: =IFERROR(W35/X35,0) -> 0.77777778 | AD35: =IF(OR(AC35="",AC35=0),"Sin Línea Base", IF(AC35>1,"Proyecto adelantado respecto al cronograma", IF(AC35=1,"Proyecto a tiempo según lo planificado", IF(AC35<1,"Proyecto atrasado con respecto al cronograma", "No calculado")))) -> Proyecto atrasado con respecto al cronograma | AE35: =IFERROR(L35/AA35,0) -> 0 | AF35: =IFERROR(AE35-L35,0) -> -5280083724 | AG35: =VLOOKUP(Indicador!E18,[1]Diccionario!C$1:AC$150,27,0) -> https://growdatasas.sharepoint.com/:x:/r/sites/Gestiondocumental/Administrativa/GD/Financiera/_layouts/15/Doc.aspx?sourcedoc=%7BC3EFE0E2-C211-45B0-905D-ECEF11221767%7D&file=299.%20DEFENSORIA_ERP.xlsm&action=default&mobileredirect=true | AH35: 1 | AI35: 1 | AJ35: ok
A36: 2024 | B36: Marzo | C36: 93afa0f2-87b4-ee11-b12b-00155d10d37b | D36: 45307.665 | E36: INFOTIC-DPC-SOC | F36: Janeth Annelise Araujo Ramos | G36: https://growdatasas.sharepoint.com/sites/pwa/INFOTIC-DPC-SOC | H36: ​Implementación y puesta en operación del Centro de Operaciones de Seguridad (SOC). | I36: TI | J36: 0320 | K36: Cerrado | L36: =VLOOKUP(E36,[1]Diccionario!C$2:AC$150,22,0) -> 5280083724 | M36: =VLOOKUP(E36,[1]Diccionario!C$2:AC$150,24,0) -> 45300 | N36: =VLOOKUP(E36,[1]Diccionario!C$2:AC$150,25,0) -> 45473 | O36: =VLOOKUP(E36,[1]Diccionario!C$2:AC$150,26,0) -> 5.7 | P36: =Q36-O36 -> -2.7 | Q36: 3 | R36: 6 | S36: 0.6 | T36: 0.38 | U36: =U35+TablaIndicador[[#This Row],[Costo Mensual]] -> 0 | W36: =IFERROR(T36*L36,0) -> 2.0064318e+09 | X36: =S36*L36 -> 3.1680502e+09 | Y36: =IFERROR(W36-U36,0) -> 2.0064318e+09 | Z36: =W36-X36 -> -1.1616184e+09 | AA36: =IFERROR(W36/U36,"No se realizó gasto en este corte") -> No se realizó gasto en este corte | AB36: =IFERROR( IF(OR(AA36="",AA36=0), "No calculado", IF(AA36>1,"Costo eficiente: se está gastando menos de lo presupuestado", IF(AA36=1,"Costo según lo presupuestado", "Costo ineficiente: se está gastando más de lo presupuestado"))), "No calculado") -> Costo eficiente: se está gastando menos de lo presupuestado | AC36: =IFERROR(W36/X36,0) -> 0.63333333 | AD36: =IF(OR(AC36="",AC36=0),"Sin Línea Base", IF(AC36>1,"Proyecto adelantado respecto al cronograma", IF(AC36=1,"Proyecto a tiempo según lo planificado", IF(AC36<1,"Proyecto atrasado con respecto al cronograma", "No calculado")))) -> Proyecto atrasado con respecto al cronograma | AE36: =IFERROR(L36/AA36,0) -> 0 | AF36: =IFERROR(AE36-L36,0) -> -5280083724 | AG36: =VLOOKUP(Indicador!E19,[1]Diccionario!C$1:AC$150,27,0) -> https://growdatasas.sharepoint.com/:x:/r/sites/Gestiondocumental/Administrativa/GD/Financiera/_layouts/15/Doc.aspx?sourcedoc=%7BC3EFE0E2-C211-45B0-905D-ECEF11221767%7D&file=299.%20DEFENSORIA_ERP.xlsm&action=default&mobileredirect=true | AH36: 1 | AI36: 1 | AJ36: ok
A37: 2024 | B37: Abril | C37: 93afa0f2-87b4-ee11-b12b-00155d10d37b | D37: 45307.665 | E37: INFOTIC-DPC-SOC | F37: Janeth Annelise Araujo Ramos | G37: https://growdatasas.sharepoint.com/sites/pwa/INFOTIC-DPC-SOC | H37: ​Implementación y puesta en operación del Centro de Operaciones de Seguridad (SOC). | I37: TI | J37: 0320 | K37: Cerrado | L37: =VLOOKUP(E37,[1]Diccionario!C$2:AC$150,22,0) -> 5280083724 | M37: =VLOOKUP(E37,[1]Diccionario!C$2:AC$150,24,0) -> 45300 | N37: =VLOOKUP(E37,[1]Diccionario!C$2:AC$150,25,0) -> 45473 | O37: =VLOOKUP(E37,[1]Diccionario!C$2:AC$150,26,0) -> 5.7 | P37: =Q37-O37 -> -1.7 | Q37: 4 | R37: 6 | S37: 0.75 | T37: 0.49 | U37: =U36+TablaIndicador[[#This Row],[Costo Mensual]] -> 0 | W37: =IFERROR(T37*L37,0) -> 2.587241e+09 | X37: =S37*L37 -> 3960062793 | Y37: =IFERROR(W37-U37,0) -> 2.587241e+09 | Z37: =W37-X37 -> -1.3728218e+09 | AA37: =IFERROR(W37/U37,"No se realizó gasto en este corte") -> No se realizó gasto en este corte | AB37: =IFERROR( IF(OR(AA37="",AA37=0), "No calculado", IF(AA37>1,"Costo eficiente: se está gastando menos de lo presupuestado", IF(AA37=1,"Costo según lo presupuestado", "Costo ineficiente: se está gastando más de lo presupuestado"))), "No calculado") -> Costo eficiente: se está gastando menos de lo presupuestado | AC37: =IFERROR(W37/X37,0) -> 0.65333333 | AD37: =IF(OR(AC37="",AC37=0),"Sin Línea Base", IF(AC37>1,"Proyecto adelantado respecto al cronograma", IF(AC37=1,"Proyecto a tiempo según lo planificado", IF(AC37<1,"Proyecto atrasado con respecto al cronograma", "No calculado")))) -> Proyecto atrasado con respecto al cronograma | AE37: =IFERROR(L37/AA37,0) -> 0 | AF37: =IFERROR(AE37-L37,0) -> -5280083724 | AG37: =VLOOKUP(Indicador!E20,[1]Diccionario!C$1:AC$150,27,0) -> https://growdatasas.sharepoint.com/:x:/r/sites/Gestiondocumental/Administrativa/GD/Financiera/_layouts/15/Doc.aspx?sourcedoc=%7BC3EFE0E2-C211-45B0-905D-ECEF11221767%7D&file=299.%20DEFENSORIA_ERP.xlsm&action=default&mobileredirect=true | AH37: 1 | AI37: 1 | AJ37: ok
A38: 2024 | B38: Mayo | C38: 93afa0f2-87b4-ee11-b12b-00155d10d37b | D38: 45307.665 | E38: INFOTIC-DPC-SOC | F38: Janeth Annelise Araujo Ramos | G38: https://growdatasas.sharepoint.com/sites/pwa/INFOTIC-DPC-SOC | H38: ​Implementación y puesta en operación del Centro de Operaciones de Seguridad (SOC). | I38: TI | J38: 0320 | K38: Cerrado | L38: =VLOOKUP(E38,[1]Diccionario!C$2:AC$150,22,0) -> 5280083724 | M38: =VLOOKUP(E38,[1]Diccionario!C$2:AC$150,24,0) -> 45300 | N38: =VLOOKUP(E38,[1]Diccionario!C$2:AC$150,25,0) -> 45473 | O38: =VLOOKUP(E38,[1]Diccionario!C$2:AC$150,26,0) -> 5.7 | P38: =Q38-O38 -> -0.7 | Q38: 5 | R38: 6 | S38: 0.8 | T38: 0.6 | U38: =U37+TablaIndicador[[#This Row],[Costo Mensual]] -> 0 | W38: =IFERROR(T38*L38,0) -> 3.1680502e+09 | X38: =S38*L38 -> 4.224067e+09 | Y38: =IFERROR(W38-U38,0) -> 3.1680502e+09 | Z38: =W38-X38 -> -1.0560167e+09 | AA38: =IFERROR(W38/U38,"No se realizó gasto en este corte") -> No se realizó gasto en este corte | AB38: =IFERROR( IF(OR(AA38="",AA38=0), "No calculado", IF(AA38>1,"Costo eficiente: se está gastando menos de lo presupuestado", IF(AA38=1,"Costo según lo presupuestado", "Costo ineficiente: se está gastando más de lo presupuestado"))), "No calculado") -> Costo eficiente: se está gastando menos de lo presupuestado | AC38: =IFERROR(W38/X38,0) -> 0.75 | AD38: =IF(OR(AC38="",AC38=0),"Sin Línea Base", IF(AC38>1,"Proyecto adelantado respecto al cronograma", IF(AC38=1,"Proyecto a tiempo según lo planificado", IF(AC38<1,"Proyecto atrasado con respecto al cronograma", "No calculado")))) -> Proyecto atrasado con respecto al cronograma | AE38: =IFERROR(L38/AA38,0) -> 0 | AF38: =IFERROR(AE38-L38,0) -> -5280083724 | AG38: =VLOOKUP(Indicador!E21,[1]Diccionario!C$1:AC$150,27,0) -> https://growdatasas.sharepoint.com/:x:/r/sites/Gestiondocumental/Administrativa/GD/Financiera/_layouts/15/Doc.aspx?sourcedoc=%7BC3EFE0E2-C211-45B0-905D-ECEF11221767%7D&file=299.%20DEFENSORIA_ERP.xlsm&action=default&mobileredirect=true | AH38: 1 | AI38: 1 | AJ38: ok
A39: 2024 | B39: Junio | C39: 93afa0f2-87b4-ee11-b12b-00155d10d37b | D39: 45307.665 | E39: INFOTIC-DPC-SOC | F39: Janeth Annelise Araujo Ramos | G39: https://growdatasas.sharepoint.com/sites/pwa/INFOTIC-DPC-SOC | H39: ​Implementación y puesta en operación del Centro de Operaciones de Seguridad (SOC). | I39: TI | J39: 0320 | K39: Cerrado | L39: =VLOOKUP(E39,[1]Diccionario!C$2:AC$150,22,0) -> 5280083724 | M39: =VLOOKUP(E39,[1]Diccionario!C$2:AC$150,24,0) -> 45300 | N39: =VLOOKUP(E39,[1]Diccionario!C$2:AC$150,25,0) -> 45473 | O39: =VLOOKUP(E39,[1]Diccionario!C$2:AC$150,26,0) -> 5.7 | P39: =Q39-O39 -> 0.3 | Q39: 6 | R39: 6 | S39: 1 | T39: 0.78 | U39: =U38+TablaIndicador[[#This Row],[Costo Mensual]] -> 0 | W39: =IFERROR(T39*L39,0) -> 4.1184653e+09 | X39: =S39*L39 -> 5280083724 | Y39: =IFERROR(W39-U39,0) -> 4.1184653e+09 | Z39: =W39-X39 -> -1.1616184e+09 | AA39: =IFERROR(W39/U39,"No se realizó gasto en este corte") -> No se realizó gasto en este corte | AB39: =IFERROR( IF(OR(AA39="",AA39=0), "No calculado", IF(AA39>1,"Costo eficiente: se está gastando menos de lo presupuestado", IF(AA39=1,"Costo según lo presupuestado", "Costo ineficiente: se está gastando más de lo presupuestado"))), "No calculado") -> Costo eficiente: se está gastando menos de lo presupuestado | AC39: =IFERROR(W39/X39,0) -> 0.78 | AD39: =IF(OR(AC39="",AC39=0),"Sin Línea Base", IF(AC39>1,"Proyecto adelantado respecto al cronograma", IF(AC39=1,"Proyecto a tiempo según lo planificado", IF(AC39<1,"Proyecto atrasado con respecto al cronograma", "No calculado")))) -> Proyecto atrasado con respecto al cronograma | AE39: =IFERROR(L39/AA39,0) -> 0 | AF39: =IFERROR(AE39-L39,0) -> -5280083724 | AG39: =VLOOKUP(Indicador!E22,[1]Diccionario!C$1:AC$150,27,0) -> https://growdatasas.sharepoint.com/:x:/r/sites/Gestiondocumental/Administrativa/GD/Financiera/_layouts/15/Doc.aspx?sourcedoc=%7BC3EFE0E2-C211-45B0-905D-ECEF11221767%7D&file=299.%20DEFENSORIA_ERP.xlsm&action=default&mobileredirect=true | AH39: 1 | AI39: 1 | AJ39: ok
A40: 2024 | B40: Julio | C40: 93afa0f2-87b4-ee11-b12b-00155d10d37b | D40: 45307.665 | E40: INFOTIC-DPC-SOC | F40: Janeth Annelise Araujo Ramos | G40: https://growdatasas.sharepoint.com/sites/pwa/INFOTIC-DPC-SOC | H40: ​Implementación y puesta en operación del Centro de Operaciones de Seguridad (SOC). | I40: TI | J40: 0320 | K40: Cerrado | L40: =VLOOKUP(E40,[1]Diccionario!C$2:AC$150,22,0) -> 5280083724 | M40: =VLOOKUP(E40,[1]Diccionario!C$2:AC$150,24,0) -> 45300 | N40: =VLOOKUP(E40,[1]Diccionario!C$2:AC$150,25,0) -> 45473 | O40: =VLOOKUP(E40,[1]Diccionario!C$2:AC$150,26,0) -> 5.7 | P40: =Q40-O40 -> 1.3 | Q40: 7 | R40: 6 | S40: 1 | T40: 0.9 | U40: =U39+TablaIndicador[[#This Row],[Costo Mensual]] -> 0 | W40: =IFERROR(T40*L40,0) -> 4.7520754e+09 | X40: =S40*L40 -> 5280083724 | Y40: =IFERROR(W40-U40,0) -> 4.7520754e+09 | Z40: =W40-X40 -> -5.2800837e+08 | AA40: =IFERROR(W40/U40,"No se realizó gasto en este corte") -> No se realizó gasto en este corte | AB40: =IFERROR( IF(OR(AA40="",AA40=0), "No calculado", IF(AA40>1,"Costo eficiente: se está gastando menos de lo presupuestado", IF(AA40=1,"Costo según lo presupuestado", "Costo ineficiente: se está gastando más de lo presupuestado"))), "No calculado") -> Costo eficiente: se está gastando menos de lo presupuestado | AC40: =IFERROR(W40/X40,0) -> 0.9 | AD40: =IF(OR(AC40="",AC40=0),"Sin Línea Base", IF(AC40>1,"Proyecto adelantado respecto al cronograma", IF(AC40=1,"Proyecto a tiempo según lo planificado", IF(AC40<1,"Proyecto atrasado con respecto al cronograma", "No calculado")))) -> Proyecto atrasado con respecto al cronograma | AE40: =IFERROR(L40/AA40,0) -> 0 | AF40: =IFERROR(AE40-L40,0) -> -5280083724 | AG40: =VLOOKUP(Indicador!E23,[1]Diccionario!C$1:AC$150,27,0) -> https://growdatasas.sharepoint.com/:x:/r/sites/Gestiondocumental/Administrativa/GD/Financiera/_layouts/15/Doc.aspx?sourcedoc=%7BC3EFE0E2-C211-45B0-905D-ECEF11221767%7D&file=299.%20DEFENSORIA_ERP.xlsm&action=default&mobileredirect=true | AH40: 1 | AI40: 1 | AJ40: ok
A41: 2024 | B41: Agosto | C41: 93afa0f2-87b4-ee11-b12b-00155d10d37b | D41: 45307.665 | E41: INFOTIC-DPC-SOC | F41: Janeth Annelise Araujo Ramos | G41: https://growdatasas.sharepoint.com/sites/pwa/INFOTIC-DPC-SOC | H41: ​Implementación y puesta en operación del Centro de Operaciones de Seguridad (SOC). | I41: TI | J41: 0320 | K41: Cerrado | L41: =VLOOKUP(E41,[1]Diccionario!C$2:AC$150,22,0) -> 5280083724 | M41: =VLOOKUP(E41,[1]Diccionario!C$2:AC$150,24,0) -> 45300 | N41: =VLOOKUP(E41,[1]Diccionario!C$2:AC$150,25,0) -> 45473 | O41: =VLOOKUP(E41,[1]Diccionario!C$2:AC$150,26,0) -> 5.7 | P41: =Q41-O41 -> 2.3 | Q41: 8 | R41: 6 | S41: 1 | T41: 1 | U41: =U40+TablaIndicador[[#This Row],[Costo Mensual]] -> 0 | W41: =IFERROR(T41*L41,0) -> 5280083724 | X41: =S41*L41 -> 5280083724 | Y41: =IFERROR(W41-U41,0) -> 5280083724 | Z41: =W41-X41 -> 0 | AA41: =IFERROR(W41/U41,"No se realizó gasto en este corte") -> No se realizó gasto en este corte | AB41: =IFERROR( IF(OR(AA41="",AA41=0), "No calculado", IF(AA41>1,"Costo eficiente: se está gastando menos de lo presupuestado", IF(AA41=1,"Costo según lo presupuestado", "Costo ineficiente: se está gastando más de lo presupuestado"))), "No calculado") -> Costo eficiente: se está gastando menos de lo presupuestado | AC41: =IFERROR(W41/X41,0) -> 1 | AD41: =IF(OR(AC41="",AC41=0),"Sin Línea Base", IF(AC41>1,"Proyecto adelantado respecto al cronograma", IF(AC41=1,"Proyecto a tiempo según lo planificado", IF(AC41<1,"Proyecto atrasado con respecto al cronograma", "No calculado")))) -> Proyecto a tiempo según lo planificado | AE41: =IFERROR(L41/AA41,0) -> 0 | AF41: =IFERROR(AE41-L41,0) -> -5280083724 | AG41: =VLOOKUP(Indicador!E24,[1]Diccionario!C$1:AC$150,27,0) -> https://growdatasas.sharepoint.com/:x:/r/sites/Gestiondocumental/Administrativa/GD/Financiera/_layouts/15/Doc.aspx?sourcedoc=%7BC3EFE0E2-C211-45B0-905D-ECEF11221767%7D&file=299.%20DEFENSORIA_ERP.xlsm&action=default&mobileredirect=true | AH41: 1 | AI41: 1 | AJ41: ok
A42: 2024 | B42: Enero | C42: b3dee2f4-49c1-ee11-add8-00155d10211a | D42: 45323.9 | E42: CORP COLOMBIA DIGITAL-FNA-AE | F42: Johan Sebastian Rodriguez Niño | G42: https://growdatasas.sharepoint.com/sites/pwa/CORP COLOMBIA DIGITAL-FNA-AE | H42: Consultoría para el diseño de la Transformación Digital de la entidad que designe la Corporación Colombia Digital, basado en desarrollar la arquitectura empresarial - AR, la definición e implementación del Gobierno y la gestión de datos, la definición de la hoja de ruta de la AR para el plan estratégico de TI PETI, la formación de personal y la planeación del proyecto de la entidad designada. | I42: CONSULTORÍA | J42: 0315 | K42: Activo.En Cierre | L42: =VLOOKUP(E42,[1]Diccionario!C$2:AC$150,22,0) -> 1422409157 | M42: =VLOOKUP(E42,[1]Diccionario!C$2:AC$150,24,0) -> 45292 | N42: =VLOOKUP(E42,[1]Diccionario!C$2:AC$150,25,0) -> 45534 | O42: =VLOOKUP(E42,[1]Diccionario!C$2:AC$150,26,0) -> 7.97 | P42: =Q42-O42 -> -6.97 | Q42: 1 | R42: 8 | S42: 0.1 | T42: 0.08 | U42: =TablaIndicador[[#This Row],[Costo Mensual]] -> 0 | W42: =IFERROR(T42*L42,0) -> 1.1379273e+08 | X42: =S42*L42 -> 1.4224092e+08 | Y42: =IFERROR(W42-U42,0) -> 1.1379273e+08 | Z42: =W42-X42 -> -28448183 | AA42: =IFERROR(W42/U42,"No se realizó gasto en este corte") -> No se realizó gasto en este corte | AB42: =IFERROR( IF(OR(AA42="",AA42=0), "No calculado", IF(AA42>1,"Costo eficiente: se está gastando menos de lo presupuestado", IF(AA42=1,"Costo según lo presupuestado", "Costo ineficiente: se está gastando más de lo presupuestado"))), "No calculado") -> Costo eficiente: se está gastando menos de lo presupuestado | AC42: =IFERROR(W42/X42,0) -> 0.8 | AD42: =IF(OR(AC42="",AC42=0),"Sin Línea Base", IF(AC42>1,"Proyecto adelantado respecto al cronograma", IF(AC42=1,"Proyecto a tiempo según lo planificado", IF(AC42<1,"Proyecto atrasado con respecto al cronograma", "No calculado")))) -> Proyecto atrasado con respecto al cronograma | AE42: =IFERROR(L42/AA42,0) -> 0 | AF42: =IFERROR(AE42-L42,0) -> -1422409157 | AG42: =VLOOKUP(Indicador!E6,[1]Diccionario!C$1:AC$150,27,0) -> https://growdatasas.sharepoint.com/:x:/r/sites/Gestiondocumental/Administrativa/GD/Financiera/_layouts/15/Doc.aspx?sourcedoc=%7BC3EFE0E2-C211-45B0-905D-ECEF11221767%7D&file=299.%20DEFENSORIA_ERP.xlsm&action=default&mobileredirect=true | AH42: 1 | AI42: 1 | AJ42: ok
A43: 2024 | B43: Febrero | C43: b3dee2f4-49c1-ee11-add8-00155d10211a | D43: 45323.9 | E43: CORP COLOMBIA DIGITAL-FNA-AE | F43: Johan Sebastian Rodriguez Niño | G43: https://growdatasas.sharepoint.com/sites/pwa/CORP COLOMBIA DIGITAL-FNA-AE | H43: Consultoría para el diseño de la Transformación Digital de la entidad que designe la Corporación Colombia Digital, basado en desarrollar la arquitectura empresarial - AR, la definición e implementación del Gobierno y la gestión de datos, la definición de la hoja de ruta de la AR para el plan estratégico de TI PETI, la formación de personal y la planeación del proyecto de la entidad designada. | I43: CONSULTORÍA | J43: 0315 | K43: Activo.En Cierre | L43: =VLOOKUP(E43,[1]Diccionario!C$2:AC$150,22,0) -> 1422409157 | M43: =VLOOKUP(E43,[1]Diccionario!C$2:AC$150,24,0) -> 45292 | N43: =VLOOKUP(E43,[1]Diccionario!C$2:AC$150,25,0) -> 45534 | O43: =VLOOKUP(E43,[1]Diccionario!C$2:AC$150,26,0) -> 7.97 | P43: =Q43-O43 -> -5.97 | Q43: 2 | R43: 8 | S43: 0.2 | T43: 0.18 | U43: =U42+TablaIndicador[[#This Row],[Costo Mensual]] -> 0 | W43: =IFERROR(T43*L43,0) -> 2.5603365e+08 | X43: =S43*L43 -> 2.8448183e+08 | Y43: =IFERROR(W43-U43,0) -> 2.5603365e+08 | Z43: =W43-X43 -> -28448183 | AA43: =IFERROR(W43/U43,"No se realizó gasto en este corte") -> No se realizó gasto en este corte | AB43: =IFERROR( IF(OR(AA43="",AA43=0), "No calculado", IF(AA43>1,"Costo eficiente: se está gastando menos de lo presupuestado", IF(AA43=1,"Costo según lo presupuestado", "Costo ineficiente: se está gastando más de lo presupuestado"))), "No calculado") -> Costo eficiente: se está gastando menos de lo presupuestado | AC43: =IFERROR(W43/X43,0) -> 0.9 | AD43: =IF(OR(AC43="",AC43=0),"Sin Línea Base", IF(AC43>1,"Proyecto adelantado respecto al cronograma", IF(AC43=1,"Proyecto a tiempo según lo planificado", IF(AC43<1,"Proyecto atrasado con respecto al cronograma", "No calculado")))) -> Proyecto atrasado con respecto al cronograma | AE43: =IFERROR(L43/AA43,0) -> 0 | AF43: =IFERROR(AE43-L43,0) -> -1422409157 | AG43: =VLOOKUP(Indicador!E7,[1]Diccionario!C$1:AC$150,27,0) -> https://growdatasas.sharepoint.com/:x:/r/sites/Gestiondocumental/Administrativa/GD/Financiera/_layouts/15/Doc.aspx?sourcedoc=%7BC3EFE0E2-C211-45B0-905D-ECEF11221767%7D&file=299.%20DEFENSORIA_ERP.xlsm&action=default&mobileredirect=true | AH43: 1 | AI43: 1 | AJ43: ok
A44: 2024 | B44: Marzo | C44: b3dee2f4-49c1-ee11-add8-00155d10211a | D44: 45323.9 | E44: CORP COLOMBIA DIGITAL-FNA-AE | F44: Johan Sebastian Rodriguez Niño | G44: https://growdatasas.sharepoint.com/sites/pwa/CORP COLOMBIA DIGITAL-FNA-AE | H44: Consultoría para el diseño de la Transformación Digital de la entidad que designe la Corporación Colombia Digital, basado en desarrollar la arquitectura empresarial - AR, la definición e implementación del Gobierno y la gestión de datos, la definición de la hoja de ruta de la AR para el plan estratégico de TI PETI, la formación de personal y la planeación del proyecto de la entidad designada. | I44: CONSULTORÍA | J44: 0315 | K44: Activo.En Cierre | L44: =VLOOKUP(E44,[1]Diccionario!C$2:AC$150,22,0) -> 1422409157 | M44: =VLOOKUP(E44,[1]Diccionario!C$2:AC$150,24,0) -> 45292 | N44: =VLOOKUP(E44,[1]Diccionario!C$2:AC$150,25,0) -> 45534 | O44: =VLOOKUP(E44,[1]Diccionario!C$2:AC$150,26,0) -> 7.97 | P44: =Q44-O44 -> -4.97 | Q44: 3 | R44: 8 | S44: 0.3 | T44: 0.32 | U44: =U43+TablaIndicador[[#This Row],[Costo Mensual]] -> 0 | W44: =IFERROR(T44*L44,0) -> 4.5517093e+08 | X44: =S44*L44 -> 4.2672275e+08 | Y44: =IFERROR(W44-U44,0) -> 4.5517093e+08 | Z44: =W44-X44 -> 28448183 | AA44: =IFERROR(W44/U44,"No se realizó gasto en este corte") -> No se realizó gasto en este corte | AB44: =IFERROR( IF(OR(AA44="",AA44=0), "No calculado", IF(AA44>1,"Costo eficiente: se está gastando menos de lo presupuestado", IF(AA44=1,"Costo según lo presupuestado", "Costo ineficiente: se está gastando más de lo presupuestado"))), "No calculado") -> Costo eficiente: se está gastando menos de lo presupuestado | AC44: =IFERROR(W44/X44,0) -> 1.0666667 | AD44: =IF(OR(AC44="",AC44=0),"Sin Línea Base", IF(AC44>1,"Proyecto adelantado respecto al cronograma", IF(AC44=1,"Proyecto a tiempo según lo planificado", IF(AC44<1,"Proyecto atrasado con respecto al cronograma", "No calculado")))) -> Proyecto adelantado respecto al cronograma | AE44: =IFERROR(L44/AA44,0) -> 0 | AF44: =IFERROR(AE44-L44,0) -> -1422409157 | AG44: =VLOOKUP(Indicador!E8,[1]Diccionario!C$1:AC$150,27,0) -> https://growdatasas.sharepoint.com/:x:/r/sites/Gestiondocumental/Administrativa/GD/Financiera/_layouts/15/Doc.aspx?sourcedoc=%7BC3EFE0E2-C211-45B0-905D-ECEF11221767%7D&file=299.%20DEFENSORIA_ERP.xlsm&action=default&mobileredirect=true | AH44: 1 | AI44: 1 | AJ44: ok
A45: 2024 | B45: Abril | C45: b3dee2f4-49c1-ee11-add8-00155d10211a | D45: 45323.9 | E45: CORP COLOMBIA DIGITAL-FNA-AE | F45: Johan Sebastian Rodriguez Niño | G45: https://growdatasas.sharepoint.com/sites/pwa/CORP COLOMBIA DIGITAL-FNA-AE | H45: Consultoría para el diseño de la Transformación Digital de la entidad que designe la Corporación Colombia Digital, basado en desarrollar la arquitectura empresarial - AR, la definición e implementación del Gobierno y la gestión de datos, la definición de la hoja de ruta de la AR para el plan estratégico de TI PETI, la formación de personal y la planeación del proyecto de la entidad designada. | I45: CONSULTORÍA | J45: 0315 | K45: Activo.En Cierre | L45: =VLOOKUP(E45,[1]Diccionario!C$2:AC$150,22,0) -> 1422409157 | M45: =VLOOKUP(E45,[1]Diccionario!C$2:AC$150,24,0) -> 45292 | N45: =VLOOKUP(E45,[1]Diccionario!C$2:AC$150,25,0) -> 45534 | O45: =VLOOKUP(E45,[1]Diccionario!C$2:AC$150,26,0) -> 7.97 | P45: =Q45-O45 -> -3.97 | Q45: 4 | R45: 8 | S45: 0.5 | T45: 0.51 | U45: =U44+TablaIndicador[[#This Row],[Costo Mensual]] -> 0 | W45: =IFERROR(T45*L45,0) -> 7.2542867e+08 | X45: =S45*L45 -> 7.1120458e+08 | Y45: =IFERROR(W45-U45,0) -> 7.2542867e+08 | Z45: =W45-X45 -> 14224092 | AA45: =IFERROR(W45/U45,"No se realizó gasto en este corte") -> No se realizó gasto en este corte | AB45: =IFERROR( IF(OR(AA45="",AA45=0), "No calculado", IF(AA45>1,"Costo eficiente: se está gastando menos de lo presupuestado", IF(AA45=1,"Costo según lo presupuestado", "Costo ineficiente: se está gastando más de lo presupuestado"))), "No calculado") -> Costo eficiente: se está gastando menos de lo presupuestado | AC45: =IFERROR(W45/X45,0) -> 1.02 | AD45: =IF(OR(AC45="",AC45=0),"Sin Línea Base", IF(AC45>1,"Proyecto adelantado respecto al cronograma", IF(AC45=1,"Proyecto a tiempo según lo planificado", IF(AC45<1,"Proyecto atrasado con respecto al cronograma", "No calculado")))) -> Proyecto adelantado respecto al cronograma | AE45: =IFERROR(L45/AA45,0) -> 0 | AF45: =IFERROR(AE45-L45,0) -> -1422409157 | AG45: =VLOOKUP(Indicador!E9,[1]Diccionario!C$1:AC$150,27,0) -> https://growdatasas.sharepoint.com/:x:/r/sites/Gestiondocumental/Administrativa/GD/Financiera/_layouts/15/Doc.aspx?sourcedoc=%7BC3EFE0E2-C211-45B0-905D-ECEF11221767%7D&file=299.%20DEFENSORIA_ERP.xlsm&action=default&mobileredirect=true | AH45: 1 | AI45: 1 | AJ45: ok
A46: 2024 | B46: Mayo | C46: b3dee2f4-49c1-ee11-add8-00155d10211a | D46: 45323.9 | E46: CORP COLOMBIA DIGITAL-FNA-AE | F46: Johan Sebastian Rodriguez Niño | G46: https://growdatasas.sharepoint.com/sites/pwa/CORP COLOMBIA DIGITAL-FNA-AE | H46: Consultoría para el diseño de la Transformación Digital de la entidad que designe la Corporación Colombia Digital, basado en desarrollar la arquitectura empresarial - AR, la definición e implementación del Gobierno y la gestión de datos, la definición de la hoja de ruta de la AR para el plan estratégico de TI PETI, la formación de personal y la planeación del proyecto de la entidad designada. | I46: CONSULTORÍA | J46: 0315 | K46: Activo.En Cierre | L46: =VLOOKUP(E46,[1]Diccionario!C$2:AC$150,22,0) -> 1422409157 | M46: =VLOOKUP(E46,[1]Diccionario!C$2:AC$150,24,0) -> 45292 | N46: =VLOOKUP(E46,[1]Diccionario!C$2:AC$150,25,0) -> 45534 | O46: =VLOOKUP(E46,[1]Diccionario!C$2:AC$150,26,0) -> 7.97 | P46: =Q46-O46 -> -2.97 | Q46: 5 | R46: 8 | S46: 0.6 | T46: 0.6 | U46: =U45+TablaIndicador[[#This Row],[Costo Mensual]] -> 0 | W46: =IFERROR(T46*L46,0) -> 8.5344549e+08 | X46: =S46*L46 -> 8.5344549e+08 | Y46: =IFERROR(W46-U46,0) -> 8.5344549e+08 | Z46: =W46-X46 -> 0 | AA46: =IFERROR(W46/U46,"No se realizó gasto en este corte") -> No se realizó gasto en este corte | AB46: =IFERROR( IF(OR(AA46="",AA46=0), "No calculado", IF(AA46>1,"Costo eficiente: se está gastando menos de lo presupuestado", IF(AA46=1,"Costo según lo presupuestado", "Costo ineficiente: se está gastando más de lo presupuestado"))), "No calculado") -> Costo eficiente: se está gastando menos de lo presupuestado | AC46: =IFERROR(W46/X46,0) -> 1 | AD46: =IF(OR(AC46="",AC46=0),"Sin Línea Base", IF(AC46>1,"Proyecto adelantado respecto al cronograma", IF(AC46=1,"Proyecto a tiempo según lo planificado", IF(AC46<1,"Proyecto atrasado con respecto al cronograma", "No calculado")))) -> Proyecto a tiempo según lo planificado | AE46: =IFERROR(L46/AA46,0) -> 0 | AF46: =IFERROR(AE46-L46,0) -> -1422409157 | AG46: =VLOOKUP(Indicador!E10,[1]Diccionario!C$1:AC$150,27,0) -> https://growdatasas.sharepoint.com/:x:/r/sites/Gestiondocumental/Administrativa/GD/Financiera/_layouts/15/Doc.aspx?sourcedoc=%7BC3EFE0E2-C211-45B0-905D-ECEF11221767%7D&file=299.%20DEFENSORIA_ERP.xlsm&action=default&mobileredirect=true | AH46: 1 | AI46: 1 | AJ46: ok
A47: 2024 | B47: Junio | C47: b3dee2f4-49c1-ee11-add8-00155d10211a | D47: 45323.9 | E47: CORP COLOMBIA DIGITAL-FNA-AE | F47: Johan Sebastian Rodriguez Niño | G47: https://growdatasas.sharepoint.com/sites/pwa/CORP COLOMBIA DIGITAL-FNA-AE | H47: Consultoría para el diseño de la Transformación Digital de la entidad que designe la Corporación Colombia Digital, basado en desarrollar la arquitectura empresarial - AR, la definición e implementación del Gobierno y la gestión de datos, la definición de la hoja de ruta de la AR para el plan estratégico de TI PETI, la formación de personal y la planeación del proyecto de la entidad designada. | I47: CONSULTORÍA | J47: 0315 | K47: Activo.En Cierre | L47: =VLOOKUP(E47,[1]Diccionario!C$2:AC$150,22,0) -> 1422409157 | M47: =VLOOKUP(E47,[1]Diccionario!C$2:AC$150,24,0) -> 45292 | N47: =VLOOKUP(E47,[1]Diccionario!C$2:AC$150,25,0) -> 45534 | O47: =VLOOKUP(E47,[1]Diccionario!C$2:AC$150,26,0) -> 7.97 | P47: =Q47-O47 -> -1.97 | Q47: 6 | R47: 8 | S47: 0.75 | T47: 0.73 | U47: =U46+TablaIndicador[[#This Row],[Costo Mensual]] -> 0 | W47: =IFERROR(T47*L47,0) -> 1.0383587e+09 | X47: =S47*L47 -> 1.0668069e+09 | Y47: =IFERROR(W47-U47,0) -> 1.0383587e+09 | Z47: =W47-X47 -> -28448183 | AA47: =IFERROR(W47/U47,"No se realizó gasto en este corte") -> No se realizó gasto en este corte | AB47: =IFERROR( IF(OR(AA47="",AA47=0), "No calculado", IF(AA47>1,"Costo eficiente: se está gastando menos de lo presupuestado", IF(AA47=1,"Costo según lo presupuestado", "Costo ineficiente: se está gastando más de lo presupuestado"))), "No calculado") -> Costo eficiente: se está gastando menos de lo presupuestado | AC47: =IFERROR(W47/X47,0) -> 0.97333333 | AD47: =IF(OR(AC47="",AC47=0),"Sin Línea Base", IF(AC47>1,"Proyecto adelantado respecto al cronograma", IF(AC47=1,"Proyecto a tiempo según lo planificado", IF(AC47<1,"Proyecto atrasado con respecto al cronograma", "No calculado")))) -> Proyecto atrasado con respecto al cronograma | AE47: =IFERROR(L47/AA47,0) -> 0 | AF47: =IFERROR(AE47-L47,0) -> -1422409157 | AG47: =VLOOKUP(Indicador!E11,[1]Diccionario!C$1:AC$150,27,0) -> https://growdatasas.sharepoint.com/:x:/r/sites/Gestiondocumental/Administrativa/GD/Financiera/_layouts/15/Doc.aspx?sourcedoc=%7BC3EFE0E2-C211-45B0-905D-ECEF11221767%7D&file=299.%20DEFENSORIA_ERP.xlsm&action=default&mobileredirect=true | AH47: 1 | AI47: 1 | AJ47: ok
A48: 2024 | B48: Julio | C48: b3dee2f4-49c1-ee11-add8-00155d10211a | D48: 45323.9 | E48: CORP COLOMBIA DIGITAL-FNA-AE | F48: Johan Sebastian Rodriguez Niño | G48: https://growdatasas.sharepoint.com/sites/pwa/CORP COLOMBIA DIGITAL-FNA-AE | H48: Consultoría para el diseño de la Transformación Digital de la entidad que designe la Corporación Colombia Digital, basado en desarrollar la arquitectura empresarial - AR, la definición e implementación del Gobierno y la gestión de datos, la definición de la hoja de ruta de la AR para el plan estratégico de TI PETI, la formación de personal y la planeación del proyecto de la entidad designada. | I48: CONSULTORÍA | J48: 0315 | K48: Activo.En Cierre | L48: =VLOOKUP(E48,[1]Diccionario!C$2:AC$150,22,0) -> 1422409157 | M48: =VLOOKUP(E48,[1]Diccionario!C$2:AC$150,24,0) -> 45292 | N48: =VLOOKUP(E48,[1]Diccionario!C$2:AC$150,25,0) -> 45534 | O48: =VLOOKUP(E48,[1]Diccionario!C$2:AC$150,26,0) -> 7.97 | P48: =Q48-O48 -> -0.97 | Q48: 7 | R48: 8 | S48: 0.8 | T48: 0.82 | U48: =U47+TablaIndicador[[#This Row],[Costo Mensual]] -> 0 | W48: =IFERROR(T48*L48,0) -> 1.1663755e+09 | X48: =S48*L48 -> 1.1379273e+09 | Y48: =IFERROR(W48-U48,0) -> 1.1663755e+09 | Z48: =W48-X48 -> 28448183 | AA48: =IFERROR(W48/U48,"No se realizó gasto en este corte") -> No se realizó gasto en este corte | AB48: =IFERROR( IF(OR(AA48="",AA48=0), "No calculado", IF(AA48>1,"Costo eficiente: se está gastando menos de lo presupuestado", IF(AA48=1,"Costo según lo presupuestado", "Costo ineficiente: se está gastando más de lo presupuestado"))), "No calculado") -> Costo eficiente: se está gastando menos de lo presupuestado | AC48: =IFERROR(W48/X48,0) -> 1.025 | AD48: =IF(OR(AC48="",AC48=0),"Sin Línea Base", IF(AC48>1,"Proyecto adelantado respecto al cronograma", IF(AC48=1,"Proyecto a tiempo según lo planificado", IF(AC48<1,"Proyecto atrasado con respecto al cronograma", "No calculado")))) -> Proyecto adelantado respecto al cronograma | AE48: =IFERROR(L48/AA48,0) -> 0 | AF48: =IFERROR(AE48-L48,0) -> -1422409157 | AG48: =VLOOKUP(Indicador!E12,[1]Diccionario!C$1:AC$150,27,0) -> https://growdatasas.sharepoint.com/:x:/r/sites/Gestiondocumental/Administrativa/GD/Financiera/_layouts/15/Doc.aspx?sourcedoc=%7BC3EFE0E2-C211-45B0-905D-ECEF11221767%7D&file=299.%20DEFENSORIA_ERP.xlsm&action=default&mobileredirect=true | AH48: 1 | AI48: 1 | AJ48: ok
A49: 2024 | B49: Agosto | C49: b3dee2f4-49c1-ee11-add8-00155d10211a | D49: 45323.9 | E49: CORP COLOMBIA DIGITAL-FNA-AE | F49: Johan Sebastian Rodriguez Niño | G49: https://growdatasas.sharepoint.com/sites/pwa/CORP COLOMBIA DIGITAL-FNA-AE | H49: Consultoría para el diseño de la Transformación Digital de la entidad que designe la Corporación Colombia Digital, basado en desarrollar la arquitectura empresarial - AR, la definición e implementación del Gobierno y la gestión de datos, la definición de la hoja de ruta de la AR para el plan estratégico de TI PETI, la formación de personal y la planeación del proyecto de la entidad designada. | I49: CONSULTORÍA | J49: 0315 | K49: Activo.En Cierre | L49: =VLOOKUP(E49,[1]Diccionario!C$2:AC$150,22,0) -> 1422409157 | M49: =VLOOKUP(E49,[1]Diccionario!C$2:AC$150,24,0) -> 45292 | N49: =VLOOKUP(E49,[1]Diccionario!C$2:AC$150,25,0) -> 45534 | O49: =VLOOKUP(E49,[1]Diccionario!C$2:AC$150,26,0) -> 7.97 | P49: =Q49-O49 -> 0.03 | Q49: 8 | R49: 8 | S49: 1 | T49: 1 | U49: =U48+TablaIndicador[[#This Row],[Costo Mensual]] -> 0 | W49: =IFERROR(T49*L49,0) -> 1422409157 | X49: =S49*L49 -> 1422409157 | Y49: =IFERROR(W49-U49,0) -> 1422409157 | Z49: =W49-X49 -> 0 | AA49: =IFERROR(W49/U49,"No se realizó gasto en este corte") -> No se realizó gasto en este corte | AB49: =IFERROR( IF(OR(AA49="",AA49=0), "No calculado", IF(AA49>1,"Costo eficiente: se está gastando menos de lo presupuestado", IF(AA49=1,"Costo según lo presupuestado", "Costo ineficiente: se está gastando más de lo presupuestado"))), "No calculado") -> Costo eficiente: se está gastando menos de lo presupuestado | AC49: =IFERROR(W49/X49,0) -> 1 | AD49: =IF(OR(AC49="",AC49=0),"Sin Línea Base", IF(AC49>1,"Proyecto adelantado respecto al cronograma", IF(AC49=1,"Proyecto a tiempo según lo planificado", IF(AC49<1,"Proyecto atrasado con respecto al cronograma", "No calculado")))) -> Proyecto a tiempo según lo planificado | AE49: =IFERROR(L49/AA49,0) -> 0 | AF49: =IFERROR(AE49-L49,0) -> -1422409157 | AG49: =VLOOKUP(Indicador!E13,[1]Diccionario!C$1:AC$150,27,0) -> https://growdatasas.sharepoint.com/:x:/r/sites/Gestiondocumental/Administrativa/GD/Financiera/_layouts/15/Doc.aspx?sourcedoc=%7BC3EFE0E2-C211-45B0-905D-ECEF11221767%7D&file=299.%20DEFENSORIA_ERP.xlsm&action=default&mobileredirect=true | AH49: 1 | AI49: 1 | AJ49: ok
A50: 2024 | B50: Agosto | C50: b3dee2f4-49c1-ee11-add8-00155d10211a | D50: 45323.9 | E50: CORP COLOMBIA DIGITAL-FNA-AE | F50: Johan Sebastian Rodriguez Niño | G50: https://growdatasas.sharepoint.com/sites/pwa/CORP COLOMBIA DIGITAL-FNA-AE | H50: Consultoría para el diseño de la Transformación Digital de la entidad que designe la Corporación Colombia Digital, basado en desarrollar la arquitectura empresarial - AR, la definición e implementación del Gobierno y la gestión de datos, la definición de la hoja de ruta de la AR para el plan estratégico de TI PETI, la formación de personal y la planeación del proyecto de la entidad designada. | I50: CONSULTORÍA | J50: 0315 | K50: Activo.En Cierre | L50: =VLOOKUP(E50,[1]Diccionario!C$2:AC$150,22,0) -> 1422409157 | M50: =VLOOKUP(E50,[1]Diccionario!C$2:AC$150,24,0) -> 45292 | N50: =VLOOKUP(E50,[1]Diccionario!C$2:AC$150,25,0) -> 45534 | O50: =VLOOKUP(E50,[1]Diccionario!C$2:AC$150,26,0) -> 7.97 | P50: =Q50-O50 -> 0.03 | Q50: 8 | R50: 8 | S50: 1 | T50: 1 | U50: =U49+TablaIndicador[[#This Row],[Costo Mensual]] -> 0 | W50: =IFERROR(T50*L50,0) -> 1422409157 | X50: =S50*L50 -> 1422409157 | Y50: =IFERROR(W50-U50,0) -> 1422409157 | Z50: =W50-X50 -> 0 | AA50: =IFERROR(W50/U50,"No se realizó gasto en este corte") -> No se realizó gasto en este corte | AB50: =IFERROR( IF(OR(AA50="",AA50=0), "No calculado", IF(AA50>1,"Costo eficiente: se está gastando menos de lo presupuestado", IF(AA50=1,"Costo según lo presupuestado", "Costo ineficiente: se está gastando más de lo presupuestado"))), "No calculado") -> Costo eficiente: se está gastando menos de lo presupuestado | AC50: =IFERROR(W50/X50,0) -> 1 | AD50: =IF(OR(AC50="",AC50=0),"Sin Línea Base", IF(AC50>1,"Proyecto adelantado respecto al cronograma", IF(AC50=1,"Proyecto a tiempo según lo planificado", IF(AC50<1,"Proyecto atrasado con respecto al cronograma", "No calculado")))) -> Proyecto a tiempo según lo planificado | AE50: =IFERROR(L50/AA50,0) -> 0 | AF50: =IFERROR(AE50-L50,0) -> -1422409157 | AG50: =VLOOKUP(Indicador!E14,[1]Diccionario!C$1:AC$150,27,0) -> https://growdatasas.sharepoint.com/:x:/r/sites/Gestiondocumental/Administrativa/GD/Financiera/_layouts/15/Doc.aspx?sourcedoc=%7BC3EFE0E2-C211-45B0-905D-ECEF11221767%7D&file=299.%20DEFENSORIA_ERP.xlsm&action=default&mobileredirect=true | AH50: 1 | AI50: 1 | AJ50: ok
A51: 2024 | B51: Agosto | C51: b3dee2f4-49c1-ee11-add8-00155d10211a | D51: 45323.9 | E51: CORP COLOMBIA DIGITAL-FNA-AE | F51: Johan Sebastian Rodriguez Niño | G51: https://growdatasas.sharepoint.com/sites/pwa/CORP COLOMBIA DIGITAL-FNA-AE | H51: Consultoría para el diseño de la Transformación Digital de la entidad que designe la Corporación Colombia Digital, basado en desarrollar la arquitectura empresarial - AR, la definición e implementación del Gobierno y la gestión de datos, la definición de la hoja de ruta de la AR para el plan estratégico de TI PETI, la formación de personal y la planeación del proyecto de la entidad designada. | I51: CONSULTORÍA | J51: 0315 | K51: Activo.En Cierre | L51: =VLOOKUP(E51,[1]Diccionario!C$2:AC$150,22,0) -> 1422409157 | M51: =VLOOKUP(E51,[1]Diccionario!C$2:AC$150,24,0) -> 45292 | N51: =VLOOKUP(E51,[1]Diccionario!C$2:AC$150,25,0) -> 45534 | O51: =VLOOKUP(E51,[1]Diccionario!C$2:AC$150,26,0) -> 7.97 | P51: =Q51-O51 -> 0.03 | Q51: 8 | R51: 8 | S51: 1 | T51: 1 | U51: =U50+TablaIndicador[[#This Row],[Costo Mensual]] -> 0 | W51: =IFERROR(T51*L51,0) -> 1422409157 | X51: =S51*L51 -> 1422409157 | Y51: =IFERROR(W51-U51,0) -> 1422409157 | Z51: =W51-X51 -> 0 | AA51: =IFERROR(W51/U51,"No se realizó gasto en este corte") -> No se realizó gasto en este corte | AB51: =IFERROR( IF(OR(AA51="",AA51=0), "No calculado", IF(AA51>1,"Costo eficiente: se está gastando menos de lo presupuestado", IF(AA51=1,"Costo según lo presupuestado", "Costo ineficiente: se está gastando más de lo presupuestado"))), "No calculado") -> Costo eficiente: se está gastando menos de lo presupuestado | AC51: =IFERROR(W51/X51,0) -> 1 | AD51: =IF(OR(AC51="",AC51=0),"Sin Línea Base", IF(AC51>1,"Proyecto adelantado respecto al cronograma", IF(AC51=1,"Proyecto a tiempo según lo planificado", IF(AC51<1,"Proyecto atrasado con respecto al cronograma", "No calculado")))) -> Proyecto a tiempo según lo planificado | AE51: =IFERROR(L51/AA51,0) -> 0 | AF51: =IFERROR(AE51-L51,0) -> -1422409157 | AG51: =VLOOKUP(Indicador!E15,[1]Diccionario!C$1:AC$150,27,0) -> https://growdatasas.sharepoint.com/:x:/r/sites/Gestiondocumental/Administrativa/GD/Financiera/_layouts/15/Doc.aspx?sourcedoc=%7BC3EFE0E2-C211-45B0-905D-ECEF11221767%7D&file=299.%20DEFENSORIA_ERP.xlsm&action=default&mobileredirect=true | AH51: 1 | AI51: 1 | AJ51: ok
A52: 2024 | B52: Agosto | C52: b3dee2f4-49c1-ee11-add8-00155d10211a | D52: 45323.9 | E52: CORP COLOMBIA DIGITAL-FNA-AE | F52: Johan Sebastian Rodriguez Niño | G52: https://growdatasas.sharepoint.com/sites/pwa/CORP COLOMBIA DIGITAL-FNA-AE | H52: Consultoría para el diseño de la Transformación Digital de la entidad que designe la Corporación Colombia Digital, basado en desarrollar la arquitectura empresarial - AR, la definición e implementación del Gobierno y la gestión de datos, la definición de la hoja de ruta de la AR para el plan estratégico de TI PETI, la formación de personal y la planeación del proyecto de la entidad designada. | I52: CONSULTORÍA | J52: 0315 | K52: Activo.En Cierre | L52: =VLOOKUP(E52,[1]Diccionario!C$2:AC$150,22,0) -> 1422409157 | M52: =VLOOKUP(E52,[1]Diccionario!C$2:AC$150,24,0) -> 45292 | N52: =VLOOKUP(E52,[1]Diccionario!C$2:AC$150,25,0) -> 45534 | O52: =VLOOKUP(E52,[1]Diccionario!C$2:AC$150,26,0) -> 7.97 | P52: =Q52-O52 -> 0.03 | Q52: 8 | R52: 8 | S52: 1 | T52: 1 | U52: =U51+TablaIndicador[[#This Row],[Costo Mensual]] -> 0 | W52: =IFERROR(T52*L52,0) -> 1422409157 | X52: =S52*L52 -> 1422409157 | Y52: =IFERROR(W52-U52,0) -> 1422409157 | Z52: =W52-X52 -> 0 | AA52: =IFERROR(W52/U52,"No se realizó gasto en este corte") -> No se realizó gasto en este corte | AB52: =IFERROR( IF(OR(AA52="",AA52=0), "No calculado", IF(AA52>1,"Costo eficiente: se está gastando menos de lo presupuestado", IF(AA52=1,"Costo según lo presupuestado", "Costo ineficiente: se está gastando más de lo presupuestado"))), "No calculado") -> Costo eficiente: se está gastando menos de lo presupuestado | AC52: =IFERROR(W52/X52,0) -> 1 | AD52: =IF(OR(AC52="",AC52=0),"Sin Línea Base", IF(AC52>1,"Proyecto adelantado respecto al cronograma", IF(AC52=1,"Proyecto a tiempo según lo planificado", IF(AC52<1,"Proyecto atrasado con respecto al cronograma", "No calculado")))) -> Proyecto a tiempo según lo planificado | AE52: =IFERROR(L52/AA52,0) -> 0 | AF52: =IFERROR(AE52-L52,0) -> -1422409157 | AG52: =VLOOKUP(Indicador!E16,[1]Diccionario!C$1:AC$150,27,0) -> https://growdatasas.sharepoint.com/:x:/r/sites/Gestiondocumental/Administrativa/GD/Financiera/_layouts/15/Doc.aspx?sourcedoc=%7BC3EFE0E2-C211-45B0-905D-ECEF11221767%7D&file=299.%20DEFENSORIA_ERP.xlsm&action=default&mobileredirect=true | AH52: 1 | AI52: 1 | AJ52: ok
A53: 2024 | B53: Enero | C53: a514ea09-ced4-ee11-bd00-00155d682338 | D53: 45348.736 | E53: TELEFONICA - SENA MDA | F53: Carlos Fernando Gomez Rodriguez | G53: https://growdatasas.sharepoint.com/sites/pwa/TELEFONICA - SENA MDA | H53: ​Mesa de servicio para el SENA | I53: TI | J53: 0319 | K53: Cerrado | L53: =VLOOKUP(E53,[1]Diccionario!C$2:AC$150,22,0) -> 13344287960 | M53: =VLOOKUP(E53,[1]Diccionario!C$2:AC$150,24,0) -> 45292 | N53: =VLOOKUP(E53,[1]Diccionario!C$2:AC$150,25,0) -> 45381 | O53: =VLOOKUP(E53,[1]Diccionario!C$2:AC$150,26,0) -> 2.97 | P53: =Q53-O53 -> -1.97 | Q53: 1 | R53: 3 | S53: 0.3 | T53: 0.25 | U53: =TablaIndicador[[#This Row],[Costo Mensual]] -> 0 | W53: =IFERROR(T53*L53,0) -> 3336071990 | X53: =S53*L53 -> 4003286388 | Y53: =IFERROR(W53-U53,0) -> 3336071990 | Z53: =W53-X53 -> -667214398 | AA53: =IFERROR(W53/U53,"No se realizó gasto en este corte") -> No se realizó gasto en este corte | AB53: =IFERROR( IF(OR(AA53="",AA53=0), "No calculado", IF(AA53>1,"Costo eficiente: se está gastando menos de lo presupuestado", IF(AA53=1,"Costo según lo presupuestado", "Costo ineficiente: se está gastando más de lo presupuestado"))), "No calculado") -> Costo eficiente: se está gastando menos de lo presupuestado | AC53: =IFERROR(W53/X53,0) -> 0.83333333 | AD53: =IF(OR(AC53="",AC53=0),"Sin Línea Base", IF(AC53>1,"Proyecto adelantado respecto al cronograma", IF(AC53=1,"Proyecto a tiempo según lo planificado", IF(AC53<1,"Proyecto atrasado con respecto al cronograma", "No calculado")))) -> Proyecto atrasado con respecto al cronograma | AE53: =IFERROR(L53/AA53,0) -> 0 | AF53: =IFERROR(AE53-L53,0) -> -13344287960 | AG53: =VLOOKUP(Indicador!E3,[1]Diccionario!C$1:AC$150,27,0) -> https://growdatasas.sharepoint.com/:x:/r/sites/Gestiondocumental/Administrativa/GD/Financiera/_layouts/15/Doc.aspx?sourcedoc=%7BC3EFE0E2-C211-45B0-905D-ECEF11221767%7D&file=299.%20DEFENSORIA_ERP.xlsm&action=default&mobileredirect=true | AH53: 1 | AI53: 1 | AJ53: ok
A54: 2024 | B54: Febrero | C54: a514ea09-ced4-ee11-bd00-00155d682338 | D54: 45348.736 | E54: TELEFONICA - SENA MDA | F54: Carlos Fernando Gomez Rodriguez | G54: https://growdatasas.sharepoint.com/sites/pwa/TELEFONICA - SENA MDA | H54: ​Mesa de servicio para el SENA | I54: TI | J54: 0319 | K54: Cerrado | L54: =VLOOKUP(E54,[1]Diccionario!C$2:AC$150,22,0) -> 13344287960 | M54: =VLOOKUP(E54,[1]Diccionario!C$2:AC$150,24,0) -> 45292 | N54: =VLOOKUP(E54,[1]Diccionario!C$2:AC$150,25,0) -> 45381 | O54: =VLOOKUP(E54,[1]Diccionario!C$2:AC$150,26,0) -> 2.97 | P54: =Q54-O54 -> -0.97 | Q54: 2 | R54: 3 | S54: 0.7 | T54: 0.65 | U54: =U53+TablaIndicador[[#This Row],[Costo Mensual]] -> 0 | W54: =IFERROR(T54*L54,0) -> 8673787174 | X54: =S54*L54 -> 9341001572 | Y54: =IFERROR(W54-U54,0) -> 8673787174 | Z54: =W54-X54 -> -667214398 | AA54: =IFERROR(W54/U54,"No se realizó gasto en este corte") -> No se realizó gasto en este corte | AB54: =IFERROR( IF(OR(AA54="",AA54=0), "No calculado", IF(AA54>1,"Costo eficiente: se está gastando menos de lo presupuestado", IF(AA54=1,"Costo según lo presupuestado", "Costo ineficiente: se está gastando más de lo presupuestado"))), "No calculado") -> Costo eficiente: se está gastando menos de lo presupuestado | AC54: =IFERROR(W54/X54,0) -> 0.92857143 | AD54: =IF(OR(AC54="",AC54=0),"Sin Línea Base", IF(AC54>1,"Proyecto adelantado respecto al cronograma", IF(AC54=1,"Proyecto a tiempo según lo planificado", IF(AC54<1,"Proyecto atrasado con respecto al cronograma", "No calculado")))) -> Proyecto atrasado con respecto al cronograma | AE54: =IFERROR(L54/AA54,0) -> 0 | AF54: =IFERROR(AE54-L54,0) -> -13344287960 | AG54: =VLOOKUP(Indicador!E4,[1]Diccionario!C$1:AC$150,27,0) -> https://growdatasas.sharepoint.com/:x:/r/sites/Gestiondocumental/Administrativa/GD/Financiera/_layouts/15/Doc.aspx?sourcedoc=%7BC3EFE0E2-C211-45B0-905D-ECEF11221767%7D&file=299.%20DEFENSORIA_ERP.xlsm&action=default&mobileredirect=true | AH54: 1 | AI54: 1 | AJ54: ok
A55: 2024 | B55: Marzo | C55: a514ea09-ced4-ee11-bd00-00155d682338 | D55: 45348.736 | E55: TELEFONICA - SENA MDA | F55: Carlos Fernando Gomez Rodriguez | G55: https://growdatasas.sharepoint.com/sites/pwa/TELEFONICA - SENA MDA | H55: ​Mesa de servicio para el SENA | I55: TI | J55: 0319 | K55: Cerrado | L55: =VLOOKUP(E55,[1]Diccionario!C$2:AC$150,22,0) -> 13344287960 | M55: =VLOOKUP(E55,[1]Diccionario!C$2:AC$150,24,0) -> 45292 | N55: =VLOOKUP(E55,[1]Diccionario!C$2:AC$150,25,0) -> 45381 | O55: =VLOOKUP(E55,[1]Diccionario!C$2:AC$150,26,0) -> 2.97 | P55: =Q55-O55 -> 0.03 | Q55: 3 | R55: 3 | S55: 1 | T55: 1 | U55: =U54+TablaIndicador[[#This Row],[Costo Mensual]] -> 0 | W55: =IFERROR(T55*L55,0) -> 13344287960 | X55: =S55*L55 -> 13344287960 | Y55: =IFERROR(W55-U55,0) -> 13344287960 | Z55: =W55-X55 -> 0 | AA55: =IFERROR(W55/U55,"No se realizó gasto en este corte") -> No se realizó gasto en este corte | AB55: =IFERROR( IF(OR(AA55="",AA55=0), "No calculado", IF(AA55>1,"Costo eficiente: se está gastando menos de lo presupuestado", IF(AA55=1,"Costo según lo presupuestado", "Costo ineficiente: se está gastando más de lo presupuestado"))), "No calculado") -> Costo eficiente: se está gastando menos de lo presupuestado | AC55: =IFERROR(W55/X55,0) -> 1 | AD55: =IF(OR(AC55="",AC55=0),"Sin Línea Base", IF(AC55>1,"Proyecto adelantado respecto al cronograma", IF(AC55=1,"Proyecto a tiempo según lo planificado", IF(AC55<1,"Proyecto atrasado con respecto al cronograma", "No calculado")))) -> Proyecto a tiempo según lo planificado | AE55: =IFERROR(L55/AA55,0) -> 0 | AF55: =IFERROR(AE55-L55,0) -> -13344287960 | AG55: =VLOOKUP(Indicador!E5,[1]Diccionario!C$1:AC$150,27,0) -> https://growdatasas.sharepoint.com/:x:/r/sites/Gestiondocumental/Administrativa/GD/Financiera/_layouts/15/Doc.aspx?sourcedoc=%7BC3EFE0E2-C211-45B0-905D-ECEF11221767%7D&file=299.%20DEFENSORIA_ERP.xlsm&action=default&mobileredirect=true | AH55: 1 | AI55: 1 | AJ55: ok
A56: 2024 | B56: Febrero | C56: 3f6c4573-29db-ee11-8860-00155d681010 | D56: 45356.826 | E56: ERT- MT– DISPOSITIVOS IOT Y ANALÍTICA | F56: Mario Andres Pirachican Gil | G56: https://growdatasas.sharepoint.com/sites/pwa/ERT- MT– DISPOSITIVOS IOT Y ANALÍTICA | H56: ​Se propone prestar el servicio de asistencia técnica mediante la recolección, procesamiento y correlación de datos con capacidad de análisis, a través de una plataforma de soluciones basadas en IoT (internet de las cosas), que permita la visualización de indicadores específicos con el objetivo de mejorar la seguridad vial y trazabilidad de recorrido a través de la integración de dispositivos de georreferenciación en vehículos de transporte de carga. | I56: DATOS Y SISTEMAS DE INFORMACIÓN | J56: 0322 | K56: Postventa | L56: =VLOOKUP(E56,[1]Diccionario!C$2:AC$150,22,0) -> 4004446789 | M56: =VLOOKUP(E56,[1]Diccionario!C$2:AC$150,24,0) -> 45345 | N56: =VLOOKUP(E56,[1]Diccionario!C$2:AC$150,25,0) -> 45587 | O56: =VLOOKUP(E56,[1]Diccionario!C$2:AC$150,26,0) -> 7.97 | P56: =Q56-O56 -> -6.97 | Q56: 1 | R56: 8 | S56: 0.1 | T56: 0.09 | W56: =IFERROR(T56*L56,0) -> 3.6040021e+08 | X56: =S56*L56 -> 4.0044468e+08 | Y56: =IFERROR(W56-U56,0) -> 3.6040021e+08 | Z56: =W56-X56 -> -40044468 | AA56: =IFERROR(W56/U56,"No se realizó gasto en este corte") -> No se realizó gasto en este corte | AB56: =IFERROR( IF(OR(AA56="",AA56=0), "No calculado", IF(AA56>1,"Costo eficiente: se está gastando menos de lo presupuestado", IF(AA56=1,"Costo según lo presupuestado", "Costo ineficiente: se está gastando más de lo presupuestado"))), "No calculado") -> Costo eficiente: se está gastando menos de lo presupuestado | AC56: =IFERROR(W56/X56,0) -> 0.9 | AD56: =IF(OR(AC56="",AC56=0),"Sin Línea Base", IF(AC56>1,"Proyecto adelantado respecto al cronograma", IF(AC56=1,"Proyecto a tiempo según lo planificado", IF(AC56<1,"Proyecto atrasado con respecto al cronograma", "No calculado")))) -> Proyecto atrasado con respecto al cronograma | AE56: =IFERROR(L56/AA56,0) -> 0 | AF56: =IFERROR(AE56-L56,0) -> -4004446789 | AG56: =VLOOKUP(Indicador!E57,[1]Diccionario!C$1:AC$150,27,0) -> https://growdatasas.sharepoint.com/:x:/r/sites/Gestiondocumental/Administrativa/GD/Financiera/_layouts/15/Doc.aspx?sourcedoc=%7B29DCF375-0847-4DAD-9B9A-9F9E84ABD4DE%7D&file=322.%20MINTRANSPORTE.xlsx&action=default&mobileredirect=true | AH56: 1 | AI56: 1
A57: 2024 | B57: Marzo | C57: 3f6c4573-29db-ee11-8860-00155d681010 | D57: 45356.826 | E57: ERT- MT– DISPOSITIVOS IOT Y ANALÍTICA | F57: Mario Andres Pirachican Gil | G57: https://growdatasas.sharepoint.com/sites/pwa/ERT- MT– DISPOSITIVOS IOT Y ANALÍTICA | H57: ​Se propone prestar el servicio de asistencia técnica mediante la recolección, procesamiento y correlación de datos con capacidad de análisis, a través de una plataforma de soluciones basadas en IoT (internet de las cosas), que permita la visualización de indicadores específicos con el objetivo de mejorar la seguridad vial y trazabilidad de recorrido a través de la integración de dispositivos de georreferenciación en vehículos de transporte de carga. | I57: DATOS Y SISTEMAS DE INFORMACIÓN | J57: 0322 | K57: Postventa | L57: =VLOOKUP(E57,[1]Diccionario!C$2:AC$150,22,0) -> 4004446789 | M57: =VLOOKUP(E57,[1]Diccionario!C$2:AC$150,24,0) -> 45345 | N57: =VLOOKUP(E57,[1]Diccionario!C$2:AC$150,25,0) -> 45587 | O57: =VLOOKUP(E57,[1]Diccionario!C$2:AC$150,26,0) -> 7.97 | P57: =Q57-O57 -> -5.97 | Q57: =Q56+1 -> 2 | R57: 8 | S57: 0.2 | T57: 0.25 | W57: =IFERROR(T57*L57,0) -> 1.0011117e+09 | X57: =S57*L57 -> 8.0088936e+08 | Y57: =IFERROR(W57-U57,0) -> 1.0011117e+09 | Z57: =W57-X57 -> 2.0022234e+08 | AA57: =IFERROR(W57/U57,"No se realizó gasto en este corte") -> No se realizó gasto en este corte | AB57: =IFERROR( IF(OR(AA57="",AA57=0), "No calculado", IF(AA57>1,"Costo eficiente: se está gastando menos de lo presupuestado", IF(AA57=1,"Costo según lo presupuestado", "Costo ineficiente: se está gastando más de lo presupuestado"))), "No calculado") -> Costo eficiente: se está gastando menos de lo presupuestado | AC57: =IFERROR(W57/X57,0) -> 1.25 | AD57: =IF(OR(AC57="",AC57=0),"Sin Línea Base", IF(AC57>1,"Proyecto adelantado respecto al cronograma", IF(AC57=1,"Proyecto a tiempo según lo planificado", IF(AC57<1,"Proyecto atrasado con respecto al cronograma", "No calculado")))) -> Proyecto adelantado respecto al cronograma | AE57: =IFERROR(L57/AA57,0) -> 0 | AF57: =IFERROR(AE57-L57,0) -> -4004446789 | AG57: =VLOOKUP(Indicador!E58,[1]Diccionario!C$1:AC$150,27,0) -> https://growdatasas.sharepoint.com/:x:/r/sites/Gestiondocumental/Administrativa/GD/Financiera/_layouts/15/Doc.aspx?sourcedoc=%7B29DCF375-0847-4DAD-9B9A-9F9E84ABD4DE%7D&file=322.%20MINTRANSPORTE.xlsx&action=default&mobileredirect=true | AH57: 1 | AI57: 1
A58: 2024 | B58: Abril | C58: 3f6c4573-29db-ee11-8860-00155d681010 | D58: 45356.826 | E58: ERT- MT– DISPOSITIVOS IOT Y ANALÍTICA | F58: Mario Andres Pirachican Gil | G58: https://growdatasas.sharepoint.com/sites/pwa/ERT- MT– DISPOSITIVOS IOT Y ANALÍTICA | H58: ​Se propone prestar el servicio de asistencia técnica mediante la recolección, procesamiento y correlación de datos con capacidad de análisis, a través de una plataforma de soluciones basadas en IoT (internet de las cosas), que permita la visualización de indicadores específicos con el objetivo de mejorar la seguridad vial y trazabilidad de recorrido a través de la integración de dispositivos de georreferenciación en vehículos de transporte de carga. | I58: DATOS Y SISTEMAS DE INFORMACIÓN | J58: 0322 | K58: Postventa | L58: =VLOOKUP(E58,[1]Diccionario!C$2:AC$150,22,0) -> 4004446789 | M58: =VLOOKUP(E58,[1]Diccionario!C$2:AC$150,24,0) -> 45345 | N58: =VLOOKUP(E58,[1]Diccionario!C$2:AC$150,25,0) -> 45587 | O58: =VLOOKUP(E58,[1]Diccionario!C$2:AC$150,26,0) -> 7.97 | P58: =Q58-O58 -> -4.97 | Q58: =Q57+1 -> 3 | R58: 8 | S58: 0.3 | T58: 0.3 | W58: =IFERROR(T58*L58,0) -> 1.201334e+09 | X58: =S58*L58 -> 1.201334e+09 | Y58: =IFERROR(W58-U58,0) -> 1.201334e+09 | Z58: =W58-X58 -> 0 | AA58: =IFERROR(W58/U58,"No se realizó gasto en este corte") -> No se realizó gasto en este corte | AB58: =IFERROR( IF(OR(AA58="",AA58=0), "No calculado", IF(AA58>1,"Costo eficiente: se está gastando menos de lo presupuestado", IF(AA58=1,"Costo según lo presupuestado", "Costo ineficiente: se está gastando más de lo presupuestado"))), "No calculado") -> Costo eficiente: se está gastando menos de lo presupuestado | AC58: =IFERROR(W58/X58,0) -> 1 | AD58: =IF(OR(AC58="",AC58=0),"Sin Línea Base", IF(AC58>1,"Proyecto adelantado respecto al cronograma", IF(AC58=1,"Proyecto a tiempo según lo planificado", IF(AC58<1,"Proyecto atrasado con respecto al cronograma", "No calculado")))) -> Proyecto a tiempo según lo planificado | AE58: =IFERROR(L58/AA58,0) -> 0 | AF58: =IFERROR(AE58-L58,0) -> -4004446789 | AG58: =VLOOKUP(Indicador!E59,[1]Diccionario!C$1:AC$150,27,0) -> https://growdatasas.sharepoint.com/:x:/r/sites/Gestiondocumental/Administrativa/GD/Financiera/_layouts/15/Doc.aspx?sourcedoc=%7B29DCF375-0847-4DAD-9B9A-9F9E84ABD4DE%7D&file=322.%20MINTRANSPORTE.xlsx&action=default&mobileredirect=true | AH58: 1 | AI58: 1
A59: 2024 | B59: Mayo | C59: 3f6c4573-29db-ee11-8860-00155d681010 | D59: 45356.826 | E59: ERT- MT– DISPOSITIVOS IOT Y ANALÍTICA | F59: Mario Andres Pirachican Gil | G59: https://growdatasas.sharepoint.com/sites/pwa/ERT- MT– DISPOSITIVOS IOT Y ANALÍTICA | H59: ​Se propone prestar el servicio de asistencia técnica mediante la recolección, procesamiento y correlación de datos con capacidad de análisis, a través de una plataforma de soluciones basadas en IoT (internet de las cosas), que permita la visualización de indicadores específicos con el objetivo de mejorar la seguridad vial y trazabilidad de recorrido a través de la integración de dispositivos de georreferenciación en vehículos de transporte de carga. | I59: DATOS Y SISTEMAS DE INFORMACIÓN | J59: 0322 | K59: Postventa | L59: =VLOOKUP(E59,[1]Diccionario!C$2:AC$150,22,0) -> 4004446789 | M59: =VLOOKUP(E59,[1]Diccionario!C$2:AC$150,24,0) -> 45345 | N59: =VLOOKUP(E59,[1]Diccionario!C$2:AC$150,25,0) -> 45587 | O59: =VLOOKUP(E59,[1]Diccionario!C$2:AC$150,26,0) -> 7.97 | P59: =Q59-O59 -> -3.97 | Q59: =Q58+1 -> 4 | R59: 8 | S59: 0.45 | T59: 0.42 | W59: =IFERROR(T59*L59,0) -> 1.6818677e+09 | X59: =S59*L59 -> 1.8020011e+09 | Y59: =IFERROR(W59-U59,0) -> 1.6818677e+09 | Z59: =W59-X59 -> -1.201334e+08 | AA59: =IFERROR(W59/U59,"No se realizó gasto en este corte") -> No se realizó gasto en este corte | AB59: =IFERROR( IF(OR(AA59="",AA59=0), "No calculado", IF(AA59>1,"Costo eficiente: se está gastando menos de lo presupuestado", IF(AA59=1,"Costo según lo presupuestado", "Costo ineficiente: se está gastando más de lo presupuestado"))), "No calculado") -> Costo eficiente: se está gastando menos de lo presupuestado | AC59: =IFERROR(W59/X59,0) -> 0.93333333 | AD59: =IF(OR(AC59="",AC59=0),"Sin Línea Base", IF(AC59>1,"Proyecto adelantado respecto al cronograma", IF(AC59=1,"Proyecto a tiempo según lo planificado", IF(AC59<1,"Proyecto atrasado con respecto al cronograma", "No calculado")))) -> Proyecto atrasado con respecto al cronograma | AE59: =IFERROR(L59/AA59,0) -> 0 | AF59: =IFERROR(AE59-L59,0) -> -4004446789 | AG59: =VLOOKUP(Indicador!E60,[1]Diccionario!C$1:AC$150,27,0) -> https://growdatasas.sharepoint.com/:x:/r/sites/Gestiondocumental/Administrativa/GD/Financiera/_layouts/15/Doc.aspx?sourcedoc=%7B29DCF375-0847-4DAD-9B9A-9F9E84ABD4DE%7D&file=322.%20MINTRANSPORTE.xlsx&action=default&mobileredirect=true | AH59: 1 | AI59: 1
A60: 2024 | B60: Junio | C60: 3f6c4573-29db-ee11-8860-00155d681010 | D60: 45356.826 | E60: ERT- MT– DISPOSITIVOS IOT Y ANALÍTICA | F60: Mario Andres Pirachican Gil | G60: https://growdatasas.sharepoint.com/sites/pwa/ERT- MT– DISPOSITIVOS IOT Y ANALÍTICA | H60: ​Se propone prestar el servicio de asistencia técnica mediante la recolección, procesamiento y correlación de datos con capacidad de análisis, a través de una plataforma de soluciones basadas en IoT (internet de las cosas), que permita la visualización de indicadores específicos con el objetivo de mejorar la seguridad vial y trazabilidad de recorrido a través de la integración de dispositivos de georreferenciación en vehículos de transporte de carga. | I60: DATOS Y SISTEMAS DE INFORMACIÓN | J60: 0322 | K60: Postventa | L60: =VLOOKUP(E60,[1]Diccionario!C$2:AC$150,22,0) -> 4004446789 | M60: =VLOOKUP(E60,[1]Diccionario!C$2:AC$150,24,0) -> 45345 | N60: =VLOOKUP(E60,[1]Diccionario!C$2:AC$150,25,0) -> 45587 | O60: =VLOOKUP(E60,[1]Diccionario!C$2:AC$150,26,0) -> 7.97 | P60: =Q60-O60 -> -2.97 | Q60: =Q59+1 -> 5 | R60: 8 | S60: 0.55 | T60: 0.55 | W60: =IFERROR(T60*L60,0) -> 2.2024457e+09 | X60: =S60*L60 -> 2.2024457e+09 | Y60: =IFERROR(W60-U60,0) -> 2.2024457e+09 | Z60: =W60-X60 -> 0 | AA60: =IFERROR(W60/U60,"No se realizó gasto en este corte") -> No se realizó gasto en este corte | AB60: =IFERROR( IF(OR(AA60="",AA60=0), "No calculado", IF(AA60>1,"Costo eficiente: se está gastando menos de lo presupuestado", IF(AA60=1,"Costo según lo presupuestado", "Costo ineficiente: se está gastando más de lo presupuestado"))), "No calculado") -> Costo eficiente: se está gastando menos de lo presupuestado | AC60: =IFERROR(W60/X60,0) -> 1 | AD60: =IF(OR(AC60="",AC60=0),"Sin Línea Base", IF(AC60>1,"Proyecto adelantado respecto al cronograma", IF(AC60=1,"Proyecto a tiempo según lo planificado", IF(AC60<1,"Proyecto atrasado con respecto al cronograma", "No calculado")))) -> Proyecto a tiempo según lo planificado | AE60: =IFERROR(L60/AA60,0) -> 0 | AF60: =IFERROR(AE60-L60,0) -> -4004446789 | AG60: =VLOOKUP(Indicador!E61,[1]Diccionario!C$1:AC$150,27,0) -> https://growdatasas.sharepoint.com/:x:/r/sites/Gestiondocumental/Administrativa/GD/Financiera/_layouts/15/Doc.aspx?sourcedoc=%7B29DCF375-0847-4DAD-9B9A-9F9E84ABD4DE%7D&file=322.%20MINTRANSPORTE.xlsx&action=default&mobileredirect=true | AH60: 1 | AI60: 1
A61: 2024 | B61: Julio | C61: 3f6c4573-29db-ee11-8860-00155d681010 | D61: 45356.826 | E61: ERT- MT– DISPOSITIVOS IOT Y ANALÍTICA | F61: Mario Andres Pirachican Gil | G61: https://growdatasas.sharepoint.com/sites/pwa/ERT- MT– DISPOSITIVOS IOT Y ANALÍTICA | H61: ​Se propone prestar el servicio de asistencia técnica mediante la recolección, procesamiento y correlación de datos con capacidad de análisis, a través de una plataforma de soluciones basadas en IoT (internet de las cosas), que permita la visualización de indicadores específicos con el objetivo de mejorar la seguridad vial y trazabilidad de recorrido a través de la integración de dispositivos de georreferenciación en vehículos de transporte de carga. | I61: DATOS Y SISTEMAS DE INFORMACIÓN | J61: 0322 | K61: Postventa | L61: =VLOOKUP(E61,[1]Diccionario!C$2:AC$150,22,0) -> 4004446789 | M61: =VLOOKUP(E61,[1]Diccionario!C$2:AC$150,24,0) -> 45345 | N61: =VLOOKUP(E61,[1]Diccionario!C$2:AC$150,25,0) -> 45587 | O61: =VLOOKUP(E61,[1]Diccionario!C$2:AC$150,26,0) -> 7.97 | P61: =Q61-O61 -> -1.97 | Q61: =Q60+1 -> 6 | R61: 8 | S61: 0.65 | T61: 0.67 | W61: =IFERROR(T61*L61,0) -> 2.6829793e+09 | X61: =S61*L61 -> 2.6028904e+09 | Y61: =IFERROR(W61-U61,0) -> 2.6829793e+09 | Z61: =W61-X61 -> 80088936 | AA61: =IFERROR(W61/U61,"No se realizó gasto en este corte") -> No se realizó gasto en este corte | AB61: =IFERROR( IF(OR(AA61="",AA61=0), "No calculado", IF(AA61>1,"Costo eficiente: se está gastando menos de lo presupuestado", IF(AA61=1,"Costo según lo presupuestado", "Costo ineficiente: se está gastando más de lo presupuestado"))), "No calculado") -> Costo eficiente: se está gastando menos de lo presupuestado | AC61: =IFERROR(W61/X61,0) -> 1.0307692 | AD61: =IF(OR(AC61="",AC61=0),"Sin Línea Base", IF(AC61>1,"Proyecto adelantado respecto al cronograma", IF(AC61=1,"Proyecto a tiempo según lo planificado", IF(AC61<1,"Proyecto atrasado con respecto al cronograma", "No calculado")))) -> Proyecto adelantado respecto al cronograma | AE61: =IFERROR(L61/AA61,0) -> 0 | AF61: =IFERROR(AE61-L61,0) -> -4004446789 | AG61: =VLOOKUP(Indicador!E62,[1]Diccionario!C$1:AC$150,27,0) -> https://growdatasas.sharepoint.com/:x:/r/sites/Gestiondocumental/Administrativa/GD/Financiera/_layouts/15/Doc.aspx?sourcedoc=%7B29DCF375-0847-4DAD-9B9A-9F9E84ABD4DE%7D&file=322.%20MINTRANSPORTE.xlsx&action=default&mobileredirect=true | AH61: 1 | AI61: 1
A62: 2024 | B62: Agosto | C62: 3f6c4573-29db-ee11-8860-00155d681010 | D62: 45356.826 | E62: ERT- MT– DISPOSITIVOS IOT Y ANALÍTICA | F62: Mario Andres Pirachican Gil | G62: https://growdatasas.sharepoint.com/sites/pwa/ERT- MT– DISPOSITIVOS IOT Y ANALÍTICA | H62: ​Se propone prestar el servicio de asistencia técnica mediante la recolección, procesamiento y correlación de datos con capacidad de análisis, a través de una plataforma de soluciones basadas en IoT (internet de las cosas), que permita la visualización de indicadores específicos con el objetivo de mejorar la seguridad vial y trazabilidad de recorrido a través de la integración de dispositivos de georreferenciación en vehículos de transporte de carga. | I62: DATOS Y SISTEMAS DE INFORMACIÓN | J62: 0322 | K62: Postventa | L62: =VLOOKUP(E62,[1]Diccionario!C$2:AC$150,22,0) -> 4004446789 | M62: =VLOOKUP(E62,[1]Diccionario!C$2:AC$150,24,0) -> 45345 | N62: =VLOOKUP(E62,[1]Diccionario!C$2:AC$150,25,0) -> 45587 | O62: =VLOOKUP(E62,[1]Diccionario!C$2:AC$150,26,0) -> 7.97 | P62: =Q62-O62 -> -0.97 | Q62: =Q61+1 -> 7 | R62: 8 | S62: 0.8 | T62: 0.85 | W62: =IFERROR(T62*L62,0) -> 3.4037798e+09 | X62: =S62*L62 -> 3.2035574e+09 | Y62: =IFERROR(W62-U62,0) -> 3.4037798e+09 | Z62: =W62-X62 -> 2.0022234e+08 | AA62: =IFERROR(W62/U62,"No se realizó gasto en este corte") -> No se realizó gasto en este corte | AB62: =IFERROR( IF(OR(AA62="",AA62=0), "No calculado", IF(AA62>1,"Costo eficiente: se está gastando menos de lo presupuestado", IF(AA62=1,"Costo según lo presupuestado", "Costo ineficiente: se está gastando más de lo presupuestado"))), "No calculado") -> Costo eficiente: se está gastando menos de lo presupuestado | AC62: =IFERROR(W62/X62,0) -> 1.0625 | AD62: =IF(OR(AC62="",AC62=0),"Sin Línea Base", IF(AC62>1,"Proyecto adelantado respecto al cronograma", IF(AC62=1,"Proyecto a tiempo según lo planificado", IF(AC62<1,"Proyecto atrasado con respecto al cronograma", "No calculado")))) -> Proyecto adelantado respecto al cronograma | AE62: =IFERROR(L62/AA62,0) -> 0 | AF62: =IFERROR(AE62-L62,0) -> -4004446789 | AG62: =VLOOKUP(Indicador!E63,[1]Diccionario!C$1:AC$150,27,0) -> https://growdatasas.sharepoint.com/:x:/r/sites/Gestiondocumental/Administrativa/GD/Financiera/_layouts/15/Doc.aspx?sourcedoc=%7B29DCF375-0847-4DAD-9B9A-9F9E84ABD4DE%7D&file=322.%20MINTRANSPORTE.xlsx&action=default&mobileredirect=true | AH62: 1 | AI62: 1
A63: 2024 | B63: Septiembre | C63: 3f6c4573-29db-ee11-8860-00155d681010 | D63: 45356.826 | E63: ERT- MT– DISPOSITIVOS IOT Y ANALÍTICA | F63: Mario Andres Pirachican Gil | G63: https://growdatasas.sharepoint.com/sites/pwa/ERT- MT– DISPOSITIVOS IOT Y ANALÍTICA | H63: ​Se propone prestar el servicio de asistencia técnica mediante la recolección, procesamiento y correlación de datos con capacidad de análisis, a través de una plataforma de soluciones basadas en IoT (internet de las cosas), que permita la visualización de indicadores específicos con el objetivo de mejorar la seguridad vial y trazabilidad de recorrido a través de la integración de dispositivos de georreferenciación en vehículos de transporte de carga. | I63: DATOS Y SISTEMAS DE INFORMACIÓN | J63: 0322 | K63: Postventa | L63: =VLOOKUP(E63,[1]Diccionario!C$2:AC$150,22,0) -> 4004446789 | M63: =VLOOKUP(E63,[1]Diccionario!C$2:AC$150,24,0) -> 45345 | N63: =VLOOKUP(E63,[1]Diccionario!C$2:AC$150,25,0) -> 45587 | O63: =VLOOKUP(E63,[1]Diccionario!C$2:AC$150,26,0) -> 7.97 | P63: =Q63-O63 -> 0.03 | Q63: =Q62+1 -> 8 | R63: 8 | S63: 0.9 | T63: 1 | W63: =IFERROR(T63*L63,0) -> 4004446789 | X63: =S63*L63 -> 3.6040021e+09 | Y63: =IFERROR(W63-U63,0) -> 4004446789 | Z63: =W63-X63 -> 4.0044468e+08 | AA63: =IFERROR(W63/U63,"No se realizó gasto en este corte") -> No se realizó gasto en este corte | AB63: =IFERROR( IF(OR(AA63="",AA63=0), "No calculado", IF(AA63>1,"Costo eficiente: se está gastando menos de lo presupuestado", IF(AA63=1,"Costo según lo presupuestado", "Costo ineficiente: se está gastando más de lo presupuestado"))), "No calculado") -> Costo eficiente: se está gastando menos de lo presupuestado | AC63: =IFERROR(W63/X63,0) -> 1.1111111 | AD63: =IF(OR(AC63="",AC63=0),"Sin Línea Base", IF(AC63>1,"Proyecto adelantado respecto al cronograma", IF(AC63=1,"Proyecto a tiempo según lo planificado", IF(AC63<1,"Proyecto atrasado con respecto al cronograma", "No calculado")))) -> Proyecto adelantado respecto al cronograma | AE63: =IFERROR(L63/AA63,0) -> 0 | AF63: =IFERROR(AE63-L63,0) -> -4004446789 | AG63: =VLOOKUP(Indicador!E64,[1]Diccionario!C$1:AC$150,27,0) -> https://growdatasas.sharepoint.com/:x:/r/sites/Gestiondocumental/Administrativa/GD/Financiera/_layouts/15/Doc.aspx?sourcedoc=%7B465AB503-754C-43E2-86C3-8E24183E3BBF%7D&file=090424%20324.%20RUNT%202.0%20-%20RUNT%20MDM.xlsx&action=default&mobileredirect=true | AH63: 1 | AI63: 1
A64: 2024 | B64: Marzo | C64: b325f473-91e8-ee11-b9dc-00155d68784b | D64: 45373.887 | E64: RUNT – DISEÑO,IMPLEMENTACION MDM | F64: Leidy Susana Ramirez Herrera | G64: https://growdatasas.sharepoint.com/sites/pwa/RUNT – DISEÑO,IMPLEMENTACION MDM | H64: ​Implementar el modelo de gestión de datos maestros y de referencia a partir del diseño y definición de la estrategia de las capacidades para que permita a la entidad estandarizar y tener una única visión de los datos transversales que se manejan en los diferentes procesos del RUNT. Con el objetivo de asegurar una correcta implementación de la solución de IBM Cloud Pak for Data proponemos la incorporación de una capa de servicios profesionales especializados en la plataforma. Con un alcance de tres registros maestros a saber: Registro Nacional Automotor RNA y el Registro de Personas Jurídicas RNPJ, Registro Nacional de Conductores. | I64: DATOS Y SISTEMAS DE INFORMACIÓN | J64: 0324 | K64: Activo.En Ejecución | L64: =VLOOKUP(E64,[1]Diccionario!C$2:AC$150,22,0) -> 372376516 | M64: =VLOOKUP(E64,[1]Diccionario!C$2:AC$150,24,0) -> 45352 | N64: =VLOOKUP(E64,[1]Diccionario!C$2:AC$150,25,0) -> 45534 | O64: =VLOOKUP(E64,[1]Diccionario!C$2:AC$150,26,0) -> 5.97 | P64: =Q64-O64 -> -4.97 | Q64: 1 | R64: 6 | S64: 0.2 | T64: 0.15 | W64: =IFERROR(T64*L64,0) -> 55856477 | X64: =S64*L64 -> 74475303 | Y64: =IFERROR(W64-U64,0) -> 55856477 | Z64: =W64-X64 -> -18618826 | AA64: =IFERROR(W64/U64,"No se realizó gasto en este corte") -> No se realizó gasto en este corte | AB64: =IFERROR( IF(OR(AA64="",AA64=0), "No calculado", IF(AA64>1,"Costo eficiente: se está gastando menos de lo presupuestado", IF(AA64=1,"Costo según lo presupuestado", "Costo ineficiente: se está gastando más de lo presupuestado"))), "No calculado") -> Costo eficiente: se está gastando menos de lo presupuestado | AC64: =IFERROR(W64/X64,0) -> 0.75 | AD64: =IF(OR(AC64="",AC64=0),"Sin Línea Base", IF(AC64>1,"Proyecto adelantado respecto al cronograma", IF(AC64=1,"Proyecto a tiempo según lo planificado", IF(AC64<1,"Proyecto atrasado con respecto al cronograma", "No calculado")))) -> Proyecto atrasado con respecto al cronograma | AE64: =IFERROR(L64/AA64,0) -> 0 | AF64: =IFERROR(AE64-L64,0) -> -372376516 | AG64: =VLOOKUP(Indicador!E65,[1]Diccionario!C$1:AC$150,27,0) -> https://growdatasas.sharepoint.com/:x:/r/sites/Gestiondocumental/Administrativa/GD/Financiera/_layouts/15/Doc.aspx?sourcedoc=%7B465AB503-754C-43E2-86C3-8E24183E3BBF%7D&file=090424%20324.%20RUNT%202.0%20-%20RUNT%20MDM.xlsx&action=default&mobileredirect=true | AH64: 1 | AI64: 1
A65: 2024 | B65: Abril | C65: b325f473-91e8-ee11-b9dc-00155d68784b | D65: 45373.887 | E65: RUNT – DISEÑO,IMPLEMENTACION MDM | F65: Leidy Susana Ramirez Herrera | G65: https://growdatasas.sharepoint.com/sites/pwa/RUNT – DISEÑO,IMPLEMENTACION MDM | H65: ​Implementar el modelo de gestión de datos maestros y de referencia a partir del diseño y definición de la estrategia de las capacidades para que permita a la entidad estandarizar y tener una única visión de los datos transversales que se manejan en los diferentes procesos del RUNT. Con el objetivo de asegurar una correcta implementación de la solución de IBM Cloud Pak for Data proponemos la incorporación de una capa de servicios profesionales especializados en la plataforma. Con un alcance de tres registros maestros a saber: Registro Nacional Automotor RNA y el Registro de Personas Jurídicas RNPJ, Registro Nacional de Conductores. | I65: DATOS Y SISTEMAS DE INFORMACIÓN | J65: 0324 | K65: Activo.En Ejecución | L65: =VLOOKUP(E65,[1]Diccionario!C$2:AC$150,22,0) -> 372376516 | M65: =VLOOKUP(E65,[1]Diccionario!C$2:AC$150,24,0) -> 45352 | N65: =VLOOKUP(E65,[1]Diccionario!C$2:AC$150,25,0) -> 45534 | O65: =VLOOKUP(E65,[1]Diccionario!C$2:AC$150,26,0) -> 5.97 | P65: =Q65-O65 -> -3.97 | Q65: 2 | R65: 6 | S65: 0.3 | T65: 0.2 | W65: =IFERROR(T65*L65,0) -> 74475303 | X65: =S65*L65 -> 1.1171295e+08 | Y65: =IFERROR(W65-U65,0) -> 74475303 | Z65: =W65-X65 -> -37237652 | AA65: =IFERROR(W65/U65,"No se realizó gasto en este corte") -> No se realizó gasto en este corte | AB65: =IFERROR( IF(OR(AA65="",AA65=0), "No calculado", IF(AA65>1,"Costo eficiente: se está gastando menos de lo presupuestado", IF(AA65=1,"Costo según lo presupuestado", "Costo ineficiente: se está gastando más de lo presupuestado"))), "No calculado") -> Costo eficiente: se está gastando menos de lo presupuestado | AC65: =IFERROR(W65/X65,0) -> 0.66666667 | AD65: =IF(OR(AC65="",AC65=0),"Sin Línea Base", IF(AC65>1,"Proyecto adelantado respecto al cronograma", IF(AC65=1,"Proyecto a tiempo según lo planificado", IF(AC65<1,"Proyecto atrasado con respecto al cronograma", "No calculado")))) -> Proyecto atrasado con respecto al cronograma | AE65: =IFERROR(L65/AA65,0) -> 0 | AF65: =IFERROR(AE65-L65,0) -> -372376516 | AG65: =VLOOKUP(Indicador!E66,[1]Diccionario!C$1:AC$150,27,0) -> https://growdatasas.sharepoint.com/:x:/r/sites/Gestiondocumental/Administrativa/GD/Financiera/_layouts/15/Doc.aspx?sourcedoc=%7B465AB503-754C-43E2-86C3-8E24183E3BBF%7D&file=090424%20324.%20RUNT%202.0%20-%20RUNT%20MDM.xlsx&action=default&mobileredirect=true | AH65: 1 | AI65: 1
A66: 2024 | B66: Mayo | C66: b325f473-91e8-ee11-b9dc-00155d68784b | D66: 45373.887 | E66: RUNT – DISEÑO,IMPLEMENTACION MDM | F66: Leidy Susana Ramirez Herrera | G66: https://growdatasas.sharepoint.com/sites/pwa/RUNT – DISEÑO,IMPLEMENTACION MDM | H66: ​Implementar el modelo de gestión de datos maestros y de referencia a partir del diseño y definición de la estrategia de las capacidades para que permita a la entidad estandarizar y tener una única visión de los datos transversales que se manejan en los diferentes procesos del RUNT. Con el objetivo de asegurar una correcta implementación de la solución de IBM Cloud Pak for Data proponemos la incorporación de una capa de servicios profesionales especializados en la plataforma. Con un alcance de tres registros maestros a saber: Registro Nacional Automotor RNA y el Registro de Personas Jurídicas RNPJ, Registro Nacional de Conductores. | I66: DATOS Y SISTEMAS DE INFORMACIÓN | J66: 0324 | K66: Activo.En Ejecución | L66: =VLOOKUP(E66,[1]Diccionario!C$2:AC$150,22,0) -> 372376516 | M66: =VLOOKUP(E66,[1]Diccionario!C$2:AC$150,24,0) -> 45352 | N66: =VLOOKUP(E66,[1]Diccionario!C$2:AC$150,25,0) -> 45534 | O66: =VLOOKUP(E66,[1]Diccionario!C$2:AC$150,26,0) -> 5.97 | P66: =Q66-O66 -> -2.97 | Q66: 3 | R66: 6 | S66: 0.5 | T66: 0.4 | W66: =IFERROR(T66*L66,0) -> 1.4895061e+08 | X66: =S66*L66 -> 186188258 | Y66: =IFERROR(W66-U66,0) -> 1.4895061e+08 | Z66: =W66-X66 -> -37237652 | AA66: =IFERROR(W66/U66,"No se realizó gasto en este corte") -> No se realizó gasto en este corte | AB66: =IFERROR( IF(OR(AA66="",AA66=0), "No calculado", IF(AA66>1,"Costo eficiente: se está gastando menos de lo presupuestado", IF(AA66=1,"Costo según lo presupuestado", "Costo ineficiente: se está gastando más de lo presupuestado"))), "No calculado") -> Costo eficiente: se está gastando menos de lo presupuestado | AC66: =IFERROR(W66/X66,0) -> 0.8 | AD66: =IF(OR(AC66="",AC66=0),"Sin Línea Base", IF(AC66>1,"Proyecto adelantado respecto al cronograma", IF(AC66=1,"Proyecto a tiempo según lo planificado", IF(AC66<1,"Proyecto atrasado con respecto al cronograma", "No calculado")))) -> Proyecto atrasado con respecto al cronograma | AE66: =IFERROR(L66/AA66,0) -> 0 | AF66: =IFERROR(AE66-L66,0) -> -372376516 | AG66: =VLOOKUP(Indicador!E67,[1]Diccionario!C$1:AC$150,27,0) -> https://growdatasas.sharepoint.com/:x:/r/sites/Gestiondocumental/Administrativa/GD/Financiera/_layouts/15/Doc.aspx?sourcedoc=%7B465AB503-754C-43E2-86C3-8E24183E3BBF%7D&file=090424%20324.%20RUNT%202.0%20-%20RUNT%20MDM.xlsx&action=default&mobileredirect=true | AH66: 1 | AI66: 1
A67: 2024 | B67: Junio | C67: b325f473-91e8-ee11-b9dc-00155d68784b | D67: 45373.887 | E67: RUNT – DISEÑO,IMPLEMENTACION MDM | F67: Leidy Susana Ramirez Herrera | G67: https://growdatasas.sharepoint.com/sites/pwa/RUNT – DISEÑO,IMPLEMENTACION MDM | H67: ​Implementar el modelo de gestión de datos maestros y de referencia a partir del diseño y definición de la estrategia de las capacidades para que permita a la entidad estandarizar y tener una única visión de los datos transversales que se manejan en los diferentes procesos del RUNT. Con el objetivo de asegurar una correcta implementación de la solución de IBM Cloud Pak for Data proponemos la incorporación de una capa de servicios profesionales especializados en la plataforma. Con un alcance de tres registros maestros a saber: Registro Nacional Automotor RNA y el Registro de Personas Jurídicas RNPJ, Registro Nacional de Conductores. | I67: DATOS Y SISTEMAS DE INFORMACIÓN | J67: 0324 | K67: Activo.En Ejecución | L67: =VLOOKUP(E67,[1]Diccionario!C$2:AC$150,22,0) -> 372376516 | M67: =VLOOKUP(E67,[1]Diccionario!C$2:AC$150,24,0) -> 45352 | N67: =VLOOKUP(E67,[1]Diccionario!C$2:AC$150,25,0) -> 45534 | O67: =VLOOKUP(E67,[1]Diccionario!C$2:AC$150,26,0) -> 5.97 | P67: =Q67-O67 -> -1.97 | Q67: 4 | R67: 6 | S67: 0.75 | T67: 0.7 | W67: =IFERROR(T67*L67,0) -> 2.6066356e+08 | X67: =S67*L67 -> 279282387 | Y67: =IFERROR(W67-U67,0) -> 2.6066356e+08 | Z67: =W67-X67 -> -18618826 | AA67: =IFERROR(W67/U67,"No se realizó gasto en este corte") -> No se realizó gasto en este corte | AB67: =IFERROR( IF(OR(AA67="",AA67=0), "No calculado", IF(AA67>1,"Costo eficiente: se está gastando menos de lo presupuestado", IF(AA67=1,"Costo según lo presupuestado", "Costo ineficiente: se está gastando más de lo presupuestado"))), "No calculado") -> Costo eficiente: se está gastando menos de lo presupuestado | AC67: =IFERROR(W67/X67,0) -> 0.93333333 | AD67: =IF(OR(AC67="",AC67=0),"Sin Línea Base", IF(AC67>1,"Proyecto adelantado respecto al cronograma", IF(AC67=1,"Proyecto a tiempo según lo planificado", IF(AC67<1,"Proyecto atrasado con respecto al cronograma", "No calculado")))) -> Proyecto atrasado con respecto al cronograma | AE67: =IFERROR(L67/AA67,0) -> 0 | AF67: =IFERROR(AE67-L67,0) -> -372376516 | AG67: =VLOOKUP(Indicador!E68,[1]Diccionario!C$1:AC$150,27,0) -> https://growdatasas.sharepoint.com/:x:/r/sites/Gestiondocumental/Administrativa/GD/Financiera/_layouts/15/Doc.aspx?sourcedoc=%7B465AB503-754C-43E2-86C3-8E24183E3BBF%7D&file=090424%20324.%20RUNT%202.0%20-%20RUNT%20MDM.xlsx&action=default&mobileredirect=true | AH67: 1 | AI67: 1
A68: 2024 | B68: Julio | C68: b325f473-91e8-ee11-b9dc-00155d68784b | D68: 45373.887 | E68: RUNT – DISEÑO,IMPLEMENTACION MDM | F68: Leidy Susana Ramirez Herrera | G68: https://growdatasas.sharepoint.com/sites/pwa/RUNT – DISEÑO,IMPLEMENTACION MDM | H68: ​Implementar el modelo de gestión de datos maestros y de referencia a partir del diseño y definición de la estrategia de las capacidades para que permita a la entidad estandarizar y tener una única visión de los datos transversales que se manejan en los diferentes procesos del RUNT. Con el objetivo de asegurar una correcta implementación de la solución de IBM Cloud Pak for Data proponemos la incorporación de una capa de servicios profesionales especializados en la plataforma. Con un alcance de tres registros maestros a saber: Registro Nacional Automotor RNA y el Registro de Personas Jurídicas RNPJ, Registro Nacional de Conductores. | I68: DATOS Y SISTEMAS DE INFORMACIÓN | J68: 0324 | K68: Activo.En Ejecución | L68: =VLOOKUP(E68,[1]Diccionario!C$2:AC$150,22,0) -> 372376516 | M68: =VLOOKUP(E68,[1]Diccionario!C$2:AC$150,24,0) -> 45352 | N68: =VLOOKUP(E68,[1]Diccionario!C$2:AC$150,25,0) -> 45534 | O68: =VLOOKUP(E68,[1]Diccionario!C$2:AC$150,26,0) -> 5.97 | P68: =Q68-O68 -> -0.97 | Q68: 5 | R68: 6 | S68: 0.8 | T68: 0.79 | W68: =IFERROR(T68*L68,0) -> 2.9417745e+08 | X68: =S68*L68 -> 2.9790121e+08 | Y68: =IFERROR(W68-U68,0) -> 2.9417745e+08 | Z68: =W68-X68 -> -3723765.2 | AA68: =IFERROR(W68/U68,"No se realizó gasto en este corte") -> No se realizó gasto en este corte | AB68: =IFERROR( IF(OR(AA68="",AA68=0), "No calculado", IF(AA68>1,"Costo eficiente: se está gastando menos de lo presupuestado", IF(AA68=1,"Costo según lo presupuestado", "Costo ineficiente: se está gastando más de lo presupuestado"))), "No calculado") -> Costo eficiente: se está gastando menos de lo presupuestado | AC68: =IFERROR(W68/X68,0) -> 0.9875 | AD68: =IF(OR(AC68="",AC68=0),"Sin Línea Base", IF(AC68>1,"Proyecto adelantado respecto al cronograma", IF(AC68=1,"Proyecto a tiempo según lo planificado", IF(AC68<1,"Proyecto atrasado con respecto al cronograma", "No calculado")))) -> Proyecto atrasado con respecto al cronograma | AE68: =IFERROR(L68/AA68,0) -> 0 | AF68: =IFERROR(AE68-L68,0) -> -372376516 | AG68: =VLOOKUP(Indicador!E69,[1]Diccionario!C$1:AC$150,27,0) -> https://growdatasas.sharepoint.com/:x:/r/sites/Gestiondocumental/Administrativa/GD/Financiera/_layouts/15/Doc.aspx?sourcedoc=%7B465AB503-754C-43E2-86C3-8E24183E3BBF%7D&file=090424%20324.%20RUNT%202.0%20-%20RUNT%20MDM.xlsx&action=default&mobileredirect=true | AH68: 1 | AI68: 1
A69: 2024 | B69: Agosto | C69: b325f473-91e8-ee11-b9dc-00155d68784b | D69: 45373.887 | E69: RUNT – DISEÑO,IMPLEMENTACION MDM | F69: Leidy Susana Ramirez Herrera | G69: https://growdatasas.sharepoint.com/sites/pwa/RUNT – DISEÑO,IMPLEMENTACION MDM | H69: ​Implementar el modelo de gestión de datos maestros y de referencia a partir del diseño y definición de la estrategia de las capacidades para que permita a la entidad estandarizar y tener una única visión de los datos transversales que se manejan en los diferentes procesos del RUNT. Con el objetivo de asegurar una correcta implementación de la solución de IBM Cloud Pak for Data proponemos la incorporación de una capa de servicios profesionales especializados en la plataforma. Con un alcance de tres registros maestros a saber: Registro Nacional Automotor RNA y el Registro de Personas Jurídicas RNPJ, Registro Nacional de Conductores. | I69: DATOS Y SISTEMAS DE INFORMACIÓN | J69: 0324 | K69: Activo.En Ejecución | L69: =VLOOKUP(E69,[1]Diccionario!C$2:AC$150,22,0) -> 372376516 | M69: =VLOOKUP(E69,[1]Diccionario!C$2:AC$150,24,0) -> 45352 | N69: =VLOOKUP(E69,[1]Diccionario!C$2:AC$150,25,0) -> 45534 | O69: =VLOOKUP(E69,[1]Diccionario!C$2:AC$150,26,0) -> 5.97 | P69: =Q69-O69 -> 0.03 | Q69: 6 | R69: 6 | S69: 1 | T69: 1 | W69: =IFERROR(T69*L69,0) -> 372376516 | X69: =S69*L69 -> 372376516 | Y69: =IFERROR(W69-U69,0) -> 372376516 | Z69: =W69-X69 -> 0 | AA69: =IFERROR(W69/U69,"No se realizó gasto en este corte") -> No se realizó gasto en este corte | AB69: =IFERROR( IF(OR(AA69="",AA69=0), "No calculado", IF(AA69>1,"Costo eficiente: se está gastando menos de lo presupuestado", IF(AA69=1,"Costo según lo presupuestado", "Costo ineficiente: se está gastando más de lo presupuestado"))), "No calculado") -> Costo eficiente: se está gastando menos de lo presupuestado | AC69: =IFERROR(W69/X69,0) -> 1 | AD69: =IF(OR(AC69="",AC69=0),"Sin Línea Base", IF(AC69>1,"Proyecto adelantado respecto al cronograma", IF(AC69=1,"Proyecto a tiempo según lo planificado", IF(AC69<1,"Proyecto atrasado con respecto al cronograma", "No calculado")))) -> Proyecto a tiempo según lo planificado | AE69: =IFERROR(L69/AA69,0) -> 0 | AF69: =IFERROR(AE69-L69,0) -> -372376516 | AG69: =VLOOKUP(Indicador!E70,[1]Diccionario!C$1:AC$150,27,0) -> https://growdatasas.sharepoint.com/:x:/r/sites/Gestiondocumental/Administrativa/GD/Financiera/_layouts/15/Doc.aspx?sourcedoc=%7B293F42A2-5CA4-4376-950C-5CBFEA13F436%7D&file=327.%20ALDESARROLLO%20-%20ICFES%20-%20SOSTENIBILIDAD.xlsx&action=default&mobileredirect=true | AH69: 1 | AI69: 1
A70: 2024 | B70: Marzo | C70: 7bad0cc0-6d01-ef11-b0c0-00155d68bf05 | D70: 45405.524 | E70: ALDESARROLLO - ICFES - SOSTENIBILIDAD | F70: Laura Johanna Jaramillo Soto | G70: https://growdatasas.sharepoint.com/sites/pwa/ALDESARROLLO - ICFES - SOSTENIBILIDAD | H70: CONTRATAR LA REALIZACIÓN DEL DISEÑO DE ESTRATEGIA Y POLÍTICADE SOSTENIBILIDAD-RESPONSABILIDAD SOCIAL E INFORME DE SOSTENIBILIDAD 2023 CON EL ESTÁNDAR GRI, CON MIRAS AL FORTALECIMIENTO INSTITUCIONAL, SU PROYECCIÓN A GRUPOS DE INTERÉS Y LA DISPOSICIÓN A LOS RETOS DE INTERNACIONALIZACIÓN, COMPROMISO SOCIAL Y AMBIENTAL DE LA ENTIDAD. SE REALIZA UN OTRO SI ACLARATORIO DONDE SE AJUSTE LA NOMENCLATURA ASIGNADA AL CONTRATO DE CP-PR-2024-161 A CP-PR-2024-161A | I70: CONSULTORÍA | J70: 0327 | K70: Activo.En Ejecución | L70: =VLOOKUP(E70,[1]Diccionario!C$2:AC$150,22,0) -> 1087776079 | M70: =VLOOKUP(E70,[1]Diccionario!C$2:AC$150,24,0) -> 45369 | N70: =VLOOKUP(E70,[1]Diccionario!C$2:AC$150,25,0) -> 45552 | O70: =VLOOKUP(E70,[1]Diccionario!C$2:AC$150,26,0) -> 5.97 | P70: =Q70-O70 -> -4.97 | Q70: 1 | R70: 6 | S70: 0.3 | T70: 0.25 | W70: =IFERROR(T70*L70,0) -> 2.7194402e+08 | X70: =S70*L70 -> 3.2633282e+08 | Y70: =IFERROR(W70-U70,0) -> 2.7194402e+08 | Z70: =W70-X70 -> -54388804 | AA70: =IFERROR(W70/U70,"No se realizó gasto en este corte") -> No se realizó gasto en este corte | AB70: =IFERROR( IF(OR(AA70="",AA70=0), "No calculado", IF(AA70>1,"Costo eficiente: se está gastando menos de lo presupuestado", IF(AA70=1,"Costo según lo presupuestado", "Costo ineficiente: se está gastando más de lo presupuestado"))), "No calculado") -> Costo eficiente: se está gastando menos de lo presupuestado | AC70: =IFERROR(W70/X70,0) -> 0.83333333 | AD70: =IF(OR(AC70="",AC70=0),"Sin Línea Base", IF(AC70>1,"Proyecto adelantado respecto al cronograma", IF(AC70=1,"Proyecto a tiempo según lo planificado", IF(AC70<1,"Proyecto atrasado con respecto al cronograma", "No calculado")))) -> Proyecto atrasado con respecto al cronograma | AE70: =IFERROR(L70/AA70,0) -> 0 | AF70: =IFERROR(AE70-L70,0) -> -1087776079 | AG70: =VLOOKUP(Indicador!E71,[1]Diccionario!C$1:AC$150,27,0) -> https://growdatasas.sharepoint.com/:x:/r/sites/Gestiondocumental/Administrativa/GD/Financiera/_layouts/15/Doc.aspx?sourcedoc=%7B293F42A2-5CA4-4376-950C-5CBFEA13F436%7D&file=327.%20ALDESARROLLO%20-%20ICFES%20-%20SOSTENIBILIDAD.xlsx&action=default&mobileredirect=true | AH70: 1 | AI70: 1
A71: 2024 | B71: Abril | C71: 7bad0cc0-6d01-ef11-b0c0-00155d68bf05 | D71: 45405.524 | E71: ALDESARROLLO - ICFES - SOSTENIBILIDAD | F71: Laura Johanna Jaramillo Soto | G71: https://growdatasas.sharepoint.com/sites/pwa/ALDESARROLLO - ICFES - SOSTENIBILIDAD | H71: CONTRATAR LA REALIZACIÓN DEL DISEÑO DE ESTRATEGIA Y POLÍTICADE SOSTENIBILIDAD-RESPONSABILIDAD SOCIAL E INFORME DE SOSTENIBILIDAD 2023 CON EL ESTÁNDAR GRI, CON MIRAS AL FORTALECIMIENTO INSTITUCIONAL, SU PROYECCIÓN A GRUPOS DE INTERÉS Y LA DISPOSICIÓN A LOS RETOS DE INTERNACIONALIZACIÓN, COMPROMISO SOCIAL Y AMBIENTAL DE LA ENTIDAD. SE REALIZA UN OTRO SI ACLARATORIO DONDE SE AJUSTE LA NOMENCLATURA ASIGNADA AL CONTRATO DE CP-PR-2024-161 A CP-PR-2024-161A | I71: CONSULTORÍA | J71: 0327 | K71: Activo.En Ejecución | L71: =VLOOKUP(E71,[1]Diccionario!C$2:AC$150,22,0) -> 1087776079 | M71: =VLOOKUP(E71,[1]Diccionario!C$2:AC$150,24,0) -> 45369 | N71: =VLOOKUP(E71,[1]Diccionario!C$2:AC$150,25,0) -> 45552 | O71: =VLOOKUP(E71,[1]Diccionario!C$2:AC$150,26,0) -> 5.97 | P71: =Q71-O71 -> -3.97 | Q71: 2 | R71: 6 | S71: 0.45 | T71: 0.45 | W71: =IFERROR(T71*L71,0) -> 4.8949924e+08 | X71: =S71*L71 -> 4.8949924e+08 | Y71: =IFERROR(W71-U71,0) -> 4.8949924e+08 | Z71: =W71-X71 -> 0 | AA71: =IFERROR(W71/U71,"No se realizó gasto en este corte") -> No se realizó gasto en este corte | AB71: =IFERROR( IF(OR(AA71="",AA71=0), "No calculado", IF(AA71>1,"Costo eficiente: se está gastando menos de lo presupuestado", IF(AA71=1,"Costo según lo presupuestado", "Costo ineficiente: se está gastando más de lo presupuestado"))), "No calculado") -> Costo eficiente: se está gastando menos de lo presupuestado | AC71: =IFERROR(W71/X71,0) -> 1 | AD71: =IF(OR(AC71="",AC71=0),"Sin Línea Base", IF(AC71>1,"Proyecto adelantado respecto al cronograma", IF(AC71=1,"Proyecto a tiempo según lo planificado", IF(AC71<1,"Proyecto atrasado con respecto al cronograma", "No calculado")))) -> Proyecto a tiempo según lo planificado | AE71: =IFERROR(L71/AA71,0) -> 0 | AF71: =IFERROR(AE71-L71,0) -> -1087776079 | AG71: =VLOOKUP(Indicador!E72,[1]Diccionario!C$1:AC$150,27,0) -> https://growdatasas.sharepoint.com/:x:/r/sites/Gestiondocumental/Administrativa/GD/Financiera/_layouts/15/Doc.aspx?sourcedoc=%7B293F42A2-5CA4-4376-950C-5CBFEA13F436%7D&file=327.%20ALDESARROLLO%20-%20ICFES%20-%20SOSTENIBILIDAD.xlsx&action=default&mobileredirect=true | AH71: 1 | AI71: 1
A72: 2024 | B72: Mayo | C72: 7bad0cc0-6d01-ef11-b0c0-00155d68bf05 | D72: 45405.524 | E72: ALDESARROLLO - ICFES - SOSTENIBILIDAD | F72: Laura Johanna Jaramillo Soto | G72: https://growdatasas.sharepoint.com/sites/pwa/ALDESARROLLO - ICFES - SOSTENIBILIDAD | H72: CONTRATAR LA REALIZACIÓN DEL DISEÑO DE ESTRATEGIA Y POLÍTICADE SOSTENIBILIDAD-RESPONSABILIDAD SOCIAL E INFORME DE SOSTENIBILIDAD 2023 CON EL ESTÁNDAR GRI, CON MIRAS AL FORTALECIMIENTO INSTITUCIONAL, SU PROYECCIÓN A GRUPOS DE INTERÉS Y LA DISPOSICIÓN A LOS RETOS DE INTERNACIONALIZACIÓN, COMPROMISO SOCIAL Y AMBIENTAL DE LA ENTIDAD. SE REALIZA UN OTRO SI ACLARATORIO DONDE SE AJUSTE LA NOMENCLATURA ASIGNADA AL CONTRATO DE CP-PR-2024-161 A CP-PR-2024-161A | I72: CONSULTORÍA | J72: 0327 | K72: Activo.En Ejecución | L72: =VLOOKUP(E72,[1]Diccionario!C$2:AC$150,22,0) -> 1087776079 | M72: =VLOOKUP(E72,[1]Diccionario!C$2:AC$150,24,0) -> 45369 | N72: =VLOOKUP(E72,[1]Diccionario!C$2:AC$150,25,0) -> 45552 | O72: =VLOOKUP(E72,[1]Diccionario!C$2:AC$150,26,0) -> 5.97 | P72: =Q72-O72 -> -2.97 | Q72: 3 | R72: 6 | S72: 0.5 | T72: 0.55 | W72: =IFERROR(T72*L72,0) -> 5.9827684e+08 | X72: =S72*L72 -> 5.4388804e+08 | Y72: =IFERROR(W72-U72,0) -> 5.9827684e+08 | Z72: =W72-X72 -> 54388804 | AA72: =IFERROR(W72/U72,"No se realizó gasto en este corte") -> No se realizó gasto en este corte | AB72: =IFERROR( IF(OR(AA72="",AA72=0), "No calculado", IF(AA72>1,"Costo eficiente: se está gastando menos de lo presupuestado", IF(AA72=1,"Costo según lo presupuestado", "Costo ineficiente: se está gastando más de lo presupuestado"))), "No calculado") -> Costo eficiente: se está gastando menos de lo presupuestado | AC72: =IFERROR(W72/X72,0) -> 1.1 | AD72: =IF(OR(AC72="",AC72=0),"Sin Línea Base", IF(AC72>1,"Proyecto adelantado respecto al cronograma", IF(AC72=1,"Proyecto a tiempo según lo planificado", IF(AC72<1,"Proyecto atrasado con respecto al cronograma", "No calculado")))) -> Proyecto adelantado respecto al cronograma | AE72: =IFERROR(L72/AA72,0) -> 0 | AF72: =IFERROR(AE72-L72,0) -> -1087776079 | AG72: =VLOOKUP(Indicador!E73,[1]Diccionario!C$1:AC$150,27,0) -> https://growdatasas.sharepoint.com/:x:/r/sites/Gestiondocumental/Administrativa/GD/Financiera/_layouts/15/Doc.aspx?sourcedoc=%7B293F42A2-5CA4-4376-950C-5CBFEA13F436%7D&file=327.%20ALDESARROLLO%20-%20ICFES%20-%20SOSTENIBILIDAD.xlsx&action=default&mobileredirect=true | AH72: 1 | AI72: 1
A73: 2024 | B73: Junio | C73: 7bad0cc0-6d01-ef11-b0c0-00155d68bf05 | D73: 45405.524 | E73: ALDESARROLLO - ICFES - SOSTENIBILIDAD | F73: Laura Johanna Jaramillo Soto | G73: https://growdatasas.sharepoint.com/sites/pwa/ALDESARROLLO - ICFES - SOSTENIBILIDAD | H73: CONTRATAR LA REALIZACIÓN DEL DISEÑO DE ESTRATEGIA Y POLÍTICADE SOSTENIBILIDAD-RESPONSABILIDAD SOCIAL E INFORME DE SOSTENIBILIDAD 2023 CON EL ESTÁNDAR GRI, CON MIRAS AL FORTALECIMIENTO INSTITUCIONAL, SU PROYECCIÓN A GRUPOS DE INTERÉS Y LA DISPOSICIÓN A LOS RETOS DE INTERNACIONALIZACIÓN, COMPROMISO SOCIAL Y AMBIENTAL DE LA ENTIDAD. SE REALIZA UN OTRO SI ACLARATORIO DONDE SE AJUSTE LA NOMENCLATURA ASIGNADA AL CONTRATO DE CP-PR-2024-161 A CP-PR-2024-161A | I73: CONSULTORÍA | J73: 0327 | K73: Activo.En Ejecución | L73: =VLOOKUP(E73,[1]Diccionario!C$2:AC$150,22,0) -> 1087776079 | M73: =VLOOKUP(E73,[1]Diccionario!C$2:AC$150,24,0) -> 45369 | N73: =VLOOKUP(E73,[1]Diccionario!C$2:AC$150,25,0) -> 45552 | O73: =VLOOKUP(E73,[1]Diccionario!C$2:AC$150,26,0) -> 5.97 | P73: =Q73-O73 -> -1.97 | Q73: 4 | R73: 6 | S73: 0.75 | T73: 0.77 | W73: =IFERROR(T73*L73,0) -> 8.3758758e+08 | X73: =S73*L73 -> 8.1583206e+08 | Y73: =IFERROR(W73-U73,0) -> 8.3758758e+08 | Z73: =W73-X73 -> 21755522 | AA73: =IFERROR(W73/U73,"No se realizó gasto en este corte") -> No se realizó gasto en este corte | AB73: =IFERROR( IF(OR(AA73="",AA73=0), "No calculado", IF(AA73>1,"Costo eficiente: se está gastando menos de lo presupuestado", IF(AA73=1,"Costo según lo presupuestado", "Costo ineficiente: se está gastando más de lo presupuestado"))), "No calculado") -> Costo eficiente: se está gastando menos de lo presupuestado | AC73: =IFERROR(W73/X73,0) -> 1.0266667 | AD73: =IF(OR(AC73="",AC73=0),"Sin Línea Base", IF(AC73>1,"Proyecto adelantado respecto al cronograma", IF(AC73=1,"Proyecto a tiempo según lo planificado", IF(AC73<1,"Proyecto atrasado con respecto al cronograma", "No calculado")))) -> Proyecto adelantado respecto al cronograma | AE73: =IFERROR(L73/AA73,0) -> 0 | AF73: =IFERROR(AE73-L73,0) -> -1087776079 | AG73: =VLOOKUP(Indicador!E74,[1]Diccionario!C$1:AC$150,27,0) -> https://growdatasas.sharepoint.com/:x:/r/sites/Gestiondocumental/Administrativa/GD/Financiera/_layouts/15/Doc.aspx?sourcedoc=%7B293F42A2-5CA4-4376-950C-5CBFEA13F436%7D&file=327.%20ALDESARROLLO%20-%20ICFES%20-%20SOSTENIBILIDAD.xlsx&action=default&mobileredirect=true | AH73: 1 | AI73: 1
A74: 2024 | B74: Julio | C74: 7bad0cc0-6d01-ef11-b0c0-00155d68bf05 | D74: 45405.524 | E74: ALDESARROLLO - ICFES - SOSTENIBILIDAD | F74: Laura Johanna Jaramillo Soto | G74: https://growdatasas.sharepoint.com/sites/pwa/ALDESARROLLO - ICFES - SOSTENIBILIDAD | H74: CONTRATAR LA REALIZACIÓN DEL DISEÑO DE ESTRATEGIA Y POLÍTICADE SOSTENIBILIDAD-RESPONSABILIDAD SOCIAL E INFORME DE SOSTENIBILIDAD 2023 CON EL ESTÁNDAR GRI, CON MIRAS AL FORTALECIMIENTO INSTITUCIONAL, SU PROYECCIÓN A GRUPOS DE INTERÉS Y LA DISPOSICIÓN A LOS RETOS DE INTERNACIONALIZACIÓN, COMPROMISO SOCIAL Y AMBIENTAL DE LA ENTIDAD. SE REALIZA UN OTRO SI ACLARATORIO DONDE SE AJUSTE LA NOMENCLATURA ASIGNADA AL CONTRATO DE CP-PR-2024-161 A CP-PR-2024-161A | I74: CONSULTORÍA | J74: 0327 | K74: Activo.En Ejecución | L74: =VLOOKUP(E74,[1]Diccionario!C$2:AC$150,22,0) -> 1087776079 | M74: =VLOOKUP(E74,[1]Diccionario!C$2:AC$150,24,0) -> 45369 | N74: =VLOOKUP(E74,[1]Diccionario!C$2:AC$150,25,0) -> 45552 | O74: =VLOOKUP(E74,[1]Diccionario!C$2:AC$150,26,0) -> 5.97 | P74: =Q74-O74 -> -0.97 | Q74: 5 | R74: 6 | S74: 0.8 | T74: 0.81 | W74: =IFERROR(T74*L74,0) -> 8.8109862e+08 | X74: =S74*L74 -> 8.7022086e+08 | Y74: =IFERROR(W74-U74,0) -> 8.8109862e+08 | Z74: =W74-X74 -> 10877761 | AA74: =IFERROR(W74/U74,"No se realizó gasto en este corte") -> No se realizó gasto en este corte | AB74: =IFERROR( IF(OR(AA74="",AA74=0), "No calculado", IF(AA74>1,"Costo eficiente: se está gastando menos de lo presupuestado", IF(AA74=1,"Costo según lo presupuestado", "Costo ineficiente: se está gastando más de lo presupuestado"))), "No calculado") -> Costo eficiente: se está gastando menos de lo presupuestado | AC74: =IFERROR(W74/X74,0) -> 1.0125 | AD74: =IF(OR(AC74="",AC74=0),"Sin Línea Base", IF(AC74>1,"Proyecto adelantado respecto al cronograma", IF(AC74=1,"Proyecto a tiempo según lo planificado", IF(AC74<1,"Proyecto atrasado con respecto al cronograma", "No calculado")))) -> Proyecto adelantado respecto al cronograma | AE74: =IFERROR(L74/AA74,0) -> 0 | AF74: =IFERROR(AE74-L74,0) -> -1087776079 | AG74: =VLOOKUP(Indicador!E75,[1]Diccionario!C$1:AC$150,27,0) -> https://growdatasas.sharepoint.com/:x:/r/sites/Gestiondocumental/Administrativa/GD/Financiera/_layouts/15/Doc.aspx?sourcedoc=%7B293F42A2-5CA4-4376-950C-5CBFEA13F436%7D&file=327.%20ALDESARROLLO%20-%20ICFES%20-%20SOSTENIBILIDAD.xlsx&action=default&mobileredirect=true | AH74: 1 | AI74: 1
A75: 2024 | B75: Agosto | C75: 7bad0cc0-6d01-ef11-b0c0-00155d68bf05 | D75: 45405.524 | E75: ALDESARROLLO - ICFES - SOSTENIBILIDAD | F75: Laura Johanna Jaramillo Soto | G75: https://growdatasas.sharepoint.com/sites/pwa/ALDESARROLLO - ICFES - SOSTENIBILIDAD | H75: CONTRATAR LA REALIZACIÓN DEL DISEÑO DE ESTRATEGIA Y POLÍTICADE SOSTENIBILIDAD-RESPONSABILIDAD SOCIAL E INFORME DE SOSTENIBILIDAD 2023 CON EL ESTÁNDAR GRI, CON MIRAS AL FORTALECIMIENTO INSTITUCIONAL, SU PROYECCIÓN A GRUPOS DE INTERÉS Y LA DISPOSICIÓN A LOS RETOS DE INTERNACIONALIZACIÓN, COMPROMISO SOCIAL Y AMBIENTAL DE LA ENTIDAD. SE REALIZA UN OTRO SI ACLARATORIO DONDE SE AJUSTE LA NOMENCLATURA ASIGNADA AL CONTRATO DE CP-PR-2024-161 A CP-PR-2024-161A | I75: CONSULTORÍA | J75: 0327 | K75: Activo.En Ejecución | L75: =VLOOKUP(E75,[1]Diccionario!C$2:AC$150,22,0) -> 1087776079 | M75: =VLOOKUP(E75,[1]Diccionario!C$2:AC$150,24,0) -> 45369 | N75: =VLOOKUP(E75,[1]Diccionario!C$2:AC$150,25,0) -> 45552 | O75: =VLOOKUP(E75,[1]Diccionario!C$2:AC$150,26,0) -> 5.97 | P75: =Q75-O75 -> 0.03 | Q75: 6 | R75: 6 | S75: 1 | T75: 1 | W75: =IFERROR(T75*L75,0) -> 1087776079 | X75: =S75*L75 -> 1087776079 | Y75: =IFERROR(W75-U75,0) -> 1087776079 | Z75: =W75-X75 -> 0 | AA75: =IFERROR(W75/U75,"No se realizó gasto en este corte") -> No se realizó gasto en este corte | AB75: =IFERROR( IF(OR(AA75="",AA75=0), "No calculado", IF(AA75>1,"Costo eficiente: se está gastando menos de lo presupuestado", IF(AA75=1,"Costo según lo presupuestado", "Costo ineficiente: se está gastando más de lo presupuestado"))), "No calculado") -> Costo eficiente: se está gastando menos de lo presupuestado | AC75: =IFERROR(W75/X75,0) -> 1 | AD75: =IF(OR(AC75="",AC75=0),"Sin Línea Base", IF(AC75>1,"Proyecto adelantado respecto al cronograma", IF(AC75=1,"Proyecto a tiempo según lo planificado", IF(AC75<1,"Proyecto atrasado con respecto al cronograma", "No calculado")))) -> Proyecto a tiempo según lo planificado | AE75: =IFERROR(L75/AA75,0) -> 0 | AF75: =IFERROR(AE75-L75,0) -> -1087776079 | AG75: =VLOOKUP(Indicador!E76,[1]Diccionario!C$1:AC$150,27,0) -> https://growdatasas.sharepoint.com/:x:/r/sites/Gestiondocumental/Administrativa/GD/Financiera/_layouts/15/Doc.aspx?sourcedoc=%7BB89BD188-BEAD-4E84-BC3B-FF43B34DCCB0%7D&file=326.%20ICFES%20-%20FABRICA%20DE%20SOFTWARE%20PRUEBAS.xlsx&action=default&mobileredirect=true | AH75: 1 | AI75: 1
A76: 2024 | B76: Abril | C76: 378e9b3a-aa01-ef11-88ac-00155d682343 | D76: 45405.824 | E76: EMTEL - ICFES - FABRICA | F76: Leidy Susana Ramirez Herrera | G76: https://growdatasas.sharepoint.com/sites/pwa/EMTEL - ICFES - FABRICA | H76: Prestación de servicios de Fábrica de Software para los proyectos de transformación digital del ICFES.Prestación de servicios de pruebas funcionales, no funcionales por demanda y aseguramiento de calidad asociado a las soluciones tecnológicas definidas para el Instituto Colombiano para la Evaluación de la Educación – ICFES. | I76: DATOS Y SISTEMAS DE INFORMACIÓN | J76: 0326 | K76: Activo.En Cierre | L76: =VLOOKUP(E76,[1]Diccionario!C$2:AC$150,22,0) -> 1566562163 | M76: =VLOOKUP(E76,[1]Diccionario!C$2:AC$150,24,0) -> 45402 | N76: =VLOOKUP(E76,[1]Diccionario!C$2:AC$150,25,0) -> 45656 | O76: =VLOOKUP(E76,[1]Diccionario!C$2:AC$150,26,0) -> 8.33 | P76: =Q76-O76 -> -7.33 | Q76: 1 | R76: 8 | S76: 0.1 | T76: 0.12 | W76: =IFERROR(T76*L76,0) -> 1.8798746e+08 | X76: =S76*L76 -> 1.5665622e+08 | Y76: =IFERROR(W76-U76,0) -> 1.8798746e+08 | Z76: =W76-X76 -> 31331243 | AA76: =IFERROR(W76/U76,"No se realizó gasto en este corte") -> No se realizó gasto en este corte | AB76: =IFERROR( IF(OR(AA76="",AA76=0), "No calculado", IF(AA76>1,"Costo eficiente: se está gastando menos de lo presupuestado", IF(AA76=1,"Costo según lo presupuestado", "Costo ineficiente: se está gastando más de lo presupuestado"))), "No calculado") -> Costo eficiente: se está gastando menos de lo presupuestado | AC76: =IFERROR(W76/X76,0) -> 1.2 | AD76: =IF(OR(AC76="",AC76=0),"Sin Línea Base", IF(AC76>1,"Proyecto adelantado respecto al cronograma", IF(AC76=1,"Proyecto a tiempo según lo planificado", IF(AC76<1,"Proyecto atrasado con respecto al cronograma", "No calculado")))) -> Proyecto adelantado respecto al cronograma | AE76: =IFERROR(L76/AA76,0) -> 0 | AF76: =IFERROR(AE76-L76,0) -> -1566562163 | AG76: =VLOOKUP(Indicador!E78,[1]Diccionario!C$1:AC$150,27,0) -> https://growdatasas.sharepoint.com/:x:/r/sites/Gestiondocumental/Administrativa/GD/Financiera/_layouts/15/Doc.aspx?sourcedoc=%7BB89BD188-BEAD-4E84-BC3B-FF43B34DCCB0%7D&file=326.%20ICFES%20-%20FABRICA%20DE%20SOFTWARE%20PRUEBAS.xlsx&action=default&mobileredirect=true | AH76: 1 | AI76: 1
A77: 2024 | B77: Mayo | C77: 378e9b3a-aa01-ef11-88ac-00155d682343 | D77: 45405.824 | E77: EMTEL - ICFES - FABRICA | F77: Leidy Susana Ramirez Herrera | G77: https://growdatasas.sharepoint.com/sites/pwa/EMTEL - ICFES - FABRICA | H77: Prestación de servicios de Fábrica de Software para los proyectos de transformación digital del ICFES.Prestación de servicios de pruebas funcionales, no funcionales por demanda y aseguramiento de calidad asociado a las soluciones tecnológicas definidas para el Instituto Colombiano para la Evaluación de la Educación – ICFES. | I77: DATOS Y SISTEMAS DE INFORMACIÓN | J77: 0326 | K77: Activo.En Cierre | L77: =VLOOKUP(E77,[1]Diccionario!C$2:AC$150,22,0) -> 1566562163 | M77: =VLOOKUP(E77,[1]Diccionario!C$2:AC$150,24,0) -> 45402 | N77: =VLOOKUP(E77,[1]Diccionario!C$2:AC$150,25,0) -> 45656 | O77: =VLOOKUP(E77,[1]Diccionario!C$2:AC$150,26,0) -> 8.33 | P77: =Q77-O77 -> -6.33 | Q77: 2 | R77: 8 | S77: 0.2 | T77: 0.25 | W77: =IFERROR(T77*L77,0) -> 3.9164054e+08 | X77: =S77*L77 -> 3.1331243e+08 | Y77: =IFERROR(W77-U77,0) -> 3.9164054e+08 | Z77: =W77-X77 -> 78328108 | AA77: =IFERROR(W77/U77,"No se realizó gasto en este corte") -> No se realizó gasto en este corte | AB77: =IFERROR( IF(OR(AA77="",AA77=0), "No calculado", IF(AA77>1,"Costo eficiente: se está gastando menos de lo presupuestado", IF(AA77=1,"Costo según lo presupuestado", "Costo ineficiente: se está gastando más de lo presupuestado"))), "No calculado") -> Costo eficiente: se está gastando menos de lo presupuestado | AC77: =IFERROR(W77/X77,0) -> 1.25 | AD77: =IF(OR(AC77="",AC77=0),"Sin Línea Base", IF(AC77>1,"Proyecto adelantado respecto al cronograma", IF(AC77=1,"Proyecto a tiempo según lo planificado", IF(AC77<1,"Proyecto atrasado con respecto al cronograma", "No calculado")))) -> Proyecto adelantado respecto al cronograma | AE77: =IFERROR(L77/AA77,0) -> 0 | AF77: =IFERROR(AE77-L77,0) -> -1566562163 | AG77: =VLOOKUP(Indicador!E79,[1]Diccionario!C$1:AC$150,27,0) -> https://growdatasas.sharepoint.com/:x:/r/sites/Gestiondocumental/Administrativa/GD/Financiera/_layouts/15/Doc.aspx?sourcedoc=%7BB89BD188-BEAD-4E84-BC3B-FF43B34DCCB0%7D&file=326.%20ICFES%20-%20FABRICA%20DE%20SOFTWARE%20PRUEBAS.xlsx&action=default&mobileredirect=true | AH77: 1 | AI77: 1
A78: 2024 | B78: Junio | C78: 378e9b3a-aa01-ef11-88ac-00155d682343 | D78: 45405.824 | E78: EMTEL - ICFES - FABRICA | F78: Leidy Susana Ramirez Herrera | G78: https://growdatasas.sharepoint.com/sites/pwa/EMTEL - ICFES - FABRICA | H78: Prestación de servicios de Fábrica de Software para los proyectos de transformación digital del ICFES.Prestación de servicios de pruebas funcionales, no funcionales por demanda y aseguramiento de calidad asociado a las soluciones tecnológicas definidas para el Instituto Colombiano para la Evaluación de la Educación – ICFES. | I78: DATOS Y SISTEMAS DE INFORMACIÓN | J78: 0326 | K78: Activo.En Cierre | L78: =VLOOKUP(E78,[1]Diccionario!C$2:AC$150,22,0) -> 1566562163 | M78: =VLOOKUP(E78,[1]Diccionario!C$2:AC$150,24,0) -> 45402 | N78: =VLOOKUP(E78,[1]Diccionario!C$2:AC$150,25,0) -> 45656 | O78: =VLOOKUP(E78,[1]Diccionario!C$2:AC$150,26,0) -> 8.33 | P78: =Q78-O78 -> -5.33 | Q78: 3 | R78: 8 | S78: 0.3 | T78: 0.32 | W78: =IFERROR(T78*L78,0) -> 5.0129989e+08 | X78: =S78*L78 -> 4.6996865e+08 | Y78: =IFERROR(W78-U78,0) -> 5.0129989e+08 | Z78: =W78-X78 -> 31331243 | AA78: =IFERROR(W78/U78,"No se realizó gasto en este corte") -> No se realizó gasto en este corte | AB78: =IFERROR( IF(OR(AA78="",AA78=0), "No calculado", IF(AA78>1,"Costo eficiente: se está gastando menos de lo presupuestado", IF(AA78=1,"Costo según lo presupuestado", "Costo ineficiente: se está gastando más de lo presupuestado"))), "No calculado") -> Costo eficiente: se está gastando menos de lo presupuestado | AC78: =IFERROR(W78/X78,0) -> 1.0666667 | AD78: =IF(OR(AC78="",AC78=0),"Sin Línea Base", IF(AC78>1,"Proyecto adelantado respecto al cronograma", IF(AC78=1,"Proyecto a tiempo según lo planificado", IF(AC78<1,"Proyecto atrasado con respecto al cronograma", "No calculado")))) -> Proyecto adelantado respecto al cronograma | AE78: =IFERROR(L78/AA78,0) -> 0 | AF78: =IFERROR(AE78-L78,0) -> -1566562163 | AG78: =VLOOKUP(Indicador!E80,[1]Diccionario!C$1:AC$150,27,0) -> https://growdatasas.sharepoint.com/:x:/r/sites/Gestiondocumental/Administrativa/GD/Financiera/_layouts/15/Doc.aspx?sourcedoc=%7BB89BD188-BEAD-4E84-BC3B-FF43B34DCCB0%7D&file=326.%20ICFES%20-%20FABRICA%20DE%20SOFTWARE%20PRUEBAS.xlsx&action=default&mobileredirect=true | AH78: 1 | AI78: 1
A79: 2024 | B79: Julio | C79: 378e9b3a-aa01-ef11-88ac-00155d682343 | D79: 45405.824 | E79: EMTEL - ICFES - FABRICA | F79: Leidy Susana Ramirez Herrera | G79: https://growdatasas.sharepoint.com/sites/pwa/EMTEL - ICFES - FABRICA | H79: Prestación de servicios de Fábrica de Software para los proyectos de transformación digital del ICFES.Prestación de servicios de pruebas funcionales, no funcionales por demanda y aseguramiento de calidad asociado a las soluciones tecnológicas definidas para el Instituto Colombiano para la Evaluación de la Educación – ICFES. | I79: DATOS Y SISTEMAS DE INFORMACIÓN | J79: 0326 | K79: Activo.En Cierre | L79: =VLOOKUP(E79,[1]Diccionario!C$2:AC$150,22,0) -> 1566562163 | M79: =VLOOKUP(E79,[1]Diccionario!C$2:AC$150,24,0) -> 45402 | N79: =VLOOKUP(E79,[1]Diccionario!C$2:AC$150,25,0) -> 45656 | O79: =VLOOKUP(E79,[1]Diccionario!C$2:AC$150,26,0) -> 8.33 | P79: =Q79-O79 -> -4.33 | Q79: 4 | R79: 8 | S79: 0.45 | T79: 0.42 | W79: =IFERROR(T79*L79,0) -> 6.5795611e+08 | X79: =S79*L79 -> 7.0495297e+08 | Y79: =IFERROR(W79-U79,0) -> 6.5795611e+08 | Z79: =W79-X79 -> -46996865 | AA79: =IFERROR(W79/U79,"No se realizó gasto en este corte") -> No se realizó gasto en este corte | AB79: =IFERROR( IF(OR(AA79="",AA79=0), "No calculado", IF(AA79>1,"Costo eficiente: se está gastando menos de lo presupuestado", IF(AA79=1,"Costo según lo presupuestado", "Costo ineficiente: se está gastando más de lo presupuestado"))), "No calculado") -> Costo eficiente: se está gastando menos de lo presupuestado | AC79: =IFERROR(W79/X79,0) -> 0.93333333 | AD79: =IF(OR(AC79="",AC79=0),"Sin Línea Base", IF(AC79>1,"Proyecto adelantado respecto al cronograma", IF(AC79=1,"Proyecto a tiempo según lo planificado", IF(AC79<1,"Proyecto atrasado con respecto al cronograma", "No calculado")))) -> Proyecto atrasado con respecto al cronograma | AE79: =IFERROR(L79/AA79,0) -> 0 | AF79: =IFERROR(AE79-L79,0) -> -1566562163 | AG79: =VLOOKUP(Indicador!E81,[1]Diccionario!C$1:AC$150,27,0) -> https://growdatasas.sharepoint.com/:x:/r/sites/Gestiondocumental/Administrativa/GD/Financiera/_layouts/15/Doc.aspx?sourcedoc=%7BB89BD188-BEAD-4E84-BC3B-FF43B34DCCB0%7D&file=326.%20ICFES%20-%20FABRICA%20DE%20SOFTWARE%20PRUEBAS.xlsx&action=default&mobileredirect=true | AH79: 1 | AI79: 1
A80: 2024 | B80: Agosto | C80: 378e9b3a-aa01-ef11-88ac-00155d682343 | D80: 45405.824 | E80: EMTEL - ICFES - FABRICA | F80: Leidy Susana Ramirez Herrera | G80: https://growdatasas.sharepoint.com/sites/pwa/EMTEL - ICFES - FABRICA | H80: Prestación de servicios de Fábrica de Software para los proyectos de transformación digital del ICFES.Prestación de servicios de pruebas funcionales, no funcionales por demanda y aseguramiento de calidad asociado a las soluciones tecnológicas definidas para el Instituto Colombiano para la Evaluación de la Educación – ICFES. | I80: DATOS Y SISTEMAS DE INFORMACIÓN | J80: 0326 | K80: Activo.En Cierre | L80: =VLOOKUP(E80,[1]Diccionario!C$2:AC$150,22,0) -> 1566562163 | M80: =VLOOKUP(E80,[1]Diccionario!C$2:AC$150,24,0) -> 45402 | N80: =VLOOKUP(E80,[1]Diccionario!C$2:AC$150,25,0) -> 45656 | O80: =VLOOKUP(E80,[1]Diccionario!C$2:AC$150,26,0) -> 8.33 | P80: =Q80-O80 -> -3.33 | Q80: 5 | R80: 8 | S80: 0.55 | T80: 0.56 | W80: =IFERROR(T80*L80,0) -> 8.7727481e+08 | X80: =S80*L80 -> 8.6160919e+08 | Y80: =IFERROR(W80-U80,0) -> 8.7727481e+08 | Z80: =W80-X80 -> 15665622 | AA80: =IFERROR(W80/U80,"No se realizó gasto en este corte") -> No se realizó gasto en este corte | AB80: =IFERROR( IF(OR(AA80="",AA80=0), "No calculado", IF(AA80>1,"Costo eficiente: se está gastando menos de lo presupuestado", IF(AA80=1,"Costo según lo presupuestado", "Costo ineficiente: se está gastando más de lo presupuestado"))), "No calculado") -> Costo eficiente: se está gastando menos de lo presupuestado | AC80: =IFERROR(W80/X80,0) -> 1.0181818 | AD80: =IF(OR(AC80="",AC80=0),"Sin Línea Base", IF(AC80>1,"Proyecto adelantado respecto al cronograma", IF(AC80=1,"Proyecto a tiempo según lo planificado", IF(AC80<1,"Proyecto atrasado con respecto al cronograma", "No calculado")))) -> Proyecto adelantado respecto al cronograma | AE80: =IFERROR(L80/AA80,0) -> 0 | AF80: =IFERROR(AE80-L80,0) -> -1566562163 | AG80: =VLOOKUP(Indicador!E82,[1]Diccionario!C$1:AC$150,27,0) -> https://growdatasas.sharepoint.com/:x:/r/sites/Gestiondocumental/Administrativa/GD/Financiera/_layouts/15/Doc.aspx?sourcedoc=%7BB89BD188-BEAD-4E84-BC3B-FF43B34DCCB0%7D&file=326.%20ICFES%20-%20FABRICA%20DE%20SOFTWARE%20PRUEBAS.xlsx&action=default&mobileredirect=true | AH80: 1 | AI80: 1
A81: 2024 | B81: Septiembre | C81: 378e9b3a-aa01-ef11-88ac-00155d682343 | D81: 45405.824 | E81: EMTEL - ICFES - FABRICA | F81: Leidy Susana Ramirez Herrera | G81: https://growdatasas.sharepoint.com/sites/pwa/EMTEL - ICFES - FABRICA | H81: Prestación de servicios de Fábrica de Software para los proyectos de transformación digital del ICFES.Prestación de servicios de pruebas funcionales, no funcionales por demanda y aseguramiento de calidad asociado a las soluciones tecnológicas definidas para el Instituto Colombiano para la Evaluación de la Educación – ICFES. | I81: DATOS Y SISTEMAS DE INFORMACIÓN | J81: 0326 | K81: Activo.En Cierre | L81: =VLOOKUP(E81,[1]Diccionario!C$2:AC$150,22,0) -> 1566562163 | M81: =VLOOKUP(E81,[1]Diccionario!C$2:AC$150,24,0) -> 45402 | N81: =VLOOKUP(E81,[1]Diccionario!C$2:AC$150,25,0) -> 45656 | O81: =VLOOKUP(E81,[1]Diccionario!C$2:AC$150,26,0) -> 8.33 | P81: =Q81-O81 -> -2.33 | Q81: 6 | R81: 8 | S81: 0.65 | T81: 0.67 | W81: =IFERROR(T81*L81,0) -> 1.0495966e+09 | X81: =S81*L81 -> 1.0182654e+09 | Y81: =IFERROR(W81-U81,0) -> 1.0495966e+09 | Z81: =W81-X81 -> 31331243 | AA81: =IFERROR(W81/U81,"No se realizó gasto en este corte") -> No se realizó gasto en este corte | AB81: =IFERROR( IF(OR(AA81="",AA81=0), "No calculado", IF(AA81>1,"Costo eficiente: se está gastando menos de lo presupuestado", IF(AA81=1,"Costo según lo presupuestado", "Costo ineficiente: se está gastando más de lo presupuestado"))), "No calculado") -> Costo eficiente: se está gastando menos de lo presupuestado | AC81: =IFERROR(W81/X81,0) -> 1.0307692 | AD81: =IF(OR(AC81="",AC81=0),"Sin Línea Base", IF(AC81>1,"Proyecto adelantado respecto al cronograma", IF(AC81=1,"Proyecto a tiempo según lo planificado", IF(AC81<1,"Proyecto atrasado con respecto al cronograma", "No calculado")))) -> Proyecto adelantado respecto al cronograma | AE81: =IFERROR(L81/AA81,0) -> 0 | AF81: =IFERROR(AE81-L81,0) -> -1566562163 | AG81: =VLOOKUP(Indicador!E83,[1]Diccionario!C$1:AC$150,27,0) -> https://growdatasas.sharepoint.com/:x:/r/sites/Gestiondocumental/Administrativa/GD/Financiera/_layouts/15/Doc.aspx?sourcedoc=%7BB89BD188-BEAD-4E84-BC3B-FF43B34DCCB0%7D&file=326.%20ICFES%20-%20FABRICA%20DE%20SOFTWARE%20PRUEBAS.xlsx&action=default&mobileredirect=true | AH81: 1 | AI81: 1
A82: 2024 | B82: Octubre | C82: 378e9b3a-aa01-ef11-88ac-00155d682343 | D82: 45405.824 | E82: EMTEL - ICFES - FABRICA | F82: Leidy Susana Ramirez Herrera | G82: https://growdatasas.sharepoint.com/sites/pwa/EMTEL - ICFES - FABRICA | H82: Prestación de servicios de Fábrica de Software para los proyectos de transformación digital del ICFES.Prestación de servicios de pruebas funcionales, no funcionales por demanda y aseguramiento de calidad asociado a las soluciones tecnológicas definidas para el Instituto Colombiano para la Evaluación de la Educación – ICFES. | I82: DATOS Y SISTEMAS DE INFORMACIÓN | J82: 0326 | K82: Activo.En Cierre | L82: =VLOOKUP(E82,[1]Diccionario!C$2:AC$150,22,0) -> 1566562163 | M82: =VLOOKUP(E82,[1]Diccionario!C$2:AC$150,24,0) -> 45402 | N82: =VLOOKUP(E82,[1]Diccionario!C$2:AC$150,25,0) -> 45656 | O82: =VLOOKUP(E82,[1]Diccionario!C$2:AC$150,26,0) -> 8.33 | P82: =Q82-O82 -> -1.33 | Q82: 7 | R82: 8 | S82: 0.85 | T82: 0.85 | W82: =IFERROR(T82*L82,0) -> 1.3315778e+09 | X82: =S82*L82 -> 1.3315778e+09 | Y82: =IFERROR(W82-U82,0) -> 1.3315778e+09 | Z82: =W82-X82 -> 0 | AA82: =IFERROR(W82/U82,"No se realizó gasto en este corte") -> No se realizó gasto en este corte | AB82: =IFERROR( IF(OR(AA82="",AA82=0), "No calculado", IF(AA82>1,"Costo eficiente: se está gastando menos de lo presupuestado", IF(AA82=1,"Costo según lo presupuestado", "Costo ineficiente: se está gastando más de lo presupuestado"))), "No calculado") -> Costo eficiente: se está gastando menos de lo presupuestado | AC82: =IFERROR(W82/X82,0) -> 1 | AD82: =IF(OR(AC82="",AC82=0),"Sin Línea Base", IF(AC82>1,"Proyecto adelantado respecto al cronograma", IF(AC82=1,"Proyecto a tiempo según lo planificado", IF(AC82<1,"Proyecto atrasado con respecto al cronograma", "No calculado")))) -> Proyecto a tiempo según lo planificado | AE82: =IFERROR(L82/AA82,0) -> 0 | AF82: =IFERROR(AE82-L82,0) -> -1566562163 | AG82: =VLOOKUP(Indicador!E84,[1]Diccionario!C$1:AC$150,27,0) -> https://growdatasas.sharepoint.com/sites/Gestiondocumental/Administrativa/GD/Financiera/Documentos%20compartidos/Forms/AllItems.aspx?id=%2Fsites%2FGestiondocumental%2FAdministrativa%2FGD%2FFinanciera%2FDocumentos%20compartidos%2FAN%C3%81LISIS%20FINANCIERO%2FPMO%20SEGUIMIENTO%20A%20PROYECTOS%2F328%2E%20INFOTIC%20%2D%20ICFES%20%2D%20PRUEBAS%20CSJ&viewid=8ba7db0b%2Dbb48%2D40cc%2Da532%2D9b5bc18760d5 | AH82: 1 | AI82: 1
A83: 2024 | B83: Noviembre | C83: 378e9b3a-aa01-ef11-88ac-00155d682343 | D83: 45405.824 | E83: EMTEL - ICFES - FABRICA | F83: Leidy Susana Ramirez Herrera | G83: https://growdatasas.sharepoint.com/sites/pwa/EMTEL - ICFES - FABRICA | H83: Prestación de servicios de Fábrica de Software para los proyectos de transformación digital del ICFES.Prestación de servicios de pruebas funcionales, no funcionales por demanda y aseguramiento de calidad asociado a las soluciones tecnológicas definidas para el Instituto Colombiano para la Evaluación de la Educación – ICFES. | I83: DATOS Y SISTEMAS DE INFORMACIÓN | J83: 0326 | K83: Activo.En Cierre | L83: =VLOOKUP(E83,[1]Diccionario!C$2:AC$150,22,0) -> 1566562163 | M83: =VLOOKUP(E83,[1]Diccionario!C$2:AC$150,24,0) -> 45402 | N83: =VLOOKUP(E83,[1]Diccionario!C$2:AC$150,25,0) -> 45656 | O83: =VLOOKUP(E83,[1]Diccionario!C$2:AC$150,26,0) -> 8.33 | P83: =Q83-O83 -> -0.33 | Q83: 8 | R83: 8 | S83: 1 | T83: 1 | W83: =IFERROR(T83*L83,0) -> 1566562163 | X83: =S83*L83 -> 1566562163 | Y83: =IFERROR(W83-U83,0) -> 1566562163 | Z83: =W83-X83 -> 0 | AA83: =IFERROR(W83/U83,"No se realizó gasto en este corte") -> No se realizó gasto en este corte | AB83: =IFERROR( IF(OR(AA83="",AA83=0), "No calculado", IF(AA83>1,"Costo eficiente: se está gastando menos de lo presupuestado", IF(AA83=1,"Costo según lo presupuestado", "Costo ineficiente: se está gastando más de lo presupuestado"))), "No calculado") -> Costo eficiente: se está gastando menos de lo presupuestado | AC83: =IFERROR(W83/X83,0) -> 1 | AD83: =IF(OR(AC83="",AC83=0),"Sin Línea Base", IF(AC83>1,"Proyecto adelantado respecto al cronograma", IF(AC83=1,"Proyecto a tiempo según lo planificado", IF(AC83<1,"Proyecto atrasado con respecto al cronograma", "No calculado")))) -> Proyecto a tiempo según lo planificado | AE83: =IFERROR(L83/AA83,0) -> 0 | AF83: =IFERROR(AE83-L83,0) -> -1566562163 | AG83: =VLOOKUP(Indicador!E85,[1]Diccionario!C$1:AC$150,27,0) -> https://growdatasas.sharepoint.com/sites/Gestiondocumental/Administrativa/GD/Financiera/Documentos%20compartidos/Forms/AllItems.aspx?id=%2Fsites%2FGestiondocumental%2FAdministrativa%2FGD%2FFinanciera%2FDocumentos%20compartidos%2FAN%C3%81LISIS%20FINANCIERO%2FPMO%20SEGUIMIENTO%20A%20PROYECTOS%2F328%2E%20INFOTIC%20%2D%20ICFES%20%2D%20PRUEBAS%20CSJ&viewid=8ba7db0b%2Dbb48%2D40cc%2Da532%2D9b5bc18760d5 | AH83: 1 | AI83: 1
A84: 2024 | B84: Mayo | C84: 2f048f31-0b0f-ef11-9ac8-00155d68220c | D84: 45422.85 | E84: INFOTIC - ICFES - PRUEBAS CSJ | F84: Janeth Annelise Araujo Ramos | G84: https://growdatasas.sharepoint.com/sites/pwa/INFOTIC - ICFES - PRUEBAS CSJ | H84: APLICACIÓN ELECTRÓNICA DEL EXAMEN PARA EJERCER LA PROFESIÓN DE ABOGADO A REALIZARSE EN LA VIGENCIA 2024SUMINISTRO DE MESA DE SERVICIO CON COBERTURA NACIONAL | I84: TI | J84: 0328 | K84: Activo.En Cierre | L84: =VLOOKUP(E84,[1]Diccionario!C$2:AC$150,22,0) -> 830180856 | M84: =VLOOKUP(E84,[1]Diccionario!C$2:AC$150,24,0) -> 45414 | N84: =VLOOKUP(E84,[1]Diccionario!C$2:AC$150,25,0) -> 45596 | O84: =VLOOKUP(E84,[1]Diccionario!C$2:AC$150,26,0) -> 5.97 | P84: =Q84-O84 -> 17.03 | Q84: =DATEDIF(M84,TODAY(),"m") -> 23 | R84: 6 | S84: 0.2 | T84: 0.15 | W84: =IFERROR(T84*L84,0) -> 1.2452713e+08 | X84: =S84*L84 -> 1.6603617e+08 | Y84: =IFERROR(W84-U84,0) -> 1.2452713e+08 | Z84: =W84-X84 -> -41509043 | AA84: =IFERROR(W84/U84,"No se realizó gasto en este corte") -> No se realizó gasto en este corte | AB84: =IFERROR( IF(OR(AA84="",AA84=0), "No calculado", IF(AA84>1,"Costo eficiente: se está gastando menos de lo presupuestado", IF(AA84=1,"Costo según lo presupuestado", "Costo ineficiente: se está gastando más de lo presupuestado"))), "No calculado") -> Costo eficiente: se está gastando menos de lo presupuestado | AC84: =IFERROR(W84/X84,0) -> 0.75 | AD84: =IF(OR(AC84="",AC84=0),"Sin Línea Base", IF(AC84>1,"Proyecto adelantado respecto al cronograma", IF(AC84=1,"Proyecto a tiempo según lo planificado", IF(AC84<1,"Proyecto atrasado con respecto al cronograma", "No calculado")))) -> Proyecto atrasado con respecto al cronograma | AE84: =IFERROR(L84/AA84,0) -> 0 | AF84: =IFERROR(AE84-L84,0) -> -830180856 | AG84: =VLOOKUP(Indicador!E91,[1]Diccionario!C$1:AC$150,27,0) -> https://growdatasas.sharepoint.com/:x:/r/sites/Gestiondocumental/Administrativa/GD/Financiera/_layouts/15/Doc.aspx?sourcedoc=%7B0974E3E6-B78B-4C29-8F8A-9CF11A235CF4%7D&file=20240530%20UT%20ENTERRITORIO%202027%20(SERVICIO).xlsm&action=default&mobileredirect=true | AH84: 1 | AI84: 1
A85: 2024 | B85: Junio | C85: 2f048f31-0b0f-ef11-9ac8-00155d68220c | D85: 45422.85 | E85: INFOTIC - ICFES - PRUEBAS CSJ | F85: Janeth Annelise Araujo Ramos | G85: https://growdatasas.sharepoint.com/sites/pwa/INFOTIC - ICFES - PRUEBAS CSJ | H85: APLICACIÓN ELECTRÓNICA DEL EXAMEN PARA EJERCER LA PROFESIÓN DE ABOGADO A REALIZARSE EN LA VIGENCIA 2024SUMINISTRO DE MESA DE SERVICIO CON COBERTURA NACIONAL | I85: TI | J85: 0328 | K85: Activo.En Cierre | L85: =VLOOKUP(E85,[1]Diccionario!C$2:AC$150,22,0) -> 830180856 | M85: =VLOOKUP(E85,[1]Diccionario!C$2:AC$150,24,0) -> 45414 | N85: =VLOOKUP(E85,[1]Diccionario!C$2:AC$150,25,0) -> 45596 | O85: =VLOOKUP(E85,[1]Diccionario!C$2:AC$150,26,0) -> 5.97 | P85: =Q85-O85 -> 17.03 | Q85: =DATEDIF(M85,TODAY(),"m") -> 23 | R85: 6 | S85: 0.4 | T85: 0.35 | W85: =IFERROR(T85*L85,0) -> 2.905633e+08 | X85: =S85*L85 -> 3.3207234e+08 | Y85: =IFERROR(W85-U85,0) -> 2.905633e+08 | Z85: =W85-X85 -> -41509043 | AA85: =IFERROR(W85/U85,"No se realizó gasto en este corte") -> No se realizó gasto en este corte | AB85: =IFERROR( IF(OR(AA85="",AA85=0), "No calculado", IF(AA85>1,"Costo eficiente: se está gastando menos de lo presupuestado", IF(AA85=1,"Costo según lo presupuestado", "Costo ineficiente: se está gastando más de lo presupuestado"))), "No calculado") -> Costo eficiente: se está gastando menos de lo presupuestado | AC85: =IFERROR(W85/X85,0) -> 0.875 | AD85: =IF(OR(AC85="",AC85=0),"Sin Línea Base", IF(AC85>1,"Proyecto adelantado respecto al cronograma", IF(AC85=1,"Proyecto a tiempo según lo planificado", IF(AC85<1,"Proyecto atrasado con respecto al cronograma", "No calculado")))) -> Proyecto atrasado con respecto al cronograma | AE85: =IFERROR(L85/AA85,0) -> 0 | AF85: =IFERROR(AE85-L85,0) -> -830180856 | AG85: =VLOOKUP(Indicador!E92,[1]Diccionario!C$1:AC$150,27,0) -> https://growdatasas.sharepoint.com/:x:/r/sites/Gestiondocumental/Administrativa/GD/Financiera/_layouts/15/Doc.aspx?sourcedoc=%7B0974E3E6-B78B-4C29-8F8A-9CF11A235CF4%7D&file=20240530%20UT%20ENTERRITORIO%202027%20(SERVICIO).xlsm&action=default&mobileredirect=true | AH85: 1 | AI85: 1
A86: 2024 | B86: Julio | C86: 2f048f31-0b0f-ef11-9ac8-00155d68220c | D86: 45422.85 | E86: INFOTIC - ICFES - PRUEBAS CSJ | F86: Janeth Annelise Araujo Ramos | G86: https://growdatasas.sharepoint.com/sites/pwa/INFOTIC - ICFES - PRUEBAS CSJ | H86: APLICACIÓN ELECTRÓNICA DEL EXAMEN PARA EJERCER LA PROFESIÓN DE ABOGADO A REALIZARSE EN LA VIGENCIA 2024SUMINISTRO DE MESA DE SERVICIO CON COBERTURA NACIONAL | I86: TI | J86: 0328 | K86: Activo.En Cierre | L86: =VLOOKUP(E86,[1]Diccionario!C$2:AC$150,22,0) -> 830180856 | M86: =VLOOKUP(E86,[1]Diccionario!C$2:AC$150,24,0) -> 45414 | N86: =VLOOKUP(E86,[1]Diccionario!C$2:AC$150,25,0) -> 45596 | O86: =VLOOKUP(E86,[1]Diccionario!C$2:AC$150,26,0) -> 5.97 | P86: =Q86-O86 -> 17.03 | Q86: =DATEDIF(M86,TODAY(),"m") -> 23 | R86: 6 | S86: 0.6 | T86: 0.56 | W86: =IFERROR(T86*L86,0) -> 4.6490128e+08 | X86: =S86*L86 -> 4.9810851e+08 | Y86: =IFERROR(W86-U86,0) -> 4.6490128e+08 | Z86: =W86-X86 -> -33207234 | AA86: =IFERROR(W86/U86,"No se realizó gasto en este corte") -> No se realizó gasto en este corte | AB86: =IFERROR( IF(OR(AA86="",AA86=0), "No calculado", IF(AA86>1,"Costo eficiente: se está gastando menos de lo presupuestado", IF(AA86=1,"Costo según lo presupuestado", "Costo ineficiente: se está gastando más de lo presupuestado"))), "No calculado") -> Costo eficiente: se está gastando menos de lo presupuestado | AC86: =IFERROR(W86/X86,0) -> 0.93333333 | AD86: =IF(OR(AC86="",AC86=0),"Sin Línea Base", IF(AC86>1,"Proyecto adelantado respecto al cronograma", IF(AC86=1,"Proyecto a tiempo según lo planificado", IF(AC86<1,"Proyecto atrasado con respecto al cronograma", "No calculado")))) -> Proyecto atrasado con respecto al cronograma | AE86: =IFERROR(L86/AA86,0) -> 0 | AF86: =IFERROR(AE86-L86,0) -> -830180856 | AG86: =VLOOKUP(Indicador!E93,[1]Diccionario!C$1:AC$150,27,0) -> https://growdatasas.sharepoint.com/:x:/r/sites/Gestiondocumental/Administrativa/GD/Financiera/_layouts/15/Doc.aspx?sourcedoc=%7B0974E3E6-B78B-4C29-8F8A-9CF11A235CF4%7D&file=20240530%20UT%20ENTERRITORIO%202027%20(SERVICIO).xlsm&action=default&mobileredirect=true | AH86: 1 | AI86: 1
A87: 2024 | B87: Agosto | C87: 2f048f31-0b0f-ef11-9ac8-00155d68220c | D87: 45422.85 | E87: INFOTIC - ICFES - PRUEBAS CSJ | F87: Janeth Annelise Araujo Ramos | G87: https://growdatasas.sharepoint.com/sites/pwa/INFOTIC - ICFES - PRUEBAS CSJ | H87: APLICACIÓN ELECTRÓNICA DEL EXAMEN PARA EJERCER LA PROFESIÓN DE ABOGADO A REALIZARSE EN LA VIGENCIA 2024SUMINISTRO DE MESA DE SERVICIO CON COBERTURA NACIONAL | I87: TI | J87: 0328 | K87: Activo.En Cierre | L87: =VLOOKUP(E87,[1]Diccionario!C$2:AC$150,22,0) -> 830180856 | M87: =VLOOKUP(E87,[1]Diccionario!C$2:AC$150,24,0) -> 45414 | N87: =VLOOKUP(E87,[1]Diccionario!C$2:AC$150,25,0) -> 45596 | O87: =VLOOKUP(E87,[1]Diccionario!C$2:AC$150,26,0) -> 5.97 | P87: =Q87-O87 -> 17.03 | Q87: =DATEDIF(M87,TODAY(),"m") -> 23 | R87: 6 | S87: 0.8 | T87: 0.67 | W87: =IFERROR(T87*L87,0) -> 5.5622117e+08 | X87: =S87*L87 -> 6.6414468e+08 | Y87: =IFERROR(W87-U87,0) -> 5.5622117e+08 | Z87: =W87-X87 -> -1.0792351e+08 | AA87: =IFERROR(W87/U87,"No se realizó gasto en este corte") -> No se realizó gasto en este corte | AB87: =IFERROR( IF(OR(AA87="",AA87=0), "No calculado", IF(AA87>1,"Costo eficiente: se está gastando menos de lo presupuestado", IF(AA87=1,"Costo según lo presupuestado", "Costo ineficiente: se está gastando más de lo presupuestado"))), "No calculado") -> Costo eficiente: se está gastando menos de lo presupuestado | AC87: =IFERROR(W87/X87,0) -> 0.8375 | AD87: =IF(OR(AC87="",AC87=0),"Sin Línea Base", IF(AC87>1,"Proyecto adelantado respecto al cronograma", IF(AC87=1,"Proyecto a tiempo según lo planificado", IF(AC87<1,"Proyecto atrasado con respecto al cronograma", "No calculado")))) -> Proyecto atrasado con respecto al cronograma | AE87: =IFERROR(L87/AA87,0) -> 0 | AF87: =IFERROR(AE87-L87,0) -> -830180856 | AG87: =VLOOKUP(Indicador!E94,[1]Diccionario!C$1:AC$150,27,0) -> https://growdatasas.sharepoint.com/:x:/r/sites/Gestiondocumental/Administrativa/GD/Financiera/_layouts/15/Doc.aspx?sourcedoc=%7B0974E3E6-B78B-4C29-8F8A-9CF11A235CF4%7D&file=20240530%20UT%20ENTERRITORIO%202027%20(SERVICIO).xlsm&action=default&mobileredirect=true | AH87: 1 | AI87: 1
