Workbook

Sheet Calidad de Datos
B1: Se realiza sobre las entidades Integradas | E1: Entidades con % > 0 / Cantidad total de entidades integradas
B2: COMPLETITUD: Mide el grado en que todos los atributos de la entidad se encuentran diligenciados | E2: Completitud = (número de registros completos/númerto total de registros)*100 | H2: Compeltitud por registro = (número de atributos completos / número total de atributor) * 100
B3: OPORTUNIDAD: Mide si los datos se encuentran disponibles en el momento que se necesitan | E3: % datos disponibles = porcentaje de datos que se pueden acceder en un tiempo definido | H3: Tasa de cumplimiento = mide si el sistema de datos cumple con los tiempos de entrega
B4: CONSISTENCIA: Mide la uniformidad y coherencia de los datos entre diferentes sistemas, asegurando que no haya discrepancias | E4: % de registros consistentes = % de registros que cumplen con las reglas de consistencia
B5: CONFORMIDAD: Mide que los datos se adhieran a las políticas, regulaciones y estándares establecidos | E5: Calidad de datos = % de datos que cumplen los estándares de precisión, integridad y consistencia
C6: =IFERROR(AVERAGEIF(Tabla1[Completitud Ago/2024],">0",Tabla1[Completitud Ago/2024]),0) -> 0.95342105 | D6: =IFERROR(AVERAGEIF(Tabla1[Oportunidad Ago/2024],">0",Tabla1[Oportunidad Ago/2024]),0) -> 0.99710526 | E6: =IFERROR(AVERAGEIF(Tabla1[Consistencia Ago/2024],">0",Tabla1[Consistencia Ago/2024]),0) -> 0.99210526 | F6: =IFERROR(AVERAGEIF(Tabla1[Conformidad Ago/2024],">0",Tabla1[Conformidad Ago/2024]),0) -> 0.8 | G6: =IFERROR(AVERAGEIF(Tabla1[Completitud Sep/2024],">0",Tabla1[Completitud Sep/2024]),0) -> 0.95342105 | H6: =IFERROR(AVERAGEIF(Tabla1[Oportunidad Sep/2024],">0",Tabla1[Oportunidad Sep/2024]),0) -> 1 | I6: =IFERROR(AVERAGEIF(Tabla1[Consistencia Sep/2024],">0",Tabla1[Consistencia Sep/2024]),0) -> 0.99210526 | J6: =IFERROR(AVERAGEIF(Tabla1[Conformidad Sep/2024],">0",Tabla1[Conformidad Sep/2024]),0) -> 0.85 | K6: =IFERROR(AVERAGEIF(Tabla1[Completitud Oct/2024],">0",Tabla1[Completitud Oct/2024]),0) -> 0.95342105 | L6: =IFERROR(AVERAGEIF(Tabla1[Oportunidad Oct/2024],">0",Tabla1[Oportunidad Oct/2024]),0) -> 0.99763158 | M6: =IFERROR(AVERAGEIF(Tabla1[Consistencia Oct/2024],">0",Tabla1[Consistencia Oct/2024]),0) -> 0.99447368 | N6: =IFERROR(AVERAGEIF(Tabla1[Conformidad Oct/2024],">0",Tabla1[Conformidad Oct/2024]),0) -> 0.85 | O6: =IFERROR(AVERAGEIF(Tabla1[Completitud Nov/2024],">0",Tabla1[Completitud Nov/2024]),0) -> 0.93142857 | P6: =IFERROR(AVERAGEIF(Tabla1[Oportunidad Nov/2024],">0",Tabla1[Oportunidad Nov/2024]),0) -> 1 | Q6: =IFERROR(AVERAGEIF(Tabla1[Consistencia Nov/2024],">0",Tabla1[Consistencia Nov/2024]),0) -> 0.96785714 | R6: =IFERROR(AVERAGEIF(Tabla1[Conformidad Nov/2024],">0",Tabla1[Conformidad Nov/2024]),0) -> 0.9 | S6: =IFERROR(AVERAGEIF(Tabla1[Completitud Dic/2024],">0",Tabla1[Completitud Dic/2024]),0) -> 0.93142857 | T6: =IFERROR(AVERAGEIF(Tabla1[Oportunidad Dic/2024],">0",Tabla1[Oportunidad Dic/2024]),0) -> 0.99839286 | U6: =IFERROR(AVERAGEIF(Tabla1[Consistencia Dic/2024],">0",Tabla1[Consistencia Dic/2024]),0) -> 0.97089286 | V6: =IFERROR(AVERAGEIF(Tabla1[Conformidad Dic/2024],">0",Tabla1[Conformidad Dic/2024]),0) -> 0.95 | W6: =IFERROR(AVERAGEIF(Tabla1[Completitud Ene/2025],">0",Tabla1[Completitud Ene/2025]),0) -> 0.96035714 | X6: =IFERROR(AVERAGEIF(Tabla1[Oportunidad Ene/2025],">0",Tabla1[Oportunidad Ene/2025]),0) -> 1 | Y6: =IFERROR(AVERAGEIF(Tabla1[Consistencia Ene/2025],">0",Tabla1[Consistencia Ene/2025]),0) -> 0.97285714 | Z6: =IFERROR(AVERAGEIF(Tabla1[Conformidad Ene/2025],">0",Tabla1[Conformidad Ene/2025]),0) -> 0.975 | AA6: =IFERROR(AVERAGEIF(Tabla1[Completitud Feb/2025],">0",Tabla1[Completitud Feb/2025]),0) -> 0.96566667 | AB6: =IFERROR(AVERAGEIF(Tabla1[Oportunidad Feb/2025],">0",Tabla1[Oportunidad Feb/2025]),0) -> 1 | AC6: =IFERROR(AVERAGEIF(Tabla1[Consistencia Feb/2025],">0",Tabla1[Consistencia Feb/2025]),0) -> 0.979 | AD6: =IFERROR(AVERAGEIF(Tabla1[Conformidad Feb/2025],">0",Tabla1[Conformidad Feb/2025]),0) -> 1 | AE6: =IFERROR(AVERAGEIF(Tabla1[Completitud Mar/2025],">0",Tabla1[Completitud Mar/2025]),0) -> 0.96816667 | AF6: =IFERROR(AVERAGEIF(Tabla1[Oportunidad Mar/2025],">0",Tabla1[Oportunidad Mar/2025]),0) -> 1 | AG6: =IFERROR(AVERAGEIF(Tabla1[Consistencia Mar/2025],">0",Tabla1[Consistencia Mar/2025]),0) -> 0.979 | AH6: =IFERROR(AVERAGEIF(Tabla1[Conformidad Mar/2025],">0",Tabla1[Conformidad Mar/2025]),0) -> 1 | AI6: =IFERROR(AVERAGEIF(Tabla1[Completitud Abr/2025],">0",Tabla1[Completitud Abr/2025]),0) -> 0.976125 | AJ6: =IFERROR(AVERAGEIF(Tabla1[Oportunidad Abr/2025],">0",Tabla1[Oportunidad Abr/2025]),0) -> 0.9325 | AK6: =IFERROR(AVERAGEIF(Tabla1[Consistencia Abr/2025],">0",Tabla1[Consistencia Abr/2025]),0) -> 0.8875 | AL6: =IFERROR(AVERAGEIF(Tabla1[Conformidad Abr/2025],">0",Tabla1[Conformidad Abr/2025]),0) -> 0.9625 | AM6: =IFERROR(AVERAGEIF(Tabla1[Completitud May/2025],">0",Tabla1[Completitud May/2025]),0) -> 0.989 | AN6: =IFERROR(AVERAGEIF(Tabla1[Oportunidad May/2025],">0",Tabla1[Oportunidad May/2025]),0) -> 1 | AO6: =IFERROR(AVERAGEIF(Tabla1[Consistencia May/2025],">0",Tabla1[Consistencia May/2025]),0) -> 0.998 | AP6: =IFERROR(AVERAGEIF(Tabla1[Conformidad May/2025],">0",Tabla1[Conformidad May/2025]),0) -> 1 | AQ6: =IFERROR(AVERAGEIF(Tabla1[Completitud Jun/2025],">0",Tabla1[Completitud Jun/2025]),0) -> 0.9915 | AR6: =IFERROR(AVERAGEIF(Tabla1[Oportunidad Jun/2025],">0",Tabla1[Oportunidad Jun/2025]),0) -> 1 | AS6: =IFERROR(AVERAGEIF(Tabla1[Consistencia Jun/2025],">0",Tabla1[Consistencia Jun/2025]),0) -> 0.998 | AT6: =IFERROR(AVERAGEIF(Tabla1[Conformidad Jun/2025],">0",Tabla1[Conformidad Jun/2025]),0) -> 1 | AU6: =IFERROR(AVERAGEIF(Tabla1[Completitud Sep/2025],">0",Tabla1[Completitud Sep/2025]),0) -> 1 | AV6: =IFERROR(AVERAGEIF(Tabla1[Oportunidad Sep/2025],">0",Tabla1[Oportunidad Sep/2025]),0) -> 1 | AW6: =IFERROR(AVERAGEIF(Tabla1[Consistencia Sep/2025],">0",Tabla1[Consistencia Sep/2025]),0) -> 1 | AX6: =IFERROR(AVERAGEIF(Tabla1[Conformidad Sep/2025],">0",Tabla1[Conformidad Sep/2025]),0) -> 1 | AY6: =IFERROR(AVERAGEIF(Tabla1[Completitud Dic/2025],">0",Tabla1[Completitud Dic/2025]),0) -> 0.89792857 | AZ6: =IFERROR(AVERAGEIF(Tabla1[Oportunidad Dic/2025],">0",Tabla1[Oportunidad Dic/2025]),0) -> 1 | BA6: =IFERROR(AVERAGEIF(Tabla1[Consistencia Dic/2025],">0",Tabla1[Consistencia Dic/2025]),0) -> 0.88813559 | BB6: =IFERROR(AVERAGEIF(Tabla1[Conformidad Dic/2025],">0",Tabla1[Conformidad Dic/2025]),0) -> 1 | BC6: =IFERROR(AVERAGEIF(Tabla1[Completitud Mar/2026],">0",Tabla1[Completitud Mar/2026]),0) -> 0.92676056 | BD6: =IFERROR(AVERAGEIF(Tabla1[Oportunidad Mar/2026],">0",Tabla1[Oportunidad Mar/2026]),0) -> 1 | BE6: =IFERROR(AVERAGEIF(Tabla1[Consistencia Mar/2026],">0",Tabla1[Consistencia Mar/2026]),0) -> 0.98481013 | BF6: =IFERROR(AVERAGEIF(Tabla1[Conformidad Mar/2026],">0",Tabla1[Conformidad Mar/2026]),0) -> 1
B7: Entidades | C7: Completitud Ago/2024 | D7: Oportunidad Ago/2024 | E7: Consistencia Ago/2024 | F7: Conformidad Ago/2024 | G7: Completitud Sep/2024 | H7: Oportunidad Sep/2024 | I7: Consistencia Sep/2024 | J7: Conformidad Sep/2024 | K7: Completitud Oct/2024 | L7: Oportunidad Oct/2024 | M7: Consistencia Oct/2024 | N7: Conformidad Oct/2024 | O7: Completitud Nov/2024 | P7: Oportunidad Nov/2024 | Q7: Consistencia Nov/2024 | R7: Conformidad Nov/2024 | S7: Completitud Dic/2024 | T7: Oportunidad Dic/2024 | U7: Consistencia Dic/2024 | V7: Conformidad Dic/2024 | W7: Completitud Ene/2025 | X7: Oportunidad Ene/2025 | Y7: Consistencia Ene/2025 | Z7: Conformidad Ene/2025 | AA7: Completitud Feb/2025 | AB7: Oportunidad Feb/2025 | AC7: Consistencia Feb/2025 | AD7: Conformidad Feb/2025 | AE7: Completitud Mar/2025 | AF7: Oportunidad Mar/2025 | AG7: Consistencia Mar/2025 | AH7: Conformidad Mar/2025 | AI7: Completitud Abr/2025 | AJ7: Oportunidad Abr/2025 | AK7: Consistencia Abr/2025 | AL7: Conformidad Abr/2025 | AM7: Completitud May/2025 | AN7: Oportunidad May/2025 | AO7: Consistencia May/2025 | AP7: Conformidad May/2025 | AQ7: Completitud Jun/2025 | AR7: Oportunidad Jun/2025 | AS7: Consistencia Jun/2025 | AT7: Conformidad Jun/2025 | AU7: Completitud Sep/2025 | AV7: Oportunidad Sep/2025 | AW7: Consistencia Sep/2025 | AX7: Conformidad Sep/2025 | AY7: Completitud Dic/2025 | AZ7: Oportunidad Dic/2025 | BA7: Consistencia Dic/2025 | BB7: Conformidad Dic/2025 | BC7: Completitud Mar/2026 | BD7: Oportunidad Mar/2026 | BE7: Consistencia Mar/2026 | BF7: Conformidad Mar/2026
B8: Oportunidades | C8: 0.7 | D8: 0.94 | E8: 0.9 | F8: 0.4 | G8: 0.7 | H8: 1 | I8: 0.9 | J8: 0.55 | K8: 0.7 | L8: 0.95 | M8: 0.93 | N8: 0.55 | O8: 0.7 | P8: 1 | Q8: 0.95 | R8: 0.85 | S8: 0.7 | T8: 0.95 | U8: 0.995 | V8: 1 | W8: 0.7 | X8: 1 | Y8: 1 | Z8: 1 | AA8: 0.7 | AB8: 1 | AC8: 1 | AD8: 1 | AE8: 0.7 | AF8: 1 | AG8: 1 | AH8: 1 | AI8: 0.7 | AJ8: 1 | AK8: 1 | AL8: 1 | AM8: 0.8 | AN8: 1 | AO8: 1 | AP8: 1 | AQ8: 0.85 | AR8: 1 | AS8: 1 | AT8: 1 | AU8: 1 | AV8: 1 | AW8: 1 | AX8: 1 | AY8: 0.5255 | AZ8: 1 | BA8: 1 | BB8: 1 | BC8: 0.85 | BD8: 1 | BE8: 1 | BF8: 1
B9: Línea de negocios | C9: 1 | D9: 1 | E9: 1 | F9: 1 | G9: 1 | H9: 1 | I9: 1 | J9: 1 | K9: 1 | L9: 1 | M9: 1 | N9: 1 | O9: 1 | P9: 1 | Q9: 1 | R9: 1 | S9: 1 | T9: 1 | U9: 1 | V9: 1 | W9: 1 | X9: 1 | Y9: 1 | Z9: 1 | AA9: 1 | AB9: 1 | AC9: 1 | AD9: 1 | AE9: 1 | AF9: 1 | AG9: 1 | AH9: 1 | AI9: 1 | AJ9: 1 | AK9: 1 | AL9: 1 | AM9: 1 | AN9: 1 | AO9: 1 | AP9: 1 | AQ9: 1 | AR9: 1 | AS9: 1 | AT9: 1 | AU9: 1 | AV9: 1 | AW9: 1 | AX9: 1 | AY9: 1 | AZ9: 1 | BA9: 1 | BB9: 1 | BC9: 1 | BD9: 1 | BE9: 1 | BF9: 1
B10: Equipo de ventas | C10: 1 | D10: 1 | E10: 1 | F10: 1 | G10: 1 | H10: 1 | I10: 1 | J10: 1 | K10: 1 | L10: 1 | M10: 1 | N10: 1 | O10: 1 | P10: 1 | Q10: 1 | R10: 1 | S10: 1 | T10: 1 | U10: 1 | V10: 1 | W10: 1 | X10: 1 | Y10: 1 | Z10: 1 | AA10: 1 | AB10: 1 | AC10: 1 | AD10: 1 | AE10: 1 | AF10: 1 | AG10: 1 | AH10: 1 | AI10: 1 | AJ10: 1 | AK10: 1 | AL10: 1 | AM10: 1 | AN10: 1 | AO10: 1 | AP10: 1 | AQ10: 1 | AR10: 1 | AS10: 1 | AT10: 1 | AU10: 1 | AV10: 1 | AW10: 1 | AX10: 1 | AY10: 1 | AZ10: 1 | BA10: 1 | BB10: 1 | BC10: 1 | BD10: 1 | BE10: 1 | BF10: 1
B11: Tipo de cliente | C11: 1 | D11: 1 | E11: 1 | F11: 1 | G11: 1 | H11: 1 | I11: 1 | J11: 1 | K11: 1 | L11: 1 | M11: 1 | N11: 1 | O11: 1 | P11: 1 | Q11: 1 | R11: 1 | S11: 1 | T11: 1 | U11: 1 | V11: 1 | W11: 1 | X11: 1 | Y11: 1 | Z11: 1 | AA11: 1 | AB11: 1 | AC11: 1 | AD11: 1 | AE11: 1 | AF11: 1 | AG11: 1 | AH11: 1 | AI11: 1 | AJ11: 1 | AK11: 1 | AL11: 1 | AM11: 1 | AN11: 1 | AO11: 1 | AP11: 1 | AQ11: 1 | AR11: 1 | AS11: 1 | AT11: 1 | AU11: 1 | AV11: 1 | AW11: 1 | AX11: 1 | AY11: 1 | AZ11: 1 | BA11: 1 | BB11: 1 | BC11: 1 | BD11: 1 | BE11: 1 | BF11: 1
B12: Cliente | C12: 0.3 | D12: 1 | E12: 0.9 | F12: 0.3 | G12: 0.3 | H12: 1 | I12: 0.9 | J12: 0.3 | K12: 0.3 | L12: 1 | M12: 0.93 | N12: 0.3 | O12: 0.3 | P12: 1 | Q12: 0.95 | R12: 0.8 | S12: 0.3 | T12: 1 | U12: 0.995 | V12: 1 | W12: 0.3 | X12: 1 | Y12: 1 | Z12: 1 | AA12: 0.3 | AB12: 1 | AC12: 1 | AD12: 1 | AE12: 0.3 | AF12: 1 | AG12: 1 | AH12: 1 | AI12: 0.3 | AJ12: 1 | AK12: 1 | AL12: 1 | AM12: 0.3 | AN12: 1 | AO12: 1 | AP12: 1 | AQ12: 0.5 | AR12: 1 | AS12: 1 | AT12: 1 | AU12: 1 | AV12: 1 | AW12: 1 | AX12: 1 | AY12: 0.354 | AZ12: 1 | BA12: 1 | BB12: 1 | BC12: 0.9 | BD12: 1 | BE12: 0.6 | BF12: 1
B13: Tipo de venta | C13: 1 | D13: 1 | E13: 1 | F13: 1 | G13: 1 | H13: 1 | I13: 1 | J13: 1 | K13: 1 | L13: 1 | M13: 1 | N13: 1 | O13: 1 | P13: 1 | Q13: 1 | R13: 1 | S13: 1 | T13: 1 | U13: 1 | V13: 1 | W13: 1 | X13: 1 | Y13: 1 | Z13: 1 | AA13: 1 | AB13: 1 | AC13: 1 | AD13: 1 | AE13: 1 | AF13: 1 | AG13: 1 | AH13: 1 | AI13: 1 | AJ13: 1 | AK13: 1 | AL13: 1 | AM13: 1 | AN13: 1 | AO13: 1 | AP13: 1 | AQ13: 1 | AR13: 1 | AS13: 1 | AT13: 1 | AU13: 1 | AV13: 1 | AW13: 1 | AX13: 1 | AY13: 1 | AZ13: 1 | BA13: 1 | BB13: 1 | BC13: 1 | BD13: 1 | BE13: 1 | BF13: 1
B14: Tipo de oportunidad | C14: 1 | D14: 1 | E14: 1 | F14: 1 | G14: 1 | H14: 1 | I14: 1 | J14: 1 | K14: 1 | L14: 1 | M14: 1 | N14: 1 | O14: 1 | P14: 1 | Q14: 1 | R14: 1 | S14: 1 | T14: 1 | U14: 1 | V14: 1 | W14: 1 | X14: 1 | Y14: 1 | Z14: 1 | AA14: 1 | AB14: 1 | AC14: 1 | AD14: 1 | AE14: 1 | AF14: 1 | AG14: 1 | AH14: 1 | AI14: 1 | AJ14: 1 | AK14: 1 | AL14: 1 | AM14: 1 | AN14: 1 | AO14: 1 | AP14: 1 | AQ14: 1 | AR14: 1 | AS14: 1 | AT14: 1 | AU14: 1 | AV14: 1 | AW14: 1 | AX14: 1 | AY14: 1 | AZ14: 1 | BA14: 1 | BB14: 1 | BC14: 1 | BD14: 1 | BE14: 1 | BF14: 1
B15: Etapa actual | C15: 1 | D15: 1 | E15: 1 | F15: 1 | G15: 1 | H15: 1 | I15: 1 | J15: 1 | K15: 1 | L15: 1 | M15: 1 | N15: 1 | O15: 1 | P15: 1 | Q15: 1 | R15: 1 | S15: 1 | T15: 1 | U15: 1 | V15: 1 | W15: 1 | X15: 1 | Y15: 1 | Z15: 1 | AA15: 1 | AB15: 1 | AC15: 1 | AD15: 1 | AE15: 1 | AF15: 1 | AG15: 1 | AH15: 1 | AI15: 1 | AJ15: 1 | AK15: 1 | AL15: 1 | AM15: 1 | AN15: 1 | AO15: 1 | AP15: 1 | AQ15: 1 | AR15: 1 | AS15: 1 | AT15: 1 | AU15: 1 | AV15: 1 | AW15: 1 | AX15: 1 | AY15: 1 | AZ15: 1 | BA15: 1 | BB15: 1 | BC15: 1 | BD15: 1 | BE15: 1 | BF15: 1
B16: Ganado | C16: 1 | D16: 1 | E16: 1 | F16: 1 | G16: 1 | H16: 1 | I16: 1 | J16: 1 | K16: 1 | L16: 1 | M16: 1 | N16: 1 | O16: 1 | P16: 1 | Q16: 1 | R16: 1 | S16: 1 | T16: 1 | U16: 1 | V16: 1 | W16: 1 | X16: 1 | Y16: 1 | Z16: 1 | AA16: 1 | AB16: 1 | AC16: 1 | AD16: 1 | AE16: 1 | AF16: 1 | AG16: 1 | AH16: 1 | AI16: 1 | AJ16: 1 | AK16: 1 | AL16: 1 | AM16: 1 | AN16: 1 | AO16: 1 | AP16: 1 | AQ16: 1 | AR16: 1 | AS16: 1 | AT16: 1 | AU16: 1 | AV16: 1 | AW16: 1 | AX16: 1 | AY16: 1 | AZ16: 1 | BA16: 1 | BB16: 1 | BC16: 1 | BD16: 1 | BE16: 1 | BF16: 1
B17: Metas | C17: 1 | D17: 1 | E17: 1 | F17: 1 | G17: 1 | H17: 1 | I17: 1 | J17: 1 | K17: 1 | L17: 1 | M17: 1 | N17: 1 | O17: 1 | P17: 1 | Q17: 1 | R17: 1 | S17: 1 | T17: 1 | U17: 1 | V17: 1 | W17: 1 | X17: 1 | Y17: 1 | Z17: 1 | AA17: 1 | AB17: 1 | AC17: 1 | AD17: 1 | AE17: 1 | AF17: 1 | AG17: 1 | AH17: 1 | AI17: 1 | AJ17: 1 | AK17: 1 | AL17: 1 | AM17: 1 | AN17: 1 | AO17: 1 | AP17: 1 | AQ17: 1 | AR17: 1 | AS17: 1 | AT17: 1 | AU17: 1 | AV17: 1 | AW17: 1 | AX17: 1 | AY17: 1 | AZ17: 1 | BA17: 1 | BB17: 1 | BC17: 1 | BD17: 1 | BE17: 1 | BF17: 1
B18: Metas de Comercial | C18: 1 | D18: 1 | E18: 1 | F18: 1 | G18: 1 | H18: 1 | I18: 1 | J18: 1 | K18: 1 | L18: 1 | M18: 1 | N18: 1 | O18: 1 | P18: 1 | Q18: 1 | R18: 1 | S18: 1 | T18: 1 | U18: 1 | V18: 1 | W18: 1 | X18: 1 | Y18: 1 | Z18: 1 | AA18: 1 | AB18: 1 | AC18: 1 | AD18: 1 | AE18: 1 | AF18: 1 | AG18: 1 | AH18: 1 | AI18: 1 | AJ18: 1 | AK18: 1 | AL18: 1 | AM18: 1 | AN18: 1 | AO18: 1 | AP18: 1 | AQ18: 1 | AR18: 1 | AS18: 1 | AT18: 1 | AU18: 1 | AV18: 1 | AW18: 1 | AX18: 1 | AY18: 1 | AZ18: 1 | BA18: 1 | BB18: 1 | BC18: 1 | BD18: 1 | BE18: 1 | BF18: 1
B19: Área | C19: 1 | D19: 1 | E19: 1 | F19: 1 | G19: 1 | H19: 1 | I19: 1 | J19: 1 | K19: 1 | L19: 1 | M19: 1 | N19: 1 | O19: 1 | P19: 1 | Q19: 1 | R19: 1 | S19: 1 | T19: 1 | U19: 1 | V19: 1 | W19: 1 | X19: 1 | Y19: 1 | Z19: 1 | AA19: 1 | AB19: 1 | AC19: 1 | AD19: 1 | AE19: 1 | AF19: 1 | AG19: 1 | AH19: 1 | AI19: 1 | AJ19: 1 | AK19: 1 | AL19: 1 | AM19: 1 | AN19: 1 | AO19: 1 | AP19: 1 | AQ19: 1 | AR19: 1 | AS19: 1 | AT19: 1 | AU19: 1 | AV19: 1 | AW19: 1 | AX19: 1 | AY19: 1 | AZ19: 1 | BA19: 1 | BB19: 1 | BC19: 1 | BD19: 1 | BE19: 1 | BF19: 1
... B58: Plan de capacitaciones | C58: 0 | D58: 0 | E58: 0 | F58: 0 | G58: 0 | H58: 0 | I58: 0 | J58: 0 | K58: 0 | L58: 0 | M58: 0 | N58: 0 | O58: 0.72 | P58: 1 | Q58: 0.8 | R58: 0.5 | S58: 0.72 | T58: 1 | U58: 0.8 | V58: 0.7 | W58: 0.9 | X58: 1 | Y58: 0.9 | Z58: 0.9 | AA58: 0.95 | AB58: 1 | AC58: 0.9 | AD58: 1 | AE58: 1 | AF58: 1 | AG58: 0.9 | AH58: 1 | AI58: 1 | AJ58: 1 | AK58: 1 | AL58: 1 | AM58: 1 | AN58: 1 | AO58: 1 | AP58: 1 | AQ58: 1 | AR58: 1 | AS58: 1 | AT58: 1 | AU58: 1 | AV58: 1 | AW58: 1 | AX58: 1 | AY58: 1 | AZ58: 1 | BA58: 1 | BB58: 1 | BC58: 1 | BD58: 1 | BE58: 1 | BF58: 1
B59: Ordenes de compras | AI59: 1 | AJ59: 0.4 | AK59: 0.4 | AL59: 0.4 | AM59: 1 | AN59: 1 | AO59: 1 | AP59: 1 | AQ59: 1 | AR59: 1 | AS59: 1 | AT59: 1 | AU59: 1 | AV59: 1 | AW59: 1 | AX59: 1 | AY59: 1 | AZ59: 1 | BA59: 1 | BB59: 1 | BC59: 1 | BD59: 1 | BE59: 1 | BF59: 1
B60: Proveedores | AI60: 1 | AJ60: 0.4 | AK60: 0.4 | AL60: 0.4 | AM60: 1 | AN60: 1 | AO60: 1 | AP60: 1 | AQ60: 1 | AR60: 1 | AS60: 1 | AT60: 1 | AU60: 1 | AV60: 1 | AW60: 1 | AX60: 1 | AY60: 1 | AZ60: 1 | BA60: 1 | BB60: 1 | BC60: 1 | BD60: 1 | BE60: 1 | BF60: 1
B61: Requisiciones | AI61: 1 | AJ61: 0.4 | AK61: 0.4 | AL61: 0.4 | AM61: 1 | AN61: 1 | AO61: 1 | AP61: 1 | AQ61: 1 | AR61: 1 | AS61: 1 | AT61: 1 | AU61: 1 | AV61: 1 | AW61: 1 | AX61: 1 | AY61: 1 | AZ61: 1 | BA61: 1 | BB61: 1 | BC61: 1 | BD61: 1 | BE61: 1 | BF61: 1
B62: Contratos | AI62: 1 | AJ62: 0.4 | AK62: 0.4 | AL62: 1 | AM62: 1 | AN62: 1 | AO62: 1 | AP62: 1 | AQ62: 1 | AR62: 1 | AS62: 1 | AT62: 1 | AU62: 1 | AV62: 1 | AW62: 1 | AX62: 1 | AY62: 1 | AZ62: 1 | BA62: 1 | BB62: 1 | BC62: 1 | BD62: 1 | BE62: 1 | BF62: 1
B63: Solicitud de contratación logistica | AI63: 1 | AJ63: 0.4 | AK63: 0.4 | AL63: 1 | AM63: 1 | AN63: 1 | AO63: 1 | AP63: 1 | AQ63: 1 | AR63: 1 | AS63: 1 | AT63: 1 | AU63: 1 | AV63: 1 | AW63: 1 | AX63: 1 | AY63: 1 | AZ63: 1 | BA63: 1 | BB63: 1 | BC63: 1 | BD63: 1 | BE63: 1 | BF63: 1
B64: Registro de ahorros | AI64: 1 | AJ64: 0.4 | AK64: 0.4 | AL64: 1 | AM64: 1 | AN64: 1 | AO64: 1 | AP64: 1 | AQ64: 1 | AR64: 1 | AS64: 1 | AT64: 1 | AU64: 1 | AV64: 1 | AW64: 1 | AX64: 1 | AY64: 1 | AZ64: 1 | BA64: 1 | BB64: 1 | BC64: 1 | BD64: 1 | BE64: 1 | BF64: 1
B65: Modelo financiero | AM65: 1 | AN65: 1 | AO65: 1 | AP65: 1 | AQ65: 1 | AR65: 1 | AS65: 1 | AT65: 1 | AU65: 1 | AV65: 1 | AW65: 1 | AX65: 1 | AY65: 1 | AZ65: 1 | BA65: 1 | BB65: 1 | BC65: 1 | BD65: 1 | BE65: 1 | BF65: 1
B66: Oferta comercial | AY66: 0.8 | AZ66: 1 | BA66: 1 | BB66: 1 | BC66: 1 | BD66: 1 | BE66: 1 | BF66: 1
B67: Acta | AY67: 1 | AZ67: 1 | BA67: 1 | BB67: 1 | BC67: 1 | BD67: 1 | BE67: 1 | BF67: 1
B68: Fabricante | AI68: 1 | AJ68: 1 | AK68: 1 | AL68: 1 | AM68: 1 | AN68: 1 | AO68: 1 | AP68: 1 | AQ68: 1 | AR68: 1 | AS68: 1 | AT68: 1 | AU68: 1 | AV68: 1 | AW68: 1 | AX68: 1 | AY68: 1 | AZ68: 1 | BA68: 1 | BB68: 1 | BC68: 1 | BD68: 1 | BE68: 1 | BF68: 1
B69: Proceso | AY69: 0.8 | AZ69: 1 | BA69: 1 | BB69: 1 | BC69: 0.8 | BD69: 1 | BE69: 1 | BF69: 1
B70: Productos | AY70: 0.8 | AZ70: 1 | BA70: 1 | BB70: 1 | BC70: 0.8 | BD70: 1 | BE70: 1 | BF70: 1
B71: Servicio | AI71: 1 | AJ71: 1 | AK71: 1 | AL71: 1 | AM71: 1 | AN71: 1 | AO71: 1 | AP71: 1 | AQ71: 1 | AR71: 1 | AS71: 1 | AT71: 1 | AU71: 1 | AV71: 1 | AW71: 1 | AX71: 1 | AY71: 1 | AZ71: 1 | BA71: 1 | BB71: 1 | BC71: 1 | BD71: 1 | BE71: 1 | BF71: 1
B72: Entregable | AY72: 0.4 | AZ72: 1 | BA72: 1 | BB72: 1 | BC72: 0.4 | BD72: 1 | BE72: 1 | BF72: 1
B73: Artefacto | AY73: 0.4 | AZ73: 1 | BA73: 1 | BB73: 1 | BC73: 0.4 | BD73: 1 | BE73: 1 | BF73: 1
B74: Riesgos y Oportunidades | AY74: 0.4 | AZ74: 1 | BA74: 1 | BB74: 1 | BC74: 0.4 | BD74: 1 | BE74: 1 | BF74: 1
B75: Política | AY75: 0.8 | AZ75: 1 | BA75: 1 | BB75: 1 | BC75: 0.8 | BD75: 1 | BE75: 1 | BF75: 1
B76: Guía | AY76: 0.8 | AZ76: 1 | BA76: 1 | BB76: 1 | BC76: 0.8 | BD76: 1 | BE76: 1 | BF76: 1
B77: Requisitos Norma ISO 9001 | AY77: 0.4 | AZ77: 1 | BA77: 1 | BB77: 1 | BC77: 0.4 | BD77: 1 | BE77: 1 | BF77: 1
B78: Salidas no conformes | AY78: 0.7 | AZ78: 1 | BA78: 1 | BB78: 1 | BC78: 0.8 | BD78: 1 | BE78: 1 | BF78: 1
B79: Tipo de tratamiento | AM79: 1 | AN79: 1 | AO79: 1 | AP79: 1 | AQ79: 1 | AR79: 1 | AS79: 1 | AT79: 1 | AU79: 1 | AV79: 1 | AW79: 1 | AX79: 1 | AY79: 1 | AZ79: 1 | BA79: 1 | BB79: 1 | BC79: 1 | BD79: 1 | BE79: 1 | BF79: 1
B80: Acción correctiva | AM80: 1 | AN80: 1 | AO80: 1 | AP80: 1 | AQ80: 1 | AR80: 1 | AS80: 1 | AT80: 1 | AU80: 1 | AV80: 1 | AW80: 1 | AX80: 1 | AY80: 1 | AZ80: 1 | BA80: 1 | BB80: 1 | BC80: 1 | BD80: 1 | BE80: 1 | BF80: 1
B81: Solicitud de acción correctiva | AM81: 1 | AN81: 1 | AO81: 1 | AP81: 1 | AQ81: 1 | AR81: 1 | AS81: 1 | AT81: 1 | AU81: 1 | AV81: 1 | AW81: 1 | AX81: 1 | AY81: 1 | AZ81: 1 | BA81: 1 | BB81: 1 | BC81: 1 | BD81: 1 | BE81: 1 | BF81: 1
B82: Plan de tratamiento de riesgos | AY82: 0 | AZ82: 1 | BA82: 0.6 | BB82: 1 | BC82: 0 | BD82: 1 | BE82: 0.6 | BF82: 1
B83: Planificación de cambios | AY83: 0.4 | AZ83: 1 | BA83: 0.4 | BB83: 1 | BC83: 0.4 | BD83: 1 | BE83: 0.4 | BF83: 1
B84: Aliado Estratégico | AY84: 1 | AZ84: 1 | BA84: 1 | BB84: 1 | BC84: 1 | BD84: 1 | BE84: 1 | BF84: 1
B85: Requerimientos de servicios y productos | AY85: 0.4 | AZ85: 1 | BA85: 0.4 | BB85: 1 | BC85: 0.4 | BD85: 1 | BE85: 1 | BF85: 1
B86: Términos de referencia | AY86: 0.4 | AZ86: 1 | BA86: 0.4 | BB86: 1 | BC86: 0.4 | BD86: 1 | BE86: 1 | BF86: 1
B87: Portafolio de productos y servicios | AY87: 0.8 | AZ87: 1 | BA87: 1 | BB87: 1 | BC87: 0.8 | BD87: 1 | BE87: 1 | BF87: 1
B88: Viabilidad Técnica | AY88: 0 | AZ88: 1 | BA88: 0.6 | BB88: 1 | BC88: 0 | BD88: 1 | BE88: 1 | BF88: 1
B89: Oferta técnica | AY89: 0 | AZ89: 1 | BA89: 0.6 | BB89: 1 | BC89: 0 | BD89: 1 | BE89: 1 | BF89: 1
B90: Minuta | AY90: 0.8 | AZ90: 1 | BA90: 1 | BB90: 1 | BC90: 0.8 | BD90: 1 | BE90: 1 | BF90: 1
B91: Otrosí | AY91: 0.8 | AZ91: 1 | BA91: 1 | BB91: 1 | BC91: 0.8 | BD91: 1 | BE91: 1 | BF91: 1
B92: Póliza | AY92: 1 | AZ92: 1 | BA92: 1 | BB92: 1 | BC92: 1 | BD92: 1 | BE92: 1 | BF92: 1
B93: Ficha del proyecto | AY93: 0.9 | AZ93: 1 | BA93: 1 | BB93: 1 | BC93: 0.9 | BD93: 1 | BE93: 1 | BF93: 1
... B97: Procedimiento | AY97: 0.8 | AZ97: 1 | BA97: 1 | BB97: 1 | BC97: 0.8 | BD97: 1 | BE97: 1 | BF97: 1
B98: Ventas | C98: 1 | D98: 1 | E98: 1 | F98: 0.4 | G98: 1 | H98: 1 | I98: 1 | J98: 0.55 | K98: 1 | L98: 1 | M98: 1 | N98: 0.55 | O98: 1 | P98: 1 | Q98: 1 | R98: 0.85 | S98: 1 | T98: 1 | U98: 1 | V98: 1 | W98: 1 | X98: 1 | Y98: 1 | Z98: 1 | AA98: 1 | AB98: 1 | AC98: 1 | AD98: 1 | AE98: 1 | AF98: 1 | AG98: 1 | AH98: 1 | AI98: 1 | AJ98: 1 | AK98: 1 | AL98: 1 | AM98: 1 | AN98: 1 | AO98: 1 | AP98: 1 | AQ98: 1 | AR98: 1 | AS98: 1 | AT98: 1 | AU98: 1 | AV98: 1 | AW98: 1 | AX98: 1 | AY98: 1 | AZ98: 1 | BA98: 1 | BB98: 1 | BC98: 1 | BD98: 1 | BE98: 1 | BF98: 1
B99: Solicitud de recursos | AY99: 0.8 | AZ99: 1 | BA99: 1 | BB99: 1 | BC99: 0.85 | BD99: 1 | BE99: 1 | BF99: 1
B100: Propuesta comercial | AY100: 0.6 | AZ100: 1 | BA100: 0.6 | BB100: 1 | BC100: 0.6 | BD100: 1 | BE100: 1 | BF100: 1
B101: Cronograma | AY101: 1 | AZ101: 1 | BA101: 1 | BB101: 1 | BC101: 1 | BD101: 1 | BE101: 1 | BF101: 1
B102: Pedido de ventas | AY102: 1 | AZ102: 1 | BA102: 1 | BB102: 1 | BC102: 1 | BD102: 1 | BE102: 1 | BF102: 1
B103: Recurso | AY103: 0.8 | AZ103: 1 | BA103: 1 | BB103: 1 | BC103: 0.8 | BD103: 1 | BE103: 1 | BF103: 1
B104: Acuerdo técnico | AY104: 0.6 | AZ104: 1 | BA104: 0.6 | BB104: 1 | BC104: 0.6 | BD104: 1 | BE104: 1 | BF104: 1
B105: Acuerdo comercial | AY105: 0.6 | AZ105: 1 | BA105: 0.6 | BB105: 1 | BC105: 0.6 | BD105: 1 | BE105: 1 | BF105: 1
B106: Tratamiento de no conforme | AY106: 0.6 | AZ106: 1 | BA106: 0.6 | BB106: 1 | BC106: 1 | BD106: 1 | BE106: 1 | BF106: 1
B107: Nomenclatura | AY107: 1 | AZ107: 1 | BA107: 1 | BB107: 1 | BC107: 1 | BD107: 1 | BE107: 1 | BF107: 1
B108: Forecast | C108: 1 | D108: 1 | E108: 1 | F108: 0.4 | G108: 1 | H108: 1 | I108: 1 | J108: 0.55 | K108: 1 | L108: 1 | M108: 1 | N108: 0.55 | O108: 1 | P108: 1 | Q108: 1 | R108: 0.85 | S108: 1 | T108: 1 | U108: 1 | V108: 1 | W108: 1 | X108: 1 | Y108: 1 | Z108: 1 | AA108: 1 | AB108: 1 | AC108: 1 | AD108: 1 | AE108: 1 | AF108: 1 | AG108: 1 | AH108: 1 | AI108: 1 | AJ108: 1 | AK108: 1 | AL108: 1 | AM108: 1 | AN108: 1 | AO108: 1 | AP108: 1 | AQ108: 1 | AR108: 1 | AS108: 1 | AT108: 1 | AU108: 1 | AV108: 1 | AW108: 1 | AX108: 1 | AY108: 1 | AZ108: 1 | BA108: 1 | BB108: 1 | BC108: 1 | BD108: 1 | BE108: 1 | BF108: 1
B109: Probabilidad | AY109: 1 | AZ109: 1 | BA109: 1 | BB109: 1 | BC109: 1 | BD109: 1 | BE109: 1 | BF109: 1
B110: Impacto | AY110: 0.4 | AZ110: 1 | BA110: 0.4 | BB110: 1 | BC110: 0.4 | BD110: 1 | BE110: 1 | BF110: 1
B111: Plan de acción | AY111: 0 | AZ111: 1 | BA111: 0.6 | BB111: 1 | BC111: 0 | BD111: 1 | BE111: 1 | BF111: 1
B112: Conocimiento de persona | AY112: 0 | AZ112: 1 | BA112: 0 | BB112: 1 | BC112: 0 | BD112: 1 | BE112: 1 | BF112: 1
B113: Clase de vinculación | AY113: 0.6 | AZ113: 1 | BA113: 1 | BB113: 1 | BC113: 0.6 | BD113: 1 | BE113: 1 | BF113: 1
B114: Tipo de documento | AY114: 1 | AZ114: 1 | BA114: 1 | BB114: 1 | BC114: 1 | BD114: 1 | BE114: 1 | BF114: 1
B115: País | AY115: 1 | AZ115: 1 | BA115: 1 | BB115: 1 | BC115: 1 | BD115: 1 | BE115: 1 | BF115: 1
B116: Normas 9001 - 2015 | AY116: 1 | AZ116: 1 | BA116: 1 | BB116: 1 | BC116: 1 | BD116: 1 | BE116: 1 | BF116: 1
B117: Auditorías internas | AM117: 1 | AN117: 1 | AO117: 1 | AP117: 1 | AQ117: 1 | AR117: 1 | AS117: 1 | AT117: 1 | AU117: 1 | AV117: 1 | AW117: 1 | AX117: 1 | AY117: 1 | AZ117: 1 | BA117: 1 | BB117: 1 | BC117: 1 | BD117: 1 | BE117: 1 | BF117: 1
B118: Gestión de riesgos | AY118: 0.8 | AZ118: 1 | BA118: 0.6 | BB118: 1 | BC118: 1 | BD118: 1 | BE118: 0.6 | BF118: 1
B119: Programa | AY119: 0.8 | AZ119: 1 | BA119: 0.6 | BB119: 1 | BC119: 0.8 | BD119: 1 | BE119: 0.6 | BF119: 1
B120: Metodología | AY120: 0.8 | AZ120: 1 | BA120: 1 | BB120: 1 | BC120: 0.8 | BD120: 1 | BE120: 1 | BF120: 1
B121: Acción de mejora | AM121: 1 | AN121: 1 | AO121: 1 | AP121: 1 | AQ121: 1 | AR121: 1 | AS121: 1 | AT121: 1 | AU121: 1 | AV121: 1 | AW121: 1 | AX121: 1 | AY121: 1 | AZ121: 1 | BA121: 1 | BB121: 1 | BC121: 1 | BD121: 1 | BE121: 1 | BF121: 1
B122: Programa de seguimiento SGC | AM122: 1 | AN122: 1 | AO122: 1 | AP122: 1 | AQ122: 1 | AR122: 1 | AS122: 1 | AT122: 1 | AU122: 1 | AV122: 1 | AW122: 1 | AX122: 1 | AY122: 1 | AZ122: 1 | BA122: 1 | BB122: 1 | BC122: 1 | BD122: 1 | BE122: 1 | BF122: 1
B123: Acciones correctivas | AM123: 1 | AN123: 1 | AO123: 1 | AP123: 1 | AQ123: 1 | AR123: 1 | AS123: 1 | AT123: 1 | AU123: 1 | AV123: 1 | AW123: 1 | AX123: 1 | AY123: 1 | AZ123: 1 | BA123: 1 | BB123: 1 | BC123: 1 | BD123: 1 | BE123: 1 | BF123: 1
B124: Programa de auditorías | AM124: 1 | AN124: 1 | AO124: 1 | AP124: 1 | AQ124: 1 | AR124: 1 | AS124: 1 | AT124: 1 | AU124: 1 | AV124: 1 | AW124: 1 | AX124: 1 | AY124: 1 | AZ124: 1 | BA124: 1 | BB124: 1 | BC124: 1 | BD124: 1 | BE124: 1 | BF124: 1
B125: Banco de Ideas | AY125: 0.4 | AZ125: 1 | BA125: 1 | BB125: 1 | BC125: 0.4 | BD125: 1 | BE125: 1 | BF125: 1
B126: Compras | AI126: 1 | AJ126: 0.4 | AK126: 0.4 | AL126: 0.4 | AM126: 1 | AN126: 1 | AO126: 1 | AP126: 1 | AQ126: 1 | AR126: 1 | AS126: 1 | AT126: 1 | AU126: 1 | AV126: 1 | AW126: 1 | AX126: 1 | AY126: 1 | AZ126: 1 | BA126: 1 | BB126: 1 | BC126: 1 | BD126: 1 | BE126: 1 | BF126: 1
B127: Contratación | AI127: 1 | AJ127: 0.4 | AK127: 0.4 | AL127: 0.4 | AM127: 1 | AN127: 1 | AO127: 1 | AP127: 1 | AQ127: 1 | AR127: 1 | AS127: 1 | AT127: 1 | AU127: 1 | AV127: 1 | AW127: 1 | AX127: 1 | AY127: 1 | AZ127: 1 | BA127: 1 | BB127: 1 | BC127: 1 | BD127: 1 | BE127: 1 | BF127: 1
B128: Evaluación de proveedores | AY128: 1 | AZ128: 1 | BA128: 1 | BB128: 1 | BC128: 1 | BD128: 1 | BE128: 1 | BF128: 1
B129: Presupuesto del modelo financiero | AY129: 1 | AZ129: 1 | BA129: 1 | BB129: 1 | BC129: 1 | BD129: 1 | BE129: 1 | BF129: 1
B130: Órden de contratación | AM130: 1 | AN130: 1 | AO130: 1 | AP130: 1 | AQ130: 1 | AR130: 1 | AS130: 1 | AT130: 1 | AU130: 1 | AV130: 1 | AW130: 1 | AX130: 1 | AY130: 1 | AZ130: 1 | BA130: 1 | BB130: 1 | BC130: 1 | BD130: 1 | BE130: 1 | BF130: 1
B131: Inventario | AY131: 0.4 | AZ131: 1 | BA131: 1 | BB131: 1 | BC131: 0.4 | BD131: 1 | BE131: 1 | BF131: 1
B132: Evaluación de Sagrilaft | AY132: 1 | AZ132: 1 | BA132: 1 | BB132: 1 | BC132: 1 | BD132: 1 | BE132: 1 | BF132: 1
B133: Solicitud para anexo y Otrosí | AI133: 1 | AJ133: 0.4 | AK133: 0.4 | AL133: 1 | AM133: 1 | AN133: 1 | AO133: 1 | AP133: 1 | AQ133: 1 | AR133: 1 | AS133: 1 | AT133: 1 | AU133: 1 | AV133: 1 | AW133: 1 | AX133: 1 | AY133: 1 | AZ133: 1 | BA133: 1 | BB133: 1 | BC133: 1 | BD133: 1 | BE133: 1 | BF133: 1
B134: Solicitud para Acuerdo Marco | AY134: 0.6 | AZ134: 1 | BA134: 0.6 | BB134: 1 | BC134: 0.6 | BD134: 1 | BE134: 0.6 | BF134: 1
B135: Recibido a conformidad proveedores | AY135: 0.7 | AZ135: 1 | BA135: 1 | BB135: 1 | BC135: 0.7 | BD135: 1 | BE135: 1 | BF135: 1
B136: Sagrilaft persona | AY136: 0.7 | AZ136: 1 | BA136: 1 | BB136: 1 | BC136: 0.7 | BD136: 1 | BE136: 1 | BF136: 1
B137: Movimiento de inventario | AY137: 0 | AZ137: 1 | BA137: 0.4 | BB137: 1 | BC137: 0 | BD137: 1 | BE137: 1 | BF137: 1
B138: Activos fijos | AY138: 0.7 | AZ138: 1 | BA138: 1 | BB138: 1 | BC138: 0.7 | BD138: 1 | BE138: 1 | BF138: 1
B139: Nivel Criticidad Proveedores Sagrilaft | AY139: 0.8 | AZ139: 1 | BA139: 1 | BB139: 1 | BC139: 0.8 | BD139: 1 | BE139: 1 | BF139: 1
B140: Constitución del proyecto | AY140: 0.8 | AZ140: 1 | BA140: 1 | BB140: 1 | BC140: 0.8 | BD140: 1 | BE140: 1 | BF140: 1
B141: Plan de trabajo | AY141: 0.8 | AZ141: 1 | BA141: 1 | BB141: 1 | BC141: 1 | BD141: 1 | BE141: 1 | BF141: 1
...

Sheet Uso-Acceso Datos
B1: Se realiza sobre las entidades identificadas en los procesos
C2: =AVERAGE(Tabla13[Uso y acceso Ago/2024]) -> 0.86971154 | D2: =AVERAGE(Tabla13[Uso y acceso Sep/2024]) -> 0.87163462 | E2: =AVERAGE(Tabla13[Uso y acceso Oct/2024]) -> 0.94182692 | F2: =AVERAGE(Tabla13[Uso y acceso Nov/2024]) -> 0.94459135 | G2: =AVERAGE(Tabla13[Uso y acceso Dic/2024]) -> 0.95766827 | H2: =AVERAGE(Tabla13[Uso y acceso Ene/2025]) -> 0.95766827 | I2: =AVERAGE(Tabla13[Uso y acceso Feb/2025]) -> 0.95941038 | J2: =AVERAGE(Tabla13[Uso y acceso Mar/2025]) -> 0.95941038 | K2: =AVERAGE(Tabla13[Uso y acceso Abr/2025]) -> 0.96052752 | L2: =AVERAGE(Tabla13[Uso y acceso May/2025]) -> 0.97845291 | M2: =AVERAGE(Tabla13[Uso y acceso Jun/2025]) -> 0.97847534 | N2: =AVERAGE(Tabla13[Uso y acceso Sep/2025]) -> 0.97847534 | O2: =AVERAGE(Tabla13[Uso y acceso Dic/2025]) -> 0.98779412 | P2: =AVERAGE(Tabla13[Uso y acceso Mar/2026]) -> 0.98403361
B3: Entidades | C3: Uso y acceso Ago/2024 | D3: Uso y acceso Sep/2024 | E3: Uso y acceso Oct/2024 | F3: Uso y acceso Nov/2024 | G3: Uso y acceso Dic/2024 | H3: Uso y acceso Ene/2025 | I3: Uso y acceso Feb/2025 | J3: Uso y acceso Mar/2025 | K3: Uso y acceso Abr/2025 | L3: Uso y acceso May/2025 | M3: Uso y acceso Jun/2025 | N3: Uso y acceso Sep/2025 | O3: Uso y acceso Dic/2025 | P3: Uso y acceso Mar/2026
B4: Oportunidades | C4: 1 | D4: 1 | E4: 1 | F4: 1 | G4: 1 | H4: 1 | I4: 1 | J4: 1 | K4: 1 | L4: 1 | M4: 1 | N4: 1 | O4: 1 | P4: 1
B5: Línea de negocios | C5: 1 | D5: 1 | E5: 1 | F5: 1 | G5: 1 | H5: 1 | I5: 1 | J5: 1 | K5: 1 | L5: 1 | M5: 1 | N5: 1 | O5: 1 | P5: 1
B6: Equipo de ventas | C6: 1 | D6: 1 | E6: 1 | F6: 1 | G6: 1 | H6: 1 | I6: 1 | J6: 1 | K6: 1 | L6: 1 | M6: 1 | N6: 1 | O6: 1 | P6: 1
B7: Tipo de cliente | C7: 1 | D7: 1 | E7: 1 | F7: 1 | G7: 1 | H7: 1 | I7: 1 | J7: 1 | K7: 1 | L7: 1 | M7: 1 | N7: 1 | O7: 1 | P7: 1
B8: Cliente | C8: 1 | D8: 1 | E8: 1 | F8: 1 | G8: 1 | H8: 1 | I8: 1 | J8: 1 | K8: 1 | L8: 1 | M8: 1 | N8: 1 | O8: 1 | P8: 1
B9: Tipo de venta | C9: 1 | D9: 1 | E9: 1 | F9: 1 | G9: 1 | H9: 1 | I9: 1 | J9: 1 | K9: 1 | L9: 1 | M9: 1 | N9: 1 | O9: 1 | P9: 1
B10: Tipo de oportunidad | C10: 1 | D10: 1 | E10: 1 | F10: 1 | G10: 1 | H10: 1 | I10: 1 | J10: 1 | K10: 1 | L10: 1 | M10: 1 | N10: 1 | O10: 1 | P10: 1
B11: Etapa actual | C11: 1 | D11: 1 | E11: 1 | F11: 1 | G11: 1 | H11: 1 | I11: 1 | J11: 1 | K11: 1 | L11: 1 | M11: 1 | N11: 1 | O11: 1 | P11: 1
B12: Ganado | C12: 1 | D12: 1 | E12: 1 | F12: 1 | G12: 1 | H12: 1 | I12: 1 | J12: 1 | K12: 1 | L12: 1 | M12: 1 | N12: 1 | O12: 1 | P12: 1
B13: Metas | C13: 1 | D13: 1 | E13: 1 | F13: 1 | G13: 1 | H13: 1 | I13: 1 | J13: 1 | K13: 1 | L13: 1 | M13: 1 | N13: 1 | O13: 1 | P13: 1
B14: Metas de Comercial | C14: 1 | D14: 1 | E14: 1 | F14: 1 | G14: 1 | H14: 1 | I14: 1 | J14: 1 | K14: 1 | L14: 1 | M14: 1 | N14: 1 | O14: 1 | P14: 1
B15: Área | C15: 1 | D15: 1 | E15: 1 | F15: 1 | G15: 1 | H15: 1 | I15: 1 | J15: 1 | K15: 1 | L15: 1 | M15: 1 | N15: 1 | O15: 1 | P15: 1
... B211: Hallazgos | C211: 1 | D211: 1 | E211: 1 | F211: 1 | G211: 1 | H211: 1 | I211: 1 | J211: 1 | K211: 1 | L211: 1 | M211: 1 | N211: 1 | O211: 1 | P211: 1
B212: Tipo de retiro | I212: 1 | J212: 1 | K212: 1 | L212: 1 | M212: 1 | N212: 1 | O212: 1 | P212: 1
B213: Tipo de movimiento laboral | I213: 1 | J213: 1 | K213: 1 | L213: 1 | M213: 1 | N213: 1 | O213: 1 | P213: 1
B214: Tipo de fuero | I214: 1 | J214: 1 | K214: 1 | L214: 1 | M214: 1 | N214: 1 | O214: 1 | P214: 1
B215: Generación por año de nacimiento | I215: 1 | J215: 1 | K215: 1 | L215: 1 | M215: 1 | N215: 1 | O215: 1 | P215: 1
B216: Identificación del proceso | K216: 1 | L216: 1 | M216: 1 | N216: 1 | O216: 1 | P216: 1
B217: Modalidad de contratación | K217: 1 | L217: 1 | M217: 1 | N217: 1 | O217: 1 | P217: 1
B218: Sector | K218: 1 | L218: 1 | M218: 1 | N218: 1 | O218: 1 | P218: 1
B219: Subsector | K219: 1 | L219: 1 | M219: 1 | N219: 1 | O219: 1 | P219: 1
B220: Orden de servicio | K220: 1 | L220: 1 | M220: 1 | N220: 1 | O220: 1 | P220: 1
B221: Orden de trabajo | K221: 1 | L221: 1 | M221: 1 | N221: 1 | O221: 1 | P221: 1
B222: Categoría servicios TI | L222: 1 | M222: 1 | N222: 1 | O222: 1 | P222: 1
B223: Servicios TI | L223: 1 | M223: 1 | N223: 1 | O223: 1 | P223: 1
B224: Control de acceso | L224: 1 | M224: 1 | N224: 1 | O224: 1 | P224: 1
B225: Evento | L225: 1 | M225: 1 | N225: 1 | O225: 1 | P225: 1
B226: Canales digitales | L226: 1 | M226: 1 | N226: 1 | O226: 1 | P226: 1
B227: Medio de solicitud a doit | O227: 1 | P227: 1
B228: Prioridad del Ticket | O228: 1 | P228: 1
B229: Naturaleza del caso | O229: 1 | P229: 1
B230: Estados de los tickets TI | O230: 1 | P230: 1
B231: Estado orden de servicio | O231: 1 | P231: 1
B232: Canal de recepción | O232: 1 | P232: 1
B233: Canal de comunicación | O233: 1 | P233: 1
B234: Tipo de entregable | O234: 1 | P234: 1
B235: Segmentación Proyectos | O235: 1 | P235: 1
B236: Rubros del Modelo Financiero | O236: 1 | P236: 1
B237: Subrubros del Modelo Financiero | O237: 1 | P237: 1
B238: Rubros del Presupuesto General | O238: 1 | P238: 1
... B241: Área Financiera | O241: 1 | P241: 1

Sheet Integracion-Flujo Datos
B1: Se realiza sobre las entidades identificadas en los procesos
C2: =AVERAGE(Tabla58[Integración Ago/2024]) -> 0.18028846 | D2: =AVERAGE(Tabla58[Integración Sep/2024]) -> 0.18125 | E2: =AVERAGE(Tabla58[Integración Oct/2024]) -> 0.19591346 | F2: =AVERAGE(Tabla58[Integración Nov/2024]) -> 0.21730769 | G2: =AVERAGE(Tabla58[Integración Dic/2024]) -> 0.25192308 | H2: =AVERAGE(Tabla58[Integración Ene/2025]) -> 0.25528846 | I2: =AVERAGE(Tabla58[Integración Feb/2025]) -> 0.29292453 | J2: =AVERAGE(Tabla58[Integración Mar/2025]) -> 0.29292453 | K2: =AVERAGE(Tabla58[Integración Abr/2025]) -> 0.32981651 | L2: =AVERAGE(Tabla58[Integración May/2025]) -> 0.34394619 | M2: =AVERAGE(Tabla58[Integración Jun/2025]) -> 0.35560538 | N2: =AVERAGE(Tabla58[Integración Sep/2025]) -> 0.3632287 | O2: =AVERAGE(Tabla58[Integración Dic/2025]) -> 0.80042017 | P2: =AVERAGE(Tabla58[Integración Mar/2026]) -> 0.79957983
B3: Entidades | C3: Integración Ago/2024 | D3: Integración Sep/2024 | E3: Integración Oct/2024 | F3: Integración Nov/2024 | G3: Integración Dic/2024 | H3: Integración Ene/2025 | I3: Integración Feb/2025 | J3: Integración Mar/2025 | K3: Integración Abr/2025 | L3: Integración May/2025 | M3: Integración Jun/2025 | N3: Integración Sep/2025 | O3: Integración Dic/2025 | P3: Integración Mar/2026
B4: Oportunidades | C4: 1 | D4: 1 | E4: 1 | F4: 1 | G4: 1 | H4: 1 | I4: 1 | J4: 1 | K4: 1 | L4: 1 | M4: 1 | N4: 1 | O4: 1 | P4: 1
B5: Línea de negocios | C5: 1 | D5: 1 | E5: 1 | F5: 1 | G5: 1 | H5: 1 | I5: 1 | J5: 1 | K5: 1 | L5: 1 | M5: 1 | N5: 1 | O5: 1 | P5: 1
B6: Equipo de ventas | C6: 1 | D6: 1 | E6: 1 | F6: 1 | G6: 1 | H6: 1 | I6: 1 | J6: 1 | K6: 1 | L6: 1 | M6: 1 | N6: 1 | O6: 1 | P6: 1
B7: Tipo de cliente | C7: 1 | D7: 1 | E7: 1 | F7: 1 | G7: 1 | H7: 1 | I7: 1 | J7: 1 | K7: 1 | L7: 1 | M7: 1 | N7: 1 | O7: 1 | P7: 1
B8: Cliente | C8: 1 | D8: 1 | E8: 1 | F8: 1 | G8: 1 | H8: 1 | I8: 1 | J8: 1 | K8: 1 | L8: 1 | M8: 1 | N8: 1 | O8: 1 | P8: 1
B9: Tipo de venta | C9: 1 | D9: 1 | E9: 1 | F9: 1 | G9: 1 | H9: 1 | I9: 1 | J9: 1 | K9: 1 | L9: 1 | M9: 1 | N9: 1 | O9: 1 | P9: 1
B10: Tipo de oportunidad | C10: 1 | D10: 1 | E10: 1 | F10: 1 | G10: 1 | H10: 1 | I10: 1 | J10: 1 | K10: 1 | L10: 1 | M10: 1 | N10: 1 | O10: 1 | P10: 1
B11: Etapa actual | C11: 1 | D11: 1 | E11: 1 | F11: 1 | G11: 1 | H11: 1 | I11: 1 | J11: 1 | K11: 1 | L11: 1 | M11: 1 | N11: 1 | O11: 1 | P11: 1
B12: Ganado | C12: 1 | D12: 1 | E12: 1 | F12: 1 | G12: 1 | H12: 1 | I12: 1 | J12: 1 | K12: 1 | L12: 1 | M12: 1 | N12: 1 | O12: 1 | P12: 1
B13: Metas | C13: 1 | D13: 1 | E13: 1 | F13: 1 | G13: 1 | H13: 1 | I13: 1 | J13: 1 | K13: 1 | L13: 1 | M13: 1 | N13: 1 | O13: 1 | P13: 1
B14: Metas de Comercial | C14: 1 | D14: 1 | E14: 1 | F14: 1 | G14: 1 | H14: 1 | I14: 1 | J14: 1 | K14: 1 | L14: 1 | M14: 1 | N14: 1 | O14: 1 | P14: 1
B15: Área | C15: 1 | D15: 1 | E15: 1 | F15: 1 | G15: 1 | H15: 1 | I15: 1 | J15: 1 | K15: 1 | L15: 1 | M15: 1 | N15: 1 | O15: 1 | P15: 1
... B211: Hallazgos | C211: 0 | D211: 0 | E211: 0 | F211: 0 | G211: 0 | H211: 0 | I211: 0 | J211: 0 | K211: 0 | L211: 0.3 | M211: 0.3 | N211: 0.3 | O211: 0.6 | P211: 0.6
B212: Tipo de retiro | I212: 1 | J212: 1 | K212: 1 | L212: 1 | M212: 1 | N212: 1 | O212: 1 | P212: 1
B213: Tipo de movimiento laboral | I213: 1 | J213: 1 | K213: 1 | L213: 1 | M213: 1 | N213: 1 | O213: 1 | P213: 1
B214: Tipo de fuero | I214: 1 | J214: 1 | K214: 1 | L214: 1 | M214: 1 | N214: 1 | O214: 1 | P214: 1
B215: Generación por año de nacimiento | I215: 1 | J215: 1 | K215: 1 | L215: 1 | M215: 1 | N215: 1 | O215: 1 | P215: 1
B216: Identificación del proceso | K216: 1 | L216: 1 | M216: 1 | N216: 1 | O216: 1 | P216: 1
B217: Modalidad de contratación | K217: 1 | L217: 1 | M217: 1 | N217: 1 | O217: 1 | P217: 1
B218: Sector | K218: 1 | L218: 1 | M218: 1 | N218: 1 | O218: 1 | P218: 1
B219: Subsector | K219: 1 | L219: 1 | M219: 1 | N219: 1 | O219: 1 | P219: 1
B220: Orden de servicio | K220: 0.3 | L220: 0.3 | M220: 0.3 | N220: 0.3 | O220: 0.8 | P220: 0.8
B221: Orden de trabajo | K221: 0.3 | L221: 0.3 | M221: 0.3 | N221: 0.3 | O221: 0.8 | P221: 0.8
B222: Categoría servicios TI | L222: 0.3 | M222: 0.3 | N222: 0.3 | O222: 1 | P222: 1
B223: Servicios TI | L223: 0.3 | M223: 0.3 | N223: 0.3 | O223: 1 | P223: 1
B224: Control de acceso | L224: 0.3 | M224: 0.3 | N224: 0.3 | O224: 0.8 | P224: 0.8
B225: Evento | L225: 0.3 | M225: 0.3 | N225: 0.3 | O225: 0.8 | P225: 0.8
B226: Canales digitales | L226: 0.3 | M226: 0.3 | N226: 0.3 | O226: 1 | P226: 1
B227: Medio de solicitud a doit | O227: 1 | P227: 1
B228: Prioridad del Ticket | O228: 1 | P228: 1
B229: Naturaleza del caso | O229: 1 | P229: 1
B230: Estados de los tickets TI | O230: 1 | P230: 1
B231: Estado orden de servicio | O231: 1 | P231: 1
B232: Canal de recepción | O232: 1 | P232: 1
B233: Canal de comunicación | O233: 1 | P233: 1
B234: Tipo de entregable | O234: 1 | P234: 1
B235: Segmentación Proyectos | O235: 1 | P235: 1
B236: Rubros del Modelo Financiero | O236: 1 | P236: 1
B237: Subrubros del Modelo Financiero | O237: 1 | P237: 1
B238: Rubros del Presupuesto General | O238: 1 | P238: 1
... B241: Área Financiera | O241: 1 | P241: 1

Sheet Gestion Ciclo-Vida Datos
B1: Se realiza sobre las entidades identificadas en los procesos. Esta definido por los indicadores Calidad de datos, Uso-Acceso Datos, Integración-Flujo de datos; adicional a estos Creación y captura, Almacenamiento y registro
C2: =IFERROR(AVERAGEIF(Tabla4[Creación y captura Ago/2024],">0",Tabla4[Creación y captura Ago/2024]),0) -> 0.99605263 | D2: =IFERROR(AVERAGEIF(Tabla4[Almacenamiento y registro Ago/2024],">0",Tabla4[Almacenamiento y registro Ago/2024]),0) -> 0.98684211 | E2: =IFERROR(AVERAGEIF(Tabla4[Calidad de datos Ago/2024],">0",Tabla4[Calidad de datos Ago/2024]),0) -> 0.93565789 | F2: =IF(ISERROR(AVERAGE(Tabla4[Uso y acceso Ago/2024])),"",AVERAGE(Tabla4[Uso y acceso Ago/2024])) -> 0.86971154 | G2: =IF(ISERROR(AVERAGE(Tabla4[Compartición e Interoperabilidad Ago/2024])),"",AVERAGE(Tabla4[Compartición e Interoperabilidad Ago/2024])) -> 0.18028846 | H2: =IF(ISERROR(AVERAGE(C2:G2)),"",AVERAGE(C2:G2)) -> 0.79371053 | I2: =IFERROR(AVERAGEIF(Tabla4[Creación y captura Sep/2024],">0",Tabla4[Creación y captura Sep/2024]),0) -> 0.97948718 | J2: =IFERROR(AVERAGEIF(Tabla4[Almacenamiento y registro Sep/2024],">0",Tabla4[Almacenamiento y registro Sep/2024]),0) -> 0.96666667 | K2: =IFERROR(AVERAGEIF(Tabla4[Calidad de datos Sep/2024],">0",Tabla4[Calidad de datos Sep/2024]),0) -> 0.94888158 | L2: =IF(ISERROR(AVERAGE(Tabla4[Uso y acceso Sep/2024])),"",AVERAGE(Tabla4[Uso y acceso Sep/2024])) -> 0.87163462 | M2: =IF(ISERROR(AVERAGE(Tabla4[Compartición e Interoperabilidad Sep/2024])),"",AVERAGE(Tabla4[Compartición e Interoperabilidad Sep/2024])) -> 0.18125 | N2: =IF(ISERROR(AVERAGE(I2:M2)),"",AVERAGE(I2:M2)) -> 0.78958401 | O2: =IFERROR(AVERAGEIF(Tabla4[Creación y captura Oct/2024],">0",Tabla4[Creación y captura Oct/2024]),0) -> 0.86666667 | P2: =IFERROR(AVERAGEIF(Tabla4[Almacenamiento y registro Oct/2024],">0",Tabla4[Almacenamiento y registro Oct/2024]),0) -> 0.79901961 | Q2: =IFERROR(AVERAGEIF(Tabla4[Calidad de datos Oct/2024],">0",Tabla4[Calidad de datos Oct/2024]),0) -> 0.94888158 | R2: =IF(ISERROR(AVERAGE(Tabla4[Uso y acceso Oct/2024])),"",AVERAGE(Tabla4[Uso y acceso Oct/2024])) -> 0.94182692 | S2: =IF(ISERROR(AVERAGE(Tabla4[Compartición e Interoperabilidad Oct/2024])),"",AVERAGE(Tabla4[Compartición e Interoperabilidad Oct/2024])) -> 0.19591346 | T2: =IF(ISERROR(AVERAGE(O2:S2)),"",AVERAGE(O2:S2)) -> 0.75046165 | U2: =IFERROR(AVERAGEIF(Tabla4[Creación y captura Nov/2024],">0",Tabla4[Creación y captura Nov/2024]),0) -> 0.96785714 | V2: =IFERROR(AVERAGEIF(Tabla4[Almacenamiento y registro Nov/2024],">0",Tabla4[Almacenamiento y registro Nov/2024]),0) -> 0.91730769 | W2: =IFERROR(AVERAGEIF(Tabla4[Calidad de datos Nov/2024],">0",Tabla4[Calidad de datos Nov/2024]),0) -> 0.94982143 | X2: =IF(ISERROR(AVERAGE(Tabla4[Uso y acceso Nov/2024])),"",AVERAGE(Tabla4[Uso y acceso Nov/2024])) -> 0.94459135 | Y2: =IF(ISERROR(AVERAGE(Tabla4[Compartición e Interoperabilidad Nov/2024])),"",AVERAGE(Tabla4[Compartición e Interoperabilidad Nov/2024])) -> 0.21730769 | Z2: =IF(ISERROR(AVERAGE(U2:Y2)),"",AVERAGE(U2:Y2)) -> 0.79937706 | AA2: =IFERROR(AVERAGEIF(Tabla4[Creación y captura Dic/2024],">0",Tabla4[Creación y captura Dic/2024]),0) -> 0.97142857 | AB2: =IFERROR(AVERAGEIF(Tabla4[Almacenamiento y registro Dic/2024],">0",Tabla4[Almacenamiento y registro Dic/2024]),0) -> 0.98867925 | AC2: =IFERROR(AVERAGEIF(Tabla4[Calidad de datos Dic/2024],">0",Tabla4[Calidad de datos Dic/2024]),0) -> 0.96267857 | AD2: =IF(ISERROR(AVERAGE(Tabla4[Uso y acceso Dic/2024])),"",AVERAGE(Tabla4[Uso y acceso Dic/2024])) -> 0.95766827 | AE2: =IF(ISERROR(AVERAGE(Tabla4[Compartición e Interoperabilidad Dic/2024])),"",AVERAGE(Tabla4[Compartición e Interoperabilidad Dic/2024])) -> 0.25192308 | AF2: =IF(ISERROR(AVERAGE(AA2:AE2)),"",AVERAGE(AA2:AE2)) -> 0.82647555 | AG2: =IFERROR(AVERAGEIF(Tabla4[Creación y captura Ene/2025],">0",Tabla4[Creación y captura Ene/2025]),0) -> 0.98571429 | AH2: =IFERROR(AVERAGEIF(Tabla4[Almacenamiento y registro Ene/2025],">0",Tabla4[Almacenamiento y registro Ene/2025]),0) -> 0.98611111 | AI2: =IFERROR(AVERAGEIF(Tabla4[Calidad de datos Ene/2025],">0",Tabla4[Calidad de datos Ene/2025]),0) -> 0.97705357 | AJ2: =IF(ISERROR(AVERAGE(Tabla4[Uso y acceso Ene/2025])),"",AVERAGE(Tabla4[Uso y acceso Ene/2025])) -> 0.95766827 | AK2: =IF(ISERROR(AVERAGE(Tabla4[Compartición e Interoperabilidad Ene/2025])),"",AVERAGE(Tabla4[Compartición e Interoperabilidad Ene/2025])) -> 0.25528846 | AL2: =IF(ISERROR(AVERAGE(AG2:AK2)),"",AVERAGE(AG2:AK2)) -> 0.83236714 | AM2: =IFERROR(AVERAGEIF(Tabla4[Creación y captura Feb/2025],">0",Tabla4[Creación y captura Feb/2025]),0) -> 0.98934426 | AN2: =IFERROR(AVERAGEIF(Tabla4[Almacenamiento y registro Feb/2025],">0",Tabla4[Almacenamiento y registro Feb/2025]),0) -> 0.99344262 | AO2: =IFERROR(AVERAGEIF(Tabla4[Calidad de datos Feb/2025],">0",Tabla4[Calidad de datos Feb/2025]),0) -> 0.98616667 | AP2: =IF(ISERROR(AVERAGE(Tabla4[Uso y acceso Feb/2025])),"",AVERAGE(Tabla4[Uso y acceso Feb/2025])) -> 0.95941038 | AQ2: =IF(ISERROR(AVERAGE(Tabla4[Compartición e Interoperabilidad Feb/2025])),"",AVERAGE(Tabla4[Compartición e Interoperabilidad Feb/2025])) -> 0.29292453 | AR2: =IF(ISERROR(AVERAGE(AM2:AQ2)),"",AVERAGE(AM2:AQ2)) -> 0.84425769 | AS2: =IFERROR(AVERAGEIF(Tabla4[Creación y captura Mar/2025],">0",Tabla4[Creación y captura Mar/2025]),0) -> 0.99166667 | AT2: =IFERROR(AVERAGEIF(Tabla4[Almacenamiento y registro Mar/2025],">0",Tabla4[Almacenamiento y registro Mar/2025]),0) -> 1 | AU2: =IFERROR(AVERAGEIF(Tabla4[Calidad de datos Mar/2025],">0",Tabla4[Calidad de datos Mar/2025]),0) -> 0.98679167 | AV2: =IF(ISERROR(AVERAGE(Tabla4[Uso y acceso Mar/2025])),"",AVERAGE(Tabla4[Uso y acceso Mar/2025])) -> 0.95941038 | AW2: =IF(ISERROR(AVERAGE(Tabla4[Compartición e Interoperabilidad Mar/2025])),"",AVERAGE(Tabla4[Compartición e Interoperabilidad Mar/2025])) -> 0.29292453 | AX2: =IF(ISERROR(AVERAGE(AS2:AW2)),"",AVERAGE(AS2:AW2)) -> 0.84615865 | AY2: =IFERROR(AVERAGEIF(Tabla4[Creación y captura Abr/2025],">0",Tabla4[Creación y captura Abr/2025]),0) -> 0.9575 | AZ2: =IFERROR(AVERAGEIF(Tabla4[Almacenamiento y registro Abr/2025],">0",Tabla4[Almacenamiento y registro Abr/2025]),0) -> 0.9025 | BA2: =IFERROR(AVERAGEIF(Tabla4[Calidad de datos Abr/2025],">0",Tabla4[Calidad de datos Abr/2025]),0) -> 0.93965625 | BB2: =IF(ISERROR(AVERAGE(Tabla4[Uso y acceso Abr/2025])),"",AVERAGE(Tabla4[Uso y acceso Abr/2025])) -> 0.96052752 | BC2: =IF(ISERROR(AVERAGE(Tabla4[Compartición e Interoperabilidad Abr/2025])),"",AVERAGE(Tabla4[Compartición e Interoperabilidad Abr/2025])) -> 0.32981651 | BD2: =IF(ISERROR(AVERAGE(AY2:BC2)),"",AVERAGE(AY2:BC2)) -> 0.81800006 | BE2: =IFERROR(AVERAGEIF(Tabla4[Creación y captura May/2025],">0",Tabla4[Creación y captura May/2025]),0) -> 0.927 | BF2: =IFERROR(AVERAGEIF(Tabla4[Almacenamiento y registro May/2025],">0",Tabla4[Almacenamiento y registro May/2025]),0) -> 0.837 | BG2: =IFERROR(AVERAGEIF(Tabla4[Calidad de datos May/2025],">0",Tabla4[Calidad de datos May/2025]),0) -> 0.99675 | BH2: =IF(ISERROR(AVERAGE(Tabla4[Uso y acceso May/2025])),"",AVERAGE(Tabla4[Uso y acceso May/2025])) -> 0.97845291 | BI2: =IF(ISERROR(AVERAGE(Tabla4[Compartición e Interoperabilidad May/2025])),"",AVERAGE(Tabla4[Compartición e Interoperabilidad May/2025])) -> 0.34394619 | BJ2: =IF(ISERROR(AVERAGE(BE2:BI2)),"",AVERAGE(BE2:BI2)) -> 0.81662982 | BK2: =IFERROR(AVERAGEIF(Tabla4[Creación y captura Jun/2025],">0",Tabla4[Creación y captura Jun/2025]),0) -> 0.91553398 | BL2: =IFERROR(AVERAGEIF(Tabla4[Almacenamiento y registro Jun/2025],">0",Tabla4[Almacenamiento y registro Jun/2025]),0) -> 0.83009709 | BM2: =IFERROR(AVERAGEIF(Tabla4[Calidad de datos Jun/2025],">0",Tabla4[Calidad de datos Jun/2025]),0) -> 0.997375 | BN2: =IF(ISERROR(AVERAGE(Tabla4[Uso y acceso Jun/2025])),"",AVERAGE(Tabla4[Uso y acceso Jun/2025])) -> 0.97847534 | BO2: =IF(ISERROR(AVERAGE(Tabla4[Compartición e Interoperabilidad Jun/2025])),"",AVERAGE(Tabla4[Compartición e Interoperabilidad Jun/2025])) -> 0.35560538 | BP2: =IF(ISERROR(AVERAGE(BK2:BO2)),"",AVERAGE(BK2:BO2)) -> 0.81541736 | BQ2: =IFERROR(AVERAGEIF(Tabla4[Creación y captura Sep/2025],">0",Tabla4[Creación y captura Sep/2025]),0) -> 0.8968254 | BR2: =IFERROR(AVERAGEIF(Tabla4[Almacenamiento y registro Sep/2025],">0",Tabla4[Almacenamiento y registro Sep/2025]),0) -> 0.78015873 | BS2: =IFERROR(AVERAGEIF(Tabla4[Calidad de datos Sep/2025],">0",Tabla4[Calidad de datos Sep/2025]),0) -> 1 | BT2: =IF(ISERROR(AVERAGE(Tabla4[Uso y acceso Sep/2025])),"",AVERAGE(Tabla4[Uso y acceso Sep/2025])) -> 0.97847534 | BU2: =IF(ISERROR(AVERAGE(Tabla4[Compartición e Interoperabilidad Sep/2025])),"",AVERAGE(Tabla4[Compartición e Interoperabilidad Sep/2025])) -> 0.3632287 | BV2: =IF(ISERROR(AVERAGE(BQ2:BU2)),"",AVERAGE(BQ2:BU2)) -> 0.80373763 | BW2: =IFERROR(AVERAGEIF(Tabla4[Creación y captura Dic/2025],">0",Tabla4[Creación y captura Dic/2025]),0) -> 0.95766423 | BX2: =IFERROR(AVERAGEIF(Tabla4[Almacenamiento y registro Dic/2025],">0",Tabla4[Almacenamiento y registro Dic/2025]),0) -> 0.90510949 | BY2: =IFERROR(AVERAGEIF(Tabla4[Calidad de datos Dic/2025],">0",Tabla4[Calidad de datos Dic/2025]),0) -> 0.91163813 | BZ2: =IF(ISERROR(AVERAGE(Tabla4[Uso y acceso Dic/2025])),"",AVERAGE(Tabla4[Uso y acceso Dic/2025])) -> 0.98779412 | CA2: =IF(ISERROR(AVERAGE(Tabla4[Compartición e Interoperabilidad Dic/2025])),"",AVERAGE(Tabla4[Compartición e Interoperabilidad Dic/2025])) -> 0.80042017 | CB2: =IF(ISERROR(AVERAGE(BW2:CA2)),"",AVERAGE(BW2:CA2)) -> 0.91252523 | CC2: =IFERROR(AVERAGEIF(Tabla4[Creación y captura Mar/2026],">0",Tabla4[Creación y captura Mar/2026]),0) -> 0.81344538 | CD2: =IFERROR(AVERAGEIF(Tabla4[Almacenamiento y registro Mar/2026],">0",Tabla4[Almacenamiento y registro Mar/2026]),0) -> 0.76596639 | CE2: =IFERROR(AVERAGEIF(Tabla4[Calidad de datos Mar/2026],">0",Tabla4[Calidad de datos Mar/2026]),0) -> 0.95252101 | CF2: =IF(ISERROR(AVERAGE(Tabla4[Uso y acceso Mar/2026])),"",AVERAGE(Tabla4[Uso y acceso Mar/2026])) -> 0.98403361 | CG2: =IF(ISERROR(AVERAGE(Tabla4[Compartición e Interoperabilidad Mar/2026])),"",AVERAGE(Tabla4[Compartición e Interoperabilidad Mar/2026])) -> 0.79957983 | CH2: =IF(ISERROR(AVERAGE(CC2:CG2)),"",AVERAGE(CC2:CG2)) -> 0.86310924
B3: Entidades | C3: Creación y captura Ago/2024 | D3: Almacenamiento y registro Ago/2024 | E3: Calidad de datos Ago/2024 | F3: Uso y acceso Ago/2024 | G3: Compartición e Interoperabilidad Ago/2024 | H3: Gestión ciclo de Vida Ago/2024 | I3: Creación y captura Sep/2024 | J3: Almacenamiento y registro Sep/2024 | K3: Calidad de datos Sep/2024 | L3: Uso y acceso Sep/2024 | M3: Compartición e Interoperabilidad Sep/2024 | N3: Gestión ciclo de Vida Sep/2024 | O3: Creación y captura Oct/2024 | P3: Almacenamiento y registro Oct/2024 | Q3: Calidad de datos Oct/2024 | R3: Uso y acceso Oct/2024 | S3: Compartición e Interoperabilidad Oct/2024 | T3: Gestión ciclo de Vida Oct/2024 | U3: Creación y captura Nov/2024 | V3: Almacenamiento y registro Nov/2024 | W3: Calidad de datos Nov/2024 | X3: Uso y acceso Nov/2024 | Y3: Compartición e Interoperabilidad Nov/2024 | Z3: Gestión ciclo de Vida Nov/2024 | AA3: Creación y captura Dic/2024 | AB3: Almacenamiento y registro Dic/2024 | AC3: Calidad de datos Dic/2024 | AD3: Uso y acceso Dic/2024 | AE3: Compartición e Interoperabilidad Dic/2024 | AF3: Gestión ciclo de Vida Dic/2024 | AG3: Creación y captura Ene/2025 | AH3: Almacenamiento y registro Ene/2025 | AI3: Calidad de datos Ene/2025 | AJ3: Uso y acceso Ene/2025 | AK3: Compartición e Interoperabilidad Ene/2025 | AL3: Gestión ciclo de Vida Ene/2025 | AM3: Creación y captura Feb/2025 | AN3: Almacenamiento y registro Feb/2025 | AO3: Calidad de datos Feb/2025 | AP3: Uso y acceso Feb/2025 | AQ3: Compartición e Interoperabilidad Feb/2025 | AR3: Gestión ciclo de Vida Feb/2025 | AS3: Creación y captura Mar/2025 | AT3: Almacenamiento y registro Mar/2025 | AU3: Calidad de datos Mar/2025 | AV3: Uso y acceso Mar/2025 | AW3: Compartición e Interoperabilidad Mar/2025 | AX3: Gestión ciclo de Vida Mar/2025 | AY3: Creación y captura Abr/2025 | AZ3: Almacenamiento y registro Abr/2025 | BA3: Calidad de datos Abr/2025 | BB3: Uso y acceso Abr/2025 | BC3: Compartición e Interoperabilidad Abr/2025 | BD3: Gestión ciclo de Vida Abr/2025 | BE3: Creación y captura May/2025 | BF3: Almacenamiento y registro May/2025 | BG3: Calidad de datos May/2025 | BH3: Uso y acceso May/2025 | BI3: Compartición e Interoperabilidad May/2025 | BJ3: Gestión ciclo de Vida May/2025 | BK3: Creación y captura Jun/2025 | BL3: Almacenamiento y registro Jun/2025 | BM3: Calidad de datos Jun/2025 | BN3: Uso y acceso Jun/2025 | BO3: Compartición e Interoperabilidad Jun/2025 | BP3: Gestión ciclo de Vida Jun/2025 | BQ3: Creación y captura Sep/2025 | BR3: Almacenamiento y registro Sep/2025 | BS3: Calidad de datos Sep/2025 | BT3: Uso y acceso Sep/2025 | BU3: Compartición e Interoperabilidad Sep/2025 | BV3: Gestión ciclo de Vida Sep/2025 | BW3: Creación y captura Dic/2025 | BX3: Almacenamiento y registro Dic/2025 | BY3: Calidad de datos Dic/2025 | BZ3: Uso y acceso Dic/2025 | CA3: Compartición e Interoperabilidad Dic/2025 | CB3: Gestión ciclo de Vida Dic/2025 | CC3: Creación y captura Mar/2026 | CD3: Almacenamiento y registro Mar/2026 | CE3: Calidad de datos Mar/2026 | CF3: Uso y acceso Mar/2026 | CG3: Compartición e Interoperabilidad Mar/2026 | CH3: Gestión ciclo de Vida Mar/2026
B4: Oportunidades | C4: 1 | D4: 1 | E4: =IF(ISERROR(AVERAGE('Calidad de Datos'!C8:F8)),"",AVERAGE('Calidad de Datos'!C8:F8)) -> 0.735 | F4: =IF(Tabla13[[#This Row],[Uso y acceso Ago/2024]]="","",Tabla13[[#This Row],[Uso y acceso Ago/2024]]) -> 1 | G4: =IF(Tabla58[[#This Row],[Integración Ago/2024]]="","",Tabla58[[#This Row],[Integración Ago/2024]]) -> 1 | H4: =IF(ISERROR(AVERAGE(Tabla4[[#This Row],[Creación y captura Ago/2024]:[Compartición e Interoperabilidad Ago/2024]])),"",AVERAGE(Tabla4[[#This Row],[Creación y captura Ago/2024]:[Compartición e Interoperabilidad Ago/2024]])) -> 0.947 | I4: 1 | J4: 1 | K4: =IF(ISERROR(AVERAGE('Calidad de Datos'!G8:J8)),"",AVERAGE('Calidad de Datos'!G8:J8)) -> 0.7875 | L4: =IF(Tabla13[[#This Row],[Uso y acceso Sep/2024]]="","",Tabla13[[#This Row],[Uso y acceso Sep/2024]]) -> 1 | M4: =IF(Tabla58[[#This Row],[Integración Sep/2024]]="","",Tabla58[[#This Row],[Integración Sep/2024]]) -> 1 | N4: =IF(ISERROR(AVERAGE(Tabla4[[#This Row],[Creación y captura Sep/2024]:[Compartición e Interoperabilidad Sep/2024]])),"",AVERAGE(Tabla4[[#This Row],[Creación y captura Sep/2024]:[Compartición e Interoperabilidad Sep/2024]])) -> 0.9575 | O4: 1 | P4: 1 | Q4: =IF(ISERROR(AVERAGE('Calidad de Datos'!K8:N8)),"",AVERAGE('Calidad de Datos'!K8:N8)) -> 0.7825 | R4: =IF(Tabla13[[#This Row],[Uso y acceso Oct/2024]]="","",Tabla13[[#This Row],[Uso y acceso Oct/2024]]) -> 1 | S4: =IF(Tabla58[[#This Row],[Integración Oct/2024]]="","",Tabla58[[#This Row],[Integración Oct/2024]]) -> 1 | T4: =IF(ISERROR(AVERAGE(Tabla4[[#This Row],[Creación y captura Oct/2024]:[Compartición e Interoperabilidad Oct/2024]])),"",AVERAGE(Tabla4[[#This Row],[Creación y captura Oct/2024]:[Compartición e Interoperabilidad Oct/2024]])) -> 0.9565 | U4: 1 | V4: 1 | W4: =IF(ISERROR(AVERAGE('Calidad de Datos'!O8:R8)),"",AVERAGE('Calidad de Datos'!O8:R8)) -> 0.875 | X4: =IF(Tabla13[[#This Row],[Uso y acceso Nov/2024]]="","",Tabla13[[#This Row],[Uso y acceso Nov/2024]]) -> 1 | Y4: =IF(Tabla58[[#This Row],[Integración Nov/2024]]="","",Tabla58[[#This Row],[Integración Nov/2024]]) -> 1 | Z4: =IF(ISERROR(AVERAGE(Tabla4[[#This Row],[Creación y captura Nov/2024]:[Compartición e Interoperabilidad Nov/2024]])),"",AVERAGE(Tabla4[[#This Row],[Creación y captura Nov/2024]:[Compartición e Interoperabilidad Nov/2024]])) -> 0.975 | AA4: 1 | AB4: 1 | AC4: =IF(ISERROR(AVERAGE('Calidad de Datos'!S8:V8)),"",AVERAGE('Calidad de Datos'!S8:V8)) -> 0.91125 | AD4: =IF(Tabla13[[#This Row],[Uso y acceso Dic/2024]]="","",Tabla13[[#This Row],[Uso y acceso Dic/2024]]) -> 1 | AE4: =IF(Tabla58[[#This Row],[Integración Dic/2024]]="","",Tabla58[[#This Row],[Integración Dic/2024]]) -> 1 | AF4: =IF(ISERROR(AVERAGE(Tabla4[[#This Row],[Creación y captura Dic/2024]:[Compartición e Interoperabilidad Dic/2024]])),"",AVERAGE(Tabla4[[#This Row],[Creación y captura Dic/2024]:[Compartición e Interoperabilidad Dic/2024]])) -> 0.98225 | AG4: 1 | AH4: 1 | AI4: =IF(ISERROR(AVERAGE('Calidad de Datos'!W8:Z8)),"",AVERAGE('Calidad de Datos'!W8:Z8)) -> 0.925 | AJ4: =IF(Tabla13[[#This Row],[Uso y acceso Ene/2025]]="","",Tabla13[[#This Row],[Uso y acceso Ene/2025]]) -> 1 | AK4: =IF(Tabla58[[#This Row],[Integración Ene/2025]]="","",Tabla58[[#This Row],[Integración Ene/2025]]) -> 1 | AL4: =IF(ISERROR(AVERAGE(Tabla4[[#This Row],[Creación y captura Ene/2025]:[Compartición e Interoperabilidad Ene/2025]])),"",AVERAGE(Tabla4[[#This Row],[Creación y captura Ene/2025]:[Compartición e Interoperabilidad Ene/2025]])) -> 0.985 | AM4: 1 | AN4: 1 | AO4: =IF(ISERROR(AVERAGE('Calidad de Datos'!AA8:AD8)),"",AVERAGE('Calidad de Datos'!AA8:AD8)) -> 0.925 | AP4: =IF(Tabla13[[#This Row],[Uso y acceso Feb/2025]]="","",Tabla13[[#This Row],[Uso y acceso Feb/2025]]) -> 1 | AQ4: =IF(Tabla58[[#This Row],[Integración Feb/2025]]="","",Tabla58[[#This Row],[Integración Feb/2025]]) -> 1 | AR4: =IF(ISERROR(AVERAGE(Tabla4[[#This Row],[Creación y captura Feb/2025]:[Compartición e Interoperabilidad Feb/2025]])),"",AVERAGE(Tabla4[[#This Row],[Creación y captura Feb/2025]:[Compartición e Interoperabilidad Feb/2025]])) -> 0.985 | AS4: 1 | AT4: 1 | AU4: =IF(ISERROR(AVERAGE('Calidad de Datos'!AE8:AH8)),"",AVERAGE('Calidad de Datos'!AE8:AH8)) -> 0.925 | AV4: =IF(Tabla13[[#This Row],[Uso y acceso Mar/2025]]="","",Tabla13[[#This Row],[Uso y acceso Mar/2025]]) -> 1 | AW4: =IF(Tabla58[[#This Row],[Integración Mar/2025]]="","",Tabla58[[#This Row],[Integración Mar/2025]]) -> 1 | AX4: =IF(ISERROR(AVERAGE(Tabla4[[#This Row],[Creación y captura Mar/2025]:[Compartición e Interoperabilidad Mar/2025]])),"",AVERAGE(Tabla4[[#This Row],[Creación y captura Mar/2025]:[Compartición e Interoperabilidad Mar/2025]])) -> 0.985 | AY4: 1 | AZ4: 1 | BA4: =IF(ISERROR(AVERAGE('Calidad de Datos'!AI8:AL8)),"",AVERAGE('Calidad de Datos'!AI8:AL8)) -> 0.925 | BB4: =IF(Tabla13[[#This Row],[Uso y acceso Abr/2025]]="","",Tabla13[[#This Row],[Uso y acceso Abr/2025]]) -> 1 | BC4: =IF(Tabla58[[#This Row],[Integración Abr/2025]]="","",Tabla58[[#This Row],[Integración Abr/2025]]) -> 1 | BD4: =IF(ISERROR(AVERAGE(Tabla4[[#This Row],[Creación y captura Abr/2025]:[Compartición e Interoperabilidad Abr/2025]])),"",AVERAGE(Tabla4[[#This Row],[Creación y captura Abr/2025]:[Compartición e Interoperabilidad Abr/2025]])) -> 0.985 | BE4: 1 | BF4: 1 | BG4: =IF(ISERROR(AVERAGE('Calidad de Datos'!AM8:AP8)),"",AVERAGE('Calidad de Datos'!AM8:AP8)) -> 0.95 | BH4: =IF(Tabla13[[#This Row],[Uso y acceso May/2025]]="","",Tabla13[[#This Row],[Uso y acceso May/2025]]) -> 1 | BI4: =IF(Tabla58[[#This Row],[Integración May/2025]]="","",Tabla58[[#This Row],[Integración May/2025]]) -> 1 | BJ4: =IF(ISERROR(AVERAGE(Tabla4[[#This Row],[Creación y captura May/2025]:[Compartición e Interoperabilidad May/2025]])),"",AVERAGE(Tabla4[[#This Row],[Creación y captura May/2025]:[Compartición e Interoperabilidad May/2025]])) -> 0.99 | BK4: 1 | BL4: 1 | BM4: =IF(ISERROR(AVERAGE('Calidad de Datos'!AQ8:AT8)),"",AVERAGE('Calidad de Datos'!AQ8:AT8)) -> 0.9625 | BN4: =IF(Tabla13[[#This Row],[Uso y acceso Jun/2025]]="","",Tabla13[[#This Row],[Uso y acceso Jun/2025]]) -> 1 | BO4: =IF(Tabla58[[#This Row],[Integración Jun/2025]]="","",Tabla58[[#This Row],[Integración Jun/2025]]) -> 1 | BP4: =IF(ISERROR(AVERAGE(Tabla4[[#This Row],[Creación y captura Jun/2025]:[Compartición e Interoperabilidad Jun/2025]])),"",AVERAGE(Tabla4[[#This Row],[Creación y captura Jun/2025]:[Compartición e Interoperabilidad Jun/2025]])) -> 0.9925 | BQ4: 1 | BR4: 1 | BS4: =IF(ISERROR(AVERAGE('Calidad de Datos'!AU8:AX8)),"",AVERAGE('Calidad de Datos'!AU8:AX8)) -> 1 | BT4: =IF(Tabla13[[#This Row],[Uso y acceso Sep/2025]]="","",Tabla13[[#This Row],[Uso y acceso Sep/2025]]) -> 1 | BU4: =IF(Tabla58[[#This Row],[Integración Sep/2025]]="","",Tabla58[[#This Row],[Integración Sep/2025]]) -> 1 | BV4: =IF(ISERROR(AVERAGE(Tabla4[[#This Row],[Creación y captura Sep/2025]:[Compartición e Interoperabilidad Sep/2025]])),"",AVERAGE(Tabla4[[#This Row],[Creación y captura Sep/2025]:[Compartición e Interoperabilidad Sep/2025]])) -> 1 | BW4: 1 | BX4: 1 | BY4: =IF(ISERROR(AVERAGE('Calidad de Datos'!AY8:BB8)),"",AVERAGE('Calidad de Datos'!AY8:BB8)) -> 0.881375 | BZ4: =IF(ISERROR(Tabla13[[#This Row],[Uso y acceso Dic/2025]]),"",Tabla13[[#This Row],[Uso y acceso Dic/2025]]) -> 1 | CA4: =IF(ISERROR(Tabla58[[#This Row],[Integración Dic/2025]]),"",Tabla58[[#This Row],[Integración Dic/2025]]) -> 1 | CB4: =IF(ISERROR(AVERAGE(Tabla4[[#This Row],[Creación y captura Dic/2025]:[Compartición e Interoperabilidad Dic/2025]])),"",AVERAGE(Tabla4[[#This Row],[Creación y captura Dic/2025]:[Compartición e Interoperabilidad Dic/2025]])) -> 0.976275 | CC4: 1 | CD4: 1 | CE4: =IF(ISERROR(AVERAGE('Calidad de Datos'!BC8:BF8)),"",AVERAGE('Calidad de Datos'!BC8:BF8)) -> 0.9625 | CF4: =IF(ISERROR(Tabla13[[#This Row],[Uso y acceso Mar/2026]]),"",Tabla13[[#This Row],[Uso y acceso Mar/2026]]) -> 1 | CG4: =IF(ISERROR(Tabla58[[#This Row],[Integración Mar/2026]]),"",Tabla58[[#This Row],[Integración Mar/2026]]) -> 1 | CH4: =IF(ISERROR(AVERAGE(Tabla4[[#This Row],[Creación y captura Mar/2026]:[Compartición e Interoperabilidad Mar/2026]])),"",AVERAGE(Tabla4[[#This Row],[Creación y captura Mar/2026]:[Compartición e Interoperabilidad Mar/2026]])) -> 0.9925
B5: Línea de negocios | C5: 1 | D5: 1 | E5: =IF(ISERROR(AVERAGE('Calidad de Datos'!C9:F9)),"",AVERAGE('Calidad de Datos'!C9:F9)) -> 1 | F5: =IF(Tabla13[[#This Row],[Uso y acceso Ago/2024]]="","",Tabla13[[#This Row],[Uso y acceso Ago/2024]]) -> 1 | G5: =IF(Tabla58[[#This Row],[Integración Ago/2024]]="","",Tabla58[[#This Row],[Integración Ago/2024]]) -> 1 | H5: =IF(ISERROR(AVERAGE(Tabla4[[#This Row],[Creación y captura Ago/2024]:[Compartición e Interoperabilidad Ago/2024]])),"",AVERAGE(Tabla4[[#This Row],[Creación y captura Ago/2024]:[Compartición e Interoperabilidad Ago/2024]])) -> 1 | I5: 1 | J5: 1 | K5: =IF(ISERROR(AVERAGE('Calidad de Datos'!G9:J9)),"",AVERAGE('Calidad de Datos'!G9:J9)) -> 1 | L5: =IF(Tabla13[[#This Row],[Uso y acceso Sep/2024]]="","",Tabla13[[#This Row],[Uso y acceso Sep/2024]]) -> 1 | M5: =IF(Tabla58[[#This Row],[Integración Sep/2024]]="","",Tabla58[[#This Row],[Integración Sep/2024]]) -> 1 | N5: =IF(ISERROR(AVERAGE(Tabla4[[#This Row],[Creación y captura Sep/2024]:[Compartición e Interoperabilidad Sep/2024]])),"",AVERAGE(Tabla4[[#This Row],[Creación y captura Sep/2024]:[Compartición e Interoperabilidad Sep/2024]])) -> 1 | O5: 1 | P5: 1 | Q5: =IF(ISERROR(AVERAGE('Calidad de Datos'!K9:N9)),"",AVERAGE('Calidad de Datos'!K9:N9)) -> 1 | R5: =IF(Tabla13[[#This Row],[Uso y acceso Oct/2024]]="","",Tabla13[[#This Row],[Uso y acceso Oct/2024]]) -> 1 | S5: =IF(Tabla58[[#This Row],[Integración Oct/2024]]="","",Tabla58[[#This Row],[Integración Oct/2024]]) -> 1 | T5: =IF(ISERROR(AVERAGE(Tabla4[[#This Row],[Creación y captura Oct/2024]:[Compartición e Interoperabilidad Oct/2024]])),"",AVERAGE(Tabla4[[#This Row],[Creación y captura Oct/2024]:[Compartición e Interoperabilidad Oct/2024]])) -> 1 | U5: 1 | V5: 1 | W5: =IF(ISERROR(AVERAGE('Calidad de Datos'!O9:R9)),"",AVERAGE('Calidad de Datos'!O9:R9)) -> 1 | X5: =IF(Tabla13[[#This Row],[Uso y acceso Nov/2024]]="","",Tabla13[[#This Row],[Uso y acceso Nov/2024]]) -> 1 | Y5: =IF(Tabla58[[#This Row],[Integración Nov/2024]]="","",Tabla58[[#This Row],[Integración Nov/2024]]) -> 1 | Z5: =IF(ISERROR(AVERAGE(Tabla4[[#This Row],[Creación y captura Nov/2024]:[Compartición e Interoperabilidad Nov/2024]])),"",AVERAGE(Tabla4[[#This Row],[Creación y captura Nov/2024]:[Compartición e Interoperabilidad Nov/2024]])) -> 1 | AA5: 1 | AB5: 1 | AC5: =IF(ISERROR(AVERAGE('Calidad de Datos'!S9:V9)),"",AVERAGE('Calidad de Datos'!S9:V9)) -> 1 | AD5: =IF(Tabla13[[#This Row],[Uso y acceso Dic/2024]]="","",Tabla13[[#This Row],[Uso y acceso Dic/2024]]) -> 1 | AE5: =IF(Tabla58[[#This Row],[Integración Dic/2024]]="","",Tabla58[[#This Row],[Integración Dic/2024]]) -> 1 | AF5: =IF(ISERROR(AVERAGE(Tabla4[[#This Row],[Creación y captura Dic/2024]:[Compartición e Interoperabilidad Dic/2024]])),"",AVERAGE(Tabla4[[#This Row],[Creación y captura Dic/2024]:[Compartición e Interoperabilidad Dic/2024]])) -> 1 | AG5: 1 | AH5: 1 | AI5: =IF(ISERROR(AVERAGE('Calidad de Datos'!W9:Z9)),"",AVERAGE('Calidad de Datos'!W9:Z9)) -> 1 | AJ5: =IF(Tabla13[[#This Row],[Uso y acceso Ene/2025]]="","",Tabla13[[#This Row],[Uso y acceso Ene/2025]]) -> 1 | AK5: =IF(Tabla58[[#This Row],[Integración Ene/2025]]="","",Tabla58[[#This Row],[Integración Ene/2025]]) -> 1 | AL5: =IF(ISERROR(AVERAGE(Tabla4[[#This Row],[Creación y captura Ene/2025]:[Compartición e Interoperabilidad Ene/2025]])),"",AVERAGE(Tabla4[[#This Row],[Creación y captura Ene/2025]:[Compartición e Interoperabilidad Ene/2025]])) -> 1 | AM5: 1 | AN5: 1 | AO5: =IF(ISERROR(AVERAGE('Calidad de Datos'!AA9:AD9)),"",AVERAGE('Calidad de Datos'!AA9:AD9)) -> 1 | AP5: =IF(Tabla13[[#This Row],[Uso y acceso Feb/2025]]="","",Tabla13[[#This Row],[Uso y acceso Feb/2025]]) -> 1 | AQ5: =IF(Tabla58[[#This Row],[Integración Feb/2025]]="","",Tabla58[[#This Row],[Integración Feb/2025]]) -> 1 | AR5: =IF(ISERROR(AVERAGE(Tabla4[[#This Row],[Creación y captura Feb/2025]:[Compartición e Interoperabilidad Feb/2025]])),"",AVERAGE(Tabla4[[#This Row],[Creación y captura Feb/2025]:[Compartición e Interoperabilidad Feb/2025]])) -> 1 | AS5: 1 | AT5: 1 | AU5: =IF(ISERROR(AVERAGE('Calidad de Datos'!AE9:AH9)),"",AVERAGE('Calidad de Datos'!AE9:AH9)) -> 1 | AV5: =IF(Tabla13[[#This Row],[Uso y acceso Mar/2025]]="","",Tabla13[[#This Row],[Uso y acceso Mar/2025]]) -> 1 | AW5: =IF(Tabla58[[#This Row],[Integración Mar/2025]]="","",Tabla58[[#This Row],[Integración Mar/2025]]) -> 1 | AX5: =IF(ISERROR(AVERAGE(Tabla4[[#This Row],[Creación y captura Mar/2025]:[Compartición e Interoperabilidad Mar/2025]])),"",AVERAGE(Tabla4[[#This Row],[Creación y captura Mar/2025]:[Compartición e Interoperabilidad Mar/2025]])) -> 1 | AY5: 1 | AZ5: 1 | BA5: =IF(ISERROR(AVERAGE('Calidad de Datos'!AI9:AL9)),"",AVERAGE('Calidad de Datos'!AI9:AL9)) -> 1 | BB5: =IF(Tabla13[[#This Row],[Uso y acceso Abr/2025]]="","",Tabla13[[#This Row],[Uso y acceso Abr/2025]]) -> 1 | BC5: =IF(Tabla58[[#This Row],[Integración Abr/2025]]="","",Tabla58[[#This Row],[Integración Abr/2025]]) -> 1 | BD5: =IF(ISERROR(AVERAGE(Tabla4[[#This Row],[Creación y captura Abr/2025]:[Compartición e Interoperabilidad Abr/2025]])),"",AVERAGE(Tabla4[[#This Row],[Creación y captura Abr/2025]:[Compartición e Interoperabilidad Abr/2025]])) -> 1 | BE5: 1 | BF5: 1 | BG5: =IF(ISERROR(AVERAGE('Calidad de Datos'!AM9:AP9)),"",AVERAGE('Calidad de Datos'!AM9:AP9)) -> 1 | BH5: =IF(Tabla13[[#This Row],[Uso y acceso May/2025]]="","",Tabla13[[#This Row],[Uso y acceso May/2025]]) -> 1 | BI5: =IF(Tabla58[[#This Row],[Integración May/2025]]="","",Tabla58[[#This Row],[Integración May/2025]]) -> 1 | BJ5: =IF(ISERROR(AVERAGE(Tabla4[[#This Row],[Creación y captura May/2025]:[Compartición e Interoperabilidad May/2025]])),"",AVERAGE(Tabla4[[#This Row],[Creación y captura May/2025]:[Compartición e Interoperabilidad May/2025]])) -> 1 | BK5: 1 | BL5: 1 | BM5: =IF(ISERROR(AVERAGE('Calidad de Datos'!AQ9:AT9)),"",AVERAGE('Calidad de Datos'!AQ9:AT9)) -> 1 | BN5: =IF(Tabla13[[#This Row],[Uso y acceso Jun/2025]]="","",Tabla13[[#This Row],[Uso y acceso Jun/2025]]) -> 1 | BO5: =IF(Tabla58[[#This Row],[Integración Jun/2025]]="","",Tabla58[[#This Row],[Integración Jun/2025]]) -> 1 | BP5: =IF(ISERROR(AVERAGE(Tabla4[[#This Row],[Creación y captura Jun/2025]:[Compartición e Interoperabilidad Jun/2025]])),"",AVERAGE(Tabla4[[#This Row],[Creación y captura Jun/2025]:[Compartición e Interoperabilidad Jun/2025]])) -> 1 | BQ5: 1 | BR5: 1 | BS5: =IF(ISERROR(AVERAGE('Calidad de Datos'!AU9:AX9)),"",AVERAGE('Calidad de Datos'!AU9:AX9)) -> 1 | BT5: =IF(Tabla13[[#This Row],[Uso y acceso Sep/2025]]="","",Tabla13[[#This Row],[Uso y acceso Sep/2025]]) -> 1 | BU5: =IF(Tabla58[[#This Row],[Integración Sep/2025]]="","",Tabla58[[#This Row],[Integración Sep/2025]]) -> 1 | BV5: =IF(ISERROR(AVERAGE(Tabla4[[#This Row],[Creación y captura Sep/2025]:[Compartición e Interoperabilidad Sep/2025]])),"",AVERAGE(Tabla4[[#This Row],[Creación y captura Sep/2025]:[Compartición e Interoperabilidad Sep/2025]])) -> 1 | BW5: 1 | BX5: 1 | BY5: =IF(ISERROR(AVERAGE('Calidad de Datos'!AY9:BB9)),"",AVERAGE('Calidad de Datos'!AY9:BB9)) -> 1 | BZ5: =IF(ISERROR(Tabla13[[#This Row],[Uso y acceso Dic/2025]]),"",Tabla13[[#This Row],[Uso y acceso Dic/2025]]) -> 1 | CA5: =IF(ISERROR(Tabla58[[#This Row],[Integración Dic/2025]]),"",Tabla58[[#This Row],[Integración Dic/2025]]) -> 1 | CB5: =IF(ISERROR(AVERAGE(Tabla4[[#This Row],[Creación y captura Dic/2025]:[Compartición e Interoperabilidad Dic/2025]])),"",AVERAGE(Tabla4[[#This Row],[Creación y captura Dic/2025]:[Compartición e Interoperabilidad Dic/2025]])) -> 1 | CC5: 1 | CD5: 1 | CE5: =IF(ISERROR(AVERAGE('Calidad de Datos'!BC9:BF9)),"",AVERAGE('Calidad de Datos'!BC9:BF9)) -> 1 | CF5: =IF(ISERROR(Tabla13[[#This Row],[Uso y acceso Mar/2026]]),"",Tabla13[[#This Row],[Uso y acceso Mar/2026]]) -> 1 | CG5: =IF(ISERROR(Tabla58[[#This Row],[Integración Mar/2026]]),"",Tabla58[[#This Row],[Integración Mar/2026]]) -> 1 | CH5: =IF(ISERROR(AVERAGE(Tabla4[[#This Row],[Creación y captura Mar/2026]:[Compartición e Interoperabilidad Mar/2026]])),"",AVERAGE(Tabla4[[#This Row],[Creación y captura Mar/2026]:[Compartición e Interoperabilidad Mar/2026]])) -> 1
B6: Equipo de ventas | C6: 1 | D6: 1 | E6: =IF(ISERROR(AVERAGE('Calidad de Datos'!C10:F10)),"",AVERAGE('Calidad de Datos'!C10:F10)) -> 1 | F6: =IF(Tabla13[[#This Row],[Uso y acceso Ago/2024]]="","",Tabla13[[#This Row],[Uso y acceso Ago/2024]]) -> 1 | G6: =IF(Tabla58[[#This Row],[Integración Ago/2024]]="","",Tabla58[[#This Row],[Integración Ago/2024]]) -> 1 | H6: =IF(ISERROR(AVERAGE(Tabla4[[#This Row],[Creación y captura Ago/2024]:[Compartición e Interoperabilidad Ago/2024]])),"",AVERAGE(Tabla4[[#This Row],[Creación y captura Ago/2024]:[Compartición e Interoperabilidad Ago/2024]])) -> 1 | I6: 1 | J6: 1 | K6: =IF(ISERROR(AVERAGE('Calidad de Datos'!G10:J10)),"",AVERAGE('Calidad de Datos'!G10:J10)) -> 1 | L6: =IF(Tabla13[[#This Row],[Uso y acceso Sep/2024]]="","",Tabla13[[#This Row],[Uso y acceso Sep/2024]]) -> 1 | M6: =IF(Tabla58[[#This Row],[Integración Sep/2024]]="","",Tabla58[[#This Row],[Integración Sep/2024]]) -> 1 | N6: =IF(ISERROR(AVERAGE(Tabla4[[#This Row],[Creación y captura Sep/2024]:[Compartición e Interoperabilidad Sep/2024]])),"",AVERAGE(Tabla4[[#This Row],[Creación y captura Sep/2024]:[Compartición e Interoperabilidad Sep/2024]])) -> 1 | O6: 1 | P6: 1 | Q6: =IF(ISERROR(AVERAGE('Calidad de Datos'!K10:N10)),"",AVERAGE('Calidad de Datos'!K10:N10)) -> 1 | R6: =IF(Tabla13[[#This Row],[Uso y acceso Oct/2024]]="","",Tabla13[[#This Row],[Uso y acceso Oct/2024]]) -> 1 | S6: =IF(Tabla58[[#This Row],[Integración Oct/2024]]="","",Tabla58[[#This Row],[Integración Oct/2024]]) -> 1 | T6: =IF(ISERROR(AVERAGE(Tabla4[[#This Row],[Creación y captura Oct/2024]:[Compartición e Interoperabilidad Oct/2024]])),"",AVERAGE(Tabla4[[#This Row],[Creación y captura Oct/2024]:[Compartición e Interoperabilidad Oct/2024]])) -> 1 | U6: 1 | V6: 1 | W6: =IF(ISERROR(AVERAGE('Calidad de Datos'!O10:R10)),"",AVERAGE('Calidad de Datos'!O10:R10)) -> 1 | X6: =IF(Tabla13[[#This Row],[Uso y acceso Nov/2024]]="","",Tabla13[[#This Row],[Uso y acceso Nov/2024]]) -> 1 | Y6: =IF(Tabla58[[#This Row],[Integración Nov/2024]]="","",Tabla58[[#This Row],[Integración Nov/2024]]) -> 1 | Z6: =IF(ISERROR(AVERAGE(Tabla4[[#This Row],[Creación y captura Nov/2024]:[Compartición e Interoperabilidad Nov/2024]])),"",AVERAGE(Tabla4[[#This Row],[Creación y captura Nov/2024]:[Compartición e Interoperabilidad Nov/2024]])) -> 1 | AA6: 1 | AB6: 1 | AC6: =IF(ISERROR(AVERAGE('Calidad de Datos'!S10:V10)),"",AVERAGE('Calidad de Datos'!S10:V10)) -> 1 | AD6: =IF(Tabla13[[#This Row],[Uso y acceso Dic/2024]]="","",Tabla13[[#This Row],[Uso y acceso Dic/2024]]) -> 1 | AE6: =IF(Tabla58[[#This Row],[Integración Dic/2024]]="","",Tabla58[[#This Row],[Integración Dic/2024]]) -> 1 | AF6: =IF(ISERROR(AVERAGE(Tabla4[[#This Row],[Creación y captura Dic/2024]:[Compartición e Interoperabilidad Dic/2024]])),"",AVERAGE(Tabla4[[#This Row],[Creación y captura Dic/2024]:[Compartición e Interoperabilidad Dic/2024]])) -> 1 | AG6: 1 | AH6: 1 | AI6: =IF(ISERROR(AVERAGE('Calidad de Datos'!W10:Z10)),"",AVERAGE('Calidad de Datos'!W10:Z10)) -> 1 | AJ6: =IF(Tabla13[[#This Row],[Uso y acceso Ene/2025]]="","",Tabla13[[#This Row],[Uso y acceso Ene/2025]]) -> 1 | AK6: =IF(Tabla58[[#This Row],[Integración Ene/2025]]="","",Tabla58[[#This Row],[Integración Ene/2025]]) -> 1 | AL6: =IF(ISERROR(AVERAGE(Tabla4[[#This Row],[Creación y captura Ene/2025]:[Compartición e Interoperabilidad Ene/2025]])),"",AVERAGE(Tabla4[[#This Row],[Creación y captura Ene/2025]:[Compartición e Interoperabilidad Ene/2025]])) -> 1 | AM6: 1 | AN6: 1 | AO6: =IF(ISERROR(AVERAGE('Calidad de Datos'!AA10:AD10)),"",AVERAGE('Calidad de Datos'!AA10:AD10)) -> 1 | AP6: =IF(Tabla13[[#This Row],[Uso y acceso Feb/2025]]="","",Tabla13[[#This Row],[Uso y acceso Feb/2025]]) -> 1 | AQ6: =IF(Tabla58[[#This Row],[Integración Feb/2025]]="","",Tabla58[[#This Row],[Integración Feb/2025]]) -> 1 | AR6: =IF(ISERROR(AVERAGE(Tabla4[[#This Row],[Creación y captura Feb/2025]:[Compartición e Interoperabilidad Feb/2025]])),"",AVERAGE(Tabla4[[#This Row],[Creación y captura Feb/2025]:[Compartición e Interoperabilidad Feb/2025]])) -> 1 | AS6: 1 | AT6: 1 | AU6: =IF(ISERROR(AVERAGE('Calidad de Datos'!AE10:AH10)),"",AVERAGE('Calidad de Datos'!AE10:AH10)) -> 1 | AV6: =IF(Tabla13[[#This Row],[Uso y acceso Mar/2025]]="","",Tabla13[[#This Row],[Uso y acceso Mar/2025]]) -> 1 | AW6: =IF(Tabla58[[#This Row],[Integración Mar/2025]]="","",Tabla58[[#This Row],[Integración Mar/2025]]) -> 1 | AX6: =IF(ISERROR(AVERAGE(Tabla4[[#This Row],[Creación y captura Mar/2025]:[Compartición e Interoperabilidad Mar/2025]])),"",AVERAGE(Tabla4[[#This Row],[Creación y captura Mar/2025]:[Compartición e Interoperabilidad Mar/2025]])) -> 1 | AY6: 1 | AZ6: 1 | BA6: =IF(ISERROR(AVERAGE('Calidad de Datos'!AI10:AL10)),"",AVERAGE('Calidad de Datos'!AI10:AL10)) -> 1 | BB6: =IF(Tabla13[[#This Row],[Uso y acceso Abr/2025]]="","",Tabla13[[#This Row],[Uso y acceso Abr/2025]]) -> 1 | BC6: =IF(Tabla58[[#This Row],[Integración Abr/2025]]="","",Tabla58[[#This Row],[Integración Abr/2025]]) -> 1 | BD6: =IF(ISERROR(AVERAGE(Tabla4[[#This Row],[Creación y captura Abr/2025]:[Compartición e Interoperabilidad Abr/2025]])),"",AVERAGE(Tabla4[[#This Row],[Creación y captura Abr/2025]:[Compartición e Interoperabilidad Abr/2025]])) -> 1 | BE6: 1 | BF6: 1 | BG6: =IF(ISERROR(AVERAGE('Calidad de Datos'!AM10:AP10)),"",AVERAGE('Calidad de Datos'!AM10:AP10)) -> 1 | BH6: =IF(Tabla13[[#This Row],[Uso y acceso May/2025]]="","",Tabla13[[#This Row],[Uso y acceso May/2025]]) -> 1 | BI6: =IF(Tabla58[[#This Row],[Integración May/2025]]="","",Tabla58[[#This Row],[Integración May/2025]]) -> 1 | BJ6: =IF(ISERROR(AVERAGE(Tabla4[[#This Row],[Creación y captura May/2025]:[Compartición e Interoperabilidad May/2025]])),"",AVERAGE(Tabla4[[#This Row],[Creación y captura May/2025]:[Compartición e Interoperabilidad May/2025]])) -> 1 | BK6: 1 | BL6: 1 | BM6: =IF(ISERROR(AVERAGE('Calidad de Datos'!AQ10:AT10)),"",AVERAGE('Calidad de Datos'!AQ10:AT10)) -> 1 | BN6: =IF(Tabla13[[#This Row],[Uso y acceso Jun/2025]]="","",Tabla13[[#This Row],[Uso y acceso Jun/2025]]) -> 1 | BO6: =IF(Tabla58[[#This Row],[Integración Jun/2025]]="","",Tabla58[[#This Row],[Integración Jun/2025]]) -> 1 | BP6: =IF(ISERROR(AVERAGE(Tabla4[[#This Row],[Creación y captura Jun/2025]:[Compartición e Interoperabilidad Jun/2025]])),"",AVERAGE(Tabla4[[#This Row],[Creación y captura Jun/2025]:[Compartición e Interoperabilidad Jun/2025]])) -> 1 | BQ6: 1 | BR6: 1 | BS6: =IF(ISERROR(AVERAGE('Calidad de Datos'!AU10:AX10)),"",AVERAGE('Calidad de Datos'!AU10:AX10)) -> 1 | BT6: =IF(Tabla13[[#This Row],[Uso y acceso Sep/2025]]="","",Tabla13[[#This Row],[Uso y acceso Sep/2025]]) -> 1 | BU6: =IF(Tabla58[[#This Row],[Integración Sep/2025]]="","",Tabla58[[#This Row],[Integración Sep/2025]]) -> 1 | BV6: =IF(ISERROR(AVERAGE(Tabla4[[#This Row],[Creación y captura Sep/2025]:[Compartición e Interoperabilidad Sep/2025]])),"",AVERAGE(Tabla4[[#This Row],[Creación y captura Sep/2025]:[Compartición e Interoperabilidad Sep/2025]])) -> 1 | BW6: 1 | BX6: 1 | BY6: =IF(ISERROR(AVERAGE('Calidad de Datos'!AY10:BB10)),"",AVERAGE('Calidad de Datos'!AY10:BB10)) -> 1 | BZ6: =IF(ISERROR(Tabla13[[#This Row],[Uso y acceso Dic/2025]]),"",Tabla13[[#This Row],[Uso y acceso Dic/2025]]) -> 1 | CA6: =IF(ISERROR(Tabla58[[#This Row],[Integración Dic/2025]]),"",Tabla58[[#This Row],[Integración Dic/2025]]) -> 1 | CB6: =IF(ISERROR(AVERAGE(Tabla4[[#This Row],[Creación y captura Dic/2025]:[Compartición e Interoperabilidad Dic/2025]])),"",AVERAGE(Tabla4[[#This Row],[Creación y captura Dic/2025]:[Compartición e Interoperabilidad Dic/2025]])) -> 1 | CC6: 1 | CD6: 1 | CE6: =IF(ISERROR(AVERAGE('Calidad de Datos'!BC10:BF10)),"",AVERAGE('Calidad de Datos'!BC10:BF10)) -> 1 | CF6: =IF(ISERROR(Tabla13[[#This Row],[Uso y acceso Mar/2026]]),"",Tabla13[[#This Row],[Uso y acceso Mar/2026]]) -> 1 | CG6: =IF(ISERROR(Tabla58[[#This Row],[Integración Mar/2026]]),"",Tabla58[[#This Row],[Integración Mar/2026]]) -> 1 | CH6: =IF(ISERROR(AVERAGE(Tabla4[[#This Row],[Creación y captura Mar/2026]:[Compartición e Interoperabilidad Mar/2026]])),"",AVERAGE(Tabla4[[#This Row],[Creación y captura Mar/2026]:[Compartición e Interoperabilidad Mar/2026]])) -> 1
B7: Tipo de cliente | C7: 1 | D7: 1 | E7: =IF(ISERROR(AVERAGE('Calidad de Datos'!C11:F11)),"",AVERAGE('Calidad de Datos'!C11:F11)) -> 1 | F7: =IF(Tabla13[[#This Row],[Uso y acceso Ago/2024]]="","",Tabla13[[#This Row],[Uso y acceso Ago/2024]]) -> 1 | G7: =IF(Tabla58[[#This Row],[Integración Ago/2024]]="","",Tabla58[[#This Row],[Integración Ago/2024]]) -> 1 | H7: =IF(ISERROR(AVERAGE(Tabla4[[#This Row],[Creación y captura Ago/2024]:[Compartición e Interoperabilidad Ago/2024]])),"",AVERAGE(Tabla4[[#This Row],[Creación y captura Ago/2024]:[Compartición e Interoperabilidad Ago/2024]])) -> 1 | I7: 1 | J7: 1 | K7: =IF(ISERROR(AVERAGE('Calidad de Datos'!G11:J11)),"",AVERAGE('Calidad de Datos'!G11:J11)) -> 1 | L7: =IF(Tabla13[[#This Row],[Uso y acceso Sep/2024]]="","",Tabla13[[#This Row],[Uso y acceso Sep/2024]]) -> 1 | M7: =IF(Tabla58[[#This Row],[Integración Sep/2024]]="","",Tabla58[[#This Row],[Integración Sep/2024]]) -> 1 | N7: =IF(ISERROR(AVERAGE(Tabla4[[#This Row],[Creación y captura Sep/2024]:[Compartición e Interoperabilidad Sep/2024]])),"",AVERAGE(Tabla4[[#This Row],[Creación y captura Sep/2024]:[Compartición e Interoperabilidad Sep/2024]])) -> 1 | O7: 1 | P7: 1 | Q7: =IF(ISERROR(AVERAGE('Calidad de Datos'!K11:N11)),"",AVERAGE('Calidad de Datos'!K11:N11)) -> 1 | R7: =IF(Tabla13[[#This Row],[Uso y acceso Oct/2024]]="","",Tabla13[[#This Row],[Uso y acceso Oct/2024]]) -> 1 | S7: =IF(Tabla58[[#This Row],[Integración Oct/2024]]="","",Tabla58[[#This Row],[Integración Oct/2024]]) -> 1 | T7: =IF(ISERROR(AVERAGE(Tabla4[[#This Row],[Creación y captura Oct/2024]:[Compartición e Interoperabilidad Oct/2024]])),"",AVERAGE(Tabla4[[#This Row],[Creación y captura Oct/2024]:[Compartición e Interoperabilidad Oct/2024]])) -> 1 | U7: 1 | V7: 1 | W7: =IF(ISERROR(AVERAGE('Calidad de Datos'!O11:R11)),"",AVERAGE('Calidad de Datos'!O11:R11)) -> 1 | X7: =IF(Tabla13[[#This Row],[Uso y acceso Nov/2024]]="","",Tabla13[[#This Row],[Uso y acceso Nov/2024]]) -> 1 | Y7: =IF(Tabla58[[#This Row],[Integración Nov/2024]]="","",Tabla58[[#This Row],[Integración Nov/2024]]) -> 1 | Z7: =IF(ISERROR(AVERAGE(Tabla4[[#This Row],[Creación y captura Nov/2024]:[Compartición e Interoperabilidad Nov/2024]])),"",AVERAGE(Tabla4[[#This Row],[Creación y captura Nov/2024]:[Compartición e Interoperabilidad Nov/2024]])) -> 1 | AA7: 1 | AB7: 1 | AC7: =IF(ISERROR(AVERAGE('Calidad de Datos'!S11:V11)),"",AVERAGE('Calidad de Datos'!S11:V11)) -> 1 | AD7: =IF(Tabla13[[#This Row],[Uso y acceso Dic/2024]]="","",Tabla13[[#This Row],[Uso y acceso Dic/2024]]) -> 1 | AE7: =IF(Tabla58[[#This Row],[Integración Dic/2024]]="","",Tabla58[[#This Row],[Integración Dic/2024]]) -> 1 | AF7: =IF(ISERROR(AVERAGE(Tabla4[[#This Row],[Creación y captura Dic/2024]:[Compartición e Interoperabilidad Dic/2024]])),"",AVERAGE(Tabla4[[#This Row],[Creación y captura Dic/2024]:[Compartición e Interoperabilidad Dic/2024]])) -> 1 | AG7: 1 | AH7: 1 | AI7: =IF(ISERROR(AVERAGE('Calidad de Datos'!W11:Z11)),"",AVERAGE('Calidad de Datos'!W11:Z11)) -> 1 | AJ7: =IF(Tabla13[[#This Row],[Uso y acceso Ene/2025]]="","",Tabla13[[#This Row],[Uso y acceso Ene/2025]]) -> 1 | AK7: =IF(Tabla58[[#This Row],[Integración Ene/2025]]="","",Tabla58[[#This Row],[Integración Ene/2025]]) -> 1 | AL7: =IF(ISERROR(AVERAGE(Tabla4[[#This Row],[Creación y captura Ene/2025]:[Compartición e Interoperabilidad Ene/2025]])),"",AVERAGE(Tabla4[[#This Row],[Creación y captura Ene/2025]:[Compartición e Interoperabilidad Ene/2025]])) -> 1 | AM7: 1 | AN7: 1 | AO7: =IF(ISERROR(AVERAGE('Calidad de Datos'!AA11:AD11)),"",AVERAGE('Calidad de Datos'!AA11:AD11)) -> 1 | AP7: =IF(Tabla13[[#This Row],[Uso y acceso Feb/2025]]="","",Tabla13[[#This Row],[Uso y acceso Feb/2025]]) -> 1 | AQ7: =IF(Tabla58[[#This Row],[Integración Feb/2025]]="","",Tabla58[[#This Row],[Integración Feb/2025]]) -> 1 | AR7: =IF(ISERROR(AVERAGE(Tabla4[[#This Row],[Creación y captura Feb/2025]:[Compartición e Interoperabilidad Feb/2025]])),"",AVERAGE(Tabla4[[#This Row],[Creación y captura Feb/2025]:[Compartición e Interoperabilidad Feb/2025]])) -> 1 | AS7: 1 | AT7: 1 | AU7: =IF(ISERROR(AVERAGE('Calidad de Datos'!AE11:AH11)),"",AVERAGE('Calidad de Datos'!AE11:AH11)) -> 1 | AV7: =IF(Tabla13[[#This Row],[Uso y acceso Mar/2025]]="","",Tabla13[[#This Row],[Uso y acceso Mar/2025]]) -> 1 | AW7: =IF(Tabla58[[#This Row],[Integración Mar/2025]]="","",Tabla58[[#This Row],[Integración Mar/2025]]) -> 1 | AX7: =IF(ISERROR(AVERAGE(Tabla4[[#This Row],[Creación y captura Mar/2025]:[Compartición e Interoperabilidad Mar/2025]])),"",AVERAGE(Tabla4[[#This Row],[Creación y captura Mar/2025]:[Compartición e Interoperabilidad Mar/2025]])) -> 1 | AY7: 1 | AZ7: 1 | BA7: =IF(ISERROR(AVERAGE('Calidad de Datos'!AI11:AL11)),"",AVERAGE('Calidad de Datos'!AI11:AL11)) -> 1 | BB7: =IF(Tabla13[[#This Row],[Uso y acceso Abr/2025]]="","",Tabla13[[#This Row],[Uso y acceso Abr/2025]]) -> 1 | BC7: =IF(Tabla58[[#This Row],[Integración Abr/2025]]="","",Tabla58[[#This Row],[Integración Abr/2025]]) -> 1 | BD7: =IF(ISERROR(AVERAGE(Tabla4[[#This Row],[Creación y captura Abr/2025]:[Compartición e Interoperabilidad Abr/2025]])),"",AVERAGE(Tabla4[[#This Row],[Creación y captura Abr/2025]:[Compartición e Interoperabilidad Abr/2025]])) -> 1 | BE7: 1 | BF7: 1 | BG7: =IF(ISERROR(AVERAGE('Calidad de Datos'!AM11:AP11)),"",AVERAGE('Calidad de Datos'!AM11:AP11)) -> 1 | BH7: =IF(Tabla13[[#This Row],[Uso y acceso May/2025]]="","",Tabla13[[#This Row],[Uso y acceso May/2025]]) -> 1 | BI7: =IF(Tabla58[[#This Row],[Integración May/2025]]="","",Tabla58[[#This Row],[Integración May/2025]]) -> 1 | BJ7: =IF(ISERROR(AVERAGE(Tabla4[[#This Row],[Creación y captura May/2025]:[Compartición e Interoperabilidad May/2025]])),"",AVERAGE(Tabla4[[#This Row],[Creación y captura May/2025]:[Compartición e Interoperabilidad May/2025]])) -> 1 | BK7: 1 | BL7: 1 | BM7: =IF(ISERROR(AVERAGE('Calidad de Datos'!AQ11:AT11)),"",AVERAGE('Calidad de Datos'!AQ11:AT11)) -> 1 | BN7: =IF(Tabla13[[#This Row],[Uso y acceso Jun/2025]]="","",Tabla13[[#This Row],[Uso y acceso Jun/2025]]) -> 1 | BO7: =IF(Tabla58[[#This Row],[Integración Jun/2025]]="","",Tabla58[[#This Row],[Integración Jun/2025]]) -> 1 | BP7: =IF(ISERROR(AVERAGE(Tabla4[[#This Row],[Creación y captura Jun/2025]:[Compartición e Interoperabilidad Jun/2025]])),"",AVERAGE(Tabla4[[#This Row],[Creación y captura Jun/2025]:[Compartición e Interoperabilidad Jun/2025]])) -> 1 | BQ7: 1 | BR7: 1 | BS7: =IF(ISERROR(AVERAGE('Calidad de Datos'!AU11:AX11)),"",AVERAGE('Calidad de Datos'!AU11:AX11)) -> 1 | BT7: =IF(Tabla13[[#This Row],[Uso y acceso Sep/2025]]="","",Tabla13[[#This Row],[Uso y acceso Sep/2025]]) -> 1 | BU7: =IF(Tabla58[[#This Row],[Integración Sep/2025]]="","",Tabla58[[#This Row],[Integración Sep/2025]]) -> 1 | BV7: =IF(ISERROR(AVERAGE(Tabla4[[#This Row],[Creación y captura Sep/2025]:[Compartición e Interoperabilidad Sep/2025]])),"",AVERAGE(Tabla4[[#This Row],[Creación y captura Sep/2025]:[Compartición e Interoperabilidad Sep/2025]])) -> 1 | BW7: 1 | BX7: 1 | BY7: =IF(ISERROR(AVERAGE('Calidad de Datos'!AY11:BB11)),"",AVERAGE('Calidad de Datos'!AY11:BB11)) -> 1 | BZ7: =IF(ISERROR(Tabla13[[#This Row],[Uso y acceso Dic/2025]]),"",Tabla13[[#This Row],[Uso y acceso Dic/2025]]) -> 1 | CA7: =IF(ISERROR(Tabla58[[#This Row],[Integración Dic/2025]]),"",Tabla58[[#This Row],[Integración Dic/2025]]) -> 1 | CB7: =IF(ISERROR(AVERAGE(Tabla4[[#This Row],[Creación y captura Dic/2025]:[Compartición e Interoperabilidad Dic/2025]])),"",AVERAGE(Tabla4[[#This Row],[Creación y captura Dic/2025]:[Compartición e Interoperabilidad Dic/2025]])) -> 1 | CC7: 1 | CD7: 1 | CE7: =IF(ISERROR(AVERAGE('Calidad de Datos'!BC11:BF11)),"",AVERAGE('Calidad de Datos'!BC11:BF11)) -> 1 | CF7: =IF(ISERROR(Tabla13[[#This Row],[Uso y acceso Mar/2026]]),"",Tabla13[[#This Row],[Uso y acceso Mar/2026]]) -> 1 | CG7: =IF(ISERROR(Tabla58[[#This Row],[Integración Mar/2026]]),"",Tabla58[[#This Row],[Integración Mar/2026]]) -> 1 | CH7: =IF(ISERROR(AVERAGE(Tabla4[[#This Row],[Creación y captura Mar/2026]:[Compartición e Interoperabilidad Mar/2026]])),"",AVERAGE(Tabla4[[#This Row],[Creación y captura Mar/2026]:[Compartición e Interoperabilidad Mar/2026]])) -> 1
B8: Cliente | C8: 1 | D8: 1 | E8: =IF(ISERROR(AVERAGE('Calidad de Datos'!C12:F12)),"",AVERAGE('Calidad de Datos'!C12:F12)) -> 0.625 | F8: =IF(Tabla13[[#This Row],[Uso y acceso Ago/2024]]="","",Tabla13[[#This Row],[Uso y acceso Ago/2024]]) -> 1 | G8: =IF(Tabla58[[#This Row],[Integración Ago/2024]]="","",Tabla58[[#This Row],[Integración Ago/2024]]) -> 1 | H8: =IF(ISERROR(AVERAGE(Tabla4[[#This Row],[Creación y captura Ago/2024]:[Compartición e Interoperabilidad Ago/2024]])),"",AVERAGE(Tabla4[[#This Row],[Creación y captura Ago/2024]:[Compartición e Interoperabilidad Ago/2024]])) -> 0.925 | I8: 1 | J8: 1 | K8: =IF(ISERROR(AVERAGE('Calidad de Datos'!G12:J12)),"",AVERAGE('Calidad de Datos'!G12:J12)) -> 0.625 | L8: =IF(Tabla13[[#This Row],[Uso y acceso Sep/2024]]="","",Tabla13[[#This Row],[Uso y acceso Sep/2024]]) -> 1 | M8: =IF(Tabla58[[#This Row],[Integración Sep/2024]]="","",Tabla58[[#This Row],[Integración Sep/2024]]) -> 1 | N8: =IF(ISERROR(AVERAGE(Tabla4[[#This Row],[Creación y captura Sep/2024]:[Compartición e Interoperabilidad Sep/2024]])),"",AVERAGE(Tabla4[[#This Row],[Creación y captura Sep/2024]:[Compartición e Interoperabilidad Sep/2024]])) -> 0.925 | O8: 1 | P8: 1 | Q8: =IF(ISERROR(AVERAGE('Calidad de Datos'!K12:N12)),"",AVERAGE('Calidad de Datos'!K12:N12)) -> 0.6325 | R8: =IF(Tabla13[[#This Row],[Uso y acceso Oct/2024]]="","",Tabla13[[#This Row],[Uso y acceso Oct/2024]]) -> 1 | S8: =IF(Tabla58[[#This Row],[Integración Oct/2024]]="","",Tabla58[[#This Row],[Integración Oct/2024]]) -> 1 | T8: =IF(ISERROR(AVERAGE(Tabla4[[#This Row],[Creación y captura Oct/2024]:[Compartición e Interoperabilidad Oct/2024]])),"",AVERAGE(Tabla4[[#This Row],[Creación y captura Oct/2024]:[Compartición e Interoperabilidad Oct/2024]])) -> 0.9265 | U8: 1 | V8: 1 | W8: =IF(ISERROR(AVERAGE('Calidad de Datos'!O12:R12)),"",AVERAGE('Calidad de Datos'!O12:R12)) -> 0.7625 | X8: =IF(Tabla13[[#This Row],[Uso y acceso Nov/2024]]="","",Tabla13[[#This Row],[Uso y acceso Nov/2024]]) -> 1 | Y8: =IF(Tabla58[[#This Row],[Integración Nov/2024]]="","",Tabla58[[#This Row],[Integración Nov/2024]]) -> 1 | Z8: =IF(ISERROR(AVERAGE(Tabla4[[#This Row],[Creación y captura Nov/2024]:[Compartición e Interoperabilidad Nov/2024]])),"",AVERAGE(Tabla4[[#This Row],[Creación y captura Nov/2024]:[Compartición e Interoperabilidad Nov/2024]])) -> 0.9525 | AA8: 1 | AB8: 1 | AC8: =IF(ISERROR(AVERAGE('Calidad de Datos'!S12:V12)),"",AVERAGE('Calidad de Datos'!S12:V12)) -> 0.82375 | AD8: =IF(Tabla13[[#This Row],[Uso y acceso Dic/2024]]="","",Tabla13[[#This Row],[Uso y acceso Dic/2024]]) -> 1 | AE8: =IF(Tabla58[[#This Row],[Integración Dic/2024]]="","",Tabla58[[#This Row],[Integración Dic/2024]]) -> 1 | AF8: =IF(ISERROR(AVERAGE(Tabla4[[#This Row],[Creación y captura Dic/2024]:[Compartición e Interoperabilidad Dic/2024]])),"",AVERAGE(Tabla4[[#This Row],[Creación y captura Dic/2024]:[Compartición e Interoperabilidad Dic/2024]])) -> 0.96475 | AG8: 1 | AH8: 1 | AI8: =IF(ISERROR(AVERAGE('Calidad de Datos'!W12:Z12)),"",AVERAGE('Calidad de Datos'!W12:Z12)) -> 0.825 | AJ8: =IF(Tabla13[[#This Row],[Uso y acceso Ene/2025]]="","",Tabla13[[#This Row],[Uso y acceso Ene/2025]]) -> 1 | AK8: =IF(Tabla58[[#This Row],[Integración Ene/2025]]="","",Tabla58[[#This Row],[Integración Ene/2025]]) -> 1 | AL8: =IF(ISERROR(AVERAGE(Tabla4[[#This Row],[Creación y captura Ene/2025]:[Compartición e Interoperabilidad Ene/2025]])),"",AVERAGE(Tabla4[[#This Row],[Creación y captura Ene/2025]:[Compartición e Interoperabilidad Ene/2025]])) -> 0.965 | AM8: 1 | AN8: 1 | AO8: =IF(ISERROR(AVERAGE('Calidad de Datos'!AA12:AD12)),"",AVERAGE('Calidad de Datos'!AA12:AD12)) -> 0.825 | AP8: =IF(Tabla13[[#This Row],[Uso y acceso Feb/2025]]="","",Tabla13[[#This Row],[Uso y acceso Feb/2025]]) -> 1 | AQ8: =IF(Tabla58[[#This Row],[Integración Feb/2025]]="","",Tabla58[[#This Row],[Integración Feb/2025]]) -> 1 | AR8: =IF(ISERROR(AVERAGE(Tabla4[[#This Row],[Creación y captura Feb/2025]:[Compartición e Interoperabilidad Feb/2025]])),"",AVERAGE(Tabla4[[#This Row],[Creación y captura Feb/2025]:[Compartición e Interoperabilidad Feb/2025]])) -> 0.965 | AS8: 1 | AT8: 1 | AU8: =IF(ISERROR(AVERAGE('Calidad de Datos'!AE12:AH12)),"",AVERAGE('Calidad de Datos'!AE12:AH12)) -> 0.825 | AV8: =IF(Tabla13[[#This Row],[Uso y acceso Mar/2025]]="","",Tabla13[[#This Row],[Uso y acceso Mar/2025]]) -> 1 | AW8: =IF(Tabla58[[#This Row],[Integración Mar/2025]]="","",Tabla58[[#This Row],[Integración Mar/2025]]) -> 1 | AX8: =IF(ISERROR(AVERAGE(Tabla4[[#This Row],[Creación y captura Mar/2025]:[Compartición e Interoperabilidad Mar/2025]])),"",AVERAGE(Tabla4[[#This Row],[Creación y captura Mar/2025]:[Compartición e Interoperabilidad Mar/2025]])) -> 0.965 | AY8: 1 | AZ8: 1 | BA8: =IF(ISERROR(AVERAGE('Calidad de Datos'!AI12:AL12)),"",AVERAGE('Calidad de Datos'!AI12:AL12)) -> 0.825 | BB8: =IF(Tabla13[[#This Row],[Uso y acceso Abr/2025]]="","",Tabla13[[#This Row],[Uso y acceso Abr/2025]]) -> 1 | BC8: =IF(Tabla58[[#This Row],[Integración Abr/2025]]="","",Tabla58[[#This Row],[Integración Abr/2025]]) -> 1 | BD8: =IF(ISERROR(AVERAGE(Tabla4[[#This Row],[Creación y captura Abr/2025]:[Compartición e Interoperabilidad Abr/2025]])),"",AVERAGE(Tabla4[[#This Row],[Creación y captura Abr/2025]:[Compartición e Interoperabilidad Abr/2025]])) -> 0.965 | BE8: 1 | BF8: 1 | BG8: =IF(ISERROR(AVERAGE('Calidad de Datos'!AM12:AP12)),"",AVERAGE('Calidad de Datos'!AM12:AP12)) -> 0.825 | BH8: =IF(Tabla13[[#This Row],[Uso y acceso May/2025]]="","",Tabla13[[#This Row],[Uso y acceso May/2025]]) -> 1 | BI8: =IF(Tabla58[[#This Row],[Integración May/2025]]="","",Tabla58[[#This Row],[Integración May/2025]]) -> 1 | BJ8: =IF(ISERROR(AVERAGE(Tabla4[[#This Row],[Creación y captura May/2025]:[Compartición e Interoperabilidad May/2025]])),"",AVERAGE(Tabla4[[#This Row],[Creación y captura May/2025]:[Compartición e Interoperabilidad May/2025]])) -> 0.965 | BK8: 1 | BL8: 1 | BM8: =IF(ISERROR(AVERAGE('Calidad de Datos'!AQ12:AT12)),"",AVERAGE('Calidad de Datos'!AQ12:AT12)) -> 0.875 | BN8: =IF(Tabla13[[#This Row],[Uso y acceso Jun/2025]]="","",Tabla13[[#This Row],[Uso y acceso Jun/2025]]) -> 1 | BO8: =IF(Tabla58[[#This Row],[Integración Jun/2025]]="","",Tabla58[[#This Row],[Integración Jun/2025]]) -> 1 | BP8: =IF(ISERROR(AVERAGE(Tabla4[[#This Row],[Creación y captura Jun/2025]:[Compartición e Interoperabilidad Jun/2025]])),"",AVERAGE(Tabla4[[#This Row],[Creación y captura Jun/2025]:[Compartición e Interoperabilidad Jun/2025]])) -> 0.975 | BQ8: 1 | BR8: 1 | BS8: =IF(ISERROR(AVERAGE('Calidad de Datos'!AU12:AX12)),"",AVERAGE('Calidad de Datos'!AU12:AX12)) -> 1 | BT8: =IF(Tabla13[[#This Row],[Uso y acceso Sep/2025]]="","",Tabla13[[#This Row],[Uso y acceso Sep/2025]]) -> 1 | BU8: =IF(Tabla58[[#This Row],[Integración Sep/2025]]="","",Tabla58[[#This Row],[Integración Sep/2025]]) -> 1 | BV8: =IF(ISERROR(AVERAGE(Tabla4[[#This Row],[Creación y captura Sep/2025]:[Compartición e Interoperabilidad Sep/2025]])),"",AVERAGE(Tabla4[[#This Row],[Creación y captura Sep/2025]:[Compartición e Interoperabilidad Sep/2025]])) -> 1 | BW8: 1 | BX8: 1 | BY8: =IF(ISERROR(AVERAGE('Calidad de Datos'!AY12:BB12)),"",AVERAGE('Calidad de Datos'!AY12:BB12)) -> 0.8385 | BZ8: =IF(ISERROR(Tabla13[[#This Row],[Uso y acceso Dic/2025]]),"",Tabla13[[#This Row],[Uso y acceso Dic/2025]]) -> 1 | CA8: =IF(ISERROR(Tabla58[[#This Row],[Integración Dic/2025]]),"",Tabla58[[#This Row],[Integración Dic/2025]]) -> 1 | CB8: =IF(ISERROR(AVERAGE(Tabla4[[#This Row],[Creación y captura Dic/2025]:[Compartición e Interoperabilidad Dic/2025]])),"",AVERAGE(Tabla4[[#This Row],[Creación y captura Dic/2025]:[Compartición e Interoperabilidad Dic/2025]])) -> 0.9677 | CC8: 1 | CD8: 1 | CE8: =IF(ISERROR(AVERAGE('Calidad de Datos'!BC12:BF12)),"",AVERAGE('Calidad de Datos'!BC12:BF12)) -> 0.875 | CF8: =IF(ISERROR(Tabla13[[#This Row],[Uso y acceso Mar/2026]]),"",Tabla13[[#This Row],[Uso y acceso Mar/2026]]) -> 1 | CG8: =IF(ISERROR(Tabla58[[#This Row],[Integración Mar/2026]]),"",Tabla58[[#This Row],[Integración Mar/2026]]) -> 1 | CH8: =IF(ISERROR(AVERAGE(Tabla4[[#This Row],[Creación y captura Mar/2026]:[Compartición e Interoperabilidad Mar/2026]])),"",AVERAGE(Tabla4[[#This Row],[Creación y captura Mar/2026]:[Compartición e Interoperabilidad Mar/2026]])) -> 0.975
B9: Tipo de venta | C9: 1 | D9: 1 | E9: =IF(ISERROR(AVERAGE('Calidad de Datos'!C13:F13)),"",AVERAGE('Calidad de Datos'!C13:F13)) -> 1 | F9: =IF(Tabla13[[#This Row],[Uso y acceso Ago/2024]]="","",Tabla13[[#This Row],[Uso y acceso Ago/2024]]) -> 1 | G9: =IF(Tabla58[[#This Row],[Integración Ago/2024]]="","",Tabla58[[#This Row],[Integración Ago/2024]]) -> 1 | H9: =IF(ISERROR(AVERAGE(Tabla4[[#This Row],[Creación y captura Ago/2024]:[Compartición e Interoperabilidad Ago/2024]])),"",AVERAGE(Tabla4[[#This Row],[Creación y captura Ago/2024]:[Compartición e Interoperabilidad Ago/2024]])) -> 1 | I9: 1 | J9: 1 | K9: =IF(ISERROR(AVERAGE('Calidad de Datos'!G13:J13)),"",AVERAGE('Calidad de Datos'!G13:J13)) -> 1 | L9: =IF(Tabla13[[#This Row],[Uso y acceso Sep/2024]]="","",Tabla13[[#This Row],[Uso y acceso Sep/2024]]) -> 1 | M9: =IF(Tabla58[[#This Row],[Integración Sep/2024]]="","",Tabla58[[#This Row],[Integración Sep/2024]]) -> 1 | N9: =IF(ISERROR(AVERAGE(Tabla4[[#This Row],[Creación y captura Sep/2024]:[Compartición e Interoperabilidad Sep/2024]])),"",AVERAGE(Tabla4[[#This Row],[Creación y captura Sep/2024]:[Compartición e Interoperabilidad Sep/2024]])) -> 1 | O9: 1 | P9: 1 | Q9: =IF(ISERROR(AVERAGE('Calidad de Datos'!K13:N13)),"",AVERAGE('Calidad de Datos'!K13:N13)) -> 1 | R9: =IF(Tabla13[[#This Row],[Uso y acceso Oct/2024]]="","",Tabla13[[#This Row],[Uso y acceso Oct/2024]]) -> 1 | S9: =IF(Tabla58[[#This Row],[Integración Oct/2024]]="","",Tabla58[[#This Row],[Integración Oct/2024]]) -> 1 | T9: =IF(ISERROR(AVERAGE(Tabla4[[#This Row],[Creación y captura Oct/2024]:[Compartición e Interoperabilidad Oct/2024]])),"",AVERAGE(Tabla4[[#This Row],[Creación y captura Oct/2024]:[Compartición e Interoperabilidad Oct/2024]])) -> 1 | U9: 1 | V9: 1 | W9: =IF(ISERROR(AVERAGE('Calidad de Datos'!O13:R13)),"",AVERAGE('Calidad de Datos'!O13:R13)) -> 1 | X9: =IF(Tabla13[[#This Row],[Uso y acceso Nov/2024]]="","",Tabla13[[#This Row],[Uso y acceso Nov/2024]]) -> 1 | Y9: =IF(Tabla58[[#This Row],[Integración Nov/2024]]="","",Tabla58[[#This Row],[Integración Nov/2024]]) -> 1 | Z9: =IF(ISERROR(AVERAGE(Tabla4[[#This Row],[Creación y captura Nov/2024]:[Compartición e Interoperabilidad Nov/2024]])),"",AVERAGE(Tabla4[[#This Row],[Creación y captura Nov/2024]:[Compartición e Interoperabilidad Nov/2024]])) -> 1 | AA9: 1 | AB9: 1 | AC9: =IF(ISERROR(AVERAGE('Calidad de Datos'!S13:V13)),"",AVERAGE('Calidad de Datos'!S13:V13)) -> 1 | AD9: =IF(Tabla13[[#This Row],[Uso y acceso Dic/2024]]="","",Tabla13[[#This Row],[Uso y acceso Dic/2024]]) -> 1 | AE9: =IF(Tabla58[[#This Row],[Integración Dic/2024]]="","",Tabla58[[#This Row],[Integración Dic/2024]]) -> 1 | AF9: =IF(ISERROR(AVERAGE(Tabla4[[#This Row],[Creación y captura Dic/2024]:[Compartición e Interoperabilidad Dic/2024]])),"",AVERAGE(Tabla4[[#This Row],[Creación y captura Dic/2024]:[Compartición e Interoperabilidad Dic/2024]])) -> 1 | AG9: 1 | AH9: 1 | AI9: =IF(ISERROR(AVERAGE('Calidad de Datos'!W13:Z13)),"",AVERAGE('Calidad de Datos'!W13:Z13)) -> 1 | AJ9: =IF(Tabla13[[#This Row],[Uso y acceso Ene/2025]]="","",Tabla13[[#This Row],[Uso y acceso Ene/2025]]) -> 1 | AK9: =IF(Tabla58[[#This Row],[Integración Ene/2025]]="","",Tabla58[[#This Row],[Integración Ene/2025]]) -> 1 | AL9: =IF(ISERROR(AVERAGE(Tabla4[[#This Row],[Creación y captura Ene/2025]:[Compartición e Interoperabilidad Ene/2025]])),"",AVERAGE(Tabla4[[#This Row],[Creación y captura Ene/2025]:[Compartición e Interoperabilidad Ene/2025]])) -> 1 | AM9: 1 | AN9: 1 | AO9: =IF(ISERROR(AVERAGE('Calidad de Datos'!AA13:AD13)),"",AVERAGE('Calidad de Datos'!AA13:AD13)) -> 1 | AP9: =IF(Tabla13[[#This Row],[Uso y acceso Feb/2025]]="","",Tabla13[[#This Row],[Uso y acceso Feb/2025]]) -> 1 | AQ9: =IF(Tabla58[[#This Row],[Integración Feb/2025]]="","",Tabla58[[#This Row],[Integración Feb/2025]]) -> 1 | AR9: =IF(ISERROR(AVERAGE(Tabla4[[#This Row],[Creación y captura Feb/2025]:[Compartición e Interoperabilidad Feb/2025]])),"",AVERAGE(Tabla4[[#This Row],[Creación y captura Feb/2025]:[Compartición e Interoperabilidad Feb/2025]])) -> 1 | AS9: 1 | AT9: 1 | AU9: =IF(ISERROR(AVERAGE('Calidad de Datos'!AE13:AH13)),"",AVERAGE('Calidad de Datos'!AE13:AH13)) -> 1 | AV9: =IF(Tabla13[[#This Row],[Uso y acceso Mar/2025]]="","",Tabla13[[#This Row],[Uso y acceso Mar/2025]]) -> 1 | AW9: =IF(Tabla58[[#This Row],[Integración Mar/2025]]="","",Tabla58[[#This Row],[Integración Mar/2025]]) -> 1 | AX9: =IF(ISERROR(AVERAGE(Tabla4[[#This Row],[Creación y captura Mar/2025]:[Compartición e Interoperabilidad Mar/2025]])),"",AVERAGE(Tabla4[[#This Row],[Creación y captura Mar/2025]:[Compartición e Interoperabilidad Mar/2025]])) -> 1 | AY9: 1 | AZ9: 1 | BA9: =IF(ISERROR(AVERAGE('Calidad de Datos'!AI13:AL13)),"",AVERAGE('Calidad de Datos'!AI13:AL13)) -> 1 | BB9: =IF(Tabla13[[#This Row],[Uso y acceso Abr/2025]]="","",Tabla13[[#This Row],[Uso y acceso Abr/2025]]) -> 1 | BC9: =IF(Tabla58[[#This Row],[Integración Abr/2025]]="","",Tabla58[[#This Row],[Integración Abr/2025]]) -> 1 | BD9: =IF(ISERROR(AVERAGE(Tabla4[[#This Row],[Creación y captura Abr/2025]:[Compartición e Interoperabilidad Abr/2025]])),"",AVERAGE(Tabla4[[#This Row],[Creación y captura Abr/2025]:[Compartición e Interoperabilidad Abr/2025]])) -> 1 | BE9: 1 | BF9: 1 | BG9: =IF(ISERROR(AVERAGE('Calidad de Datos'!AM13:AP13)),"",AVERAGE('Calidad de Datos'!AM13:AP13)) -> 1 | BH9: =IF(Tabla13[[#This Row],[Uso y acceso May/2025]]="","",Tabla13[[#This Row],[Uso y acceso May/2025]]) -> 1 | BI9: =IF(Tabla58[[#This Row],[Integración May/2025]]="","",Tabla58[[#This Row],[Integración May/2025]]) -> 1 | BJ9: =IF(ISERROR(AVERAGE(Tabla4[[#This Row],[Creación y captura May/2025]:[Compartición e Interoperabilidad May/2025]])),"",AVERAGE(Tabla4[[#This Row],[Creación y captura May/2025]:[Compartición e Interoperabilidad May/2025]])) -> 1 | BK9: 1 | BL9: 1 | BM9: =IF(ISERROR(AVERAGE('Calidad de Datos'!AQ13:AT13)),"",AVERAGE('Calidad de Datos'!AQ13:AT13)) -> 1 | BN9: =IF(Tabla13[[#This Row],[Uso y acceso Jun/2025]]="","",Tabla13[[#This Row],[Uso y acceso Jun/2025]]) -> 1 | BO9: =IF(Tabla58[[#This Row],[Integración Jun/2025]]="","",Tabla58[[#This Row],[Integración Jun/2025]]) -> 1 | BP9: =IF(ISERROR(AVERAGE(Tabla4[[#This Row],[Creación y captura Jun/2025]:[Compartición e Interoperabilidad Jun/2025]])),"",AVERAGE(Tabla4[[#This Row],[Creación y captura Jun/2025]:[Compartición e Interoperabilidad Jun/2025]])) -> 1 | BQ9: 1 | BR9: 1 | BS9: =IF(ISERROR(AVERAGE('Calidad de Datos'!AU13:AX13)),"",AVERAGE('Calidad de Datos'!AU13:AX13)) -> 1 | BT9: =IF(Tabla13[[#This Row],[Uso y acceso Sep/2025]]="","",Tabla13[[#This Row],[Uso y acceso Sep/2025]]) -> 1 | BU9: =IF(Tabla58[[#This Row],[Integración Sep/2025]]="","",Tabla58[[#This Row],[Integración Sep/2025]]) -> 1 | BV9: =IF(ISERROR(AVERAGE(Tabla4[[#This Row],[Creación y captura Sep/2025]:[Compartición e Interoperabilidad Sep/2025]])),"",AVERAGE(Tabla4[[#This Row],[Creación y captura Sep/2025]:[Compartición e Interoperabilidad Sep/2025]])) -> 1 | BW9: 1 | BX9: 1 | BY9: =IF(ISERROR(AVERAGE('Calidad de Datos'!AY13:BB13)),"",AVERAGE('Calidad de Datos'!AY13:BB13)) -> 1 | BZ9: =IF(ISERROR(Tabla13[[#This Row],[Uso y acceso Dic/2025]]),"",Tabla13[[#This Row],[Uso y acceso Dic/2025]]) -> 1 | CA9: =IF(ISERROR(Tabla58[[#This Row],[Integración Dic/2025]]),"",Tabla58[[#This Row],[Integración Dic/2025]]) -> 1 | CB9: =IF(ISERROR(AVERAGE(Tabla4[[#This Row],[Creación y captura Dic/2025]:[Compartición e Interoperabilidad Dic/2025]])),"",AVERAGE(Tabla4[[#This Row],[Creación y captura Dic/2025]:[Compartición e Interoperabilidad Dic/2025]])) -> 1 | CC9: 1 | CD9: 1 | CE9: =IF(ISERROR(AVERAGE('Calidad de Datos'!BC13:BF13)),"",AVERAGE('Calidad de Datos'!BC13:BF13)) -> 1 | CF9: =IF(ISERROR(Tabla13[[#This Row],[Uso y acceso Mar/2026]]),"",Tabla13[[#This Row],[Uso y acceso Mar/2026]]) -> 1 | CG9: =IF(ISERROR(Tabla58[[#This Row],[Integración Mar/2026]]),"",Tabla58[[#This Row],[Integración Mar/2026]]) -> 1 | CH9: =IF(ISERROR(AVERAGE(Tabla4[[#This Row],[Creación y captura Mar/2026]:[Compartición e Interoperabilidad Mar/2026]])),"",AVERAGE(Tabla4[[#This Row],[Creación y captura Mar/2026]:[Compartición e Interoperabilidad Mar/2026]])) -> 1
B10: Tipo de oportunidad | C10: 1 | D10: 1 | E10: =IF(ISERROR(AVERAGE('Calidad de Datos'!C14:F14)),"",AVERAGE('Calidad de Datos'!C14:F14)) -> 1 | F10: =IF(Tabla13[[#This Row],[Uso y acceso Ago/2024]]="","",Tabla13[[#This Row],[Uso y acceso Ago/2024]]) -> 1 | G10: =IF(Tabla58[[#This Row],[Integración Ago/2024]]="","",Tabla58[[#This Row],[Integración Ago/2024]]) -> 1 | H10: =IF(ISERROR(AVERAGE(Tabla4[[#This Row],[Creación y captura Ago/2024]:[Compartición e Interoperabilidad Ago/2024]])),"",AVERAGE(Tabla4[[#This Row],[Creación y captura Ago/2024]:[Compartición e Interoperabilidad Ago/2024]])) -> 1 | I10: 1 | J10: 1 | K10: =IF(ISERROR(AVERAGE('Calidad de Datos'!G14:J14)),"",AVERAGE('Calidad de Datos'!G14:J14)) -> 1 | L10: =IF(Tabla13[[#This Row],[Uso y acceso Sep/2024]]="","",Tabla13[[#This Row],[Uso y acceso Sep/2024]]) -> 1 | M10: =IF(Tabla58[[#This Row],[Integración Sep/2024]]="","",Tabla58[[#This Row],[Integración Sep/2024]]) -> 1 | N10: =IF(ISERROR(AVERAGE(Tabla4[[#This Row],[Creación y captura Sep/2024]:[Compartición e Interoperabilidad Sep/2024]])),"",AVERAGE(Tabla4[[#This Row],[Creación y captura Sep/2024]:[Compartición e Interoperabilidad Sep/2024]])) -> 1 | O10: 1 | P10: 1 | Q10: =IF(ISERROR(AVERAGE('Calidad de Datos'!K14:N14)),"",AVERAGE('Calidad de Datos'!K14:N14)) -> 1 | R10: =IF(Tabla13[[#This Row],[Uso y acceso Oct/2024]]="","",Tabla13[[#This Row],[Uso y acceso Oct/2024]]) -> 1 | S10: =IF(Tabla58[[#This Row],[Integración Oct/2024]]="","",Tabla58[[#This Row],[Integración Oct/2024]]) -> 1 | T10: =IF(ISERROR(AVERAGE(Tabla4[[#This Row],[Creación y captura Oct/2024]:[Compartición e Interoperabilidad Oct/2024]])),"",AVERAGE(Tabla4[[#This Row],[Creación y captura Oct/2024]:[Compartición e Interoperabilidad Oct/2024]])) -> 1 | U10: 1 | V10: 1 | W10: =IF(ISERROR(AVERAGE('Calidad de Datos'!O14:R14)),"",AVERAGE('Calidad de Datos'!O14:R14)) -> 1 | X10: =IF(Tabla13[[#This Row],[Uso y acceso Nov/2024]]="","",Tabla13[[#This Row],[Uso y acceso Nov/2024]]) -> 1 | Y10: =IF(Tabla58[[#This Row],[Integración Nov/2024]]="","",Tabla58[[#This Row],[Integración Nov/2024]]) -> 1 | Z10: =IF(ISERROR(AVERAGE(Tabla4[[#This Row],[Creación y captura Nov/2024]:[Compartición e Interoperabilidad Nov/2024]])),"",AVERAGE(Tabla4[[#This Row],[Creación y captura Nov/2024]:[Compartición e Interoperabilidad Nov/2024]])) -> 1 | AA10: 1 | AB10: 1 | AC10: =IF(ISERROR(AVERAGE('Calidad de Datos'!S14:V14)),"",AVERAGE('Calidad de Datos'!S14:V14)) -> 1 | AD10: =IF(Tabla13[[#This Row],[Uso y acceso Dic/2024]]="","",Tabla13[[#This Row],[Uso y acceso Dic/2024]]) -> 1 | AE10: =IF(Tabla58[[#This Row],[Integración Dic/2024]]="","",Tabla58[[#This Row],[Integración Dic/2024]]) -> 1 | AF10: =IF(ISERROR(AVERAGE(Tabla4[[#This Row],[Creación y captura Dic/2024]:[Compartición e Interoperabilidad Dic/2024]])),"",AVERAGE(Tabla4[[#This Row],[Creación y captura Dic/2024]:[Compartición e Interoperabilidad Dic/2024]])) -> 1 | AG10: 1 | AH10: 1 | AI10: =IF(ISERROR(AVERAGE('Calidad de Datos'!W14:Z14)),"",AVERAGE('Calidad de Datos'!W14:Z14)) -> 1 | AJ10: =IF(Tabla13[[#This Row],[Uso y acceso Ene/2025]]="","",Tabla13[[#This Row],[Uso y acceso Ene/2025]]) -> 1 | AK10: =IF(Tabla58[[#This Row],[Integración Ene/2025]]="","",Tabla58[[#This Row],[Integración Ene/2025]]) -> 1 | AL10: =IF(ISERROR(AVERAGE(Tabla4[[#This Row],[Creación y captura Ene/2025]:[Compartición e Interoperabilidad Ene/2025]])),"",AVERAGE(Tabla4[[#This Row],[Creación y captura Ene/2025]:[Compartición e Interoperabilidad Ene/2025]])) -> 1 | AM10: 1 | AN10: 1 | AO10: =IF(ISERROR(AVERAGE('Calidad de Datos'!AA14:AD14)),"",AVERAGE('Calidad de Datos'!AA14:AD14)) -> 1 | AP10: =IF(Tabla13[[#This Row],[Uso y acceso Feb/2025]]="","",Tabla13[[#This Row],[Uso y acceso Feb/2025]]) -> 1 | AQ10: =IF(Tabla58[[#This Row],[Integración Feb/2025]]="","",Tabla58[[#This Row],[Integración Feb/2025]]) -> 1 | AR10: =IF(ISERROR(AVERAGE(Tabla4[[#This Row],[Creación y captura Feb/2025]:[Compartición e Interoperabilidad Feb/2025]])),"",AVERAGE(Tabla4[[#This Row],[Creación y captura Feb/2025]:[Compartición e Interoperabilidad Feb/2025]])) -> 1 | AS10: 1 | AT10: 1 | AU10: =IF(ISERROR(AVERAGE('Calidad de Datos'!AE14:AH14)),"",AVERAGE('Calidad de Datos'!AE14:AH14)) -> 1 | AV10: =IF(Tabla13[[#This Row],[Uso y acceso Mar/2025]]="","",Tabla13[[#This Row],[Uso y acceso Mar/2025]]) -> 1 | AW10: =IF(Tabla58[[#This Row],[Integración Mar/2025]]="","",Tabla58[[#This Row],[Integración Mar/2025]]) -> 1 | AX10: =IF(ISERROR(AVERAGE(Tabla4[[#This Row],[Creación y captura Mar/2025]:[Compartición e Interoperabilidad Mar/2025]])),"",AVERAGE(Tabla4[[#This Row],[Creación y captura Mar/2025]:[Compartición e Interoperabilidad Mar/2025]])) -> 1 | AY10: 1 | AZ10: 1 | BA10: =IF(ISERROR(AVERAGE('Calidad de Datos'!AI14:AL14)),"",AVERAGE('Calidad de Datos'!AI14:AL14)) -> 1 | BB10: =IF(Tabla13[[#This Row],[Uso y acceso Abr/2025]]="","",Tabla13[[#This Row],[Uso y acceso Abr/2025]]) -> 1 | BC10: =IF(Tabla58[[#This Row],[Integración Abr/2025]]="","",Tabla58[[#This Row],[Integración Abr/2025]]) -> 1 | BD10: =IF(ISERROR(AVERAGE(Tabla4[[#This Row],[Creación y captura Abr/2025]:[Compartición e Interoperabilidad Abr/2025]])),"",AVERAGE(Tabla4[[#This Row],[Creación y captura Abr/2025]:[Compartición e Interoperabilidad Abr/2025]])) -> 1 | BE10: 1 | BF10: 1 | BG10: =IF(ISERROR(AVERAGE('Calidad de Datos'!AM14:AP14)),"",AVERAGE('Calidad de Datos'!AM14:AP14)) -> 1 | BH10: =IF(Tabla13[[#This Row],[Uso y acceso May/2025]]="","",Tabla13[[#This Row],[Uso y acceso May/2025]]) -> 1 | BI10: =IF(Tabla58[[#This Row],[Integración May/2025]]="","",Tabla58[[#This Row],[Integración May/2025]]) -> 1 | BJ10: =IF(ISERROR(AVERAGE(Tabla4[[#This Row],[Creación y captura May/2025]:[Compartición e Interoperabilidad May/2025]])),"",AVERAGE(Tabla4[[#This Row],[Creación y captura May/2025]:[Compartición e Interoperabilidad May/2025]])) -> 1 | BK10: 1 | BL10: 1 | BM10: =IF(ISERROR(AVERAGE('Calidad de Datos'!AQ14:AT14)),"",AVERAGE('Calidad de Datos'!AQ14:AT14)) -> 1 | BN10: =IF(Tabla13[[#This Row],[Uso y acceso Jun/2025]]="","",Tabla13[[#This Row],[Uso y acceso Jun/2025]]) -> 1 | BO10: =IF(Tabla58[[#This Row],[Integración Jun/2025]]="","",Tabla58[[#This Row],[Integración Jun/2025]]) -> 1 | BP10: =IF(ISERROR(AVERAGE(Tabla4[[#This Row],[Creación y captura Jun/2025]:[Compartición e Interoperabilidad Jun/2025]])),"",AVERAGE(Tabla4[[#This Row],[Creación y captura Jun/2025]:[Compartición e Interoperabilidad Jun/2025]])) -> 1 | BQ10: 1 | BR10: 1 | BS10: =IF(ISERROR(AVERAGE('Calidad de Datos'!AU14:AX14)),"",AVERAGE('Calidad de Datos'!AU14:AX14)) -> 1 | BT10: =IF(Tabla13[[#This Row],[Uso y acceso Sep/2025]]="","",Tabla13[[#This Row],[Uso y acceso Sep/2025]]) -> 1 | BU10: =IF(Tabla58[[#This Row],[Integración Sep/2025]]="","",Tabla58[[#This Row],[Integración Sep/2025]]) -> 1 | BV10: =IF(ISERROR(AVERAGE(Tabla4[[#This Row],[Creación y captura Sep/2025]:[Compartición e Interoperabilidad Sep/2025]])),"",AVERAGE(Tabla4[[#This Row],[Creación y captura Sep/2025]:[Compartición e Interoperabilidad Sep/2025]])) -> 1 | BW10: 1 | BX10: 1 | BY10: =IF(ISERROR(AVERAGE('Calidad de Datos'!AY14:BB14)),"",AVERAGE('Calidad de Datos'!AY14:BB14)) -> 1 | BZ10: =IF(ISERROR(Tabla13[[#This Row],[Uso y acceso Dic/2025]]),"",Tabla13[[#This Row],[Uso y acceso Dic/2025]]) -> 1 | CA10: =IF(ISERROR(Tabla58[[#This Row],[Integración Dic/2025]]),"",Tabla58[[#This Row],[Integración Dic/2025]]) -> 1 | CB10: =IF(ISERROR(AVERAGE(Tabla4[[#This Row],[Creación y captura Dic/2025]:[Compartición e Interoperabilidad Dic/2025]])),"",AVERAGE(Tabla4[[#This Row],[Creación y captura Dic/2025]:[Compartición e Interoperabilidad Dic/2025]])) -> 1 | CC10: 1 | CD10: 1 | CE10: =IF(ISERROR(AVERAGE('Calidad de Datos'!BC14:BF14)),"",AVERAGE('Calidad de Datos'!BC14:BF14)) -> 1 | CF10: =IF(ISERROR(Tabla13[[#This Row],[Uso y acceso Mar/2026]]),"",Tabla13[[#This Row],[Uso y acceso Mar/2026]]) -> 1 | CG10: =IF(ISERROR(Tabla58[[#This Row],[Integración Mar/2026]]),"",Tabla58[[#This Row],[Integración Mar/2026]]) -> 1 | CH10: =IF(ISERROR(AVERAGE(Tabla4[[#This Row],[Creación y captura Mar/2026]:[Compartición e Interoperabilidad Mar/2026]])),"",AVERAGE(Tabla4[[#This Row],[Creación y captura Mar/2026]:[Compartición e Interoperabilidad Mar/2026]])) -> 1
B11: Etapa actual | C11: 1 | D11: 1 | E11: =IF(ISERROR(AVERAGE('Calidad de Datos'!C15:F15)),"",AVERAGE('Calidad de Datos'!C15:F15)) -> 1 | F11: =IF(Tabla13[[#This Row],[Uso y acceso Ago/2024]]="","",Tabla13[[#This Row],[Uso y acceso Ago/2024]]) -> 1 | G11: =IF(Tabla58[[#This Row],[Integración Ago/2024]]="","",Tabla58[[#This Row],[Integración Ago/2024]]) -> 1 | H11: =IF(ISERROR(AVERAGE(Tabla4[[#This Row],[Creación y captura Ago/2024]:[Compartición e Interoperabilidad Ago/2024]])),"",AVERAGE(Tabla4[[#This Row],[Creación y captura Ago/2024]:[Compartición e Interoperabilidad Ago/2024]])) -> 1 | I11: 1 | J11: 1 | K11: =IF(ISERROR(AVERAGE('Calidad de Datos'!G15:J15)),"",AVERAGE('Calidad de Datos'!G15:J15)) -> 1 | L11: =IF(Tabla13[[#This Row],[Uso y acceso Sep/2024]]="","",Tabla13[[#This Row],[Uso y acceso Sep/2024]]) -> 1 | M11: =IF(Tabla58[[#This Row],[Integración Sep/2024]]="","",Tabla58[[#This Row],[Integración Sep/2024]]) -> 1 | N11: =IF(ISERROR(AVERAGE(Tabla4[[#This Row],[Creación y captura Sep/2024]:[Compartición e Interoperabilidad Sep/2024]])),"",AVERAGE(Tabla4[[#This Row],[Creación y captura Sep/2024]:[Compartición e Interoperabilidad Sep/2024]])) -> 1 | O11: 1 | P11: 1 | Q11: =IF(ISERROR(AVERAGE('Calidad de Datos'!K15:N15)),"",AVERAGE('Calidad de Datos'!K15:N15)) -> 1 | R11: =IF(Tabla13[[#This Row],[Uso y acceso Oct/2024]]="","",Tabla13[[#This Row],[Uso y acceso Oct/2024]]) -> 1 | S11: =IF(Tabla58[[#This Row],[Integración Oct/2024]]="","",Tabla58[[#This Row],[Integración Oct/2024]]) -> 1 | T11: =IF(ISERROR(AVERAGE(Tabla4[[#This Row],[Creación y captura Oct/2024]:[Compartición e Interoperabilidad Oct/2024]])),"",AVERAGE(Tabla4[[#This Row],[Creación y captura Oct/2024]:[Compartición e Interoperabilidad Oct/2024]])) -> 1 | U11: 1 | V11: 1 | W11: =IF(ISERROR(AVERAGE('Calidad de Datos'!O15:R15)),"",AVERAGE('Calidad de Datos'!O15:R15)) -> 1 | X11: =IF(Tabla13[[#This Row],[Uso y acceso Nov/2024]]="","",Tabla13[[#This Row],[Uso y acceso Nov/2024]]) -> 1 | Y11: =IF(Tabla58[[#This Row],[Integración Nov/2024]]="","",Tabla58[[#This Row],[Integración Nov/2024]]) -> 1 | Z11: =IF(ISERROR(AVERAGE(Tabla4[[#This Row],[Creación y captura Nov/2024]:[Compartición e Interoperabilidad Nov/2024]])),"",AVERAGE(Tabla4[[#This Row],[Creación y captura Nov/2024]:[Compartición e Interoperabilidad Nov/2024]])) -> 1 | AA11: 1 | AB11: 1 | AC11: =IF(ISERROR(AVERAGE('Calidad de Datos'!S15:V15)),"",AVERAGE('Calidad de Datos'!S15:V15)) -> 1 | AD11: =IF(Tabla13[[#This Row],[Uso y acceso Dic/2024]]="","",Tabla13[[#This Row],[Uso y acceso Dic/2024]]) -> 1 | AE11: =IF(Tabla58[[#This Row],[Integración Dic/2024]]="","",Tabla58[[#This Row],[Integración Dic/2024]]) -> 1 | AF11: =IF(ISERROR(AVERAGE(Tabla4[[#This Row],[Creación y captura Dic/2024]:[Compartición e Interoperabilidad Dic/2024]])),"",AVERAGE(Tabla4[[#This Row],[Creación y captura Dic/2024]:[Compartición e Interoperabilidad Dic/2024]])) -> 1 | AG11: 1 | AH11: 1 | AI11: =IF(ISERROR(AVERAGE('Calidad de Datos'!W15:Z15)),"",AVERAGE('Calidad de Datos'!W15:Z15)) -> 1 | AJ11: =IF(Tabla13[[#This Row],[Uso y acceso Ene/2025]]="","",Tabla13[[#This Row],[Uso y acceso Ene/2025]]) -> 1 | AK11: =IF(Tabla58[[#This Row],[Integración Ene/2025]]="","",Tabla58[[#This Row],[Integración Ene/2025]]) -> 1 | AL11: =IF(ISERROR(AVERAGE(Tabla4[[#This Row],[Creación y captura Ene/2025]:[Compartición e Interoperabilidad Ene/2025]])),"",AVERAGE(Tabla4[[#This Row],[Creación y captura Ene/2025]:[Compartición e Interoperabilidad Ene/2025]])) -> 1 | AM11: 1 | AN11: 1 | AO11: =IF(ISERROR(AVERAGE('Calidad de Datos'!AA15:AD15)),"",AVERAGE('Calidad de Datos'!AA15:AD15)) -> 1 | AP11: =IF(Tabla13[[#This Row],[Uso y acceso Feb/2025]]="","",Tabla13[[#This Row],[Uso y acceso Feb/2025]]) -> 1 | AQ11: =IF(Tabla58[[#This Row],[Integración Feb/2025]]="","",Tabla58[[#This Row],[Integración Feb/2025]]) -> 1 | AR11: =IF(ISERROR(AVERAGE(Tabla4[[#This Row],[Creación y captura Feb/2025]:[Compartición e Interoperabilidad Feb/2025]])),"",AVERAGE(Tabla4[[#This Row],[Creación y captura Feb/2025]:[Compartición e Interoperabilidad Feb/2025]])) -> 1 | AS11: 1 | AT11: 1 | AU11: =IF(ISERROR(AVERAGE('Calidad de Datos'!AE15:AH15)),"",AVERAGE('Calidad de Datos'!AE15:AH15)) -> 1 | AV11: =IF(Tabla13[[#This Row],[Uso y acceso Mar/2025]]="","",Tabla13[[#This Row],[Uso y acceso Mar/2025]]) -> 1 | AW11: =IF(Tabla58[[#This Row],[Integración Mar/2025]]="","",Tabla58[[#This Row],[Integración Mar/2025]]) -> 1 | AX11: =IF(ISERROR(AVERAGE(Tabla4[[#This Row],[Creación y captura Mar/2025]:[Compartición e Interoperabilidad Mar/2025]])),"",AVERAGE(Tabla4[[#This Row],[Creación y captura Mar/2025]:[Compartición e Interoperabilidad Mar/2025]])) -> 1 | AY11: 1 | AZ11: 1 | BA11: =IF(ISERROR(AVERAGE('Calidad de Datos'!AI15:AL15)),"",AVERAGE('Calidad de Datos'!AI15:AL15)) -> 1 | BB11: =IF(Tabla13[[#This Row],[Uso y acceso Abr/2025]]="","",Tabla13[[#This Row],[Uso y acceso Abr/2025]]) -> 1 | BC11: =IF(Tabla58[[#This Row],[Integración Abr/2025]]="","",Tabla58[[#This Row],[Integración Abr/2025]]) -> 1 | BD11: =IF(ISERROR(AVERAGE(Tabla4[[#This Row],[Creación y captura Abr/2025]:[Compartición e Interoperabilidad Abr/2025]])),"",AVERAGE(Tabla4[[#This Row],[Creación y captura Abr/2025]:[Compartición e Interoperabilidad Abr/2025]])) -> 1 | BE11: 1 | BF11: 1 | BG11: =IF(ISERROR(AVERAGE('Calidad de Datos'!AM15:AP15)),"",AVERAGE('Calidad de Datos'!AM15:AP15)) -> 1 | BH11: =IF(Tabla13[[#This Row],[Uso y acceso May/2025]]="","",Tabla13[[#This Row],[Uso y acceso May/2025]]) -> 1 | BI11: =IF(Tabla58[[#This Row],[Integración May/2025]]="","",Tabla58[[#This Row],[Integración May/2025]]) -> 1 | BJ11: =IF(ISERROR(AVERAGE(Tabla4[[#This Row],[Creación y captura May/2025]:[Compartición e Interoperabilidad May/2025]])),"",AVERAGE(Tabla4[[#This Row],[Creación y captura May/2025]:[Compartición e Interoperabilidad May/2025]])) -> 1 | BK11: 1 | BL11: 1 | BM11: =IF(ISERROR(AVERAGE('Calidad de Datos'!AQ15:AT15)),"",AVERAGE('Calidad de Datos'!AQ15:AT15)) -> 1 | BN11: =IF(Tabla13[[#This Row],[Uso y acceso Jun/2025]]="","",Tabla13[[#This Row],[Uso y acceso Jun/2025]]) -> 1 | BO11: =IF(Tabla58[[#This Row],[Integración Jun/2025]]="","",Tabla58[[#This Row],[Integración Jun/2025]]) -> 1 | BP11: =IF(ISERROR(AVERAGE(Tabla4[[#This Row],[Creación y captura Jun/2025]:[Compartición e Interoperabilidad Jun/2025]])),"",AVERAGE(Tabla4[[#This Row],[Creación y captura Jun/2025]:[Compartición e Interoperabilidad Jun/2025]])) -> 1 | BQ11: 1 | BR11: 1 | BS11: =IF(ISERROR(AVERAGE('Calidad de Datos'!AU15:AX15)),"",AVERAGE('Calidad de Datos'!AU15:AX15)) -> 1 | BT11: =IF(Tabla13[[#This Row],[Uso y acceso Sep/2025]]="","",Tabla13[[#This Row],[Uso y acceso Sep/2025]]) -> 1 | BU11: =IF(Tabla58[[#This Row],[Integración Sep/2025]]="","",Tabla58[[#This Row],[Integración Sep/2025]]) -> 1 | BV11: =IF(ISERROR(AVERAGE(Tabla4[[#This Row],[Creación y captura Sep/2025]:[Compartición e Interoperabilidad Sep/2025]])),"",AVERAGE(Tabla4[[#This Row],[Creación y captura Sep/2025]:[Compartición e Interoperabilidad Sep/2025]])) -> 1 | BW11: 1 | BX11: 1 | BY11: =IF(ISERROR(AVERAGE('Calidad de Datos'!AY15:BB15)),"",AVERAGE('Calidad de Datos'!AY15:BB15)) -> 1 | BZ11: =IF(ISERROR(Tabla13[[#This Row],[Uso y acceso Dic/2025]]),"",Tabla13[[#This Row],[Uso y acceso Dic/2025]]) -> 1 | CA11: =IF(ISERROR(Tabla58[[#This Row],[Integración Dic/2025]]),"",Tabla58[[#This Row],[Integración Dic/2025]]) -> 1 | CB11: =IF(ISERROR(AVERAGE(Tabla4[[#This Row],[Creación y captura Dic/2025]:[Compartición e Interoperabilidad Dic/2025]])),"",AVERAGE(Tabla4[[#This Row],[Creación y captura Dic/2025]:[Compartición e Interoperabilidad Dic/2025]])) -> 1 | CC11: 1 | CD11: 1 | CE11: =IF(ISERROR(AVERAGE('Calidad de Datos'!BC15:BF15)),"",AVERAGE('Calidad de Datos'!BC15:BF15)) -> 1 | CF11: =IF(ISERROR(Tabla13[[#This Row],[Uso y acceso Mar/2026]]),"",Tabla13[[#This Row],[Uso y acceso Mar/2026]]) -> 1 | CG11: =IF(ISERROR(Tabla58[[#This Row],[Integración Mar/2026]]),"",Tabla58[[#This Row],[Integración Mar/2026]]) -> 1 | CH11: =IF(ISERROR(AVERAGE(Tabla4[[#This Row],[Creación y captura Mar/2026]:[Compartición e Interoperabilidad Mar/2026]])),"",AVERAGE(Tabla4[[#This Row],[Creación y captura Mar/2026]:[Compartición e Interoperabilidad Mar/2026]])) -> 1
B12: Ganado | C12: 1 | D12: 1 | E12: =IF(ISERROR(AVERAGE('Calidad de Datos'!C16:F16)),"",AVERAGE('Calidad de Datos'!C16:F16)) -> 1 | F12: =IF(Tabla13[[#This Row],[Uso y acceso Ago/2024]]="","",Tabla13[[#This Row],[Uso y acceso Ago/2024]]) -> 1 | G12: =IF(Tabla58[[#This Row],[Integración Ago/2024]]="","",Tabla58[[#This Row],[Integración Ago/2024]]) -> 1 | H12: =IF(ISERROR(AVERAGE(Tabla4[[#This Row],[Creación y captura Ago/2024]:[Compartición e Interoperabilidad Ago/2024]])),"",AVERAGE(Tabla4[[#This Row],[Creación y captura Ago/2024]:[Compartición e Interoperabilidad Ago/2024]])) -> 1 | I12: 1 | J12: 1 | K12: =IF(ISERROR(AVERAGE('Calidad de Datos'!G16:J16)),"",AVERAGE('Calidad de Datos'!G16:J16)) -> 1 | L12: =IF(Tabla13[[#This Row],[Uso y acceso Sep/2024]]="","",Tabla13[[#This Row],[Uso y acceso Sep/2024]]) -> 1 | M12: =IF(Tabla58[[#This Row],[Integración Sep/2024]]="","",Tabla58[[#This Row],[Integración Sep/2024]]) -> 1 | N12: =IF(ISERROR(AVERAGE(Tabla4[[#This Row],[Creación y captura Sep/2024]:[Compartición e Interoperabilidad Sep/2024]])),"",AVERAGE(Tabla4[[#This Row],[Creación y captura Sep/2024]:[Compartición e Interoperabilidad Sep/2024]])) -> 1 | O12: 1 | P12: 1 | Q12: =IF(ISERROR(AVERAGE('Calidad de Datos'!K16:N16)),"",AVERAGE('Calidad de Datos'!K16:N16)) -> 1 | R12: =IF(Tabla13[[#This Row],[Uso y acceso Oct/2024]]="","",Tabla13[[#This Row],[Uso y acceso Oct/2024]]) -> 1 | S12: =IF(Tabla58[[#This Row],[Integración Oct/2024]]="","",Tabla58[[#This Row],[Integración Oct/2024]]) -> 1 | T12: =IF(ISERROR(AVERAGE(Tabla4[[#This Row],[Creación y captura Oct/2024]:[Compartición e Interoperabilidad Oct/2024]])),"",AVERAGE(Tabla4[[#This Row],[Creación y captura Oct/2024]:[Compartición e Interoperabilidad Oct/2024]])) -> 1 | U12: 1 | V12: 1 | W12: =IF(ISERROR(AVERAGE('Calidad de Datos'!O16:R16)),"",AVERAGE('Calidad de Datos'!O16:R16)) -> 1 | X12: =IF(Tabla13[[#This Row],[Uso y acceso Nov/2024]]="","",Tabla13[[#This Row],[Uso y acceso Nov/2024]]) -> 1 | Y12: =IF(Tabla58[[#This Row],[Integración Nov/2024]]="","",Tabla58[[#This Row],[Integración Nov/2024]]) -> 1 | Z12: =IF(ISERROR(AVERAGE(Tabla4[[#This Row],[Creación y captura Nov/2024]:[Compartición e Interoperabilidad Nov/2024]])),"",AVERAGE(Tabla4[[#This Row],[Creación y captura Nov/2024]:[Compartición e Interoperabilidad Nov/2024]])) -> 1 | AA12: 1 | AB12: 1 | AC12: =IF(ISERROR(AVERAGE('Calidad de Datos'!S16:V16)),"",AVERAGE('Calidad de Datos'!S16:V16)) -> 1 | AD12: =IF(Tabla13[[#This Row],[Uso y acceso Dic/2024]]="","",Tabla13[[#This Row],[Uso y acceso Dic/2024]]) -> 1 | AE12: =IF(Tabla58[[#This Row],[Integración Dic/2024]]="","",Tabla58[[#This Row],[Integración Dic/2024]]) -> 1 | AF12: =IF(ISERROR(AVERAGE(Tabla4[[#This Row],[Creación y captura Dic/2024]:[Compartición e Interoperabilidad Dic/2024]])),"",AVERAGE(Tabla4[[#This Row],[Creación y captura Dic/2024]:[Compartición e Interoperabilidad Dic/2024]])) -> 1 | AG12: 1 | AH12: 1 | AI12: =IF(ISERROR(AVERAGE('Calidad de Datos'!W16:Z16)),"",AVERAGE('Calidad de Datos'!W16:Z16)) -> 1 | AJ12: =IF(Tabla13[[#This Row],[Uso y acceso Ene/2025]]="","",Tabla13[[#This Row],[Uso y acceso Ene/2025]]) -> 1 | AK12: =IF(Tabla58[[#This Row],[Integración Ene/2025]]="","",Tabla58[[#This Row],[Integración Ene/2025]]) -> 1 | AL12: =IF(ISERROR(AVERAGE(Tabla4[[#This Row],[Creación y captura Ene/2025]:[Compartición e Interoperabilidad Ene/2025]])),"",AVERAGE(Tabla4[[#This Row],[Creación y captura Ene/2025]:[Compartición e Interoperabilidad Ene/2025]])) -> 1 | AM12: 1 | AN12: 1 | AO12: =IF(ISERROR(AVERAGE('Calidad de Datos'!AA16:AD16)),"",AVERAGE('Calidad de Datos'!AA16:AD16)) -> 1 | AP12: =IF(Tabla13[[#This Row],[Uso y acceso Feb/2025]]="","",Tabla13[[#This Row],[Uso y acceso Feb/2025]]) -> 1 | AQ12: =IF(Tabla58[[#This Row],[Integración Feb/2025]]="","",Tabla58[[#This Row],[Integración Feb/2025]]) -> 1 | AR12: =IF(ISERROR(AVERAGE(Tabla4[[#This Row],[Creación y captura Feb/2025]:[Compartición e Interoperabilidad Feb/2025]])),"",AVERAGE(Tabla4[[#This Row],[Creación y captura Feb/2025]:[Compartición e Interoperabilidad Feb/2025]])) -> 1 | AS12: 1 | AT12: 1 | AU12: =IF(ISERROR(AVERAGE('Calidad de Datos'!AE16:AH16)),"",AVERAGE('Calidad de Datos'!AE16:AH16)) -> 1 | AV12: =IF(Tabla13[[#This Row],[Uso y acceso Mar/2025]]="","",Tabla13[[#This Row],[Uso y acceso Mar/2025]]) -> 1 | AW12: =IF(Tabla58[[#This Row],[Integración Mar/2025]]="","",Tabla58[[#This Row],[Integración Mar/2025]]) -> 1 | AX12: =IF(ISERROR(AVERAGE(Tabla4[[#This Row],[Creación y captura Mar/2025]:[Compartición e Interoperabilidad Mar/2025]])),"",AVERAGE(Tabla4[[#This Row],[Creación y captura Mar/2025]:[Compartición e Interoperabilidad Mar/2025]])) -> 1 | AY12: 1 | AZ12: 1 | BA12: =IF(ISERROR(AVERAGE('Calidad de Datos'!AI16:AL16)),"",AVERAGE('Calidad de Datos'!AI16:AL16)) -> 1 | BB12: =IF(Tabla13[[#This Row],[Uso y acceso Abr/2025]]="","",Tabla13[[#This Row],[Uso y acceso Abr/2025]]) -> 1 | BC12: =IF(Tabla58[[#This Row],[Integración Abr/2025]]="","",Tabla58[[#This Row],[Integración Abr/2025]]) -> 1 | BD12: =IF(ISERROR(AVERAGE(Tabla4[[#This Row],[Creación y captura Abr/2025]:[Compartición e Interoperabilidad Abr/2025]])),"",AVERAGE(Tabla4[[#This Row],[Creación y captura Abr/2025]:[Compartición e Interoperabilidad Abr/2025]])) -> 1 | BE12: 1 | BF12: 1 | BG12: =IF(ISERROR(AVERAGE('Calidad de Datos'!AM16:AP16)),"",AVERAGE('Calidad de Datos'!AM16:AP16)) -> 1 | BH12: =IF(Tabla13[[#This Row],[Uso y acceso May/2025]]="","",Tabla13[[#This Row],[Uso y acceso May/2025]]) -> 1 | BI12: =IF(Tabla58[[#This Row],[Integración May/2025]]="","",Tabla58[[#This Row],[Integración May/2025]]) -> 1 | BJ12: =IF(ISERROR(AVERAGE(Tabla4[[#This Row],[Creación y captura May/2025]:[Compartición e Interoperabilidad May/2025]])),"",AVERAGE(Tabla4[[#This Row],[Creación y captura May/2025]:[Compartición e Interoperabilidad May/2025]])) -> 1 | BK12: 1 | BL12: 1 | BM12: =IF(ISERROR(AVERAGE('Calidad de Datos'!AQ16:AT16)),"",AVERAGE('Calidad de Datos'!AQ16:AT16)) -> 1 | BN12: =IF(Tabla13[[#This Row],[Uso y acceso Jun/2025]]="","",Tabla13[[#This Row],[Uso y acceso Jun/2025]]) -> 1 | BO12: =IF(Tabla58[[#This Row],[Integración Jun/2025]]="","",Tabla58[[#This Row],[Integración Jun/2025]]) -> 1 | BP12: =IF(ISERROR(AVERAGE(Tabla4[[#This Row],[Creación y captura Jun/2025]:[Compartición e Interoperabilidad Jun/2025]])),"",AVERAGE(Tabla4[[#This Row],[Creación y captura Jun/2025]:[Compartición e Interoperabilidad Jun/2025]])) -> 1 | BQ12: 1 | BR12: 1 | BS12: =IF(ISERROR(AVERAGE('Calidad de Datos'!AU16:AX16)),"",AVERAGE('Calidad de Datos'!AU16:AX16)) -> 1 | BT12: =IF(Tabla13[[#This Row],[Uso y acceso Sep/2025]]="","",Tabla13[[#This Row],[Uso y acceso Sep/2025]]) -> 1 | BU12: =IF(Tabla58[[#This Row],[Integración Sep/2025]]="","",Tabla58[[#This Row],[Integración Sep/2025]]) -> 1 | BV12: =IF(ISERROR(AVERAGE(Tabla4[[#This Row],[Creación y captura Sep/2025]:[Compartición e Interoperabilidad Sep/2025]])),"",AVERAGE(Tabla4[[#This Row],[Creación y captura Sep/2025]:[Compartición e Interoperabilidad Sep/2025]])) -> 1 | BW12: 1 | BX12: 1 | BY12: =IF(ISERROR(AVERAGE('Calidad de Datos'!AY16:BB16)),"",AVERAGE('Calidad de Datos'!AY16:BB16)) -> 1 | BZ12: =IF(ISERROR(Tabla13[[#This Row],[Uso y acceso Dic/2025]]),"",Tabla13[[#This Row],[Uso y acceso Dic/2025]]) -> 1 | CA12: =IF(ISERROR(Tabla58[[#This Row],[Integración Dic/2025]]),"",Tabla58[[#This Row],[Integración Dic/2025]]) -> 1 | CB12: =IF(ISERROR(AVERAGE(Tabla4[[#This Row],[Creación y captura Dic/2025]:[Compartición e Interoperabilidad Dic/2025]])),"",AVERAGE(Tabla4[[#This Row],[Creación y captura Dic/2025]:[Compartición e Interoperabilidad Dic/2025]])) -> 1 | CC12: 1 | CD12: 1 | CE12: =IF(ISERROR(AVERAGE('Calidad de Datos'!BC16:BF16)),"",AVERAGE('Calidad de Datos'!BC16:BF16)) -> 1 | CF12: =IF(ISERROR(Tabla13[[#This Row],[Uso y acceso Mar/2026]]),"",Tabla13[[#This Row],[Uso y acceso Mar/2026]]) -> 1 | CG12: =IF(ISERROR(Tabla58[[#This Row],[Integración Mar/2026]]),"",Tabla58[[#This Row],[Integración Mar/2026]]) -> 1 | CH12: =IF(ISERROR(AVERAGE(Tabla4[[#This Row],[Creación y captura Mar/2026]:[Compartición e Interoperabilidad Mar/2026]])),"",AVERAGE(Tabla4[[#This Row],[Creación y captura Mar/2026]:[Compartición e Interoperabilidad Mar/2026]])) -> 1
B13: Metas | C13: 1 | D13: 1 | E13: =IF(ISERROR(AVERAGE('Calidad de Datos'!C17:F17)),"",AVERAGE('Calidad de Datos'!C17:F17)) -> 1 | F13: =IF(Tabla13[[#This Row],[Uso y acceso Ago/2024]]="","",Tabla13[[#This Row],[Uso y acceso Ago/2024]]) -> 1 | G13: =IF(Tabla58[[#This Row],[Integración Ago/2024]]="","",Tabla58[[#This Row],[Integración Ago/2024]]) -> 1 | H13: =IF(ISERROR(AVERAGE(Tabla4[[#This Row],[Creación y captura Ago/2024]:[Compartición e Interoperabilidad Ago/2024]])),"",AVERAGE(Tabla4[[#This Row],[Creación y captura Ago/2024]:[Compartición e Interoperabilidad Ago/2024]])) -> 1 | I13: 1 | J13: 1 | K13: =IF(ISERROR(AVERAGE('Calidad de Datos'!G17:J17)),"",AVERAGE('Calidad de Datos'!G17:J17)) -> 1 | L13: =IF(Tabla13[[#This Row],[Uso y acceso Sep/2024]]="","",Tabla13[[#This Row],[Uso y acceso Sep/2024]]) -> 1 | M13: =IF(Tabla58[[#This Row],[Integración Sep/2024]]="","",Tabla58[[#This Row],[Integración Sep/2024]]) -> 1 | N13: =IF(ISERROR(AVERAGE(Tabla4[[#This Row],[Creación y captura Sep/2024]:[Compartición e Interoperabilidad Sep/2024]])),"",AVERAGE(Tabla4[[#This Row],[Creación y captura Sep/2024]:[Compartición e Interoperabilidad Sep/2024]])) -> 1 | O13: 1 | P13: 1 | Q13: =IF(ISERROR(AVERAGE('Calidad de Datos'!K17:N17)),"",AVERAGE('Calidad de Datos'!K17:N17)) -> 1 | R13: =IF(Tabla13[[#This Row],[Uso y acceso Oct/2024]]="","",Tabla13[[#This Row],[Uso y acceso Oct/2024]]) -> 1 | S13: =IF(Tabla58[[#This Row],[Integración Oct/2024]]="","",Tabla58[[#This Row],[Integración Oct/2024]]) -> 1 | T13: =IF(ISERROR(AVERAGE(Tabla4[[#This Row],[Creación y captura Oct/2024]:[Compartición e Interoperabilidad Oct/2024]])),"",AVERAGE(Tabla4[[#This Row],[Creación y captura Oct/2024]:[Compartición e Interoperabilidad Oct/2024]])) -> 1 | U13: 1 | V13: 1 | W13: =IF(ISERROR(AVERAGE('Calidad de Datos'!O17:R17)),"",AVERAGE('Calidad de Datos'!O17:R17)) -> 1 | X13: =IF(Tabla13[[#This Row],[Uso y acceso Nov/2024]]="","",Tabla13[[#This Row],[Uso y acceso Nov/2024]]) -> 1 | Y13: =IF(Tabla58[[#This Row],[Integración Nov/2024]]="","",Tabla58[[#This Row],[Integración Nov/2024]]) -> 1 | Z13: =IF(ISERROR(AVERAGE(Tabla4[[#This Row],[Creación y captura Nov/2024]:[Compartición e Interoperabilidad Nov/2024]])),"",AVERAGE(Tabla4[[#This Row],[Creación y captura Nov/2024]:[Compartición e Interoperabilidad Nov/2024]])) -> 1 | AA13: 1 | AB13: 1 | AC13: =IF(ISERROR(AVERAGE('Calidad de Datos'!S17:V17)),"",AVERAGE('Calidad de Datos'!S17:V17)) -> 1 | AD13: =IF(Tabla13[[#This Row],[Uso y acceso Dic/2024]]="","",Tabla13[[#This Row],[Uso y acceso Dic/2024]]) -> 1 | AE13: =IF(Tabla58[[#This Row],[Integración Dic/2024]]="","",Tabla58[[#This Row],[Integración Dic/2024]]) -> 1 | AF13: =IF(ISERROR(AVERAGE(Tabla4[[#This Row],[Creación y captura Dic/2024]:[Compartición e Interoperabilidad Dic/2024]])),"",AVERAGE(Tabla4[[#This Row],[Creación y captura Dic/2024]:[Compartición e Interoperabilidad Dic/2024]])) -> 1 | AG13: 1 | AH13: 1 | AI13: =IF(ISERROR(AVERAGE('Calidad de Datos'!W17:Z17)),"",AVERAGE('Calidad de Datos'!W17:Z17)) -> 1 | AJ13: =IF(Tabla13[[#This Row],[Uso y acceso Ene/2025]]="","",Tabla13[[#This Row],[Uso y acceso Ene/2025]]) -> 1 | AK13: =IF(Tabla58[[#This Row],[Integración Ene/2025]]="","",Tabla58[[#This Row],[Integración Ene/2025]]) -> 1 | AL13: =IF(ISERROR(AVERAGE(Tabla4[[#This Row],[Creación y captura Ene/2025]:[Compartición e Interoperabilidad Ene/2025]])),"",AVERAGE(Tabla4[[#This Row],[Creación y captura Ene/2025]:[Compartición e Interoperabilidad Ene/2025]])) -> 1 | AM13: 1 | AN13: 1 | AO13: =IF(ISERROR(AVERAGE('Calidad de Datos'!AA17:AD17)),"",AVERAGE('Calidad de Datos'!AA17:AD17)) -> 1 | AP13: =IF(Tabla13[[#This Row],[Uso y acceso Feb/2025]]="","",Tabla13[[#This Row],[Uso y acceso Feb/2025]]) -> 1 | AQ13: =IF(Tabla58[[#This Row],[Integración Feb/2025]]="","",Tabla58[[#This Row],[Integración Feb/2025]]) -> 1 | AR13: =IF(ISERROR(AVERAGE(Tabla4[[#This Row],[Creación y captura Feb/2025]:[Compartición e Interoperabilidad Feb/2025]])),"",AVERAGE(Tabla4[[#This Row],[Creación y captura Feb/2025]:[Compartición e Interoperabilidad Feb/2025]])) -> 1 | AS13: 1 | AT13: 1 | AU13: =IF(ISERROR(AVERAGE('Calidad de Datos'!AE17:AH17)),"",AVERAGE('Calidad de Datos'!AE17:AH17)) -> 1 | AV13: =IF(Tabla13[[#This Row],[Uso y acceso Mar/2025]]="","",Tabla13[[#This Row],[Uso y acceso Mar/2025]]) -> 1 | AW13: =IF(Tabla58[[#This Row],[Integración Mar/2025]]="","",Tabla58[[#This Row],[Integración Mar/2025]]) -> 1 | AX13: =IF(ISERROR(AVERAGE(Tabla4[[#This Row],[Creación y captura Mar/2025]:[Compartición e Interoperabilidad Mar/2025]])),"",AVERAGE(Tabla4[[#This Row],[Creación y captura Mar/2025]:[Compartición e Interoperabilidad Mar/2025]])) -> 1 | AY13: 1 | AZ13: 1 | BA13: =IF(ISERROR(AVERAGE('Calidad de Datos'!AI17:AL17)),"",AVERAGE('Calidad de Datos'!AI17:AL17)) -> 1 | BB13: =IF(Tabla13[[#This Row],[Uso y acceso Abr/2025]]="","",Tabla13[[#This Row],[Uso y acceso Abr/2025]]) -> 1 | BC13: =IF(Tabla58[[#This Row],[Integración Abr/2025]]="","",Tabla58[[#This Row],[Integración Abr/2025]]) -> 1 | BD13: =IF(ISERROR(AVERAGE(Tabla4[[#This Row],[Creación y captura Abr/2025]:[Compartición e Interoperabilidad Abr/2025]])),"",AVERAGE(Tabla4[[#This Row],[Creación y captura Abr/2025]:[Compartición e Interoperabilidad Abr/2025]])) -> 1 | BE13: 1 | BF13: 1 | BG13: =IF(ISERROR(AVERAGE('Calidad de Datos'!AM17:AP17)),"",AVERAGE('Calidad de Datos'!AM17:AP17)) -> 1 | BH13: =IF(Tabla13[[#This Row],[Uso y acceso May/2025]]="","",Tabla13[[#This Row],[Uso y acceso May/2025]]) -> 1 | BI13: =IF(Tabla58[[#This Row],[Integración May/2025]]="","",Tabla58[[#This Row],[Integración May/2025]]) -> 1 | BJ13: =IF(ISERROR(AVERAGE(Tabla4[[#This Row],[Creación y captura May/2025]:[Compartición e Interoperabilidad May/2025]])),"",AVERAGE(Tabla4[[#This Row],[Creación y captura May/2025]:[Compartición e Interoperabilidad May/2025]])) -> 1 | BK13: 1 | BL13: 1 | BM13: =IF(ISERROR(AVERAGE('Calidad de Datos'!AQ17:AT17)),"",AVERAGE('Calidad de Datos'!AQ17:AT17)) -> 1 | BN13: =IF(Tabla13[[#This Row],[Uso y acceso Jun/2025]]="","",Tabla13[[#This Row],[Uso y acceso Jun/2025]]) -> 1 | BO13: =IF(Tabla58[[#This Row],[Integración Jun/2025]]="","",Tabla58[[#This Row],[Integración Jun/2025]]) -> 1 | BP13: =IF(ISERROR(AVERAGE(Tabla4[[#This Row],[Creación y captura Jun/2025]:[Compartición e Interoperabilidad Jun/2025]])),"",AVERAGE(Tabla4[[#This Row],[Creación y captura Jun/2025]:[Compartición e Interoperabilidad Jun/2025]])) -> 1 | BQ13: 1 | BR13: 1 | BS13: =IF(ISERROR(AVERAGE('Calidad de Datos'!AU17:AX17)),"",AVERAGE('Calidad de Datos'!AU17:AX17)) -> 1 | BT13: =IF(Tabla13[[#This Row],[Uso y acceso Sep/2025]]="","",Tabla13[[#This Row],[Uso y acceso Sep/2025]]) -> 1 | BU13: =IF(Tabla58[[#This Row],[Integración Sep/2025]]="","",Tabla58[[#This Row],[Integración Sep/2025]]) -> 1 | BV13: =IF(ISERROR(AVERAGE(Tabla4[[#This Row],[Creación y captura Sep/2025]:[Compartición e Interoperabilidad Sep/2025]])),"",AVERAGE(Tabla4[[#This Row],[Creación y captura Sep/2025]:[Compartición e Interoperabilidad Sep/2025]])) -> 1 | BW13: 1 | BX13: 1 | BY13: =IF(ISERROR(AVERAGE('Calidad de Datos'!AY17:BB17)),"",AVERAGE('Calidad de Datos'!AY17:BB17)) -> 1 | BZ13: =IF(ISERROR(Tabla13[[#This Row],[Uso y acceso Dic/2025]]),"",Tabla13[[#This Row],[Uso y acceso Dic/2025]]) -> 1 | CA13: =IF(ISERROR(Tabla58[[#This Row],[Integración Dic/2025]]),"",Tabla58[[#This Row],[Integración Dic/2025]]) -> 1 | CB13: =IF(ISERROR(AVERAGE(Tabla4[[#This Row],[Creación y captura Dic/2025]:[Compartición e Interoperabilidad Dic/2025]])),"",AVERAGE(Tabla4[[#This Row],[Creación y captura Dic/2025]:[Compartición e Interoperabilidad Dic/2025]])) -> 1 | CC13: 1 | CD13: 1 | CE13: =IF(ISERROR(AVERAGE('Calidad de Datos'!BC17:BF17)),"",AVERAGE('Calidad de Datos'!BC17:BF17)) -> 1 | CF13: =IF(ISERROR(Tabla13[[#This Row],[Uso y acceso Mar/2026]]),"",Tabla13[[#This Row],[Uso y acceso Mar/2026]]) -> 1 | CG13: =IF(ISERROR(Tabla58[[#This Row],[Integración Mar/2026]]),"",Tabla58[[#This Row],[Integración Mar/2026]]) -> 1 | CH13: =IF(ISERROR(AVERAGE(Tabla4[[#This Row],[Creación y captura Mar/2026]:[Compartición e Interoperabilidad Mar/2026]])),"",AVERAGE(Tabla4[[#This Row],[Creación y captura Mar/2026]:[Compartición e Interoperabilidad Mar/2026]])) -> 1
B14: Metas de Comercial | C14: 1 | D14: 1 | E14: =IF(ISERROR(AVERAGE('Calidad de Datos'!C18:F18)),"",AVERAGE('Calidad de Datos'!C18:F18)) -> 1 | F14: =IF(Tabla13[[#This Row],[Uso y acceso Ago/2024]]="","",Tabla13[[#This Row],[Uso y acceso Ago/2024]]) -> 1 | G14: =IF(Tabla58[[#This Row],[Integración Ago/2024]]="","",Tabla58[[#This Row],[Integración Ago/2024]]) -> 1 | H14: =IF(ISERROR(AVERAGE(Tabla4[[#This Row],[Creación y captura Ago/2024]:[Compartición e Interoperabilidad Ago/2024]])),"",AVERAGE(Tabla4[[#This Row],[Creación y captura Ago/2024]:[Compartición e Interoperabilidad Ago/2024]])) -> 1 | I14: 1 | J14: 1 | K14: =IF(ISERROR(AVERAGE('Calidad de Datos'!G18:J18)),"",AVERAGE('Calidad de Datos'!G18:J18)) -> 1 | L14: =IF(Tabla13[[#This Row],[Uso y acceso Sep/2024]]="","",Tabla13[[#This Row],[Uso y acceso Sep/2024]]) -> 1 | M14: =IF(Tabla58[[#This Row],[Integración Sep/2024]]="","",Tabla58[[#This Row],[Integración Sep/2024]]) -> 1 | N14: =IF(ISERROR(AVERAGE(Tabla4[[#This Row],[Creación y captura Sep/2024]:[Compartición e Interoperabilidad Sep/2024]])),"",AVERAGE(Tabla4[[#This Row],[Creación y captura Sep/2024]:[Compartición e Interoperabilidad Sep/2024]])) -> 1 | O14: 1 | P14: 1 | Q14: =IF(ISERROR(AVERAGE('Calidad de Datos'!K18:N18)),"",AVERAGE('Calidad de Datos'!K18:N18)) -> 1 | R14: =IF(Tabla13[[#This Row],[Uso y acceso Oct/2024]]="","",Tabla13[[#This Row],[Uso y acceso Oct/2024]]) -> 1 | S14: =IF(Tabla58[[#This Row],[Integración Oct/2024]]="","",Tabla58[[#This Row],[Integración Oct/2024]]) -> 1 | T14: =IF(ISERROR(AVERAGE(Tabla4[[#This Row],[Creación y captura Oct/2024]:[Compartición e Interoperabilidad Oct/2024]])),"",AVERAGE(Tabla4[[#This Row],[Creación y captura Oct/2024]:[Compartición e Interoperabilidad Oct/2024]])) -> 1 | U14: 1 | V14: 1 | W14: =IF(ISERROR(AVERAGE('Calidad de Datos'!O18:R18)),"",AVERAGE('Calidad de Datos'!O18:R18)) -> 1 | X14: =IF(Tabla13[[#This Row],[Uso y acceso Nov/2024]]="","",Tabla13[[#This Row],[Uso y acceso Nov/2024]]) -> 1 | Y14: =IF(Tabla58[[#This Row],[Integración Nov/2024]]="","",Tabla58[[#This Row],[Integración Nov/2024]]) -> 1 | Z14: =IF(ISERROR(AVERAGE(Tabla4[[#This Row],[Creación y captura Nov/2024]:[Compartición e Interoperabilidad Nov/2024]])),"",AVERAGE(Tabla4[[#This Row],[Creación y captura Nov/2024]:[Compartición e Interoperabilidad Nov/2024]])) -> 1 | AA14: 1 | AB14: 1 | AC14: =IF(ISERROR(AVERAGE('Calidad de Datos'!S18:V18)),"",AVERAGE('Calidad de Datos'!S18:V18)) -> 1 | AD14: =IF(Tabla13[[#This Row],[Uso y acceso Dic/2024]]="","",Tabla13[[#This Row],[Uso y acceso Dic/2024]]) -> 1 | AE14: =IF(Tabla58[[#This Row],[Integración Dic/2024]]="","",Tabla58[[#This Row],[Integración Dic/2024]]) -> 1 | AF14: =IF(ISERROR(AVERAGE(Tabla4[[#This Row],[Creación y captura Dic/2024]:[Compartición e Interoperabilidad Dic/2024]])),"",AVERAGE(Tabla4[[#This Row],[Creación y captura Dic/2024]:[Compartición e Interoperabilidad Dic/2024]])) -> 1 | AG14: 1 | AH14: 1 | AI14: =IF(ISERROR(AVERAGE('Calidad de Datos'!W18:Z18)),"",AVERAGE('Calidad de Datos'!W18:Z18)) -> 1 | AJ14: =IF(Tabla13[[#This Row],[Uso y acceso Ene/2025]]="","",Tabla13[[#This Row],[Uso y acceso Ene/2025]]) -> 1 | AK14: =IF(Tabla58[[#This Row],[Integración Ene/2025]]="","",Tabla58[[#This Row],[Integración Ene/2025]]) -> 1 | AL14: =IF(ISERROR(AVERAGE(Tabla4[[#This Row],[Creación y captura Ene/2025]:[Compartición e Interoperabilidad Ene/2025]])),"",AVERAGE(Tabla4[[#This Row],[Creación y captura Ene/2025]:[Compartición e Interoperabilidad Ene/2025]])) -> 1 | AM14: 1 | AN14: 1 | AO14: =IF(ISERROR(AVERAGE('Calidad de Datos'!AA18:AD18)),"",AVERAGE('Calidad de Datos'!AA18:AD18)) -> 1 | AP14: =IF(Tabla13[[#This Row],[Uso y acceso Feb/2025]]="","",Tabla13[[#This Row],[Uso y acceso Feb/2025]]) -> 1 | AQ14: =IF(Tabla58[[#This Row],[Integración Feb/2025]]="","",Tabla58[[#This Row],[Integración Feb/2025]]) -> 1 | AR14: =IF(ISERROR(AVERAGE(Tabla4[[#This Row],[Creación y captura Feb/2025]:[Compartición e Interoperabilidad Feb/2025]])),"",AVERAGE(Tabla4[[#This Row],[Creación y captura Feb/2025]:[Compartición e Interoperabilidad Feb/2025]])) -> 1 | AS14: 1 | AT14: 1 | AU14: =IF(ISERROR(AVERAGE('Calidad de Datos'!AE18:AH18)),"",AVERAGE('Calidad de Datos'!AE18:AH18)) -> 1 | AV14: =IF(Tabla13[[#This Row],[Uso y acceso Mar/2025]]="","",Tabla13[[#This Row],[Uso y acceso Mar/2025]]) -> 1 | AW14: =IF(Tabla58[[#This Row],[Integración Mar/2025]]="","",Tabla58[[#This Row],[Integración Mar/2025]]) -> 1 | AX14: =IF(ISERROR(AVERAGE(Tabla4[[#This Row],[Creación y captura Mar/2025]:[Compartición e Interoperabilidad Mar/2025]])),"",AVERAGE(Tabla4[[#This Row],[Creación y captura Mar/2025]:[Compartición e Interoperabilidad Mar/2025]])) -> 1 | AY14: 1 | AZ14: 1 | BA14: =IF(ISERROR(AVERAGE('Calidad de Datos'!AI18:AL18)),"",AVERAGE('Calidad de Datos'!AI18:AL18)) -> 1 | BB14: =IF(Tabla13[[#This Row],[Uso y acceso Abr/2025]]="","",Tabla13[[#This Row],[Uso y acceso Abr/2025]]) -> 1 | BC14: =IF(Tabla58[[#This Row],[Integración Abr/2025]]="","",Tabla58[[#This Row],[Integración Abr/2025]]) -> 1 | BD14: =IF(ISERROR(AVERAGE(Tabla4[[#This Row],[Creación y captura Abr/2025]:[Compartición e Interoperabilidad Abr/2025]])),"",AVERAGE(Tabla4[[#This Row],[Creación y captura Abr/2025]:[Compartición e Interoperabilidad Abr/2025]])) -> 1 | BE14: 1 | BF14: 1 | BG14: =IF(ISERROR(AVERAGE('Calidad de Datos'!AM18:AP18)),"",AVERAGE('Calidad de Datos'!AM18:AP18)) -> 1 | BH14: =IF(Tabla13[[#This Row],[Uso y acceso May/2025]]="","",Tabla13[[#This Row],[Uso y acceso May/2025]]) -> 1 | BI14: =IF(Tabla58[[#This Row],[Integración May/2025]]="","",Tabla58[[#This Row],[Integración May/2025]]) -> 1 | BJ14: =IF(ISERROR(AVERAGE(Tabla4[[#This Row],[Creación y captura May/2025]:[Compartición e Interoperabilidad May/2025]])),"",AVERAGE(Tabla4[[#This Row],[Creación y captura May/2025]:[Compartición e Interoperabilidad May/2025]])) -> 1 | BK14: 1 | BL14: 1 | BM14: =IF(ISERROR(AVERAGE('Calidad de Datos'!AQ18:AT18)),"",AVERAGE('Calidad de Datos'!AQ18:AT18)) -> 1 | BN14: =IF(Tabla13[[#This Row],[Uso y acceso Jun/2025]]="","",Tabla13[[#This Row],[Uso y acceso Jun/2025]]) -> 1 | BO14: =IF(Tabla58[[#This Row],[Integración Jun/2025]]="","",Tabla58[[#This Row],[Integración Jun/2025]]) -> 1 | BP14: =IF(ISERROR(AVERAGE(Tabla4[[#This Row],[Creación y captura Jun/2025]:[Compartición e Interoperabilidad Jun/2025]])),"",AVERAGE(Tabla4[[#This Row],[Creación y captura Jun/2025]:[Compartición e Interoperabilidad Jun/2025]])) -> 1 | BQ14: 1 | BR14: 1 | BS14: =IF(ISERROR(AVERAGE('Calidad de Datos'!AU18:AX18)),"",AVERAGE('Calidad de Datos'!AU18:AX18)) -> 1 | BT14: =IF(Tabla13[[#This Row],[Uso y acceso Sep/2025]]="","",Tabla13[[#This Row],[Uso y acceso Sep/2025]]) -> 1 | BU14: =IF(Tabla58[[#This Row],[Integración Sep/2025]]="","",Tabla58[[#This Row],[Integración Sep/2025]]) -> 1 | BV14: =IF(ISERROR(AVERAGE(Tabla4[[#This Row],[Creación y captura Sep/2025]:[Compartición e Interoperabilidad Sep/2025]])),"",AVERAGE(Tabla4[[#This Row],[Creación y captura Sep/2025]:[Compartición e Interoperabilidad Sep/2025]])) -> 1 | BW14: 1 | BX14: 1 | BY14: =IF(ISERROR(AVERAGE('Calidad de Datos'!AY18:BB18)),"",AVERAGE('Calidad de Datos'!AY18:BB18)) -> 1 | BZ14: =IF(ISERROR(Tabla13[[#This Row],[Uso y acceso Dic/2025]]),"",Tabla13[[#This Row],[Uso y acceso Dic/2025]]) -> 1 | CA14: =IF(ISERROR(Tabla58[[#This Row],[Integración Dic/2025]]),"",Tabla58[[#This Row],[Integración Dic/2025]]) -> 1 | CB14: =IF(ISERROR(AVERAGE(Tabla4[[#This Row],[Creación y captura Dic/2025]:[Compartición e Interoperabilidad Dic/2025]])),"",AVERAGE(Tabla4[[#This Row],[Creación y captura Dic/2025]:[Compartición e Interoperabilidad Dic/2025]])) -> 1 | CC14: 1 | CD14: 1 | CE14: =IF(ISERROR(AVERAGE('Calidad de Datos'!BC18:BF18)),"",AVERAGE('Calidad de Datos'!BC18:BF18)) -> 1 | CF14: =IF(ISERROR(Tabla13[[#This Row],[Uso y acceso Mar/2026]]),"",Tabla13[[#This Row],[Uso y acceso Mar/2026]]) -> 1 | CG14: =IF(ISERROR(Tabla58[[#This Row],[Integración Mar/2026]]),"",Tabla58[[#This Row],[Integración Mar/2026]]) -> 1 | CH14: =IF(ISERROR(AVERAGE(Tabla4[[#This Row],[Creación y captura Mar/2026]:[Compartición e Interoperabilidad Mar/2026]])),"",AVERAGE(Tabla4[[#This Row],[Creación y captura Mar/2026]:[Compartición e Interoperabilidad Mar/2026]])) -> 1
B15: Área | C15: 1 | D15: 1 | E15: =IF(ISERROR(AVERAGE('Calidad de Datos'!C19:F19)),"",AVERAGE('Calidad de Datos'!C19:F19)) -> 1 | F15: =IF(Tabla13[[#This Row],[Uso y acceso Ago/2024]]="","",Tabla13[[#This Row],[Uso y acceso Ago/2024]]) -> 1 | G15: =IF(Tabla58[[#This Row],[Integración Ago/2024]]="","",Tabla58[[#This Row],[Integración Ago/2024]]) -> 1 | H15: =IF(ISERROR(AVERAGE(Tabla4[[#This Row],[Creación y captura Ago/2024]:[Compartición e Interoperabilidad Ago/2024]])),"",AVERAGE(Tabla4[[#This Row],[Creación y captura Ago/2024]:[Compartición e Interoperabilidad Ago/2024]])) -> 1 | I15: 1 | J15: 1 | K15: =IF(ISERROR(AVERAGE('Calidad de Datos'!G19:J19)),"",AVERAGE('Calidad de Datos'!G19:J19)) -> 1 | L15: =IF(Tabla13[[#This Row],[Uso y acceso Sep/2024]]="","",Tabla13[[#This Row],[Uso y acceso Sep/2024]]) -> 1 | M15: =IF(Tabla58[[#This Row],[Integración Sep/2024]]="","",Tabla58[[#This Row],[Integración Sep/2024]]) -> 1 | N15: =IF(ISERROR(AVERAGE(Tabla4[[#This Row],[Creación y captura Sep/2024]:[Compartición e Interoperabilidad Sep/2024]])),"",AVERAGE(Tabla4[[#This Row],[Creación y captura Sep/2024]:[Compartición e Interoperabilidad Sep/2024]])) -> 1 | O15: 1 | P15: 1 | Q15: =IF(ISERROR(AVERAGE('Calidad de Datos'!K19:N19)),"",AVERAGE('Calidad de Datos'!K19:N19)) -> 1 | R15: =IF(Tabla13[[#This Row],[Uso y acceso Oct/2024]]="","",Tabla13[[#This Row],[Uso y acceso Oct/2024]]) -> 1 | S15: =IF(Tabla58[[#This Row],[Integración Oct/2024]]="","",Tabla58[[#This Row],[Integración Oct/2024]]) -> 1 | T15: =IF(ISERROR(AVERAGE(Tabla4[[#This Row],[Creación y captura Oct/2024]:[Compartición e Interoperabilidad Oct/2024]])),"",AVERAGE(Tabla4[[#This Row],[Creación y captura Oct/2024]:[Compartición e Interoperabilidad Oct/2024]])) -> 1 | U15: 1 | V15: 1 | W15: =IF(ISERROR(AVERAGE('Calidad de Datos'!O19:R19)),"",AVERAGE('Calidad de Datos'!O19:R19)) -> 1 | X15: =IF(Tabla13[[#This Row],[Uso y acceso Nov/2024]]="","",Tabla13[[#This Row],[Uso y acceso Nov/2024]]) -> 1 | Y15: =IF(Tabla58[[#This Row],[Integración Nov/2024]]="","",Tabla58[[#This Row],[Integración Nov/2024]]) -> 1 | Z15: =IF(ISERROR(AVERAGE(Tabla4[[#This Row],[Creación y captura Nov/2024]:[Compartición e Interoperabilidad Nov/2024]])),"",AVERAGE(Tabla4[[#This Row],[Creación y captura Nov/2024]:[Compartición e Interoperabilidad Nov/2024]])) -> 1 | AA15: 1 | AB15: 1 | AC15: =IF(ISERROR(AVERAGE('Calidad de Datos'!S19:V19)),"",AVERAGE('Calidad de Datos'!S19:V19)) -> 1 | AD15: =IF(Tabla13[[#This Row],[Uso y acceso Dic/2024]]="","",Tabla13[[#This Row],[Uso y acceso Dic/2024]]) -> 1 | AE15: =IF(Tabla58[[#This Row],[Integración Dic/2024]]="","",Tabla58[[#This Row],[Integración Dic/2024]]) -> 1 | AF15: =IF(ISERROR(AVERAGE(Tabla4[[#This Row],[Creación y captura Dic/2024]:[Compartición e Interoperabilidad Dic/2024]])),"",AVERAGE(Tabla4[[#This Row],[Creación y captura Dic/2024]:[Compartición e Interoperabilidad Dic/2024]])) -> 1 | AG15: 1 | AH15: 1 | AI15: =IF(ISERROR(AVERAGE('Calidad de Datos'!W19:Z19)),"",AVERAGE('Calidad de Datos'!W19:Z19)) -> 1 | AJ15: =IF(Tabla13[[#This Row],[Uso y acceso Ene/2025]]="","",Tabla13[[#This Row],[Uso y acceso Ene/2025]]) -> 1 | AK15: =IF(Tabla58[[#This Row],[Integración Ene/2025]]="","",Tabla58[[#This Row],[Integración Ene/2025]]) -> 1 | AL15: =IF(ISERROR(AVERAGE(Tabla4[[#This Row],[Creación y captura Ene/2025]:[Compartición e Interoperabilidad Ene/2025]])),"",AVERAGE(Tabla4[[#This Row],[Creación y captura Ene/2025]:[Compartición e Interoperabilidad Ene/2025]])) -> 1 | AM15: 1 | AN15: 1 | AO15: =IF(ISERROR(AVERAGE('Calidad de Datos'!AA19:AD19)),"",AVERAGE('Calidad de Datos'!AA19:AD19)) -> 1 | AP15: =IF(Tabla13[[#This Row],[Uso y acceso Feb/2025]]="","",Tabla13[[#This Row],[Uso y acceso Feb/2025]]) -> 1 | AQ15: =IF(Tabla58[[#This Row],[Integración Feb/2025]]="","",Tabla58[[#This Row],[Integración Feb/2025]]) -> 1 | AR15: =IF(ISERROR(AVERAGE(Tabla4[[#This Row],[Creación y captura Feb/2025]:[Compartición e Interoperabilidad Feb/2025]])),"",AVERAGE(Tabla4[[#This Row],[Creación y captura Feb/2025]:[Compartición e Interoperabilidad Feb/2025]])) -> 1 | AS15: 1 | AT15: 1 | AU15: =IF(ISERROR(AVERAGE('Calidad de Datos'!AE19:AH19)),"",AVERAGE('Calidad de Datos'!AE19:AH19)) -> 1 | AV15: =IF(Tabla13[[#This Row],[Uso y acceso Mar/2025]]="","",Tabla13[[#This Row],[Uso y acceso Mar/2025]]) -> 1 | AW15: =IF(Tabla58[[#This Row],[Integración Mar/2025]]="","",Tabla58[[#This Row],[Integración Mar/2025]]) -> 1 | AX15: =IF(ISERROR(AVERAGE(Tabla4[[#This Row],[Creación y captura Mar/2025]:[Compartición e Interoperabilidad Mar/2025]])),"",AVERAGE(Tabla4[[#This Row],[Creación y captura Mar/2025]:[Compartición e Interoperabilidad Mar/2025]])) -> 1 | AY15: 1 | AZ15: 1 | BA15: =IF(ISERROR(AVERAGE('Calidad de Datos'!AI19:AL19)),"",AVERAGE('Calidad de Datos'!AI19:AL19)) -> 1 | BB15: =IF(Tabla13[[#This Row],[Uso y acceso Abr/2025]]="","",Tabla13[[#This Row],[Uso y acceso Abr/2025]]) -> 1 | BC15: =IF(Tabla58[[#This Row],[Integración Abr/2025]]="","",Tabla58[[#This Row],[Integración Abr/2025]]) -> 1 | BD15: =IF(ISERROR(AVERAGE(Tabla4[[#This Row],[Creación y captura Abr/2025]:[Compartición e Interoperabilidad Abr/2025]])),"",AVERAGE(Tabla4[[#This Row],[Creación y captura Abr/2025]:[Compartición e Interoperabilidad Abr/2025]])) -> 1 | BE15: 1 | BF15: 1 | BG15: =IF(ISERROR(AVERAGE('Calidad de Datos'!AM19:AP19)),"",AVERAGE('Calidad de Datos'!AM19:AP19)) -> 1 | BH15: =IF(Tabla13[[#This Row],[Uso y acceso May/2025]]="","",Tabla13[[#This Row],[Uso y acceso May/2025]]) -> 1 | BI15: =IF(Tabla58[[#This Row],[Integración May/2025]]="","",Tabla58[[#This Row],[Integración May/2025]]) -> 1 | BJ15: =IF(ISERROR(AVERAGE(Tabla4[[#This Row],[Creación y captura May/2025]:[Compartición e Interoperabilidad May/2025]])),"",AVERAGE(Tabla4[[#This Row],[Creación y captura May/2025]:[Compartición e Interoperabilidad May/2025]])) -> 1 | BK15: 1 | BL15: 1 | BM15: =IF(ISERROR(AVERAGE('Calidad de Datos'!AQ19:AT19)),"",AVERAGE('Calidad de Datos'!AQ19:AT19)) -> 1 | BN15: =IF(Tabla13[[#This Row],[Uso y acceso Jun/2025]]="","",Tabla13[[#This Row],[Uso y acceso Jun/2025]]) -> 1 | BO15: =IF(Tabla58[[#This Row],[Integración Jun/2025]]="","",Tabla58[[#This Row],[Integración Jun/2025]]) -> 1 | BP15: =IF(ISERROR(AVERAGE(Tabla4[[#This Row],[Creación y captura Jun/2025]:[Compartición e Interoperabilidad Jun/2025]])),"",AVERAGE(Tabla4[[#This Row],[Creación y captura Jun/2025]:[Compartición e Interoperabilidad Jun/2025]])) -> 1 | BQ15: 1 | BR15: 1 | BS15: =IF(ISERROR(AVERAGE('Calidad de Datos'!AU19:AX19)),"",AVERAGE('Calidad de Datos'!AU19:AX19)) -> 1 | BT15: =IF(Tabla13[[#This Row],[Uso y acceso Sep/2025]]="","",Tabla13[[#This Row],[Uso y acceso Sep/2025]]) -> 1 | BU15: =IF(Tabla58[[#This Row],[Integración Sep/2025]]="","",Tabla58[[#This Row],[Integración Sep/2025]]) -> 1 | BV15: =IF(ISERROR(AVERAGE(Tabla4[[#This Row],[Creación y captura Sep/2025]:[Compartición e Interoperabilidad Sep/2025]])),"",AVERAGE(Tabla4[[#This Row],[Creación y captura Sep/2025]:[Compartición e Interoperabilidad Sep/2025]])) -> 1 | BW15: 1 | BX15: 1 | BY15: =IF(ISERROR(AVERAGE('Calidad de Datos'!AY19:BB19)),"",AVERAGE('Calidad de Datos'!AY19:BB19)) -> 1 | BZ15: =IF(ISERROR(Tabla13[[#This Row],[Uso y acceso Dic/2025]]),"",Tabla13[[#This Row],[Uso y acceso Dic/2025]]) -> 1 | CA15: =IF(ISERROR(Tabla58[[#This Row],[Integración Dic/2025]]),"",Tabla58[[#This Row],[Integración Dic/2025]]) -> 1 | CB15: =IF(ISERROR(AVERAGE(Tabla4[[#This Row],[Creación y captura Dic/2025]:[Compartición e Interoperabilidad Dic/2025]])),"",AVERAGE(Tabla4[[#This Row],[Creación y captura Dic/2025]:[Compartición e Interoperabilidad Dic/2025]])) -> 1 | CC15: 1 | CD15: 1 | CE15: =IF(ISERROR(AVERAGE('Calidad de Datos'!BC19:BF19)),"",AVERAGE('Calidad de Datos'!BC19:BF19)) -> 1 | CF15: =IF(ISERROR(Tabla13[[#This Row],[Uso y acceso Mar/2026]]),"",Tabla13[[#This Row],[Uso y acceso Mar/2026]]) -> 1 | CG15: =IF(ISERROR(Tabla58[[#This Row],[Integración Mar/2026]]),"",Tabla58[[#This Row],[Integración Mar/2026]]) -> 1 | CH15: =IF(ISERROR(AVERAGE(Tabla4[[#This Row],[Creación y captura Mar/2026]:[Compartición e Interoperabilidad Mar/2026]])),"",AVERAGE(Tabla4[[#This Row],[Creación y captura Mar/2026]:[Compartición e Interoperabilidad Mar/2026]])) -> 1
... B36: Semáforo alerta de proyectos | C36: 1 | D36: 1 | E36: =IF(ISERROR(AVERAGE('Calidad de Datos'!C40:F40)),"",AVERAGE('Calidad de Datos'!C40:F40)) -> 0.8875 | F36: =IF(Tabla13[[#This Row],[Uso y acceso Ago/2024]]="","",Tabla13[[#This Row],[Uso y acceso Ago/2024]]) -> 1 | G36: =IF(Tabla58[[#This Row],[Integración Ago/2024]]="","",Tabla58[[#This Row],[Integración Ago/2024]]) -> 1 | H36: =IF(ISERROR(AVERAGE(Tabla4[[#This Row],[Creación y captura Ago/2024]:[Compartición e Interoperabilidad Ago/2024]])),"",AVERAGE(Tabla4[[#This Row],[Creación y captura Ago/2024]:[Compartición e Interoperabilidad Ago/2024]])) -> 0.9775 | I36: 1 | J36: 1 | K36: =IF(ISERROR(AVERAGE('Calidad de Datos'!G40:J40)),"",AVERAGE('Calidad de Datos'!G40:J40)) -> 0.9125 | L36: =IF(Tabla13[[#This Row],[Uso y acceso Sep/2024]]="","",Tabla13[[#This Row],[Uso y acceso Sep/2024]]) -> 1 | M36: =IF(Tabla58[[#This Row],[Integración Sep/2024]]="","",Tabla58[[#This Row],[Integración Sep/2024]]) -> 1 | N36: =IF(ISERROR(AVERAGE(Tabla4[[#This Row],[Creación y captura Sep/2024]:[Compartición e Interoperabilidad Sep/2024]])),"",AVERAGE(Tabla4[[#This Row],[Creación y captura Sep/2024]:[Compartición e Interoperabilidad Sep/2024]])) -> 0.9825 | O36: 1 | P36: 1 | Q36: =IF(ISERROR(AVERAGE('Calidad de Datos'!K40:N40)),"",AVERAGE('Calidad de Datos'!K40:N40)) -> 0.9125 | R36: =IF(Tabla13[[#This Row],[Uso y acceso Oct/2024]]="","",Tabla13[[#This Row],[Uso y acceso Oct/2024]]) -> 1 | S36: =IF(Tabla58[[#This Row],[Integración Oct/2024]]="","",Tabla58[[#This Row],[Integración Oct/2024]]) -> 1 | T36: =IF(ISERROR(AVERAGE(Tabla4[[#This Row],[Creación y captura Oct/2024]:[Compartición e Interoperabilidad Oct/2024]])),"",AVERAGE(Tabla4[[#This Row],[Creación y captura Oct/2024]:[Compartición e Interoperabilidad Oct/2024]])) -> 0.9825 | U36: 1 | V36: 1 | W36: =IF(ISERROR(AVERAGE('Calidad de Datos'!O40:R40)),"",AVERAGE('Calidad de Datos'!O40:R40)) -> 1 | X36: =IF(Tabla13[[#This Row],[Uso y acceso Nov/2024]]="","",Tabla13[[#This Row],[Uso y acceso Nov/2024]]) -> 1 | Y36: =IF(Tabla58[[#This Row],[Integración Nov/2024]]="","",Tabla58[[#This Row],[Integración Nov/2024]]) -> 1 | Z36: =IF(ISERROR(AVERAGE(Tabla4[[#This Row],[Creación y captura Nov/2024]:[Compartición e Interoperabilidad Nov/2024]])),"",AVERAGE(Tabla4[[#This Row],[Creación y captura Nov/2024]:[Compartición e Interoperabilidad Nov/2024]])) -> 1 | AA36: 1 | AB36: 1 | AC36: =IF(ISERROR(AVERAGE('Calidad de Datos'!S40:V40)),"",AVERAGE('Calidad de Datos'!S40:V40)) -> 1 | AD36: =IF(Tabla13[[#This Row],[Uso y acceso Dic/2024]]="","",Tabla13[[#This Row],[Uso y acceso Dic/2024]]) -> 1 | AE36: =IF(Tabla58[[#This Row],[Integración Dic/2024]]="","",Tabla58[[#This Row],[Integración Dic/2024]]) -> 1 | AF36: =IF(ISERROR(AVERAGE(Tabla4[[#This Row],[Creación y captura Dic/2024]:[Compartición e Interoperabilidad Dic/2024]])),"",AVERAGE(Tabla4[[#This Row],[Creación y captura Dic/2024]:[Compartición e Interoperabilidad Dic/2024]])) -> 1 | AG36: 1 | AH36: 1 | AI36: =IF(ISERROR(AVERAGE('Calidad de Datos'!W40:Z40)),"",AVERAGE('Calidad de Datos'!W40:Z40)) -> 1 | AJ36: =IF(Tabla13[[#This Row],[Uso y acceso Ene/2025]]="","",Tabla13[[#This Row],[Uso y acceso Ene/2025]]) -> 1 | AK36: =IF(Tabla58[[#This Row],[Integración Ene/2025]]="","",Tabla58[[#This Row],[Integración Ene/2025]]) -> 1 | AL36: =IF(ISERROR(AVERAGE(Tabla4[[#This Row],[Creación y captura Ene/2025]:[Compartición e Interoperabilidad Ene/2025]])),"",AVERAGE(Tabla4[[#This Row],[Creación y captura Ene/2025]:[Compartición e Interoperabilidad Ene/2025]])) -> 1 | AM36: 1 | AN36: 1 | AO36: =IF(ISERROR(AVERAGE('Calidad de Datos'!AA40:AD40)),"",AVERAGE('Calidad de Datos'!AA40:AD40)) -> 1 | AP36: =IF(Tabla13[[#This Row],[Uso y acceso Feb/2025]]="","",Tabla13[[#This Row],[Uso y acceso Feb/2025]]) -> 1 | AQ36: =IF(Tabla58[[#This Row],[Integración Feb/2025]]="","",Tabla58[[#This Row],[Integración Feb/2025]]) -> 1 | AR36: =IF(ISERROR(AVERAGE(Tabla4[[#This Row],[Creación y captura Feb/2025]:[Compartición e Interoperabilidad Feb/2025]])),"",AVERAGE(Tabla4[[#This Row],[Creación y captura Feb/2025]:[Compartición e Interoperabilidad Feb/2025]])) -> 1 | AS36: 1 | AT36: 1 | AU36: =IF(ISERROR(AVERAGE('Calidad de Datos'!AE40:AH40)),"",AVERAGE('Calidad de Datos'!AE40:AH40)) -> 1 | AV36: =IF(Tabla13[[#This Row],[Uso y acceso Mar/2025]]="","",Tabla13[[#This Row],[Uso y acceso Mar/2025]]) -> 1 | AW36: =IF(Tabla58[[#This Row],[Integración Mar/2025]]="","",Tabla58[[#This Row],[Integración Mar/2025]]) -> 1 | AX36: =IF(ISERROR(AVERAGE(Tabla4[[#This Row],[Creación y captura Mar/2025]:[Compartición e Interoperabilidad Mar/2025]])),"",AVERAGE(Tabla4[[#This Row],[Creación y captura Mar/2025]:[Compartición e Interoperabilidad Mar/2025]])) -> 1 | AY36: 1 | AZ36: 1 | BA36: =IF(ISERROR(AVERAGE('Calidad de Datos'!AI40:AL40)),"",AVERAGE('Calidad de Datos'!AI40:AL40)) -> 1 | BB36: =IF(Tabla13[[#This Row],[Uso y acceso Abr/2025]]="","",Tabla13[[#This Row],[Uso y acceso Abr/2025]]) -> 1 | BC36: =IF(Tabla58[[#This Row],[Integración Abr/2025]]="","",Tabla58[[#This Row],[Integración Abr/2025]]) -> 1 | BD36: =IF(ISERROR(AVERAGE(Tabla4[[#This Row],[Creación y captura Abr/2025]:[Compartición e Interoperabilidad Abr/2025]])),"",AVERAGE(Tabla4[[#This Row],[Creación y captura Abr/2025]:[Compartición e Interoperabilidad Abr/2025]])) -> 1 | BE36: 1 | BF36: 1 | BG36: =IF(ISERROR(AVERAGE('Calidad de Datos'!AM40:AP40)),"",AVERAGE('Calidad de Datos'!AM40:AP40)) -> 1 | BH36: =IF(Tabla13[[#This Row],[Uso y acceso May/2025]]="","",Tabla13[[#This Row],[Uso y acceso May/2025]]) -> 1 | BI36: =IF(Tabla58[[#This Row],[Integración May/2025]]="","",Tabla58[[#This Row],[Integración May/2025]]) -> 1 | BJ36: =IF(ISERROR(AVERAGE(Tabla4[[#This Row],[Creación y captura May/2025]:[Compartición e Interoperabilidad May/2025]])),"",AVERAGE(Tabla4[[#This Row],[Creación y captura May/2025]:[Compartición e Interoperabilidad May/2025]])) -> 1 | BK36: 1 | BL36: 1 | BM36: =IF(ISERROR(AVERAGE('Calidad de Datos'!AQ40:AT40)),"",AVERAGE('Calidad de Datos'!AQ40:AT40)) -> 1 | BN36: =IF(Tabla13[[#This Row],[Uso y acceso Jun/2025]]="","",Tabla13[[#This Row],[Uso y acceso Jun/2025]]) -> 1 | BO36: =IF(Tabla58[[#This Row],[Integración Jun/2025]]="","",Tabla58[[#This Row],[Integración Jun/2025]]) -> 1 | BP36: =IF(ISERROR(AVERAGE(Tabla4[[#This Row],[Creación y captura Jun/2025]:[Compartición e Interoperabilidad Jun/2025]])),"",AVERAGE(Tabla4[[#This Row],[Creación y captura Jun/2025]:[Compartición e Interoperabilidad Jun/2025]])) -> 1 | BQ36: 1 | BR36: 1 | BS36: =IF(ISERROR(AVERAGE('Calidad de Datos'!AU40:AX40)),"",AVERAGE('Calidad de Datos'!AU40:AX40)) -> 1 | BT36: =IF(Tabla13[[#This Row],[Uso y acceso Sep/2025]]="","",Tabla13[[#This Row],[Uso y acceso Sep/2025]]) -> 1 | BU36: =IF(Tabla58[[#This Row],[Integración Sep/2025]]="","",Tabla58[[#This Row],[Integración Sep/2025]]) -> 1 | BV36: =IF(ISERROR(AVERAGE(Tabla4[[#This Row],[Creación y captura Sep/2025]:[Compartición e Interoperabilidad Sep/2025]])),"",AVERAGE(Tabla4[[#This Row],[Creación y captura Sep/2025]:[Compartición e Interoperabilidad Sep/2025]])) -> 1 | BW36: 1 | BX36: 1 | BY36: =IF(ISERROR(AVERAGE('Calidad de Datos'!AY40:BB40)),"",AVERAGE('Calidad de Datos'!AY40:BB40)) -> 1 | BZ36: =IF(ISERROR(Tabla13[[#This Row],[Uso y acceso Dic/2025]]),"",Tabla13[[#This Row],[Uso y acceso Dic/2025]]) -> 1 | CA36: =IF(ISERROR(Tabla58[[#This Row],[Integración Dic/2025]]),"",Tabla58[[#This Row],[Integración Dic/2025]]) -> 1 | CB36: =IF(ISERROR(AVERAGE(Tabla4[[#This Row],[Creación y captura Dic/2025]:[Compartición e Interoperabilidad Dic/2025]])),"",AVERAGE(Tabla4[[#This Row],[Creación y captura Dic/2025]:[Compartición e Interoperabilidad Dic/2025]])) -> 1 | CC36: 1 | CD36: 1 | CE36: =IF(ISERROR(AVERAGE('Calidad de Datos'!BC40:BF40)),"",AVERAGE('Calidad de Datos'!BC40:BF40)) -> 1 | CF36: =IF(ISERROR(Tabla13[[#This Row],[Uso y acceso Mar/2026]]),"",Tabla13[[#This Row],[Uso y acceso Mar/2026]]) -> 1 | CG36: =IF(ISERROR(Tabla58[[#This Row],[Integración Mar/2026]]),"",Tabla58[[#This Row],[Integración Mar/2026]]) -> 1 | CH36: =IF(ISERROR(AVERAGE(Tabla4[[#This Row],[Creación y captura Mar/2026]:[Compartición e Interoperabilidad Mar/2026]])),"",AVERAGE(Tabla4[[#This Row],[Creación y captura Mar/2026]:[Compartición e Interoperabilidad Mar/2026]])) -> 1
B37: Nivel educativo | E37: =IF(ISERROR(AVERAGE('Calidad de Datos'!C41:F41)),"",AVERAGE('Calidad de Datos'!C41:F41)) -> 0 | F37: =IF(Tabla13[[#This Row],[Uso y acceso Ago/2024]]="","",Tabla13[[#This Row],[Uso y acceso Ago/2024]]) -> 0.3 | G37: =IF(Tabla58[[#This Row],[Integración Ago/2024]]="","",Tabla58[[#This Row],[Integración Ago/2024]]) -> 0 | H37: =IF(ISERROR(AVERAGE(Tabla4[[#This Row],[Creación y captura Ago/2024]:[Compartición e Interoperabilidad Ago/2024]])),"",AVERAGE(Tabla4[[#This Row],[Creación y captura Ago/2024]:[Compartición e Interoperabilidad Ago/2024]])) -> 0.1 | K37: =IF(ISERROR(AVERAGE('Calidad de Datos'!G41:J41)),"",AVERAGE('Calidad de Datos'!G41:J41)) -> 0 | L37: =IF(Tabla13[[#This Row],[Uso y acceso Sep/2024]]="","",Tabla13[[#This Row],[Uso y acceso Sep/2024]]) -> 0.3 | M37: =IF(Tabla58[[#This Row],[Integración Sep/2024]]="","",Tabla58[[#This Row],[Integración Sep/2024]]) -> 0 | N37: =IF(ISERROR(AVERAGE(Tabla4[[#This Row],[Creación y captura Sep/2024]:[Compartición e Interoperabilidad Sep/2024]])),"",AVERAGE(Tabla4[[#This Row],[Creación y captura Sep/2024]:[Compartición e Interoperabilidad Sep/2024]])) -> 0.1 | O37: 0.5 | P37: 0.2 | Q37: =IF(ISERROR(AVERAGE('Calidad de Datos'!K41:N41)),"",AVERAGE('Calidad de Datos'!K41:N41)) -> 0 | R37: =IF(Tabla13[[#This Row],[Uso y acceso Oct/2024]]="","",Tabla13[[#This Row],[Uso y acceso Oct/2024]]) -> 0.5 | S37: =IF(Tabla58[[#This Row],[Integración Oct/2024]]="","",Tabla58[[#This Row],[Integración Oct/2024]]) -> 0.2 | T37: =IF(ISERROR(AVERAGE(Tabla4[[#This Row],[Creación y captura Oct/2024]:[Compartición e Interoperabilidad Oct/2024]])),"",AVERAGE(Tabla4[[#This Row],[Creación y captura Oct/2024]:[Compartición e Interoperabilidad Oct/2024]])) -> 0.28 | U37: 1 | V37: 1 | W37: =IF(ISERROR(AVERAGE('Calidad de Datos'!O41:R41)),"",AVERAGE('Calidad de Datos'!O41:R41)) -> 1 | X37: =IF(Tabla13[[#This Row],[Uso y acceso Nov/2024]]="","",Tabla13[[#This Row],[Uso y acceso Nov/2024]]) -> 1 | Y37: =IF(Tabla58[[#This Row],[Integración Nov/2024]]="","",Tabla58[[#This Row],[Integración Nov/2024]]) -> 0.5 | Z37: =IF(ISERROR(AVERAGE(Tabla4[[#This Row],[Creación y captura Nov/2024]:[Compartición e Interoperabilidad Nov/2024]])),"",AVERAGE(Tabla4[[#This Row],[Creación y captura Nov/2024]:[Compartición e Interoperabilidad Nov/2024]])) -> 0.9 | AA37: 1 | AB37: 1 | AC37: =IF(ISERROR(AVERAGE('Calidad de Datos'!S41:V41)),"",AVERAGE('Calidad de Datos'!S41:V41)) -> 1 | AD37: =IF(Tabla13[[#This Row],[Uso y acceso Dic/2024]]="","",Tabla13[[#This Row],[Uso y acceso Dic/2024]]) -> 1 | AE37: =IF(Tabla58[[#This Row],[Integración Dic/2024]]="","",Tabla58[[#This Row],[Integración Dic/2024]]) -> 1 | AF37: =IF(ISERROR(AVERAGE(Tabla4[[#This Row],[Creación y captura Dic/2024]:[Compartición e Interoperabilidad Dic/2024]])),"",AVERAGE(Tabla4[[#This Row],[Creación y captura Dic/2024]:[Compartición e Interoperabilidad Dic/2024]])) -> 1 | AG37: 1 | AH37: 1 | AI37: =IF(ISERROR(AVERAGE('Calidad de Datos'!W41:Z41)),"",AVERAGE('Calidad de Datos'!W41:Z41)) -> 1 | AJ37: =IF(Tabla13[[#This Row],[Uso y acceso Ene/2025]]="","",Tabla13[[#This Row],[Uso y acceso Ene/2025]]) -> 1 | AK37: =IF(Tabla58[[#This Row],[Integración Ene/2025]]="","",Tabla58[[#This Row],[Integración Ene/2025]]) -> 1 | AL37: =IF(ISERROR(AVERAGE(Tabla4[[#This Row],[Creación y captura Ene/2025]:[Compartición e Interoperabilidad Ene/2025]])),"",AVERAGE(Tabla4[[#This Row],[Creación y captura Ene/2025]:[Compartición e Interoperabilidad Ene/2025]])) -> 1 | AM37: 1 | AN37: 1 | AO37: =IF(ISERROR(AVERAGE('Calidad de Datos'!AA41:AD41)),"",AVERAGE('Calidad de Datos'!AA41:AD41)) -> 1 | AP37: =IF(Tabla13[[#This Row],[Uso y acceso Feb/2025]]="","",Tabla13[[#This Row],[Uso y acceso Feb/2025]]) -> 1 | AQ37: =IF(Tabla58[[#This Row],[Integración Feb/2025]]="","",Tabla58[[#This Row],[Integración Feb/2025]]) -> 1 | AR37: =IF(ISERROR(AVERAGE(Tabla4[[#This Row],[Creación y captura Feb/2025]:[Compartición e Interoperabilidad Feb/2025]])),"",AVERAGE(Tabla4[[#This Row],[Creación y captura Feb/2025]:[Compartición e Interoperabilidad Feb/2025]])) -> 1 | AS37: 1 | AT37: 1 | AU37: =IF(ISERROR(AVERAGE('Calidad de Datos'!AE41:AH41)),"",AVERAGE('Calidad de Datos'!AE41:AH41)) -> 1 | AV37: =IF(Tabla13[[#This Row],[Uso y acceso Mar/2025]]="","",Tabla13[[#This Row],[Uso y acceso Mar/2025]]) -> 1 | AW37: =IF(Tabla58[[#This Row],[Integración Mar/2025]]="","",Tabla58[[#This Row],[Integración Mar/2025]]) -> 1 | AX37: =IF(ISERROR(AVERAGE(Tabla4[[#This Row],[Creación y captura Mar/2025]:[Compartición e Interoperabilidad Mar/2025]])),"",AVERAGE(Tabla4[[#This Row],[Creación y captura Mar/2025]:[Compartición e Interoperabilidad Mar/2025]])) -> 1 | AY37: 1 | AZ37: 1 | BA37: =IF(ISERROR(AVERAGE('Calidad de Datos'!AI41:AL41)),"",AVERAGE('Calidad de Datos'!AI41:AL41)) -> 1 | BB37: =IF(Tabla13[[#This Row],[Uso y acceso Abr/2025]]="","",Tabla13[[#This Row],[Uso y acceso Abr/2025]]) -> 1 | BC37: =IF(Tabla58[[#This Row],[Integración Abr/2025]]="","",Tabla58[[#This Row],[Integración Abr/2025]]) -> 1 | BD37: =IF(ISERROR(AVERAGE(Tabla4[[#This Row],[Creación y captura Abr/2025]:[Compartición e Interoperabilidad Abr/2025]])),"",AVERAGE(Tabla4[[#This Row],[Creación y captura Abr/2025]:[Compartición e Interoperabilidad Abr/2025]])) -> 1 | BE37: 1 | BF37: 1 | BG37: =IF(ISERROR(AVERAGE('Calidad de Datos'!AM41:AP41)),"",AVERAGE('Calidad de Datos'!AM41:AP41)) -> 1 | BH37: =IF(Tabla13[[#This Row],[Uso y acceso May/2025]]="","",Tabla13[[#This Row],[Uso y acceso May/2025]]) -> 1 | BI37: =IF(Tabla58[[#This Row],[Integración May/2025]]="","",Tabla58[[#This Row],[Integración May/2025]]) -> 1 | BJ37: =IF(ISERROR(AVERAGE(Tabla4[[#This Row],[Creación y captura May/2025]:[Compartición e Interoperabilidad May/2025]])),"",AVERAGE(Tabla4[[#This Row],[Creación y captura May/2025]:[Compartición e Interoperabilidad May/2025]])) -> 1 | BK37: 1 | BL37: 1 | BM37: =IF(ISERROR(AVERAGE('Calidad de Datos'!AQ41:AT41)),"",AVERAGE('Calidad de Datos'!AQ41:AT41)) -> 1 | BN37: =IF(Tabla13[[#This Row],[Uso y acceso Jun/2025]]="","",Tabla13[[#This Row],[Uso y acceso Jun/2025]]) -> 1 | BO37: =IF(Tabla58[[#This Row],[Integración Jun/2025]]="","",Tabla58[[#This Row],[Integración Jun/2025]]) -> 1 | BP37: =IF(ISERROR(AVERAGE(Tabla4[[#This Row],[Creación y captura Jun/2025]:[Compartición e Interoperabilidad Jun/2025]])),"",AVERAGE(Tabla4[[#This Row],[Creación y captura Jun/2025]:[Compartición e Interoperabilidad Jun/2025]])) -> 1 | BQ37: 1 | BR37: 1 | BS37: =IF(ISERROR(AVERAGE('Calidad de Datos'!AU41:AX41)),"",AVERAGE('Calidad de Datos'!AU41:AX41)) -> 1 | BT37: =IF(Tabla13[[#This Row],[Uso y acceso Sep/2025]]="","",Tabla13[[#This Row],[Uso y acceso Sep/2025]]) -> 1 | BU37: =IF(Tabla58[[#This Row],[Integración Sep/2025]]="","",Tabla58[[#This Row],[Integración Sep/2025]]) -> 1 | BV37: =IF(ISERROR(AVERAGE(Tabla4[[#This Row],[Creación y captura Sep/2025]:[Compartición e Interoperabilidad Sep/2025]])),"",AVERAGE(Tabla4[[#This Row],[Creación y captura Sep/2025]:[Compartición e Interoperabilidad Sep/2025]])) -> 1 | BW37: 1 | BX37: 1 | BY37: =IF(ISERROR(AVERAGE('Calidad de Datos'!AY41:BB41)),"",AVERAGE('Calidad de Datos'!AY41:BB41)) -> 1 | BZ37: =IF(ISERROR(Tabla13[[#This Row],[Uso y acceso Dic/2025]]),"",Tabla13[[#This Row],[Uso y acceso Dic/2025]]) -> 1 | CA37: =IF(ISERROR(Tabla58[[#This Row],[Integración Dic/2025]]),"",Tabla58[[#This Row],[Integración Dic/2025]]) -> 1 | CB37: =IF(ISERROR(AVERAGE(Tabla4[[#This Row],[Creación y captura Dic/2025]:[Compartición e Interoperabilidad Dic/2025]])),"",AVERAGE(Tabla4[[#This Row],[Creación y captura Dic/2025]:[Compartición e Interoperabilidad Dic/2025]])) -> 1 | CC37: 1 | CD37: 1 | CE37: =IF(ISERROR(AVERAGE('Calidad de Datos'!BC41:BF41)),"",AVERAGE('Calidad de Datos'!BC41:BF41)) -> 1 | CF37: =IF(ISERROR(Tabla13[[#This Row],[Uso y acceso Mar/2026]]),"",Tabla13[[#This Row],[Uso y acceso Mar/2026]]) -> 1 | CG37: =IF(ISERROR(Tabla58[[#This Row],[Integración Mar/2026]]),"",Tabla58[[#This Row],[Integración Mar/2026]]) -> 1 | CH37: =IF(ISERROR(AVERAGE(Tabla4[[#This Row],[Creación y captura Mar/2026]:[Compartición e Interoperabilidad Mar/2026]])),"",AVERAGE(Tabla4[[#This Row],[Creación y captura Mar/2026]:[Compartición e Interoperabilidad Mar/2026]])) -> 1
B38: Tipo de contrato laboral | E38: =IF(ISERROR(AVERAGE('Calidad de Datos'!C42:F42)),"",AVERAGE('Calidad de Datos'!C42:F42)) -> 0 | F38: =IF(Tabla13[[#This Row],[Uso y acceso Ago/2024]]="","",Tabla13[[#This Row],[Uso y acceso Ago/2024]]) -> 0.3 | G38: =IF(Tabla58[[#This Row],[Integración Ago/2024]]="","",Tabla58[[#This Row],[Integración Ago/2024]]) -> 0 | H38: =IF(ISERROR(AVERAGE(Tabla4[[#This Row],[Creación y captura Ago/2024]:[Compartición e Interoperabilidad Ago/2024]])),"",AVERAGE(Tabla4[[#This Row],[Creación y captura Ago/2024]:[Compartición e Interoperabilidad Ago/2024]])) -> 0.1 | K38: =IF(ISERROR(AVERAGE('Calidad de Datos'!G42:J42)),"",AVERAGE('Calidad de Datos'!G42:J42)) -> 0 | L38: =IF(Tabla13[[#This Row],[Uso y acceso Sep/2024]]="","",Tabla13[[#This Row],[Uso y acceso Sep/2024]]) -> 0.3 | M38: =IF(Tabla58[[#This Row],[Integración Sep/2024]]="","",Tabla58[[#This Row],[Integración Sep/2024]]) -> 0 | N38: =IF(ISERROR(AVERAGE(Tabla4[[#This Row],[Creación y captura Sep/2024]:[Compartición e Interoperabilidad Sep/2024]])),"",AVERAGE(Tabla4[[#This Row],[Creación y captura Sep/2024]:[Compartición e Interoperabilidad Sep/2024]])) -> 0.1 | O38: 0.5 | P38: 0.2 | Q38: =IF(ISERROR(AVERAGE('Calidad de Datos'!K42:N42)),"",AVERAGE('Calidad de Datos'!K42:N42)) -> 0 | R38: =IF(Tabla13[[#This Row],[Uso y acceso Oct/2024]]="","",Tabla13[[#This Row],[Uso y acceso Oct/2024]]) -> 0.5 | S38: =IF(Tabla58[[#This Row],[Integración Oct/2024]]="","",Tabla58[[#This Row],[Integración Oct/2024]]) -> 0.2 | T38: =IF(ISERROR(AVERAGE(Tabla4[[#This Row],[Creación y captura Oct/2024]:[Compartición e Interoperabilidad Oct/2024]])),"",AVERAGE(Tabla4[[#This Row],[Creación y captura Oct/2024]:[Compartición e Interoperabilidad Oct/2024]])) -> 0.28 | U38: 1 | V38: 1 | W38: =IF(ISERROR(AVERAGE('Calidad de Datos'!O42:R42)),"",AVERAGE('Calidad de Datos'!O42:R42)) -> 1 | X38: =IF(Tabla13[[#This Row],[Uso y acceso Nov/2024]]="","",Tabla13[[#This Row],[Uso y acceso Nov/2024]]) -> 1 | Y38: =IF(Tabla58[[#This Row],[Integración Nov/2024]]="","",Tabla58[[#This Row],[Integración Nov/2024]]) -> 0.5 | Z38: =IF(ISERROR(AVERAGE(Tabla4[[#This Row],[Creación y captura Nov/2024]:[Compartición e Interoperabilidad Nov/2024]])),"",AVERAGE(Tabla4[[#This Row],[Creación y captura Nov/2024]:[Compartición e Interoperabilidad Nov/2024]])) -> 0.9 | AA38: 1 | AB38: 1 | AC38: =IF(ISERROR(AVERAGE('Calidad de Datos'!S42:V42)),"",AVERAGE('Calidad de Datos'!S42:V42)) -> 1 | AD38: =IF(Tabla13[[#This Row],[Uso y acceso Dic/2024]]="","",Tabla13[[#This Row],[Uso y acceso Dic/2024]]) -> 1 | AE38: =IF(Tabla58[[#This Row],[Integración Dic/2024]]="","",Tabla58[[#This Row],[Integración Dic/2024]]) -> 1 | AF38: =IF(ISERROR(AVERAGE(Tabla4[[#This Row],[Creación y captura Dic/2024]:[Compartición e Interoperabilidad Dic/2024]])),"",AVERAGE(Tabla4[[#This Row],[Creación y captura Dic/2024]:[Compartición e Interoperabilidad Dic/2024]])) -> 1 | AG38: 1 | AH38: 1 | AI38: =IF(ISERROR(AVERAGE('Calidad de Datos'!W42:Z42)),"",AVERAGE('Calidad de Datos'!W42:Z42)) -> 1 | AJ38: =IF(Tabla13[[#This Row],[Uso y acceso Ene/2025]]="","",Tabla13[[#This Row],[Uso y acceso Ene/2025]]) -> 1 | AK38: =IF(Tabla58[[#This Row],[Integración Ene/2025]]="","",Tabla58[[#This Row],[Integración Ene/2025]]) -> 1 | AL38: =IF(ISERROR(AVERAGE(Tabla4[[#This Row],[Creación y captura Ene/2025]:[Compartición e Interoperabilidad Ene/2025]])),"",AVERAGE(Tabla4[[#This Row],[Creación y captura Ene/2025]:[Compartición e Interoperabilidad Ene/2025]])) -> 1 | AM38: 1 | AN38: 1 | AO38: =IF(ISERROR(AVERAGE('Calidad de Datos'!AA42:AD42)),"",AVERAGE('Calidad de Datos'!AA42:AD42)) -> 1 | AP38: =IF(Tabla13[[#This Row],[Uso y acceso Feb/2025]]="","",Tabla13[[#This Row],[Uso y acceso Feb/2025]]) -> 1 | AQ38: =IF(Tabla58[[#This Row],[Integración Feb/2025]]="","",Tabla58[[#This Row],[Integración Feb/2025]]) -> 1 | AR38: =IF(ISERROR(AVERAGE(Tabla4[[#This Row],[Creación y captura Feb/2025]:[Compartición e Interoperabilidad Feb/2025]])),"",AVERAGE(Tabla4[[#This Row],[Creación y captura Feb/2025]:[Compartición e Interoperabilidad Feb/2025]])) -> 1 | AS38: 1 | AT38: 1 | AU38: =IF(ISERROR(AVERAGE('Calidad de Datos'!AE42:AH42)),"",AVERAGE('Calidad de Datos'!AE42:AH42)) -> 1 | AV38: =IF(Tabla13[[#This Row],[Uso y acceso Mar/2025]]="","",Tabla13[[#This Row],[Uso y acceso Mar/2025]]) -> 1 | AW38: =IF(Tabla58[[#This Row],[Integración Mar/2025]]="","",Tabla58[[#This Row],[Integración Mar/2025]]) -> 1 | AX38: =IF(ISERROR(AVERAGE(Tabla4[[#This Row],[Creación y captura Mar/2025]:[Compartición e Interoperabilidad Mar/2025]])),"",AVERAGE(Tabla4[[#This Row],[Creación y captura Mar/2025]:[Compartición e Interoperabilidad Mar/2025]])) -> 1 | AY38: 1 | AZ38: 1 | BA38: =IF(ISERROR(AVERAGE('Calidad de Datos'!AI42:AL42)),"",AVERAGE('Calidad de Datos'!AI42:AL42)) -> 1 | BB38: =IF(Tabla13[[#This Row],[Uso y acceso Abr/2025]]="","",Tabla13[[#This Row],[Uso y acceso Abr/2025]]) -> 1 | BC38: =IF(Tabla58[[#This Row],[Integración Abr/2025]]="","",Tabla58[[#This Row],[Integración Abr/2025]]) -> 1 | BD38: =IF(ISERROR(AVERAGE(Tabla4[[#This Row],[Creación y captura Abr/2025]:[Compartición e Interoperabilidad Abr/2025]])),"",AVERAGE(Tabla4[[#This Row],[Creación y captura Abr/2025]:[Compartición e Interoperabilidad Abr/2025]])) -> 1 | BE38: 1 | BF38: 1 | BG38: =IF(ISERROR(AVERAGE('Calidad de Datos'!AM42:AP42)),"",AVERAGE('Calidad de Datos'!AM42:AP42)) -> 1 | BH38: =IF(Tabla13[[#This Row],[Uso y acceso May/2025]]="","",Tabla13[[#This Row],[Uso y acceso May/2025]]) -> 1 | BI38: =IF(Tabla58[[#This Row],[Integración May/2025]]="","",Tabla58[[#This Row],[Integración May/2025]]) -> 1 | BJ38: =IF(ISERROR(AVERAGE(Tabla4[[#This Row],[Creación y captura May/2025]:[Compartición e Interoperabilidad May/2025]])),"",AVERAGE(Tabla4[[#This Row],[Creación y captura May/2025]:[Compartición e Interoperabilidad May/2025]])) -> 1 | BK38: 1 | BL38: 1 | BM38: =IF(ISERROR(AVERAGE('Calidad de Datos'!AQ42:AT42)),"",AVERAGE('Calidad de Datos'!AQ42:AT42)) -> 1 | BN38: =IF(Tabla13[[#This Row],[Uso y acceso Jun/2025]]="","",Tabla13[[#This Row],[Uso y acceso Jun/2025]]) -> 1 | BO38: =IF(Tabla58[[#This Row],[Integración Jun/2025]]="","",Tabla58[[#This Row],[Integración Jun/2025]]) -> 1 | BP38: =IF(ISERROR(AVERAGE(Tabla4[[#This Row],[Creación y captura Jun/2025]:[Compartición e Interoperabilidad Jun/2025]])),"",AVERAGE(Tabla4[[#This Row],[Creación y captura Jun/2025]:[Compartición e Interoperabilidad Jun/2025]])) -> 1 | BQ38: 1 | BR38: 1 | BS38: =IF(ISERROR(AVERAGE('Calidad de Datos'!AU42:AX42)),"",AVERAGE('Calidad de Datos'!AU42:AX42)) -> 1 | BT38: =IF(Tabla13[[#This Row],[Uso y acceso Sep/2025]]="","",Tabla13[[#This Row],[Uso y acceso Sep/2025]]) -> 1 | BU38: =IF(Tabla58[[#This Row],[Integración Sep/2025]]="","",Tabla58[[#This Row],[Integración Sep/2025]]) -> 1 | BV38: =IF(ISERROR(AVERAGE(Tabla4[[#This Row],[Creación y captura Sep/2025]:[Compartición e Interoperabilidad Sep/2025]])),"",AVERAGE(Tabla4[[#This Row],[Creación y captura Sep/2025]:[Compartición e Interoperabilidad Sep/2025]])) -> 1 | BW38: 1 | BX38: 1 | BY38: =IF(ISERROR(AVERAGE('Calidad de Datos'!AY42:BB42)),"",AVERAGE('Calidad de Datos'!AY42:BB42)) -> 1 | BZ38: =IF(ISERROR(Tabla13[[#This Row],[Uso y acceso Dic/2025]]),"",Tabla13[[#This Row],[Uso y acceso Dic/2025]]) -> 1 | CA38: =IF(ISERROR(Tabla58[[#This Row],[Integración Dic/2025]]),"",Tabla58[[#This Row],[Integración Dic/2025]]) -> 1 | CB38: =IF(ISERROR(AVERAGE(Tabla4[[#This Row],[Creación y captura Dic/2025]:[Compartición e Interoperabilidad Dic/2025]])),"",AVERAGE(Tabla4[[#This Row],[Creación y captura Dic/2025]:[Compartición e Interoperabilidad Dic/2025]])) -> 1 | CC38: 1 | CD38: 1 | CE38: =IF(ISERROR(AVERAGE('Calidad de Datos'!BC42:BF42)),"",AVERAGE('Calidad de Datos'!BC42:BF42)) -> 1 | CF38: =IF(ISERROR(Tabla13[[#This Row],[Uso y acceso Mar/2026]]),"",Tabla13[[#This Row],[Uso y acceso Mar/2026]]) -> 1 | CG38: =IF(ISERROR(Tabla58[[#This Row],[Integración Mar/2026]]),"",Tabla58[[#This Row],[Integración Mar/2026]]) -> 1 | CH38: =IF(ISERROR(AVERAGE(Tabla4[[#This Row],[Creación y captura Mar/2026]:[Compartición e Interoperabilidad Mar/2026]])),"",AVERAGE(Tabla4[[#This Row],[Creación y captura Mar/2026]:[Compartición e Interoperabilidad Mar/2026]])) -> 1
B39: Departamento-Municipio | E39: =IF(ISERROR(AVERAGE('Calidad de Datos'!C43:F43)),"",AVERAGE('Calidad de Datos'!C43:F43)) -> 0 | F39: =IF(Tabla13[[#This Row],[Uso y acceso Ago/2024]]="","",Tabla13[[#This Row],[Uso y acceso Ago/2024]]) -> 0 | G39: =IF(Tabla58[[#This Row],[Integración Ago/2024]]="","",Tabla58[[#This Row],[Integración Ago/2024]]) -> 0 | H39: =IF(ISERROR(AVERAGE(Tabla4[[#This Row],[Creación y captura Ago/2024]:[Compartición e Interoperabilidad Ago/2024]])),"",AVERAGE(Tabla4[[#This Row],[Creación y captura Ago/2024]:[Compartición e Interoperabilidad Ago/2024]])) -> 0 | I39: 0.2 | J39: 0.2 | K39: =IF(ISERROR(AVERAGE('Calidad de Datos'!G43:J43)),"",AVERAGE('Calidad de Datos'!G43:J43)) -> 0 | L39: =IF(Tabla13[[#This Row],[Uso y acceso Sep/2024]]="","",Tabla13[[#This Row],[Uso y acceso Sep/2024]]) -> 0 | M39: =IF(Tabla58[[#This Row],[Integración Sep/2024]]="","",Tabla58[[#This Row],[Integración Sep/2024]]) -> 0.2 | N39: =IF(ISERROR(AVERAGE(Tabla4[[#This Row],[Creación y captura Sep/2024]:[Compartición e Interoperabilidad Sep/2024]])),"",AVERAGE(Tabla4[[#This Row],[Creación y captura Sep/2024]:[Compartición e Interoperabilidad Sep/2024]])) -> 0.12 | O39: 0.55 | P39: 0.25 | Q39: =IF(ISERROR(AVERAGE('Calidad de Datos'!K43:N43)),"",AVERAGE('Calidad de Datos'!K43:N43)) -> 0 | R39: =IF(Tabla13[[#This Row],[Uso y acceso Oct/2024]]="","",Tabla13[[#This Row],[Uso y acceso Oct/2024]]) -> 1 | S39: =IF(Tabla58[[#This Row],[Integración Oct/2024]]="","",Tabla58[[#This Row],[Integración Oct/2024]]) -> 0.25 | T39: =IF(ISERROR(AVERAGE(Tabla4[[#This Row],[Creación y captura Oct/2024]:[Compartición e Interoperabilidad Oct/2024]])),"",AVERAGE(Tabla4[[#This Row],[Creación y captura Oct/2024]:[Compartición e Interoperabilidad Oct/2024]])) -> 0.41 | U39: 1 | V39: 1 | W39: =IF(ISERROR(AVERAGE('Calidad de Datos'!O43:R43)),"",AVERAGE('Calidad de Datos'!O43:R43)) -> 1 | X39: =IF(Tabla13[[#This Row],[Uso y acceso Nov/2024]]="","",Tabla13[[#This Row],[Uso y acceso Nov/2024]]) -> 1 | Y39: =IF(Tabla58[[#This Row],[Integración Nov/2024]]="","",Tabla58[[#This Row],[Integración Nov/2024]]) -> 0.5 | Z39: =IF(ISERROR(AVERAGE(Tabla4[[#This Row],[Creación y captura Nov/2024]:[Compartición e Interoperabilidad Nov/2024]])),"",AVERAGE(Tabla4[[#This Row],[Creación y captura Nov/2024]:[Compartición e Interoperabilidad Nov/2024]])) -> 0.9 | AA39: 1 | AB39: 1 | AC39: =IF(ISERROR(AVERAGE('Calidad de Datos'!S43:V43)),"",AVERAGE('Calidad de Datos'!S43:V43)) -> 1 | AD39: =IF(Tabla13[[#This Row],[Uso y acceso Dic/2024]]="","",Tabla13[[#This Row],[Uso y acceso Dic/2024]]) -> 1 | AE39: =IF(Tabla58[[#This Row],[Integración Dic/2024]]="","",Tabla58[[#This Row],[Integración Dic/2024]]) -> 1 | AF39: =IF(ISERROR(AVERAGE(Tabla4[[#This Row],[Creación y captura Dic/2024]:[Compartición e Interoperabilidad Dic/2024]])),"",AVERAGE(Tabla4[[#This Row],[Creación y captura Dic/2024]:[Compartición e Interoperabilidad Dic/2024]])) -> 1 | AG39: 1 | AH39: 1 | AI39: =IF(ISERROR(AVERAGE('Calidad de Datos'!W43:Z43)),"",AVERAGE('Calidad de Datos'!W43:Z43)) -> 1 | AJ39: =IF(Tabla13[[#This Row],[Uso y acceso Ene/2025]]="","",Tabla13[[#This Row],[Uso y acceso Ene/2025]]) -> 1 | AK39: =IF(Tabla58[[#This Row],[Integración Ene/2025]]="","",Tabla58[[#This Row],[Integración Ene/2025]]) -> 1 | AL39: =IF(ISERROR(AVERAGE(Tabla4[[#This Row],[Creación y captura Ene/2025]:[Compartición e Interoperabilidad Ene/2025]])),"",AVERAGE(Tabla4[[#This Row],[Creación y captura Ene/2025]:[Compartición e Interoperabilidad Ene/2025]])) -> 1 | AM39: 1 | AN39: 1 | AO39: =IF(ISERROR(AVERAGE('Calidad de Datos'!AA43:AD43)),"",AVERAGE('Calidad de Datos'!AA43:AD43)) -> 1 | AP39: =IF(Tabla13[[#This Row],[Uso y acceso Feb/2025]]="","",Tabla13[[#This Row],[Uso y acceso Feb/2025]]) -> 1 | AQ39: =IF(Tabla58[[#This Row],[Integración Feb/2025]]="","",Tabla58[[#This Row],[Integración Feb/2025]]) -> 1 | AR39: =IF(ISERROR(AVERAGE(Tabla4[[#This Row],[Creación y captura Feb/2025]:[Compartición e Interoperabilidad Feb/2025]])),"",AVERAGE(Tabla4[[#This Row],[Creación y captura Feb/2025]:[Compartición e Interoperabilidad Feb/2025]])) -> 1 | AS39: 1 | AT39: 1 | AU39: =IF(ISERROR(AVERAGE('Calidad de Datos'!AE43:AH43)),"",AVERAGE('Calidad de Datos'!AE43:AH43)) -> 1 | AV39: =IF(Tabla13[[#This Row],[Uso y acceso Mar/2025]]="","",Tabla13[[#This Row],[Uso y acceso Mar/2025]]) -> 1 | AW39: =IF(Tabla58[[#This Row],[Integración Mar/2025]]="","",Tabla58[[#This Row],[Integración Mar/2025]]) -> 1 | AX39: =IF(ISERROR(AVERAGE(Tabla4[[#This Row],[Creación y captura Mar/2025]:[Compartición e Interoperabilidad Mar/2025]])),"",AVERAGE(Tabla4[[#This Row],[Creación y captura Mar/2025]:[Compartición e Interoperabilidad Mar/2025]])) -> 1 | AY39: 1 | AZ39: 1 | BA39: =IF(ISERROR(AVERAGE('Calidad de Datos'!AI43:AL43)),"",AVERAGE('Calidad de Datos'!AI43:AL43)) -> 1 | BB39: =IF(Tabla13[[#This Row],[Uso y acceso Abr/2025]]="","",Tabla13[[#This Row],[Uso y acceso Abr/2025]]) -> 1 | BC39: =IF(Tabla58[[#This Row],[Integración Abr/2025]]="","",Tabla58[[#This Row],[Integración Abr/2025]]) -> 1 | BD39: =IF(ISERROR(AVERAGE(Tabla4[[#This Row],[Creación y captura Abr/2025]:[Compartición e Interoperabilidad Abr/2025]])),"",AVERAGE(Tabla4[[#This Row],[Creación y captura Abr/2025]:[Compartición e Interoperabilidad Abr/2025]])) -> 1 | BE39: 1 | BF39: 1 | BG39: =IF(ISERROR(AVERAGE('Calidad de Datos'!AM43:AP43)),"",AVERAGE('Calidad de Datos'!AM43:AP43)) -> 1 | BH39: =IF(Tabla13[[#This Row],[Uso y acceso May/2025]]="","",Tabla13[[#This Row],[Uso y acceso May/2025]]) -> 1 | BI39: =IF(Tabla58[[#This Row],[Integración May/2025]]="","",Tabla58[[#This Row],[Integración May/2025]]) -> 1 | BJ39: =IF(ISERROR(AVERAGE(Tabla4[[#This Row],[Creación y captura May/2025]:[Compartición e Interoperabilidad May/2025]])),"",AVERAGE(Tabla4[[#This Row],[Creación y captura May/2025]:[Compartición e Interoperabilidad May/2025]])) -> 1 | BK39: 1 | BL39: 1 | BM39: =IF(ISERROR(AVERAGE('Calidad de Datos'!AQ43:AT43)),"",AVERAGE('Calidad de Datos'!AQ43:AT43)) -> 1 | BN39: =IF(Tabla13[[#This Row],[Uso y acceso Jun/2025]]="","",Tabla13[[#This Row],[Uso y acceso Jun/2025]]) -> 1 | BO39: =IF(Tabla58[[#This Row],[Integración Jun/2025]]="","",Tabla58[[#This Row],[Integración Jun/2025]]) -> 1 | BP39: =IF(ISERROR(AVERAGE(Tabla4[[#This Row],[Creación y captura Jun/2025]:[Compartición e Interoperabilidad Jun/2025]])),"",AVERAGE(Tabla4[[#This Row],[Creación y captura Jun/2025]:[Compartición e Interoperabilidad Jun/2025]])) -> 1 | BQ39: 1 | BR39: 1 | BS39: =IF(ISERROR(AVERAGE('Calidad de Datos'!AU43:AX43)),"",AVERAGE('Calidad de Datos'!AU43:AX43)) -> 1 | BT39: =IF(Tabla13[[#This Row],[Uso y acceso Sep/2025]]="","",Tabla13[[#This Row],[Uso y acceso Sep/2025]]) -> 1 | BU39: =IF(Tabla58[[#This Row],[Integración Sep/2025]]="","",Tabla58[[#This Row],[Integración Sep/2025]]) -> 1 | BV39: =IF(ISERROR(AVERAGE(Tabla4[[#This Row],[Creación y captura Sep/2025]:[Compartición e Interoperabilidad Sep/2025]])),"",AVERAGE(Tabla4[[#This Row],[Creación y captura Sep/2025]:[Compartición e Interoperabilidad Sep/2025]])) -> 1 | BW39: 1 | BX39: 1 | BY39: =IF(ISERROR(AVERAGE('Calidad de Datos'!AY43:BB43)),"",AVERAGE('Calidad de Datos'!AY43:BB43)) -> 1 | BZ39: =IF(ISERROR(Tabla13[[#This Row],[Uso y acceso Dic/2025]]),"",Tabla13[[#This Row],[Uso y acceso Dic/2025]]) -> 1 | CA39: =IF(ISERROR(Tabla58[[#This Row],[Integración Dic/2025]]),"",Tabla58[[#This Row],[Integración Dic/2025]]) -> 1 | CB39: =IF(ISERROR(AVERAGE(Tabla4[[#This Row],[Creación y captura Dic/2025]:[Compartición e Interoperabilidad Dic/2025]])),"",AVERAGE(Tabla4[[#This Row],[Creación y captura Dic/2025]:[Compartición e Interoperabilidad Dic/2025]])) -> 1 | CC39: 1 | CD39: 1 | CE39: =IF(ISERROR(AVERAGE('Calidad de Datos'!BC43:BF43)),"",AVERAGE('Calidad de Datos'!BC43:BF43)) -> 1 | CF39: =IF(ISERROR(Tabla13[[#This Row],[Uso y acceso Mar/2026]]),"",Tabla13[[#This Row],[Uso y acceso Mar/2026]]) -> 1 | CG39: =IF(ISERROR(Tabla58[[#This Row],[Integración Mar/2026]]),"",Tabla58[[#This Row],[Integración Mar/2026]]) -> 1 | CH39: =IF(ISERROR(AVERAGE(Tabla4[[#This Row],[Creación y captura Mar/2026]:[Compartición e Interoperabilidad Mar/2026]])),"",AVERAGE(Tabla4[[#This Row],[Creación y captura Mar/2026]:[Compartición e Interoperabilidad Mar/2026]])) -> 1
B40: Persona datos laborales | E40: =IF(ISERROR(AVERAGE('Calidad de Datos'!C44:F44)),"",AVERAGE('Calidad de Datos'!C44:F44)) -> 0 | F40: =IF(Tabla13[[#This Row],[Uso y acceso Ago/2024]]="","",Tabla13[[#This Row],[Uso y acceso Ago/2024]]) -> 0.5 | G40: =IF(Tabla58[[#This Row],[Integración Ago/2024]]="","",Tabla58[[#This Row],[Integración Ago/2024]]) -> 0 | H40: =IF(ISERROR(AVERAGE(Tabla4[[#This Row],[Creación y captura Ago/2024]:[Compartición e Interoperabilidad Ago/2024]])),"",AVERAGE(Tabla4[[#This Row],[Creación y captura Ago/2024]:[Compartición e Interoperabilidad Ago/2024]])) -> 0.16666667 | K40: =IF(ISERROR(AVERAGE('Calidad de Datos'!G44:J44)),"",AVERAGE('Calidad de Datos'!G44:J44)) -> 0 | L40: =IF(Tabla13[[#This Row],[Uso y acceso Sep/2024]]="","",Tabla13[[#This Row],[Uso y acceso Sep/2024]]) -> 0.9 | M40: =IF(Tabla58[[#This Row],[Integración Sep/2024]]="","",Tabla58[[#This Row],[Integración Sep/2024]]) -> 0 | N40: =IF(ISERROR(AVERAGE(Tabla4[[#This Row],[Creación y captura Sep/2024]:[Compartición e Interoperabilidad Sep/2024]])),"",AVERAGE(Tabla4[[#This Row],[Creación y captura Sep/2024]:[Compartición e Interoperabilidad Sep/2024]])) -> 0.3 | O40: 0.3 | P40: 0.15 | Q40: =IF(ISERROR(AVERAGE('Calidad de Datos'!K44:N44)),"",AVERAGE('Calidad de Datos'!K44:N44)) -> 0 | R40: =IF(Tabla13[[#This Row],[Uso y acceso Oct/2024]]="","",Tabla13[[#This Row],[Uso y acceso Oct/2024]]) -> 0.9 | S40: =IF(Tabla58[[#This Row],[Integración Oct/2024]]="","",Tabla58[[#This Row],[Integración Oct/2024]]) -> 0.15 | T40: =IF(ISERROR(AVERAGE(Tabla4[[#This Row],[Creación y captura Oct/2024]:[Compartición e Interoperabilidad Oct/2024]])),"",AVERAGE(Tabla4[[#This Row],[Creación y captura Oct/2024]:[Compartición e Interoperabilidad Oct/2024]])) -> 0.3 | U40: 0.8 | V40: 0.8 | W40: =IF(ISERROR(AVERAGE('Calidad de Datos'!O44:R44)),"",AVERAGE('Calidad de Datos'!O44:R44)) -> 0.805 | X40: =IF(Tabla13[[#This Row],[Uso y acceso Nov/2024]]="","",Tabla13[[#This Row],[Uso y acceso Nov/2024]]) -> 0.995 | Y40: =IF(Tabla58[[#This Row],[Integración Nov/2024]]="","",Tabla58[[#This Row],[Integración Nov/2024]]) -> 0.6 | Z40: =IF(ISERROR(AVERAGE(Tabla4[[#This Row],[Creación y captura Nov/2024]:[Compartición e Interoperabilidad Nov/2024]])),"",AVERAGE(Tabla4[[#This Row],[Creación y captura Nov/2024]:[Compartición e Interoperabilidad Nov/2024]])) -> 0.8 | AA40: 0.9 | AB40: 0.9 | AC40: =IF(ISERROR(AVERAGE('Calidad de Datos'!S44:V44)),"",AVERAGE('Calidad de Datos'!S44:V44)) -> 0.905 | AD40: =IF(Tabla13[[#This Row],[Uso y acceso Dic/2024]]="","",Tabla13[[#This Row],[Uso y acceso Dic/2024]]) -> 0.995 | AE40: =IF(Tabla58[[#This Row],[Integración Dic/2024]]="","",Tabla58[[#This Row],[Integración Dic/2024]]) -> 0.9 | AF40: =IF(ISERROR(AVERAGE(Tabla4[[#This Row],[Creación y captura Dic/2024]:[Compartición e Interoperabilidad Dic/2024]])),"",AVERAGE(Tabla4[[#This Row],[Creación y captura Dic/2024]:[Compartición e Interoperabilidad Dic/2024]])) -> 0.92 | AG40: 0.95 | AH40: 1 | AI40: =IF(ISERROR(AVERAGE('Calidad de Datos'!W44:Z44)),"",AVERAGE('Calidad de Datos'!W44:Z44)) -> 0.9375 | AJ40: =IF(Tabla13[[#This Row],[Uso y acceso Ene/2025]]="","",Tabla13[[#This Row],[Uso y acceso Ene/2025]]) -> 0.995 | AK40: =IF(Tabla58[[#This Row],[Integración Ene/2025]]="","",Tabla58[[#This Row],[Integración Ene/2025]]) -> 0.95 | AL40: =IF(ISERROR(AVERAGE(Tabla4[[#This Row],[Creación y captura Ene/2025]:[Compartición e Interoperabilidad Ene/2025]])),"",AVERAGE(Tabla4[[#This Row],[Creación y captura Ene/2025]:[Compartición e Interoperabilidad Ene/2025]])) -> 0.9665 | AM40: 0.95 | AN40: 1 | AO40: =IF(ISERROR(AVERAGE('Calidad de Datos'!AA44:AD44)),"",AVERAGE('Calidad de Datos'!AA44:AD44)) -> 0.9825 | AP40: =IF(Tabla13[[#This Row],[Uso y acceso Feb/2025]]="","",Tabla13[[#This Row],[Uso y acceso Feb/2025]]) -> 0.995 | AQ40: =IF(Tabla58[[#This Row],[Integración Feb/2025]]="","",Tabla58[[#This Row],[Integración Feb/2025]]) -> 1 | AR40: =IF(ISERROR(AVERAGE(Tabla4[[#This Row],[Creación y captura Feb/2025]:[Compartición e Interoperabilidad Feb/2025]])),"",AVERAGE(Tabla4[[#This Row],[Creación y captura Feb/2025]:[Compartición e Interoperabilidad Feb/2025]])) -> 0.9855 | AS40: 0.95 | AT40: 1 | AU40: =IF(ISERROR(AVERAGE('Calidad de Datos'!AE44:AH44)),"",AVERAGE('Calidad de Datos'!AE44:AH44)) -> 0.9875 | AV40: =IF(Tabla13[[#This Row],[Uso y acceso Mar/2025]]="","",Tabla13[[#This Row],[Uso y acceso Mar/2025]]) -> 0.995 | AW40: =IF(Tabla58[[#This Row],[Integración Mar/2025]]="","",Tabla58[[#This Row],[Integración Mar/2025]]) -> 1 | AX40: =IF(ISERROR(AVERAGE(Tabla4[[#This Row],[Creación y captura Mar/2025]:[Compartición e Interoperabilidad Mar/2025]])),"",AVERAGE(Tabla4[[#This Row],[Creación y captura Mar/2025]:[Compartición e Interoperabilidad Mar/2025]])) -> 0.9865 | AY40: 1 | AZ40: 1 | BA40: =IF(ISERROR(AVERAGE('Calidad de Datos'!AI44:AL44)),"",AVERAGE('Calidad de Datos'!AI44:AL44)) -> 1 | BB40: =IF(Tabla13[[#This Row],[Uso y acceso Abr/2025]]="","",Tabla13[[#This Row],[Uso y acceso Abr/2025]]) -> 0.995 | BC40: =IF(Tabla58[[#This Row],[Integración Abr/2025]]="","",Tabla58[[#This Row],[Integración Abr/2025]]) -> 1 | BD40: =IF(ISERROR(AVERAGE(Tabla4[[#This Row],[Creación y captura Abr/2025]:[Compartición e Interoperabilidad Abr/2025]])),"",AVERAGE(Tabla4[[#This Row],[Creación y captura Abr/2025]:[Compartición e Interoperabilidad Abr/2025]])) -> 0.999 | BE40: 1 | BF40: 1 | BG40: =IF(ISERROR(AVERAGE('Calidad de Datos'!AM44:AP44)),"",AVERAGE('Calidad de Datos'!AM44:AP44)) -> 1 | BH40: =IF(Tabla13[[#This Row],[Uso y acceso May/2025]]="","",Tabla13[[#This Row],[Uso y acceso May/2025]]) -> 0.995 | BI40: =IF(Tabla58[[#This Row],[Integración May/2025]]="","",Tabla58[[#This Row],[Integración May/2025]]) -> 1 | BJ40: =IF(ISERROR(AVERAGE(Tabla4[[#This Row],[Creación y captura May/2025]:[Compartición e Interoperabilidad May/2025]])),"",AVERAGE(Tabla4[[#This Row],[Creación y captura May/2025]:[Compartición e Interoperabilidad May/2025]])) -> 0.999 | BK40: 1 | BL40: 1 | BM40: =IF(ISERROR(AVERAGE('Calidad de Datos'!AQ44:AT44)),"",AVERAGE('Calidad de Datos'!AQ44:AT44)) -> 1 | BN40: =IF(Tabla13[[#This Row],[Uso y acceso Jun/2025]]="","",Tabla13[[#This Row],[Uso y acceso Jun/2025]]) -> 0.9 | BO40: =IF(Tabla58[[#This Row],[Integración Jun/2025]]="","",Tabla58[[#This Row],[Integración Jun/2025]]) -> 1 | BP40: =IF(ISERROR(AVERAGE(Tabla4[[#This Row],[Creación y captura Jun/2025]:[Compartición e Interoperabilidad Jun/2025]])),"",AVERAGE(Tabla4[[#This Row],[Creación y captura Jun/2025]:[Compartición e Interoperabilidad Jun/2025]])) -> 0.98 | BQ40: 1 | BR40: 1 | BS40: =IF(ISERROR(AVERAGE('Calidad de Datos'!AU44:AX44)),"",AVERAGE('Calidad de Datos'!AU44:AX44)) -> 1 | BT40: =IF(Tabla13[[#This Row],[Uso y acceso Sep/2025]]="","",Tabla13[[#This Row],[Uso y acceso Sep/2025]]) -> 0.9 | BU40: =IF(Tabla58[[#This Row],[Integración Sep/2025]]="","",Tabla58[[#This Row],[Integración Sep/2025]]) -> 1 | BV40: =IF(ISERROR(AVERAGE(Tabla4[[#This Row],[Creación y captura Sep/2025]:[Compartición e Interoperabilidad Sep/2025]])),"",AVERAGE(Tabla4[[#This Row],[Creación y captura Sep/2025]:[Compartición e Interoperabilidad Sep/2025]])) -> 0.98 | BW40: 1 | BX40: 1 | BY40: =IF(ISERROR(AVERAGE('Calidad de Datos'!AY44:BB44)),"",AVERAGE('Calidad de Datos'!AY44:BB44)) -> 1 | BZ40: =IF(ISERROR(Tabla13[[#This Row],[Uso y acceso Dic/2025]]),"",Tabla13[[#This Row],[Uso y acceso Dic/2025]]) -> 0.995 | CA40: =IF(ISERROR(Tabla58[[#This Row],[Integración Dic/2025]]),"",Tabla58[[#This Row],[Integración Dic/2025]]) -> 1 | CB40: =IF(ISERROR(AVERAGE(Tabla4[[#This Row],[Creación y captura Dic/2025]:[Compartición e Interoperabilidad Dic/2025]])),"",AVERAGE(Tabla4[[#This Row],[Creación y captura Dic/2025]:[Compartición e Interoperabilidad Dic/2025]])) -> 0.999 | CC40: 1 | CD40: 1 | CE40: =IF(ISERROR(AVERAGE('Calidad de Datos'!BC44:BF44)),"",AVERAGE('Calidad de Datos'!BC44:BF44)) -> 1 | CF40: =IF(ISERROR(Tabla13[[#This Row],[Uso y acceso Mar/2026]]),"",Tabla13[[#This Row],[Uso y acceso Mar/2026]]) -> 0.9 | CG40: =IF(ISERROR(Tabla58[[#This Row],[Integración Mar/2026]]),"",Tabla58[[#This Row],[Integración Mar/2026]]) -> 1 | CH40: =IF(ISERROR(AVERAGE(Tabla4[[#This Row],[Creación y captura Mar/2026]:[Compartición e Interoperabilidad Mar/2026]])),"",AVERAGE(Tabla4[[#This Row],[Creación y captura Mar/2026]:[Compartición e Interoperabilidad Mar/2026]])) -> 0.98
