Workbook

Sheet Calidad de Datos
B1: Se realiza sobre las entidades Integradas | E1: Entidades con % > 0 / Cantidad total de entidades integradas
B2: COMPLETITUD: Mide el grado en que todos los atributos de la entidad se encuentran diligenciados | E2: Completitud = (número de registros completos/númerto total de registros)*100 | H2: Compeltitud por registro = (número de atributos completos / número total de atributor) * 100
B3: OPORTUNIDAD: Mide si los datos se encuentran disponibles en el momento que se necesitan | E3: % datos disponibles = porcentaje de datos que se pueden acceder en un tiempo definido | H3: Tasa de cumplimiento = mide si el sistema de datos cumple con los tiempos de entrega
B4: CONSISTENCIA: Mide la uniformidad y coherencia de los datos entre diferentes sistemas, asegurando que no haya discrepancias | E4: % de registros consistentes = % de registros que cumplen con las reglas de consistencia
B5: CONFORMIDAD: Mide que los datos se adhieran a las políticas, regulaciones y estándares establecidos | E5: Calidad de datos = % de datos que cumplen los estándares de precisión, integridad y consistencia
C6: Completitud | D6: Oportunidad | E6: Consistencia | F6: Conformidad | G6: Completitud | H6: Oportunidad | I6: Consistencia | J6: Conformidad | K6: Completitud | L6: Oportunidad | M6: Consistencia | N6: Conformidad | O6: Completitud | P6: Oportunidad | Q6: Consistencia | R6: Conformidad | S6: Completitud | T6: Oportunidad | U6: Consistencia | V6: Conformidad | W6: Completitud | X6: Oportunidad | Y6: Consistencia | Z6: Conformidad | AA6: Completitud | AB6: Oportunidad | AC6: Consistencia | AD6: Conformidad | AE6: Completitud | AF6: Oportunidad | AG6: Consistencia | AH6: Conformidad | AI6: Completitud | AJ6: Oportunidad | AK6: Consistencia | AL6: Conformidad | AM6: Completitud | AN6: Oportunidad | AO6: Consistencia | AP6: Conformidad | AQ6: Completitud | AR6: Oportunidad | AS6: Consistencia | AT6: Conformidad
C7: 1 | D7: 1 | E7: 1 | F7: 1 | G7: 2 | H7: 2 | I7: 2 | J7: 2 | K7: 3 | L7: 3 | M7: 3 | N7: 3 | O7: 4 | P7: 4 | Q7: 4 | R7: 4 | S7: 5 | T7: 5 | U7: 5 | V7: 5 | W7: 6 | X7: 6 | Y7: 6 | Z7: 6 | AA7: 7 | AB7: 7 | AC7: 7 | AD7: 7 | AE7: 8 | AF7: 8 | AG7: 8 | AH7: 8 | AI7: 9 | AJ7: 9 | AK7: 9 | AL7: 9 | AM7: 10 | AN7: 10 | AO7: 10 | AP7: 10 | AQ7: 17 | AR7: 17 | AS7: 17 | AT7: 17
C8: =SUMIF(C11:C217,">0")/COUNTIF(C11:C217,">0") -> 0.95342105 | D8: =SUMIF(D11:D217,">0")/COUNTIF(D11:D217,">0") -> 0.99710526 | E8: =SUMIF(E11:E217,">0")/COUNTIF(E11:E217,">0") -> 0.99210526 | F8: =SUMIF(F11:F217,">0")/COUNTIF(F11:F217,">0") -> 0.8 | G8: =SUMIF(G11:G217,">0")/COUNTIF(G11:G217,">0") -> 0.95342105 | H8: =SUMIF(H11:H217,">0")/COUNTIF(H11:H217,">0") -> 1 | I8: =SUMIF(I11:I217,">0")/COUNTIF(I11:I217,">0") -> 0.99210526 | J8: =SUMIF(J11:J217,">0")/COUNTIF(J11:J217,">0") -> 0.85 | ... AT8: =SUMIF(AT11:AT217,">0")/COUNTIF(AT11:AT217,">0") -> 1
C9: =IFERROR(AVERAGEIF(Tabla1[Completitud Ago/2024],">0",Tabla1[Completitud Ago/2024]),0) -> 0.95342105 | D9: =IFERROR(AVERAGEIF(Tabla1[Oportunidad Ago/2024],">0",Tabla1[Oportunidad Ago/2024]),0) -> 0.99710526 | E9: =IFERROR(AVERAGEIF(Tabla1[Consistencia Ago/2024],">0",Tabla1[Consistencia Ago/2024]),0) -> 0.99210526 | F9: =IFERROR(AVERAGEIF(Tabla1[Conformidad Ago/2024],">0",Tabla1[Conformidad Ago/2024]),0) -> 0.8 | G9: =IFERROR(AVERAGEIF(Tabla1[Completitud Sep/2024],">0",Tabla1[Completitud Sep/2024]),0) -> 0.95342105 | H9: =IFERROR(AVERAGEIF(Tabla1[Oportunidad Sep/2024],">0",Tabla1[Oportunidad Sep/2024]),0) -> 1 | I9: =IFERROR(AVERAGEIF(Tabla1[Consistencia Sep/2024],">0",Tabla1[Consistencia Sep/2024]),0) -> 0.99210526 | J9: =IFERROR(AVERAGEIF(Tabla1[Conformidad Sep/2024],">0",Tabla1[Conformidad Sep/2024]),0) -> 0.85 | K9: =IFERROR(AVERAGEIF(Tabla1[Completitud Oct/2024],">0",Tabla1[Completitud Oct/2024]),0) -> 0.95342105 | L9: =IFERROR(AVERAGEIF(Tabla1[Oportunidad Oct/2024],">0",Tabla1[Oportunidad Oct/2024]),0) -> 0.99763158 | M9: =IFERROR(AVERAGEIF(Tabla1[Consistencia Oct/2024],">0",Tabla1[Consistencia Oct/2024]),0) -> 0.99447368 | N9: =IFERROR(AVERAGEIF(Tabla1[Conformidad Oct/2024],">0",Tabla1[Conformidad Oct/2024]),0) -> 0.85 | O9: =IFERROR(AVERAGEIF(Tabla1[Completitud Nov/2024],">0",Tabla1[Completitud Nov/2024]),0) -> 0.93142857 | P9: =IFERROR(AVERAGEIF(Tabla1[Oportunidad Nov/2024],">0",Tabla1[Oportunidad Nov/2024]),0) -> 1 | Q9: =IFERROR(AVERAGEIF(Tabla1[Consistencia Nov/2024],">0",Tabla1[Consistencia Nov/2024]),0) -> 0.96785714 | R9: =IFERROR(AVERAGEIF(Tabla1[Conformidad Nov/2024],">0",Tabla1[Conformidad Nov/2024]),0) -> 0.9 | S9: =IFERROR(AVERAGEIF(Tabla1[Completitud Dic/2024],">0",Tabla1[Completitud Dic/2024]),0) -> 0.93142857 | T9: =IFERROR(AVERAGEIF(Tabla1[Oportunidad Dic/2024],">0",Tabla1[Oportunidad Dic/2024]),0) -> 0.99839286 | U9: =IFERROR(AVERAGEIF(Tabla1[Consistencia Dic/2024],">0",Tabla1[Consistencia Dic/2024]),0) -> 0.97089286 | V9: =IFERROR(AVERAGEIF(Tabla1[Conformidad Dic/2024],">0",Tabla1[Conformidad Dic/2024]),0) -> 0.95 | W9: =IFERROR(AVERAGEIF(Tabla1[Completitud Ene/2025],">0",Tabla1[Completitud Ene/2025]),0) -> 0.96035714 | X9: =IFERROR(AVERAGEIF(Tabla1[Oportunidad Ene/2025],">0",Tabla1[Oportunidad Ene/2025]),0) -> 1 | Y9: =IFERROR(AVERAGEIF(Tabla1[Consistencia Ene/2025],">0",Tabla1[Consistencia Ene/2025]),0) -> 0.97285714 | Z9: =IFERROR(AVERAGEIF(Tabla1[Conformidad Ene/2025],">0",Tabla1[Conformidad Ene/2025]),0) -> 0.975 | AA9: =IFERROR(AVERAGEIF(Tabla1[Completitud Feb/2025],">0",Tabla1[Completitud Feb/2025]),0) -> 0.96566667 | AB9: =IFERROR(AVERAGEIF(Tabla1[Oportunidad Feb/2025],">0",Tabla1[Oportunidad Feb/2025]),0) -> 1 | AC9: =IFERROR(AVERAGEIF(Tabla1[Consistencia Feb/2025],">0",Tabla1[Consistencia Feb/2025]),0) -> 0.979 | AD9: =IFERROR(AVERAGEIF(Tabla1[Conformidad Feb/2025],">0",Tabla1[Conformidad Feb/2025]),0) -> 1 | AE9: =IFERROR(AVERAGEIF(Tabla1[Completitud Mar/2025],">0",Tabla1[Completitud Mar/2025]),0) -> 0.96816667 | AF9: =IFERROR(AVERAGEIF(Tabla1[Oportunidad Mar/2025],">0",Tabla1[Oportunidad Mar/2025]),0) -> 1 | AG9: =IFERROR(AVERAGEIF(Tabla1[Consistencia Mar/2025],">0",Tabla1[Consistencia Mar/2025]),0) -> 0.979 | AH9: =IFERROR(AVERAGEIF(Tabla1[Conformidad Mar/2025],">0",Tabla1[Conformidad Mar/2025]),0) -> 1 | AI9: =IFERROR(AVERAGEIF(Tabla1[Completitud Abr/2025],">0",Tabla1[Completitud Abr/2025]),0) -> 0.976125 | AJ9: =IFERROR(AVERAGEIF(Tabla1[Oportunidad Abr/2025],">0",Tabla1[Oportunidad Abr/2025]),0) -> 0.9325 | AK9: =IFERROR(AVERAGEIF(Tabla1[Consistencia Abr/2025],">0",Tabla1[Consistencia Abr/2025]),0) -> 0.8875 | AL9: =IFERROR(AVERAGEIF(Tabla1[Conformidad Abr/2025],">0",Tabla1[Conformidad Abr/2025]),0) -> 0.9625 | AM9: =IFERROR(AVERAGEIF(Tabla1[Completitud May/2025],">0",Tabla1[Completitud May/2025]),0) -> 0.989 | AN9: =IFERROR(AVERAGEIF(Tabla1[Oportunidad May/2025],">0",Tabla1[Oportunidad May/2025]),0) -> 1 | AO9: =IFERROR(AVERAGEIF(Tabla1[Consistencia May/2025],">0",Tabla1[Consistencia May/2025]),0) -> 0.998 | AP9: =IFERROR(AVERAGEIF(Tabla1[Conformidad May/2025],">0",Tabla1[Conformidad May/2025]),0) -> 1 | AQ9: =IFERROR(AVERAGEIF(Tabla1[Completitud Dic/2025],">0",Tabla1[Completitud Dic/2025]),0) -> 0.89792857 | AR9: =IFERROR(AVERAGEIF(Tabla1[Oportunidad Dic/2025],">0",Tabla1[Oportunidad Dic/2025]),0) -> 1 | AS9: =IFERROR(AVERAGEIF(Tabla1[Consistencia Dic/2025],">0",Tabla1[Consistencia Dic/2025]),0) -> 0.88813559 | AT9: =IFERROR(AVERAGEIF(Tabla1[Conformidad Dic/2025],">0",Tabla1[Conformidad Dic/2025]),0) -> 1
B10: Entidades | C10: Completitud Ago/2024 | D10: Oportunidad Ago/2024 | E10: Consistencia Ago/2024 | F10: Conformidad Ago/2024 | G10: Completitud Sep/2024 | H10: Oportunidad Sep/2024 | I10: Consistencia Sep/2024 | J10: Conformidad Sep/2024 | K10: Completitud Oct/2024 | L10: Oportunidad Oct/2024 | M10: Consistencia Oct/2024 | N10: Conformidad Oct/2024 | O10: Completitud Nov/2024 | P10: Oportunidad Nov/2024 | Q10: Consistencia Nov/2024 | R10: Conformidad Nov/2024 | S10: Completitud Dic/2024 | T10: Oportunidad Dic/2024 | U10: Consistencia Dic/2024 | V10: Conformidad Dic/2024 | W10: Completitud Ene/2025 | X10: Oportunidad Ene/2025 | Y10: Consistencia Ene/2025 | Z10: Conformidad Ene/2025 | AA10: Completitud Feb/2025 | AB10: Oportunidad Feb/2025 | AC10: Consistencia Feb/2025 | AD10: Conformidad Feb/2025 | AE10: Completitud Mar/2025 | AF10: Oportunidad Mar/2025 | AG10: Consistencia Mar/2025 | AH10: Conformidad Mar/2025 | AI10: Completitud Abr/2025 | AJ10: Oportunidad Abr/2025 | AK10: Consistencia Abr/2025 | AL10: Conformidad Abr/2025 | AM10: Completitud May/2025 | AN10: Oportunidad May/2025 | AO10: Consistencia May/2025 | AP10: Conformidad May/2025 | AQ10: Completitud Dic/2025 | AR10: Oportunidad Dic/2025 | AS10: Consistencia Dic/2025 | AT10: Conformidad Dic/2025
B11: Oportunidades | C11: 0.7 | D11: 0.94 | E11: 0.9 | F11: 0.4 | G11: 0.7 | H11: 1 | I11: 0.9 | J11: 0.55 | K11: 0.7 | L11: 0.95 | M11: 0.93 | N11: 0.55 | O11: 0.7 | P11: 1 | Q11: 0.95 | R11: 0.85 | S11: 0.7 | T11: 0.95 | U11: 0.995 | V11: 1 | W11: 0.7 | X11: 1 | Y11: 1 | Z11: 1 | AA11: 0.7 | AB11: 1 | AC11: 1 | AD11: 1 | AE11: 0.7 | AF11: 1 | AG11: 1 | AH11: 1 | AI11: 0.7 | AJ11: 1 | AK11: 1 | AL11: 1 | AM11: 0.8 | AN11: 1 | AO11: 1 | AP11: 1 | AQ11: 0.5255 | AR11: 1 | AS11: 1 | AT11: 1
B12: Línea de negocios | C12: 1 | D12: 1 | E12: 1 | F12: 1 | G12: 1 | H12: 1 | I12: 1 | J12: 1 | K12: 1 | L12: 1 | M12: 1 | N12: 1 | O12: 1 | P12: 1 | Q12: 1 | R12: 1 | S12: 1 | T12: 1 | U12: 1 | V12: 1 | W12: 1 | X12: 1 | Y12: 1 | Z12: 1 | AA12: 1 | AB12: 1 | AC12: 1 | AD12: 1 | AE12: 1 | AF12: 1 | AG12: 1 | AH12: 1 | AI12: 1 | AJ12: 1 | AK12: 1 | AL12: 1 | AM12: 1 | AN12: 1 | AO12: 1 | AP12: 1 | AQ12: 1 | AR12: 1 | AS12: 1 | AT12: 1
B13: Equipo de ventas | C13: 1 | D13: 1 | E13: 1 | F13: 1 | G13: 1 | H13: 1 | I13: 1 | J13: 1 | K13: 1 | L13: 1 | M13: 1 | N13: 1 | O13: 1 | P13: 1 | Q13: 1 | R13: 1 | S13: 1 | T13: 1 | U13: 1 | V13: 1 | W13: 1 | X13: 1 | Y13: 1 | Z13: 1 | AA13: 1 | AB13: 1 | AC13: 1 | AD13: 1 | AE13: 1 | AF13: 1 | AG13: 1 | AH13: 1 | AI13: 1 | AJ13: 1 | AK13: 1 | AL13: 1 | AM13: 1 | AN13: 1 | AO13: 1 | AP13: 1 | AQ13: 1 | AR13: 1 | AS13: 1 | AT13: 1
B14: Tipo de cliente | C14: 1 | D14: 1 | E14: 1 | F14: 1 | G14: 1 | H14: 1 | I14: 1 | J14: 1 | K14: 1 | L14: 1 | M14: 1 | N14: 1 | O14: 1 | P14: 1 | Q14: 1 | R14: 1 | S14: 1 | T14: 1 | U14: 1 | V14: 1 | W14: 1 | X14: 1 | Y14: 1 | Z14: 1 | AA14: 1 | AB14: 1 | AC14: 1 | AD14: 1 | AE14: 1 | AF14: 1 | AG14: 1 | AH14: 1 | AI14: 1 | AJ14: 1 | AK14: 1 | AL14: 1 | AM14: 1 | AN14: 1 | AO14: 1 | AP14: 1 | AQ14: 1 | AR14: 1 | AS14: 1 | AT14: 1
B15: Cliente | C15: 0.3 | D15: 1 | E15: 0.9 | F15: 0.3 | G15: 0.3 | H15: 1 | I15: 0.9 | J15: 0.3 | K15: 0.3 | L15: 1 | M15: 0.93 | N15: 0.3 | O15: 0.3 | P15: 1 | Q15: 0.95 | R15: 0.8 | S15: 0.3 | T15: 1 | U15: 0.995 | V15: 1 | W15: 0.3 | X15: 1 | Y15: 1 | Z15: 1 | AA15: 0.3 | AB15: 1 | AC15: 1 | AD15: 1 | AE15: 0.3 | AF15: 1 | AG15: 1 | AH15: 1 | AI15: 0.3 | AJ15: 1 | AK15: 1 | AL15: 1 | AM15: 0.3 | AN15: 1 | AO15: 1 | AP15: 1 | AQ15: 0.354 | AR15: 1 | AS15: 1 | AT15: 1
B16: Tipo de venta | C16: 1 | D16: 1 | E16: 1 | F16: 1 | G16: 1 | H16: 1 | I16: 1 | J16: 1 | K16: 1 | L16: 1 | M16: 1 | N16: 1 | O16: 1 | P16: 1 | Q16: 1 | R16: 1 | S16: 1 | T16: 1 | U16: 1 | V16: 1 | W16: 1 | X16: 1 | Y16: 1 | Z16: 1 | AA16: 1 | AB16: 1 | AC16: 1 | AD16: 1 | AE16: 1 | AF16: 1 | AG16: 1 | AH16: 1 | AI16: 1 | AJ16: 1 | AK16: 1 | AL16: 1 | AM16: 1 | AN16: 1 | AO16: 1 | AP16: 1 | AQ16: 1 | AR16: 1 | AS16: 1 | AT16: 1
B17: Tipo de oportunidad | C17: 1 | D17: 1 | E17: 1 | F17: 1 | G17: 1 | H17: 1 | I17: 1 | J17: 1 | K17: 1 | L17: 1 | M17: 1 | N17: 1 | O17: 1 | P17: 1 | Q17: 1 | R17: 1 | S17: 1 | T17: 1 | U17: 1 | V17: 1 | W17: 1 | X17: 1 | Y17: 1 | Z17: 1 | AA17: 1 | AB17: 1 | AC17: 1 | AD17: 1 | AE17: 1 | AF17: 1 | AG17: 1 | AH17: 1 | AI17: 1 | AJ17: 1 | AK17: 1 | AL17: 1 | AM17: 1 | AN17: 1 | AO17: 1 | AP17: 1 | AQ17: 1 | AR17: 1 | AS17: 1 | AT17: 1
B18: Etapa actual | C18: 1 | D18: 1 | E18: 1 | F18: 1 | G18: 1 | H18: 1 | I18: 1 | J18: 1 | K18: 1 | L18: 1 | M18: 1 | N18: 1 | O18: 1 | P18: 1 | Q18: 1 | R18: 1 | S18: 1 | T18: 1 | U18: 1 | V18: 1 | W18: 1 | X18: 1 | Y18: 1 | Z18: 1 | AA18: 1 | AB18: 1 | AC18: 1 | AD18: 1 | AE18: 1 | AF18: 1 | AG18: 1 | AH18: 1 | AI18: 1 | AJ18: 1 | AK18: 1 | AL18: 1 | AM18: 1 | AN18: 1 | AO18: 1 | AP18: 1 | AQ18: 1 | AR18: 1 | AS18: 1 | AT18: 1
B19: Ganado | C19: 1 | D19: 1 | E19: 1 | F19: 1 | G19: 1 | H19: 1 | I19: 1 | J19: 1 | K19: 1 | L19: 1 | M19: 1 | N19: 1 | O19: 1 | P19: 1 | Q19: 1 | R19: 1 | S19: 1 | T19: 1 | U19: 1 | V19: 1 | W19: 1 | X19: 1 | Y19: 1 | Z19: 1 | AA19: 1 | AB19: 1 | AC19: 1 | AD19: 1 | AE19: 1 | AF19: 1 | AG19: 1 | AH19: 1 | AI19: 1 | AJ19: 1 | AK19: 1 | AL19: 1 | AM19: 1 | AN19: 1 | AO19: 1 | AP19: 1 | AQ19: 1 | AR19: 1 | AS19: 1 | AT19: 1
B20: Metas | C20: 1 | D20: 1 | E20: 1 | F20: 1 | G20: 1 | H20: 1 | I20: 1 | J20: 1 | K20: 1 | L20: 1 | M20: 1 | N20: 1 | O20: 1 | P20: 1 | Q20: 1 | R20: 1 | S20: 1 | T20: 1 | U20: 1 | V20: 1 | W20: 1 | X20: 1 | Y20: 1 | Z20: 1 | AA20: 1 | AB20: 1 | AC20: 1 | AD20: 1 | AE20: 1 | AF20: 1 | AG20: 1 | AH20: 1 | AI20: 1 | AJ20: 1 | AK20: 1 | AL20: 1 | AM20: 1 | AN20: 1 | AO20: 1 | AP20: 1 | AQ20: 1 | AR20: 1 | AS20: 1 | AT20: 1
B21: Metas de Comercial | C21: 1 | D21: 1 | E21: 1 | F21: 1 | G21: 1 | H21: 1 | I21: 1 | J21: 1 | K21: 1 | L21: 1 | M21: 1 | N21: 1 | O21: 1 | P21: 1 | Q21: 1 | R21: 1 | S21: 1 | T21: 1 | U21: 1 | V21: 1 | W21: 1 | X21: 1 | Y21: 1 | Z21: 1 | AA21: 1 | AB21: 1 | AC21: 1 | AD21: 1 | AE21: 1 | AF21: 1 | AG21: 1 | AH21: 1 | AI21: 1 | AJ21: 1 | AK21: 1 | AL21: 1 | AM21: 1 | AN21: 1 | AO21: 1 | AP21: 1 | AQ21: 1 | AR21: 1 | AS21: 1 | AT21: 1
B22: Área | C22: 1 | D22: 1 | E22: 1 | F22: 1 | G22: 1 | H22: 1 | I22: 1 | J22: 1 | K22: 1 | L22: 1 | M22: 1 | N22: 1 | O22: 1 | P22: 1 | Q22: 1 | R22: 1 | S22: 1 | T22: 1 | U22: 1 | V22: 1 | W22: 1 | X22: 1 | Y22: 1 | Z22: 1 | AA22: 1 | AB22: 1 | AC22: 1 | AD22: 1 | AE22: 1 | AF22: 1 | AG22: 1 | AH22: 1 | AI22: 1 | AJ22: 1 | AK22: 1 | AL22: 1 | AM22: 1 | AN22: 1 | AO22: 1 | AP22: 1 | AQ22: 1 | AR22: 1 | AS22: 1 | AT22: 1
... B61: Plan de capacitaciones | C61: 0 | D61: 0 | E61: 0 | F61: 0 | G61: 0 | H61: 0 | I61: 0 | J61: 0 | K61: 0 | L61: 0 | M61: 0 | N61: 0 | O61: 0.72 | P61: 1 | Q61: 0.8 | R61: 0.5 | S61: 0.72 | T61: 1 | U61: 0.8 | V61: 0.7 | W61: 0.9 | X61: 1 | Y61: 0.9 | Z61: 0.9 | AA61: 0.95 | AB61: 1 | AC61: 0.9 | AD61: 1 | AE61: 1 | AF61: 1 | AG61: 0.9 | AH61: 1 | AI61: 1 | AJ61: 1 | AK61: 1 | AL61: 1 | AM61: 1 | AN61: 1 | AO61: 1 | AP61: 1 | AQ61: 1 | AR61: 1 | AS61: 1 | AT61: 1
B62: Ordenes de compras | AI62: 1 | AJ62: 0.4 | AK62: 0.4 | AL62: 0.4 | AM62: 1 | AN62: 1 | AO62: 1 | AP62: 1 | AQ62: 1 | AR62: 1 | AS62: 1 | AT62: 1
B63: Proveedores | AI63: 1 | AJ63: 0.4 | AK63: 0.4 | AL63: 0.4 | AM63: 1 | AN63: 1 | AO63: 1 | AP63: 1 | AQ63: 1 | AR63: 1 | AS63: 1 | AT63: 1
B64: Requisiciones | AI64: 1 | AJ64: 0.4 | AK64: 0.4 | AL64: 0.4 | AM64: 1 | AN64: 1 | AO64: 1 | AP64: 1 | AQ64: 1 | AR64: 1 | AS64: 1 | AT64: 1
B65: Contratos | AI65: 1 | AJ65: 0.4 | AK65: 0.4 | AL65: 1 | AM65: 1 | AN65: 1 | AO65: 1 | AP65: 1 | AQ65: 1 | AR65: 1 | AS65: 1 | AT65: 1
B66: Solicitud de contratación logistica | AI66: 1 | AJ66: 0.4 | AK66: 0.4 | AL66: 1 | AM66: 1 | AN66: 1 | AO66: 1 | AP66: 1 | AQ66: 1 | AR66: 1 | AS66: 1 | AT66: 1
B67: Registro de ahorros | AI67: 1 | AJ67: 0.4 | AK67: 0.4 | AL67: 1 | AM67: 1 | AN67: 1 | AO67: 1 | AP67: 1 | AQ67: 1 | AR67: 1 | AS67: 1 | AT67: 1
B68: Modelo financiero | AM68: 1 | AN68: 1 | AO68: 1 | AP68: 1 | AQ68: 1 | AR68: 1 | AS68: 1 | AT68: 1
B69: Oferta comercial | AQ69: 0.8 | AR69: 1 | AS69: 1 | AT69: 1
B70: Acta | AQ70: 1 | AR70: 1 | AS70: 1 | AT70: 1
B71: Fabricante | AI71: 1 | AJ71: 1 | AK71: 1 | AL71: 1 | AM71: 1 | AN71: 1 | AO71: 1 | AP71: 1 | AQ71: 1 | AR71: 1 | AS71: 1 | AT71: 1
B72: Proceso | AQ72: 0.8 | AR72: 1 | AS72: 1 | AT72: 1
B73: Productos | AQ73: 0.8 | AR73: 1 | AS73: 1 | AT73: 1
B74: Servicio | AI74: 1 | AJ74: 1 | AK74: 1 | AL74: 1 | AM74: 1 | AN74: 1 | AO74: 1 | AP74: 1 | AQ74: 1 | AR74: 1 | AS74: 1 | AT74: 1
B75: Entregable | AQ75: 0.4 | AR75: 1 | AS75: 1 | AT75: 1
B76: Artefacto | AQ76: 0.4 | AR76: 1 | AS76: 1 | AT76: 1
B77: Riesgos y Oportunidades | AQ77: 0.4 | AR77: 1 | AS77: 1 | AT77: 1
B78: Política | AQ78: 0.8 | AR78: 1 | AS78: 1 | AT78: 1
B79: Guía | AQ79: 0.8 | AR79: 1 | AS79: 1 | AT79: 1
B80: Requisitos Norma ISO 9001 | AQ80: 0.4 | AR80: 1 | AS80: 1 | AT80: 1
B81: Salidas no conformes | AQ81: 0.7 | AR81: 1 | AS81: 1 | AT81: 1
B82: Tipo de tratamiento | AM82: 1 | AN82: 1 | AO82: 1 | AP82: 1 | AQ82: 1 | AR82: 1 | AS82: 1 | AT82: 1
B83: Acción correctiva | AM83: 1 | AN83: 1 | AO83: 1 | AP83: 1 | AQ83: 1 | AR83: 1 | AS83: 1 | AT83: 1
B84: Solicitud de acción correctiva | AM84: 1 | AN84: 1 | AO84: 1 | AP84: 1 | AQ84: 1 | AR84: 1 | AS84: 1 | AT84: 1
B85: Plan de tratamiento de riesgos | AQ85: 0 | AR85: 1 | AS85: 0.6 | AT85: 1
B86: Planificación de cambios | AQ86: 0.4 | AR86: 1 | AS86: 0.4 | AT86: 1
B87: Aliado Estratégico | AQ87: 1 | AR87: 1 | AS87: 1 | AT87: 1
B88: Requerimientos de servicios y productos | AQ88: 0.4 | AR88: 1 | AS88: 0.4 | AT88: 1
B89: Términos de referencia | AQ89: 0.4 | AR89: 1 | AS89: 0.4 | AT89: 1
B90: Portafolio de productos y servicios | AQ90: 0.8 | AR90: 1 | AS90: 1 | AT90: 1
B91: Viabilidad Técnica | AQ91: 0 | AR91: 1 | AS91: 0.6 | AT91: 1
B92: Oferta técnica | AQ92: 0 | AR92: 1 | AS92: 0.6 | AT92: 1
B93: Minuta | AQ93: 0.8 | AR93: 1 | AS93: 1 | AT93: 1
B94: Otrosí | AQ94: 0.8 | AR94: 1 | AS94: 1 | AT94: 1
B95: Póliza | AQ95: 1 | AR95: 1 | AS95: 1 | AT95: 1
B96: Ficha del proyecto | AQ96: 0.9 | AR96: 1 | AS96: 1 | AT96: 1
... B100: Procedimiento | AQ100: 0.8 | AR100: 1 | AS100: 1 | AT100: 1
B101: Ventas | C101: 1 | D101: 1 | E101: 1 | F101: 0.4 | G101: 1 | H101: 1 | I101: 1 | J101: 0.55 | K101: 1 | L101: 1 | M101: 1 | N101: 0.55 | O101: 1 | P101: 1 | Q101: 1 | R101: 0.85 | S101: 1 | T101: 1 | U101: 1 | V101: 1 | W101: 1 | X101: 1 | Y101: 1 | Z101: 1 | AA101: 1 | AB101: 1 | AC101: 1 | AD101: 1 | AE101: 1 | AF101: 1 | AG101: 1 | AH101: 1 | AI101: 1 | AJ101: 1 | AK101: 1 | AL101: 1 | AM101: 1 | AN101: 1 | AO101: 1 | AP101: 1 | AQ101: 1 | AR101: 1 | AS101: 1 | AT101: 1
B102: Solicitud de recursos | AQ102: 0.8 | AR102: 1 | AS102: 1 | AT102: 1
B103: Propuesta comercial | AQ103: 0.6 | AR103: 1 | AS103: 0.6 | AT103: 1
B104: Cronograma | AQ104: 1 | AR104: 1 | AS104: 1 | AT104: 1
B105: Pedido de ventas | AQ105: 1 | AR105: 1 | AS105: 1 | AT105: 1
B106: Recurso | AQ106: 0.8 | AR106: 1 | AS106: 1 | AT106: 1
B107: Acuerdo técnico | AQ107: 0.6 | AR107: 1 | AS107: 0.6 | AT107: 1
B108: Acuerdo comercial | AQ108: 0.6 | AR108: 1 | AS108: 0.6 | AT108: 1
B109: Tratamiento de no conforme | AQ109: 0.6 | AR109: 1 | AS109: 0.6 | AT109: 1
B110: Nomenclatura | AQ110: 1 | AR110: 1 | AS110: 1 | AT110: 1
B111: Forecast | C111: 1 | D111: 1 | E111: 1 | F111: 0.4 | G111: 1 | H111: 1 | I111: 1 | J111: 0.55 | K111: 1 | L111: 1 | M111: 1 | N111: 0.55 | O111: 1 | P111: 1 | Q111: 1 | R111: 0.85 | S111: 1 | T111: 1 | U111: 1 | V111: 1 | W111: 1 | X111: 1 | Y111: 1 | Z111: 1 | AA111: 1 | AB111: 1 | AC111: 1 | AD111: 1 | AE111: 1 | AF111: 1 | AG111: 1 | AH111: 1 | AI111: 1 | AJ111: 1 | AK111: 1 | AL111: 1 | AM111: 1 | AN111: 1 | AO111: 1 | AP111: 1 | AQ111: 1 | AR111: 1 | AS111: 1 | AT111: 1
B112: Probabilidad | AQ112: 1 | AR112: 1 | AS112: 1 | AT112: 1
B113: Impacto | AQ113: 0.4 | AR113: 1 | AS113: 0.4 | AT113: 1
B114: Plan de acción | AQ114: 0 | AR114: 1 | AS114: 0.6 | AT114: 1
B115: Conocimiento de persona | AQ115: 0 | AR115: 1 | AS115: 0 | AT115: 1
B116: Clase de vinculación | AQ116: 0.6 | AR116: 1 | AS116: 1 | AT116: 1
B117: Tipo de documento | AQ117: 1 | AR117: 1 | AS117: 1 | AT117: 1
B118: País | AQ118: 1 | AR118: 1 | AS118: 1 | AT118: 1
B119: Normas 9001 - 2015 | AQ119: 1 | AR119: 1 | AS119: 1 | AT119: 1
B120: Auditorías internas | AM120: 1 | AN120: 1 | AO120: 1 | AP120: 1 | AQ120: 1 | AR120: 1 | AS120: 1 | AT120: 1
B121: Gestión de riesgos | AQ121: 0.8 | AR121: 1 | AS121: 0.6 | AT121: 1
B122: Programa | AQ122: 0.8 | AR122: 1 | AS122: 0.6 | AT122: 1
B123: Metodología | AQ123: 0.8 | AR123: 1 | AS123: 1 | AT123: 1
B124: Acción de mejora | AM124: 1 | AN124: 1 | AO124: 1 | AP124: 1 | AQ124: 1 | AR124: 1 | AS124: 1 | AT124: 1
B125: Programa de seguimiento SGC | AM125: 1 | AN125: 1 | AO125: 1 | AP125: 1 | AQ125: 1 | AR125: 1 | AS125: 1 | AT125: 1
B126: Acciones correctivas | AM126: 1 | AN126: 1 | AO126: 1 | AP126: 1 | AQ126: 1 | AR126: 1 | AS126: 1 | AT126: 1
B127: Programa de auditorías | AM127: 1 | AN127: 1 | AO127: 1 | AP127: 1 | AQ127: 1 | AR127: 1 | AS127: 1 | AT127: 1
B128: Banco de Ideas | AQ128: 0.4 | AR128: 1 | AS128: 1 | AT128: 1
B129: Compras | AI129: 1 | AJ129: 0.4 | AK129: 0.4 | AL129: 0.4 | AM129: 1 | AN129: 1 | AO129: 1 | AP129: 1 | AQ129: 1 | AR129: 1 | AS129: 1 | AT129: 1
B130: Contratación | AI130: 1 | AJ130: 0.4 | AK130: 0.4 | AL130: 0.4 | AM130: 1 | AN130: 1 | AO130: 1 | AP130: 1 | AQ130: 1 | AR130: 1 | AS130: 1 | AT130: 1
B131: Evaluación de proveedores | AQ131: 1 | AR131: 1 | AS131: 1 | AT131: 1
B132: Presupuesto del modelo financiero | AQ132: 1 | AR132: 1 | AS132: 1 | AT132: 1
B133: Órden de contratación | AM133: 1 | AN133: 1 | AO133: 1 | AP133: 1 | AQ133: 1 | AR133: 1 | AS133: 1 | AT133: 1
B134: Inventario | AQ134: 0.4 | AR134: 1 | AS134: 1 | AT134: 1
B135: Evaluación de Sagrilaft | AQ135: 1 | AR135: 1 | AS135: 1 | AT135: 1
B136: Solicitud para anexo y Otrosí | AI136: 1 | AJ136: 0.4 | AK136: 0.4 | AL136: 1 | AM136: 1 | AN136: 1 | AO136: 1 | AP136: 1 | AQ136: 1 | AR136: 1 | AS136: 1 | AT136: 1
B137: Solicitud para Acuerdo Marco | AQ137: 0.6 | AR137: 1 | AS137: 0.6 | AT137: 1
B138: Recibido a conformidad proveedores | AQ138: 0.7 | AR138: 1 | AS138: 1 | AT138: 1
B139: Sagrilaft persona | AQ139: 0.7 | AR139: 1 | AS139: 1 | AT139: 1
B140: Movimiento de inventario | AQ140: 0 | AR140: 1 | AS140: 0.4 | AT140: 1
B141: Activos fijos | AQ141: 0.7 | AR141: 1 | AS141: 1 | AT141: 1
...

Sheet Uso-Acceso Datos
B1: Se realiza sobre las entidades identificadas en los procesos
C2: Uso y acceso | D2: Uso y acceso | E2: Uso y acceso | F2: Uso y acceso | G2: Uso y acceso | H2: Uso y acceso | I2: Uso y acceso | J2: Uso y acceso | K2: Uso y acceso | L2: Uso y acceso | M2: Uso y acceso
C3: 1 | D3: 2 | E3: 3 | F3: 4 | G3: 5 | H3: 6 | I3: 7 | J3: 8 | K3: 9 | L3: 10 | M3: 17
C4: =SUMIF(C7:C244,">0")/COUNTIF(C7:C244,">0") -> 0.88676471 | D4: =SUMIF(D7:D244,">0")/COUNTIF(D7:D244,">0") -> 0.88872549 | E4: =SUMIF(E7:E244,">0")/COUNTIF(E7:E244,">0") -> 0.95097087 | F4: =SUMIF(F7:F244,">0")/COUNTIF(F7:F244,">0") -> 0.95376214 | G4: =SUMIF(G7:G244,">0")/COUNTIF(G7:G244,">0") -> 0.96696602 | H4: =SUMIF(H7:H244,">0")/COUNTIF(H7:H244,">0") -> 0.96696602 | I4: =SUMIF(I7:I244,">0")/COUNTIF(I7:I244,">0") -> 0.96854762 | J4: =SUMIF(J7:J244,">0")/COUNTIF(J7:J244,">0") -> 0.96854762 | ... M4: =SUMIF(M7:M244,">0")/COUNTIF(M7:M244,">0") -> 0.99196203
C5: =AVERAGE(Tabla13[Uso y acceso Ago/2024]) -> 0.86971154 | D5: =AVERAGE(Tabla13[Uso y acceso Sep/2024]) -> 0.87163462 | E5: =AVERAGE(Tabla13[Uso y acceso Oct/2024]) -> 0.94182692 | F5: =AVERAGE(Tabla13[Uso y acceso Nov/2024]) -> 0.94459135 | G5: =AVERAGE(Tabla13[Uso y acceso Dic/2024]) -> 0.95766827 | H5: =AVERAGE(Tabla13[Uso y acceso Ene/2025]) -> 0.95766827 | I5: =AVERAGE(Tabla13[Uso y acceso Feb/2025]) -> 0.95941038 | J5: =AVERAGE(Tabla13[Uso y acceso Mar/2025]) -> 0.95941038 | K5: =AVERAGE(Tabla13[Uso y acceso Abr/2025]) -> 0.96052752 | L5: =AVERAGE(Tabla13[Uso y acceso May/2025]) -> 0.97845291 | M5: =AVERAGE(Tabla13[Uso y acceso Dic/2025]) -> 0.98779412
B6: Entidades | C6: Uso y acceso Ago/2024 | D6: Uso y acceso Sep/2024 | E6: Uso y acceso Oct/2024 | F6: Uso y acceso Nov/2024 | G6: Uso y acceso Dic/2024 | H6: Uso y acceso Ene/2025 | I6: Uso y acceso Feb/2025 | J6: Uso y acceso Mar/2025 | K6: Uso y acceso Abr/2025 | L6: Uso y acceso May/2025 | M6: Uso y acceso Dic/2025
B7: Oportunidades | C7: 1 | D7: 1 | E7: 1 | F7: 1 | G7: 1 | H7: 1 | I7: 1 | J7: 1 | K7: 1 | L7: 1 | M7: 1
B8: Línea de negocios | C8: 1 | D8: 1 | E8: 1 | F8: 1 | G8: 1 | H8: 1 | I8: 1 | J8: 1 | K8: 1 | L8: 1 | M8: 1
B9: Equipo de ventas | C9: 1 | D9: 1 | E9: 1 | F9: 1 | G9: 1 | H9: 1 | I9: 1 | J9: 1 | K9: 1 | L9: 1 | M9: 1
B10: Tipo de cliente | C10: 1 | D10: 1 | E10: 1 | F10: 1 | G10: 1 | H10: 1 | I10: 1 | J10: 1 | K10: 1 | L10: 1 | M10: 1
B11: Cliente | C11: 1 | D11: 1 | E11: 1 | F11: 1 | G11: 1 | H11: 1 | I11: 1 | J11: 1 | K11: 1 | L11: 1 | M11: 1
B12: Tipo de venta | C12: 1 | D12: 1 | E12: 1 | F12: 1 | G12: 1 | H12: 1 | I12: 1 | J12: 1 | K12: 1 | L12: 1 | M12: 1
B13: Tipo de oportunidad | C13: 1 | D13: 1 | E13: 1 | F13: 1 | G13: 1 | H13: 1 | I13: 1 | J13: 1 | K13: 1 | L13: 1 | M13: 1
B14: Etapa actual | C14: 1 | D14: 1 | E14: 1 | F14: 1 | G14: 1 | H14: 1 | I14: 1 | J14: 1 | K14: 1 | L14: 1 | M14: 1
B15: Ganado | C15: 1 | D15: 1 | E15: 1 | F15: 1 | G15: 1 | H15: 1 | I15: 1 | J15: 1 | K15: 1 | L15: 1 | M15: 1
B16: Metas | C16: 1 | D16: 1 | E16: 1 | F16: 1 | G16: 1 | H16: 1 | I16: 1 | J16: 1 | K16: 1 | L16: 1 | M16: 1
B17: Metas de Comercial | C17: 1 | D17: 1 | E17: 1 | F17: 1 | G17: 1 | H17: 1 | I17: 1 | J17: 1 | K17: 1 | L17: 1 | M17: 1
B18: Área | C18: 1 | D18: 1 | E18: 1 | F18: 1 | G18: 1 | H18: 1 | I18: 1 | J18: 1 | K18: 1 | L18: 1 | M18: 1
... B214: Hallazgos | C214: 1 | D214: 1 | E214: 1 | F214: 1 | G214: 1 | H214: 1 | I214: 1 | J214: 1 | K214: 1 | L214: 1 | M214: 1
B215: Tipo de retiro | I215: 1 | J215: 1 | K215: 1 | L215: 1 | M215: 1
B216: Tipo de movimiento laboral | I216: 1 | J216: 1 | K216: 1 | L216: 1 | M216: 1
B217: Tipo de fuero | I217: 1 | J217: 1 | K217: 1 | L217: 1 | M217: 1
B218: Generación por año de nacimiento | I218: 1 | J218: 1 | K218: 1 | L218: 1 | M218: 1
B219: Identificación del proceso | K219: 1 | L219: 1 | M219: 1
B220: Modalidad de contratación | K220: 1 | L220: 1 | M220: 1
B221: Sector | K221: 1 | L221: 1 | M221: 1
B222: Subsector | K222: 1 | L222: 1 | M222: 1
B223: Orden de servicio | K223: 1 | L223: 1 | M223: 1
B224: Orden de trabajo | K224: 1 | L224: 1 | M224: 1
B225: Categoría servicios TI | L225: 1 | M225: 1
B226: Servicios TI | L226: 1 | M226: 1
B227: Control de acceso | L227: 1 | M227: 1
B228: Evento | L228: 1 | M228: 1
B229: Canales digitales | L229: 1 | M229: 1
B230: Medio de solicitud a doit | M230: 1
B231: Prioridad del Ticket | M231: 1
B232: Naturaleza del caso | M232: 1
B233: Estados de los tickets TI | M233: 1
B234: Estado orden de servicio | M234: 1
B235: Canal de recepción | M235: 1
B236: Canal de comunicación | M236: 1
B237: Tipo de entregable | M237: 1
B238: Segmentación Proyectos | M238: 1
B239: Rubros del Modelo Financiero | M239: 1
B240: Subrubros del Modelo Financiero | M240: 1
B241: Rubros del Presupuesto General | M241: 1
... B244: Área Financiera | M244: 1

Sheet Integracion-Flujo Datos
B1: Se realiza sobre las entidades identificadas en los procesos
C2: Integración | D2: Integración | E2: Integración | F2: Integración | G2: Integración | H2: Integración | I2: Integración | J2: Integración | K2: Integración | L2: Integración | M2: Integración
C3: 1 | D3: 2 | E3: 3 | F3: 4 | G3: 5 | H3: 6 | I3: 7 | J3: 8 | K3: 9 | L3: 10 | M3: 17
C4: =SUMIF(C7:C244,">0")/COUNTIF(C7:C244,">0") -> 0.98684211 | D4: =SUMIF(D7:D244,">0")/COUNTIF(D7:D244,">0") -> 0.96666667 | E4: =SUMIF(E7:E244,">0")/COUNTIF(E7:E244,">0") -> 0.79901961 | F4: =SUMIF(F7:F244,">0")/COUNTIF(F7:F244,">0") -> 0.86923077 | G4: =SUMIF(G7:G244,">0")/COUNTIF(G7:G244,">0") -> 0.98867925 | H4: =SUMIF(H7:H244,">0")/COUNTIF(H7:H244,">0") -> 0.98333333 | I4: =SUMIF(I7:I244,">0")/COUNTIF(I7:I244,">0") -> 0.94090909 | J4: =SUMIF(J7:J244,">0")/COUNTIF(J7:J244,">0") -> 0.94090909 | ... M4: =SUMIF(M7:M244,">0")/COUNTIF(M7:M244,">0") -> 0.80042017
C5: =AVERAGE(Tabla58[Integración Ago/2024]) -> 0.18028846 | D5: =AVERAGE(Tabla58[Integración Sep/2024]) -> 0.18125 | E5: =AVERAGE(Tabla58[Integración Oct/2024]) -> 0.19591346 | F5: =AVERAGE(Tabla58[Integración Nov/2024]) -> 0.21730769 | G5: =AVERAGE(Tabla58[Integración Dic/2024]) -> 0.25192308 | H5: =AVERAGE(Tabla58[Integración Ene/2025]) -> 0.25528846 | I5: =AVERAGE(Tabla58[Integración Feb/2025]) -> 0.29292453 | J5: =AVERAGE(Tabla58[Integración Mar/2025]) -> 0.29292453 | K5: =AVERAGE(Tabla58[Integración Abr/2025]) -> 0.32981651 | L5: =AVERAGE(Tabla58[Integración May/2025]) -> 0.34394619 | M5: =AVERAGE(Tabla58[Integración Dic/2025]) -> 0.80042017
B6: Entidades | C6: Integración Ago/2024 | D6: Integración Sep/2024 | E6: Integración Oct/2024 | F6: Integración Nov/2024 | G6: Integración Dic/2024 | H6: Integración Ene/2025 | I6: Integración Feb/2025 | J6: Integración Mar/2025 | K6: Integración Abr/2025 | L6: Integración May/2025 | M6: Integración Dic/2025
B7: Oportunidades | C7: 1 | D7: 1 | E7: 1 | F7: 1 | G7: 1 | H7: 1 | I7: 1 | J7: 1 | K7: 1 | L7: 1 | M7: 1
B8: Línea de negocios | C8: 1 | D8: 1 | E8: 1 | F8: 1 | G8: 1 | H8: 1 | I8: 1 | J8: 1 | K8: 1 | L8: 1 | M8: 1
B9: Equipo de ventas | C9: 1 | D9: 1 | E9: 1 | F9: 1 | G9: 1 | H9: 1 | I9: 1 | J9: 1 | K9: 1 | L9: 1 | M9: 1
B10: Tipo de cliente | C10: 1 | D10: 1 | E10: 1 | F10: 1 | G10: 1 | H10: 1 | I10: 1 | J10: 1 | K10: 1 | L10: 1 | M10: 1
B11: Cliente | C11: 1 | D11: 1 | E11: 1 | F11: 1 | G11: 1 | H11: 1 | I11: 1 | J11: 1 | K11: 1 | L11: 1 | M11: 1
B12: Tipo de venta | C12: 1 | D12: 1 | E12: 1 | F12: 1 | G12: 1 | H12: 1 | I12: 1 | J12: 1 | K12: 1 | L12: 1 | M12: 1
B13: Tipo de oportunidad | C13: 1 | D13: 1 | E13: 1 | F13: 1 | G13: 1 | H13: 1 | I13: 1 | J13: 1 | K13: 1 | L13: 1 | M13: 1
B14: Etapa actual | C14: 1 | D14: 1 | E14: 1 | F14: 1 | G14: 1 | H14: 1 | I14: 1 | J14: 1 | K14: 1 | L14: 1 | M14: 1
B15: Ganado | C15: 1 | D15: 1 | E15: 1 | F15: 1 | G15: 1 | H15: 1 | I15: 1 | J15: 1 | K15: 1 | L15: 1 | M15: 1
B16: Metas | C16: 1 | D16: 1 | E16: 1 | F16: 1 | G16: 1 | H16: 1 | I16: 1 | J16: 1 | K16: 1 | L16: 1 | M16: 1
B17: Metas de Comercial | C17: 1 | D17: 1 | E17: 1 | F17: 1 | G17: 1 | H17: 1 | I17: 1 | J17: 1 | K17: 1 | L17: 1 | M17: 1
B18: Área | C18: 1 | D18: 1 | E18: 1 | F18: 1 | G18: 1 | H18: 1 | I18: 1 | J18: 1 | K18: 1 | L18: 1 | M18: 1
... B214: Hallazgos | C214: 0 | D214: 0 | E214: 0 | F214: 0 | G214: 0 | H214: 0 | I214: 0 | J214: 0 | K214: 0 | L214: 0.3 | M214: 0.6
B215: Tipo de retiro | I215: 1 | J215: 1 | K215: 1 | L215: 1 | M215: 1
B216: Tipo de movimiento laboral | I216: 1 | J216: 1 | K216: 1 | L216: 1 | M216: 1
B217: Tipo de fuero | I217: 1 | J217: 1 | K217: 1 | L217: 1 | M217: 1
B218: Generación por año de nacimiento | I218: 1 | J218: 1 | K218: 1 | L218: 1 | M218: 1
B219: Identificación del proceso | K219: 1 | L219: 1 | M219: 1
B220: Modalidad de contratación | K220: 1 | L220: 1 | M220: 1
B221: Sector | K221: 1 | L221: 1 | M221: 1
B222: Subsector | K222: 1 | L222: 1 | M222: 1
B223: Orden de servicio | K223: 0.3 | L223: 0.3 | M223: 0.8
B224: Orden de trabajo | K224: 0.3 | L224: 0.3 | M224: 0.8
B225: Categoría servicios TI | L225: 0.3 | M225: 1
B226: Servicios TI | L226: 0.3 | M226: 1
B227: Control de acceso | L227: 0.3 | M227: 0.8
B228: Evento | L228: 0.3 | M228: 0.8
B229: Canales digitales | L229: 0.3 | M229: 1
B230: Medio de solicitud a doit | M230: 1
B231: Prioridad del Ticket | M231: 1
B232: Naturaleza del caso | M232: 1
B233: Estados de los tickets TI | M233: 1
B234: Estado orden de servicio | M234: 1
B235: Canal de recepción | M235: 1
B236: Canal de comunicación | M236: 1
B237: Tipo de entregable | M237: 1
B238: Segmentación Proyectos | M238: 1
B239: Rubros del Modelo Financiero | M239: 1
B240: Subrubros del Modelo Financiero | M240: 1
B241: Rubros del Presupuesto General | M241: 1
... B244: Área Financiera | M244: 1

Sheet Gestion Ciclo-Vida Datos
B1: Se realiza sobre las entidades identificadas en los procesos. Esta definido por los indicadores Calidad de datos, Uso-Acceso Datos, Integración-Flujo de datos; adicional a estos Creación y captura, Almacenamiento y registro
C2: Creación y Captura | D2: Almacenamiento y Registro | E2: Calidad de datos | F2: Uso y acceso | G2: Compartición e Interoperabilidad | H2: Gestión ciclo de Vida | I2: Creación y Captura | J2: Almacenamiento y Registro | K2: Calidad de datos | L2: Uso y acceso | M2: Compartición e Interoperabilidad | N2: Gestión ciclo de Vida | O2: Creación y Captura | P2: Almacenamiento y Registro | Q2: Calidad de datos | R2: Uso y acceso | S2: Compartición e Interoperabilidad | T2: Gestión ciclo de Vida | U2: Creación y Captura | V2: Almacenamiento y Registro | W2: Calidad de datos | X2: Uso y acceso | Y2: Compartición e Interoperabilidad | Z2: Gestión ciclo de Vida | AA2: Creación y Captura | AB2: Almacenamiento y Registro | AC2: Calidad de datos | AD2: Uso y acceso | AE2: Compartición e Interoperabilidad | AF2: Gestión ciclo de Vida | AG2: Creación y Captura | AH2: Almacenamiento y Registro | AI2: Calidad de datos | AJ2: Uso y acceso | AK2: Compartición e Interoperabilidad | AL2: Gestión ciclo de Vida | AM2: Creación y Captura | AN2: Almacenamiento y Registro | AO2: Calidad de datos | AP2: Uso y acceso | AQ2: Compartición e Interoperabilidad | AR2: Gestión ciclo de Vida | AS2: Creación y Captura | AT2: Almacenamiento y Registro | AU2: Calidad de datos | AV2: Uso y acceso | AW2: Compartición e Interoperabilidad | AX2: Gestión ciclo de Vida | AY2: Creación y Captura | AZ2: Almacenamiento y Registro | BA2: Calidad de datos | BB2: Uso y acceso | BC2: Compartición e Interoperabilidad | BD2: Gestión ciclo de Vida | BE2: Creación y Captura | BF2: Almacenamiento y Registro | BG2: Calidad de datos | BH2: Uso y acceso | BI2: Compartición e Interoperabilidad | BJ2: Gestión ciclo de Vida | BK2: Creación y Captura | BL2: Almacenamiento y Registro | BM2: Calidad de datos | BN2: Uso y acceso | BO2: Compartición e Interoperabilidad | BP2: Gestión ciclo de Vida
C3: 1 | D3: 1 | E3: 1 | F3: 1 | G3: 1 | H3: 1 | I3: 2 | J3: 2 | K3: 2 | L3: 2 | M3: 2 | N3: 2 | O3: 3 | P3: 3 | Q3: 3 | R3: 3 | S3: 3 | T3: 3 | U3: 4 | V3: 4 | W3: 4 | X3: 4 | Y3: 4 | Z3: 4 | AA3: 5 | AB3: 5 | AC3: 5 | AD3: 5 | AE3: 5 | AF3: 5 | AG3: 6 | AH3: 6 | AI3: 6 | AJ3: 6 | AK3: 6 | AL3: 6 | AM3: 7 | AN3: 7 | AO3: 7 | AP3: 7 | AQ3: 7 | AR3: 7 | AS3: 8 | AT3: 8 | AU3: 8 | AV3: 8 | AW3: 8 | AX3: 8 | AY3: 9 | AZ3: 9 | BA3: 9 | BB3: 9 | BC3: 9 | BD3: 9 | BE3: 10 | BF3: 10 | BG3: 10 | BH3: 10 | BI3: 10 | BJ3: 10 | BK3: 17 | BL3: 17 | BM3: 17 | BN3: 17 | BO3: 17 | BP3: 17
C4: =SUMIF(C7:C244,">0")/COUNTIF(C7:C244,">0") -> 0.99605263 | D4: =SUMIF(D7:D244,">0")/COUNTIF(D7:D244,">0") -> 0.98684211 | E4: =SUMIF(E7:E244,">0")/COUNTIF(E7:E244,">0") -> 0.93565789 | F4: =SUMIF(F7:F244,">0")/COUNTIF(F7:F244,">0") -> 0.88676471 | G4: =SUMIF(G7:G244,">0")/COUNTIF(G7:G244,">0") -> 0.98684211 | H4: =SUMIF(H7:H244,">0")/COUNTIF(H7:H244,">0") -> 0.52703105 | I4: =SUMIF(I7:I244,">0")/COUNTIF(I7:I244,">0") -> 0.97948718 | J4: =SUMIF(J7:J244,">0")/COUNTIF(J7:J244,">0") -> 0.96666667 | ... BP4: =SUMIF(BP7:BP244,">0")/COUNTIF(BP7:BP244,">0") -> 0.88886754
C5: =IFERROR(AVERAGEIF(Tabla4[Creación y captura Ago/2024],">0",Tabla4[Creación y captura Ago/2024]),0) -> 0.99605263 | D5: =IFERROR(AVERAGEIF(Tabla4[Almacenamiento y registro Ago/2024],">0",Tabla4[Almacenamiento y registro Ago/2024]),0) -> 0.98684211 | E5: =IFERROR(AVERAGEIF(Tabla4[Calidad de datos Ago/2024],">0",Tabla4[Calidad de datos Ago/2024]),0) -> 0.93565789 | F5: =AVERAGE(Tabla4[Uso y acceso Ago/2024]) -> 0.76008403 | G5: =AVERAGE(Tabla4[Compartición e Interoperabilidad Ago/2024]) -> 0.15756303 | H5: =AVERAGE(C5:G5) -> 0.76723994 | I5: =IFERROR(AVERAGEIF(Tabla4[Creación y captura Sep/2024],">0",Tabla4[Creación y captura Sep/2024]),0) -> 0.97948718 | J5: =IFERROR(AVERAGEIF(Tabla4[Almacenamiento y registro Sep/2024],">0",Tabla4[Almacenamiento y registro Sep/2024]),0) -> 0.96666667 | K5: =IFERROR(AVERAGEIF(Tabla4[Calidad de datos Sep/2024],">0",Tabla4[Calidad de datos Sep/2024]),0) -> 0.94888158 | L5: =AVERAGE(Tabla4[Uso y acceso Sep/2024]) -> 0.76176471 | M5: =AVERAGE(Tabla4[Compartición e Interoperabilidad Sep/2024]) -> 0.15840336 | N5: =AVERAGE(I5:M5) -> 0.7630407 | O5: =IFERROR(AVERAGEIF(Tabla4[Creación y captura Oct/2024],">0",Tabla4[Creación y captura Oct/2024]),0) -> 0.86666667 | P5: =IFERROR(AVERAGEIF(Tabla4[Almacenamiento y registro Oct/2024],">0",Tabla4[Almacenamiento y registro Oct/2024]),0) -> 0.79901961 | Q5: =IFERROR(AVERAGEIF(Tabla4[Calidad de datos Oct/2024],">0",Tabla4[Calidad de datos Oct/2024]),0) -> 0.94888158 | R5: =AVERAGE(Tabla4[Uso y acceso Oct/2024]) -> 0.82310924 | S5: =AVERAGE(Tabla4[Compartición e Interoperabilidad Oct/2024]) -> 0.17121849 | T5: =AVERAGE(O5:S5) -> 0.72177912 | U5: =IFERROR(AVERAGEIF(Tabla4[Creación y captura Nov/2024],">0",Tabla4[Creación y captura Nov/2024]),0) -> 0.96785714 | V5: =IFERROR(AVERAGEIF(Tabla4[Almacenamiento y registro Nov/2024],">0",Tabla4[Almacenamiento y registro Nov/2024]),0) -> 0.91730769 | W5: =IFERROR(AVERAGEIF(Tabla4[Calidad de datos Nov/2024],">0",Tabla4[Calidad de datos Nov/2024]),0) -> 0.94982143 | X5: =AVERAGE(Tabla4[Uso y acceso Nov/2024]) -> 0.82552521 | Y5: =AVERAGE(Tabla4[Compartición e Interoperabilidad Nov/2024]) -> 0.18991597 | Z5: =AVERAGE(U5:Y5) -> 0.77008549 | AA5: =IFERROR(AVERAGEIF(Tabla4[Creación y captura Dic/2024],">0",Tabla4[Creación y captura Dic/2024]),0) -> 0.97142857 | AB5: =IFERROR(AVERAGEIF(Tabla4[Almacenamiento y registro Dic/2024],">0",Tabla4[Almacenamiento y registro Dic/2024]),0) -> 0.98867925 | AC5: =IFERROR(AVERAGEIF(Tabla4[Calidad de datos Dic/2024],">0",Tabla4[Calidad de datos Dic/2024]),0) -> 0.96267857 | AD5: =AVERAGE(Tabla4[Uso y acceso Dic/2024]) -> 0.83695378 | AE5: =AVERAGE(Tabla4[Compartición e Interoperabilidad Dic/2024]) -> 0.22016807 | AF5: =AVERAGE(AA5:AE5) -> 0.79598165 | AG5: =IFERROR(AVERAGEIF(Tabla4[Creación y captura Ene/2025],">0",Tabla4[Creación y captura Ene/2025]),0) -> 0.98571429 | AH5: =IFERROR(AVERAGEIF(Tabla4[Almacenamiento y registro Ene/2025],">0",Tabla4[Almacenamiento y registro Ene/2025]),0) -> 0.98611111 | AI5: =IFERROR(AVERAGEIF(Tabla4[Calidad de datos Ene/2025],">0",Tabla4[Calidad de datos Ene/2025]),0) -> 0.97705357 | AJ5: =AVERAGE(Tabla4[Uso y acceso Ene/2025]) -> 0.83695378 | AK5: =AVERAGE(Tabla4[Compartición e Interoperabilidad Ene/2025]) -> 0.22310924 | AL5: =AVERAGE(AG5:AK5) -> 0.8017884 | AM5: =IFERROR(AVERAGEIF(Tabla4[Creación y captura Feb/2025],">0",Tabla4[Creación y captura Feb/2025]),0) -> 0.98934426 | AN5: =IFERROR(AVERAGEIF(Tabla4[Almacenamiento y registro Feb/2025],">0",Tabla4[Almacenamiento y registro Feb/2025]),0) -> 0.99344262 | AO5: =IFERROR(AVERAGEIF(Tabla4[Calidad de datos Feb/2025],">0",Tabla4[Calidad de datos Feb/2025]),0) -> 0.98616667 | AP5: =AVERAGE(Tabla4[Uso y acceso Feb/2025]) -> 0.85460084 | AQ5: =AVERAGE(Tabla4[Compartición e Interoperabilidad Feb/2025]) -> 0.26092437 | AR5: =AVERAGE(AM5:AQ5) -> 0.81689575 | AS5: =IFERROR(AVERAGEIF(Tabla4[Creación y captura Mar/2025],">0",Tabla4[Creación y captura Mar/2025]),0) -> 0.99166667 | AT5: =IFERROR(AVERAGEIF(Tabla4[Almacenamiento y registro Mar/2025],">0",Tabla4[Almacenamiento y registro Mar/2025]),0) -> 1 | AU5: =IFERROR(AVERAGEIF(Tabla4[Calidad de datos Mar/2025],">0",Tabla4[Calidad de datos Mar/2025]),0) -> 0.98679167 | AV5: =AVERAGE(Tabla4[Uso y acceso Mar/2025]) -> 0.85460084 | AW5: =AVERAGE(Tabla4[Compartición e Interoperabilidad Mar/2025]) -> 0.26092437 | AX5: =AVERAGE(AS5:AW5) -> 0.81879671 | AY5: =IFERROR(AVERAGEIF(Tabla4[Creación y captura Abr/2025],">0",Tabla4[Creación y captura Abr/2025]),0) -> 0.9575 | AZ5: =IFERROR(AVERAGEIF(Tabla4[Almacenamiento y registro Abr/2025],">0",Tabla4[Almacenamiento y registro Abr/2025]),0) -> 0.9025 | BA5: =IFERROR(AVERAGEIF(Tabla4[Calidad de datos Abr/2025],">0",Tabla4[Calidad de datos Abr/2025]),0) -> 0.93965625 | BB5: =AVERAGE(Tabla4[Uso y acceso Abr/2025]) -> 0.87981092 | BC5: =AVERAGE(Tabla4[Compartición e Interoperabilidad Abr/2025]) -> 0.30210084 | BD5: =AVERAGE(AY5:BC5) -> 0.7963136 | BE5: =IFERROR(AVERAGEIF(Tabla4[Creación y captura May/2025],">0",Tabla4[Creación y captura May/2025]),0) -> 0.927 | BF5: =IFERROR(AVERAGEIF(Tabla4[Almacenamiento y registro May/2025],">0",Tabla4[Almacenamiento y registro May/2025]),0) -> 0.837 | BG5: =IFERROR(AVERAGEIF(Tabla4[Calidad de datos May/2025],">0",Tabla4[Calidad de datos May/2025]),0) -> 0.996875 | BH5: =AVERAGE(Tabla4[Uso y acceso May/2025]) -> 0.91678571 | BI5: =AVERAGE(Tabla4[Compartición e Interoperabilidad May/2025]) -> 0.32226891 | BJ5: =AVERAGE(BE5:BI5) -> 0.79998592 | BK5: =IFERROR(AVERAGEIF(Tabla4[Creación y captura Dic/2025],">0",Tabla4[Creación y captura Dic/2025]),0) -> 0.95766423 | BL5: =IFERROR(AVERAGEIF(Tabla4[Almacenamiento y registro Dic/2025],">0",Tabla4[Almacenamiento y registro Dic/2025]),0) -> 0.90510949 | BM5: =IFERROR(AVERAGEIF(Tabla4[Calidad de datos Dic/2025],">0",Tabla4[Calidad de datos Dic/2025]),0) -> 0.91163813 | BN5: =AVERAGE(Tabla4[Uso y acceso Dic/2025]) -> 0.98779412 | BO5: =AVERAGE(Tabla4[Compartición e Interoperabilidad Dic/2025]) -> 0.80042017 | BP5: =AVERAGE(BK5:BO5) -> 0.91252523
B6: Entidades | C6: Creación y captura Ago/2024 | D6: Almacenamiento y registro Ago/2024 | E6: Calidad de datos Ago/2024 | F6: Uso y acceso Ago/2024 | G6: Compartición e Interoperabilidad Ago/2024 | H6: Gestión ciclo de Vida Ago/2024 | I6: Creación y captura Sep/2024 | J6: Almacenamiento y registro Sep/2024 | K6: Calidad de datos Sep/2024 | L6: Uso y acceso Sep/2024 | M6: Compartición e Interoperabilidad Sep/2024 | N6: Gestión ciclo de Vida Sep/2024 | O6: Creación y captura Oct/2024 | P6: Almacenamiento y registro Oct/2024 | Q6: Calidad de datos Oct/2024 | R6: Uso y acceso Oct/2024 | S6: Compartición e Interoperabilidad Oct/2024 | T6: Gestión ciclo de Vida Oct/2024 | U6: Creación y captura Nov/2024 | V6: Almacenamiento y registro Nov/2024 | W6: Calidad de datos Nov/2024 | X6: Uso y acceso Nov/2024 | Y6: Compartición e Interoperabilidad Nov/2024 | Z6: Gestión ciclo de Vida Nov/2024 | AA6: Creación y captura Dic/2024 | AB6: Almacenamiento y registro Dic/2024 | AC6: Calidad de datos Dic/2024 | AD6: Uso y acceso Dic/2024 | AE6: Compartición e Interoperabilidad Dic/2024 | AF6: Gestión ciclo de Vida Dic/2024 | AG6: Creación y captura Ene/2025 | AH6: Almacenamiento y registro Ene/2025 | AI6: Calidad de datos Ene/2025 | AJ6: Uso y acceso Ene/2025 | AK6: Compartición e Interoperabilidad Ene/2025 | AL6: Gestión ciclo de Vida Ene/2025 | AM6: Creación y captura Feb/2025 | AN6: Almacenamiento y registro Feb/2025 | AO6: Calidad de datos Feb/2025 | AP6: Uso y acceso Feb/2025 | AQ6: Compartición e Interoperabilidad Feb/2025 | AR6: Gestión ciclo de Vida Feb/2025 | AS6: Creación y captura Mar/2025 | AT6: Almacenamiento y registro Mar/2025 | AU6: Calidad de datos Mar/2025 | AV6: Uso y acceso Mar/2025 | AW6: Compartición e Interoperabilidad Mar/2025 | AX6: Gestión ciclo de Vida Mar/2025 | AY6: Creación y captura Abr/2025 | AZ6: Almacenamiento y registro Abr/2025 | BA6: Calidad de datos Abr/2025 | BB6: Uso y acceso Abr/2025 | BC6: Compartición e Interoperabilidad Abr/2025 | BD6: Gestión ciclo de Vida Abr/2025 | BE6: Creación y captura May/2025 | BF6: Almacenamiento y registro May/2025 | BG6: Calidad de datos May/2025 | BH6: Uso y acceso May/2025 | BI6: Compartición e Interoperabilidad May/2025 | BJ6: Gestión ciclo de Vida May/2025 | BK6: Creación y captura Dic/2025 | BL6: Almacenamiento y registro Dic/2025 | BM6: Calidad de datos Dic/2025 | BN6: Uso y acceso Dic/2025 | BO6: Compartición e Interoperabilidad Dic/2025 | BP6: Gestión ciclo de Vida Dic/2025
B7: Oportunidades | C7: 1 | D7: 1 | E7: =AVERAGE('Calidad de Datos'!C11:F11) -> 0.735 | F7: =Tabla13[[#This Row],[Uso y acceso Ago/2024]] -> 1 | G7: =Tabla58[[#This Row],[Integración Ago/2024]] -> 1 | H7: =AVERAGE(Tabla4[[#This Row],[Creación y captura Ago/2024]:[Compartición e Interoperabilidad Ago/2024]]) -> 0.947 | I7: 1 | J7: 1 | K7: =AVERAGE('Calidad de Datos'!G11:J11) -> 0.7875 | L7: =Tabla13[[#This Row],[Uso y acceso Sep/2024]] -> 1 | M7: =Tabla58[[#This Row],[Integración Sep/2024]] -> 1 | N7: =AVERAGE(Tabla4[[#This Row],[Creación y captura Sep/2024]:[Compartición e Interoperabilidad Sep/2024]]) -> 0.9575 | O7: 1 | P7: 1 | Q7: =AVERAGE('Calidad de Datos'!K11:N11) -> 0.7825 | R7: =Tabla13[[#This Row],[Uso y acceso Oct/2024]] -> 1 | S7: =Tabla58[[#This Row],[Integración Oct/2024]] -> 1 | T7: =AVERAGE(Tabla4[[#This Row],[Creación y captura Oct/2024]:[Compartición e Interoperabilidad Oct/2024]]) -> 0.9565 | U7: 1 | V7: 1 | W7: =AVERAGE('Calidad de Datos'!O11:R11) -> 0.875 | X7: =Tabla13[[#This Row],[Uso y acceso Nov/2024]] -> 1 | Y7: =Tabla58[[#This Row],[Integración Nov/2024]] -> 1 | Z7: =AVERAGE(Tabla4[[#This Row],[Creación y captura Nov/2024]:[Compartición e Interoperabilidad Nov/2024]]) -> 0.975 | AA7: 1 | AB7: 1 | AC7: =AVERAGE('Calidad de Datos'!S11:V11) -> 0.91125 | AD7: =Tabla13[[#This Row],[Uso y acceso Dic/2024]] -> 1 | AE7: =Tabla58[[#This Row],[Integración Dic/2024]] -> 1 | AF7: =AVERAGE(Tabla4[[#This Row],[Creación y captura Dic/2024]:[Compartición e Interoperabilidad Dic/2024]]) -> 0.98225 | AG7: 1 | AH7: 1 | AI7: =AVERAGE('Calidad de Datos'!W11:Z11) -> 0.925 | AJ7: =Tabla13[[#This Row],[Uso y acceso Ene/2025]] -> 1 | AK7: =Tabla58[[#This Row],[Integración Ene/2025]] -> 1 | AL7: =AVERAGE(Tabla4[[#This Row],[Creación y captura Ene/2025]:[Compartición e Interoperabilidad Ene/2025]]) -> 0.985 | AM7: 1 | AN7: 1 | AO7: =AVERAGE('Calidad de Datos'!AA11:AD11) -> 0.925 | AP7: =Tabla13[[#This Row],[Uso y acceso Feb/2025]] -> 1 | AQ7: =Tabla58[[#This Row],[Integración Feb/2025]] -> 1 | AR7: =AVERAGE(Tabla4[[#This Row],[Creación y captura Feb/2025]:[Compartición e Interoperabilidad Feb/2025]]) -> 0.985 | AS7: 1 | AT7: 1 | AU7: =AVERAGE('Calidad de Datos'!AE11:AH11) -> 0.925 | AV7: =Tabla13[[#This Row],[Uso y acceso Mar/2025]] -> 1 | AW7: =Tabla58[[#This Row],[Integración Mar/2025]] -> 1 | AX7: =AVERAGE(Tabla4[[#This Row],[Creación y captura Mar/2025]:[Compartición e Interoperabilidad Mar/2025]]) -> 0.985 | AY7: 1 | AZ7: 1 | BA7: =AVERAGE('Calidad de Datos'!AI11:AL11) -> 0.925 | BB7: =Tabla13[[#This Row],[Uso y acceso Abr/2025]] -> 1 | BC7: =Tabla58[[#This Row],[Integración Abr/2025]] -> 1 | BD7: =AVERAGE(Tabla4[[#This Row],[Creación y captura Abr/2025]:[Compartición e Interoperabilidad Abr/2025]]) -> 0.985 | BE7: 1 | BF7: 1 | BG7: =AVERAGE('Calidad de Datos'!AM11:AP11) -> 0.95 | BH7: =Tabla13[[#This Row],[Uso y acceso May/2025]] -> 1 | BI7: =Tabla58[[#This Row],[Integración May/2025]] -> 1 | BJ7: =AVERAGE(Tabla4[[#This Row],[Creación y captura May/2025]:[Compartición e Interoperabilidad May/2025]]) -> 0.99 | BK7: 1 | BL7: 1 | BM7: =AVERAGE('Calidad de Datos'!AQ11:AT11) -> 0.881375 | BN7: =Tabla13[[#This Row],[Uso y acceso Dic/2025]] -> 1 | BO7: =Tabla58[[#This Row],[Integración Dic/2025]] -> 1 | BP7: =AVERAGE(Tabla4[[#This Row],[Creación y captura Dic/2025]:[Compartición e Interoperabilidad Dic/2025]]) -> 0.976275
B8: Línea de negocios | C8: 1 | D8: 1 | E8: =AVERAGE('Calidad de Datos'!C12:F12) -> 1 | F8: =Tabla13[[#This Row],[Uso y acceso Ago/2024]] -> 1 | G8: =Tabla58[[#This Row],[Integración Ago/2024]] -> 1 | H8: =AVERAGE(Tabla4[[#This Row],[Creación y captura Ago/2024]:[Compartición e Interoperabilidad Ago/2024]]) -> 1 | I8: 1 | J8: 1 | K8: =AVERAGE('Calidad de Datos'!G12:J12) -> 1 | L8: =Tabla13[[#This Row],[Uso y acceso Sep/2024]] -> 1 | M8: =Tabla58[[#This Row],[Integración Sep/2024]] -> 1 | N8: =AVERAGE(Tabla4[[#This Row],[Creación y captura Sep/2024]:[Compartición e Interoperabilidad Sep/2024]]) -> 1 | O8: 1 | P8: 1 | Q8: =AVERAGE('Calidad de Datos'!K12:N12) -> 1 | R8: =Tabla13[[#This Row],[Uso y acceso Oct/2024]] -> 1 | S8: =Tabla58[[#This Row],[Integración Oct/2024]] -> 1 | T8: =AVERAGE(Tabla4[[#This Row],[Creación y captura Oct/2024]:[Compartición e Interoperabilidad Oct/2024]]) -> 1 | U8: 1 | V8: 1 | W8: =AVERAGE('Calidad de Datos'!O12:R12) -> 1 | X8: =Tabla13[[#This Row],[Uso y acceso Nov/2024]] -> 1 | Y8: =Tabla58[[#This Row],[Integración Nov/2024]] -> 1 | Z8: =AVERAGE(Tabla4[[#This Row],[Creación y captura Nov/2024]:[Compartición e Interoperabilidad Nov/2024]]) -> 1 | AA8: 1 | AB8: 1 | AC8: =AVERAGE('Calidad de Datos'!S12:V12) -> 1 | AD8: =Tabla13[[#This Row],[Uso y acceso Dic/2024]] -> 1 | AE8: =Tabla58[[#This Row],[Integración Dic/2024]] -> 1 | AF8: =AVERAGE(Tabla4[[#This Row],[Creación y captura Dic/2024]:[Compartición e Interoperabilidad Dic/2024]]) -> 1 | AG8: 1 | AH8: 1 | AI8: =AVERAGE('Calidad de Datos'!W12:Z12) -> 1 | AJ8: =Tabla13[[#This Row],[Uso y acceso Ene/2025]] -> 1 | AK8: =Tabla58[[#This Row],[Integración Ene/2025]] -> 1 | AL8: =AVERAGE(Tabla4[[#This Row],[Creación y captura Ene/2025]:[Compartición e Interoperabilidad Ene/2025]]) -> 1 | AM8: 1 | AN8: 1 | AO8: =AVERAGE('Calidad de Datos'!AA12:AD12) -> 1 | AP8: =Tabla13[[#This Row],[Uso y acceso Feb/2025]] -> 1 | AQ8: =Tabla58[[#This Row],[Integración Feb/2025]] -> 1 | AR8: =AVERAGE(Tabla4[[#This Row],[Creación y captura Feb/2025]:[Compartición e Interoperabilidad Feb/2025]]) -> 1 | AS8: 1 | AT8: 1 | AU8: =AVERAGE('Calidad de Datos'!AE12:AH12) -> 1 | AV8: =Tabla13[[#This Row],[Uso y acceso Mar/2025]] -> 1 | AW8: =Tabla58[[#This Row],[Integración Mar/2025]] -> 1 | AX8: =AVERAGE(Tabla4[[#This Row],[Creación y captura Mar/2025]:[Compartición e Interoperabilidad Mar/2025]]) -> 1 | AY8: 1 | AZ8: 1 | BA8: =AVERAGE('Calidad de Datos'!AI12:AL12) -> 1 | BB8: =Tabla13[[#This Row],[Uso y acceso Abr/2025]] -> 1 | BC8: =Tabla58[[#This Row],[Integración Abr/2025]] -> 1 | BD8: =AVERAGE(Tabla4[[#This Row],[Creación y captura Abr/2025]:[Compartición e Interoperabilidad Abr/2025]]) -> 1 | BE8: 1 | BF8: 1 | BG8: =AVERAGE('Calidad de Datos'!AM12:AP12) -> 1 | BH8: =Tabla13[[#This Row],[Uso y acceso May/2025]] -> 1 | BI8: =Tabla58[[#This Row],[Integración May/2025]] -> 1 | BJ8: =AVERAGE(Tabla4[[#This Row],[Creación y captura May/2025]:[Compartición e Interoperabilidad May/2025]]) -> 1 | BK8: 1 | BL8: 1 | BM8: =AVERAGE('Calidad de Datos'!AQ12:AT12) -> 1 | BN8: =Tabla13[[#This Row],[Uso y acceso Dic/2025]] -> 1 | BO8: =Tabla58[[#This Row],[Integración Dic/2025]] -> 1 | BP8: =AVERAGE(Tabla4[[#This Row],[Creación y captura Dic/2025]:[Compartición e Interoperabilidad Dic/2025]]) -> 1
B9: Equipo de ventas | C9: 1 | D9: 1 | E9: =AVERAGE('Calidad de Datos'!C13:F13) -> 1 | F9: =Tabla13[[#This Row],[Uso y acceso Ago/2024]] -> 1 | G9: =Tabla58[[#This Row],[Integración Ago/2024]] -> 1 | H9: =AVERAGE(Tabla4[[#This Row],[Creación y captura Ago/2024]:[Compartición e Interoperabilidad Ago/2024]]) -> 1 | I9: 1 | J9: 1 | K9: =AVERAGE('Calidad de Datos'!G13:J13) -> 1 | L9: =Tabla13[[#This Row],[Uso y acceso Sep/2024]] -> 1 | M9: =Tabla58[[#This Row],[Integración Sep/2024]] -> 1 | N9: =AVERAGE(Tabla4[[#This Row],[Creación y captura Sep/2024]:[Compartición e Interoperabilidad Sep/2024]]) -> 1 | O9: 1 | P9: 1 | Q9: =AVERAGE('Calidad de Datos'!K13:N13) -> 1 | R9: =Tabla13[[#This Row],[Uso y acceso Oct/2024]] -> 1 | S9: =Tabla58[[#This Row],[Integración Oct/2024]] -> 1 | T9: =AVERAGE(Tabla4[[#This Row],[Creación y captura Oct/2024]:[Compartición e Interoperabilidad Oct/2024]]) -> 1 | U9: 1 | V9: 1 | W9: =AVERAGE('Calidad de Datos'!O13:R13) -> 1 | X9: =Tabla13[[#This Row],[Uso y acceso Nov/2024]] -> 1 | Y9: =Tabla58[[#This Row],[Integración Nov/2024]] -> 1 | Z9: =AVERAGE(Tabla4[[#This Row],[Creación y captura Nov/2024]:[Compartición e Interoperabilidad Nov/2024]]) -> 1 | AA9: 1 | AB9: 1 | AC9: =AVERAGE('Calidad de Datos'!S13:V13) -> 1 | AD9: =Tabla13[[#This Row],[Uso y acceso Dic/2024]] -> 1 | AE9: =Tabla58[[#This Row],[Integración Dic/2024]] -> 1 | AF9: =AVERAGE(Tabla4[[#This Row],[Creación y captura Dic/2024]:[Compartición e Interoperabilidad Dic/2024]]) -> 1 | AG9: 1 | AH9: 1 | AI9: =AVERAGE('Calidad de Datos'!W13:Z13) -> 1 | AJ9: =Tabla13[[#This Row],[Uso y acceso Ene/2025]] -> 1 | AK9: =Tabla58[[#This Row],[Integración Ene/2025]] -> 1 | AL9: =AVERAGE(Tabla4[[#This Row],[Creación y captura Ene/2025]:[Compartición e Interoperabilidad Ene/2025]]) -> 1 | AM9: 1 | AN9: 1 | AO9: =AVERAGE('Calidad de Datos'!AA13:AD13) -> 1 | AP9: =Tabla13[[#This Row],[Uso y acceso Feb/2025]] -> 1 | AQ9: =Tabla58[[#This Row],[Integración Feb/2025]] -> 1 | AR9: =AVERAGE(Tabla4[[#This Row],[Creación y captura Feb/2025]:[Compartición e Interoperabilidad Feb/2025]]) -> 1 | AS9: 1 | AT9: 1 | AU9: =AVERAGE('Calidad de Datos'!AE13:AH13) -> 1 | AV9: =Tabla13[[#This Row],[Uso y acceso Mar/2025]] -> 1 | AW9: =Tabla58[[#This Row],[Integración Mar/2025]] -> 1 | AX9: =AVERAGE(Tabla4[[#This Row],[Creación y captura Mar/2025]:[Compartición e Interoperabilidad Mar/2025]]) -> 1 | AY9: 1 | AZ9: 1 | BA9: =AVERAGE('Calidad de Datos'!AI13:AL13) -> 1 | BB9: =Tabla13[[#This Row],[Uso y acceso Abr/2025]] -> 1 | BC9: =Tabla58[[#This Row],[Integración Abr/2025]] -> 1 | BD9: =AVERAGE(Tabla4[[#This Row],[Creación y captura Abr/2025]:[Compartición e Interoperabilidad Abr/2025]]) -> 1 | BE9: 1 | BF9: 1 | BG9: =AVERAGE('Calidad de Datos'!AM13:AP13) -> 1 | BH9: =Tabla13[[#This Row],[Uso y acceso May/2025]] -> 1 | BI9: =Tabla58[[#This Row],[Integración May/2025]] -> 1 | BJ9: =AVERAGE(Tabla4[[#This Row],[Creación y captura May/2025]:[Compartición e Interoperabilidad May/2025]]) -> 1 | BK9: 1 | BL9: 1 | BM9: =AVERAGE('Calidad de Datos'!AQ13:AT13) -> 1 | BN9: =Tabla13[[#This Row],[Uso y acceso Dic/2025]] -> 1 | BO9: =Tabla58[[#This Row],[Integración Dic/2025]] -> 1 | BP9: =AVERAGE(Tabla4[[#This Row],[Creación y captura Dic/2025]:[Compartición e Interoperabilidad Dic/2025]]) -> 1
B10: Tipo de cliente | C10: 1 | D10: 1 | E10: =AVERAGE('Calidad de Datos'!C14:F14) -> 1 | F10: =Tabla13[[#This Row],[Uso y acceso Ago/2024]] -> 1 | G10: =Tabla58[[#This Row],[Integración Ago/2024]] -> 1 | H10: =AVERAGE(Tabla4[[#This Row],[Creación y captura Ago/2024]:[Compartición e Interoperabilidad Ago/2024]]) -> 1 | I10: 1 | J10: 1 | K10: =AVERAGE('Calidad de Datos'!G14:J14) -> 1 | L10: =Tabla13[[#This Row],[Uso y acceso Sep/2024]] -> 1 | M10: =Tabla58[[#This Row],[Integración Sep/2024]] -> 1 | N10: =AVERAGE(Tabla4[[#This Row],[Creación y captura Sep/2024]:[Compartición e Interoperabilidad Sep/2024]]) -> 1 | O10: 1 | P10: 1 | Q10: =AVERAGE('Calidad de Datos'!K14:N14) -> 1 | R10: =Tabla13[[#This Row],[Uso y acceso Oct/2024]] -> 1 | S10: =Tabla58[[#This Row],[Integración Oct/2024]] -> 1 | T10: =AVERAGE(Tabla4[[#This Row],[Creación y captura Oct/2024]:[Compartición e Interoperabilidad Oct/2024]]) -> 1 | U10: 1 | V10: 1 | W10: =AVERAGE('Calidad de Datos'!O14:R14) -> 1 | X10: =Tabla13[[#This Row],[Uso y acceso Nov/2024]] -> 1 | Y10: =Tabla58[[#This Row],[Integración Nov/2024]] -> 1 | Z10: =AVERAGE(Tabla4[[#This Row],[Creación y captura Nov/2024]:[Compartición e Interoperabilidad Nov/2024]]) -> 1 | AA10: 1 | AB10: 1 | AC10: =AVERAGE('Calidad de Datos'!S14:V14) -> 1 | AD10: =Tabla13[[#This Row],[Uso y acceso Dic/2024]] -> 1 | AE10: =Tabla58[[#This Row],[Integración Dic/2024]] -> 1 | AF10: =AVERAGE(Tabla4[[#This Row],[Creación y captura Dic/2024]:[Compartición e Interoperabilidad Dic/2024]]) -> 1 | AG10: 1 | AH10: 1 | AI10: =AVERAGE('Calidad de Datos'!W14:Z14) -> 1 | AJ10: =Tabla13[[#This Row],[Uso y acceso Ene/2025]] -> 1 | AK10: =Tabla58[[#This Row],[Integración Ene/2025]] -> 1 | AL10: =AVERAGE(Tabla4[[#This Row],[Creación y captura Ene/2025]:[Compartición e Interoperabilidad Ene/2025]]) -> 1 | AM10: 1 | AN10: 1 | AO10: =AVERAGE('Calidad de Datos'!AA14:AD14) -> 1 | AP10: =Tabla13[[#This Row],[Uso y acceso Feb/2025]] -> 1 | AQ10: =Tabla58[[#This Row],[Integración Feb/2025]] -> 1 | AR10: =AVERAGE(Tabla4[[#This Row],[Creación y captura Feb/2025]:[Compartición e Interoperabilidad Feb/2025]]) -> 1 | AS10: 1 | AT10: 1 | AU10: =AVERAGE('Calidad de Datos'!AE14:AH14) -> 1 | AV10: =Tabla13[[#This Row],[Uso y acceso Mar/2025]] -> 1 | AW10: =Tabla58[[#This Row],[Integración Mar/2025]] -> 1 | AX10: =AVERAGE(Tabla4[[#This Row],[Creación y captura Mar/2025]:[Compartición e Interoperabilidad Mar/2025]]) -> 1 | AY10: 1 | AZ10: 1 | BA10: =AVERAGE('Calidad de Datos'!AI14:AL14) -> 1 | BB10: =Tabla13[[#This Row],[Uso y acceso Abr/2025]] -> 1 | BC10: =Tabla58[[#This Row],[Integración Abr/2025]] -> 1 | BD10: =AVERAGE(Tabla4[[#This Row],[Creación y captura Abr/2025]:[Compartición e Interoperabilidad Abr/2025]]) -> 1 | BE10: 1 | BF10: 1 | BG10: =AVERAGE('Calidad de Datos'!AM14:AP14) -> 1 | BH10: =Tabla13[[#This Row],[Uso y acceso May/2025]] -> 1 | BI10: =Tabla58[[#This Row],[Integración May/2025]] -> 1 | BJ10: =AVERAGE(Tabla4[[#This Row],[Creación y captura May/2025]:[Compartición e Interoperabilidad May/2025]]) -> 1 | BK10: 1 | BL10: 1 | BM10: =AVERAGE('Calidad de Datos'!AQ14:AT14) -> 1 | BN10: =Tabla13[[#This Row],[Uso y acceso Dic/2025]] -> 1 | BO10: =Tabla58[[#This Row],[Integración Dic/2025]] -> 1 | BP10: =AVERAGE(Tabla4[[#This Row],[Creación y captura Dic/2025]:[Compartición e Interoperabilidad Dic/2025]]) -> 1
B11: Cliente | C11: 1 | D11: 1 | E11: =AVERAGE('Calidad de Datos'!C15:F15) -> 0.625 | F11: =Tabla13[[#This Row],[Uso y acceso Ago/2024]] -> 1 | G11: =Tabla58[[#This Row],[Integración Ago/2024]] -> 1 | H11: =AVERAGE(Tabla4[[#This Row],[Creación y captura Ago/2024]:[Compartición e Interoperabilidad Ago/2024]]) -> 0.925 | I11: 1 | J11: 1 | K11: =AVERAGE('Calidad de Datos'!G15:J15) -> 0.625 | L11: =Tabla13[[#This Row],[Uso y acceso Sep/2024]] -> 1 | M11: =Tabla58[[#This Row],[Integración Sep/2024]] -> 1 | N11: =AVERAGE(Tabla4[[#This Row],[Creación y captura Sep/2024]:[Compartición e Interoperabilidad Sep/2024]]) -> 0.925 | O11: 1 | P11: 1 | Q11: =AVERAGE('Calidad de Datos'!K15:N15) -> 0.6325 | R11: =Tabla13[[#This Row],[Uso y acceso Oct/2024]] -> 1 | S11: =Tabla58[[#This Row],[Integración Oct/2024]] -> 1 | T11: =AVERAGE(Tabla4[[#This Row],[Creación y captura Oct/2024]:[Compartición e Interoperabilidad Oct/2024]]) -> 0.9265 | U11: 1 | V11: 1 | W11: =AVERAGE('Calidad de Datos'!O15:R15) -> 0.7625 | X11: =Tabla13[[#This Row],[Uso y acceso Nov/2024]] -> 1 | Y11: =Tabla58[[#This Row],[Integración Nov/2024]] -> 1 | Z11: =AVERAGE(Tabla4[[#This Row],[Creación y captura Nov/2024]:[Compartición e Interoperabilidad Nov/2024]]) -> 0.9525 | AA11: 1 | AB11: 1 | AC11: =AVERAGE('Calidad de Datos'!S15:V15) -> 0.82375 | AD11: =Tabla13[[#This Row],[Uso y acceso Dic/2024]] -> 1 | AE11: =Tabla58[[#This Row],[Integración Dic/2024]] -> 1 | AF11: =AVERAGE(Tabla4[[#This Row],[Creación y captura Dic/2024]:[Compartición e Interoperabilidad Dic/2024]]) -> 0.96475 | AG11: 1 | AH11: 1 | AI11: =AVERAGE('Calidad de Datos'!W15:Z15) -> 0.825 | AJ11: =Tabla13[[#This Row],[Uso y acceso Ene/2025]] -> 1 | AK11: =Tabla58[[#This Row],[Integración Ene/2025]] -> 1 | AL11: =AVERAGE(Tabla4[[#This Row],[Creación y captura Ene/2025]:[Compartición e Interoperabilidad Ene/2025]]) -> 0.965 | AM11: 1 | AN11: 1 | AO11: =AVERAGE('Calidad de Datos'!AA15:AD15) -> 0.825 | AP11: =Tabla13[[#This Row],[Uso y acceso Feb/2025]] -> 1 | AQ11: =Tabla58[[#This Row],[Integración Feb/2025]] -> 1 | AR11: =AVERAGE(Tabla4[[#This Row],[Creación y captura Feb/2025]:[Compartición e Interoperabilidad Feb/2025]]) -> 0.965 | AS11: 1 | AT11: 1 | AU11: =AVERAGE('Calidad de Datos'!AE15:AH15) -> 0.825 | AV11: =Tabla13[[#This Row],[Uso y acceso Mar/2025]] -> 1 | AW11: =Tabla58[[#This Row],[Integración Mar/2025]] -> 1 | AX11: =AVERAGE(Tabla4[[#This Row],[Creación y captura Mar/2025]:[Compartición e Interoperabilidad Mar/2025]]) -> 0.965 | AY11: 1 | AZ11: 1 | BA11: =AVERAGE('Calidad de Datos'!AI15:AL15) -> 0.825 | BB11: =Tabla13[[#This Row],[Uso y acceso Abr/2025]] -> 1 | BC11: =Tabla58[[#This Row],[Integración Abr/2025]] -> 1 | BD11: =AVERAGE(Tabla4[[#This Row],[Creación y captura Abr/2025]:[Compartición e Interoperabilidad Abr/2025]]) -> 0.965 | BE11: 1 | BF11: 1 | BG11: =AVERAGE('Calidad de Datos'!AM15:AP15) -> 0.825 | BH11: =Tabla13[[#This Row],[Uso y acceso May/2025]] -> 1 | BI11: =Tabla58[[#This Row],[Integración May/2025]] -> 1 | BJ11: =AVERAGE(Tabla4[[#This Row],[Creación y captura May/2025]:[Compartición e Interoperabilidad May/2025]]) -> 0.965 | BK11: 1 | BL11: 1 | BM11: =AVERAGE('Calidad de Datos'!AQ15:AT15) -> 0.8385 | BN11: =Tabla13[[#This Row],[Uso y acceso Dic/2025]] -> 1 | BO11: =Tabla58[[#This Row],[Integración Dic/2025]] -> 1 | BP11: =AVERAGE(Tabla4[[#This Row],[Creación y captura Dic/2025]:[Compartición e Interoperabilidad Dic/2025]]) -> 0.9677
B12: Tipo de venta | C12: 1 | D12: 1 | E12: =AVERAGE('Calidad de Datos'!C16:F16) -> 1 | F12: =Tabla13[[#This Row],[Uso y acceso Ago/2024]] -> 1 | G12: =Tabla58[[#This Row],[Integración Ago/2024]] -> 1 | H12: =AVERAGE(Tabla4[[#This Row],[Creación y captura Ago/2024]:[Compartición e Interoperabilidad Ago/2024]]) -> 1 | I12: 1 | J12: 1 | K12: =AVERAGE('Calidad de Datos'!G16:J16) -> 1 | L12: =Tabla13[[#This Row],[Uso y acceso Sep/2024]] -> 1 | M12: =Tabla58[[#This Row],[Integración Sep/2024]] -> 1 | N12: =AVERAGE(Tabla4[[#This Row],[Creación y captura Sep/2024]:[Compartición e Interoperabilidad Sep/2024]]) -> 1 | O12: 1 | P12: 1 | Q12: =AVERAGE('Calidad de Datos'!K16:N16) -> 1 | R12: =Tabla13[[#This Row],[Uso y acceso Oct/2024]] -> 1 | S12: =Tabla58[[#This Row],[Integración Oct/2024]] -> 1 | T12: =AVERAGE(Tabla4[[#This Row],[Creación y captura Oct/2024]:[Compartición e Interoperabilidad Oct/2024]]) -> 1 | U12: 1 | V12: 1 | W12: =AVERAGE('Calidad de Datos'!O16:R16) -> 1 | X12: =Tabla13[[#This Row],[Uso y acceso Nov/2024]] -> 1 | Y12: =Tabla58[[#This Row],[Integración Nov/2024]] -> 1 | Z12: =AVERAGE(Tabla4[[#This Row],[Creación y captura Nov/2024]:[Compartición e Interoperabilidad Nov/2024]]) -> 1 | AA12: 1 | AB12: 1 | AC12: =AVERAGE('Calidad de Datos'!S16:V16) -> 1 | AD12: =Tabla13[[#This Row],[Uso y acceso Dic/2024]] -> 1 | AE12: =Tabla58[[#This Row],[Integración Dic/2024]] -> 1 | AF12: =AVERAGE(Tabla4[[#This Row],[Creación y captura Dic/2024]:[Compartición e Interoperabilidad Dic/2024]]) -> 1 | AG12: 1 | AH12: 1 | AI12: =AVERAGE('Calidad de Datos'!W16:Z16) -> 1 | AJ12: =Tabla13[[#This Row],[Uso y acceso Ene/2025]] -> 1 | AK12: =Tabla58[[#This Row],[Integración Ene/2025]] -> 1 | AL12: =AVERAGE(Tabla4[[#This Row],[Creación y captura Ene/2025]:[Compartición e Interoperabilidad Ene/2025]]) -> 1 | AM12: 1 | AN12: 1 | AO12: =AVERAGE('Calidad de Datos'!AA16:AD16) -> 1 | AP12: =Tabla13[[#This Row],[Uso y acceso Feb/2025]] -> 1 | AQ12: =Tabla58[[#This Row],[Integración Feb/2025]] -> 1 | AR12: =AVERAGE(Tabla4[[#This Row],[Creación y captura Feb/2025]:[Compartición e Interoperabilidad Feb/2025]]) -> 1 | AS12: 1 | AT12: 1 | AU12: =AVERAGE('Calidad de Datos'!AE16:AH16) -> 1 | AV12: =Tabla13[[#This Row],[Uso y acceso Mar/2025]] -> 1 | AW12: =Tabla58[[#This Row],[Integración Mar/2025]] -> 1 | AX12: =AVERAGE(Tabla4[[#This Row],[Creación y captura Mar/2025]:[Compartición e Interoperabilidad Mar/2025]]) -> 1 | AY12: 1 | AZ12: 1 | BA12: =AVERAGE('Calidad de Datos'!AI16:AL16) -> 1 | BB12: =Tabla13[[#This Row],[Uso y acceso Abr/2025]] -> 1 | BC12: =Tabla58[[#This Row],[Integración Abr/2025]] -> 1 | BD12: =AVERAGE(Tabla4[[#This Row],[Creación y captura Abr/2025]:[Compartición e Interoperabilidad Abr/2025]]) -> 1 | BE12: 1 | BF12: 1 | BG12: =AVERAGE('Calidad de Datos'!AM16:AP16) -> 1 | BH12: =Tabla13[[#This Row],[Uso y acceso May/2025]] -> 1 | BI12: =Tabla58[[#This Row],[Integración May/2025]] -> 1 | BJ12: =AVERAGE(Tabla4[[#This Row],[Creación y captura May/2025]:[Compartición e Interoperabilidad May/2025]]) -> 1 | BK12: 1 | BL12: 1 | BM12: =AVERAGE('Calidad de Datos'!AQ16:AT16) -> 1 | BN12: =Tabla13[[#This Row],[Uso y acceso Dic/2025]] -> 1 | BO12: =Tabla58[[#This Row],[Integración Dic/2025]] -> 1 | BP12: =AVERAGE(Tabla4[[#This Row],[Creación y captura Dic/2025]:[Compartición e Interoperabilidad Dic/2025]]) -> 1
B13: Tipo de oportunidad | C13: 1 | D13: 1 | E13: =AVERAGE('Calidad de Datos'!C17:F17) -> 1 | F13: =Tabla13[[#This Row],[Uso y acceso Ago/2024]] -> 1 | G13: =Tabla58[[#This Row],[Integración Ago/2024]] -> 1 | H13: =AVERAGE(Tabla4[[#This Row],[Creación y captura Ago/2024]:[Compartición e Interoperabilidad Ago/2024]]) -> 1 | I13: 1 | J13: 1 | K13: =AVERAGE('Calidad de Datos'!G17:J17) -> 1 | L13: =Tabla13[[#This Row],[Uso y acceso Sep/2024]] -> 1 | M13: =Tabla58[[#This Row],[Integración Sep/2024]] -> 1 | N13: =AVERAGE(Tabla4[[#This Row],[Creación y captura Sep/2024]:[Compartición e Interoperabilidad Sep/2024]]) -> 1 | O13: 1 | P13: 1 | Q13: =AVERAGE('Calidad de Datos'!K17:N17) -> 1 | R13: =Tabla13[[#This Row],[Uso y acceso Oct/2024]] -> 1 | S13: =Tabla58[[#This Row],[Integración Oct/2024]] -> 1 | T13: =AVERAGE(Tabla4[[#This Row],[Creación y captura Oct/2024]:[Compartición e Interoperabilidad Oct/2024]]) -> 1 | U13: 1 | V13: 1 | W13: =AVERAGE('Calidad de Datos'!O17:R17) -> 1 | X13: =Tabla13[[#This Row],[Uso y acceso Nov/2024]] -> 1 | Y13: =Tabla58[[#This Row],[Integración Nov/2024]] -> 1 | Z13: =AVERAGE(Tabla4[[#This Row],[Creación y captura Nov/2024]:[Compartición e Interoperabilidad Nov/2024]]) -> 1 | AA13: 1 | AB13: 1 | AC13: =AVERAGE('Calidad de Datos'!S17:V17) -> 1 | AD13: =Tabla13[[#This Row],[Uso y acceso Dic/2024]] -> 1 | AE13: =Tabla58[[#This Row],[Integración Dic/2024]] -> 1 | AF13: =AVERAGE(Tabla4[[#This Row],[Creación y captura Dic/2024]:[Compartición e Interoperabilidad Dic/2024]]) -> 1 | AG13: 1 | AH13: 1 | AI13: =AVERAGE('Calidad de Datos'!W17:Z17) -> 1 | AJ13: =Tabla13[[#This Row],[Uso y acceso Ene/2025]] -> 1 | AK13: =Tabla58[[#This Row],[Integración Ene/2025]] -> 1 | AL13: =AVERAGE(Tabla4[[#This Row],[Creación y captura Ene/2025]:[Compartición e Interoperabilidad Ene/2025]]) -> 1 | AM13: 1 | AN13: 1 | AO13: =AVERAGE('Calidad de Datos'!AA17:AD17) -> 1 | AP13: =Tabla13[[#This Row],[Uso y acceso Feb/2025]] -> 1 | AQ13: =Tabla58[[#This Row],[Integración Feb/2025]] -> 1 | AR13: =AVERAGE(Tabla4[[#This Row],[Creación y captura Feb/2025]:[Compartición e Interoperabilidad Feb/2025]]) -> 1 | AS13: 1 | AT13: 1 | AU13: =AVERAGE('Calidad de Datos'!AE17:AH17) -> 1 | AV13: =Tabla13[[#This Row],[Uso y acceso Mar/2025]] -> 1 | AW13: =Tabla58[[#This Row],[Integración Mar/2025]] -> 1 | AX13: =AVERAGE(Tabla4[[#This Row],[Creación y captura Mar/2025]:[Compartición e Interoperabilidad Mar/2025]]) -> 1 | AY13: 1 | AZ13: 1 | BA13: =AVERAGE('Calidad de Datos'!AI17:AL17) -> 1 | BB13: =Tabla13[[#This Row],[Uso y acceso Abr/2025]] -> 1 | BC13: =Tabla58[[#This Row],[Integración Abr/2025]] -> 1 | BD13: =AVERAGE(Tabla4[[#This Row],[Creación y captura Abr/2025]:[Compartición e Interoperabilidad Abr/2025]]) -> 1 | BE13: 1 | BF13: 1 | BG13: =AVERAGE('Calidad de Datos'!AM17:AP17) -> 1 | BH13: =Tabla13[[#This Row],[Uso y acceso May/2025]] -> 1 | BI13: =Tabla58[[#This Row],[Integración May/2025]] -> 1 | BJ13: =AVERAGE(Tabla4[[#This Row],[Creación y captura May/2025]:[Compartición e Interoperabilidad May/2025]]) -> 1 | BK13: 1 | BL13: 1 | BM13: =AVERAGE('Calidad de Datos'!AQ17:AT17) -> 1 | BN13: =Tabla13[[#This Row],[Uso y acceso Dic/2025]] -> 1 | BO13: =Tabla58[[#This Row],[Integración Dic/2025]] -> 1 | BP13: =AVERAGE(Tabla4[[#This Row],[Creación y captura Dic/2025]:[Compartición e Interoperabilidad Dic/2025]]) -> 1
B14: Etapa actual | C14: 1 | D14: 1 | E14: =AVERAGE('Calidad de Datos'!C18:F18) -> 1 | F14: =Tabla13[[#This Row],[Uso y acceso Ago/2024]] -> 1 | G14: =Tabla58[[#This Row],[Integración Ago/2024]] -> 1 | H14: =AVERAGE(Tabla4[[#This Row],[Creación y captura Ago/2024]:[Compartición e Interoperabilidad Ago/2024]]) -> 1 | I14: 1 | J14: 1 | K14: =AVERAGE('Calidad de Datos'!G18:J18) -> 1 | L14: =Tabla13[[#This Row],[Uso y acceso Sep/2024]] -> 1 | M14: =Tabla58[[#This Row],[Integración Sep/2024]] -> 1 | N14: =AVERAGE(Tabla4[[#This Row],[Creación y captura Sep/2024]:[Compartición e Interoperabilidad Sep/2024]]) -> 1 | O14: 1 | P14: 1 | Q14: =AVERAGE('Calidad de Datos'!K18:N18) -> 1 | R14: =Tabla13[[#This Row],[Uso y acceso Oct/2024]] -> 1 | S14: =Tabla58[[#This Row],[Integración Oct/2024]] -> 1 | T14: =AVERAGE(Tabla4[[#This Row],[Creación y captura Oct/2024]:[Compartición e Interoperabilidad Oct/2024]]) -> 1 | U14: 1 | V14: 1 | W14: =AVERAGE('Calidad de Datos'!O18:R18) -> 1 | X14: =Tabla13[[#This Row],[Uso y acceso Nov/2024]] -> 1 | Y14: =Tabla58[[#This Row],[Integración Nov/2024]] -> 1 | Z14: =AVERAGE(Tabla4[[#This Row],[Creación y captura Nov/2024]:[Compartición e Interoperabilidad Nov/2024]]) -> 1 | AA14: 1 | AB14: 1 | AC14: =AVERAGE('Calidad de Datos'!S18:V18) -> 1 | AD14: =Tabla13[[#This Row],[Uso y acceso Dic/2024]] -> 1 | AE14: =Tabla58[[#This Row],[Integración Dic/2024]] -> 1 | AF14: =AVERAGE(Tabla4[[#This Row],[Creación y captura Dic/2024]:[Compartición e Interoperabilidad Dic/2024]]) -> 1 | AG14: 1 | AH14: 1 | AI14: =AVERAGE('Calidad de Datos'!W18:Z18) -> 1 | AJ14: =Tabla13[[#This Row],[Uso y acceso Ene/2025]] -> 1 | AK14: =Tabla58[[#This Row],[Integración Ene/2025]] -> 1 | AL14: =AVERAGE(Tabla4[[#This Row],[Creación y captura Ene/2025]:[Compartición e Interoperabilidad Ene/2025]]) -> 1 | AM14: 1 | AN14: 1 | AO14: =AVERAGE('Calidad de Datos'!AA18:AD18) -> 1 | AP14: =Tabla13[[#This Row],[Uso y acceso Feb/2025]] -> 1 | AQ14: =Tabla58[[#This Row],[Integración Feb/2025]] -> 1 | AR14: =AVERAGE(Tabla4[[#This Row],[Creación y captura Feb/2025]:[Compartición e Interoperabilidad Feb/2025]]) -> 1 | AS14: 1 | AT14: 1 | AU14: =AVERAGE('Calidad de Datos'!AE18:AH18) -> 1 | AV14: =Tabla13[[#This Row],[Uso y acceso Mar/2025]] -> 1 | AW14: =Tabla58[[#This Row],[Integración Mar/2025]] -> 1 | AX14: =AVERAGE(Tabla4[[#This Row],[Creación y captura Mar/2025]:[Compartición e Interoperabilidad Mar/2025]]) -> 1 | AY14: 1 | AZ14: 1 | BA14: =AVERAGE('Calidad de Datos'!AI18:AL18) -> 1 | BB14: =Tabla13[[#This Row],[Uso y acceso Abr/2025]] -> 1 | BC14: =Tabla58[[#This Row],[Integración Abr/2025]] -> 1 | BD14: =AVERAGE(Tabla4[[#This Row],[Creación y captura Abr/2025]:[Compartición e Interoperabilidad Abr/2025]]) -> 1 | BE14: 1 | BF14: 1 | BG14: =AVERAGE('Calidad de Datos'!AM18:AP18) -> 1 | BH14: =Tabla13[[#This Row],[Uso y acceso May/2025]] -> 1 | BI14: =Tabla58[[#This Row],[Integración May/2025]] -> 1 | BJ14: =AVERAGE(Tabla4[[#This Row],[Creación y captura May/2025]:[Compartición e Interoperabilidad May/2025]]) -> 1 | BK14: 1 | BL14: 1 | BM14: =AVERAGE('Calidad de Datos'!AQ18:AT18) -> 1 | BN14: =Tabla13[[#This Row],[Uso y acceso Dic/2025]] -> 1 | BO14: =Tabla58[[#This Row],[Integración Dic/2025]] -> 1 | BP14: =AVERAGE(Tabla4[[#This Row],[Creación y captura Dic/2025]:[Compartición e Interoperabilidad Dic/2025]]) -> 1
B15: Ganado | C15: 1 | D15: 1 | E15: =AVERAGE('Calidad de Datos'!C19:F19) -> 1 | F15: =Tabla13[[#This Row],[Uso y acceso Ago/2024]] -> 1 | G15: =Tabla58[[#This Row],[Integración Ago/2024]] -> 1 | H15: =AVERAGE(Tabla4[[#This Row],[Creación y captura Ago/2024]:[Compartición e Interoperabilidad Ago/2024]]) -> 1 | I15: 1 | J15: 1 | K15: =AVERAGE('Calidad de Datos'!G19:J19) -> 1 | L15: =Tabla13[[#This Row],[Uso y acceso Sep/2024]] -> 1 | M15: =Tabla58[[#This Row],[Integración Sep/2024]] -> 1 | N15: =AVERAGE(Tabla4[[#This Row],[Creación y captura Sep/2024]:[Compartición e Interoperabilidad Sep/2024]]) -> 1 | O15: 1 | P15: 1 | Q15: =AVERAGE('Calidad de Datos'!K19:N19) -> 1 | R15: =Tabla13[[#This Row],[Uso y acceso Oct/2024]] -> 1 | S15: =Tabla58[[#This Row],[Integración Oct/2024]] -> 1 | T15: =AVERAGE(Tabla4[[#This Row],[Creación y captura Oct/2024]:[Compartición e Interoperabilidad Oct/2024]]) -> 1 | U15: 1 | V15: 1 | W15: =AVERAGE('Calidad de Datos'!O19:R19) -> 1 | X15: =Tabla13[[#This Row],[Uso y acceso Nov/2024]] -> 1 | Y15: =Tabla58[[#This Row],[Integración Nov/2024]] -> 1 | Z15: =AVERAGE(Tabla4[[#This Row],[Creación y captura Nov/2024]:[Compartición e Interoperabilidad Nov/2024]]) -> 1 | AA15: 1 | AB15: 1 | AC15: =AVERAGE('Calidad de Datos'!S19:V19) -> 1 | AD15: =Tabla13[[#This Row],[Uso y acceso Dic/2024]] -> 1 | AE15: =Tabla58[[#This Row],[Integración Dic/2024]] -> 1 | AF15: =AVERAGE(Tabla4[[#This Row],[Creación y captura Dic/2024]:[Compartición e Interoperabilidad Dic/2024]]) -> 1 | AG15: 1 | AH15: 1 | AI15: =AVERAGE('Calidad de Datos'!W19:Z19) -> 1 | AJ15: =Tabla13[[#This Row],[Uso y acceso Ene/2025]] -> 1 | AK15: =Tabla58[[#This Row],[Integración Ene/2025]] -> 1 | AL15: =AVERAGE(Tabla4[[#This Row],[Creación y captura Ene/2025]:[Compartición e Interoperabilidad Ene/2025]]) -> 1 | AM15: 1 | AN15: 1 | AO15: =AVERAGE('Calidad de Datos'!AA19:AD19) -> 1 | AP15: =Tabla13[[#This Row],[Uso y acceso Feb/2025]] -> 1 | AQ15: =Tabla58[[#This Row],[Integración Feb/2025]] -> 1 | AR15: =AVERAGE(Tabla4[[#This Row],[Creación y captura Feb/2025]:[Compartición e Interoperabilidad Feb/2025]]) -> 1 | AS15: 1 | AT15: 1 | AU15: =AVERAGE('Calidad de Datos'!AE19:AH19) -> 1 | AV15: =Tabla13[[#This Row],[Uso y acceso Mar/2025]] -> 1 | AW15: =Tabla58[[#This Row],[Integración Mar/2025]] -> 1 | AX15: =AVERAGE(Tabla4[[#This Row],[Creación y captura Mar/2025]:[Compartición e Interoperabilidad Mar/2025]]) -> 1 | AY15: 1 | AZ15: 1 | BA15: =AVERAGE('Calidad de Datos'!AI19:AL19) -> 1 | BB15: =Tabla13[[#This Row],[Uso y acceso Abr/2025]] -> 1 | BC15: =Tabla58[[#This Row],[Integración Abr/2025]] -> 1 | BD15: =AVERAGE(Tabla4[[#This Row],[Creación y captura Abr/2025]:[Compartición e Interoperabilidad Abr/2025]]) -> 1 | BE15: 1 | BF15: 1 | BG15: =AVERAGE('Calidad de Datos'!AM19:AP19) -> 1 | BH15: =Tabla13[[#This Row],[Uso y acceso May/2025]] -> 1 | BI15: =Tabla58[[#This Row],[Integración May/2025]] -> 1 | BJ15: =AVERAGE(Tabla4[[#This Row],[Creación y captura May/2025]:[Compartición e Interoperabilidad May/2025]]) -> 1 | BK15: 1 | BL15: 1 | BM15: =AVERAGE('Calidad de Datos'!AQ19:AT19) -> 1 | BN15: =Tabla13[[#This Row],[Uso y acceso Dic/2025]] -> 1 | BO15: =Tabla58[[#This Row],[Integración Dic/2025]] -> 1 | BP15: =AVERAGE(Tabla4[[#This Row],[Creación y captura Dic/2025]:[Compartición e Interoperabilidad Dic/2025]]) -> 1
B16: Metas | C16: 1 | D16: 1 | E16: =AVERAGE('Calidad de Datos'!C20:F20) -> 1 | F16: =Tabla13[[#This Row],[Uso y acceso Ago/2024]] -> 1 | G16: =Tabla58[[#This Row],[Integración Ago/2024]] -> 1 | H16: =AVERAGE(Tabla4[[#This Row],[Creación y captura Ago/2024]:[Compartición e Interoperabilidad Ago/2024]]) -> 1 | I16: 1 | J16: 1 | K16: =AVERAGE('Calidad de Datos'!G20:J20) -> 1 | L16: =Tabla13[[#This Row],[Uso y acceso Sep/2024]] -> 1 | M16: =Tabla58[[#This Row],[Integración Sep/2024]] -> 1 | N16: =AVERAGE(Tabla4[[#This Row],[Creación y captura Sep/2024]:[Compartición e Interoperabilidad Sep/2024]]) -> 1 | O16: 1 | P16: 1 | Q16: =AVERAGE('Calidad de Datos'!K20:N20) -> 1 | R16: =Tabla13[[#This Row],[Uso y acceso Oct/2024]] -> 1 | S16: =Tabla58[[#This Row],[Integración Oct/2024]] -> 1 | T16: =AVERAGE(Tabla4[[#This Row],[Creación y captura Oct/2024]:[Compartición e Interoperabilidad Oct/2024]]) -> 1 | U16: 1 | V16: 1 | W16: =AVERAGE('Calidad de Datos'!O20:R20) -> 1 | X16: =Tabla13[[#This Row],[Uso y acceso Nov/2024]] -> 1 | Y16: =Tabla58[[#This Row],[Integración Nov/2024]] -> 1 | Z16: =AVERAGE(Tabla4[[#This Row],[Creación y captura Nov/2024]:[Compartición e Interoperabilidad Nov/2024]]) -> 1 | AA16: 1 | AB16: 1 | AC16: =AVERAGE('Calidad de Datos'!S20:V20) -> 1 | AD16: =Tabla13[[#This Row],[Uso y acceso Dic/2024]] -> 1 | AE16: =Tabla58[[#This Row],[Integración Dic/2024]] -> 1 | AF16: =AVERAGE(Tabla4[[#This Row],[Creación y captura Dic/2024]:[Compartición e Interoperabilidad Dic/2024]]) -> 1 | AG16: 1 | AH16: 1 | AI16: =AVERAGE('Calidad de Datos'!W20:Z20) -> 1 | AJ16: =Tabla13[[#This Row],[Uso y acceso Ene/2025]] -> 1 | AK16: =Tabla58[[#This Row],[Integración Ene/2025]] -> 1 | AL16: =AVERAGE(Tabla4[[#This Row],[Creación y captura Ene/2025]:[Compartición e Interoperabilidad Ene/2025]]) -> 1 | AM16: 1 | AN16: 1 | AO16: =AVERAGE('Calidad de Datos'!AA20:AD20) -> 1 | AP16: =Tabla13[[#This Row],[Uso y acceso Feb/2025]] -> 1 | AQ16: =Tabla58[[#This Row],[Integración Feb/2025]] -> 1 | AR16: =AVERAGE(Tabla4[[#This Row],[Creación y captura Feb/2025]:[Compartición e Interoperabilidad Feb/2025]]) -> 1 | AS16: 1 | AT16: 1 | AU16: =AVERAGE('Calidad de Datos'!AE20:AH20) -> 1 | AV16: =Tabla13[[#This Row],[Uso y acceso Mar/2025]] -> 1 | AW16: =Tabla58[[#This Row],[Integración Mar/2025]] -> 1 | AX16: =AVERAGE(Tabla4[[#This Row],[Creación y captura Mar/2025]:[Compartición e Interoperabilidad Mar/2025]]) -> 1 | AY16: 1 | AZ16: 1 | BA16: =AVERAGE('Calidad de Datos'!AI20:AL20) -> 1 | BB16: =Tabla13[[#This Row],[Uso y acceso Abr/2025]] -> 1 | BC16: =Tabla58[[#This Row],[Integración Abr/2025]] -> 1 | BD16: =AVERAGE(Tabla4[[#This Row],[Creación y captura Abr/2025]:[Compartición e Interoperabilidad Abr/2025]]) -> 1 | BE16: 1 | BF16: 1 | BG16: =AVERAGE('Calidad de Datos'!AM20:AP20) -> 1 | BH16: =Tabla13[[#This Row],[Uso y acceso May/2025]] -> 1 | BI16: =Tabla58[[#This Row],[Integración May/2025]] -> 1 | BJ16: =AVERAGE(Tabla4[[#This Row],[Creación y captura May/2025]:[Compartición e Interoperabilidad May/2025]]) -> 1 | BK16: 1 | BL16: 1 | BM16: =AVERAGE('Calidad de Datos'!AQ20:AT20) -> 1 | BN16: =Tabla13[[#This Row],[Uso y acceso Dic/2025]] -> 1 | BO16: =Tabla58[[#This Row],[Integración Dic/2025]] -> 1 | BP16: =AVERAGE(Tabla4[[#This Row],[Creación y captura Dic/2025]:[Compartición e Interoperabilidad Dic/2025]]) -> 1
B17: Metas de Comercial | C17: 1 | D17: 1 | E17: =AVERAGE('Calidad de Datos'!C21:F21) -> 1 | F17: =Tabla13[[#This Row],[Uso y acceso Ago/2024]] -> 1 | G17: =Tabla58[[#This Row],[Integración Ago/2024]] -> 1 | H17: =AVERAGE(Tabla4[[#This Row],[Creación y captura Ago/2024]:[Compartición e Interoperabilidad Ago/2024]]) -> 1 | I17: 1 | J17: 1 | K17: =AVERAGE('Calidad de Datos'!G21:J21) -> 1 | L17: =Tabla13[[#This Row],[Uso y acceso Sep/2024]] -> 1 | M17: =Tabla58[[#This Row],[Integración Sep/2024]] -> 1 | N17: =AVERAGE(Tabla4[[#This Row],[Creación y captura Sep/2024]:[Compartición e Interoperabilidad Sep/2024]]) -> 1 | O17: 1 | P17: 1 | Q17: =AVERAGE('Calidad de Datos'!K21:N21) -> 1 | R17: =Tabla13[[#This Row],[Uso y acceso Oct/2024]] -> 1 | S17: =Tabla58[[#This Row],[Integración Oct/2024]] -> 1 | T17: =AVERAGE(Tabla4[[#This Row],[Creación y captura Oct/2024]:[Compartición e Interoperabilidad Oct/2024]]) -> 1 | U17: 1 | V17: 1 | W17: =AVERAGE('Calidad de Datos'!O21:R21) -> 1 | X17: =Tabla13[[#This Row],[Uso y acceso Nov/2024]] -> 1 | Y17: =Tabla58[[#This Row],[Integración Nov/2024]] -> 1 | Z17: =AVERAGE(Tabla4[[#This Row],[Creación y captura Nov/2024]:[Compartición e Interoperabilidad Nov/2024]]) -> 1 | AA17: 1 | AB17: 1 | AC17: =AVERAGE('Calidad de Datos'!S21:V21) -> 1 | AD17: =Tabla13[[#This Row],[Uso y acceso Dic/2024]] -> 1 | AE17: =Tabla58[[#This Row],[Integración Dic/2024]] -> 1 | AF17: =AVERAGE(Tabla4[[#This Row],[Creación y captura Dic/2024]:[Compartición e Interoperabilidad Dic/2024]]) -> 1 | AG17: 1 | AH17: 1 | AI17: =AVERAGE('Calidad de Datos'!W21:Z21) -> 1 | AJ17: =Tabla13[[#This Row],[Uso y acceso Ene/2025]] -> 1 | AK17: =Tabla58[[#This Row],[Integración Ene/2025]] -> 1 | AL17: =AVERAGE(Tabla4[[#This Row],[Creación y captura Ene/2025]:[Compartición e Interoperabilidad Ene/2025]]) -> 1 | AM17: 1 | AN17: 1 | AO17: =AVERAGE('Calidad de Datos'!AA21:AD21) -> 1 | AP17: =Tabla13[[#This Row],[Uso y acceso Feb/2025]] -> 1 | AQ17: =Tabla58[[#This Row],[Integración Feb/2025]] -> 1 | AR17: =AVERAGE(Tabla4[[#This Row],[Creación y captura Feb/2025]:[Compartición e Interoperabilidad Feb/2025]]) -> 1 | AS17: 1 | AT17: 1 | AU17: =AVERAGE('Calidad de Datos'!AE21:AH21) -> 1 | AV17: =Tabla13[[#This Row],[Uso y acceso Mar/2025]] -> 1 | AW17: =Tabla58[[#This Row],[Integración Mar/2025]] -> 1 | AX17: =AVERAGE(Tabla4[[#This Row],[Creación y captura Mar/2025]:[Compartición e Interoperabilidad Mar/2025]]) -> 1 | AY17: 1 | AZ17: 1 | BA17: =AVERAGE('Calidad de Datos'!AI21:AL21) -> 1 | BB17: =Tabla13[[#This Row],[Uso y acceso Abr/2025]] -> 1 | BC17: =Tabla58[[#This Row],[Integración Abr/2025]] -> 1 | BD17: =AVERAGE(Tabla4[[#This Row],[Creación y captura Abr/2025]:[Compartición e Interoperabilidad Abr/2025]]) -> 1 | BE17: 1 | BF17: 1 | BG17: =AVERAGE('Calidad de Datos'!AM21:AP21) -> 1 | BH17: =Tabla13[[#This Row],[Uso y acceso May/2025]] -> 1 | BI17: =Tabla58[[#This Row],[Integración May/2025]] -> 1 | BJ17: =AVERAGE(Tabla4[[#This Row],[Creación y captura May/2025]:[Compartición e Interoperabilidad May/2025]]) -> 1 | BK17: 1 | BL17: 1 | BM17: =AVERAGE('Calidad de Datos'!AQ21:AT21) -> 1 | BN17: =Tabla13[[#This Row],[Uso y acceso Dic/2025]] -> 1 | BO17: =Tabla58[[#This Row],[Integración Dic/2025]] -> 1 | BP17: =AVERAGE(Tabla4[[#This Row],[Creación y captura Dic/2025]:[Compartición e Interoperabilidad Dic/2025]]) -> 1
B18: Área | C18: 1 | D18: 1 | E18: =AVERAGE('Calidad de Datos'!C22:F22) -> 1 | F18: =Tabla13[[#This Row],[Uso y acceso Ago/2024]] -> 1 | G18: =Tabla58[[#This Row],[Integración Ago/2024]] -> 1 | H18: =AVERAGE(Tabla4[[#This Row],[Creación y captura Ago/2024]:[Compartición e Interoperabilidad Ago/2024]]) -> 1 | I18: 1 | J18: 1 | K18: =AVERAGE('Calidad de Datos'!G22:J22) -> 1 | L18: =Tabla13[[#This Row],[Uso y acceso Sep/2024]] -> 1 | M18: =Tabla58[[#This Row],[Integración Sep/2024]] -> 1 | N18: =AVERAGE(Tabla4[[#This Row],[Creación y captura Sep/2024]:[Compartición e Interoperabilidad Sep/2024]]) -> 1 | O18: 1 | P18: 1 | Q18: =AVERAGE('Calidad de Datos'!K22:N22) -> 1 | R18: =Tabla13[[#This Row],[Uso y acceso Oct/2024]] -> 1 | S18: =Tabla58[[#This Row],[Integración Oct/2024]] -> 1 | T18: =AVERAGE(Tabla4[[#This Row],[Creación y captura Oct/2024]:[Compartición e Interoperabilidad Oct/2024]]) -> 1 | U18: 1 | V18: 1 | W18: =AVERAGE('Calidad de Datos'!O22:R22) -> 1 | X18: =Tabla13[[#This Row],[Uso y acceso Nov/2024]] -> 1 | Y18: =Tabla58[[#This Row],[Integración Nov/2024]] -> 1 | Z18: =AVERAGE(Tabla4[[#This Row],[Creación y captura Nov/2024]:[Compartición e Interoperabilidad Nov/2024]]) -> 1 | AA18: 1 | AB18: 1 | AC18: =AVERAGE('Calidad de Datos'!S22:V22) -> 1 | AD18: =Tabla13[[#This Row],[Uso y acceso Dic/2024]] -> 1 | AE18: =Tabla58[[#This Row],[Integración Dic/2024]] -> 1 | AF18: =AVERAGE(Tabla4[[#This Row],[Creación y captura Dic/2024]:[Compartición e Interoperabilidad Dic/2024]]) -> 1 | AG18: 1 | AH18: 1 | AI18: =AVERAGE('Calidad de Datos'!W22:Z22) -> 1 | AJ18: =Tabla13[[#This Row],[Uso y acceso Ene/2025]] -> 1 | AK18: =Tabla58[[#This Row],[Integración Ene/2025]] -> 1 | AL18: =AVERAGE(Tabla4[[#This Row],[Creación y captura Ene/2025]:[Compartición e Interoperabilidad Ene/2025]]) -> 1 | AM18: 1 | AN18: 1 | AO18: =AVERAGE('Calidad de Datos'!AA22:AD22) -> 1 | AP18: =Tabla13[[#This Row],[Uso y acceso Feb/2025]] -> 1 | AQ18: =Tabla58[[#This Row],[Integración Feb/2025]] -> 1 | AR18: =AVERAGE(Tabla4[[#This Row],[Creación y captura Feb/2025]:[Compartición e Interoperabilidad Feb/2025]]) -> 1 | AS18: 1 | AT18: 1 | AU18: =AVERAGE('Calidad de Datos'!AE22:AH22) -> 1 | AV18: =Tabla13[[#This Row],[Uso y acceso Mar/2025]] -> 1 | AW18: =Tabla58[[#This Row],[Integración Mar/2025]] -> 1 | AX18: =AVERAGE(Tabla4[[#This Row],[Creación y captura Mar/2025]:[Compartición e Interoperabilidad Mar/2025]]) -> 1 | AY18: 1 | AZ18: 1 | BA18: =AVERAGE('Calidad de Datos'!AI22:AL22) -> 1 | BB18: =Tabla13[[#This Row],[Uso y acceso Abr/2025]] -> 1 | BC18: =Tabla58[[#This Row],[Integración Abr/2025]] -> 1 | BD18: =AVERAGE(Tabla4[[#This Row],[Creación y captura Abr/2025]:[Compartición e Interoperabilidad Abr/2025]]) -> 1 | BE18: 1 | BF18: 1 | BG18: =AVERAGE('Calidad de Datos'!AM22:AP22) -> 1 | BH18: =Tabla13[[#This Row],[Uso y acceso May/2025]] -> 1 | BI18: =Tabla58[[#This Row],[Integración May/2025]] -> 1 | BJ18: =AVERAGE(Tabla4[[#This Row],[Creación y captura May/2025]:[Compartición e Interoperabilidad May/2025]]) -> 1 | BK18: 1 | BL18: 1 | BM18: =AVERAGE('Calidad de Datos'!AQ22:AT22) -> 1 | BN18: =Tabla13[[#This Row],[Uso y acceso Dic/2025]] -> 1 | BO18: =Tabla58[[#This Row],[Integración Dic/2025]] -> 1 | BP18: =AVERAGE(Tabla4[[#This Row],[Creación y captura Dic/2025]:[Compartición e Interoperabilidad Dic/2025]]) -> 1
... B39: Semáforo alerta de proyectos | C39: 1 | D39: 1 | E39: =AVERAGE('Calidad de Datos'!C43:F43) -> 0.8875 | F39: =Tabla13[[#This Row],[Uso y acceso Ago/2024]] -> 1 | G39: =Tabla58[[#This Row],[Integración Ago/2024]] -> 1 | H39: =AVERAGE(Tabla4[[#This Row],[Creación y captura Ago/2024]:[Compartición e Interoperabilidad Ago/2024]]) -> 0.9775 | I39: 1 | J39: 1 | K39: =AVERAGE('Calidad de Datos'!G43:J43) -> 0.9125 | L39: =Tabla13[[#This Row],[Uso y acceso Sep/2024]] -> 1 | M39: =Tabla58[[#This Row],[Integración Sep/2024]] -> 1 | N39: =AVERAGE(Tabla4[[#This Row],[Creación y captura Sep/2024]:[Compartición e Interoperabilidad Sep/2024]]) -> 0.9825 | O39: 1 | P39: 1 | Q39: =AVERAGE('Calidad de Datos'!K43:N43) -> 0.9125 | R39: =Tabla13[[#This Row],[Uso y acceso Oct/2024]] -> 1 | S39: =Tabla58[[#This Row],[Integración Oct/2024]] -> 1 | T39: =AVERAGE(Tabla4[[#This Row],[Creación y captura Oct/2024]:[Compartición e Interoperabilidad Oct/2024]]) -> 0.9825 | U39: 1 | V39: 1 | W39: =AVERAGE('Calidad de Datos'!O43:R43) -> 1 | X39: =Tabla13[[#This Row],[Uso y acceso Nov/2024]] -> 1 | Y39: =Tabla58[[#This Row],[Integración Nov/2024]] -> 1 | Z39: =AVERAGE(Tabla4[[#This Row],[Creación y captura Nov/2024]:[Compartición e Interoperabilidad Nov/2024]]) -> 1 | AA39: 1 | AB39: 1 | AC39: =AVERAGE('Calidad de Datos'!S43:V43) -> 1 | AD39: =Tabla13[[#This Row],[Uso y acceso Dic/2024]] -> 1 | AE39: =Tabla58[[#This Row],[Integración Dic/2024]] -> 1 | AF39: =AVERAGE(Tabla4[[#This Row],[Creación y captura Dic/2024]:[Compartición e Interoperabilidad Dic/2024]]) -> 1 | AG39: 1 | AH39: 1 | AI39: =AVERAGE('Calidad de Datos'!W43:Z43) -> 1 | AJ39: =Tabla13[[#This Row],[Uso y acceso Ene/2025]] -> 1 | AK39: =Tabla58[[#This Row],[Integración Ene/2025]] -> 1 | AL39: =AVERAGE(Tabla4[[#This Row],[Creación y captura Ene/2025]:[Compartición e Interoperabilidad Ene/2025]]) -> 1 | AM39: 1 | AN39: 1 | AO39: =AVERAGE('Calidad de Datos'!AA43:AD43) -> 1 | AP39: =Tabla13[[#This Row],[Uso y acceso Feb/2025]] -> 1 | AQ39: =Tabla58[[#This Row],[Integración Feb/2025]] -> 1 | AR39: =AVERAGE(Tabla4[[#This Row],[Creación y captura Feb/2025]:[Compartición e Interoperabilidad Feb/2025]]) -> 1 | AS39: 1 | AT39: 1 | AU39: =AVERAGE('Calidad de Datos'!AE43:AH43) -> 1 | AV39: =Tabla13[[#This Row],[Uso y acceso Mar/2025]] -> 1 | AW39: =Tabla58[[#This Row],[Integración Mar/2025]] -> 1 | AX39: =AVERAGE(Tabla4[[#This Row],[Creación y captura Mar/2025]:[Compartición e Interoperabilidad Mar/2025]]) -> 1 | AY39: 1 | AZ39: 1 | BA39: =AVERAGE('Calidad de Datos'!AI43:AL43) -> 1 | BB39: =Tabla13[[#This Row],[Uso y acceso Abr/2025]] -> 1 | BC39: =Tabla58[[#This Row],[Integración Abr/2025]] -> 1 | BD39: =AVERAGE(Tabla4[[#This Row],[Creación y captura Abr/2025]:[Compartición e Interoperabilidad Abr/2025]]) -> 1 | BE39: 1 | BF39: 1 | BG39: =AVERAGE('Calidad de Datos'!AM43:AP43) -> 1 | BH39: =Tabla13[[#This Row],[Uso y acceso May/2025]] -> 1 | BI39: =Tabla58[[#This Row],[Integración May/2025]] -> 1 | BJ39: =AVERAGE(Tabla4[[#This Row],[Creación y captura May/2025]:[Compartición e Interoperabilidad May/2025]]) -> 1 | BK39: 1 | BL39: 1 | BM39: =AVERAGE('Calidad de Datos'!AQ43:AT43) -> 1 | BN39: =Tabla13[[#This Row],[Uso y acceso Dic/2025]] -> 1 | BO39: =Tabla58[[#This Row],[Integración Dic/2025]] -> 1 | BP39: =AVERAGE(Tabla4[[#This Row],[Creación y captura Dic/2025]:[Compartición e Interoperabilidad Dic/2025]]) -> 1
B40: Nivel educativo | E40: =AVERAGE('Calidad de Datos'!C44:F44) -> 0 | F40: =Tabla13[[#This Row],[Uso y acceso Ago/2024]] -> 0.3 | G40: =Tabla58[[#This Row],[Integración Ago/2024]] -> 0 | H40: =AVERAGE(Tabla4[[#This Row],[Creación y captura Ago/2024]:[Compartición e Interoperabilidad Ago/2024]]) -> 0.1 | K40: =AVERAGE('Calidad de Datos'!G44:J44) -> 0 | L40: =Tabla13[[#This Row],[Uso y acceso Sep/2024]] -> 0.3 | M40: =Tabla58[[#This Row],[Integración Sep/2024]] -> 0 | N40: =AVERAGE(Tabla4[[#This Row],[Creación y captura Sep/2024]:[Compartición e Interoperabilidad Sep/2024]]) -> 0.1 | O40: 0.5 | P40: 0.2 | Q40: =AVERAGE('Calidad de Datos'!K44:N44) -> 0 | R40: =Tabla13[[#This Row],[Uso y acceso Oct/2024]] -> 0.5 | S40: =Tabla58[[#This Row],[Integración Oct/2024]] -> 0.2 | T40: =AVERAGE(Tabla4[[#This Row],[Creación y captura Oct/2024]:[Compartición e Interoperabilidad Oct/2024]]) -> 0.28 | U40: 1 | V40: 1 | W40: =AVERAGE('Calidad de Datos'!O44:R44) -> 1 | X40: =Tabla13[[#This Row],[Uso y acceso Nov/2024]] -> 1 | Y40: =Tabla58[[#This Row],[Integración Nov/2024]] -> 0.5 | Z40: =AVERAGE(Tabla4[[#This Row],[Creación y captura Nov/2024]:[Compartición e Interoperabilidad Nov/2024]]) -> 0.9 | AA40: 1 | AB40: 1 | AC40: =AVERAGE('Calidad de Datos'!S44:V44) -> 1 | AD40: =Tabla13[[#This Row],[Uso y acceso Dic/2024]] -> 1 | AE40: =Tabla58[[#This Row],[Integración Dic/2024]] -> 1 | AF40: =AVERAGE(Tabla4[[#This Row],[Creación y captura Dic/2024]:[Compartición e Interoperabilidad Dic/2024]]) -> 1 | AG40: 1 | AH40: 1 | AI40: =AVERAGE('Calidad de Datos'!W44:Z44) -> 1 | AJ40: =Tabla13[[#This Row],[Uso y acceso Ene/2025]] -> 1 | AK40: =Tabla58[[#This Row],[Integración Ene/2025]] -> 1 | AL40: =AVERAGE(Tabla4[[#This Row],[Creación y captura Ene/2025]:[Compartición e Interoperabilidad Ene/2025]]) -> 1 | AM40: 1 | AN40: 1 | AO40: =AVERAGE('Calidad de Datos'!AA44:AD44) -> 1 | AP40: =Tabla13[[#This Row],[Uso y acceso Feb/2025]] -> 1 | AQ40: =Tabla58[[#This Row],[Integración Feb/2025]] -> 1 | AR40: =AVERAGE(Tabla4[[#This Row],[Creación y captura Feb/2025]:[Compartición e Interoperabilidad Feb/2025]]) -> 1 | AS40: 1 | AT40: 1 | AU40: =AVERAGE('Calidad de Datos'!AE44:AH44) -> 1 | AV40: =Tabla13[[#This Row],[Uso y acceso Mar/2025]] -> 1 | AW40: =Tabla58[[#This Row],[Integración Mar/2025]] -> 1 | AX40: =AVERAGE(Tabla4[[#This Row],[Creación y captura Mar/2025]:[Compartición e Interoperabilidad Mar/2025]]) -> 1 | AY40: 1 | AZ40: 1 | BA40: =AVERAGE('Calidad de Datos'!AI44:AL44) -> 1 | BB40: =Tabla13[[#This Row],[Uso y acceso Abr/2025]] -> 1 | BC40: =Tabla58[[#This Row],[Integración Abr/2025]] -> 1 | BD40: =AVERAGE(Tabla4[[#This Row],[Creación y captura Abr/2025]:[Compartición e Interoperabilidad Abr/2025]]) -> 1 | BE40: 1 | BF40: 1 | BG40: =AVERAGE('Calidad de Datos'!AM44:AP44) -> 1 | BH40: =Tabla13[[#This Row],[Uso y acceso May/2025]] -> 1 | BI40: =Tabla58[[#This Row],[Integración May/2025]] -> 1 | BJ40: =AVERAGE(Tabla4[[#This Row],[Creación y captura May/2025]:[Compartición e Interoperabilidad May/2025]]) -> 1 | BK40: 1 | BL40: 1 | BM40: =AVERAGE('Calidad de Datos'!AQ44:AT44) -> 1 | BN40: =Tabla13[[#This Row],[Uso y acceso Dic/2025]] -> 1 | BO40: =Tabla58[[#This Row],[Integración Dic/2025]] -> 1 | BP40: =AVERAGE(Tabla4[[#This Row],[Creación y captura Dic/2025]:[Compartición e Interoperabilidad Dic/2025]]) -> 1
B41: Tipo de contrato laboral | E41: =AVERAGE('Calidad de Datos'!C45:F45) -> 0 | F41: =Tabla13[[#This Row],[Uso y acceso Ago/2024]] -> 0.3 | G41: =Tabla58[[#This Row],[Integración Ago/2024]] -> 0 | H41: =AVERAGE(Tabla4[[#This Row],[Creación y captura Ago/2024]:[Compartición e Interoperabilidad Ago/2024]]) -> 0.1 | K41: =AVERAGE('Calidad de Datos'!G45:J45) -> 0 | L41: =Tabla13[[#This Row],[Uso y acceso Sep/2024]] -> 0.3 | M41: =Tabla58[[#This Row],[Integración Sep/2024]] -> 0 | N41: =AVERAGE(Tabla4[[#This Row],[Creación y captura Sep/2024]:[Compartición e Interoperabilidad Sep/2024]]) -> 0.1 | O41: 0.5 | P41: 0.2 | Q41: =AVERAGE('Calidad de Datos'!K45:N45) -> 0 | R41: =Tabla13[[#This Row],[Uso y acceso Oct/2024]] -> 0.5 | S41: =Tabla58[[#This Row],[Integración Oct/2024]] -> 0.2 | T41: =AVERAGE(Tabla4[[#This Row],[Creación y captura Oct/2024]:[Compartición e Interoperabilidad Oct/2024]]) -> 0.28 | U41: 1 | V41: 1 | W41: =AVERAGE('Calidad de Datos'!O45:R45) -> 1 | X41: =Tabla13[[#This Row],[Uso y acceso Nov/2024]] -> 1 | Y41: =Tabla58[[#This Row],[Integración Nov/2024]] -> 0.5 | Z41: =AVERAGE(Tabla4[[#This Row],[Creación y captura Nov/2024]:[Compartición e Interoperabilidad Nov/2024]]) -> 0.9 | AA41: 1 | AB41: 1 | AC41: =AVERAGE('Calidad de Datos'!S45:V45) -> 1 | AD41: =Tabla13[[#This Row],[Uso y acceso Dic/2024]] -> 1 | AE41: =Tabla58[[#This Row],[Integración Dic/2024]] -> 1 | AF41: =AVERAGE(Tabla4[[#This Row],[Creación y captura Dic/2024]:[Compartición e Interoperabilidad Dic/2024]]) -> 1 | AG41: 1 | AH41: 1 | AI41: =AVERAGE('Calidad de Datos'!W45:Z45) -> 1 | AJ41: =Tabla13[[#This Row],[Uso y acceso Ene/2025]] -> 1 | AK41: =Tabla58[[#This Row],[Integración Ene/2025]] -> 1 | AL41: =AVERAGE(Tabla4[[#This Row],[Creación y captura Ene/2025]:[Compartición e Interoperabilidad Ene/2025]]) -> 1 | AM41: 1 | AN41: 1 | AO41: =AVERAGE('Calidad de Datos'!AA45:AD45) -> 1 | AP41: =Tabla13[[#This Row],[Uso y acceso Feb/2025]] -> 1 | AQ41: =Tabla58[[#This Row],[Integración Feb/2025]] -> 1 | AR41: =AVERAGE(Tabla4[[#This Row],[Creación y captura Feb/2025]:[Compartición e Interoperabilidad Feb/2025]]) -> 1 | AS41: 1 | AT41: 1 | AU41: =AVERAGE('Calidad de Datos'!AE45:AH45) -> 1 | AV41: =Tabla13[[#This Row],[Uso y acceso Mar/2025]] -> 1 | AW41: =Tabla58[[#This Row],[Integración Mar/2025]] -> 1 | AX41: =AVERAGE(Tabla4[[#This Row],[Creación y captura Mar/2025]:[Compartición e Interoperabilidad Mar/2025]]) -> 1 | AY41: 1 | AZ41: 1 | BA41: =AVERAGE('Calidad de Datos'!AI45:AL45) -> 1 | BB41: =Tabla13[[#This Row],[Uso y acceso Abr/2025]] -> 1 | BC41: =Tabla58[[#This Row],[Integración Abr/2025]] -> 1 | BD41: =AVERAGE(Tabla4[[#This Row],[Creación y captura Abr/2025]:[Compartición e Interoperabilidad Abr/2025]]) -> 1 | BE41: 1 | BF41: 1 | BG41: =AVERAGE('Calidad de Datos'!AM45:AP45) -> 1 | BH41: =Tabla13[[#This Row],[Uso y acceso May/2025]] -> 1 | BI41: =Tabla58[[#This Row],[Integración May/2025]] -> 1 | BJ41: =AVERAGE(Tabla4[[#This Row],[Creación y captura May/2025]:[Compartición e Interoperabilidad May/2025]]) -> 1 | BK41: 1 | BL41: 1 | BM41: =AVERAGE('Calidad de Datos'!AQ45:AT45) -> 1 | BN41: =Tabla13[[#This Row],[Uso y acceso Dic/2025]] -> 1 | BO41: =Tabla58[[#This Row],[Integración Dic/2025]] -> 1 | BP41: =AVERAGE(Tabla4[[#This Row],[Creación y captura Dic/2025]:[Compartición e Interoperabilidad Dic/2025]]) -> 1
B42: Departamento-Municipio | E42: =AVERAGE('Calidad de Datos'!C46:F46) -> 0 | F42: =Tabla13[[#This Row],[Uso y acceso Ago/2024]] -> 0 | G42: =Tabla58[[#This Row],[Integración Ago/2024]] -> 0 | H42: =AVERAGE(Tabla4[[#This Row],[Creación y captura Ago/2024]:[Compartición e Interoperabilidad Ago/2024]]) -> 0 | I42: 0.2 | J42: 0.2 | K42: =AVERAGE('Calidad de Datos'!G46:J46) -> 0 | L42: =Tabla13[[#This Row],[Uso y acceso Sep/2024]] -> 0 | M42: =Tabla58[[#This Row],[Integración Sep/2024]] -> 0.2 | N42: =AVERAGE(Tabla4[[#This Row],[Creación y captura Sep/2024]:[Compartición e Interoperabilidad Sep/2024]]) -> 0.12 | O42: 0.55 | P42: 0.25 | Q42: =AVERAGE('Calidad de Datos'!K46:N46) -> 0 | R42: =Tabla13[[#This Row],[Uso y acceso Oct/2024]] -> 1 | S42: =Tabla58[[#This Row],[Integración Oct/2024]] -> 0.25 | T42: =AVERAGE(Tabla4[[#This Row],[Creación y captura Oct/2024]:[Compartición e Interoperabilidad Oct/2024]]) -> 0.41 | U42: 1 | V42: 1 | W42: =AVERAGE('Calidad de Datos'!O46:R46) -> 1 | X42: =Tabla13[[#This Row],[Uso y acceso Nov/2024]] -> 1 | Y42: =Tabla58[[#This Row],[Integración Nov/2024]] -> 0.5 | Z42: =AVERAGE(Tabla4[[#This Row],[Creación y captura Nov/2024]:[Compartición e Interoperabilidad Nov/2024]]) -> 0.9 | AA42: 1 | AB42: 1 | AC42: =AVERAGE('Calidad de Datos'!S46:V46) -> 1 | AD42: =Tabla13[[#This Row],[Uso y acceso Dic/2024]] -> 1 | AE42: =Tabla58[[#This Row],[Integración Dic/2024]] -> 1 | AF42: =AVERAGE(Tabla4[[#This Row],[Creación y captura Dic/2024]:[Compartición e Interoperabilidad Dic/2024]]) -> 1 | AG42: 1 | AH42: 1 | AI42: =AVERAGE('Calidad de Datos'!W46:Z46) -> 1 | AJ42: =Tabla13[[#This Row],[Uso y acceso Ene/2025]] -> 1 | AK42: =Tabla58[[#This Row],[Integración Ene/2025]] -> 1 | AL42: =AVERAGE(Tabla4[[#This Row],[Creación y captura Ene/2025]:[Compartición e Interoperabilidad Ene/2025]]) -> 1 | AM42: 1 | AN42: 1 | AO42: =AVERAGE('Calidad de Datos'!AA46:AD46) -> 1 | AP42: =Tabla13[[#This Row],[Uso y acceso Feb/2025]] -> 1 | AQ42: =Tabla58[[#This Row],[Integración Feb/2025]] -> 1 | AR42: =AVERAGE(Tabla4[[#This Row],[Creación y captura Feb/2025]:[Compartición e Interoperabilidad Feb/2025]]) -> 1 | AS42: 1 | AT42: 1 | AU42: =AVERAGE('Calidad de Datos'!AE46:AH46) -> 1 | AV42: =Tabla13[[#This Row],[Uso y acceso Mar/2025]] -> 1 | AW42: =Tabla58[[#This Row],[Integración Mar/2025]] -> 1 | AX42: =AVERAGE(Tabla4[[#This Row],[Creación y captura Mar/2025]:[Compartición e Interoperabilidad Mar/2025]]) -> 1 | AY42: 1 | AZ42: 1 | BA42: =AVERAGE('Calidad de Datos'!AI46:AL46) -> 1 | BB42: =Tabla13[[#This Row],[Uso y acceso Abr/2025]] -> 1 | BC42: =Tabla58[[#This Row],[Integración Abr/2025]] -> 1 | BD42: =AVERAGE(Tabla4[[#This Row],[Creación y captura Abr/2025]:[Compartición e Interoperabilidad Abr/2025]]) -> 1 | BE42: 1 | BF42: 1 | BG42: =AVERAGE('Calidad de Datos'!AM46:AP46) -> 1 | BH42: =Tabla13[[#This Row],[Uso y acceso May/2025]] -> 1 | BI42: =Tabla58[[#This Row],[Integración May/2025]] -> 1 | BJ42: =AVERAGE(Tabla4[[#This Row],[Creación y captura May/2025]:[Compartición e Interoperabilidad May/2025]]) -> 1 | BK42: 1 | BL42: 1 | BM42: =AVERAGE('Calidad de Datos'!AQ46:AT46) -> 1 | BN42: =Tabla13[[#This Row],[Uso y acceso Dic/2025]] -> 1 | BO42: =Tabla58[[#This Row],[Integración Dic/2025]] -> 1 | BP42: =AVERAGE(Tabla4[[#This Row],[Creación y captura Dic/2025]:[Compartición e Interoperabilidad Dic/2025]]) -> 1
B43: Persona datos laborales | E43: =AVERAGE('Calidad de Datos'!C47:F47) -> 0 | F43: =Tabla13[[#This Row],[Uso y acceso Ago/2024]] -> 0.5 | G43: =Tabla58[[#This Row],[Integración Ago/2024]] -> 0 | H43: =AVERAGE(Tabla4[[#This Row],[Creación y captura Ago/2024]:[Compartición e Interoperabilidad Ago/2024]]) -> 0.16666667 | K43: =AVERAGE('Calidad de Datos'!G47:J47) -> 0 | L43: =Tabla13[[#This Row],[Uso y acceso Sep/2024]] -> 0.9 | M43: =Tabla58[[#This Row],[Integración Sep/2024]] -> 0 | N43: =AVERAGE(Tabla4[[#This Row],[Creación y captura Sep/2024]:[Compartición e Interoperabilidad Sep/2024]]) -> 0.3 | O43: 0.3 | P43: 0.15 | Q43: =AVERAGE('Calidad de Datos'!K47:N47) -> 0 | R43: =Tabla13[[#This Row],[Uso y acceso Oct/2024]] -> 0.9 | S43: =Tabla58[[#This Row],[Integración Oct/2024]] -> 0.15 | T43: =AVERAGE(Tabla4[[#This Row],[Creación y captura Oct/2024]:[Compartición e Interoperabilidad Oct/2024]]) -> 0.3 | U43: 0.8 | V43: 0.8 | W43: =AVERAGE('Calidad de Datos'!O47:R47) -> 0.805 | X43: =Tabla13[[#This Row],[Uso y acceso Nov/2024]] -> 0.995 | Y43: =Tabla58[[#This Row],[Integración Nov/2024]] -> 0.6 | Z43: =AVERAGE(Tabla4[[#This Row],[Creación y captura Nov/2024]:[Compartición e Interoperabilidad Nov/2024]]) -> 0.8 | AA43: 0.9 | AB43: 0.9 | AC43: =AVERAGE('Calidad de Datos'!S47:V47) -> 0.905 | AD43: =Tabla13[[#This Row],[Uso y acceso Dic/2024]] -> 0.995 | AE43: =Tabla58[[#This Row],[Integración Dic/2024]] -> 0.9 | AF43: =AVERAGE(Tabla4[[#This Row],[Creación y captura Dic/2024]:[Compartición e Interoperabilidad Dic/2024]]) -> 0.92 | AG43: 0.95 | AH43: 1 | AI43: =AVERAGE('Calidad de Datos'!W47:Z47) -> 0.9375 | AJ43: =Tabla13[[#This Row],[Uso y acceso Ene/2025]] -> 0.995 | AK43: =Tabla58[[#This Row],[Integración Ene/2025]] -> 0.95 | AL43: =AVERAGE(Tabla4[[#This Row],[Creación y captura Ene/2025]:[Compartición e Interoperabilidad Ene/2025]]) -> 0.9665 | AM43: 0.95 | AN43: 1 | AO43: =AVERAGE('Calidad de Datos'!AA47:AD47) -> 0.9825 | AP43: =Tabla13[[#This Row],[Uso y acceso Feb/2025]] -> 0.995 | AQ43: =Tabla58[[#This Row],[Integración Feb/2025]] -> 1 | AR43: =AVERAGE(Tabla4[[#This Row],[Creación y captura Feb/2025]:[Compartición e Interoperabilidad Feb/2025]]) -> 0.9855 | AS43: 0.95 | AT43: 1 | AU43: =AVERAGE('Calidad de Datos'!AE47:AH47) -> 0.9875 | AV43: =Tabla13[[#This Row],[Uso y acceso Mar/2025]] -> 0.995 | AW43: =Tabla58[[#This Row],[Integración Mar/2025]] -> 1 | AX43: =AVERAGE(Tabla4[[#This Row],[Creación y captura Mar/2025]:[Compartición e Interoperabilidad Mar/2025]]) -> 0.9865 | AY43: 1 | AZ43: 1 | BA43: =AVERAGE('Calidad de Datos'!AI47:AL47) -> 1 | BB43: =Tabla13[[#This Row],[Uso y acceso Abr/2025]] -> 0.995 | BC43: =Tabla58[[#This Row],[Integración Abr/2025]] -> 1 | BD43: =AVERAGE(Tabla4[[#This Row],[Creación y captura Abr/2025]:[Compartición e Interoperabilidad Abr/2025]]) -> 0.999 | BE43: 1 | BF43: 1 | BG43: =AVERAGE('Calidad de Datos'!AM47:AP47) -> 1 | BH43: =Tabla13[[#This Row],[Uso y acceso May/2025]] -> 0.995 | BI43: =Tabla58[[#This Row],[Integración May/2025]] -> 1 | BJ43: =AVERAGE(Tabla4[[#This Row],[Creación y captura May/2025]:[Compartición e Interoperabilidad May/2025]]) -> 0.999 | BK43: 1 | BL43: 1 | BM43: =AVERAGE('Calidad de Datos'!AQ47:AT47) -> 1 | BN43: =Tabla13[[#This Row],[Uso y acceso Dic/2025]] -> 0.995 | BO43: =Tabla58[[#This Row],[Integración Dic/2025]] -> 1 | BP43: =AVERAGE(Tabla4[[#This Row],[Creación y captura Dic/2025]:[Compartición e Interoperabilidad Dic/2025]]) -> 0.999
B44: Asignación laboral | E44: =AVERAGE('Calidad de Datos'!C48:F48) -> 0 | F44: =Tabla13[[#This Row],[Uso y acceso Ago/2024]] -> 0.3 | G44: =Tabla58[[#This Row],[Integración Ago/2024]] -> 0 | H44: =AVERAGE(Tabla4[[#This Row],[Creación y captura Ago/2024]:[Compartición e Interoperabilidad Ago/2024]]) -> 0.1 | K44: =AVERAGE('Calidad de Datos'!G48:J48) -> 0 | L44: =Tabla13[[#This Row],[Uso y acceso Sep/2024]] -> 0.3 | M44: =Tabla58[[#This Row],[Integración Sep/2024]] -> 0 | N44: =AVERAGE(Tabla4[[#This Row],[Creación y captura Sep/2024]:[Compartición e Interoperabilidad Sep/2024]]) -> 0.1 | O44: 0.3 | P44: 0.15 | Q44: =AVERAGE('Calidad de Datos'!K48:N48) -> 0 | R44: =Tabla13[[#This Row],[Uso y acceso Oct/2024]] -> 1 | S44: =Tabla58[[#This Row],[Integración Oct/2024]] -> 0.15 | T44: =AVERAGE(Tabla4[[#This Row],[Creación y captura Oct/2024]:[Compartición e Interoperabilidad Oct/2024]]) -> 0.32 | U44: 1 | V44: 1 | W44: =AVERAGE('Calidad de Datos'!O48:R48) -> 1 | X44: =Tabla13[[#This Row],[Uso y acceso Nov/2024]] -> 1 | Y44: =Tabla58[[#This Row],[Integración Nov/2024]] -> 0.6 | Z44: =AVERAGE(Tabla4[[#This Row],[Creación y captura Nov/2024]:[Compartición e Interoperabilidad Nov/2024]]) -> 0.92 | AA44: 1 | AB44: 1 | AC44: =AVERAGE('Calidad de Datos'!S48:V48) -> 1 | AD44: =Tabla13[[#This Row],[Uso y acceso Dic/2024]] -> 1 | AE44: =Tabla58[[#This Row],[Integración Dic/2024]] -> 1 | AF44: =AVERAGE(Tabla4[[#This Row],[Creación y captura Dic/2024]:[Compartición e Interoperabilidad Dic/2024]]) -> 1 | AG44: 1 | AH44: 1 | AI44: =AVERAGE('Calidad de Datos'!W48:Z48) -> 1 | AJ44: =Tabla13[[#This Row],[Uso y acceso Ene/2025]] -> 1 | AK44: =Tabla58[[#This Row],[Integración Ene/2025]] -> 1 | AL44: =AVERAGE(Tabla4[[#This Row],[Creación y captura Ene/2025]:[Compartición e Interoperabilidad Ene/2025]]) -> 1 | AM44: 1 | AN44: 1 | AO44: =AVERAGE('Calidad de Datos'!AA48:AD48) -> 1 | AP44: =Tabla13[[#This Row],[Uso y acceso Feb/2025]] -> 1 | AQ44: =Tabla58[[#This Row],[Integración Feb/2025]] -> 1 | AR44: =AVERAGE(Tabla4[[#This Row],[Creación y captura Feb/2025]:[Compartición e Interoperabilidad Feb/2025]]) -> 1 | AS44: 1 | AT44: 1 | AU44: =AVERAGE('Calidad de Datos'!AE48:AH48) -> 1 | AV44: =Tabla13[[#This Row],[Uso y acceso Mar/2025]] -> 1 | AW44: =Tabla58[[#This Row],[Integración Mar/2025]] -> 1 | AX44: =AVERAGE(Tabla4[[#This Row],[Creación y captura Mar/2025]:[Compartición e Interoperabilidad Mar/2025]]) -> 1 | AY44: 1 | AZ44: 1 | BA44: =AVERAGE('Calidad de Datos'!AI48:AL48) -> 1 | BB44: =Tabla13[[#This Row],[Uso y acceso Abr/2025]] -> 1 | BC44: =Tabla58[[#This Row],[Integración Abr/2025]] -> 1 | BD44: =AVERAGE(Tabla4[[#This Row],[Creación y captura Abr/2025]:[Compartición e Interoperabilidad Abr/2025]]) -> 1 | BE44: 1 | BF44: 1 | BG44: =AVERAGE('Calidad de Datos'!AM48:AP48) -> 1 | BH44: =Tabla13[[#This Row],[Uso y acceso May/2025]] -> 1 | BI44: =Tabla58[[#This Row],[Integración May/2025]] -> 1 | BJ44: =AVERAGE(Tabla4[[#This Row],[Creación y captura May/2025]:[Compartición e Interoperabilidad May/2025]]) -> 1 | BK44: 1 | BL44: 1 | BM44: =AVERAGE('Calidad de Datos'!AQ48:AT48) -> 1 | BN44: =Tabla13[[#This Row],[Uso y acceso Dic/2025]] -> 1 | BO44: =Tabla58[[#This Row],[Integración Dic/2025]] -> 1 | BP44: =AVERAGE(Tabla4[[#This Row],[Creación y captura Dic/2025]:[Compartición e Interoperabilidad Dic/2025]]) -> 1
B45: Estado laboral | E45: =AVERAGE('Calidad de Datos'!C49:F49) -> 0 | F45: =Tabla13[[#This Row],[Uso y acceso Ago/2024]] -> 0.3 | G45: =Tabla58[[#This Row],[Integración Ago/2024]] -> 0 | H45: =AVERAGE(Tabla4[[#This Row],[Creación y captura Ago/2024]:[Compartición e Interoperabilidad Ago/2024]]) -> 0.1 | K45: =AVERAGE('Calidad de Datos'!G49:J49) -> 0 | L45: =Tabla13[[#This Row],[Uso y acceso Sep/2024]] -> 0.3 | M45: =Tabla58[[#This Row],[Integración Sep/2024]] -> 0 | N45: =AVERAGE(Tabla4[[#This Row],[Creación y captura Sep/2024]:[Compartición e Interoperabilidad Sep/2024]]) -> 0.1 | O45: 0.5 | P45: 0.2 | Q45: =AVERAGE('Calidad de Datos'!K49:N49) -> 0 | R45: =Tabla13[[#This Row],[Uso y acceso Oct/2024]] -> 1 | S45: =Tabla58[[#This Row],[Integración Oct/2024]] -> 0.2 | T45: =AVERAGE(Tabla4[[#This Row],[Creación y captura Oct/2024]:[Compartición e Interoperabilidad Oct/2024]]) -> 0.38 | U45: 1 | V45: 1 | W45: =AVERAGE('Calidad de Datos'!O49:R49) -> 1 | X45: =Tabla13[[#This Row],[Uso y acceso Nov/2024]] -> 1 | Y45: =Tabla58[[#This Row],[Integración Nov/2024]] -> 0.5 | Z45: =AVERAGE(Tabla4[[#This Row],[Creación y captura Nov/2024]:[Compartición e Interoperabilidad Nov/2024]]) -> 0.9 | AA45: 1 | AB45: 1 | AC45: =AVERAGE('Calidad de Datos'!S49:V49) -> 1 | AD45: =Tabla13[[#This Row],[Uso y acceso Dic/2024]] -> 1 | AE45: =Tabla58[[#This Row],[Integración Dic/2024]] -> 1 | AF45: =AVERAGE(Tabla4[[#This Row],[Creación y captura Dic/2024]:[Compartición e Interoperabilidad Dic/2024]]) -> 1 | AG45: 1 | AH45: 1 | AI45: =AVERAGE('Calidad de Datos'!W49:Z49) -> 1 | AJ45: =Tabla13[[#This Row],[Uso y acceso Ene/2025]] -> 1 | AK45: =Tabla58[[#This Row],[Integración Ene/2025]] -> 1 | AL45: =AVERAGE(Tabla4[[#This Row],[Creación y captura Ene/2025]:[Compartición e Interoperabilidad Ene/2025]]) -> 1 | AM45: 1 | AN45: 1 | AO45: =AVERAGE('Calidad de Datos'!AA49:AD49) -> 1 | AP45: =Tabla13[[#This Row],[Uso y acceso Feb/2025]] -> 1 | AQ45: =Tabla58[[#This Row],[Integración Feb/2025]] -> 1 | AR45: =AVERAGE(Tabla4[[#This Row],[Creación y captura Feb/2025]:[Compartición e Interoperabilidad Feb/2025]]) -> 1 | AS45: 1 | AT45: 1 | AU45: =AVERAGE('Calidad de Datos'!AE49:AH49) -> 1 | AV45: =Tabla13[[#This Row],[Uso y acceso Mar/2025]] -> 1 | AW45: =Tabla58[[#This Row],[Integración Mar/2025]] -> 1 | AX45: =AVERAGE(Tabla4[[#This Row],[Creación y captura Mar/2025]:[Compartición e Interoperabilidad Mar/2025]]) -> 1 | AY45: 1 | AZ45: 1 | BA45: =AVERAGE('Calidad de Datos'!AI49:AL49) -> 1 | BB45: =Tabla13[[#This Row],[Uso y acceso Abr/2025]] -> 1 | BC45: =Tabla58[[#This Row],[Integración Abr/2025]] -> 1 | BD45: =AVERAGE(Tabla4[[#This Row],[Creación y captura Abr/2025]:[Compartición e Interoperabilidad Abr/2025]]) -> 1 | BE45: 1 | BF45: 1 | BG45: =AVERAGE('Calidad de Datos'!AM49:AP49) -> 1 | BH45: =Tabla13[[#This Row],[Uso y acceso May/2025]] -> 1 | BI45: =Tabla58[[#This Row],[Integración May/2025]] -> 1 | BJ45: =AVERAGE(Tabla4[[#This Row],[Creación y captura May/2025]:[Compartición e Interoperabilidad May/2025]]) -> 1 | BK45: 1 | BL45: 1 | BM45: =AVERAGE('Calidad de Datos'!AQ49:AT49) -> 1 | BN45: =Tabla13[[#This Row],[Uso y acceso Dic/2025]] -> 1 | BO45: =Tabla58[[#This Row],[Integración Dic/2025]] -> 1 | BP45: =AVERAGE(Tabla4[[#This Row],[Creación y captura Dic/2025]:[Compartición e Interoperabilidad Dic/2025]]) -> 1
B46: Categoría de cliente | C46: 1 | D46: 1 | E46: =AVERAGE('Calidad de Datos'!C50:F50) -> 1 | F46: =Tabla13[[#This Row],[Uso y acceso Ago/2024]] -> 1 | G46: =Tabla58[[#This Row],[Integración Ago/2024]] -> 1 | H46: =AVERAGE(Tabla4[[#This Row],[Creación y captura Ago/2024]:[Compartición e Interoperabilidad Ago/2024]]) -> 1 | I46: 1 | J46: 1 | K46: =AVERAGE('Calidad de Datos'!G50:J50) -> 1 | L46: =Tabla13[[#This Row],[Uso y acceso Sep/2024]] -> 1 | M46: =Tabla58[[#This Row],[Integración Sep/2024]] -> 1 | N46: =AVERAGE(Tabla4[[#This Row],[Creación y captura Sep/2024]:[Compartición e Interoperabilidad Sep/2024]]) -> 1 | O46: 1 | P46: 1 | Q46: =AVERAGE('Calidad de Datos'!K50:N50) -> 1 | R46: =Tabla13[[#This Row],[Uso y acceso Oct/2024]] -> 1 | S46: =Tabla58[[#This Row],[Integración Oct/2024]] -> 1 | T46: =AVERAGE(Tabla4[[#This Row],[Creación y captura Oct/2024]:[Compartición e Interoperabilidad Oct/2024]]) -> 1 | U46: 1 | V46: 1 | W46: =AVERAGE('Calidad de Datos'!O50:R50) -> 1 | X46: =Tabla13[[#This Row],[Uso y acceso Nov/2024]] -> 1 | Y46: =Tabla58[[#This Row],[Integración Nov/2024]] -> 1 | Z46: =AVERAGE(Tabla4[[#This Row],[Creación y captura Nov/2024]:[Compartición e Interoperabilidad Nov/2024]]) -> 1 | AA46: 1 | AB46: 1 | AC46: =AVERAGE('Calidad de Datos'!S50:V50) -> 1 | AD46: =Tabla13[[#This Row],[Uso y acceso Dic/2024]] -> 1 | AE46: =Tabla58[[#This Row],[Integración Dic/2024]] -> 1 | AF46: =AVERAGE(Tabla4[[#This Row],[Creación y captura Dic/2024]:[Compartición e Interoperabilidad Dic/2024]]) -> 1 | AG46: 1 | AH46: 1 | AI46: =AVERAGE('Calidad de Datos'!W50:Z50) -> 1 | AJ46: =Tabla13[[#This Row],[Uso y acceso Ene/2025]] -> 1 | AK46: =Tabla58[[#This Row],[Integración Ene/2025]] -> 1 | AL46: =AVERAGE(Tabla4[[#This Row],[Creación y captura Ene/2025]:[Compartición e Interoperabilidad Ene/2025]]) -> 1 | AM46: 1 | AN46: 1 | AO46: =AVERAGE('Calidad de Datos'!AA50:AD50) -> 1 | AP46: =Tabla13[[#This Row],[Uso y acceso Feb/2025]] -> 1 | AQ46: =Tabla58[[#This Row],[Integración Feb/2025]] -> 1 | AR46: =AVERAGE(Tabla4[[#This Row],[Creación y captura Feb/2025]:[Compartición e Interoperabilidad Feb/2025]]) -> 1 | AS46: 1 | AT46: 1 | AU46: =AVERAGE('Calidad de Datos'!AE50:AH50) -> 1 | AV46: =Tabla13[[#This Row],[Uso y acceso Mar/2025]] -> 1 | AW46: =Tabla58[[#This Row],[Integración Mar/2025]] -> 1 | AX46: =AVERAGE(Tabla4[[#This Row],[Creación y captura Mar/2025]:[Compartición e Interoperabilidad Mar/2025]]) -> 1 | AY46: 1 | AZ46: 1 | BA46: =AVERAGE('Calidad de Datos'!AI50:AL50) -> 1 | BB46: =Tabla13[[#This Row],[Uso y acceso Abr/2025]] -> 1 | BC46: =Tabla58[[#This Row],[Integración Abr/2025]] -> 1 | BD46: =AVERAGE(Tabla4[[#This Row],[Creación y captura Abr/2025]:[Compartición e Interoperabilidad Abr/2025]]) -> 1 | BE46: 1 | BF46: 1 | BG46: =AVERAGE('Calidad de Datos'!AM50:AP50) -> 1 | BH46: =Tabla13[[#This Row],[Uso y acceso May/2025]] -> 1 | BI46: =Tabla58[[#This Row],[Integración May/2025]] -> 1 | BJ46: =AVERAGE(Tabla4[[#This Row],[Creación y captura May/2025]:[Compartición e Interoperabilidad May/2025]]) -> 1 | BK46: 1 | BL46: 1 | BM46: =AVERAGE('Calidad de Datos'!AQ50:AT50) -> 1 | BN46: =Tabla13[[#This Row],[Uso y acceso Dic/2025]] -> 1 | BO46: =Tabla58[[#This Row],[Integración Dic/2025]] -> 1 | BP46: =AVERAGE(Tabla4[[#This Row],[Creación y captura Dic/2025]:[Compartición e Interoperabilidad Dic/2025]]) -> 1
B47: Indicadores | C47: 0.85 | D47: 1 | E47: =AVERAGE('Calidad de Datos'!C51:F51) -> 0.8625 | F47: =Tabla13[[#This Row],[Uso y acceso Ago/2024]] -> 1 | G47: =Tabla58[[#This Row],[Integración Ago/2024]] -> 1 | H47: =AVERAGE(Tabla4[[#This Row],[Creación y captura Ago/2024]:[Compartición e Interoperabilidad Ago/2024]]) -> 0.9425 | I47: 1 | J47: 1 | K47: =AVERAGE('Calidad de Datos'!G51:J51) -> 0.8875 | L47: =Tabla13[[#This Row],[Uso y acceso Sep/2024]] -> 1 | M47: =Tabla58[[#This Row],[Integración Sep/2024]] -> 1 | N47: =AVERAGE(Tabla4[[#This Row],[Creación y captura Sep/2024]:[Compartición e Interoperabilidad Sep/2024]]) -> 0.9775 | O47: 0.85 | P47: 1 | Q47: =AVERAGE('Calidad de Datos'!K51:N51) -> 0.8875 | R47: =Tabla13[[#This Row],[Uso y acceso Oct/2024]] -> 1 | S47: =Tabla58[[#This Row],[Integración Oct/2024]] -> 1 | T47: =AVERAGE(Tabla4[[#This Row],[Creación y captura Oct/2024]:[Compartición e Interoperabilidad Oct/2024]]) -> 0.9475 | U47: 0.9 | V47: 0.9 | W47: =AVERAGE('Calidad de Datos'!O51:R51) -> 0.925 | X47: =Tabla13[[#This Row],[Uso y acceso Nov/2024]] -> 1 | Y47: =Tabla58[[#This Row],[Integración Nov/2024]] -> 1 | Z47: =AVERAGE(Tabla4[[#This Row],[Creación y captura Nov/2024]:[Compartición e Interoperabilidad Nov/2024]]) -> 0.945 | AA47: 0.95 | AB47: 1 | AC47: =AVERAGE('Calidad de Datos'!S51:V51) -> 0.975 | AD47: =Tabla13[[#This Row],[Uso y acceso Dic/2024]] -> 1 | AE47: =Tabla58[[#This Row],[Integración Dic/2024]] -> 1 | AF47: =AVERAGE(Tabla4[[#This Row],[Creación y captura Dic/2024]:[Compartición e Interoperabilidad Dic/2024]]) -> 0.985 | AG47: 0.95 | AH47: 1 | AI47: =AVERAGE('Calidad de Datos'!W51:Z51) -> 0.975 | AJ47: =Tabla13[[#This Row],[Uso y acceso Ene/2025]] -> 1 | AK47: =Tabla58[[#This Row],[Integración Ene/2025]] -> 1 | AL47: =AVERAGE(Tabla4[[#This Row],[Creación y captura Ene/2025]:[Compartición e Interoperabilidad Ene/2025]]) -> 0.985 | AM47: 1 | AN47: 1 | AO47: =AVERAGE('Calidad de Datos'!AA51:AD51) -> 1 | AP47: =Tabla13[[#This Row],[Uso y acceso Feb/2025]] -> 1 | AQ47: =Tabla58[[#This Row],[Integración Feb/2025]] -> 1 | AR47: =AVERAGE(Tabla4[[#This Row],[Creación y captura Feb/2025]:[Compartición e Interoperabilidad Feb/2025]]) -> 1 | AS47: 1 | AT47: 1 | AU47: =AVERAGE('Calidad de Datos'!AE51:AH51) -> 1 | AV47: =Tabla13[[#This Row],[Uso y acceso Mar/2025]] -> 1 | AW47: =Tabla58[[#This Row],[Integración Mar/2025]] -> 1 | AX47: =AVERAGE(Tabla4[[#This Row],[Creación y captura Mar/2025]:[Compartición e Interoperabilidad Mar/2025]]) -> 1 | AY47: 1 | AZ47: 1 | BA47: =AVERAGE('Calidad de Datos'!AI51:AL51) -> 1 | BB47: =Tabla13[[#This Row],[Uso y acceso Abr/2025]] -> 1 | BC47: =Tabla58[[#This Row],[Integración Abr/2025]] -> 1 | BD47: =AVERAGE(Tabla4[[#This Row],[Creación y captura Abr/2025]:[Compartición e Interoperabilidad Abr/2025]]) -> 1 | BE47: 1 | BF47: 1 | BG47: =AVERAGE('Calidad de Datos'!AM51:AP51) -> 1 | BH47: =Tabla13[[#This Row],[Uso y acceso May/2025]] -> 1 | BI47: =Tabla58[[#This Row],[Integración May/2025]] -> 1 | BJ47: =AVERAGE(Tabla4[[#This Row],[Creación y captura May/2025]:[Compartición e Interoperabilidad May/2025]]) -> 1 | BK47: 1 | BL47: 1 | BM47: =AVERAGE('Calidad de Datos'!AQ51:AT51) -> 1 | BN47: =Tabla13[[#This Row],[Uso y acceso Dic/2025]] -> 1 | BO47: =Tabla58[[#This Row],[Integración Dic/2025]] -> 1 | BP47: =AVERAGE(Tabla4[[#This Row],[Creación y captura Dic/2025]:[Compartición e Interoperabilidad Dic/2025]]) -> 1
B48: Usuario | C48: 1 | D48: 1 | E48: =AVERAGE('Calidad de Datos'!C52:F52) -> 1 | F48: =Tabla13[[#This Row],[Uso y acceso Ago/2024]] -> 1 | G48: =Tabla58[[#This Row],[Integración Ago/2024]] -> 1 | H48: =AVERAGE(Tabla4[[#This Row],[Creación y captura Ago/2024]:[Compartición e Interoperabilidad Ago/2024]]) -> 1 | I48: 1 | J48: 1 | K48: =AVERAGE('Calidad de Datos'!G52:J52) -> 1 | L48: =Tabla13[[#This Row],[Uso y acceso Sep/2024]] -> 1 | M48: =Tabla58[[#This Row],[Integración Sep/2024]] -> 1 | N48: =AVERAGE(Tabla4[[#This Row],[Creación y captura Sep/2024]:[Compartición e Interoperabilidad Sep/2024]]) -> 1 | O48: 1 | P48: 1 | Q48: =AVERAGE('Calidad de Datos'!K52:N52) -> 1 | R48: =Tabla13[[#This Row],[Uso y acceso Oct/2024]] -> 1 | S48: =Tabla58[[#This Row],[Integración Oct/2024]] -> 1 | T48: =AVERAGE(Tabla4[[#This Row],[Creación y captura Oct/2024]:[Compartición e Interoperabilidad Oct/2024]]) -> 1 | U48: 1 | V48: 1 | W48: =AVERAGE('Calidad de Datos'!O52:R52) -> 1 | X48: =Tabla13[[#This Row],[Uso y acceso Nov/2024]] -> 1 | Y48: =Tabla58[[#This Row],[Integración Nov/2024]] -> 1 | Z48: =AVERAGE(Tabla4[[#This Row],[Creación y captura Nov/2024]:[Compartición e Interoperabilidad Nov/2024]]) -> 1 | AA48: 1 | AB48: 1 | AC48: =AVERAGE('Calidad de Datos'!S52:V52) -> 1 | AD48: =Tabla13[[#This Row],[Uso y acceso Dic/2024]] -> 1 | AE48: =Tabla58[[#This Row],[Integración Dic/2024]] -> 1 | AF48: =AVERAGE(Tabla4[[#This Row],[Creación y captura Dic/2024]:[Compartición e Interoperabilidad Dic/2024]]) -> 1 | AG48: 1 | AH48: 1 | AI48: =AVERAGE('Calidad de Datos'!W52:Z52) -> 1 | AJ48: =Tabla13[[#This Row],[Uso y acceso Ene/2025]] -> 1 | AK48: =Tabla58[[#This Row],[Integración Ene/2025]] -> 1 | AL48: =AVERAGE(Tabla4[[#This Row],[Creación y captura Ene/2025]:[Compartición e Interoperabilidad Ene/2025]]) -> 1 | AM48: 1 | AN48: 1 | AO48: =AVERAGE('Calidad de Datos'!AA52:AD52) -> 1 | AP48: =Tabla13[[#This Row],[Uso y acceso Feb/2025]] -> 1 | AQ48: =Tabla58[[#This Row],[Integración Feb/2025]] -> 1 | AR48: =AVERAGE(Tabla4[[#This Row],[Creación y captura Feb/2025]:[Compartición e Interoperabilidad Feb/2025]]) -> 1 | AS48: 1 | AT48: 1 | AU48: =AVERAGE('Calidad de Datos'!AE52:AH52) -> 1 | AV48: =Tabla13[[#This Row],[Uso y acceso Mar/2025]] -> 1 | AW48: =Tabla58[[#This Row],[Integración Mar/2025]] -> 1 | AX48: =AVERAGE(Tabla4[[#This Row],[Creación y captura Mar/2025]:[Compartición e Interoperabilidad Mar/2025]]) -> 1 | AY48: 1 | AZ48: 1 | BA48: =AVERAGE('Calidad de Datos'!AI52:AL52) -> 1 | BB48: =Tabla13[[#This Row],[Uso y acceso Abr/2025]] -> 1 | BC48: =Tabla58[[#This Row],[Integración Abr/2025]] -> 1 | BD48: =AVERAGE(Tabla4[[#This Row],[Creación y captura Abr/2025]:[Compartición e Interoperabilidad Abr/2025]]) -> 1 | BE48: 1 | BF48: 1 | BG48: =AVERAGE('Calidad de Datos'!AM52:AP52) -> 1 | BH48: =Tabla13[[#This Row],[Uso y acceso May/2025]] -> 1 | BI48: =Tabla58[[#This Row],[Integración May/2025]] -> 1 | BJ48: =AVERAGE(Tabla4[[#This Row],[Creación y captura May/2025]:[Compartición e Interoperabilidad May/2025]]) -> 1 | BK48: 1 | BL48: 1 | BM48: =AVERAGE('Calidad de Datos'!AQ52:AT52) -> 1 | BN48: =Tabla13[[#This Row],[Uso y acceso Dic/2025]] -> 1 | BO48: =Tabla58[[#This Row],[Integración Dic/2025]] -> 1 | BP48: =AVERAGE(Tabla4[[#This Row],[Creación y captura Dic/2025]:[Compartición e Interoperabilidad Dic/2025]]) -> 1
B49: Motivo de retiro | E49: =AVERAGE('Calidad de Datos'!C53:F53) -> 0 | F49: =Tabla13[[#This Row],[Uso y acceso Ago/2024]] -> 0.3 | G49: 0 | H49: =AVERAGE(Tabla4[[#This Row],[Creación y captura Ago/2024]:[Compartición e Interoperabilidad Ago/2024]]) -> 0.1 | K49: =AVERAGE('Calidad de Datos'!G53:J53) -> 0 | L49: =Tabla13[[#This Row],[Uso y acceso Sep/2024]] -> 0.3 | M49: =Tabla58[[#This Row],[Integración Sep/2024]] -> 0 | N49: =AVERAGE(Tabla4[[#This Row],[Creación y captura Sep/2024]:[Compartición e Interoperabilidad Sep/2024]]) -> 0.1 | O49: 0.5 | P49: 0.2 | Q49: =AVERAGE('Calidad de Datos'!K53:N53) -> 0 | R49: =Tabla13[[#This Row],[Uso y acceso Oct/2024]] -> 1 | S49: =Tabla58[[#This Row],[Integración Oct/2024]] -> 0.2 | T49: =AVERAGE(Tabla4[[#This Row],[Creación y captura Oct/2024]:[Compartición e Interoperabilidad Oct/2024]]) -> 0.38 | U49: 1 | V49: 0.5 | W49: =AVERAGE('Calidad de Datos'!O53:R53) -> 1 | X49: =Tabla13[[#This Row],[Uso y acceso Nov/2024]] -> 1 | Y49: =Tabla58[[#This Row],[Integración Nov/2024]] -> 0.5 | Z49: =AVERAGE(Tabla4[[#This Row],[Creación y captura Nov/2024]:[Compartición e Interoperabilidad Nov/2024]]) -> 0.8 | AA49: 1 | AB49: 1 | AC49: =AVERAGE('Calidad de Datos'!S53:V53) -> 1 | AD49: =Tabla13[[#This Row],[Uso y acceso Dic/2024]] -> 1 | AE49: =Tabla58[[#This Row],[Integración Dic/2024]] -> 1 | AF49: =AVERAGE(Tabla4[[#This Row],[Creación y captura Dic/2024]:[Compartición e Interoperabilidad Dic/2024]]) -> 1 | AG49: 1 | AH49: 1 | AI49: =AVERAGE('Calidad de Datos'!W53:Z53) -> 1 | AJ49: =Tabla13[[#This Row],[Uso y acceso Ene/2025]] -> 1 | AK49: =Tabla58[[#This Row],[Integración Ene/2025]] -> 1 | AL49: =AVERAGE(Tabla4[[#This Row],[Creación y captura Ene/2025]:[Compartición e Interoperabilidad Ene/2025]]) -> 1 | AM49: 1 | AN49: 1 | AO49: =AVERAGE('Calidad de Datos'!AA53:AD53) -> 1 | AP49: =Tabla13[[#This Row],[Uso y acceso Feb/2025]] -> 1 | AQ49: =Tabla58[[#This Row],[Integración Feb/2025]] -> 1 | AR49: =AVERAGE(Tabla4[[#This Row],[Creación y captura Feb/2025]:[Compartición e Interoperabilidad Feb/2025]]) -> 1 | AS49: 1 | AT49: 1 | AU49: =AVERAGE('Calidad de Datos'!AE53:AH53) -> 1 | AV49: =Tabla13[[#This Row],[Uso y acceso Mar/2025]] -> 1 | AW49: =Tabla58[[#This Row],[Integración Mar/2025]] -> 1 | AX49: =AVERAGE(Tabla4[[#This Row],[Creación y captura Mar/2025]:[Compartición e Interoperabilidad Mar/2025]]) -> 1 | AY49: 1 | AZ49: 1 | BA49: =AVERAGE('Calidad de Datos'!AI53:AL53) -> 1 | BB49: =Tabla13[[#This Row],[Uso y acceso Abr/2025]] -> 1 | BC49: =Tabla58[[#This Row],[Integración Abr/2025]] -> 1 | BD49: =AVERAGE(Tabla4[[#This Row],[Creación y captura Abr/2025]:[Compartición e Interoperabilidad Abr/2025]]) -> 1 | BE49: 1 | BF49: 1 | BG49: =AVERAGE('Calidad de Datos'!AM53:AP53) -> 1 | BH49: =Tabla13[[#This Row],[Uso y acceso May/2025]] -> 1 | BI49: =Tabla58[[#This Row],[Integración May/2025]] -> 1 | BJ49: =AVERAGE(Tabla4[[#This Row],[Creación y captura May/2025]:[Compartición e Interoperabilidad May/2025]]) -> 1 | BK49: 1 | BL49: 1 | BM49: =AVERAGE('Calidad de Datos'!AQ53:AT53) -> 1 | BN49: =Tabla13[[#This Row],[Uso y acceso Dic/2025]] -> 1 | BO49: =Tabla58[[#This Row],[Integración Dic/2025]] -> 1 | BP49: =AVERAGE(Tabla4[[#This Row],[Creación y captura Dic/2025]:[Compartición e Interoperabilidad Dic/2025]]) -> 1
B50: Cargo | E50: =AVERAGE('Calidad de Datos'!C54:F54) -> 0 | F50: =Tabla13[[#This Row],[Uso y acceso Ago/2024]] -> 0 | G50: 0 | H50: =AVERAGE(Tabla4[[#This Row],[Creación y captura Ago/2024]:[Compartición e Interoperabilidad Ago/2024]]) -> 0 | K50: =AVERAGE('Calidad de Datos'!G54:J54) -> 0 | L50: =Tabla13[[#This Row],[Uso y acceso Sep/2024]] -> 0 | M50: =Tabla58[[#This Row],[Integración Sep/2024]] -> 0 | N50: =AVERAGE(Tabla4[[#This Row],[Creación y captura Sep/2024]:[Compartición e Interoperabilidad Sep/2024]]) -> 0 | O50: 0.5 | P50: 0.2 | Q50: =AVERAGE('Calidad de Datos'!K54:N54) -> 0 | R50: =Tabla13[[#This Row],[Uso y acceso Oct/2024]] -> 1 | S50: =Tabla58[[#This Row],[Integración Oct/2024]] -> 0.2 | T50: =AVERAGE(Tabla4[[#This Row],[Creación y captura Oct/2024]:[Compartición e Interoperabilidad Oct/2024]]) -> 0.38 | U50: 1 | V50: 0.5 | W50: =AVERAGE('Calidad de Datos'!O54:R54) -> 1 | X50: =Tabla13[[#This Row],[Uso y acceso Nov/2024]] -> 1 | Y50: =Tabla58[[#This Row],[Integración Nov/2024]] -> 0.5 | Z50: =AVERAGE(Tabla4[[#This Row],[Creación y captura Nov/2024]:[Compartición e Interoperabilidad Nov/2024]]) -> 0.8 | AA50: 1 | AB50: 1 | AC50: =AVERAGE('Calidad de Datos'!S54:V54) -> 1 | AD50: =Tabla13[[#This Row],[Uso y acceso Dic/2024]] -> 1 | AE50: =Tabla58[[#This Row],[Integración Dic/2024]] -> 1 | AF50: =AVERAGE(Tabla4[[#This Row],[Creación y captura Dic/2024]:[Compartición e Interoperabilidad Dic/2024]]) -> 1 | AG50: 1 | AH50: 1 | AI50: =AVERAGE('Calidad de Datos'!W54:Z54) -> 1 | AJ50: =Tabla13[[#This Row],[Uso y acceso Ene/2025]] -> 1 | AK50: =Tabla58[[#This Row],[Integración Ene/2025]] -> 1 | AL50: =AVERAGE(Tabla4[[#This Row],[Creación y captura Ene/2025]:[Compartición e Interoperabilidad Ene/2025]]) -> 1 | AM50: 1 | AN50: 1 | AO50: =AVERAGE('Calidad de Datos'!AA54:AD54) -> 1 | AP50: =Tabla13[[#This Row],[Uso y acceso Feb/2025]] -> 1 | AQ50: =Tabla58[[#This Row],[Integración Feb/2025]] -> 1 | AR50: =AVERAGE(Tabla4[[#This Row],[Creación y captura Feb/2025]:[Compartición e Interoperabilidad Feb/2025]]) -> 1 | AS50: 1 | AT50: 1 | AU50: =AVERAGE('Calidad de Datos'!AE54:AH54) -> 1 | AV50: =Tabla13[[#This Row],[Uso y acceso Mar/2025]] -> 1 | AW50: =Tabla58[[#This Row],[Integración Mar/2025]] -> 1 | AX50: =AVERAGE(Tabla4[[#This Row],[Creación y captura Mar/2025]:[Compartición e Interoperabilidad Mar/2025]]) -> 1 | AY50: 1 | AZ50: 1 | BA50: =AVERAGE('Calidad de Datos'!AI54:AL54) -> 1 | BB50: =Tabla13[[#This Row],[Uso y acceso Abr/2025]] -> 1 | BC50: =Tabla58[[#This Row],[Integración Abr/2025]] -> 1 | BD50: =AVERAGE(Tabla4[[#This Row],[Creación y captura Abr/2025]:[Compartición e Interoperabilidad Abr/2025]]) -> 1 | BE50: 1 | BF50: 1 | BG50: =AVERAGE('Calidad de Datos'!AM54:AP54) -> 1 | BH50: =Tabla13[[#This Row],[Uso y acceso May/2025]] -> 1 | BI50: =Tabla58[[#This Row],[Integración May/2025]] -> 1 | BJ50: =AVERAGE(Tabla4[[#This Row],[Creación y captura May/2025]:[Compartición e Interoperabilidad May/2025]]) -> 1 | BK50: 1 | BL50: 1 | BM50: =AVERAGE('Calidad de Datos'!AQ54:AT54) -> 1 | BN50: =Tabla13[[#This Row],[Uso y acceso Dic/2025]] -> 1 | BO50: =Tabla58[[#This Row],[Integración Dic/2025]] -> 1 | BP50: =AVERAGE(Tabla4[[#This Row],[Creación y captura Dic/2025]:[Compartición e Interoperabilidad Dic/2025]]) -> 1
B51: Tipo de proceso de contratación | E51: =AVERAGE('Calidad de Datos'!C55:F55) -> 0 | F51: =Tabla13[[#This Row],[Uso y acceso Ago/2024]] -> 0.3 | G51: =Tabla58[[#This Row],[Integración Ago/2024]] -> 0 | H51: =AVERAGE(Tabla4[[#This Row],[Creación y captura Ago/2024]:[Compartición e Interoperabilidad Ago/2024]]) -> 0.1 | K51: =AVERAGE('Calidad de Datos'!G55:J55) -> 0 | L51: =Tabla13[[#This Row],[Uso y acceso Sep/2024]] -> 0.3 | M51: =Tabla58[[#This Row],[Integración Sep/2024]] -> 0 | N51: =AVERAGE(Tabla4[[#This Row],[Creación y captura Sep/2024]:[Compartición e Interoperabilidad Sep/2024]]) -> 0.1 | O51: 0.5 | P51: 0.2 | Q51: =AVERAGE('Calidad de Datos'!K55:N55) -> 0 | R51: =Tabla13[[#This Row],[Uso y acceso Oct/2024]] -> 1 | S51: =Tabla58[[#This Row],[Integración Oct/2024]] -> 0.2 | T51: =AVERAGE(Tabla4[[#This Row],[Creación y captura Oct/2024]:[Compartición e Interoperabilidad Oct/2024]]) -> 0.38 | U51: 1 | V51: 0.5 | W51: =AVERAGE('Calidad de Datos'!O55:R55) -> 1 | X51: =Tabla13[[#This Row],[Uso y acceso Nov/2024]] -> 1 | Y51: =Tabla58[[#This Row],[Integración Nov/2024]] -> 0.5 | Z51: =AVERAGE(Tabla4[[#This Row],[Creación y captura Nov/2024]:[Compartición e Interoperabilidad Nov/2024]]) -> 0.8 | AA51: 1 | AB51: 1 | AC51: =AVERAGE('Calidad de Datos'!S55:V55) -> 1 | AD51: =Tabla13[[#This Row],[Uso y acceso Dic/2024]] -> 1 | AE51: =Tabla58[[#This Row],[Integración Dic/2024]] -> 1 | AF51: =AVERAGE(Tabla4[[#This Row],[Creación y captura Dic/2024]:[Compartición e Interoperabilidad Dic/2024]]) -> 1 | AG51: 1 | AH51: 1 | AI51: =AVERAGE('Calidad de Datos'!W55:Z55) -> 1 | AJ51: =Tabla13[[#This Row],[Uso y acceso Ene/2025]] -> 1 | AK51: =Tabla58[[#This Row],[Integración Ene/2025]] -> 1 | AL51: =AVERAGE(Tabla4[[#This Row],[Creación y captura Ene/2025]:[Compartición e Interoperabilidad Ene/2025]]) -> 1 | AM51: 1 | AN51: 1 | AO51: =AVERAGE('Calidad de Datos'!AA55:AD55) -> 1 | AP51: =Tabla13[[#This Row],[Uso y acceso Feb/2025]] -> 1 | AQ51: =Tabla58[[#This Row],[Integración Feb/2025]] -> 1 | AR51: =AVERAGE(Tabla4[[#This Row],[Creación y captura Feb/2025]:[Compartición e Interoperabilidad Feb/2025]]) -> 1 | AS51: 1 | AT51: 1 | AU51: =AVERAGE('Calidad de Datos'!AE55:AH55) -> 1 | AV51: =Tabla13[[#This Row],[Uso y acceso Mar/2025]] -> 1 | AW51: =Tabla58[[#This Row],[Integración Mar/2025]] -> 1 | AX51: =AVERAGE(Tabla4[[#This Row],[Creación y captura Mar/2025]:[Compartición e Interoperabilidad Mar/2025]]) -> 1 | AY51: 1 | AZ51: 1 | BA51: =AVERAGE('Calidad de Datos'!AI55:AL55) -> 1 | BB51: =Tabla13[[#This Row],[Uso y acceso Abr/2025]] -> 1 | BC51: =Tabla58[[#This Row],[Integración Abr/2025]] -> 1 | BD51: =AVERAGE(Tabla4[[#This Row],[Creación y captura Abr/2025]:[Compartición e Interoperabilidad Abr/2025]]) -> 1 | BE51: 1 | BF51: 1 | BG51: =AVERAGE('Calidad de Datos'!AM55:AP55) -> 1 | BH51: =Tabla13[[#This Row],[Uso y acceso May/2025]] -> 1 | BI51: =Tabla58[[#This Row],[Integración May/2025]] -> 1 | BJ51: =AVERAGE(Tabla4[[#This Row],[Creación y captura May/2025]:[Compartición e Interoperabilidad May/2025]]) -> 1 | BK51: 1 | BL51: 1 | BM51: =AVERAGE('Calidad de Datos'!AQ55:AT55) -> 1 | BN51: =Tabla13[[#This Row],[Uso y acceso Dic/2025]] -> 1 | BO51: =Tabla58[[#This Row],[Integración Dic/2025]] -> 1 | BP51: =AVERAGE(Tabla4[[#This Row],[Creación y captura Dic/2025]:[Compartición e Interoperabilidad Dic/2025]]) -> 1
B52: Fuente de reclutamiento | E52: =AVERAGE('Calidad de Datos'!C56:F56) -> 0 | F52: =Tabla13[[#This Row],[Uso y acceso Ago/2024]] -> 0.3 | G52: =Tabla58[[#This Row],[Integración Ago/2024]] -> 0 | H52: =AVERAGE(Tabla4[[#This Row],[Creación y captura Ago/2024]:[Compartición e Interoperabilidad Ago/2024]]) -> 0.1 | K52: =AVERAGE('Calidad de Datos'!G56:J56) -> 0 | L52: =Tabla13[[#This Row],[Uso y acceso Sep/2024]] -> 0.3 | M52: =Tabla58[[#This Row],[Integración Sep/2024]] -> 0 | N52: =AVERAGE(Tabla4[[#This Row],[Creación y captura Sep/2024]:[Compartición e Interoperabilidad Sep/2024]]) -> 0.1 | O52: 0.5 | P52: 0.2 | Q52: =AVERAGE('Calidad de Datos'!K56:N56) -> 0 | R52: =Tabla13[[#This Row],[Uso y acceso Oct/2024]] -> 1 | S52: =Tabla58[[#This Row],[Integración Oct/2024]] -> 0.2 | T52: =AVERAGE(Tabla4[[#This Row],[Creación y captura Oct/2024]:[Compartición e Interoperabilidad Oct/2024]]) -> 0.38 | U52: 1 | V52: 0.5 | W52: =AVERAGE('Calidad de Datos'!O56:R56) -> 1 | X52: =Tabla13[[#This Row],[Uso y acceso Nov/2024]] -> 1 | Y52: =Tabla58[[#This Row],[Integración Nov/2024]] -> 0.5 | Z52: =AVERAGE(Tabla4[[#This Row],[Creación y captura Nov/2024]:[Compartición e Interoperabilidad Nov/2024]]) -> 0.8 | AA52: 1 | AB52: 1 | AC52: =AVERAGE('Calidad de Datos'!S56:V56) -> 1 | AD52: =Tabla13[[#This Row],[Uso y acceso Dic/2024]] -> 1 | AE52: =Tabla58[[#This Row],[Integración Dic/2024]] -> 1 | AF52: =AVERAGE(Tabla4[[#This Row],[Creación y captura Dic/2024]:[Compartición e Interoperabilidad Dic/2024]]) -> 1 | AG52: 1 | AH52: 1 | AI52: =AVERAGE('Calidad de Datos'!W56:Z56) -> 1 | AJ52: =Tabla13[[#This Row],[Uso y acceso Ene/2025]] -> 1 | AK52: =Tabla58[[#This Row],[Integración Ene/2025]] -> 1 | AL52: =AVERAGE(Tabla4[[#This Row],[Creación y captura Ene/2025]:[Compartición e Interoperabilidad Ene/2025]]) -> 1 | AM52: 1 | AN52: 1 | AO52: =AVERAGE('Calidad de Datos'!AA56:AD56) -> 1 | AP52: =Tabla13[[#This Row],[Uso y acceso Feb/2025]] -> 1 | AQ52: =Tabla58[[#This Row],[Integración Feb/2025]] -> 1 | AR52: =AVERAGE(Tabla4[[#This Row],[Creación y captura Feb/2025]:[Compartición e Interoperabilidad Feb/2025]]) -> 1 | AS52: 1 | AT52: 1 | AU52: =AVERAGE('Calidad de Datos'!AE56:AH56) -> 1 | AV52: =Tabla13[[#This Row],[Uso y acceso Mar/2025]] -> 1 | AW52: =Tabla58[[#This Row],[Integración Mar/2025]] -> 1 | AX52: =AVERAGE(Tabla4[[#This Row],[Creación y captura Mar/2025]:[Compartición e Interoperabilidad Mar/2025]]) -> 1 | AY52: 1 | AZ52: 1 | BA52: =AVERAGE('Calidad de Datos'!AI56:AL56) -> 1 | BB52: =Tabla13[[#This Row],[Uso y acceso Abr/2025]] -> 1 | BC52: =Tabla58[[#This Row],[Integración Abr/2025]] -> 1 | BD52: =AVERAGE(Tabla4[[#This Row],[Creación y captura Abr/2025]:[Compartición e Interoperabilidad Abr/2025]]) -> 1 | BE52: 1 | BF52: 1 | BG52: =AVERAGE('Calidad de Datos'!AM56:AP56) -> 1 | BH52: =Tabla13[[#This Row],[Uso y acceso May/2025]] -> 1 | BI52: =Tabla58[[#This Row],[Integración May/2025]] -> 1 | BJ52: =AVERAGE(Tabla4[[#This Row],[Creación y captura May/2025]:[Compartición e Interoperabilidad May/2025]]) -> 1 | BK52: 1 | BL52: 1 | BM52: =AVERAGE('Calidad de Datos'!AQ56:AT56) -> 1 | BN52: =Tabla13[[#This Row],[Uso y acceso Dic/2025]] -> 1 | BO52: =Tabla58[[#This Row],[Integración Dic/2025]] -> 1 | BP52: =AVERAGE(Tabla4[[#This Row],[Creación y captura Dic/2025]:[Compartición e Interoperabilidad Dic/2025]]) -> 1
B53: Solicitudes de personal y contratación | E53: =AVERAGE('Calidad de Datos'!C57:F57) -> 0 | F53: =Tabla13[[#This Row],[Uso y acceso Ago/2024]] -> 0.5 | G53: =Tabla58[[#This Row],[Integración Ago/2024]] -> 0 | H53: =AVERAGE(Tabla4[[#This Row],[Creación y captura Ago/2024]:[Compartición e Interoperabilidad Ago/2024]]) -> 0.16666667 | K53: =AVERAGE('Calidad de Datos'!G57:J57) -> 0 | L53: =Tabla13[[#This Row],[Uso y acceso Sep/2024]] -> 0.5 | M53: =Tabla58[[#This Row],[Integración Sep/2024]] -> 0 | N53: =AVERAGE(Tabla4[[#This Row],[Creación y captura Sep/2024]:[Compartición e Interoperabilidad Sep/2024]]) -> 0.16666667 | O53: 0.5 | P53: 0.2 | Q53: =AVERAGE('Calidad de Datos'!K57:N57) -> 0 | R53: =Tabla13[[#This Row],[Uso y acceso Oct/2024]] -> 0.8 | S53: =Tabla58[[#This Row],[Integración Oct/2024]] -> 0.2 | T53: =AVERAGE(Tabla4[[#This Row],[Creación y captura Oct/2024]:[Compartición e Interoperabilidad Oct/2024]]) -> 0.34 | U53: 0.75 | V53: 0.5 | W53: =AVERAGE('Calidad de Datos'!O57:R57) -> 0.7775 | X53: =Tabla13[[#This Row],[Uso y acceso Nov/2024]] -> 1 | Y53: =Tabla58[[#This Row],[Integración Nov/2024]] -> 0.5 | Z53: =AVERAGE(Tabla4[[#This Row],[Creación y captura Nov/2024]:[Compartición e Interoperabilidad Nov/2024]]) -> 0.7055 | AA53: 0.75 | AB53: 0.9 | AC53: =AVERAGE('Calidad de Datos'!S57:V57) -> 0.7775 | AD53: =Tabla13[[#This Row],[Uso y acceso Dic/2024]] -> 1 | AE53: =Tabla58[[#This Row],[Integración Dic/2024]] -> 0.9 | AF53: =AVERAGE(Tabla4[[#This Row],[Creación y captura Dic/2024]:[Compartición e Interoperabilidad Dic/2024]]) -> 0.8655 | AG53: 0.85 | AH53: 1 | AI53: =AVERAGE('Calidad de Datos'!W57:Z57) -> 0.8625 | AJ53: =Tabla13[[#This Row],[Uso y acceso Ene/2025]] -> 1 | AK53: =Tabla58[[#This Row],[Integración Ene/2025]] -> 0.9 | AL53: =AVERAGE(Tabla4[[#This Row],[Creación y captura Ene/2025]:[Compartición e Interoperabilidad Ene/2025]]) -> 0.9225 | AM53: 0.9 | AN53: 0.9 | AO53: =AVERAGE('Calidad de Datos'!AA57:AD57) -> 0.9375 | AP53: =Tabla13[[#This Row],[Uso y acceso Feb/2025]] -> 1 | AQ53: =Tabla58[[#This Row],[Integración Feb/2025]] -> 0.9 | AR53: =AVERAGE(Tabla4[[#This Row],[Creación y captura Feb/2025]:[Compartición e Interoperabilidad Feb/2025]]) -> 0.9275 | AS53: 0.9 | AT53: 1 | AU53: =AVERAGE('Calidad de Datos'!AE57:AH57) -> 0.9375 | AV53: =Tabla13[[#This Row],[Uso y acceso Mar/2025]] -> 1 | AW53: =Tabla58[[#This Row],[Integración Mar/2025]] -> 0.9 | AX53: =AVERAGE(Tabla4[[#This Row],[Creación y captura Mar/2025]:[Compartición e Interoperabilidad Mar/2025]]) -> 0.9475 | AY53: 0.9 | AZ53: 1 | BA53: =AVERAGE('Calidad de Datos'!AI57:AL57) -> 0.9375 | BB53: =Tabla13[[#This Row],[Uso y acceso Abr/2025]] -> 1 | BC53: =Tabla58[[#This Row],[Integración Abr/2025]] -> 0.9 | BD53: =AVERAGE(Tabla4[[#This Row],[Creación y captura Abr/2025]:[Compartición e Interoperabilidad Abr/2025]]) -> 0.9475 | BE53: 1 | BF53: 1 | BG53: =AVERAGE('Calidad de Datos'!AM57:AP57) -> 1 | BH53: =Tabla13[[#This Row],[Uso y acceso May/2025]] -> 1 | BI53: =Tabla58[[#This Row],[Integración May/2025]] -> 0.9 | BJ53: =AVERAGE(Tabla4[[#This Row],[Creación y captura May/2025]:[Compartición e Interoperabilidad May/2025]]) -> 0.98 | BK53: 1 | BL53: 1 | BM53: =AVERAGE('Calidad de Datos'!AQ57:AT57) -> 1 | BN53: =Tabla13[[#This Row],[Uso y acceso Dic/2025]] -> 1 | BO53: =Tabla58[[#This Row],[Integración Dic/2025]] -> 1 | BP53: =AVERAGE(Tabla4[[#This Row],[Creación y captura Dic/2025]:[Compartición e Interoperabilidad Dic/2025]]) -> 1
B54: Analisis de Indicadores | E54: =AVERAGE('Calidad de Datos'!C58:F58) -> 0 | F54: =Tabla13[[#This Row],[Uso y acceso Ago/2024]] -> 0.5 | G54: =Tabla58[[#This Row],[Integración Ago/2024]] -> 0 | H54: =AVERAGE(Tabla4[[#This Row],[Creación y captura Ago/2024]:[Compartición e Interoperabilidad Ago/2024]]) -> 0.16666667 | K54: =AVERAGE('Calidad de Datos'!G58:J58) -> 0 | L54: =Tabla13[[#This Row],[Uso y acceso Sep/2024]] -> 0.5 | M54: =Tabla58[[#This Row],[Integración Sep/2024]] -> 0 | N54: =AVERAGE(Tabla4[[#This Row],[Creación y captura Sep/2024]:[Compartición e Interoperabilidad Sep/2024]]) -> 0.16666667 | Q54: =AVERAGE('Calidad de Datos'!K58:N58) -> 0 | R54: =Tabla13[[#This Row],[Uso y acceso Oct/2024]] -> 0.5 | S54: =Tabla58[[#This Row],[Integración Oct/2024]] -> 0 | T54: =AVERAGE(Tabla4[[#This Row],[Creación y captura Oct/2024]:[Compartición e Interoperabilidad Oct/2024]]) -> 0.16666667 | U54: 0.75 | W54: =AVERAGE('Calidad de Datos'!O58:R58) -> 0.775 | X54: =Tabla13[[#This Row],[Uso y acceso Nov/2024]] -> 0.5 | Y54: =Tabla58[[#This Row],[Integración Nov/2024]] -> 0 | Z54: =AVERAGE(Tabla4[[#This Row],[Creación y captura Nov/2024]:[Compartición e Interoperabilidad Nov/2024]]) -> 0.50625 | AA54: 0.75 | AB54: 0.9 | AC54: =AVERAGE('Calidad de Datos'!S58:V58) -> 0.775 | AD54: =Tabla13[[#This Row],[Uso y acceso Dic/2024]] -> 1 | AE54: =Tabla58[[#This Row],[Integración Dic/2024]] -> 0.9 | AF54: =AVERAGE(Tabla4[[#This Row],[Creación y captura Dic/2024]:[Compartición e Interoperabilidad Dic/2024]]) -> 0.865 | AG54: 1 | AH54: 1 | AI54: =AVERAGE('Calidad de Datos'!W58:Z58) -> 1 | AJ54: =Tabla13[[#This Row],[Uso y acceso Ene/2025]] -> 1 | AK54: =Tabla58[[#This Row],[Integración Ene/2025]] -> 1 | AL54: =AVERAGE(Tabla4[[#This Row],[Creación y captura Ene/2025]:[Compartición e Interoperabilidad Ene/2025]]) -> 1 | AM54: 1 | AN54: 1 | AO54: =AVERAGE('Calidad de Datos'!AA58:AD58) -> 1 | AP54: =Tabla13[[#This Row],[Uso y acceso Feb/2025]] -> 1 | AQ54: =Tabla58[[#This Row],[Integración Feb/2025]] -> 1 | AR54: =AVERAGE(Tabla4[[#This Row],[Creación y captura Feb/2025]:[Compartición e Interoperabilidad Feb/2025]]) -> 1 | AS54: 1 | AT54: 1 | AU54: =AVERAGE('Calidad de Datos'!AE58:AH58) -> 1 | AV54: =Tabla13[[#This Row],[Uso y acceso Mar/2025]] -> 1 | AW54: =Tabla58[[#This Row],[Integración Mar/2025]] -> 1 | AX54: =AVERAGE(Tabla4[[#This Row],[Creación y captura Mar/2025]:[Compartición e Interoperabilidad Mar/2025]]) -> 1 | AY54: 1 | AZ54: 1 | BA54: =AVERAGE('Calidad de Datos'!AI58:AL58) -> 1 | BB54: =Tabla13[[#This Row],[Uso y acceso Abr/2025]] -> 1 | BC54: =Tabla58[[#This Row],[Integración Abr/2025]] -> 1 | BD54: =AVERAGE(Tabla4[[#This Row],[Creación y captura Abr/2025]:[Compartición e Interoperabilidad Abr/2025]]) -> 1 | BE54: 1 | BF54: 1 | BG54: =AVERAGE('Calidad de Datos'!AM58:AP58) -> 1 | BH54: =Tabla13[[#This Row],[Uso y acceso May/2025]] -> 1 | BI54: =Tabla58[[#This Row],[Integración May/2025]] -> 1 | BJ54: =AVERAGE(Tabla4[[#This Row],[Creación y captura May/2025]:[Compartición e Interoperabilidad May/2025]]) -> 1 | BK54: 1 | BL54: 1 | BM54: =AVERAGE('Calidad de Datos'!AQ58:AT58) -> 1 | BN54: =Tabla13[[#This Row],[Uso y acceso Dic/2025]] -> 1 | BO54: =Tabla58[[#This Row],[Integración Dic/2025]] -> 1 | BP54: =AVERAGE(Tabla4[[#This Row],[Creación y captura Dic/2025]:[Compartición e Interoperabilidad Dic/2025]]) -> 1
B55: Tipo de capacitación | E55: =AVERAGE('Calidad de Datos'!C59:F59) -> 0 | F55: =Tabla13[[#This Row],[Uso y acceso Ago/2024]] -> 0.3 | G55: =Tabla58[[#This Row],[Integración Ago/2024]] -> 0 | H55: =AVERAGE(Tabla4[[#This Row],[Creación y captura Ago/2024]:[Compartición e Interoperabilidad Ago/2024]]) -> 0.1 | K55: =AVERAGE('Calidad de Datos'!G59:J59) -> 0 | L55: =Tabla13[[#This Row],[Uso y acceso Sep/2024]] -> 0.3 | M55: =Tabla58[[#This Row],[Integración Sep/2024]] -> 0 | N55: =AVERAGE(Tabla4[[#This Row],[Creación y captura Sep/2024]:[Compartición e Interoperabilidad Sep/2024]]) -> 0.1 | O55: 0.6 | P55: 0.3 | Q55: =AVERAGE('Calidad de Datos'!K59:N59) -> 0 | R55: =Tabla13[[#This Row],[Uso y acceso Oct/2024]] -> 0.5 | S55: =Tabla58[[#This Row],[Integración Oct/2024]] -> 0.3 | T55: =AVERAGE(Tabla4[[#This Row],[Creación y captura Oct/2024]:[Compartición e Interoperabilidad Oct/2024]]) -> 0.34 | U55: 1 | V55: 0.5 | W55: =AVERAGE('Calidad de Datos'!O59:R59) -> 1 | X55: =Tabla13[[#This Row],[Uso y acceso Nov/2024]] -> 0.5 | Y55: =Tabla58[[#This Row],[Integración Nov/2024]] -> 0.5 | Z55: =AVERAGE(Tabla4[[#This Row],[Creación y captura Nov/2024]:[Compartición e Interoperabilidad Nov/2024]]) -> 0.7 | AA55: 1 | AB55: 0.9 | AC55: =AVERAGE('Calidad de Datos'!S59:V59) -> 1 | AD55: =Tabla13[[#This Row],[Uso y acceso Dic/2024]] -> 1 | AE55: =Tabla58[[#This Row],[Integración Dic/2024]] -> 0.9 | AF55: =AVERAGE(Tabla4[[#This Row],[Creación y captura Dic/2024]:[Compartición e Interoperabilidad Dic/2024]]) -> 0.96 | AG55: 1 | AH55: 1 | AI55: =AVERAGE('Calidad de Datos'!W59:Z59) -> 1 | AJ55: =Tabla13[[#This Row],[Uso y acceso Ene/2025]] -> 1 | AK55: =Tabla58[[#This Row],[Integración Ene/2025]] -> 1 | AL55: =AVERAGE(Tabla4[[#This Row],[Creación y captura Ene/2025]:[Compartición e Interoperabilidad Ene/2025]]) -> 1 | AM55: 1 | AN55: 1 | AO55: =AVERAGE('Calidad de Datos'!AA59:AD59) -> 1 | AP55: =Tabla13[[#This Row],[Uso y acceso Feb/2025]] -> 1 | AQ55: =Tabla58[[#This Row],[Integración Feb/2025]] -> 1 | AR55: =AVERAGE(Tabla4[[#This Row],[Creación y captura Feb/2025]:[Compartición e Interoperabilidad Feb/2025]]) -> 1 | AS55: 1 | AT55: 1 | AU55: =AVERAGE('Calidad de Datos'!AE59:AH59) -> 1 | AV55: =Tabla13[[#This Row],[Uso y acceso Mar/2025]] -> 1 | AW55: =Tabla58[[#This Row],[Integración Mar/2025]] -> 1 | AX55: =AVERAGE(Tabla4[[#This Row],[Creación y captura Mar/2025]:[Compartición e Interoperabilidad Mar/2025]]) -> 1 | AY55: 1 | AZ55: 1 | BA55: =AVERAGE('Calidad de Datos'!AI59:AL59) -> 1 | BB55: =Tabla13[[#This Row],[Uso y acceso Abr/2025]] -> 1 | BC55: =Tabla58[[#This Row],[Integración Abr/2025]] -> 1 | BD55: =AVERAGE(Tabla4[[#This Row],[Creación y captura Abr/2025]:[Compartición e Interoperabilidad Abr/2025]]) -> 1 | BE55: 1 | BF55: 1 | BG55: =AVERAGE('Calidad de Datos'!AM59:AP59) -> 1 | BH55: =Tabla13[[#This Row],[Uso y acceso May/2025]] -> 1 | BI55: =Tabla58[[#This Row],[Integración May/2025]] -> 1 | BJ55: =AVERAGE(Tabla4[[#This Row],[Creación y captura May/2025]:[Compartición e Interoperabilidad May/2025]]) -> 1 | BK55: 1 | BL55: 1 | BM55: =AVERAGE('Calidad de Datos'!AQ59:AT59) -> 1 | BN55: =Tabla13[[#This Row],[Uso y acceso Dic/2025]] -> 1 | BO55: =Tabla58[[#This Row],[Integración Dic/2025]] -> 1 | BP55: =AVERAGE(Tabla4[[#This Row],[Creación y captura Dic/2025]:[Compartición e Interoperabilidad Dic/2025]]) -> 1
B56: Medición eficacia de capacitaciones | E56: =AVERAGE('Calidad de Datos'!C60:F60) -> 0 | F56: =Tabla13[[#This Row],[Uso y acceso Ago/2024]] -> 0.3 | G56: =Tabla58[[#This Row],[Integración Ago/2024]] -> 0 | H56: =AVERAGE(Tabla4[[#This Row],[Creación y captura Ago/2024]:[Compartición e Interoperabilidad Ago/2024]]) -> 0.1 | K56: =AVERAGE('Calidad de Datos'!G60:J60) -> 0 | L56: =Tabla13[[#This Row],[Uso y acceso Sep/2024]] -> 0.3 | M56: =Tabla58[[#This Row],[Integración Sep/2024]] -> 0 | N56: =AVERAGE(Tabla4[[#This Row],[Creación y captura Sep/2024]:[Compartición e Interoperabilidad Sep/2024]]) -> 0.1 | O56: 0.6 | P56: 0.3 | Q56: =AVERAGE('Calidad de Datos'!K60:N60) -> 0 | R56: =Tabla13[[#This Row],[Uso y acceso Oct/2024]] -> 0.5 | S56: =Tabla58[[#This Row],[Integración Oct/2024]] -> 0.3 | T56: =AVERAGE(Tabla4[[#This Row],[Creación y captura Oct/2024]:[Compartición e Interoperabilidad Oct/2024]]) -> 0.34 | U56: 1 | V56: 0.5 | W56: =AVERAGE('Calidad de Datos'!O60:R60) -> 1 | X56: =Tabla13[[#This Row],[Uso y acceso Nov/2024]] -> 0.5 | Y56: =Tabla58[[#This Row],[Integración Nov/2024]] -> 0.5 | Z56: =AVERAGE(Tabla4[[#This Row],[Creación y captura Nov/2024]:[Compartición e Interoperabilidad Nov/2024]]) -> 0.7 | AA56: 1 | AB56: 0.9 | AC56: =AVERAGE('Calidad de Datos'!S60:V60) -> 1 | AD56: =Tabla13[[#This Row],[Uso y acceso Dic/2024]] -> 1 | AE56: =Tabla58[[#This Row],[Integración Dic/2024]] -> 0.9 | AF56: =AVERAGE(Tabla4[[#This Row],[Creación y captura Dic/2024]:[Compartición e Interoperabilidad Dic/2024]]) -> 0.96 | AG56: 1 | AH56: 1 | AI56: =AVERAGE('Calidad de Datos'!W60:Z60) -> 1 | AJ56: =Tabla13[[#This Row],[Uso y acceso Ene/2025]] -> 1 | AK56: =Tabla58[[#This Row],[Integración Ene/2025]] -> 1 | AL56: =AVERAGE(Tabla4[[#This Row],[Creación y captura Ene/2025]:[Compartición e Interoperabilidad Ene/2025]]) -> 1 | AM56: 1 | AN56: 1 | AO56: =AVERAGE('Calidad de Datos'!AA60:AD60) -> 1 | AP56: =Tabla13[[#This Row],[Uso y acceso Feb/2025]] -> 1 | AQ56: =Tabla58[[#This Row],[Integración Feb/2025]] -> 1 | AR56: =AVERAGE(Tabla4[[#This Row],[Creación y captura Feb/2025]:[Compartición e Interoperabilidad Feb/2025]]) -> 1 | AS56: 1 | AT56: 1 | AU56: =AVERAGE('Calidad de Datos'!AE60:AH60) -> 1 | AV56: =Tabla13[[#This Row],[Uso y acceso Mar/2025]] -> 1 | AW56: =Tabla58[[#This Row],[Integración Mar/2025]] -> 1 | AX56: =AVERAGE(Tabla4[[#This Row],[Creación y captura Mar/2025]:[Compartición e Interoperabilidad Mar/2025]]) -> 1 | AY56: 1 | AZ56: 1 | BA56: =AVERAGE('Calidad de Datos'!AI60:AL60) -> 1 | BB56: =Tabla13[[#This Row],[Uso y acceso Abr/2025]] -> 1 | BC56: =Tabla58[[#This Row],[Integración Abr/2025]] -> 1 | BD56: =AVERAGE(Tabla4[[#This Row],[Creación y captura Abr/2025]:[Compartición e Interoperabilidad Abr/2025]]) -> 1 | BE56: 1 | BF56: 1 | BG56: =AVERAGE('Calidad de Datos'!AM60:AP60) -> 1 | BH56: =Tabla13[[#This Row],[Uso y acceso May/2025]] -> 1 | BI56: =Tabla58[[#This Row],[Integración May/2025]] -> 1 | BJ56: =AVERAGE(Tabla4[[#This Row],[Creación y captura May/2025]:[Compartición e Interoperabilidad May/2025]]) -> 1 | BK56: 1 | BL56: 1 | BM56: =AVERAGE('Calidad de Datos'!AQ60:AT60) -> 1 | BN56: =Tabla13[[#This Row],[Uso y acceso Dic/2025]] -> 1 | BO56: =Tabla58[[#This Row],[Integración Dic/2025]] -> 1 | BP56: =AVERAGE(Tabla4[[#This Row],[Creación y captura Dic/2025]:[Compartición e Interoperabilidad Dic/2025]]) -> 1
B57: Plan de capacitaciones | E57: =AVERAGE('Calidad de Datos'!C61:F61) -> 0 | F57: =Tabla13[[#This Row],[Uso y acceso Ago/2024]] -> 0.5 | G57: =Tabla58[[#This Row],[Integración Ago/2024]] -> 0 | H57: =AVERAGE(Tabla4[[#This Row],[Creación y captura Ago/2024]:[Compartición e Interoperabilidad Ago/2024]]) -> 0.16666667 | K57: =AVERAGE('Calidad de Datos'!G61:J61) -> 0 | L57: =Tabla13[[#This Row],[Uso y acceso Sep/2024]] -> 0.5 | M57: =Tabla58[[#This Row],[Integración Sep/2024]] -> 0 | N57: =AVERAGE(Tabla4[[#This Row],[Creación y captura Sep/2024]:[Compartición e Interoperabilidad Sep/2024]]) -> 0.16666667 | Q57: =AVERAGE('Calidad de Datos'!K61:N61) -> 0 | R57: =Tabla13[[#This Row],[Uso y acceso Oct/2024]] -> 0.5 | S57: =Tabla58[[#This Row],[Integración Oct/2024]] -> 0 | T57: =AVERAGE(Tabla4[[#This Row],[Creación y captura Oct/2024]:[Compartición e Interoperabilidad Oct/2024]]) -> 0.16666667 | U57: 0.75 | V57: 0.5 | W57: =AVERAGE('Calidad de Datos'!O61:R61) -> 0.755 | X57: =Tabla13[[#This Row],[Uso y acceso Nov/2024]] -> 0.5 | Y57: =Tabla58[[#This Row],[Integración Nov/2024]] -> 0.5 | Z57: =AVERAGE(Tabla4[[#This Row],[Creación y captura Nov/2024]:[Compartición e Interoperabilidad Nov/2024]]) -> 0.601 | AA57: 0.8 | AB57: 0.9 | AC57: =AVERAGE('Calidad de Datos'!S61:V61) -> 0.805 | AD57: =Tabla13[[#This Row],[Uso y acceso Dic/2024]] -> 1 | AE57: =Tabla58[[#This Row],[Integración Dic/2024]] -> 0.9 | AF57: =AVERAGE(Tabla4[[#This Row],[Creación y captura Dic/2024]:[Compartición e Interoperabilidad Dic/2024]]) -> 0.881 | AG57: 0.9 | AH57: 0.95 | AI57: =AVERAGE('Calidad de Datos'!W61:Z61) -> 0.925 | AJ57: =Tabla13[[#This Row],[Uso y acceso Ene/2025]] -> 1 | AK57: =Tabla58[[#This Row],[Integración Ene/2025]] -> 0.95 | AL57: =AVERAGE(Tabla4[[#This Row],[Creación y captura Ene/2025]:[Compartición e Interoperabilidad Ene/2025]]) -> 0.945 | AM57: 0.95 | AN57: 1 | AO57: =AVERAGE('Calidad de Datos'!AA61:AD61) -> 0.9625 | AP57: =Tabla13[[#This Row],[Uso y acceso Feb/2025]] -> 1 | AQ57: =Tabla58[[#This Row],[Integración Feb/2025]] -> 1 | AR57: =AVERAGE(Tabla4[[#This Row],[Creación y captura Feb/2025]:[Compartición e Interoperabilidad Feb/2025]]) -> 0.9825 | AS57: 0.95 | AT57: 1 | AU57: =AVERAGE('Calidad de Datos'!AE61:AH61) -> 0.975 | AV57: =Tabla13[[#This Row],[Uso y acceso Mar/2025]] -> 1 | AW57: =Tabla58[[#This Row],[Integración Mar/2025]] -> 1 | AX57: =AVERAGE(Tabla4[[#This Row],[Creación y captura Mar/2025]:[Compartición e Interoperabilidad Mar/2025]]) -> 0.985 | AY57: 1 | AZ57: 1 | BA57: =AVERAGE('Calidad de Datos'!AI61:AL61) -> 1 | BB57: =Tabla13[[#This Row],[Uso y acceso Abr/2025]] -> 1 | BC57: =Tabla58[[#This Row],[Integración Abr/2025]] -> 1 | BD57: =AVERAGE(Tabla4[[#This Row],[Creación y captura Abr/2025]:[Compartición e Interoperabilidad Abr/2025]]) -> 1 | BE57: 1 | BF57: 1 | BG57: =AVERAGE('Calidad de Datos'!AM61:AP61) -> 1 | BH57: =Tabla13[[#This Row],[Uso y acceso May/2025]] -> 1 | BI57: =Tabla58[[#This Row],[Integración May/2025]] -> 1 | BJ57: =AVERAGE(Tabla4[[#This Row],[Creación y captura May/2025]:[Compartición e Interoperabilidad May/2025]]) -> 1 | BK57: 1 | BL57: 1 | BM57: =AVERAGE('Calidad de Datos'!AQ61:AT61) -> 1 | BN57: =Tabla13[[#This Row],[Uso y acceso Dic/2025]] -> 1 | BO57: =Tabla58[[#This Row],[Integración Dic/2025]] -> 1 | BP57: =AVERAGE(Tabla4[[#This Row],[Creación y captura Dic/2025]:[Compartición e Interoperabilidad Dic/2025]]) -> 1
B58: Ordenes de compras | F58: =Tabla13[[#This Row],[Uso y acceso Ago/2024]] -> 0.8 | G58: =Tabla58[[#This Row],[Integración Ago/2024]] -> 0 | H58: =AVERAGE(Tabla4[[#This Row],[Creación y captura Ago/2024]:[Compartición e Interoperabilidad Ago/2024]]) -> 0.4 | L58: =Tabla13[[#This Row],[Uso y acceso Sep/2024]] -> 0.8 | M58: =Tabla58[[#This Row],[Integración Sep/2024]] -> 0 | N58: =AVERAGE(Tabla4[[#This Row],[Creación y captura Sep/2024]:[Compartición e Interoperabilidad Sep/2024]]) -> 0.4 | R58: =Tabla13[[#This Row],[Uso y acceso Oct/2024]] -> 0.8 | S58: =Tabla58[[#This Row],[Integración Oct/2024]] -> 0 | T58: =AVERAGE(Tabla4[[#This Row],[Creación y captura Oct/2024]:[Compartición e Interoperabilidad Oct/2024]]) -> 0.4 | X58: =Tabla13[[#This Row],[Uso y acceso Nov/2024]] -> 0.08 | Y58: =Tabla58[[#This Row],[Integración Nov/2024]] -> 0 | Z58: =AVERAGE(Tabla4[[#This Row],[Creación y captura Nov/2024]:[Compartición e Interoperabilidad Nov/2024]]) -> 0.04 | AD58: =Tabla13[[#This Row],[Uso y acceso Dic/2024]] -> 0.8 | AE58: =Tabla58[[#This Row],[Integración Dic/2024]] -> 0 | AF58: =AVERAGE(Tabla4[[#This Row],[Creación y captura Dic/2024]:[Compartición e Interoperabilidad Dic/2024]]) -> 0.4 | AJ58: =Tabla13[[#This Row],[Uso y acceso Ene/2025]] -> 0.8 | AK58: =Tabla58[[#This Row],[Integración Ene/2025]] -> 0 | AL58: =AVERAGE(Tabla4[[#This Row],[Creación y captura Ene/2025]:[Compartición e Interoperabilidad Ene/2025]]) -> 0.4 | AP58: =Tabla13[[#This Row],[Uso y acceso Feb/2025]] -> 0.8 | AQ58: =Tabla58[[#This Row],[Integración Feb/2025]] -> 0 | AR58: =AVERAGE(Tabla4[[#This Row],[Creación y captura Feb/2025]:[Compartición e Interoperabilidad Feb/2025]]) -> 0.4 | AV58: =Tabla13[[#This Row],[Uso y acceso Mar/2025]] -> 0.8 | AW58: =Tabla58[[#This Row],[Integración Mar/2025]] -> 0 | AX58: =AVERAGE(Tabla4[[#This Row],[Creación y captura Mar/2025]:[Compartición e Interoperabilidad Mar/2025]]) -> 0.4 | AY58: 0.8 | AZ58: 0.5 | BA58: =AVERAGE('Calidad de Datos'!AI62:AL62) -> 0.55 | BB58: =Tabla13[[#This Row],[Uso y acceso Abr/2025]] -> 0.8 | BC58: =Tabla58[[#This Row],[Integración Abr/2025]] -> 0.3 | BD58: =AVERAGE(Tabla4[[#This Row],[Creación y captura Abr/2025]:[Compartición e Interoperabilidad Abr/2025]]) -> 0.59 | BE58: 0.8 | BF58: 0.5 | BG58: =AVERAGE('Calidad de Datos'!AM62:AP62) -> 1 | BH58: =Tabla13[[#This Row],[Uso y acceso May/2025]] -> 1 | BI58: =Tabla58[[#This Row],[Integración May/2025]] -> 0.3 | BJ58: =AVERAGE(Tabla4[[#This Row],[Creación y captura May/2025]:[Compartición e Interoperabilidad May/2025]]) -> 0.72 | BK58: 0.8 | BL58: 0.5 | BM58: =AVERAGE('Calidad de Datos'!AQ62:AT62) -> 1 | BN58: =Tabla13[[#This Row],[Uso y acceso Dic/2025]] -> 1 | BO58: =Tabla58[[#This Row],[Integración Dic/2025]] -> 0.8 | BP58: =AVERAGE(Tabla4[[#This Row],[Creación y captura Dic/2025]:[Compartición e Interoperabilidad Dic/2025]]) -> 0.82
B59: Proveedores | F59: =Tabla13[[#This Row],[Uso y acceso Ago/2024]] -> 1 | G59: =Tabla58[[#This Row],[Integración Ago/2024]] -> 0 | H59: =AVERAGE(Tabla4[[#This Row],[Creación y captura Ago/2024]:[Compartición e Interoperabilidad Ago/2024]]) -> 0.5 | L59: =Tabla13[[#This Row],[Uso y acceso Sep/2024]] -> 1 | M59: =Tabla58[[#This Row],[Integración Sep/2024]] -> 0 | N59: =AVERAGE(Tabla4[[#This Row],[Creación y captura Sep/2024]:[Compartición e Interoperabilidad Sep/2024]]) -> 0.5 | R59: =Tabla13[[#This Row],[Uso y acceso Oct/2024]] -> 1 | S59: =Tabla58[[#This Row],[Integración Oct/2024]] -> 0 | T59: =AVERAGE(Tabla4[[#This Row],[Creación y captura Oct/2024]:[Compartición e Interoperabilidad Oct/2024]]) -> 0.5 | X59: =Tabla13[[#This Row],[Uso y acceso Nov/2024]] -> 1 | Y59: =Tabla58[[#This Row],[Integración Nov/2024]] -> 0 | Z59: =AVERAGE(Tabla4[[#This Row],[Creación y captura Nov/2024]:[Compartición e Interoperabilidad Nov/2024]]) -> 0.5 | AD59: =Tabla13[[#This Row],[Uso y acceso Dic/2024]] -> 1 | AE59: =Tabla58[[#This Row],[Integración Dic/2024]] -> 0 | AF59: =AVERAGE(Tabla4[[#This Row],[Creación y captura Dic/2024]:[Compartición e Interoperabilidad Dic/2024]]) -> 0.5 | AJ59: =Tabla13[[#This Row],[Uso y acceso Ene/2025]] -> 1 | AK59: =Tabla58[[#This Row],[Integración Ene/2025]] -> 0 | AL59: =AVERAGE(Tabla4[[#This Row],[Creación y captura Ene/2025]:[Compartición e Interoperabilidad Ene/2025]]) -> 0.5 | AP59: =Tabla13[[#This Row],[Uso y acceso Feb/2025]] -> 1 | AQ59: =Tabla58[[#This Row],[Integración Feb/2025]] -> 0 | AR59: =AVERAGE(Tabla4[[#This Row],[Creación y captura Feb/2025]:[Compartición e Interoperabilidad Feb/2025]]) -> 0.5 | AV59: =Tabla13[[#This Row],[Uso y acceso Mar/2025]] -> 1 | AW59: =Tabla58[[#This Row],[Integración Mar/2025]] -> 0 | AX59: =AVERAGE(Tabla4[[#This Row],[Creación y captura Mar/2025]:[Compartición e Interoperabilidad Mar/2025]]) -> 0.5 | AY59: 0.8 | AZ59: 0.5 | BA59: =AVERAGE('Calidad de Datos'!AI63:AL63) -> 0.55 | BB59: =Tabla13[[#This Row],[Uso y acceso Abr/2025]] -> 1 | BC59: =Tabla58[[#This Row],[Integración Abr/2025]] -> 0.3 | BD59: =AVERAGE(Tabla4[[#This Row],[Creación y captura Abr/2025]:[Compartición e Interoperabilidad Abr/2025]]) -> 0.63 | BE59: 0.8 | BF59: 0.5 | BG59: =AVERAGE('Calidad de Datos'!AM63:AP63) -> 1 | BH59: =Tabla13[[#This Row],[Uso y acceso May/2025]] -> 1 | BI59: =Tabla58[[#This Row],[Integración May/2025]] -> 0.3 | BJ59: =AVERAGE(Tabla4[[#This Row],[Creación y captura May/2025]:[Compartición e Interoperabilidad May/2025]]) -> 0.72 | BK59: 1 | BL59: 1 | BM59: =AVERAGE('Calidad de Datos'!AQ63:AT63) -> 1 | BN59: =Tabla13[[#This Row],[Uso y acceso Dic/2025]] -> 1 | BO59: =Tabla58[[#This Row],[Integración Dic/2025]] -> 1 | BP59: =AVERAGE(Tabla4[[#This Row],[Creación y captura Dic/2025]:[Compartición e Interoperabilidad Dic/2025]]) -> 1
B60: Requisiciones | F60: =Tabla13[[#This Row],[Uso y acceso Ago/2024]] -> 0.8 | G60: =Tabla58[[#This Row],[Integración Ago/2024]] -> 0 | H60: =AVERAGE(Tabla4[[#This Row],[Creación y captura Ago/2024]:[Compartición e Interoperabilidad Ago/2024]]) -> 0.4 | L60: =Tabla13[[#This Row],[Uso y acceso Sep/2024]] -> 0.8 | M60: =Tabla58[[#This Row],[Integración Sep/2024]] -> 0 | N60: =AVERAGE(Tabla4[[#This Row],[Creación y captura Sep/2024]:[Compartición e Interoperabilidad Sep/2024]]) -> 0.4 | R60: =Tabla13[[#This Row],[Uso y acceso Oct/2024]] -> 0.8 | S60: =Tabla58[[#This Row],[Integración Oct/2024]] -> 0 | T60: =AVERAGE(Tabla4[[#This Row],[Creación y captura Oct/2024]:[Compartición e Interoperabilidad Oct/2024]]) -> 0.4 | X60: =Tabla13[[#This Row],[Uso y acceso Nov/2024]] -> 0.8 | Y60: =Tabla58[[#This Row],[Integración Nov/2024]] -> 0 | Z60: =AVERAGE(Tabla4[[#This Row],[Creación y captura Nov/2024]:[Compartición e Interoperabilidad Nov/2024]]) -> 0.4 | AD60: =Tabla13[[#This Row],[Uso y acceso Dic/2024]] -> 0.8 | AE60: =Tabla58[[#This Row],[Integración Dic/2024]] -> 0 | AF60: =AVERAGE(Tabla4[[#This Row],[Creación y captura Dic/2024]:[Compartición e Interoperabilidad Dic/2024]]) -> 0.4 | AJ60: =Tabla13[[#This Row],[Uso y acceso Ene/2025]] -> 0.8 | AK60: =Tabla58[[#This Row],[Integración Ene/2025]] -> 0 | AL60: =AVERAGE(Tabla4[[#This Row],[Creación y captura Ene/2025]:[Compartición e Interoperabilidad Ene/2025]]) -> 0.4 | AP60: =Tabla13[[#This Row],[Uso y acceso Feb/2025]] -> 0.8 | AQ60: =Tabla58[[#This Row],[Integración Feb/2025]] -> 0 | AR60: =AVERAGE(Tabla4[[#This Row],[Creación y captura Feb/2025]:[Compartición e Interoperabilidad Feb/2025]]) -> 0.4 | AV60: =Tabla13[[#This Row],[Uso y acceso Mar/2025]] -> 0.8 | AW60: =Tabla58[[#This Row],[Integración Mar/2025]] -> 0 | AX60: =AVERAGE(Tabla4[[#This Row],[Creación y captura Mar/2025]:[Compartición e Interoperabilidad Mar/2025]]) -> 0.4 | AY60: 0.8 | AZ60: 0.5 | BA60: =AVERAGE('Calidad de Datos'!AI64:AL64) -> 0.55 | BB60: =Tabla13[[#This Row],[Uso y acceso Abr/2025]] -> 0.8 | BC60: =Tabla58[[#This Row],[Integración Abr/2025]] -> 0.3 | BD60: =AVERAGE(Tabla4[[#This Row],[Creación y captura Abr/2025]:[Compartición e Interoperabilidad Abr/2025]]) -> 0.59 | BE60: 0.8 | BF60: 0.5 | BG60: =AVERAGE('Calidad de Datos'!AM64:AP64) -> 1 | BH60: =Tabla13[[#This Row],[Uso y acceso May/2025]] -> 1 | BI60: =Tabla58[[#This Row],[Integración May/2025]] -> 0.3 | BJ60: =AVERAGE(Tabla4[[#This Row],[Creación y captura May/2025]:[Compartición e Interoperabilidad May/2025]]) -> 0.72 | BK60: 0.8 | BL60: 0.5 | BM60: =AVERAGE('Calidad de Datos'!AQ64:AT64) -> 1 | BN60: =Tabla13[[#This Row],[Uso y acceso Dic/2025]] -> 1 | BO60: =Tabla58[[#This Row],[Integración Dic/2025]] -> 0.8 | BP60: =AVERAGE(Tabla4[[#This Row],[Creación y captura Dic/2025]:[Compartición e Interoperabilidad Dic/2025]]) -> 0.82
B61: Contratos | F61: =Tabla13[[#This Row],[Uso y acceso Ago/2024]] -> 0.8 | G61: =Tabla58[[#This Row],[Integración Ago/2024]] -> 0 | H61: =AVERAGE(Tabla4[[#This Row],[Creación y captura Ago/2024]:[Compartición e Interoperabilidad Ago/2024]]) -> 0.4 | L61: =Tabla13[[#This Row],[Uso y acceso Sep/2024]] -> 0.8 | M61: =Tabla58[[#This Row],[Integración Sep/2024]] -> 0 | N61: =AVERAGE(Tabla4[[#This Row],[Creación y captura Sep/2024]:[Compartición e Interoperabilidad Sep/2024]]) -> 0.4 | R61: =Tabla13[[#This Row],[Uso y acceso Oct/2024]] -> 0.8 | S61: =Tabla58[[#This Row],[Integración Oct/2024]] -> 0 | T61: =AVERAGE(Tabla4[[#This Row],[Creación y captura Oct/2024]:[Compartición e Interoperabilidad Oct/2024]]) -> 0.4 | X61: =Tabla13[[#This Row],[Uso y acceso Nov/2024]] -> 0.8 | Y61: =Tabla58[[#This Row],[Integración Nov/2024]] -> 0 | Z61: =AVERAGE(Tabla4[[#This Row],[Creación y captura Nov/2024]:[Compartición e Interoperabilidad Nov/2024]]) -> 0.4 | AD61: =Tabla13[[#This Row],[Uso y acceso Dic/2024]] -> 0.8 | AE61: =Tabla58[[#This Row],[Integración Dic/2024]] -> 0 | AF61: =AVERAGE(Tabla4[[#This Row],[Creación y captura Dic/2024]:[Compartición e Interoperabilidad Dic/2024]]) -> 0.4 | AJ61: =Tabla13[[#This Row],[Uso y acceso Ene/2025]] -> 0.8 | AK61: =Tabla58[[#This Row],[Integración Ene/2025]] -> 0 | AL61: =AVERAGE(Tabla4[[#This Row],[Creación y captura Ene/2025]:[Compartición e Interoperabilidad Ene/2025]]) -> 0.4 | AP61: =Tabla13[[#This Row],[Uso y acceso Feb/2025]] -> 0.8 | AQ61: =Tabla58[[#This Row],[Integración Feb/2025]] -> 0 | AR61: =AVERAGE(Tabla4[[#This Row],[Creación y captura Feb/2025]:[Compartición e Interoperabilidad Feb/2025]]) -> 0.4 | AV61: =Tabla13[[#This Row],[Uso y acceso Mar/2025]] -> 0.8 | AW61: =Tabla58[[#This Row],[Integración Mar/2025]] -> 0 | AX61: =AVERAGE(Tabla4[[#This Row],[Creación y captura Mar/2025]:[Compartición e Interoperabilidad Mar/2025]]) -> 0.4 | AY61: 0.8 | AZ61: 0.5 | BA61: =AVERAGE('Calidad de Datos'!AI65:AL65) -> 0.7 | BB61: =Tabla13[[#This Row],[Uso y acceso Abr/2025]] -> 0.8 | BC61: =Tabla58[[#This Row],[Integración Abr/2025]] -> 0.3 | BD61: =AVERAGE(Tabla4[[#This Row],[Creación y captura Abr/2025]:[Compartición e Interoperabilidad Abr/2025]]) -> 0.62 | BE61: 0.8 | BF61: 0.5 | BG61: =AVERAGE('Calidad de Datos'!AM65:AP65) -> 1 | BH61: =Tabla13[[#This Row],[Uso y acceso May/2025]] -> 1 | BI61: =Tabla58[[#This Row],[Integración May/2025]] -> 0.3 | BJ61: =AVERAGE(Tabla4[[#This Row],[Creación y captura May/2025]:[Compartición e Interoperabilidad May/2025]]) -> 0.72 | BK61: 0.8 | BL61: 0.5 | BM61: =AVERAGE('Calidad de Datos'!AQ65:AT65) -> 1 | BN61: =Tabla13[[#This Row],[Uso y acceso Dic/2025]] -> 1 | BO61: =Tabla58[[#This Row],[Integración Dic/2025]] -> 0.8 | BP61: =AVERAGE(Tabla4[[#This Row],[Creación y captura Dic/2025]:[Compartición e Interoperabilidad Dic/2025]]) -> 0.82
B62: Solicitud de contratación logistica | F62: =Tabla13[[#This Row],[Uso y acceso Ago/2024]] -> 0.8 | G62: =Tabla58[[#This Row],[Integración Ago/2024]] -> 0 | H62: =AVERAGE(Tabla4[[#This Row],[Creación y captura Ago/2024]:[Compartición e Interoperabilidad Ago/2024]]) -> 0.4 | L62: =Tabla13[[#This Row],[Uso y acceso Sep/2024]] -> 0.8 | M62: =Tabla58[[#This Row],[Integración Sep/2024]] -> 0 | N62: =AVERAGE(Tabla4[[#This Row],[Creación y captura Sep/2024]:[Compartición e Interoperabilidad Sep/2024]]) -> 0.4 | R62: =Tabla13[[#This Row],[Uso y acceso Oct/2024]] -> 0.8 | S62: =Tabla58[[#This Row],[Integración Oct/2024]] -> 0 | T62: =AVERAGE(Tabla4[[#This Row],[Creación y captura Oct/2024]:[Compartición e Interoperabilidad Oct/2024]]) -> 0.4 | X62: =Tabla13[[#This Row],[Uso y acceso Nov/2024]] -> 0.8 | Y62: =Tabla58[[#This Row],[Integración Nov/2024]] -> 0 | Z62: =AVERAGE(Tabla4[[#This Row],[Creación y captura Nov/2024]:[Compartición e Interoperabilidad Nov/2024]]) -> 0.4 | AD62: =Tabla13[[#This Row],[Uso y acceso Dic/2024]] -> 0.8 | AE62: =Tabla58[[#This Row],[Integración Dic/2024]] -> 0 | AF62: =AVERAGE(Tabla4[[#This Row],[Creación y captura Dic/2024]:[Compartición e Interoperabilidad Dic/2024]]) -> 0.4 | AJ62: =Tabla13[[#This Row],[Uso y acceso Ene/2025]] -> 0.8 | AK62: =Tabla58[[#This Row],[Integración Ene/2025]] -> 0 | AL62: =AVERAGE(Tabla4[[#This Row],[Creación y captura Ene/2025]:[Compartición e Interoperabilidad Ene/2025]]) -> 0.4 | AP62: =Tabla13[[#This Row],[Uso y acceso Feb/2025]] -> 0.8 | AQ62: =Tabla58[[#This Row],[Integración Feb/2025]] -> 0 | AR62: =AVERAGE(Tabla4[[#This Row],[Creación y captura Feb/2025]:[Compartición e Interoperabilidad Feb/2025]]) -> 0.4 | AV62: =Tabla13[[#This Row],[Uso y acceso Mar/2025]] -> 0.8 | AW62: =Tabla58[[#This Row],[Integración Mar/2025]] -> 0 | AX62: =AVERAGE(Tabla4[[#This Row],[Creación y captura Mar/2025]:[Compartición e Interoperabilidad Mar/2025]]) -> 0.4 | AY62: 0.8 | AZ62: 0.5 | BA62: =AVERAGE('Calidad de Datos'!AI66:AL66) -> 0.7 | BB62: =Tabla13[[#This Row],[Uso y acceso Abr/2025]] -> 0.8 | BC62: =Tabla58[[#This Row],[Integración Abr/2025]] -> 0.3 | BD62: =AVERAGE(Tabla4[[#This Row],[Creación y captura Abr/2025]:[Compartición e Interoperabilidad Abr/2025]]) -> 0.62 | BE62: 0.8 | BF62: 0.5 | BG62: =AVERAGE('Calidad de Datos'!AM66:AP66) -> 1 | BH62: =Tabla13[[#This Row],[Uso y acceso May/2025]] -> 1 | BI62: =Tabla58[[#This Row],[Integración May/2025]] -> 0.3 | BJ62: =AVERAGE(Tabla4[[#This Row],[Creación y captura May/2025]:[Compartición e Interoperabilidad May/2025]]) -> 0.72 | BK62: 0.8 | BL62: 0.5 | BM62: =AVERAGE('Calidad de Datos'!AQ66:AT66) -> 1 | BN62: =Tabla13[[#This Row],[Uso y acceso Dic/2025]] -> 1 | BO62: =Tabla58[[#This Row],[Integración Dic/2025]] -> 0.8 | BP62: =AVERAGE(Tabla4[[#This Row],[Creación y captura Dic/2025]:[Compartición e Interoperabilidad Dic/2025]]) -> 0.82
B63: Registro de ahorros | F63: =Tabla13[[#This Row],[Uso y acceso Ago/2024]] -> 0.8 | G63: =Tabla58[[#This Row],[Integración Ago/2024]] -> 0 | H63: =AVERAGE(Tabla4[[#This Row],[Creación y captura Ago/2024]:[Compartición e Interoperabilidad Ago/2024]]) -> 0.4 | L63: =Tabla13[[#This Row],[Uso y acceso Sep/2024]] -> 0.8 | M63: =Tabla58[[#This Row],[Integración Sep/2024]] -> 0 | N63: =AVERAGE(Tabla4[[#This Row],[Creación y captura Sep/2024]:[Compartición e Interoperabilidad Sep/2024]]) -> 0.4 | R63: =Tabla13[[#This Row],[Uso y acceso Oct/2024]] -> 0.8 | S63: =Tabla58[[#This Row],[Integración Oct/2024]] -> 0 | T63: =AVERAGE(Tabla4[[#This Row],[Creación y captura Oct/2024]:[Compartición e Interoperabilidad Oct/2024]]) -> 0.4 | X63: =Tabla13[[#This Row],[Uso y acceso Nov/2024]] -> 0.8 | Y63: =Tabla58[[#This Row],[Integración Nov/2024]] -> 0 | Z63: =AVERAGE(Tabla4[[#This Row],[Creación y captura Nov/2024]:[Compartición e Interoperabilidad Nov/2024]]) -> 0.4 | AD63: =Tabla13[[#This Row],[Uso y acceso Dic/2024]] -> 0.8 | AE63: =Tabla58[[#This Row],[Integración Dic/2024]] -> 0 | AF63: =AVERAGE(Tabla4[[#This Row],[Creación y captura Dic/2024]:[Compartición e Interoperabilidad Dic/2024]]) -> 0.4 | AJ63: =Tabla13[[#This Row],[Uso y acceso Ene/2025]] -> 0.8 | AK63: =Tabla58[[#This Row],[Integración Ene/2025]] -> 0 | AL63: =AVERAGE(Tabla4[[#This Row],[Creación y captura Ene/2025]:[Compartición e Interoperabilidad Ene/2025]]) -> 0.4 | AP63: =Tabla13[[#This Row],[Uso y acceso Feb/2025]] -> 0.8 | AQ63: =Tabla58[[#This Row],[Integración Feb/2025]] -> 0 | AR63: =AVERAGE(Tabla4[[#This Row],[Creación y captura Feb/2025]:[Compartición e Interoperabilidad Feb/2025]]) -> 0.4 | AV63: =Tabla13[[#This Row],[Uso y acceso Mar/2025]] -> 0.8 | AW63: =Tabla58[[#This Row],[Integración Mar/2025]] -> 0 | AX63: =AVERAGE(Tabla4[[#This Row],[Creación y captura Mar/2025]:[Compartición e Interoperabilidad Mar/2025]]) -> 0.4 | AY63: 0.8 | AZ63: 0.5 | BA63: =AVERAGE('Calidad de Datos'!AI67:AL67) -> 0.7 | BB63: =Tabla13[[#This Row],[Uso y acceso Abr/2025]] -> 0.8 | BC63: =Tabla58[[#This Row],[Integración Abr/2025]] -> 0.3 | BD63: =AVERAGE(Tabla4[[#This Row],[Creación y captura Abr/2025]:[Compartición e Interoperabilidad Abr/2025]]) -> 0.62 | BE63: 0.8 | BF63: 0.5 | BG63: =AVERAGE('Calidad de Datos'!AM67:AP67) -> 1 | BH63: =Tabla13[[#This Row],[Uso y acceso May/2025]] -> 1 | BI63: =Tabla58[[#This Row],[Integración May/2025]] -> 0.3 | BJ63: =AVERAGE(Tabla4[[#This Row],[Creación y captura May/2025]:[Compartición e Interoperabilidad May/2025]]) -> 0.72 | BK63: 0.8 | BL63: 0.5 | BM63: =AVERAGE('Calidad de Datos'!AQ67:AT67) -> 1 | BN63: =Tabla13[[#This Row],[Uso y acceso Dic/2025]] -> 1 | BO63: =Tabla58[[#This Row],[Integración Dic/2025]] -> 0.8 | BP63: =AVERAGE(Tabla4[[#This Row],[Creación y captura Dic/2025]:[Compartición e Interoperabilidad Dic/2025]]) -> 0.82
B64: Modelo financiero | F64: =Tabla13[[#This Row],[Uso y acceso Ago/2024]] -> 1 | G64: =Tabla58[[#This Row],[Integración Ago/2024]] -> 0 | H64: =AVERAGE(Tabla4[[#This Row],[Creación y captura Ago/2024]:[Compartición e Interoperabilidad Ago/2024]]) -> 0.5 | L64: =Tabla13[[#This Row],[Uso y acceso Sep/2024]] -> 1 | M64: =Tabla58[[#This Row],[Integración Sep/2024]] -> 0 | N64: =AVERAGE(Tabla4[[#This Row],[Creación y captura Sep/2024]:[Compartición e Interoperabilidad Sep/2024]]) -> 0.5 | R64: =Tabla13[[#This Row],[Uso y acceso Oct/2024]] -> 1 | S64: =Tabla58[[#This Row],[Integración Oct/2024]] -> 0 | T64: =AVERAGE(Tabla4[[#This Row],[Creación y captura Oct/2024]:[Compartición e Interoperabilidad Oct/2024]]) -> 0.5 | X64: =Tabla13[[#This Row],[Uso y acceso Nov/2024]] -> 1 | Y64: =Tabla58[[#This Row],[Integración Nov/2024]] -> 0 | Z64: =AVERAGE(Tabla4[[#This Row],[Creación y captura Nov/2024]:[Compartición e Interoperabilidad Nov/2024]]) -> 0.5 | AD64: =Tabla13[[#This Row],[Uso y acceso Dic/2024]] -> 1 | AE64: =Tabla58[[#This Row],[Integración Dic/2024]] -> 0 | AF64: =AVERAGE(Tabla4[[#This Row],[Creación y captura Dic/2024]:[Compartición e Interoperabilidad Dic/2024]]) -> 0.5 | AJ64: =Tabla13[[#This Row],[Uso y acceso Ene/2025]] -> 1 | AK64: =Tabla58[[#This Row],[Integración Ene/2025]] -> 0 | AL64: =AVERAGE(Tabla4[[#This Row],[Creación y captura Ene/2025]:[Compartición e Interoperabilidad Ene/2025]]) -> 0.5 | AP64: =Tabla13[[#This Row],[Uso y acceso Feb/2025]] -> 1 | AQ64: =Tabla58[[#This Row],[Integración Feb/2025]] -> 0 | AR64: =AVERAGE(Tabla4[[#This Row],[Creación y captura Feb/2025]:[Compartición e Interoperabilidad Feb/2025]]) -> 0.5 | AV64: =Tabla13[[#This Row],[Uso y acceso Mar/2025]] -> 1 | AW64: =Tabla58[[#This Row],[Integración Mar/2025]] -> 0 | AX64: =AVERAGE(Tabla4[[#This Row],[Creación y captura Mar/2025]:[Compartición e Interoperabilidad Mar/2025]]) -> 0.5 | BB64: =Tabla13[[#This Row],[Uso y acceso Abr/2025]] -> 1 | BC64: =Tabla58[[#This Row],[Integración Abr/2025]] -> 0 | BD64: =AVERAGE(Tabla4[[#This Row],[Creación y captura Abr/2025]:[Compartición e Interoperabilidad Abr/2025]]) -> 0.5 | BE64: 0.8 | BF64: 0.5 | BG64: =AVERAGE('Calidad de Datos'!AM68:AP68) -> 1 | BH64: =Tabla13[[#This Row],[Uso y acceso May/2025]] -> 1 | BI64: =Tabla58[[#This Row],[Integración May/2025]] -> 0.3 | BJ64: =AVERAGE(Tabla4[[#This Row],[Creación y captura May/2025]:[Compartición e Interoperabilidad May/2025]]) -> 0.72 | BK64: 1 | BL64: 1 | BM64: =AVERAGE('Calidad de Datos'!AQ68:AT68) -> 1 | BN64: =Tabla13[[#This Row],[Uso y acceso Dic/2025]] -> 1 | BO64: =Tabla58[[#This Row],[Integración Dic/2025]] -> 1 | BP64: =AVERAGE(Tabla4[[#This Row],[Creación y captura Dic/2025]:[Compartición e Interoperabilidad Dic/2025]]) -> 1
B65: Oferta comercial | F65: =Tabla13[[#This Row],[Uso y acceso Ago/2024]] -> 1 | G65: =Tabla58[[#This Row],[Integración Ago/2024]] -> 0 | H65: =AVERAGE(Tabla4[[#This Row],[Creación y captura Ago/2024]:[Compartición e Interoperabilidad Ago/2024]]) -> 0.5 | L65: =Tabla13[[#This Row],[Uso y acceso Sep/2024]] -> 1 | M65: =Tabla58[[#This Row],[Integración Sep/2024]] -> 0 | N65: =AVERAGE(Tabla4[[#This Row],[Creación y captura Sep/2024]:[Compartición e Interoperabilidad Sep/2024]]) -> 0.5 | R65: =Tabla13[[#This Row],[Uso y acceso Oct/2024]] -> 1 | S65: =Tabla58[[#This Row],[Integración Oct/2024]] -> 0 | T65: =AVERAGE(Tabla4[[#This Row],[Creación y captura Oct/2024]:[Compartición e Interoperabilidad Oct/2024]]) -> 0.5 | X65: =Tabla13[[#This Row],[Uso y acceso Nov/2024]] -> 1 | Y65: =Tabla58[[#This Row],[Integración Nov/2024]] -> 0 | Z65: =AVERAGE(Tabla4[[#This Row],[Creación y captura Nov/2024]:[Compartición e Interoperabilidad Nov/2024]]) -> 0.5 | AD65: =Tabla13[[#This Row],[Uso y acceso Dic/2024]] -> 1 | AE65: =Tabla58[[#This Row],[Integración Dic/2024]] -> 0 | AF65: =AVERAGE(Tabla4[[#This Row],[Creación y captura Dic/2024]:[Compartición e Interoperabilidad Dic/2024]]) -> 0.5 | AJ65: =Tabla13[[#This Row],[Uso y acceso Ene/2025]] -> 1 | AK65: =Tabla58[[#This Row],[Integración Ene/2025]] -> 0 | AL65: =AVERAGE(Tabla4[[#This Row],[Creación y captura Ene/2025]:[Compartición e Interoperabilidad Ene/2025]]) -> 0.5 | AP65: =Tabla13[[#This Row],[Uso y acceso Feb/2025]] -> 1 | AQ65: =Tabla58[[#This Row],[Integración Feb/2025]] -> 0 | AR65: =AVERAGE(Tabla4[[#This Row],[Creación y captura Feb/2025]:[Compartición e Interoperabilidad Feb/2025]]) -> 0.5 | AV65: =Tabla13[[#This Row],[Uso y acceso Mar/2025]] -> 1 | AW65: =Tabla58[[#This Row],[Integración Mar/2025]] -> 0 | AX65: =AVERAGE(Tabla4[[#This Row],[Creación y captura Mar/2025]:[Compartición e Interoperabilidad Mar/2025]]) -> 0.5 | BB65: =Tabla13[[#This Row],[Uso y acceso Abr/2025]] -> 1 | BC65: =Tabla58[[#This Row],[Integración Abr/2025]] -> 0 | BD65: =AVERAGE(Tabla4[[#This Row],[Creación y captura Abr/2025]:[Compartición e Interoperabilidad Abr/2025]]) -> 0.5 | BE65: 0 | BH65: =Tabla13[[#This Row],[Uso y acceso May/2025]] -> 1 | BI65: =Tabla58[[#This Row],[Integración May/2025]] -> 0 | BJ65: =AVERAGE(Tabla4[[#This Row],[Creación y captura May/2025]:[Compartición e Interoperabilidad May/2025]]) -> 0.33333333 | BK65: 0 | BM65: =AVERAGE('Calidad de Datos'!AQ69:AT69) -> 0.95 | BN65: =Tabla13[[#This Row],[Uso y acceso Dic/2025]] -> 1 | BO65: =Tabla58[[#This Row],[Integración Dic/2025]] -> 0.8 | BP65: =AVERAGE(Tabla4[[#This Row],[Creación y captura Dic/2025]:[Compartición e Interoperabilidad Dic/2025]]) -> 0.6875
B66: Acta | F66: =Tabla13[[#This Row],[Uso y acceso Ago/2024]] -> 1 | G66: =Tabla58[[#This Row],[Integración Ago/2024]] -> 0 | H66: =AVERAGE(Tabla4[[#This Row],[Creación y captura Ago/2024]:[Compartición e Interoperabilidad Ago/2024]]) -> 0.5 | L66: =Tabla13[[#This Row],[Uso y acceso Sep/2024]] -> 1 | M66: =Tabla58[[#This Row],[Integración Sep/2024]] -> 0 | N66: =AVERAGE(Tabla4[[#This Row],[Creación y captura Sep/2024]:[Compartición e Interoperabilidad Sep/2024]]) -> 0.5 | R66: =Tabla13[[#This Row],[Uso y acceso Oct/2024]] -> 1 | S66: =Tabla58[[#This Row],[Integración Oct/2024]] -> 0 | T66: =AVERAGE(Tabla4[[#This Row],[Creación y captura Oct/2024]:[Compartición e Interoperabilidad Oct/2024]]) -> 0.5 | X66: =Tabla13[[#This Row],[Uso y acceso Nov/2024]] -> 1 | Y66: =Tabla58[[#This Row],[Integración Nov/2024]] -> 0 | Z66: =AVERAGE(Tabla4[[#This Row],[Creación y captura Nov/2024]:[Compartición e Interoperabilidad Nov/2024]]) -> 0.5 | AD66: =Tabla13[[#This Row],[Uso y acceso Dic/2024]] -> 1 | AE66: =Tabla58[[#This Row],[Integración Dic/2024]] -> 0 | AF66: =AVERAGE(Tabla4[[#This Row],[Creación y captura Dic/2024]:[Compartición e Interoperabilidad Dic/2024]]) -> 0.5 | AJ66: =Tabla13[[#This Row],[Uso y acceso Ene/2025]] -> 1 | AK66: =Tabla58[[#This Row],[Integración Ene/2025]] -> 0 | AL66: =AVERAGE(Tabla4[[#This Row],[Creación y captura Ene/2025]:[Compartición e Interoperabilidad Ene/2025]]) -> 0.5 | AP66: =Tabla13[[#This Row],[Uso y acceso Feb/2025]] -> 1 | AQ66: =Tabla58[[#This Row],[Integración Feb/2025]] -> 0 | AR66: =AVERAGE(Tabla4[[#This Row],[Creación y captura Feb/2025]:[Compartición e Interoperabilidad Feb/2025]]) -> 0.5 | AV66: =Tabla13[[#This Row],[Uso y acceso Mar/2025]] -> 1 | AW66: =Tabla58[[#This Row],[Integración Mar/2025]] -> 0 | AX66: =AVERAGE(Tabla4[[#This Row],[Creación y captura Mar/2025]:[Compartición e Interoperabilidad Mar/2025]]) -> 0.5 | BB66: =Tabla13[[#This Row],[Uso y acceso Abr/2025]] -> 1 | BC66: =Tabla58[[#This Row],[Integración Abr/2025]] -> 0 | BD66: =AVERAGE(Tabla4[[#This Row],[Creación y captura Abr/2025]:[Compartición e Interoperabilidad Abr/2025]]) -> 0.5 | BE66: 0 | BH66: =Tabla13[[#This Row],[Uso y acceso May/2025]] -> 1 | BI66: =Tabla58[[#This Row],[Integración May/2025]] -> 0 | BJ66: =AVERAGE(Tabla4[[#This Row],[Creación y captura May/2025]:[Compartición e Interoperabilidad May/2025]]) -> 0.33333333 | BK66: 1 | BL66: 1 | BM66: =AVERAGE('Calidad de Datos'!AQ70:AT70) -> 1 | BN66: =Tabla13[[#This Row],[Uso y acceso Dic/2025]] -> 1 | BO66: =Tabla58[[#This Row],[Integración Dic/2025]] -> 1 | BP66: =AVERAGE(Tabla4[[#This Row],[Creación y captura Dic/2025]:[Compartición e Interoperabilidad Dic/2025]]) -> 1
B67: Fabricante | F67: =Tabla13[[#This Row],[Uso y acceso Ago/2024]] -> 1 | G67: =Tabla58[[#This Row],[Integración Ago/2024]] -> 0 | H67: =AVERAGE(Tabla4[[#This Row],[Creación y captura Ago/2024]:[Compartición e Interoperabilidad Ago/2024]]) -> 0.5 | L67: =Tabla13[[#This Row],[Uso y acceso Sep/2024]] -> 1 | M67: =Tabla58[[#This Row],[Integración Sep/2024]] -> 0 | N67: =AVERAGE(Tabla4[[#This Row],[Creación y captura Sep/2024]:[Compartición e Interoperabilidad Sep/2024]]) -> 0.5 | R67: =Tabla13[[#This Row],[Uso y acceso Oct/2024]] -> 1 | S67: =Tabla58[[#This Row],[Integración Oct/2024]] -> 0 | T67: =AVERAGE(Tabla4[[#This Row],[Creación y captura Oct/2024]:[Compartición e Interoperabilidad Oct/2024]]) -> 0.5 | X67: =Tabla13[[#This Row],[Uso y acceso Nov/2024]] -> 1 | Y67: =Tabla58[[#This Row],[Integración Nov/2024]] -> 0 | Z67: =AVERAGE(Tabla4[[#This Row],[Creación y captura Nov/2024]:[Compartición e Interoperabilidad Nov/2024]]) -> 0.5 | AD67: =Tabla13[[#This Row],[Uso y acceso Dic/2024]] -> 1 | AE67: =Tabla58[[#This Row],[Integración Dic/2024]] -> 0 | AF67: =AVERAGE(Tabla4[[#This Row],[Creación y captura Dic/2024]:[Compartición e Interoperabilidad Dic/2024]]) -> 0.5 | AJ67: =Tabla13[[#This Row],[Uso y acceso Ene/2025]] -> 1 | AK67: =Tabla58[[#This Row],[Integración Ene/2025]] -> 0 | AL67: =AVERAGE(Tabla4[[#This Row],[Creación y captura Ene/2025]:[Compartición e Interoperabilidad Ene/2025]]) -> 0.5 | AP67: =Tabla13[[#This Row],[Uso y acceso Feb/2025]] -> 1 | AQ67: =Tabla58[[#This Row],[Integración Feb/2025]] -> 0 | AR67: =AVERAGE(Tabla4[[#This Row],[Creación y captura Feb/2025]:[Compartición e Interoperabilidad Feb/2025]]) -> 0.5 | AV67: =Tabla13[[#This Row],[Uso y acceso Mar/2025]] -> 1 | AW67: =Tabla58[[#This Row],[Integración Mar/2025]] -> 0 | AX67: =AVERAGE(Tabla4[[#This Row],[Creación y captura Mar/2025]:[Compartición e Interoperabilidad Mar/2025]]) -> 0.5 | AY67: 1 | AZ67: 1 | BA67: =AVERAGE('Calidad de Datos'!AI71:AL71) -> 1 | BB67: =Tabla13[[#This Row],[Uso y acceso Abr/2025]] -> 1 | BC67: =Tabla58[[#This Row],[Integración Abr/2025]] -> 1 | BD67: =AVERAGE(Tabla4[[#This Row],[Creación y captura Abr/2025]:[Compartición e Interoperabilidad Abr/2025]]) -> 1 | BE67: 1 | BF67: 1 | BG67: =AVERAGE('Calidad de Datos'!AM71:AP71) -> 1 | BH67: =Tabla13[[#This Row],[Uso y acceso May/2025]] -> 1 | BI67: =Tabla58[[#This Row],[Integración May/2025]] -> 1 | BJ67: =AVERAGE(Tabla4[[#This Row],[Creación y captura May/2025]:[Compartición e Interoperabilidad May/2025]]) -> 1 | BK67: 1 | BL67: 1 | BM67: =AVERAGE('Calidad de Datos'!AQ71:AT71) -> 1 | BN67: =Tabla13[[#This Row],[Uso y acceso Dic/2025]] -> 1 | BO67: =Tabla58[[#This Row],[Integración Dic/2025]] -> 1 | BP67: =AVERAGE(Tabla4[[#This Row],[Creación y captura Dic/2025]:[Compartición e Interoperabilidad Dic/2025]]) -> 1
B68: Proceso | F68: =Tabla13[[#This Row],[Uso y acceso Ago/2024]] -> 0.8 | G68: =Tabla58[[#This Row],[Integración Ago/2024]] -> 0 | H68: =AVERAGE(Tabla4[[#This Row],[Creación y captura Ago/2024]:[Compartición e Interoperabilidad Ago/2024]]) -> 0.4 | L68: =Tabla13[[#This Row],[Uso y acceso Sep/2024]] -> 0.8 | M68: =Tabla58[[#This Row],[Integración Sep/2024]] -> 0 | N68: =AVERAGE(Tabla4[[#This Row],[Creación y captura Sep/2024]:[Compartición e Interoperabilidad Sep/2024]]) -> 0.4 | R68: =Tabla13[[#This Row],[Uso y acceso Oct/2024]] -> 1 | S68: =Tabla58[[#This Row],[Integración Oct/2024]] -> 0 | T68: =AVERAGE(Tabla4[[#This Row],[Creación y captura Oct/2024]:[Compartición e Interoperabilidad Oct/2024]]) -> 0.5 | X68: =Tabla13[[#This Row],[Uso y acceso Nov/2024]] -> 1 | Y68: =Tabla58[[#This Row],[Integración Nov/2024]] -> 0 | Z68: =AVERAGE(Tabla4[[#This Row],[Creación y captura Nov/2024]:[Compartición e Interoperabilidad Nov/2024]]) -> 0.5 | AD68: =Tabla13[[#This Row],[Uso y acceso Dic/2024]] -> 1 | AE68: =Tabla58[[#This Row],[Integración Dic/2024]] -> 0 | AF68: =AVERAGE(Tabla4[[#This Row],[Creación y captura Dic/2024]:[Compartición e Interoperabilidad Dic/2024]]) -> 0.5 | AJ68: =Tabla13[[#This Row],[Uso y acceso Ene/2025]] -> 1 | AK68: =Tabla58[[#This Row],[Integración Ene/2025]] -> 0 | AL68: =AVERAGE(Tabla4[[#This Row],[Creación y captura Ene/2025]:[Compartición e Interoperabilidad Ene/2025]]) -> 0.5 | AP68: =Tabla13[[#This Row],[Uso y acceso Feb/2025]] -> 1 | AQ68: =Tabla58[[#This Row],[Integración Feb/2025]] -> 0 | AR68: =AVERAGE(Tabla4[[#This Row],[Creación y captura Feb/2025]:[Compartición e Interoperabilidad Feb/2025]]) -> 0.5 | AV68: =Tabla13[[#This Row],[Uso y acceso Mar/2025]] -> 1 | AW68: =Tabla58[[#This Row],[Integración Mar/2025]] -> 0 | AX68: =AVERAGE(Tabla4[[#This Row],[Creación y captura Mar/2025]:[Compartición e Interoperabilidad Mar/2025]]) -> 0.5 | BB68: =Tabla13[[#This Row],[Uso y acceso Abr/2025]] -> 1 | BC68: =Tabla58[[#This Row],[Integración Abr/2025]] -> 0 | BD68: =AVERAGE(Tabla4[[#This Row],[Creación y captura Abr/2025]:[Compartición e Interoperabilidad Abr/2025]]) -> 0.5 | BE68: 0 | BH68: =Tabla13[[#This Row],[Uso y acceso May/2025]] -> 1 | BI68: =Tabla58[[#This Row],[Integración May/2025]] -> 0 | BJ68: =AVERAGE(Tabla4[[#This Row],[Creación y captura May/2025]:[Compartición e Interoperabilidad May/2025]]) -> 0.33333333 | BK68: 1 | BL68: 1 | BM68: =AVERAGE('Calidad de Datos'!AQ72:AT72) -> 0.95 | BN68: =Tabla13[[#This Row],[Uso y acceso Dic/2025]] -> 1 | BO68: =Tabla58[[#This Row],[Integración Dic/2025]] -> 1 | BP68: =AVERAGE(Tabla4[[#This Row],[Creación y captura Dic/2025]:[Compartición e Interoperabilidad Dic/2025]]) -> 0.99
B69: Productos | F69: =Tabla13[[#This Row],[Uso y acceso Ago/2024]] -> 0.8 | G69: =Tabla58[[#This Row],[Integración Ago/2024]] -> 0 | H69: =AVERAGE(Tabla4[[#This Row],[Creación y captura Ago/2024]:[Compartición e Interoperabilidad Ago/2024]]) -> 0.4 | L69: =Tabla13[[#This Row],[Uso y acceso Sep/2024]] -> 0.8 | M69: =Tabla58[[#This Row],[Integración Sep/2024]] -> 0 | N69: =AVERAGE(Tabla4[[#This Row],[Creación y captura Sep/2024]:[Compartición e Interoperabilidad Sep/2024]]) -> 0.4 | R69: =Tabla13[[#This Row],[Uso y acceso Oct/2024]] -> 1 | S69: =Tabla58[[#This Row],[Integración Oct/2024]] -> 0 | T69: =AVERAGE(Tabla4[[#This Row],[Creación y captura Oct/2024]:[Compartición e Interoperabilidad Oct/2024]]) -> 0.5 | X69: =Tabla13[[#This Row],[Uso y acceso Nov/2024]] -> 1 | Y69: =Tabla58[[#This Row],[Integración Nov/2024]] -> 0 | Z69: =AVERAGE(Tabla4[[#This Row],[Creación y captura Nov/2024]:[Compartición e Interoperabilidad Nov/2024]]) -> 0.5 | AD69: =Tabla13[[#This Row],[Uso y acceso Dic/2024]] -> 1 | AE69: =Tabla58[[#This Row],[Integración Dic/2024]] -> 0 | AF69: =AVERAGE(Tabla4[[#This Row],[Creación y captura Dic/2024]:[Compartición e Interoperabilidad Dic/2024]]) -> 0.5 | AJ69: =Tabla13[[#This Row],[Uso y acceso Ene/2025]] -> 1 | AK69: =Tabla58[[#This Row],[Integración Ene/2025]] -> 0 | AL69: =AVERAGE(Tabla4[[#This Row],[Creación y captura Ene/2025]:[Compartición e Interoperabilidad Ene/2025]]) -> 0.5 | AP69: =Tabla13[[#This Row],[Uso y acceso Feb/2025]] -> 1 | AQ69: =Tabla58[[#This Row],[Integración Feb/2025]] -> 0 | AR69: =AVERAGE(Tabla4[[#This Row],[Creación y captura Feb/2025]:[Compartición e Interoperabilidad Feb/2025]]) -> 0.5 | AV69: =Tabla13[[#This Row],[Uso y acceso Mar/2025]] -> 1 | AW69: =Tabla58[[#This Row],[Integración Mar/2025]] -> 0 | AX69: =AVERAGE(Tabla4[[#This Row],[Creación y captura Mar/2025]:[Compartición e Interoperabilidad Mar/2025]]) -> 0.5 | BB69: =Tabla13[[#This Row],[Uso y acceso Abr/2025]] -> 1 | BC69: =Tabla58[[#This Row],[Integración Abr/2025]] -> 0 | BD69: =AVERAGE(Tabla4[[#This Row],[Creación y captura Abr/2025]:[Compartición e Interoperabilidad Abr/2025]]) -> 0.5 | BE69: 0 | BH69: =Tabla13[[#This Row],[Uso y acceso May/2025]] -> 1 | BI69: =Tabla58[[#This Row],[Integración May/2025]] -> 0 | BJ69: =AVERAGE(Tabla4[[#This Row],[Creación y captura May/2025]:[Compartición e Interoperabilidad May/2025]]) -> 0.33333333 | BK69: 1 | BL69: 1 | BM69: =AVERAGE('Calidad de Datos'!AQ73:AT73) -> 0.95 | BN69: =Tabla13[[#This Row],[Uso y acceso Dic/2025]] -> 1 | BO69: =Tabla58[[#This Row],[Integración Dic/2025]] -> 1 | BP69: =AVERAGE(Tabla4[[#This Row],[Creación y captura Dic/2025]:[Compartición e Interoperabilidad Dic/2025]]) -> 0.99
B70: Servicio | F70: =Tabla13[[#This Row],[Uso y acceso Ago/2024]] -> 0.8 | G70: =Tabla58[[#This Row],[Integración Ago/2024]] -> 0 | H70: =AVERAGE(Tabla4[[#This Row],[Creación y captura Ago/2024]:[Compartición e Interoperabilidad Ago/2024]]) -> 0.4 | L70: =Tabla13[[#This Row],[Uso y acceso Sep/2024]] -> 0.8 | M70: =Tabla58[[#This Row],[Integración Sep/2024]] -> 0 | N70: =AVERAGE(Tabla4[[#This Row],[Creación y captura Sep/2024]:[Compartición e Interoperabilidad Sep/2024]]) -> 0.4 | R70: =Tabla13[[#This Row],[Uso y acceso Oct/2024]] -> 1 | S70: =Tabla58[[#This Row],[Integración Oct/2024]] -> 0 | T70: =AVERAGE(Tabla4[[#This Row],[Creación y captura Oct/2024]:[Compartición e Interoperabilidad Oct/2024]]) -> 0.5 | X70: =Tabla13[[#This Row],[Uso y acceso Nov/2024]] -> 1 | Y70: =Tabla58[[#This Row],[Integración Nov/2024]] -> 0 | Z70: =AVERAGE(Tabla4[[#This Row],[Creación y captura Nov/2024]:[Compartición e Interoperabilidad Nov/2024]]) -> 0.5 | AD70: =Tabla13[[#This Row],[Uso y acceso Dic/2024]] -> 1 | AE70: =Tabla58[[#This Row],[Integración Dic/2024]] -> 0 | AF70: =AVERAGE(Tabla4[[#This Row],[Creación y captura Dic/2024]:[Compartición e Interoperabilidad Dic/2024]]) -> 0.5 | AJ70: =Tabla13[[#This Row],[Uso y acceso Ene/2025]] -> 1 | AK70: =Tabla58[[#This Row],[Integración Ene/2025]] -> 0 | AL70: =AVERAGE(Tabla4[[#This Row],[Creación y captura Ene/2025]:[Compartición e Interoperabilidad Ene/2025]]) -> 0.5 | AP70: =Tabla13[[#This Row],[Uso y acceso Feb/2025]] -> 1 | AQ70: =Tabla58[[#This Row],[Integración Feb/2025]] -> 0 | AR70: =AVERAGE(Tabla4[[#This Row],[Creación y captura Feb/2025]:[Compartición e Interoperabilidad Feb/2025]]) -> 0.5 | AV70: =Tabla13[[#This Row],[Uso y acceso Mar/2025]] -> 1 | AW70: =Tabla58[[#This Row],[Integración Mar/2025]] -> 0 | AX70: =AVERAGE(Tabla4[[#This Row],[Creación y captura Mar/2025]:[Compartición e Interoperabilidad Mar/2025]]) -> 0.5 | AY70: 0.8 | AZ70: 0.5 | BA70: =AVERAGE('Calidad de Datos'!AI74:AL74) -> 1 | BB70: =Tabla13[[#This Row],[Uso y acceso Abr/2025]] -> 1 | BC70: =Tabla58[[#This Row],[Integración Abr/2025]] -> 0.3 | BD70: =AVERAGE(Tabla4[[#This Row],[Creación y captura Abr/2025]:[Compartición e Interoperabilidad Abr/2025]]) -> 0.72 | BE70: 0.8 | BF70: 0.5 | BG70: =AVERAGE('Calidad de Datos'!AM74:AP74) -> 1 | BH70: =Tabla13[[#This Row],[Uso y acceso May/2025]] -> 1 | BI70: =Tabla58[[#This Row],[Integración May/2025]] -> 0.3 | BJ70: =AVERAGE(Tabla4[[#This Row],[Creación y captura May/2025]:[Compartición e Interoperabilidad May/2025]]) -> 0.72 | BK70: 0.8 | BL70: 0.5 | BM70: =AVERAGE('Calidad de Datos'!AQ74:AT74) -> 1 | BN70: =Tabla13[[#This Row],[Uso y acceso Dic/2025]] -> 1 | BO70: =Tabla58[[#This Row],[Integración Dic/2025]] -> 0.8 | BP70: =AVERAGE(Tabla4[[#This Row],[Creación y captura Dic/2025]:[Compartición e Interoperabilidad Dic/2025]]) -> 0.82
B71: Entregable | F71: =Tabla13[[#This Row],[Uso y acceso Ago/2024]] -> 0.8 | G71: =Tabla58[[#This Row],[Integración Ago/2024]] -> 0 | H71: =AVERAGE(Tabla4[[#This Row],[Creación y captura Ago/2024]:[Compartición e Interoperabilidad Ago/2024]]) -> 0.4 | L71: =Tabla13[[#This Row],[Uso y acceso Sep/2024]] -> 0.8 | M71: =Tabla58[[#This Row],[Integración Sep/2024]] -> 0 | N71: =AVERAGE(Tabla4[[#This Row],[Creación y captura Sep/2024]:[Compartición e Interoperabilidad Sep/2024]]) -> 0.4 | R71: =Tabla13[[#This Row],[Uso y acceso Oct/2024]] -> 1 | S71: =Tabla58[[#This Row],[Integración Oct/2024]] -> 0 | T71: =AVERAGE(Tabla4[[#This Row],[Creación y captura Oct/2024]:[Compartición e Interoperabilidad Oct/2024]]) -> 0.5 | X71: =Tabla13[[#This Row],[Uso y acceso Nov/2024]] -> 1 | Y71: =Tabla58[[#This Row],[Integración Nov/2024]] -> 0 | Z71: =AVERAGE(Tabla4[[#This Row],[Creación y captura Nov/2024]:[Compartición e Interoperabilidad Nov/2024]]) -> 0.5 | AD71: =Tabla13[[#This Row],[Uso y acceso Dic/2024]] -> 1 | AE71: =Tabla58[[#This Row],[Integración Dic/2024]] -> 0 | AF71: =AVERAGE(Tabla4[[#This Row],[Creación y captura Dic/2024]:[Compartición e Interoperabilidad Dic/2024]]) -> 0.5 | AJ71: =Tabla13[[#This Row],[Uso y acceso Ene/2025]] -> 1 | AK71: =Tabla58[[#This Row],[Integración Ene/2025]] -> 0 | AL71: =AVERAGE(Tabla4[[#This Row],[Creación y captura Ene/2025]:[Compartición e Interoperabilidad Ene/2025]]) -> 0.5 | AP71: =Tabla13[[#This Row],[Uso y acceso Feb/2025]] -> 1 | AQ71: =Tabla58[[#This Row],[Integración Feb/2025]] -> 0 | AR71: =AVERAGE(Tabla4[[#This Row],[Creación y captura Feb/2025]:[Compartición e Interoperabilidad Feb/2025]]) -> 0.5 | AV71: =Tabla13[[#This Row],[Uso y acceso Mar/2025]] -> 1 | AW71: =Tabla58[[#This Row],[Integración Mar/2025]] -> 0 | AX71: =AVERAGE(Tabla4[[#This Row],[Creación y captura Mar/2025]:[Compartición e Interoperabilidad Mar/2025]]) -> 0.5 | BB71: =Tabla13[[#This Row],[Uso y acceso Abr/2025]] -> 1 | BC71: =Tabla58[[#This Row],[Integración Abr/2025]] -> 0 | BD71: =AVERAGE(Tabla4[[#This Row],[Creación y captura Abr/2025]:[Compartición e Interoperabilidad Abr/2025]]) -> 0.5 | BH71: =Tabla13[[#This Row],[Uso y acceso May/2025]] -> 1 | BI71: =Tabla58[[#This Row],[Integración May/2025]] -> 0 | BJ71: =AVERAGE(Tabla4[[#This Row],[Creación y captura May/2025]:[Compartición e Interoperabilidad May/2025]]) -> 0.5 | BM71: =AVERAGE('Calidad de Datos'!AQ75:AT75) -> 0.85 | BN71: =Tabla13[[#This Row],[Uso y acceso Dic/2025]] -> 1 | BO71: =Tabla58[[#This Row],[Integración Dic/2025]] -> 0.4 | BP71: =AVERAGE(Tabla4[[#This Row],[Creación y captura Dic/2025]:[Compartición e Interoperabilidad Dic/2025]]) -> 0.75
B72: Artefacto | F72: =Tabla13[[#This Row],[Uso y acceso Ago/2024]] -> 0.8 | G72: =Tabla58[[#This Row],[Integración Ago/2024]] -> 0 | H72: =AVERAGE(Tabla4[[#This Row],[Creación y captura Ago/2024]:[Compartición e Interoperabilidad Ago/2024]]) -> 0.4 | L72: =Tabla13[[#This Row],[Uso y acceso Sep/2024]] -> 0.8 | M72: =Tabla58[[#This Row],[Integración Sep/2024]] -> 0 | N72: =AVERAGE(Tabla4[[#This Row],[Creación y captura Sep/2024]:[Compartición e Interoperabilidad Sep/2024]]) -> 0.4 | R72: =Tabla13[[#This Row],[Uso y acceso Oct/2024]] -> 1 | S72: =Tabla58[[#This Row],[Integración Oct/2024]] -> 0 | T72: =AVERAGE(Tabla4[[#This Row],[Creación y captura Oct/2024]:[Compartición e Interoperabilidad Oct/2024]]) -> 0.5 | X72: =Tabla13[[#This Row],[Uso y acceso Nov/2024]] -> 1 | Y72: =Tabla58[[#This Row],[Integración Nov/2024]] -> 0 | Z72: =AVERAGE(Tabla4[[#This Row],[Creación y captura Nov/2024]:[Compartición e Interoperabilidad Nov/2024]]) -> 0.5 | AD72: =Tabla13[[#This Row],[Uso y acceso Dic/2024]] -> 1 | AE72: =Tabla58[[#This Row],[Integración Dic/2024]] -> 0 | AF72: =AVERAGE(Tabla4[[#This Row],[Creación y captura Dic/2024]:[Compartición e Interoperabilidad Dic/2024]]) -> 0.5 | AJ72: =Tabla13[[#This Row],[Uso y acceso Ene/2025]] -> 1 | AK72: =Tabla58[[#This Row],[Integración Ene/2025]] -> 0 | AL72: =AVERAGE(Tabla4[[#This Row],[Creación y captura Ene/2025]:[Compartición e Interoperabilidad Ene/2025]]) -> 0.5 | AP72: =Tabla13[[#This Row],[Uso y acceso Feb/2025]] -> 1 | AQ72: =Tabla58[[#This Row],[Integración Feb/2025]] -> 0 | AR72: =AVERAGE(Tabla4[[#This Row],[Creación y captura Feb/2025]:[Compartición e Interoperabilidad Feb/2025]]) -> 0.5 | AV72: =Tabla13[[#This Row],[Uso y acceso Mar/2025]] -> 1 | AW72: =Tabla58[[#This Row],[Integración Mar/2025]] -> 0 | AX72: =AVERAGE(Tabla4[[#This Row],[Creación y captura Mar/2025]:[Compartición e Interoperabilidad Mar/2025]]) -> 0.5 | BB72: =Tabla13[[#This Row],[Uso y acceso Abr/2025]] -> 1 | BC72: =Tabla58[[#This Row],[Integración Abr/2025]] -> 0 | BD72: =AVERAGE(Tabla4[[#This Row],[Creación y captura Abr/2025]:[Compartición e Interoperabilidad Abr/2025]]) -> 0.5 | BH72: =Tabla13[[#This Row],[Uso y acceso May/2025]] -> 1 | BI72: =Tabla58[[#This Row],[Integración May/2025]] -> 0 | BJ72: =AVERAGE(Tabla4[[#This Row],[Creación y captura May/2025]:[Compartición e Interoperabilidad May/2025]]) -> 0.5 | BM72: =AVERAGE('Calidad de Datos'!AQ76:AT76) -> 0.85 | BN72: =Tabla13[[#This Row],[Uso y acceso Dic/2025]] -> 1 | BO72: =Tabla58[[#This Row],[Integración Dic/2025]] -> 0.4 | BP72: =AVERAGE(Tabla4[[#This Row],[Creación y captura Dic/2025]:[Compartición e Interoperabilidad Dic/2025]]) -> 0.75
B73: Riesgos y Oportunidades | F73: =Tabla13[[#This Row],[Uso y acceso Ago/2024]] -> 0.8 | G73: =Tabla58[[#This Row],[Integración Ago/2024]] -> 0 | H73: =AVERAGE(Tabla4[[#This Row],[Creación y captura Ago/2024]:[Compartición e Interoperabilidad Ago/2024]]) -> 0.4 | L73: =Tabla13[[#This Row],[Uso y acceso Sep/2024]] -> 0.8 | M73: =Tabla58[[#This Row],[Integración Sep/2024]] -> 0 | N73: =AVERAGE(Tabla4[[#This Row],[Creación y captura Sep/2024]:[Compartición e Interoperabilidad Sep/2024]]) -> 0.4 | R73: =Tabla13[[#This Row],[Uso y acceso Oct/2024]] -> 1 | S73: =Tabla58[[#This Row],[Integración Oct/2024]] -> 0 | T73: =AVERAGE(Tabla4[[#This Row],[Creación y captura Oct/2024]:[Compartición e Interoperabilidad Oct/2024]]) -> 0.5 | X73: =Tabla13[[#This Row],[Uso y acceso Nov/2024]] -> 1 | Y73: =Tabla58[[#This Row],[Integración Nov/2024]] -> 0 | Z73: =AVERAGE(Tabla4[[#This Row],[Creación y captura Nov/2024]:[Compartición e Interoperabilidad Nov/2024]]) -> 0.5 | AD73: =Tabla13[[#This Row],[Uso y acceso Dic/2024]] -> 1 | AE73: =Tabla58[[#This Row],[Integración Dic/2024]] -> 0 | AF73: =AVERAGE(Tabla4[[#This Row],[Creación y captura Dic/2024]:[Compartición e Interoperabilidad Dic/2024]]) -> 0.5 | AJ73: =Tabla13[[#This Row],[Uso y acceso Ene/2025]] -> 1 | AK73: =Tabla58[[#This Row],[Integración Ene/2025]] -> 0 | AL73: =AVERAGE(Tabla4[[#This Row],[Creación y captura Ene/2025]:[Compartición e Interoperabilidad Ene/2025]]) -> 0.5 | AP73: =Tabla13[[#This Row],[Uso y acceso Feb/2025]] -> 1 | AQ73: =Tabla58[[#This Row],[Integración Feb/2025]] -> 0 | AR73: =AVERAGE(Tabla4[[#This Row],[Creación y captura Feb/2025]:[Compartición e Interoperabilidad Feb/2025]]) -> 0.5 | AV73: =Tabla13[[#This Row],[Uso y acceso Mar/2025]] -> 1 | AW73: =Tabla58[[#This Row],[Integración Mar/2025]] -> 0 | AX73: =AVERAGE(Tabla4[[#This Row],[Creación y captura Mar/2025]:[Compartición e Interoperabilidad Mar/2025]]) -> 0.5 | BB73: =Tabla13[[#This Row],[Uso y acceso Abr/2025]] -> 1 | BC73: =Tabla58[[#This Row],[Integración Abr/2025]] -> 0 | BD73: =AVERAGE(Tabla4[[#This Row],[Creación y captura Abr/2025]:[Compartición e Interoperabilidad Abr/2025]]) -> 0.5 | BH73: =Tabla13[[#This Row],[Uso y acceso May/2025]] -> 1 | BI73: =Tabla58[[#This Row],[Integración May/2025]] -> 0 | BJ73: =AVERAGE(Tabla4[[#This Row],[Creación y captura May/2025]:[Compartición e Interoperabilidad May/2025]]) -> 0.5 | BM73: =AVERAGE('Calidad de Datos'!AQ77:AT77) -> 0.85 | BN73: =Tabla13[[#This Row],[Uso y acceso Dic/2025]] -> 1 | BO73: =Tabla58[[#This Row],[Integración Dic/2025]] -> 0.4 | BP73: =AVERAGE(Tabla4[[#This Row],[Creación y captura Dic/2025]:[Compartición e Interoperabilidad Dic/2025]]) -> 0.75
B74: Política | F74: =Tabla13[[#This Row],[Uso y acceso Ago/2024]] -> 0.8 | G74: =Tabla58[[#This Row],[Integración Ago/2024]] -> 0 | H74: =AVERAGE(Tabla4[[#This Row],[Creación y captura Ago/2024]:[Compartición e Interoperabilidad Ago/2024]]) -> 0.4 | L74: =Tabla13[[#This Row],[Uso y acceso Sep/2024]] -> 0.8 | M74: =Tabla58[[#This Row],[Integración Sep/2024]] -> 0 | N74: =AVERAGE(Tabla4[[#This Row],[Creación y captura Sep/2024]:[Compartición e Interoperabilidad Sep/2024]]) -> 0.4 | R74: =Tabla13[[#This Row],[Uso y acceso Oct/2024]] -> 1 | S74: =Tabla58[[#This Row],[Integración Oct/2024]] -> 0 | T74: =AVERAGE(Tabla4[[#This Row],[Creación y captura Oct/2024]:[Compartición e Interoperabilidad Oct/2024]]) -> 0.5 | X74: =Tabla13[[#This Row],[Uso y acceso Nov/2024]] -> 1 | Y74: =Tabla58[[#This Row],[Integración Nov/2024]] -> 0 | Z74: =AVERAGE(Tabla4[[#This Row],[Creación y captura Nov/2024]:[Compartición e Interoperabilidad Nov/2024]]) -> 0.5 | AD74: =Tabla13[[#This Row],[Uso y acceso Dic/2024]] -> 1 | AE74: =Tabla58[[#This Row],[Integración Dic/2024]] -> 0 | AF74: =AVERAGE(Tabla4[[#This Row],[Creación y captura Dic/2024]:[Compartición e Interoperabilidad Dic/2024]]) -> 0.5 | AJ74: =Tabla13[[#This Row],[Uso y acceso Ene/2025]] -> 1 | AK74: =Tabla58[[#This Row],[Integración Ene/2025]] -> 0 | AL74: =AVERAGE(Tabla4[[#This Row],[Creación y captura Ene/2025]:[Compartición e Interoperabilidad Ene/2025]]) -> 0.5 | AP74: =Tabla13[[#This Row],[Uso y acceso Feb/2025]] -> 1 | AQ74: =Tabla58[[#This Row],[Integración Feb/2025]] -> 0 | AR74: =AVERAGE(Tabla4[[#This Row],[Creación y captura Feb/2025]:[Compartición e Interoperabilidad Feb/2025]]) -> 0.5 | AV74: =Tabla13[[#This Row],[Uso y acceso Mar/2025]] -> 1 | AW74: =Tabla58[[#This Row],[Integración Mar/2025]] -> 0 | AX74: =AVERAGE(Tabla4[[#This Row],[Creación y captura Mar/2025]:[Compartición e Interoperabilidad Mar/2025]]) -> 0.5 | BB74: =Tabla13[[#This Row],[Uso y acceso Abr/2025]] -> 1 | BC74: =Tabla58[[#This Row],[Integración Abr/2025]] -> 0 | BD74: =AVERAGE(Tabla4[[#This Row],[Creación y captura Abr/2025]:[Compartición e Interoperabilidad Abr/2025]]) -> 0.5 | BH74: =Tabla13[[#This Row],[Uso y acceso May/2025]] -> 1 | BI74: =Tabla58[[#This Row],[Integración May/2025]] -> 0 | BJ74: =AVERAGE(Tabla4[[#This Row],[Creación y captura May/2025]:[Compartición e Interoperabilidad May/2025]]) -> 0.5 | BK74: 1 | BL74: 1 | BM74: =AVERAGE('Calidad de Datos'!AQ78:AT78) -> 0.95 | BN74: =Tabla13[[#This Row],[Uso y acceso Dic/2025]] -> 1 | BO74: =Tabla58[[#This Row],[Integración Dic/2025]] -> 1 | BP74: =AVERAGE(Tabla4[[#This Row],[Creación y captura Dic/2025]:[Compartición e Interoperabilidad Dic/2025]]) -> 0.99
B75: Guía | F75: =Tabla13[[#This Row],[Uso y acceso Ago/2024]] -> 0.8 | G75: =Tabla58[[#This Row],[Integración Ago/2024]] -> 0 | H75: =AVERAGE(Tabla4[[#This Row],[Creación y captura Ago/2024]:[Compartición e Interoperabilidad Ago/2024]]) -> 0.4 | L75: =Tabla13[[#This Row],[Uso y acceso Sep/2024]] -> 0.8 | M75: =Tabla58[[#This Row],[Integración Sep/2024]] -> 0 | N75: =AVERAGE(Tabla4[[#This Row],[Creación y captura Sep/2024]:[Compartición e Interoperabilidad Sep/2024]]) -> 0.4 | R75: =Tabla13[[#This Row],[Uso y acceso Oct/2024]] -> 1 | S75: =Tabla58[[#This Row],[Integración Oct/2024]] -> 0 | T75: =AVERAGE(Tabla4[[#This Row],[Creación y captura Oct/2024]:[Compartición e Interoperabilidad Oct/2024]]) -> 0.5 | X75: =Tabla13[[#This Row],[Uso y acceso Nov/2024]] -> 1 | Y75: =Tabla58[[#This Row],[Integración Nov/2024]] -> 0 | Z75: =AVERAGE(Tabla4[[#This Row],[Creación y captura Nov/2024]:[Compartición e Interoperabilidad Nov/2024]]) -> 0.5 | AD75: =Tabla13[[#This Row],[Uso y acceso Dic/2024]] -> 1 | AE75: =Tabla58[[#This Row],[Integración Dic/2024]] -> 0 | AF75: =AVERAGE(Tabla4[[#This Row],[Creación y captura Dic/2024]:[Compartición e Interoperabilidad Dic/2024]]) -> 0.5 | AJ75: =Tabla13[[#This Row],[Uso y acceso Ene/2025]] -> 1 | AK75: =Tabla58[[#This Row],[Integración Ene/2025]] -> 0 | AL75: =AVERAGE(Tabla4[[#This Row],[Creación y captura Ene/2025]:[Compartición e Interoperabilidad Ene/2025]]) -> 0.5 | AP75: =Tabla13[[#This Row],[Uso y acceso Feb/2025]] -> 1 | AQ75: =Tabla58[[#This Row],[Integración Feb/2025]] -> 0 | AR75: =AVERAGE(Tabla4[[#This Row],[Creación y captura Feb/2025]:[Compartición e Interoperabilidad Feb/2025]]) -> 0.5 | AV75: =Tabla13[[#This Row],[Uso y acceso Mar/2025]] -> 1 | AW75: =Tabla58[[#This Row],[Integración Mar/2025]] -> 0 | AX75: =AVERAGE(Tabla4[[#This Row],[Creación y captura Mar/2025]:[Compartición e Interoperabilidad Mar/2025]]) -> 0.5 | BB75: =Tabla13[[#This Row],[Uso y acceso Abr/2025]] -> 1 | BC75: =Tabla58[[#This Row],[Integración Abr/2025]] -> 0 | BD75: =AVERAGE(Tabla4[[#This Row],[Creación y captura Abr/2025]:[Compartición e Interoperabilidad Abr/2025]]) -> 0.5 | BH75: =Tabla13[[#This Row],[Uso y acceso May/2025]] -> 1 | BI75: =Tabla58[[#This Row],[Integración May/2025]] -> 0 | BJ75: =AVERAGE(Tabla4[[#This Row],[Creación y captura May/2025]:[Compartición e Interoperabilidad May/2025]]) -> 0.5 | BK75: 1 | BL75: 1 | BM75: =AVERAGE('Calidad de Datos'!AQ79:AT79) -> 0.95 | BN75: =Tabla13[[#This Row],[Uso y acceso Dic/2025]] -> 1 | BO75: =Tabla58[[#This Row],[Integración Dic/2025]] -> 1 | BP75: =AVERAGE(Tabla4[[#This Row],[Creación y captura Dic/2025]:[Compartición e Interoperabilidad Dic/2025]]) -> 0.99
B76: Requisitos Norma ISO 9001 | F76: =Tabla13[[#This Row],[Uso y acceso Ago/2024]] -> 1 | G76: =Tabla58[[#This Row],[Integración Ago/2024]] -> 0 | H76: =AVERAGE(Tabla4[[#This Row],[Creación y captura Ago/2024]:[Compartición e Interoperabilidad Ago/2024]]) -> 0.5 | L76: =Tabla13[[#This Row],[Uso y acceso Sep/2024]] -> 1 | M76: =Tabla58[[#This Row],[Integración Sep/2024]] -> 0 | N76: =AVERAGE(Tabla4[[#This Row],[Creación y captura Sep/2024]:[Compartición e Interoperabilidad Sep/2024]]) -> 0.5 | R76: =Tabla13[[#This Row],[Uso y acceso Oct/2024]] -> 1 | S76: =Tabla58[[#This Row],[Integración Oct/2024]] -> 0 | T76: =AVERAGE(Tabla4[[#This Row],[Creación y captura Oct/2024]:[Compartición e Interoperabilidad Oct/2024]]) -> 0.5 | X76: =Tabla13[[#This Row],[Uso y acceso Nov/2024]] -> 1 | Y76: =Tabla58[[#This Row],[Integración Nov/2024]] -> 0 | Z76: =AVERAGE(Tabla4[[#This Row],[Creación y captura Nov/2024]:[Compartición e Interoperabilidad Nov/2024]]) -> 0.5 | AD76: =Tabla13[[#This Row],[Uso y acceso Dic/2024]] -> 1 | AE76: =Tabla58[[#This Row],[Integración Dic/2024]] -> 0 | AF76: =AVERAGE(Tabla4[[#This Row],[Creación y captura Dic/2024]:[Compartición e Interoperabilidad Dic/2024]]) -> 0.5 | AJ76: =Tabla13[[#This Row],[Uso y acceso Ene/2025]] -> 1 | AK76: =Tabla58[[#This Row],[Integración Ene/2025]] -> 0 | AL76: =AVERAGE(Tabla4[[#This Row],[Creación y captura Ene/2025]:[Compartición e Interoperabilidad Ene/2025]]) -> 0.5 | AP76: =Tabla13[[#This Row],[Uso y acceso Feb/2025]] -> 1 | AQ76: =Tabla58[[#This Row],[Integración Feb/2025]] -> 0 | AR76: =AVERAGE(Tabla4[[#This Row],[Creación y captura Feb/2025]:[Compartición e Interoperabilidad Feb/2025]]) -> 0.5 | AV76: =Tabla13[[#This Row],[Uso y acceso Mar/2025]] -> 1 | AW76: =Tabla58[[#This Row],[Integración Mar/2025]] -> 0 | AX76: =AVERAGE(Tabla4[[#This Row],[Creación y captura Mar/2025]:[Compartición e Interoperabilidad Mar/2025]]) -> 0.5 | BB76: =Tabla13[[#This Row],[Uso y acceso Abr/2025]] -> 1 | BC76: =Tabla58[[#This Row],[Integración Abr/2025]] -> 0 | BD76: =AVERAGE(Tabla4[[#This Row],[Creación y captura Abr/2025]:[Compartición e Interoperabilidad Abr/2025]]) -> 0.5 | BH76: =Tabla13[[#This Row],[Uso y acceso May/2025]] -> 1 | BI76: =Tabla58[[#This Row],[Integración May/2025]] -> 0 | BJ76: =AVERAGE(Tabla4[[#This Row],[Creación y captura May/2025]:[Compartición e Interoperabilidad May/2025]]) -> 0.5 | BM76: =AVERAGE('Calidad de Datos'!AQ80:AT80) -> 0.85 | BN76: =Tabla13[[#This Row],[Uso y acceso Dic/2025]] -> 1 | BO76: =Tabla58[[#This Row],[Integración Dic/2025]] -> 0.4 | BP76: =AVERAGE(Tabla4[[#This Row],[Creación y captura Dic/2025]:[Compartición e Interoperabilidad Dic/2025]]) -> 0.75
